package com.google.android.gms.wearable.internal;

import android.net.Uri;
import android.os.Binder;
import android.os.IBinder;
import android.os.IInterface;
import android.os.Parcel;
import android.os.ParcelFileDescriptor;
import android.os.Parcelable.Creator;
import android.os.RemoteException;
import com.google.android.gms.wearable.Asset;
import com.google.android.gms.wearable.ConnectionConfiguration;
import com.google.android.gms.wearable.PutDataRequest;

public abstract interface zzbb
  extends IInterface
{
  public abstract void zza(zzaz paramzzaz)
    throws RemoteException;
  
  public abstract void zza(zzaz paramzzaz, byte paramByte)
    throws RemoteException;
  
  public abstract void zza(zzaz paramzzaz, int paramInt)
    throws RemoteException;
  
  public abstract void zza(zzaz paramzzaz, Uri paramUri)
    throws RemoteException;
  
  public abstract void zza(zzaz paramzzaz, Uri paramUri, int paramInt)
    throws RemoteException;
  
  public abstract void zza(zzaz paramzzaz, Asset paramAsset)
    throws RemoteException;
  
  public abstract void zza(zzaz paramzzaz, ConnectionConfiguration paramConnectionConfiguration)
    throws RemoteException;
  
  public abstract void zza(zzaz paramzzaz, PutDataRequest paramPutDataRequest)
    throws RemoteException;
  
  public abstract void zza(zzaz paramzzaz, AddListenerRequest paramAddListenerRequest)
    throws RemoteException;
  
  public abstract void zza(zzaz paramzzaz, AncsNotificationParcelable paramAncsNotificationParcelable)
    throws RemoteException;
  
  public abstract void zza(zzaz paramzzaz, LargeAssetEnqueueRequest paramLargeAssetEnqueueRequest)
    throws RemoteException;
  
  public abstract void zza(zzaz paramzzaz, LargeAssetQuery paramLargeAssetQuery)
    throws RemoteException;
  
  public abstract void zza(zzaz paramzzaz, LargeAssetRemoveRequest paramLargeAssetRemoveRequest)
    throws RemoteException;
  
  public abstract void zza(zzaz paramzzaz, RemoveListenerRequest paramRemoveListenerRequest)
    throws RemoteException;
  
  public abstract void zza(zzaz paramzzaz, zzaw paramzzaw, String paramString)
    throws RemoteException;
  
  public abstract void zza(zzaz paramzzaz, String paramString)
    throws RemoteException;
  
  public abstract void zza(zzaz paramzzaz, String paramString, int paramInt)
    throws RemoteException;
  
  public abstract void zza(zzaz paramzzaz, String paramString, ParcelFileDescriptor paramParcelFileDescriptor)
    throws RemoteException;
  
  public abstract void zza(zzaz paramzzaz, String paramString, ParcelFileDescriptor paramParcelFileDescriptor, long paramLong1, long paramLong2)
    throws RemoteException;
  
  public abstract void zza(zzaz paramzzaz, String paramString1, String paramString2)
    throws RemoteException;
  
  public abstract void zza(zzaz paramzzaz, String paramString1, String paramString2, byte[] paramArrayOfByte)
    throws RemoteException;
  
  public abstract void zza(zzaz paramzzaz, boolean paramBoolean)
    throws RemoteException;
  
  public abstract void zzb(zzaz paramzzaz)
    throws RemoteException;
  
  public abstract void zzb(zzaz paramzzaz, int paramInt)
    throws RemoteException;
  
  public abstract void zzb(zzaz paramzzaz, Uri paramUri)
    throws RemoteException;
  
  public abstract void zzb(zzaz paramzzaz, Uri paramUri, int paramInt)
    throws RemoteException;
  
  public abstract void zzb(zzaz paramzzaz, ConnectionConfiguration paramConnectionConfiguration)
    throws RemoteException;
  
  public abstract void zzb(zzaz paramzzaz, zzaw paramzzaw, String paramString)
    throws RemoteException;
  
  public abstract void zzb(zzaz paramzzaz, String paramString)
    throws RemoteException;
  
  public abstract void zzb(zzaz paramzzaz, String paramString, int paramInt)
    throws RemoteException;
  
  public abstract void zzb(zzaz paramzzaz, boolean paramBoolean)
    throws RemoteException;
  
  public abstract void zzc(zzaz paramzzaz)
    throws RemoteException;
  
  public abstract void zzc(zzaz paramzzaz, int paramInt)
    throws RemoteException;
  
  public abstract void zzc(zzaz paramzzaz, Uri paramUri)
    throws RemoteException;
  
  public abstract void zzc(zzaz paramzzaz, String paramString)
    throws RemoteException;
  
  public abstract void zzd(zzaz paramzzaz)
    throws RemoteException;
  
  public abstract void zzd(zzaz paramzzaz, String paramString)
    throws RemoteException;
  
  public abstract void zze(zzaz paramzzaz)
    throws RemoteException;
  
  public abstract void zze(zzaz paramzzaz, String paramString)
    throws RemoteException;
  
  public abstract void zzf(zzaz paramzzaz)
    throws RemoteException;
  
  public abstract void zzf(zzaz paramzzaz, String paramString)
    throws RemoteException;
  
  public abstract void zzg(zzaz paramzzaz)
    throws RemoteException;
  
  public abstract void zzh(zzaz paramzzaz)
    throws RemoteException;
  
  public abstract void zzi(zzaz paramzzaz)
    throws RemoteException;
  
  public abstract void zzj(zzaz paramzzaz)
    throws RemoteException;
  
  public abstract void zzk(zzaz paramzzaz)
    throws RemoteException;
  
  public abstract void zzl(zzaz paramzzaz)
    throws RemoteException;
  
  public abstract void zzm(zzaz paramzzaz)
    throws RemoteException;
  
  public abstract void zzn(zzaz paramzzaz)
    throws RemoteException;
  
  public abstract void zzo(zzaz paramzzaz)
    throws RemoteException;
  
  public abstract void zzp(zzaz paramzzaz)
    throws RemoteException;
  
  public abstract void zzq(zzaz paramzzaz)
    throws RemoteException;
  
  public static abstract class zza
    extends Binder
    implements zzbb
  {
    public static zzbb zzic(IBinder paramIBinder)
    {
      if (paramIBinder == null) {
        return null;
      }
      IInterface localIInterface = paramIBinder.queryLocalInterface("com.google.android.gms.wearable.internal.IWearableService");
      if ((localIInterface != null) && ((localIInterface instanceof zzbb))) {
        return (zzbb)localIInterface;
      }
      return new zza(paramIBinder);
    }
    
    public boolean onTransact(int paramInt1, Parcel paramParcel1, Parcel paramParcel2, int paramInt2)
      throws RemoteException
    {
      switch (paramInt1)
      {
      default: 
        return super.onTransact(paramInt1, paramParcel1, paramParcel2, paramInt2);
      case 1598968902: 
        paramParcel2.writeString("com.google.android.gms.wearable.internal.IWearableService");
        return true;
      case 20: 
        paramParcel1.enforceInterface("com.google.android.gms.wearable.internal.IWearableService");
        zzaz localzzaz19 = zzaz.zza.zzia(paramParcel1.readStrongBinder());
        int i12 = paramParcel1.readInt();
        ConnectionConfiguration localConnectionConfiguration2 = null;
        if (i12 != 0) {
          localConnectionConfiguration2 = (ConnectionConfiguration)ConnectionConfiguration.CREATOR.createFromParcel(paramParcel1);
        }
        zza(localzzaz19, localConnectionConfiguration2);
        paramParcel2.writeNoException();
        return true;
      case 21: 
        paramParcel1.enforceInterface("com.google.android.gms.wearable.internal.IWearableService");
        zza(zzaz.zza.zzia(paramParcel1.readStrongBinder()), paramParcel1.readString());
        paramParcel2.writeNoException();
        return true;
      case 22: 
        paramParcel1.enforceInterface("com.google.android.gms.wearable.internal.IWearableService");
        zza(zzaz.zza.zzia(paramParcel1.readStrongBinder()));
        paramParcel2.writeNoException();
        return true;
      case 23: 
        paramParcel1.enforceInterface("com.google.android.gms.wearable.internal.IWearableService");
        zzb(zzaz.zza.zzia(paramParcel1.readStrongBinder()), paramParcel1.readString());
        paramParcel2.writeNoException();
        return true;
      case 24: 
        paramParcel1.enforceInterface("com.google.android.gms.wearable.internal.IWearableService");
        zzc(zzaz.zza.zzia(paramParcel1.readStrongBinder()), paramParcel1.readString());
        paramParcel2.writeNoException();
        return true;
      case 6: 
        paramParcel1.enforceInterface("com.google.android.gms.wearable.internal.IWearableService");
        zzaz localzzaz18 = zzaz.zza.zzia(paramParcel1.readStrongBinder());
        int i11 = paramParcel1.readInt();
        PutDataRequest localPutDataRequest = null;
        if (i11 != 0) {
          localPutDataRequest = (PutDataRequest)PutDataRequest.CREATOR.createFromParcel(paramParcel1);
        }
        zza(localzzaz18, localPutDataRequest);
        paramParcel2.writeNoException();
        return true;
      case 7: 
        paramParcel1.enforceInterface("com.google.android.gms.wearable.internal.IWearableService");
        zzaz localzzaz17 = zzaz.zza.zzia(paramParcel1.readStrongBinder());
        int i10 = paramParcel1.readInt();
        Uri localUri5 = null;
        if (i10 != 0) {
          localUri5 = (Uri)Uri.CREATOR.createFromParcel(paramParcel1);
        }
        zza(localzzaz17, localUri5);
        paramParcel2.writeNoException();
        return true;
      case 8: 
        paramParcel1.enforceInterface("com.google.android.gms.wearable.internal.IWearableService");
        zzb(zzaz.zza.zzia(paramParcel1.readStrongBinder()));
        paramParcel2.writeNoException();
        return true;
      case 9: 
        paramParcel1.enforceInterface("com.google.android.gms.wearable.internal.IWearableService");
        zzaz localzzaz16 = zzaz.zza.zzia(paramParcel1.readStrongBinder());
        int i9 = paramParcel1.readInt();
        Uri localUri4 = null;
        if (i9 != 0) {
          localUri4 = (Uri)Uri.CREATOR.createFromParcel(paramParcel1);
        }
        zzb(localzzaz16, localUri4);
        paramParcel2.writeNoException();
        return true;
      case 40: 
        paramParcel1.enforceInterface("com.google.android.gms.wearable.internal.IWearableService");
        zzaz localzzaz15 = zzaz.zza.zzia(paramParcel1.readStrongBinder());
        int i8 = paramParcel1.readInt();
        Uri localUri3 = null;
        if (i8 != 0) {
          localUri3 = (Uri)Uri.CREATOR.createFromParcel(paramParcel1);
        }
        zza(localzzaz15, localUri3, paramParcel1.readInt());
        paramParcel2.writeNoException();
        return true;
      case 11: 
        paramParcel1.enforceInterface("com.google.android.gms.wearable.internal.IWearableService");
        zzaz localzzaz14 = zzaz.zza.zzia(paramParcel1.readStrongBinder());
        int i7 = paramParcel1.readInt();
        Uri localUri2 = null;
        if (i7 != 0) {
          localUri2 = (Uri)Uri.CREATOR.createFromParcel(paramParcel1);
        }
        zzc(localzzaz14, localUri2);
        paramParcel2.writeNoException();
        return true;
      case 41: 
        paramParcel1.enforceInterface("com.google.android.gms.wearable.internal.IWearableService");
        zzaz localzzaz13 = zzaz.zza.zzia(paramParcel1.readStrongBinder());
        int i6 = paramParcel1.readInt();
        Uri localUri1 = null;
        if (i6 != 0) {
          localUri1 = (Uri)Uri.CREATOR.createFromParcel(paramParcel1);
        }
        zzb(localzzaz13, localUri1, paramParcel1.readInt());
        paramParcel2.writeNoException();
        return true;
      case 12: 
        paramParcel1.enforceInterface("com.google.android.gms.wearable.internal.IWearableService");
        zza(zzaz.zza.zzia(paramParcel1.readStrongBinder()), paramParcel1.readString(), paramParcel1.readString(), paramParcel1.createByteArray());
        paramParcel2.writeNoException();
        return true;
      case 13: 
        paramParcel1.enforceInterface("com.google.android.gms.wearable.internal.IWearableService");
        zzaz localzzaz12 = zzaz.zza.zzia(paramParcel1.readStrongBinder());
        int i5 = paramParcel1.readInt();
        Asset localAsset = null;
        if (i5 != 0) {
          localAsset = (Asset)Asset.CREATOR.createFromParcel(paramParcel1);
        }
        zza(localzzaz12, localAsset);
        paramParcel2.writeNoException();
        return true;
      case 14: 
        paramParcel1.enforceInterface("com.google.android.gms.wearable.internal.IWearableService");
        zzc(zzaz.zza.zzia(paramParcel1.readStrongBinder()));
        paramParcel2.writeNoException();
        return true;
      case 15: 
        paramParcel1.enforceInterface("com.google.android.gms.wearable.internal.IWearableService");
        zzd(zzaz.zza.zzia(paramParcel1.readStrongBinder()));
        paramParcel2.writeNoException();
        return true;
      case 42: 
        paramParcel1.enforceInterface("com.google.android.gms.wearable.internal.IWearableService");
        zza(zzaz.zza.zzia(paramParcel1.readStrongBinder()), paramParcel1.readString(), paramParcel1.readInt());
        paramParcel2.writeNoException();
        return true;
      case 43: 
        paramParcel1.enforceInterface("com.google.android.gms.wearable.internal.IWearableService");
        zza(zzaz.zza.zzia(paramParcel1.readStrongBinder()), paramParcel1.readInt());
        paramParcel2.writeNoException();
        return true;
      case 46: 
        paramParcel1.enforceInterface("com.google.android.gms.wearable.internal.IWearableService");
        zzd(zzaz.zza.zzia(paramParcel1.readStrongBinder()), paramParcel1.readString());
        paramParcel2.writeNoException();
        return true;
      case 47: 
        paramParcel1.enforceInterface("com.google.android.gms.wearable.internal.IWearableService");
        zze(zzaz.zza.zzia(paramParcel1.readStrongBinder()), paramParcel1.readString());
        paramParcel2.writeNoException();
        return true;
      case 16: 
        paramParcel1.enforceInterface("com.google.android.gms.wearable.internal.IWearableService");
        zzaz localzzaz11 = zzaz.zza.zzia(paramParcel1.readStrongBinder());
        int i4 = paramParcel1.readInt();
        AddListenerRequest localAddListenerRequest = null;
        if (i4 != 0) {
          localAddListenerRequest = (AddListenerRequest)AddListenerRequest.CREATOR.createFromParcel(paramParcel1);
        }
        zza(localzzaz11, localAddListenerRequest);
        paramParcel2.writeNoException();
        return true;
      case 17: 
        paramParcel1.enforceInterface("com.google.android.gms.wearable.internal.IWearableService");
        zzaz localzzaz10 = zzaz.zza.zzia(paramParcel1.readStrongBinder());
        int i3 = paramParcel1.readInt();
        RemoveListenerRequest localRemoveListenerRequest = null;
        if (i3 != 0) {
          localRemoveListenerRequest = (RemoveListenerRequest)RemoveListenerRequest.CREATOR.createFromParcel(paramParcel1);
        }
        zza(localzzaz10, localRemoveListenerRequest);
        paramParcel2.writeNoException();
        return true;
      case 18: 
        paramParcel1.enforceInterface("com.google.android.gms.wearable.internal.IWearableService");
        zze(zzaz.zza.zzia(paramParcel1.readStrongBinder()));
        paramParcel2.writeNoException();
        return true;
      case 19: 
        paramParcel1.enforceInterface("com.google.android.gms.wearable.internal.IWearableService");
        zzf(zzaz.zza.zzia(paramParcel1.readStrongBinder()));
        paramParcel2.writeNoException();
        return true;
      case 25: 
        paramParcel1.enforceInterface("com.google.android.gms.wearable.internal.IWearableService");
        zzg(zzaz.zza.zzia(paramParcel1.readStrongBinder()));
        paramParcel2.writeNoException();
        return true;
      case 26: 
        paramParcel1.enforceInterface("com.google.android.gms.wearable.internal.IWearableService");
        zzh(zzaz.zza.zzia(paramParcel1.readStrongBinder()));
        paramParcel2.writeNoException();
        return true;
      case 27: 
        paramParcel1.enforceInterface("com.google.android.gms.wearable.internal.IWearableService");
        zzaz localzzaz9 = zzaz.zza.zzia(paramParcel1.readStrongBinder());
        int i2 = paramParcel1.readInt();
        AncsNotificationParcelable localAncsNotificationParcelable = null;
        if (i2 != 0) {
          localAncsNotificationParcelable = (AncsNotificationParcelable)AncsNotificationParcelable.CREATOR.createFromParcel(paramParcel1);
        }
        zza(localzzaz9, localAncsNotificationParcelable);
        paramParcel2.writeNoException();
        return true;
      case 28: 
        paramParcel1.enforceInterface("com.google.android.gms.wearable.internal.IWearableService");
        zzb(zzaz.zza.zzia(paramParcel1.readStrongBinder()), paramParcel1.readInt());
        paramParcel2.writeNoException();
        return true;
      case 29: 
        paramParcel1.enforceInterface("com.google.android.gms.wearable.internal.IWearableService");
        zzc(zzaz.zza.zzia(paramParcel1.readStrongBinder()), paramParcel1.readInt());
        paramParcel2.writeNoException();
        return true;
      case 30: 
        paramParcel1.enforceInterface("com.google.android.gms.wearable.internal.IWearableService");
        zzi(zzaz.zza.zzia(paramParcel1.readStrongBinder()));
        paramParcel2.writeNoException();
        return true;
      case 31: 
        paramParcel1.enforceInterface("com.google.android.gms.wearable.internal.IWearableService");
        zza(zzaz.zza.zzia(paramParcel1.readStrongBinder()), paramParcel1.readString(), paramParcel1.readString());
        paramParcel2.writeNoException();
        return true;
      case 32: 
        paramParcel1.enforceInterface("com.google.android.gms.wearable.internal.IWearableService");
        zzf(zzaz.zza.zzia(paramParcel1.readStrongBinder()), paramParcel1.readString());
        paramParcel2.writeNoException();
        return true;
      case 33: 
        paramParcel1.enforceInterface("com.google.android.gms.wearable.internal.IWearableService");
        zzb(zzaz.zza.zzia(paramParcel1.readStrongBinder()), paramParcel1.readString(), paramParcel1.readInt());
        paramParcel2.writeNoException();
        return true;
      case 34: 
        paramParcel1.enforceInterface("com.google.android.gms.wearable.internal.IWearableService");
        zza(zzaz.zza.zzia(paramParcel1.readStrongBinder()), zzaw.zza.zzhX(paramParcel1.readStrongBinder()), paramParcel1.readString());
        paramParcel2.writeNoException();
        return true;
      case 35: 
        paramParcel1.enforceInterface("com.google.android.gms.wearable.internal.IWearableService");
        zzb(zzaz.zza.zzia(paramParcel1.readStrongBinder()), zzaw.zza.zzhX(paramParcel1.readStrongBinder()), paramParcel1.readString());
        paramParcel2.writeNoException();
        return true;
      case 38: 
        paramParcel1.enforceInterface("com.google.android.gms.wearable.internal.IWearableService");
        zzaz localzzaz8 = zzaz.zza.zzia(paramParcel1.readStrongBinder());
        String str2 = paramParcel1.readString();
        int i1 = paramParcel1.readInt();
        ParcelFileDescriptor localParcelFileDescriptor2 = null;
        if (i1 != 0) {
          localParcelFileDescriptor2 = (ParcelFileDescriptor)ParcelFileDescriptor.CREATOR.createFromParcel(paramParcel1);
        }
        zza(localzzaz8, str2, localParcelFileDescriptor2);
        paramParcel2.writeNoException();
        return true;
      case 39: 
        paramParcel1.enforceInterface("com.google.android.gms.wearable.internal.IWearableService");
        zzaz localzzaz7 = zzaz.zza.zzia(paramParcel1.readStrongBinder());
        String str1 = paramParcel1.readString();
        if (paramParcel1.readInt() != 0) {}
        for (ParcelFileDescriptor localParcelFileDescriptor1 = (ParcelFileDescriptor)ParcelFileDescriptor.CREATOR.createFromParcel(paramParcel1);; localParcelFileDescriptor1 = null)
        {
          zza(localzzaz7, str1, localParcelFileDescriptor1, paramParcel1.readLong(), paramParcel1.readLong());
          paramParcel2.writeNoException();
          return true;
        }
      case 54: 
        paramParcel1.enforceInterface("com.google.android.gms.wearable.internal.IWearableService");
        zzaz localzzaz6 = zzaz.zza.zzia(paramParcel1.readStrongBinder());
        int n = paramParcel1.readInt();
        LargeAssetEnqueueRequest localLargeAssetEnqueueRequest = null;
        if (n != 0) {
          localLargeAssetEnqueueRequest = (LargeAssetEnqueueRequest)LargeAssetEnqueueRequest.CREATOR.createFromParcel(paramParcel1);
        }
        zza(localzzaz6, localLargeAssetEnqueueRequest);
        paramParcel2.writeNoException();
        return true;
      case 55: 
        paramParcel1.enforceInterface("com.google.android.gms.wearable.internal.IWearableService");
        zzaz localzzaz5 = zzaz.zza.zzia(paramParcel1.readStrongBinder());
        int m = paramParcel1.readInt();
        LargeAssetRemoveRequest localLargeAssetRemoveRequest = null;
        if (m != 0) {
          localLargeAssetRemoveRequest = (LargeAssetRemoveRequest)LargeAssetRemoveRequest.CREATOR.createFromParcel(paramParcel1);
        }
        zza(localzzaz5, localLargeAssetRemoveRequest);
        paramParcel2.writeNoException();
        return true;
      case 56: 
        paramParcel1.enforceInterface("com.google.android.gms.wearable.internal.IWearableService");
        zzaz localzzaz4 = zzaz.zza.zzia(paramParcel1.readStrongBinder());
        int k = paramParcel1.readInt();
        LargeAssetQuery localLargeAssetQuery = null;
        if (k != 0) {
          localLargeAssetQuery = (LargeAssetQuery)LargeAssetQuery.CREATOR.createFromParcel(paramParcel1);
        }
        zza(localzzaz4, localLargeAssetQuery);
        paramParcel2.writeNoException();
        return true;
      case 57: 
        paramParcel1.enforceInterface("com.google.android.gms.wearable.internal.IWearableService");
        zzj(zzaz.zza.zzia(paramParcel1.readStrongBinder()));
        paramParcel2.writeNoException();
        return true;
      case 37: 
        paramParcel1.enforceInterface("com.google.android.gms.wearable.internal.IWearableService");
        zzk(zzaz.zza.zzia(paramParcel1.readStrongBinder()));
        paramParcel2.writeNoException();
        return true;
      case 48: 
        paramParcel1.enforceInterface("com.google.android.gms.wearable.internal.IWearableService");
        zzaz localzzaz3 = zzaz.zza.zzia(paramParcel1.readStrongBinder());
        if (paramParcel1.readInt() != 0) {}
        for (boolean bool2 = true;; bool2 = false)
        {
          zza(localzzaz3, bool2);
          paramParcel2.writeNoException();
          return true;
        }
      case 49: 
        paramParcel1.enforceInterface("com.google.android.gms.wearable.internal.IWearableService");
        zzl(zzaz.zza.zzia(paramParcel1.readStrongBinder()));
        paramParcel2.writeNoException();
        return true;
      case 50: 
        paramParcel1.enforceInterface("com.google.android.gms.wearable.internal.IWearableService");
        zzaz localzzaz2 = zzaz.zza.zzia(paramParcel1.readStrongBinder());
        int j = paramParcel1.readInt();
        boolean bool1 = false;
        if (j != 0) {
          bool1 = true;
        }
        zzb(localzzaz2, bool1);
        paramParcel2.writeNoException();
        return true;
      case 51: 
        paramParcel1.enforceInterface("com.google.android.gms.wearable.internal.IWearableService");
        zzm(zzaz.zza.zzia(paramParcel1.readStrongBinder()));
        paramParcel2.writeNoException();
        return true;
      case 52: 
        paramParcel1.enforceInterface("com.google.android.gms.wearable.internal.IWearableService");
        zzn(zzaz.zza.zzia(paramParcel1.readStrongBinder()));
        paramParcel2.writeNoException();
        return true;
      case 53: 
        paramParcel1.enforceInterface("com.google.android.gms.wearable.internal.IWearableService");
        zza(zzaz.zza.zzia(paramParcel1.readStrongBinder()), paramParcel1.readByte());
        paramParcel2.writeNoException();
        return true;
      case 2: 
        paramParcel1.enforceInterface("com.google.android.gms.wearable.internal.IWearableService");
        zzaz localzzaz1 = zzaz.zza.zzia(paramParcel1.readStrongBinder());
        int i = paramParcel1.readInt();
        ConnectionConfiguration localConnectionConfiguration1 = null;
        if (i != 0) {
          localConnectionConfiguration1 = (ConnectionConfiguration)ConnectionConfiguration.CREATOR.createFromParcel(paramParcel1);
        }
        zzb(localzzaz1, localConnectionConfiguration1);
        paramParcel2.writeNoException();
        return true;
      case 3: 
        paramParcel1.enforceInterface("com.google.android.gms.wearable.internal.IWearableService");
        zzo(zzaz.zza.zzia(paramParcel1.readStrongBinder()));
        paramParcel2.writeNoException();
        return true;
      case 4: 
        paramParcel1.enforceInterface("com.google.android.gms.wearable.internal.IWearableService");
        zzp(zzaz.zza.zzia(paramParcel1.readStrongBinder()));
        paramParcel2.writeNoException();
        return true;
      }
      paramParcel1.enforceInterface("com.google.android.gms.wearable.internal.IWearableService");
      zzq(zzaz.zza.zzia(paramParcel1.readStrongBinder()));
      paramParcel2.writeNoException();
      return true;
    }
    
    private static final class zza
      implements zzbb
    {
      private IBinder zzop;
      
      zza(IBinder paramIBinder)
      {
        this.zzop = paramIBinder;
      }
      
      public final IBinder asBinder()
      {
        return this.zzop;
      }
      
      /* Error */
      public final void zza(zzaz paramzzaz)
        throws RemoteException
      {
        // Byte code:
        //   0: invokestatic 27	android/os/Parcel:obtain	()Landroid/os/Parcel;
        //   3: astore_2
        //   4: invokestatic 27	android/os/Parcel:obtain	()Landroid/os/Parcel;
        //   7: astore_3
        //   8: aload_2
        //   9: ldc 29
        //   11: invokevirtual 33	android/os/Parcel:writeInterfaceToken	(Ljava/lang/String;)V
        //   14: aload_1
        //   15: ifnull +45 -> 60
        //   18: aload_1
        //   19: invokeinterface 37 1 0
        //   24: astore 5
        //   26: aload_2
        //   27: aload 5
        //   29: invokevirtual 40	android/os/Parcel:writeStrongBinder	(Landroid/os/IBinder;)V
        //   32: aload_0
        //   33: getfield 15	com/google/android/gms/wearable/internal/zzbb$zza$zza:zzop	Landroid/os/IBinder;
        //   36: bipush 22
        //   38: aload_2
        //   39: aload_3
        //   40: iconst_0
        //   41: invokeinterface 46 5 0
        //   46: pop
        //   47: aload_3
        //   48: invokevirtual 49	android/os/Parcel:readException	()V
        //   51: aload_3
        //   52: invokevirtual 52	android/os/Parcel:recycle	()V
        //   55: aload_2
        //   56: invokevirtual 52	android/os/Parcel:recycle	()V
        //   59: return
        //   60: aconst_null
        //   61: astore 5
        //   63: goto -37 -> 26
        //   66: astore 4
        //   68: aload_3
        //   69: invokevirtual 52	android/os/Parcel:recycle	()V
        //   72: aload_2
        //   73: invokevirtual 52	android/os/Parcel:recycle	()V
        //   76: aload 4
        //   78: athrow
        // Local variable table:
        //   start	length	slot	name	signature
        //   0	79	0	this	zza
        //   0	79	1	paramzzaz	zzaz
        //   3	70	2	localParcel1	Parcel
        //   7	62	3	localParcel2	Parcel
        //   66	11	4	localObject	Object
        //   24	38	5	localIBinder	IBinder
        // Exception table:
        //   from	to	target	type
        //   8	14	66	finally
        //   18	26	66	finally
        //   26	51	66	finally
      }
      
      /* Error */
      public final void zza(zzaz paramzzaz, byte paramByte)
        throws RemoteException
      {
        // Byte code:
        //   0: invokestatic 27	android/os/Parcel:obtain	()Landroid/os/Parcel;
        //   3: astore_3
        //   4: invokestatic 27	android/os/Parcel:obtain	()Landroid/os/Parcel;
        //   7: astore 4
        //   9: aload_3
        //   10: ldc 29
        //   12: invokevirtual 33	android/os/Parcel:writeInterfaceToken	(Ljava/lang/String;)V
        //   15: aload_1
        //   16: ifnull +53 -> 69
        //   19: aload_1
        //   20: invokeinterface 37 1 0
        //   25: astore 6
        //   27: aload_3
        //   28: aload 6
        //   30: invokevirtual 40	android/os/Parcel:writeStrongBinder	(Landroid/os/IBinder;)V
        //   33: aload_3
        //   34: iload_2
        //   35: invokevirtual 57	android/os/Parcel:writeByte	(B)V
        //   38: aload_0
        //   39: getfield 15	com/google/android/gms/wearable/internal/zzbb$zza$zza:zzop	Landroid/os/IBinder;
        //   42: bipush 53
        //   44: aload_3
        //   45: aload 4
        //   47: iconst_0
        //   48: invokeinterface 46 5 0
        //   53: pop
        //   54: aload 4
        //   56: invokevirtual 49	android/os/Parcel:readException	()V
        //   59: aload 4
        //   61: invokevirtual 52	android/os/Parcel:recycle	()V
        //   64: aload_3
        //   65: invokevirtual 52	android/os/Parcel:recycle	()V
        //   68: return
        //   69: aconst_null
        //   70: astore 6
        //   72: goto -45 -> 27
        //   75: astore 5
        //   77: aload 4
        //   79: invokevirtual 52	android/os/Parcel:recycle	()V
        //   82: aload_3
        //   83: invokevirtual 52	android/os/Parcel:recycle	()V
        //   86: aload 5
        //   88: athrow
        // Local variable table:
        //   start	length	slot	name	signature
        //   0	89	0	this	zza
        //   0	89	1	paramzzaz	zzaz
        //   0	89	2	paramByte	byte
        //   3	80	3	localParcel1	Parcel
        //   7	71	4	localParcel2	Parcel
        //   75	12	5	localObject	Object
        //   25	46	6	localIBinder	IBinder
        // Exception table:
        //   from	to	target	type
        //   9	15	75	finally
        //   19	27	75	finally
        //   27	59	75	finally
      }
      
      /* Error */
      public final void zza(zzaz paramzzaz, int paramInt)
        throws RemoteException
      {
        // Byte code:
        //   0: invokestatic 27	android/os/Parcel:obtain	()Landroid/os/Parcel;
        //   3: astore_3
        //   4: invokestatic 27	android/os/Parcel:obtain	()Landroid/os/Parcel;
        //   7: astore 4
        //   9: aload_3
        //   10: ldc 29
        //   12: invokevirtual 33	android/os/Parcel:writeInterfaceToken	(Ljava/lang/String;)V
        //   15: aload_1
        //   16: ifnull +53 -> 69
        //   19: aload_1
        //   20: invokeinterface 37 1 0
        //   25: astore 6
        //   27: aload_3
        //   28: aload 6
        //   30: invokevirtual 40	android/os/Parcel:writeStrongBinder	(Landroid/os/IBinder;)V
        //   33: aload_3
        //   34: iload_2
        //   35: invokevirtual 62	android/os/Parcel:writeInt	(I)V
        //   38: aload_0
        //   39: getfield 15	com/google/android/gms/wearable/internal/zzbb$zza$zza:zzop	Landroid/os/IBinder;
        //   42: bipush 43
        //   44: aload_3
        //   45: aload 4
        //   47: iconst_0
        //   48: invokeinterface 46 5 0
        //   53: pop
        //   54: aload 4
        //   56: invokevirtual 49	android/os/Parcel:readException	()V
        //   59: aload 4
        //   61: invokevirtual 52	android/os/Parcel:recycle	()V
        //   64: aload_3
        //   65: invokevirtual 52	android/os/Parcel:recycle	()V
        //   68: return
        //   69: aconst_null
        //   70: astore 6
        //   72: goto -45 -> 27
        //   75: astore 5
        //   77: aload 4
        //   79: invokevirtual 52	android/os/Parcel:recycle	()V
        //   82: aload_3
        //   83: invokevirtual 52	android/os/Parcel:recycle	()V
        //   86: aload 5
        //   88: athrow
        // Local variable table:
        //   start	length	slot	name	signature
        //   0	89	0	this	zza
        //   0	89	1	paramzzaz	zzaz
        //   0	89	2	paramInt	int
        //   3	80	3	localParcel1	Parcel
        //   7	71	4	localParcel2	Parcel
        //   75	12	5	localObject	Object
        //   25	46	6	localIBinder	IBinder
        // Exception table:
        //   from	to	target	type
        //   9	15	75	finally
        //   19	27	75	finally
        //   27	59	75	finally
      }
      
      /* Error */
      public final void zza(zzaz paramzzaz, Uri paramUri)
        throws RemoteException
      {
        // Byte code:
        //   0: invokestatic 27	android/os/Parcel:obtain	()Landroid/os/Parcel;
        //   3: astore_3
        //   4: invokestatic 27	android/os/Parcel:obtain	()Landroid/os/Parcel;
        //   7: astore 4
        //   9: aload_3
        //   10: ldc 29
        //   12: invokevirtual 33	android/os/Parcel:writeInterfaceToken	(Ljava/lang/String;)V
        //   15: aload_1
        //   16: ifnull +63 -> 79
        //   19: aload_1
        //   20: invokeinterface 37 1 0
        //   25: astore 6
        //   27: aload_3
        //   28: aload 6
        //   30: invokevirtual 40	android/os/Parcel:writeStrongBinder	(Landroid/os/IBinder;)V
        //   33: aload_2
        //   34: ifnull +51 -> 85
        //   37: aload_3
        //   38: iconst_1
        //   39: invokevirtual 62	android/os/Parcel:writeInt	(I)V
        //   42: aload_2
        //   43: aload_3
        //   44: iconst_0
        //   45: invokevirtual 69	android/net/Uri:writeToParcel	(Landroid/os/Parcel;I)V
        //   48: aload_0
        //   49: getfield 15	com/google/android/gms/wearable/internal/zzbb$zza$zza:zzop	Landroid/os/IBinder;
        //   52: bipush 7
        //   54: aload_3
        //   55: aload 4
        //   57: iconst_0
        //   58: invokeinterface 46 5 0
        //   63: pop
        //   64: aload 4
        //   66: invokevirtual 49	android/os/Parcel:readException	()V
        //   69: aload 4
        //   71: invokevirtual 52	android/os/Parcel:recycle	()V
        //   74: aload_3
        //   75: invokevirtual 52	android/os/Parcel:recycle	()V
        //   78: return
        //   79: aconst_null
        //   80: astore 6
        //   82: goto -55 -> 27
        //   85: aload_3
        //   86: iconst_0
        //   87: invokevirtual 62	android/os/Parcel:writeInt	(I)V
        //   90: goto -42 -> 48
        //   93: astore 5
        //   95: aload 4
        //   97: invokevirtual 52	android/os/Parcel:recycle	()V
        //   100: aload_3
        //   101: invokevirtual 52	android/os/Parcel:recycle	()V
        //   104: aload 5
        //   106: athrow
        // Local variable table:
        //   start	length	slot	name	signature
        //   0	107	0	this	zza
        //   0	107	1	paramzzaz	zzaz
        //   0	107	2	paramUri	Uri
        //   3	98	3	localParcel1	Parcel
        //   7	89	4	localParcel2	Parcel
        //   93	12	5	localObject	Object
        //   25	56	6	localIBinder	IBinder
        // Exception table:
        //   from	to	target	type
        //   9	15	93	finally
        //   19	27	93	finally
        //   27	33	93	finally
        //   37	48	93	finally
        //   48	69	93	finally
        //   85	90	93	finally
      }
      
      /* Error */
      public final void zza(zzaz paramzzaz, Uri paramUri, int paramInt)
        throws RemoteException
      {
        // Byte code:
        //   0: invokestatic 27	android/os/Parcel:obtain	()Landroid/os/Parcel;
        //   3: astore 4
        //   5: invokestatic 27	android/os/Parcel:obtain	()Landroid/os/Parcel;
        //   8: astore 5
        //   10: aload 4
        //   12: ldc 29
        //   14: invokevirtual 33	android/os/Parcel:writeInterfaceToken	(Ljava/lang/String;)V
        //   17: aload_1
        //   18: ifnull +74 -> 92
        //   21: aload_1
        //   22: invokeinterface 37 1 0
        //   27: astore 7
        //   29: aload 4
        //   31: aload 7
        //   33: invokevirtual 40	android/os/Parcel:writeStrongBinder	(Landroid/os/IBinder;)V
        //   36: aload_2
        //   37: ifnull +61 -> 98
        //   40: aload 4
        //   42: iconst_1
        //   43: invokevirtual 62	android/os/Parcel:writeInt	(I)V
        //   46: aload_2
        //   47: aload 4
        //   49: iconst_0
        //   50: invokevirtual 69	android/net/Uri:writeToParcel	(Landroid/os/Parcel;I)V
        //   53: aload 4
        //   55: iload_3
        //   56: invokevirtual 62	android/os/Parcel:writeInt	(I)V
        //   59: aload_0
        //   60: getfield 15	com/google/android/gms/wearable/internal/zzbb$zza$zza:zzop	Landroid/os/IBinder;
        //   63: bipush 40
        //   65: aload 4
        //   67: aload 5
        //   69: iconst_0
        //   70: invokeinterface 46 5 0
        //   75: pop
        //   76: aload 5
        //   78: invokevirtual 49	android/os/Parcel:readException	()V
        //   81: aload 5
        //   83: invokevirtual 52	android/os/Parcel:recycle	()V
        //   86: aload 4
        //   88: invokevirtual 52	android/os/Parcel:recycle	()V
        //   91: return
        //   92: aconst_null
        //   93: astore 7
        //   95: goto -66 -> 29
        //   98: aload 4
        //   100: iconst_0
        //   101: invokevirtual 62	android/os/Parcel:writeInt	(I)V
        //   104: goto -51 -> 53
        //   107: astore 6
        //   109: aload 5
        //   111: invokevirtual 52	android/os/Parcel:recycle	()V
        //   114: aload 4
        //   116: invokevirtual 52	android/os/Parcel:recycle	()V
        //   119: aload 6
        //   121: athrow
        // Local variable table:
        //   start	length	slot	name	signature
        //   0	122	0	this	zza
        //   0	122	1	paramzzaz	zzaz
        //   0	122	2	paramUri	Uri
        //   0	122	3	paramInt	int
        //   3	112	4	localParcel1	Parcel
        //   8	102	5	localParcel2	Parcel
        //   107	13	6	localObject	Object
        //   27	67	7	localIBinder	IBinder
        // Exception table:
        //   from	to	target	type
        //   10	17	107	finally
        //   21	29	107	finally
        //   29	36	107	finally
        //   40	53	107	finally
        //   53	81	107	finally
        //   98	104	107	finally
      }
      
      /* Error */
      public final void zza(zzaz paramzzaz, Asset paramAsset)
        throws RemoteException
      {
        // Byte code:
        //   0: invokestatic 27	android/os/Parcel:obtain	()Landroid/os/Parcel;
        //   3: astore_3
        //   4: invokestatic 27	android/os/Parcel:obtain	()Landroid/os/Parcel;
        //   7: astore 4
        //   9: aload_3
        //   10: ldc 29
        //   12: invokevirtual 33	android/os/Parcel:writeInterfaceToken	(Ljava/lang/String;)V
        //   15: aload_1
        //   16: ifnull +63 -> 79
        //   19: aload_1
        //   20: invokeinterface 37 1 0
        //   25: astore 6
        //   27: aload_3
        //   28: aload 6
        //   30: invokevirtual 40	android/os/Parcel:writeStrongBinder	(Landroid/os/IBinder;)V
        //   33: aload_2
        //   34: ifnull +51 -> 85
        //   37: aload_3
        //   38: iconst_1
        //   39: invokevirtual 62	android/os/Parcel:writeInt	(I)V
        //   42: aload_2
        //   43: aload_3
        //   44: iconst_0
        //   45: invokevirtual 74	com/google/android/gms/wearable/Asset:writeToParcel	(Landroid/os/Parcel;I)V
        //   48: aload_0
        //   49: getfield 15	com/google/android/gms/wearable/internal/zzbb$zza$zza:zzop	Landroid/os/IBinder;
        //   52: bipush 13
        //   54: aload_3
        //   55: aload 4
        //   57: iconst_0
        //   58: invokeinterface 46 5 0
        //   63: pop
        //   64: aload 4
        //   66: invokevirtual 49	android/os/Parcel:readException	()V
        //   69: aload 4
        //   71: invokevirtual 52	android/os/Parcel:recycle	()V
        //   74: aload_3
        //   75: invokevirtual 52	android/os/Parcel:recycle	()V
        //   78: return
        //   79: aconst_null
        //   80: astore 6
        //   82: goto -55 -> 27
        //   85: aload_3
        //   86: iconst_0
        //   87: invokevirtual 62	android/os/Parcel:writeInt	(I)V
        //   90: goto -42 -> 48
        //   93: astore 5
        //   95: aload 4
        //   97: invokevirtual 52	android/os/Parcel:recycle	()V
        //   100: aload_3
        //   101: invokevirtual 52	android/os/Parcel:recycle	()V
        //   104: aload 5
        //   106: athrow
        // Local variable table:
        //   start	length	slot	name	signature
        //   0	107	0	this	zza
        //   0	107	1	paramzzaz	zzaz
        //   0	107	2	paramAsset	Asset
        //   3	98	3	localParcel1	Parcel
        //   7	89	4	localParcel2	Parcel
        //   93	12	5	localObject	Object
        //   25	56	6	localIBinder	IBinder
        // Exception table:
        //   from	to	target	type
        //   9	15	93	finally
        //   19	27	93	finally
        //   27	33	93	finally
        //   37	48	93	finally
        //   48	69	93	finally
        //   85	90	93	finally
      }
      
      /* Error */
      public final void zza(zzaz paramzzaz, ConnectionConfiguration paramConnectionConfiguration)
        throws RemoteException
      {
        // Byte code:
        //   0: invokestatic 27	android/os/Parcel:obtain	()Landroid/os/Parcel;
        //   3: astore_3
        //   4: invokestatic 27	android/os/Parcel:obtain	()Landroid/os/Parcel;
        //   7: astore 4
        //   9: aload_3
        //   10: ldc 29
        //   12: invokevirtual 33	android/os/Parcel:writeInterfaceToken	(Ljava/lang/String;)V
        //   15: aload_1
        //   16: ifnull +63 -> 79
        //   19: aload_1
        //   20: invokeinterface 37 1 0
        //   25: astore 6
        //   27: aload_3
        //   28: aload 6
        //   30: invokevirtual 40	android/os/Parcel:writeStrongBinder	(Landroid/os/IBinder;)V
        //   33: aload_2
        //   34: ifnull +51 -> 85
        //   37: aload_3
        //   38: iconst_1
        //   39: invokevirtual 62	android/os/Parcel:writeInt	(I)V
        //   42: aload_2
        //   43: aload_3
        //   44: iconst_0
        //   45: invokevirtual 78	com/google/android/gms/wearable/ConnectionConfiguration:writeToParcel	(Landroid/os/Parcel;I)V
        //   48: aload_0
        //   49: getfield 15	com/google/android/gms/wearable/internal/zzbb$zza$zza:zzop	Landroid/os/IBinder;
        //   52: bipush 20
        //   54: aload_3
        //   55: aload 4
        //   57: iconst_0
        //   58: invokeinterface 46 5 0
        //   63: pop
        //   64: aload 4
        //   66: invokevirtual 49	android/os/Parcel:readException	()V
        //   69: aload 4
        //   71: invokevirtual 52	android/os/Parcel:recycle	()V
        //   74: aload_3
        //   75: invokevirtual 52	android/os/Parcel:recycle	()V
        //   78: return
        //   79: aconst_null
        //   80: astore 6
        //   82: goto -55 -> 27
        //   85: aload_3
        //   86: iconst_0
        //   87: invokevirtual 62	android/os/Parcel:writeInt	(I)V
        //   90: goto -42 -> 48
        //   93: astore 5
        //   95: aload 4
        //   97: invokevirtual 52	android/os/Parcel:recycle	()V
        //   100: aload_3
        //   101: invokevirtual 52	android/os/Parcel:recycle	()V
        //   104: aload 5
        //   106: athrow
        // Local variable table:
        //   start	length	slot	name	signature
        //   0	107	0	this	zza
        //   0	107	1	paramzzaz	zzaz
        //   0	107	2	paramConnectionConfiguration	ConnectionConfiguration
        //   3	98	3	localParcel1	Parcel
        //   7	89	4	localParcel2	Parcel
        //   93	12	5	localObject	Object
        //   25	56	6	localIBinder	IBinder
        // Exception table:
        //   from	to	target	type
        //   9	15	93	finally
        //   19	27	93	finally
        //   27	33	93	finally
        //   37	48	93	finally
        //   48	69	93	finally
        //   85	90	93	finally
      }
      
      /* Error */
      public final void zza(zzaz paramzzaz, PutDataRequest paramPutDataRequest)
        throws RemoteException
      {
        // Byte code:
        //   0: invokestatic 27	android/os/Parcel:obtain	()Landroid/os/Parcel;
        //   3: astore_3
        //   4: invokestatic 27	android/os/Parcel:obtain	()Landroid/os/Parcel;
        //   7: astore 4
        //   9: aload_3
        //   10: ldc 29
        //   12: invokevirtual 33	android/os/Parcel:writeInterfaceToken	(Ljava/lang/String;)V
        //   15: aload_1
        //   16: ifnull +63 -> 79
        //   19: aload_1
        //   20: invokeinterface 37 1 0
        //   25: astore 6
        //   27: aload_3
        //   28: aload 6
        //   30: invokevirtual 40	android/os/Parcel:writeStrongBinder	(Landroid/os/IBinder;)V
        //   33: aload_2
        //   34: ifnull +51 -> 85
        //   37: aload_3
        //   38: iconst_1
        //   39: invokevirtual 62	android/os/Parcel:writeInt	(I)V
        //   42: aload_2
        //   43: aload_3
        //   44: iconst_0
        //   45: invokevirtual 82	com/google/android/gms/wearable/PutDataRequest:writeToParcel	(Landroid/os/Parcel;I)V
        //   48: aload_0
        //   49: getfield 15	com/google/android/gms/wearable/internal/zzbb$zza$zza:zzop	Landroid/os/IBinder;
        //   52: bipush 6
        //   54: aload_3
        //   55: aload 4
        //   57: iconst_0
        //   58: invokeinterface 46 5 0
        //   63: pop
        //   64: aload 4
        //   66: invokevirtual 49	android/os/Parcel:readException	()V
        //   69: aload 4
        //   71: invokevirtual 52	android/os/Parcel:recycle	()V
        //   74: aload_3
        //   75: invokevirtual 52	android/os/Parcel:recycle	()V
        //   78: return
        //   79: aconst_null
        //   80: astore 6
        //   82: goto -55 -> 27
        //   85: aload_3
        //   86: iconst_0
        //   87: invokevirtual 62	android/os/Parcel:writeInt	(I)V
        //   90: goto -42 -> 48
        //   93: astore 5
        //   95: aload 4
        //   97: invokevirtual 52	android/os/Parcel:recycle	()V
        //   100: aload_3
        //   101: invokevirtual 52	android/os/Parcel:recycle	()V
        //   104: aload 5
        //   106: athrow
        // Local variable table:
        //   start	length	slot	name	signature
        //   0	107	0	this	zza
        //   0	107	1	paramzzaz	zzaz
        //   0	107	2	paramPutDataRequest	PutDataRequest
        //   3	98	3	localParcel1	Parcel
        //   7	89	4	localParcel2	Parcel
        //   93	12	5	localObject	Object
        //   25	56	6	localIBinder	IBinder
        // Exception table:
        //   from	to	target	type
        //   9	15	93	finally
        //   19	27	93	finally
        //   27	33	93	finally
        //   37	48	93	finally
        //   48	69	93	finally
        //   85	90	93	finally
      }
      
      /* Error */
      public final void zza(zzaz paramzzaz, AddListenerRequest paramAddListenerRequest)
        throws RemoteException
      {
        // Byte code:
        //   0: invokestatic 27	android/os/Parcel:obtain	()Landroid/os/Parcel;
        //   3: astore_3
        //   4: invokestatic 27	android/os/Parcel:obtain	()Landroid/os/Parcel;
        //   7: astore 4
        //   9: aload_3
        //   10: ldc 29
        //   12: invokevirtual 33	android/os/Parcel:writeInterfaceToken	(Ljava/lang/String;)V
        //   15: aload_1
        //   16: ifnull +63 -> 79
        //   19: aload_1
        //   20: invokeinterface 37 1 0
        //   25: astore 6
        //   27: aload_3
        //   28: aload 6
        //   30: invokevirtual 40	android/os/Parcel:writeStrongBinder	(Landroid/os/IBinder;)V
        //   33: aload_2
        //   34: ifnull +51 -> 85
        //   37: aload_3
        //   38: iconst_1
        //   39: invokevirtual 62	android/os/Parcel:writeInt	(I)V
        //   42: aload_2
        //   43: aload_3
        //   44: iconst_0
        //   45: invokevirtual 86	com/google/android/gms/wearable/internal/AddListenerRequest:writeToParcel	(Landroid/os/Parcel;I)V
        //   48: aload_0
        //   49: getfield 15	com/google/android/gms/wearable/internal/zzbb$zza$zza:zzop	Landroid/os/IBinder;
        //   52: bipush 16
        //   54: aload_3
        //   55: aload 4
        //   57: iconst_0
        //   58: invokeinterface 46 5 0
        //   63: pop
        //   64: aload 4
        //   66: invokevirtual 49	android/os/Parcel:readException	()V
        //   69: aload 4
        //   71: invokevirtual 52	android/os/Parcel:recycle	()V
        //   74: aload_3
        //   75: invokevirtual 52	android/os/Parcel:recycle	()V
        //   78: return
        //   79: aconst_null
        //   80: astore 6
        //   82: goto -55 -> 27
        //   85: aload_3
        //   86: iconst_0
        //   87: invokevirtual 62	android/os/Parcel:writeInt	(I)V
        //   90: goto -42 -> 48
        //   93: astore 5
        //   95: aload 4
        //   97: invokevirtual 52	android/os/Parcel:recycle	()V
        //   100: aload_3
        //   101: invokevirtual 52	android/os/Parcel:recycle	()V
        //   104: aload 5
        //   106: athrow
        // Local variable table:
        //   start	length	slot	name	signature
        //   0	107	0	this	zza
        //   0	107	1	paramzzaz	zzaz
        //   0	107	2	paramAddListenerRequest	AddListenerRequest
        //   3	98	3	localParcel1	Parcel
        //   7	89	4	localParcel2	Parcel
        //   93	12	5	localObject	Object
        //   25	56	6	localIBinder	IBinder
        // Exception table:
        //   from	to	target	type
        //   9	15	93	finally
        //   19	27	93	finally
        //   27	33	93	finally
        //   37	48	93	finally
        //   48	69	93	finally
        //   85	90	93	finally
      }
      
      /* Error */
      public final void zza(zzaz paramzzaz, AncsNotificationParcelable paramAncsNotificationParcelable)
        throws RemoteException
      {
        // Byte code:
        //   0: invokestatic 27	android/os/Parcel:obtain	()Landroid/os/Parcel;
        //   3: astore_3
        //   4: invokestatic 27	android/os/Parcel:obtain	()Landroid/os/Parcel;
        //   7: astore 4
        //   9: aload_3
        //   10: ldc 29
        //   12: invokevirtual 33	android/os/Parcel:writeInterfaceToken	(Ljava/lang/String;)V
        //   15: aload_1
        //   16: ifnull +63 -> 79
        //   19: aload_1
        //   20: invokeinterface 37 1 0
        //   25: astore 6
        //   27: aload_3
        //   28: aload 6
        //   30: invokevirtual 40	android/os/Parcel:writeStrongBinder	(Landroid/os/IBinder;)V
        //   33: aload_2
        //   34: ifnull +51 -> 85
        //   37: aload_3
        //   38: iconst_1
        //   39: invokevirtual 62	android/os/Parcel:writeInt	(I)V
        //   42: aload_2
        //   43: aload_3
        //   44: iconst_0
        //   45: invokevirtual 90	com/google/android/gms/wearable/internal/AncsNotificationParcelable:writeToParcel	(Landroid/os/Parcel;I)V
        //   48: aload_0
        //   49: getfield 15	com/google/android/gms/wearable/internal/zzbb$zza$zza:zzop	Landroid/os/IBinder;
        //   52: bipush 27
        //   54: aload_3
        //   55: aload 4
        //   57: iconst_0
        //   58: invokeinterface 46 5 0
        //   63: pop
        //   64: aload 4
        //   66: invokevirtual 49	android/os/Parcel:readException	()V
        //   69: aload 4
        //   71: invokevirtual 52	android/os/Parcel:recycle	()V
        //   74: aload_3
        //   75: invokevirtual 52	android/os/Parcel:recycle	()V
        //   78: return
        //   79: aconst_null
        //   80: astore 6
        //   82: goto -55 -> 27
        //   85: aload_3
        //   86: iconst_0
        //   87: invokevirtual 62	android/os/Parcel:writeInt	(I)V
        //   90: goto -42 -> 48
        //   93: astore 5
        //   95: aload 4
        //   97: invokevirtual 52	android/os/Parcel:recycle	()V
        //   100: aload_3
        //   101: invokevirtual 52	android/os/Parcel:recycle	()V
        //   104: aload 5
        //   106: athrow
        // Local variable table:
        //   start	length	slot	name	signature
        //   0	107	0	this	zza
        //   0	107	1	paramzzaz	zzaz
        //   0	107	2	paramAncsNotificationParcelable	AncsNotificationParcelable
        //   3	98	3	localParcel1	Parcel
        //   7	89	4	localParcel2	Parcel
        //   93	12	5	localObject	Object
        //   25	56	6	localIBinder	IBinder
        // Exception table:
        //   from	to	target	type
        //   9	15	93	finally
        //   19	27	93	finally
        //   27	33	93	finally
        //   37	48	93	finally
        //   48	69	93	finally
        //   85	90	93	finally
      }
      
      /* Error */
      public final void zza(zzaz paramzzaz, LargeAssetEnqueueRequest paramLargeAssetEnqueueRequest)
        throws RemoteException
      {
        // Byte code:
        //   0: invokestatic 27	android/os/Parcel:obtain	()Landroid/os/Parcel;
        //   3: astore_3
        //   4: invokestatic 27	android/os/Parcel:obtain	()Landroid/os/Parcel;
        //   7: astore 4
        //   9: aload_3
        //   10: ldc 29
        //   12: invokevirtual 33	android/os/Parcel:writeInterfaceToken	(Ljava/lang/String;)V
        //   15: aload_1
        //   16: ifnull +63 -> 79
        //   19: aload_1
        //   20: invokeinterface 37 1 0
        //   25: astore 6
        //   27: aload_3
        //   28: aload 6
        //   30: invokevirtual 40	android/os/Parcel:writeStrongBinder	(Landroid/os/IBinder;)V
        //   33: aload_2
        //   34: ifnull +51 -> 85
        //   37: aload_3
        //   38: iconst_1
        //   39: invokevirtual 62	android/os/Parcel:writeInt	(I)V
        //   42: aload_2
        //   43: aload_3
        //   44: iconst_0
        //   45: invokevirtual 94	com/google/android/gms/wearable/internal/LargeAssetEnqueueRequest:writeToParcel	(Landroid/os/Parcel;I)V
        //   48: aload_0
        //   49: getfield 15	com/google/android/gms/wearable/internal/zzbb$zza$zza:zzop	Landroid/os/IBinder;
        //   52: bipush 54
        //   54: aload_3
        //   55: aload 4
        //   57: iconst_0
        //   58: invokeinterface 46 5 0
        //   63: pop
        //   64: aload 4
        //   66: invokevirtual 49	android/os/Parcel:readException	()V
        //   69: aload 4
        //   71: invokevirtual 52	android/os/Parcel:recycle	()V
        //   74: aload_3
        //   75: invokevirtual 52	android/os/Parcel:recycle	()V
        //   78: return
        //   79: aconst_null
        //   80: astore 6
        //   82: goto -55 -> 27
        //   85: aload_3
        //   86: iconst_0
        //   87: invokevirtual 62	android/os/Parcel:writeInt	(I)V
        //   90: goto -42 -> 48
        //   93: astore 5
        //   95: aload 4
        //   97: invokevirtual 52	android/os/Parcel:recycle	()V
        //   100: aload_3
        //   101: invokevirtual 52	android/os/Parcel:recycle	()V
        //   104: aload 5
        //   106: athrow
        // Local variable table:
        //   start	length	slot	name	signature
        //   0	107	0	this	zza
        //   0	107	1	paramzzaz	zzaz
        //   0	107	2	paramLargeAssetEnqueueRequest	LargeAssetEnqueueRequest
        //   3	98	3	localParcel1	Parcel
        //   7	89	4	localParcel2	Parcel
        //   93	12	5	localObject	Object
        //   25	56	6	localIBinder	IBinder
        // Exception table:
        //   from	to	target	type
        //   9	15	93	finally
        //   19	27	93	finally
        //   27	33	93	finally
        //   37	48	93	finally
        //   48	69	93	finally
        //   85	90	93	finally
      }
      
      /* Error */
      public final void zza(zzaz paramzzaz, LargeAssetQuery paramLargeAssetQuery)
        throws RemoteException
      {
        // Byte code:
        //   0: invokestatic 27	android/os/Parcel:obtain	()Landroid/os/Parcel;
        //   3: astore_3
        //   4: invokestatic 27	android/os/Parcel:obtain	()Landroid/os/Parcel;
        //   7: astore 4
        //   9: aload_3
        //   10: ldc 29
        //   12: invokevirtual 33	android/os/Parcel:writeInterfaceToken	(Ljava/lang/String;)V
        //   15: aload_1
        //   16: ifnull +63 -> 79
        //   19: aload_1
        //   20: invokeinterface 37 1 0
        //   25: astore 6
        //   27: aload_3
        //   28: aload 6
        //   30: invokevirtual 40	android/os/Parcel:writeStrongBinder	(Landroid/os/IBinder;)V
        //   33: aload_2
        //   34: ifnull +51 -> 85
        //   37: aload_3
        //   38: iconst_1
        //   39: invokevirtual 62	android/os/Parcel:writeInt	(I)V
        //   42: aload_2
        //   43: aload_3
        //   44: iconst_0
        //   45: invokevirtual 98	com/google/android/gms/wearable/internal/LargeAssetQuery:writeToParcel	(Landroid/os/Parcel;I)V
        //   48: aload_0
        //   49: getfield 15	com/google/android/gms/wearable/internal/zzbb$zza$zza:zzop	Landroid/os/IBinder;
        //   52: bipush 56
        //   54: aload_3
        //   55: aload 4
        //   57: iconst_0
        //   58: invokeinterface 46 5 0
        //   63: pop
        //   64: aload 4
        //   66: invokevirtual 49	android/os/Parcel:readException	()V
        //   69: aload 4
        //   71: invokevirtual 52	android/os/Parcel:recycle	()V
        //   74: aload_3
        //   75: invokevirtual 52	android/os/Parcel:recycle	()V
        //   78: return
        //   79: aconst_null
        //   80: astore 6
        //   82: goto -55 -> 27
        //   85: aload_3
        //   86: iconst_0
        //   87: invokevirtual 62	android/os/Parcel:writeInt	(I)V
        //   90: goto -42 -> 48
        //   93: astore 5
        //   95: aload 4
        //   97: invokevirtual 52	android/os/Parcel:recycle	()V
        //   100: aload_3
        //   101: invokevirtual 52	android/os/Parcel:recycle	()V
        //   104: aload 5
        //   106: athrow
        // Local variable table:
        //   start	length	slot	name	signature
        //   0	107	0	this	zza
        //   0	107	1	paramzzaz	zzaz
        //   0	107	2	paramLargeAssetQuery	LargeAssetQuery
        //   3	98	3	localParcel1	Parcel
        //   7	89	4	localParcel2	Parcel
        //   93	12	5	localObject	Object
        //   25	56	6	localIBinder	IBinder
        // Exception table:
        //   from	to	target	type
        //   9	15	93	finally
        //   19	27	93	finally
        //   27	33	93	finally
        //   37	48	93	finally
        //   48	69	93	finally
        //   85	90	93	finally
      }
      
      /* Error */
      public final void zza(zzaz paramzzaz, LargeAssetRemoveRequest paramLargeAssetRemoveRequest)
        throws RemoteException
      {
        // Byte code:
        //   0: invokestatic 27	android/os/Parcel:obtain	()Landroid/os/Parcel;
        //   3: astore_3
        //   4: invokestatic 27	android/os/Parcel:obtain	()Landroid/os/Parcel;
        //   7: astore 4
        //   9: aload_3
        //   10: ldc 29
        //   12: invokevirtual 33	android/os/Parcel:writeInterfaceToken	(Ljava/lang/String;)V
        //   15: aload_1
        //   16: ifnull +63 -> 79
        //   19: aload_1
        //   20: invokeinterface 37 1 0
        //   25: astore 6
        //   27: aload_3
        //   28: aload 6
        //   30: invokevirtual 40	android/os/Parcel:writeStrongBinder	(Landroid/os/IBinder;)V
        //   33: aload_2
        //   34: ifnull +51 -> 85
        //   37: aload_3
        //   38: iconst_1
        //   39: invokevirtual 62	android/os/Parcel:writeInt	(I)V
        //   42: aload_2
        //   43: aload_3
        //   44: iconst_0
        //   45: invokevirtual 102	com/google/android/gms/wearable/internal/LargeAssetRemoveRequest:writeToParcel	(Landroid/os/Parcel;I)V
        //   48: aload_0
        //   49: getfield 15	com/google/android/gms/wearable/internal/zzbb$zza$zza:zzop	Landroid/os/IBinder;
        //   52: bipush 55
        //   54: aload_3
        //   55: aload 4
        //   57: iconst_0
        //   58: invokeinterface 46 5 0
        //   63: pop
        //   64: aload 4
        //   66: invokevirtual 49	android/os/Parcel:readException	()V
        //   69: aload 4
        //   71: invokevirtual 52	android/os/Parcel:recycle	()V
        //   74: aload_3
        //   75: invokevirtual 52	android/os/Parcel:recycle	()V
        //   78: return
        //   79: aconst_null
        //   80: astore 6
        //   82: goto -55 -> 27
        //   85: aload_3
        //   86: iconst_0
        //   87: invokevirtual 62	android/os/Parcel:writeInt	(I)V
        //   90: goto -42 -> 48
        //   93: astore 5
        //   95: aload 4
        //   97: invokevirtual 52	android/os/Parcel:recycle	()V
        //   100: aload_3
        //   101: invokevirtual 52	android/os/Parcel:recycle	()V
        //   104: aload 5
        //   106: athrow
        // Local variable table:
        //   start	length	slot	name	signature
        //   0	107	0	this	zza
        //   0	107	1	paramzzaz	zzaz
        //   0	107	2	paramLargeAssetRemoveRequest	LargeAssetRemoveRequest
        //   3	98	3	localParcel1	Parcel
        //   7	89	4	localParcel2	Parcel
        //   93	12	5	localObject	Object
        //   25	56	6	localIBinder	IBinder
        // Exception table:
        //   from	to	target	type
        //   9	15	93	finally
        //   19	27	93	finally
        //   27	33	93	finally
        //   37	48	93	finally
        //   48	69	93	finally
        //   85	90	93	finally
      }
      
      /* Error */
      public final void zza(zzaz paramzzaz, RemoveListenerRequest paramRemoveListenerRequest)
        throws RemoteException
      {
        // Byte code:
        //   0: invokestatic 27	android/os/Parcel:obtain	()Landroid/os/Parcel;
        //   3: astore_3
        //   4: invokestatic 27	android/os/Parcel:obtain	()Landroid/os/Parcel;
        //   7: astore 4
        //   9: aload_3
        //   10: ldc 29
        //   12: invokevirtual 33	android/os/Parcel:writeInterfaceToken	(Ljava/lang/String;)V
        //   15: aload_1
        //   16: ifnull +63 -> 79
        //   19: aload_1
        //   20: invokeinterface 37 1 0
        //   25: astore 6
        //   27: aload_3
        //   28: aload 6
        //   30: invokevirtual 40	android/os/Parcel:writeStrongBinder	(Landroid/os/IBinder;)V
        //   33: aload_2
        //   34: ifnull +51 -> 85
        //   37: aload_3
        //   38: iconst_1
        //   39: invokevirtual 62	android/os/Parcel:writeInt	(I)V
        //   42: aload_2
        //   43: aload_3
        //   44: iconst_0
        //   45: invokevirtual 106	com/google/android/gms/wearable/internal/RemoveListenerRequest:writeToParcel	(Landroid/os/Parcel;I)V
        //   48: aload_0
        //   49: getfield 15	com/google/android/gms/wearable/internal/zzbb$zza$zza:zzop	Landroid/os/IBinder;
        //   52: bipush 17
        //   54: aload_3
        //   55: aload 4
        //   57: iconst_0
        //   58: invokeinterface 46 5 0
        //   63: pop
        //   64: aload 4
        //   66: invokevirtual 49	android/os/Parcel:readException	()V
        //   69: aload 4
        //   71: invokevirtual 52	android/os/Parcel:recycle	()V
        //   74: aload_3
        //   75: invokevirtual 52	android/os/Parcel:recycle	()V
        //   78: return
        //   79: aconst_null
        //   80: astore 6
        //   82: goto -55 -> 27
        //   85: aload_3
        //   86: iconst_0
        //   87: invokevirtual 62	android/os/Parcel:writeInt	(I)V
        //   90: goto -42 -> 48
        //   93: astore 5
        //   95: aload 4
        //   97: invokevirtual 52	android/os/Parcel:recycle	()V
        //   100: aload_3
        //   101: invokevirtual 52	android/os/Parcel:recycle	()V
        //   104: aload 5
        //   106: athrow
        // Local variable table:
        //   start	length	slot	name	signature
        //   0	107	0	this	zza
        //   0	107	1	paramzzaz	zzaz
        //   0	107	2	paramRemoveListenerRequest	RemoveListenerRequest
        //   3	98	3	localParcel1	Parcel
        //   7	89	4	localParcel2	Parcel
        //   93	12	5	localObject	Object
        //   25	56	6	localIBinder	IBinder
        // Exception table:
        //   from	to	target	type
        //   9	15	93	finally
        //   19	27	93	finally
        //   27	33	93	finally
        //   37	48	93	finally
        //   48	69	93	finally
        //   85	90	93	finally
      }
      
      /* Error */
      public final void zza(zzaz paramzzaz, zzaw paramzzaw, String paramString)
        throws RemoteException
      {
        // Byte code:
        //   0: invokestatic 27	android/os/Parcel:obtain	()Landroid/os/Parcel;
        //   3: astore 4
        //   5: invokestatic 27	android/os/Parcel:obtain	()Landroid/os/Parcel;
        //   8: astore 5
        //   10: aload 4
        //   12: ldc 29
        //   14: invokevirtual 33	android/os/Parcel:writeInterfaceToken	(Ljava/lang/String;)V
        //   17: aload_1
        //   18: ifnull +79 -> 97
        //   21: aload_1
        //   22: invokeinterface 37 1 0
        //   27: astore 7
        //   29: aload 4
        //   31: aload 7
        //   33: invokevirtual 40	android/os/Parcel:writeStrongBinder	(Landroid/os/IBinder;)V
        //   36: aconst_null
        //   37: astore 8
        //   39: aload_2
        //   40: ifnull +11 -> 51
        //   43: aload_2
        //   44: invokeinterface 110 1 0
        //   49: astore 8
        //   51: aload 4
        //   53: aload 8
        //   55: invokevirtual 40	android/os/Parcel:writeStrongBinder	(Landroid/os/IBinder;)V
        //   58: aload 4
        //   60: aload_3
        //   61: invokevirtual 113	android/os/Parcel:writeString	(Ljava/lang/String;)V
        //   64: aload_0
        //   65: getfield 15	com/google/android/gms/wearable/internal/zzbb$zza$zza:zzop	Landroid/os/IBinder;
        //   68: bipush 34
        //   70: aload 4
        //   72: aload 5
        //   74: iconst_0
        //   75: invokeinterface 46 5 0
        //   80: pop
        //   81: aload 5
        //   83: invokevirtual 49	android/os/Parcel:readException	()V
        //   86: aload 5
        //   88: invokevirtual 52	android/os/Parcel:recycle	()V
        //   91: aload 4
        //   93: invokevirtual 52	android/os/Parcel:recycle	()V
        //   96: return
        //   97: aconst_null
        //   98: astore 7
        //   100: goto -71 -> 29
        //   103: astore 6
        //   105: aload 5
        //   107: invokevirtual 52	android/os/Parcel:recycle	()V
        //   110: aload 4
        //   112: invokevirtual 52	android/os/Parcel:recycle	()V
        //   115: aload 6
        //   117: athrow
        // Local variable table:
        //   start	length	slot	name	signature
        //   0	118	0	this	zza
        //   0	118	1	paramzzaz	zzaz
        //   0	118	2	paramzzaw	zzaw
        //   0	118	3	paramString	String
        //   3	108	4	localParcel1	Parcel
        //   8	98	5	localParcel2	Parcel
        //   103	13	6	localObject	Object
        //   27	72	7	localIBinder1	IBinder
        //   37	17	8	localIBinder2	IBinder
        // Exception table:
        //   from	to	target	type
        //   10	17	103	finally
        //   21	29	103	finally
        //   29	36	103	finally
        //   43	51	103	finally
        //   51	86	103	finally
      }
      
      /* Error */
      public final void zza(zzaz paramzzaz, String paramString)
        throws RemoteException
      {
        // Byte code:
        //   0: invokestatic 27	android/os/Parcel:obtain	()Landroid/os/Parcel;
        //   3: astore_3
        //   4: invokestatic 27	android/os/Parcel:obtain	()Landroid/os/Parcel;
        //   7: astore 4
        //   9: aload_3
        //   10: ldc 29
        //   12: invokevirtual 33	android/os/Parcel:writeInterfaceToken	(Ljava/lang/String;)V
        //   15: aload_1
        //   16: ifnull +53 -> 69
        //   19: aload_1
        //   20: invokeinterface 37 1 0
        //   25: astore 6
        //   27: aload_3
        //   28: aload 6
        //   30: invokevirtual 40	android/os/Parcel:writeStrongBinder	(Landroid/os/IBinder;)V
        //   33: aload_3
        //   34: aload_2
        //   35: invokevirtual 113	android/os/Parcel:writeString	(Ljava/lang/String;)V
        //   38: aload_0
        //   39: getfield 15	com/google/android/gms/wearable/internal/zzbb$zza$zza:zzop	Landroid/os/IBinder;
        //   42: bipush 21
        //   44: aload_3
        //   45: aload 4
        //   47: iconst_0
        //   48: invokeinterface 46 5 0
        //   53: pop
        //   54: aload 4
        //   56: invokevirtual 49	android/os/Parcel:readException	()V
        //   59: aload 4
        //   61: invokevirtual 52	android/os/Parcel:recycle	()V
        //   64: aload_3
        //   65: invokevirtual 52	android/os/Parcel:recycle	()V
        //   68: return
        //   69: aconst_null
        //   70: astore 6
        //   72: goto -45 -> 27
        //   75: astore 5
        //   77: aload 4
        //   79: invokevirtual 52	android/os/Parcel:recycle	()V
        //   82: aload_3
        //   83: invokevirtual 52	android/os/Parcel:recycle	()V
        //   86: aload 5
        //   88: athrow
        // Local variable table:
        //   start	length	slot	name	signature
        //   0	89	0	this	zza
        //   0	89	1	paramzzaz	zzaz
        //   0	89	2	paramString	String
        //   3	80	3	localParcel1	Parcel
        //   7	71	4	localParcel2	Parcel
        //   75	12	5	localObject	Object
        //   25	46	6	localIBinder	IBinder
        // Exception table:
        //   from	to	target	type
        //   9	15	75	finally
        //   19	27	75	finally
        //   27	59	75	finally
      }
      
      /* Error */
      public final void zza(zzaz paramzzaz, String paramString, int paramInt)
        throws RemoteException
      {
        // Byte code:
        //   0: invokestatic 27	android/os/Parcel:obtain	()Landroid/os/Parcel;
        //   3: astore 4
        //   5: invokestatic 27	android/os/Parcel:obtain	()Landroid/os/Parcel;
        //   8: astore 5
        //   10: aload 4
        //   12: ldc 29
        //   14: invokevirtual 33	android/os/Parcel:writeInterfaceToken	(Ljava/lang/String;)V
        //   17: aload_1
        //   18: ifnull +63 -> 81
        //   21: aload_1
        //   22: invokeinterface 37 1 0
        //   27: astore 7
        //   29: aload 4
        //   31: aload 7
        //   33: invokevirtual 40	android/os/Parcel:writeStrongBinder	(Landroid/os/IBinder;)V
        //   36: aload 4
        //   38: aload_2
        //   39: invokevirtual 113	android/os/Parcel:writeString	(Ljava/lang/String;)V
        //   42: aload 4
        //   44: iload_3
        //   45: invokevirtual 62	android/os/Parcel:writeInt	(I)V
        //   48: aload_0
        //   49: getfield 15	com/google/android/gms/wearable/internal/zzbb$zza$zza:zzop	Landroid/os/IBinder;
        //   52: bipush 42
        //   54: aload 4
        //   56: aload 5
        //   58: iconst_0
        //   59: invokeinterface 46 5 0
        //   64: pop
        //   65: aload 5
        //   67: invokevirtual 49	android/os/Parcel:readException	()V
        //   70: aload 5
        //   72: invokevirtual 52	android/os/Parcel:recycle	()V
        //   75: aload 4
        //   77: invokevirtual 52	android/os/Parcel:recycle	()V
        //   80: return
        //   81: aconst_null
        //   82: astore 7
        //   84: goto -55 -> 29
        //   87: astore 6
        //   89: aload 5
        //   91: invokevirtual 52	android/os/Parcel:recycle	()V
        //   94: aload 4
        //   96: invokevirtual 52	android/os/Parcel:recycle	()V
        //   99: aload 6
        //   101: athrow
        // Local variable table:
        //   start	length	slot	name	signature
        //   0	102	0	this	zza
        //   0	102	1	paramzzaz	zzaz
        //   0	102	2	paramString	String
        //   0	102	3	paramInt	int
        //   3	92	4	localParcel1	Parcel
        //   8	82	5	localParcel2	Parcel
        //   87	13	6	localObject	Object
        //   27	56	7	localIBinder	IBinder
        // Exception table:
        //   from	to	target	type
        //   10	17	87	finally
        //   21	29	87	finally
        //   29	70	87	finally
      }
      
      /* Error */
      public final void zza(zzaz paramzzaz, String paramString, ParcelFileDescriptor paramParcelFileDescriptor)
        throws RemoteException
      {
        // Byte code:
        //   0: invokestatic 27	android/os/Parcel:obtain	()Landroid/os/Parcel;
        //   3: astore 4
        //   5: invokestatic 27	android/os/Parcel:obtain	()Landroid/os/Parcel;
        //   8: astore 5
        //   10: aload 4
        //   12: ldc 29
        //   14: invokevirtual 33	android/os/Parcel:writeInterfaceToken	(Ljava/lang/String;)V
        //   17: aload_1
        //   18: ifnull +74 -> 92
        //   21: aload_1
        //   22: invokeinterface 37 1 0
        //   27: astore 7
        //   29: aload 4
        //   31: aload 7
        //   33: invokevirtual 40	android/os/Parcel:writeStrongBinder	(Landroid/os/IBinder;)V
        //   36: aload 4
        //   38: aload_2
        //   39: invokevirtual 113	android/os/Parcel:writeString	(Ljava/lang/String;)V
        //   42: aload_3
        //   43: ifnull +55 -> 98
        //   46: aload 4
        //   48: iconst_1
        //   49: invokevirtual 62	android/os/Parcel:writeInt	(I)V
        //   52: aload_3
        //   53: aload 4
        //   55: iconst_0
        //   56: invokevirtual 119	android/os/ParcelFileDescriptor:writeToParcel	(Landroid/os/Parcel;I)V
        //   59: aload_0
        //   60: getfield 15	com/google/android/gms/wearable/internal/zzbb$zza$zza:zzop	Landroid/os/IBinder;
        //   63: bipush 38
        //   65: aload 4
        //   67: aload 5
        //   69: iconst_0
        //   70: invokeinterface 46 5 0
        //   75: pop
        //   76: aload 5
        //   78: invokevirtual 49	android/os/Parcel:readException	()V
        //   81: aload 5
        //   83: invokevirtual 52	android/os/Parcel:recycle	()V
        //   86: aload 4
        //   88: invokevirtual 52	android/os/Parcel:recycle	()V
        //   91: return
        //   92: aconst_null
        //   93: astore 7
        //   95: goto -66 -> 29
        //   98: aload 4
        //   100: iconst_0
        //   101: invokevirtual 62	android/os/Parcel:writeInt	(I)V
        //   104: goto -45 -> 59
        //   107: astore 6
        //   109: aload 5
        //   111: invokevirtual 52	android/os/Parcel:recycle	()V
        //   114: aload 4
        //   116: invokevirtual 52	android/os/Parcel:recycle	()V
        //   119: aload 6
        //   121: athrow
        // Local variable table:
        //   start	length	slot	name	signature
        //   0	122	0	this	zza
        //   0	122	1	paramzzaz	zzaz
        //   0	122	2	paramString	String
        //   0	122	3	paramParcelFileDescriptor	ParcelFileDescriptor
        //   3	112	4	localParcel1	Parcel
        //   8	102	5	localParcel2	Parcel
        //   107	13	6	localObject	Object
        //   27	67	7	localIBinder	IBinder
        // Exception table:
        //   from	to	target	type
        //   10	17	107	finally
        //   21	29	107	finally
        //   29	42	107	finally
        //   46	59	107	finally
        //   59	81	107	finally
        //   98	104	107	finally
      }
      
      /* Error */
      public final void zza(zzaz paramzzaz, String paramString, ParcelFileDescriptor paramParcelFileDescriptor, long paramLong1, long paramLong2)
        throws RemoteException
      {
        // Byte code:
        //   0: invokestatic 27	android/os/Parcel:obtain	()Landroid/os/Parcel;
        //   3: astore 8
        //   5: invokestatic 27	android/os/Parcel:obtain	()Landroid/os/Parcel;
        //   8: astore 9
        //   10: aload 8
        //   12: ldc 29
        //   14: invokevirtual 33	android/os/Parcel:writeInterfaceToken	(Ljava/lang/String;)V
        //   17: aload_1
        //   18: ifnull +88 -> 106
        //   21: aload_1
        //   22: invokeinterface 37 1 0
        //   27: astore 11
        //   29: aload 8
        //   31: aload 11
        //   33: invokevirtual 40	android/os/Parcel:writeStrongBinder	(Landroid/os/IBinder;)V
        //   36: aload 8
        //   38: aload_2
        //   39: invokevirtual 113	android/os/Parcel:writeString	(Ljava/lang/String;)V
        //   42: aload_3
        //   43: ifnull +69 -> 112
        //   46: aload 8
        //   48: iconst_1
        //   49: invokevirtual 62	android/os/Parcel:writeInt	(I)V
        //   52: aload_3
        //   53: aload 8
        //   55: iconst_0
        //   56: invokevirtual 119	android/os/ParcelFileDescriptor:writeToParcel	(Landroid/os/Parcel;I)V
        //   59: aload 8
        //   61: lload 4
        //   63: invokevirtual 124	android/os/Parcel:writeLong	(J)V
        //   66: aload 8
        //   68: lload 6
        //   70: invokevirtual 124	android/os/Parcel:writeLong	(J)V
        //   73: aload_0
        //   74: getfield 15	com/google/android/gms/wearable/internal/zzbb$zza$zza:zzop	Landroid/os/IBinder;
        //   77: bipush 39
        //   79: aload 8
        //   81: aload 9
        //   83: iconst_0
        //   84: invokeinterface 46 5 0
        //   89: pop
        //   90: aload 9
        //   92: invokevirtual 49	android/os/Parcel:readException	()V
        //   95: aload 9
        //   97: invokevirtual 52	android/os/Parcel:recycle	()V
        //   100: aload 8
        //   102: invokevirtual 52	android/os/Parcel:recycle	()V
        //   105: return
        //   106: aconst_null
        //   107: astore 11
        //   109: goto -80 -> 29
        //   112: aload 8
        //   114: iconst_0
        //   115: invokevirtual 62	android/os/Parcel:writeInt	(I)V
        //   118: goto -59 -> 59
        //   121: astore 10
        //   123: aload 9
        //   125: invokevirtual 52	android/os/Parcel:recycle	()V
        //   128: aload 8
        //   130: invokevirtual 52	android/os/Parcel:recycle	()V
        //   133: aload 10
        //   135: athrow
        // Local variable table:
        //   start	length	slot	name	signature
        //   0	136	0	this	zza
        //   0	136	1	paramzzaz	zzaz
        //   0	136	2	paramString	String
        //   0	136	3	paramParcelFileDescriptor	ParcelFileDescriptor
        //   0	136	4	paramLong1	long
        //   0	136	6	paramLong2	long
        //   3	126	8	localParcel1	Parcel
        //   8	116	9	localParcel2	Parcel
        //   121	13	10	localObject	Object
        //   27	81	11	localIBinder	IBinder
        // Exception table:
        //   from	to	target	type
        //   10	17	121	finally
        //   21	29	121	finally
        //   29	42	121	finally
        //   46	59	121	finally
        //   59	95	121	finally
        //   112	118	121	finally
      }
      
      /* Error */
      public final void zza(zzaz paramzzaz, String paramString1, String paramString2)
        throws RemoteException
      {
        // Byte code:
        //   0: invokestatic 27	android/os/Parcel:obtain	()Landroid/os/Parcel;
        //   3: astore 4
        //   5: invokestatic 27	android/os/Parcel:obtain	()Landroid/os/Parcel;
        //   8: astore 5
        //   10: aload 4
        //   12: ldc 29
        //   14: invokevirtual 33	android/os/Parcel:writeInterfaceToken	(Ljava/lang/String;)V
        //   17: aload_1
        //   18: ifnull +63 -> 81
        //   21: aload_1
        //   22: invokeinterface 37 1 0
        //   27: astore 7
        //   29: aload 4
        //   31: aload 7
        //   33: invokevirtual 40	android/os/Parcel:writeStrongBinder	(Landroid/os/IBinder;)V
        //   36: aload 4
        //   38: aload_2
        //   39: invokevirtual 113	android/os/Parcel:writeString	(Ljava/lang/String;)V
        //   42: aload 4
        //   44: aload_3
        //   45: invokevirtual 113	android/os/Parcel:writeString	(Ljava/lang/String;)V
        //   48: aload_0
        //   49: getfield 15	com/google/android/gms/wearable/internal/zzbb$zza$zza:zzop	Landroid/os/IBinder;
        //   52: bipush 31
        //   54: aload 4
        //   56: aload 5
        //   58: iconst_0
        //   59: invokeinterface 46 5 0
        //   64: pop
        //   65: aload 5
        //   67: invokevirtual 49	android/os/Parcel:readException	()V
        //   70: aload 5
        //   72: invokevirtual 52	android/os/Parcel:recycle	()V
        //   75: aload 4
        //   77: invokevirtual 52	android/os/Parcel:recycle	()V
        //   80: return
        //   81: aconst_null
        //   82: astore 7
        //   84: goto -55 -> 29
        //   87: astore 6
        //   89: aload 5
        //   91: invokevirtual 52	android/os/Parcel:recycle	()V
        //   94: aload 4
        //   96: invokevirtual 52	android/os/Parcel:recycle	()V
        //   99: aload 6
        //   101: athrow
        // Local variable table:
        //   start	length	slot	name	signature
        //   0	102	0	this	zza
        //   0	102	1	paramzzaz	zzaz
        //   0	102	2	paramString1	String
        //   0	102	3	paramString2	String
        //   3	92	4	localParcel1	Parcel
        //   8	82	5	localParcel2	Parcel
        //   87	13	6	localObject	Object
        //   27	56	7	localIBinder	IBinder
        // Exception table:
        //   from	to	target	type
        //   10	17	87	finally
        //   21	29	87	finally
        //   29	70	87	finally
      }
      
      /* Error */
      public final void zza(zzaz paramzzaz, String paramString1, String paramString2, byte[] paramArrayOfByte)
        throws RemoteException
      {
        // Byte code:
        //   0: invokestatic 27	android/os/Parcel:obtain	()Landroid/os/Parcel;
        //   3: astore 5
        //   5: invokestatic 27	android/os/Parcel:obtain	()Landroid/os/Parcel;
        //   8: astore 6
        //   10: aload 5
        //   12: ldc 29
        //   14: invokevirtual 33	android/os/Parcel:writeInterfaceToken	(Ljava/lang/String;)V
        //   17: aload_1
        //   18: ifnull +70 -> 88
        //   21: aload_1
        //   22: invokeinterface 37 1 0
        //   27: astore 8
        //   29: aload 5
        //   31: aload 8
        //   33: invokevirtual 40	android/os/Parcel:writeStrongBinder	(Landroid/os/IBinder;)V
        //   36: aload 5
        //   38: aload_2
        //   39: invokevirtual 113	android/os/Parcel:writeString	(Ljava/lang/String;)V
        //   42: aload 5
        //   44: aload_3
        //   45: invokevirtual 113	android/os/Parcel:writeString	(Ljava/lang/String;)V
        //   48: aload 5
        //   50: aload 4
        //   52: invokevirtual 130	android/os/Parcel:writeByteArray	([B)V
        //   55: aload_0
        //   56: getfield 15	com/google/android/gms/wearable/internal/zzbb$zza$zza:zzop	Landroid/os/IBinder;
        //   59: bipush 12
        //   61: aload 5
        //   63: aload 6
        //   65: iconst_0
        //   66: invokeinterface 46 5 0
        //   71: pop
        //   72: aload 6
        //   74: invokevirtual 49	android/os/Parcel:readException	()V
        //   77: aload 6
        //   79: invokevirtual 52	android/os/Parcel:recycle	()V
        //   82: aload 5
        //   84: invokevirtual 52	android/os/Parcel:recycle	()V
        //   87: return
        //   88: aconst_null
        //   89: astore 8
        //   91: goto -62 -> 29
        //   94: astore 7
        //   96: aload 6
        //   98: invokevirtual 52	android/os/Parcel:recycle	()V
        //   101: aload 5
        //   103: invokevirtual 52	android/os/Parcel:recycle	()V
        //   106: aload 7
        //   108: athrow
        // Local variable table:
        //   start	length	slot	name	signature
        //   0	109	0	this	zza
        //   0	109	1	paramzzaz	zzaz
        //   0	109	2	paramString1	String
        //   0	109	3	paramString2	String
        //   0	109	4	paramArrayOfByte	byte[]
        //   3	99	5	localParcel1	Parcel
        //   8	89	6	localParcel2	Parcel
        //   94	13	7	localObject	Object
        //   27	63	8	localIBinder	IBinder
        // Exception table:
        //   from	to	target	type
        //   10	17	94	finally
        //   21	29	94	finally
        //   29	77	94	finally
      }
      
      /* Error */
      public final void zza(zzaz paramzzaz, boolean paramBoolean)
        throws RemoteException
      {
        // Byte code:
        //   0: invokestatic 27	android/os/Parcel:obtain	()Landroid/os/Parcel;
        //   3: astore_3
        //   4: invokestatic 27	android/os/Parcel:obtain	()Landroid/os/Parcel;
        //   7: astore 4
        //   9: aload_3
        //   10: ldc 29
        //   12: invokevirtual 33	android/os/Parcel:writeInterfaceToken	(Ljava/lang/String;)V
        //   15: aload_1
        //   16: ifnull +64 -> 80
        //   19: aload_1
        //   20: invokeinterface 37 1 0
        //   25: astore 6
        //   27: aload_3
        //   28: aload 6
        //   30: invokevirtual 40	android/os/Parcel:writeStrongBinder	(Landroid/os/IBinder;)V
        //   33: iconst_0
        //   34: istore 7
        //   36: iload_2
        //   37: ifeq +6 -> 43
        //   40: iconst_1
        //   41: istore 7
        //   43: aload_3
        //   44: iload 7
        //   46: invokevirtual 62	android/os/Parcel:writeInt	(I)V
        //   49: aload_0
        //   50: getfield 15	com/google/android/gms/wearable/internal/zzbb$zza$zza:zzop	Landroid/os/IBinder;
        //   53: bipush 48
        //   55: aload_3
        //   56: aload 4
        //   58: iconst_0
        //   59: invokeinterface 46 5 0
        //   64: pop
        //   65: aload 4
        //   67: invokevirtual 49	android/os/Parcel:readException	()V
        //   70: aload 4
        //   72: invokevirtual 52	android/os/Parcel:recycle	()V
        //   75: aload_3
        //   76: invokevirtual 52	android/os/Parcel:recycle	()V
        //   79: return
        //   80: aconst_null
        //   81: astore 6
        //   83: goto -56 -> 27
        //   86: astore 5
        //   88: aload 4
        //   90: invokevirtual 52	android/os/Parcel:recycle	()V
        //   93: aload_3
        //   94: invokevirtual 52	android/os/Parcel:recycle	()V
        //   97: aload 5
        //   99: athrow
        // Local variable table:
        //   start	length	slot	name	signature
        //   0	100	0	this	zza
        //   0	100	1	paramzzaz	zzaz
        //   0	100	2	paramBoolean	boolean
        //   3	91	3	localParcel1	Parcel
        //   7	82	4	localParcel2	Parcel
        //   86	12	5	localObject	Object
        //   25	57	6	localIBinder	IBinder
        //   34	11	7	i	int
        // Exception table:
        //   from	to	target	type
        //   9	15	86	finally
        //   19	27	86	finally
        //   27	33	86	finally
        //   43	70	86	finally
      }
      
      /* Error */
      public final void zzb(zzaz paramzzaz)
        throws RemoteException
      {
        // Byte code:
        //   0: invokestatic 27	android/os/Parcel:obtain	()Landroid/os/Parcel;
        //   3: astore_2
        //   4: invokestatic 27	android/os/Parcel:obtain	()Landroid/os/Parcel;
        //   7: astore_3
        //   8: aload_2
        //   9: ldc 29
        //   11: invokevirtual 33	android/os/Parcel:writeInterfaceToken	(Ljava/lang/String;)V
        //   14: aload_1
        //   15: ifnull +45 -> 60
        //   18: aload_1
        //   19: invokeinterface 37 1 0
        //   24: astore 5
        //   26: aload_2
        //   27: aload 5
        //   29: invokevirtual 40	android/os/Parcel:writeStrongBinder	(Landroid/os/IBinder;)V
        //   32: aload_0
        //   33: getfield 15	com/google/android/gms/wearable/internal/zzbb$zza$zza:zzop	Landroid/os/IBinder;
        //   36: bipush 8
        //   38: aload_2
        //   39: aload_3
        //   40: iconst_0
        //   41: invokeinterface 46 5 0
        //   46: pop
        //   47: aload_3
        //   48: invokevirtual 49	android/os/Parcel:readException	()V
        //   51: aload_3
        //   52: invokevirtual 52	android/os/Parcel:recycle	()V
        //   55: aload_2
        //   56: invokevirtual 52	android/os/Parcel:recycle	()V
        //   59: return
        //   60: aconst_null
        //   61: astore 5
        //   63: goto -37 -> 26
        //   66: astore 4
        //   68: aload_3
        //   69: invokevirtual 52	android/os/Parcel:recycle	()V
        //   72: aload_2
        //   73: invokevirtual 52	android/os/Parcel:recycle	()V
        //   76: aload 4
        //   78: athrow
        // Local variable table:
        //   start	length	slot	name	signature
        //   0	79	0	this	zza
        //   0	79	1	paramzzaz	zzaz
        //   3	70	2	localParcel1	Parcel
        //   7	62	3	localParcel2	Parcel
        //   66	11	4	localObject	Object
        //   24	38	5	localIBinder	IBinder
        // Exception table:
        //   from	to	target	type
        //   8	14	66	finally
        //   18	26	66	finally
        //   26	51	66	finally
      }
      
      /* Error */
      public final void zzb(zzaz paramzzaz, int paramInt)
        throws RemoteException
      {
        // Byte code:
        //   0: invokestatic 27	android/os/Parcel:obtain	()Landroid/os/Parcel;
        //   3: astore_3
        //   4: invokestatic 27	android/os/Parcel:obtain	()Landroid/os/Parcel;
        //   7: astore 4
        //   9: aload_3
        //   10: ldc 29
        //   12: invokevirtual 33	android/os/Parcel:writeInterfaceToken	(Ljava/lang/String;)V
        //   15: aload_1
        //   16: ifnull +53 -> 69
        //   19: aload_1
        //   20: invokeinterface 37 1 0
        //   25: astore 6
        //   27: aload_3
        //   28: aload 6
        //   30: invokevirtual 40	android/os/Parcel:writeStrongBinder	(Landroid/os/IBinder;)V
        //   33: aload_3
        //   34: iload_2
        //   35: invokevirtual 62	android/os/Parcel:writeInt	(I)V
        //   38: aload_0
        //   39: getfield 15	com/google/android/gms/wearable/internal/zzbb$zza$zza:zzop	Landroid/os/IBinder;
        //   42: bipush 28
        //   44: aload_3
        //   45: aload 4
        //   47: iconst_0
        //   48: invokeinterface 46 5 0
        //   53: pop
        //   54: aload 4
        //   56: invokevirtual 49	android/os/Parcel:readException	()V
        //   59: aload 4
        //   61: invokevirtual 52	android/os/Parcel:recycle	()V
        //   64: aload_3
        //   65: invokevirtual 52	android/os/Parcel:recycle	()V
        //   68: return
        //   69: aconst_null
        //   70: astore 6
        //   72: goto -45 -> 27
        //   75: astore 5
        //   77: aload 4
        //   79: invokevirtual 52	android/os/Parcel:recycle	()V
        //   82: aload_3
        //   83: invokevirtual 52	android/os/Parcel:recycle	()V
        //   86: aload 5
        //   88: athrow
        // Local variable table:
        //   start	length	slot	name	signature
        //   0	89	0	this	zza
        //   0	89	1	paramzzaz	zzaz
        //   0	89	2	paramInt	int
        //   3	80	3	localParcel1	Parcel
        //   7	71	4	localParcel2	Parcel
        //   75	12	5	localObject	Object
        //   25	46	6	localIBinder	IBinder
        // Exception table:
        //   from	to	target	type
        //   9	15	75	finally
        //   19	27	75	finally
        //   27	59	75	finally
      }
      
      /* Error */
      public final void zzb(zzaz paramzzaz, Uri paramUri)
        throws RemoteException
      {
        // Byte code:
        //   0: invokestatic 27	android/os/Parcel:obtain	()Landroid/os/Parcel;
        //   3: astore_3
        //   4: invokestatic 27	android/os/Parcel:obtain	()Landroid/os/Parcel;
        //   7: astore 4
        //   9: aload_3
        //   10: ldc 29
        //   12: invokevirtual 33	android/os/Parcel:writeInterfaceToken	(Ljava/lang/String;)V
        //   15: aload_1
        //   16: ifnull +63 -> 79
        //   19: aload_1
        //   20: invokeinterface 37 1 0
        //   25: astore 6
        //   27: aload_3
        //   28: aload 6
        //   30: invokevirtual 40	android/os/Parcel:writeStrongBinder	(Landroid/os/IBinder;)V
        //   33: aload_2
        //   34: ifnull +51 -> 85
        //   37: aload_3
        //   38: iconst_1
        //   39: invokevirtual 62	android/os/Parcel:writeInt	(I)V
        //   42: aload_2
        //   43: aload_3
        //   44: iconst_0
        //   45: invokevirtual 69	android/net/Uri:writeToParcel	(Landroid/os/Parcel;I)V
        //   48: aload_0
        //   49: getfield 15	com/google/android/gms/wearable/internal/zzbb$zza$zza:zzop	Landroid/os/IBinder;
        //   52: bipush 9
        //   54: aload_3
        //   55: aload 4
        //   57: iconst_0
        //   58: invokeinterface 46 5 0
        //   63: pop
        //   64: aload 4
        //   66: invokevirtual 49	android/os/Parcel:readException	()V
        //   69: aload 4
        //   71: invokevirtual 52	android/os/Parcel:recycle	()V
        //   74: aload_3
        //   75: invokevirtual 52	android/os/Parcel:recycle	()V
        //   78: return
        //   79: aconst_null
        //   80: astore 6
        //   82: goto -55 -> 27
        //   85: aload_3
        //   86: iconst_0
        //   87: invokevirtual 62	android/os/Parcel:writeInt	(I)V
        //   90: goto -42 -> 48
        //   93: astore 5
        //   95: aload 4
        //   97: invokevirtual 52	android/os/Parcel:recycle	()V
        //   100: aload_3
        //   101: invokevirtual 52	android/os/Parcel:recycle	()V
        //   104: aload 5
        //   106: athrow
        // Local variable table:
        //   start	length	slot	name	signature
        //   0	107	0	this	zza
        //   0	107	1	paramzzaz	zzaz
        //   0	107	2	paramUri	Uri
        //   3	98	3	localParcel1	Parcel
        //   7	89	4	localParcel2	Parcel
        //   93	12	5	localObject	Object
        //   25	56	6	localIBinder	IBinder
        // Exception table:
        //   from	to	target	type
        //   9	15	93	finally
        //   19	27	93	finally
        //   27	33	93	finally
        //   37	48	93	finally
        //   48	69	93	finally
        //   85	90	93	finally
      }
      
      /* Error */
      public final void zzb(zzaz paramzzaz, Uri paramUri, int paramInt)
        throws RemoteException
      {
        // Byte code:
        //   0: invokestatic 27	android/os/Parcel:obtain	()Landroid/os/Parcel;
        //   3: astore 4
        //   5: invokestatic 27	android/os/Parcel:obtain	()Landroid/os/Parcel;
        //   8: astore 5
        //   10: aload 4
        //   12: ldc 29
        //   14: invokevirtual 33	android/os/Parcel:writeInterfaceToken	(Ljava/lang/String;)V
        //   17: aload_1
        //   18: ifnull +74 -> 92
        //   21: aload_1
        //   22: invokeinterface 37 1 0
        //   27: astore 7
        //   29: aload 4
        //   31: aload 7
        //   33: invokevirtual 40	android/os/Parcel:writeStrongBinder	(Landroid/os/IBinder;)V
        //   36: aload_2
        //   37: ifnull +61 -> 98
        //   40: aload 4
        //   42: iconst_1
        //   43: invokevirtual 62	android/os/Parcel:writeInt	(I)V
        //   46: aload_2
        //   47: aload 4
        //   49: iconst_0
        //   50: invokevirtual 69	android/net/Uri:writeToParcel	(Landroid/os/Parcel;I)V
        //   53: aload 4
        //   55: iload_3
        //   56: invokevirtual 62	android/os/Parcel:writeInt	(I)V
        //   59: aload_0
        //   60: getfield 15	com/google/android/gms/wearable/internal/zzbb$zza$zza:zzop	Landroid/os/IBinder;
        //   63: bipush 41
        //   65: aload 4
        //   67: aload 5
        //   69: iconst_0
        //   70: invokeinterface 46 5 0
        //   75: pop
        //   76: aload 5
        //   78: invokevirtual 49	android/os/Parcel:readException	()V
        //   81: aload 5
        //   83: invokevirtual 52	android/os/Parcel:recycle	()V
        //   86: aload 4
        //   88: invokevirtual 52	android/os/Parcel:recycle	()V
        //   91: return
        //   92: aconst_null
        //   93: astore 7
        //   95: goto -66 -> 29
        //   98: aload 4
        //   100: iconst_0
        //   101: invokevirtual 62	android/os/Parcel:writeInt	(I)V
        //   104: goto -51 -> 53
        //   107: astore 6
        //   109: aload 5
        //   111: invokevirtual 52	android/os/Parcel:recycle	()V
        //   114: aload 4
        //   116: invokevirtual 52	android/os/Parcel:recycle	()V
        //   119: aload 6
        //   121: athrow
        // Local variable table:
        //   start	length	slot	name	signature
        //   0	122	0	this	zza
        //   0	122	1	paramzzaz	zzaz
        //   0	122	2	paramUri	Uri
        //   0	122	3	paramInt	int
        //   3	112	4	localParcel1	Parcel
        //   8	102	5	localParcel2	Parcel
        //   107	13	6	localObject	Object
        //   27	67	7	localIBinder	IBinder
        // Exception table:
        //   from	to	target	type
        //   10	17	107	finally
        //   21	29	107	finally
        //   29	36	107	finally
        //   40	53	107	finally
        //   53	81	107	finally
        //   98	104	107	finally
      }
      
      /* Error */
      public final void zzb(zzaz paramzzaz, ConnectionConfiguration paramConnectionConfiguration)
        throws RemoteException
      {
        // Byte code:
        //   0: invokestatic 27	android/os/Parcel:obtain	()Landroid/os/Parcel;
        //   3: astore_3
        //   4: invokestatic 27	android/os/Parcel:obtain	()Landroid/os/Parcel;
        //   7: astore 4
        //   9: aload_3
        //   10: ldc 29
        //   12: invokevirtual 33	android/os/Parcel:writeInterfaceToken	(Ljava/lang/String;)V
        //   15: aload_1
        //   16: ifnull +62 -> 78
        //   19: aload_1
        //   20: invokeinterface 37 1 0
        //   25: astore 6
        //   27: aload_3
        //   28: aload 6
        //   30: invokevirtual 40	android/os/Parcel:writeStrongBinder	(Landroid/os/IBinder;)V
        //   33: aload_2
        //   34: ifnull +50 -> 84
        //   37: aload_3
        //   38: iconst_1
        //   39: invokevirtual 62	android/os/Parcel:writeInt	(I)V
        //   42: aload_2
        //   43: aload_3
        //   44: iconst_0
        //   45: invokevirtual 78	com/google/android/gms/wearable/ConnectionConfiguration:writeToParcel	(Landroid/os/Parcel;I)V
        //   48: aload_0
        //   49: getfield 15	com/google/android/gms/wearable/internal/zzbb$zza$zza:zzop	Landroid/os/IBinder;
        //   52: iconst_2
        //   53: aload_3
        //   54: aload 4
        //   56: iconst_0
        //   57: invokeinterface 46 5 0
        //   62: pop
        //   63: aload 4
        //   65: invokevirtual 49	android/os/Parcel:readException	()V
        //   68: aload 4
        //   70: invokevirtual 52	android/os/Parcel:recycle	()V
        //   73: aload_3
        //   74: invokevirtual 52	android/os/Parcel:recycle	()V
        //   77: return
        //   78: aconst_null
        //   79: astore 6
        //   81: goto -54 -> 27
        //   84: aload_3
        //   85: iconst_0
        //   86: invokevirtual 62	android/os/Parcel:writeInt	(I)V
        //   89: goto -41 -> 48
        //   92: astore 5
        //   94: aload 4
        //   96: invokevirtual 52	android/os/Parcel:recycle	()V
        //   99: aload_3
        //   100: invokevirtual 52	android/os/Parcel:recycle	()V
        //   103: aload 5
        //   105: athrow
        // Local variable table:
        //   start	length	slot	name	signature
        //   0	106	0	this	zza
        //   0	106	1	paramzzaz	zzaz
        //   0	106	2	paramConnectionConfiguration	ConnectionConfiguration
        //   3	97	3	localParcel1	Parcel
        //   7	88	4	localParcel2	Parcel
        //   92	12	5	localObject	Object
        //   25	55	6	localIBinder	IBinder
        // Exception table:
        //   from	to	target	type
        //   9	15	92	finally
        //   19	27	92	finally
        //   27	33	92	finally
        //   37	48	92	finally
        //   48	68	92	finally
        //   84	89	92	finally
      }
      
      /* Error */
      public final void zzb(zzaz paramzzaz, zzaw paramzzaw, String paramString)
        throws RemoteException
      {
        // Byte code:
        //   0: invokestatic 27	android/os/Parcel:obtain	()Landroid/os/Parcel;
        //   3: astore 4
        //   5: invokestatic 27	android/os/Parcel:obtain	()Landroid/os/Parcel;
        //   8: astore 5
        //   10: aload 4
        //   12: ldc 29
        //   14: invokevirtual 33	android/os/Parcel:writeInterfaceToken	(Ljava/lang/String;)V
        //   17: aload_1
        //   18: ifnull +79 -> 97
        //   21: aload_1
        //   22: invokeinterface 37 1 0
        //   27: astore 7
        //   29: aload 4
        //   31: aload 7
        //   33: invokevirtual 40	android/os/Parcel:writeStrongBinder	(Landroid/os/IBinder;)V
        //   36: aconst_null
        //   37: astore 8
        //   39: aload_2
        //   40: ifnull +11 -> 51
        //   43: aload_2
        //   44: invokeinterface 110 1 0
        //   49: astore 8
        //   51: aload 4
        //   53: aload 8
        //   55: invokevirtual 40	android/os/Parcel:writeStrongBinder	(Landroid/os/IBinder;)V
        //   58: aload 4
        //   60: aload_3
        //   61: invokevirtual 113	android/os/Parcel:writeString	(Ljava/lang/String;)V
        //   64: aload_0
        //   65: getfield 15	com/google/android/gms/wearable/internal/zzbb$zza$zza:zzop	Landroid/os/IBinder;
        //   68: bipush 35
        //   70: aload 4
        //   72: aload 5
        //   74: iconst_0
        //   75: invokeinterface 46 5 0
        //   80: pop
        //   81: aload 5
        //   83: invokevirtual 49	android/os/Parcel:readException	()V
        //   86: aload 5
        //   88: invokevirtual 52	android/os/Parcel:recycle	()V
        //   91: aload 4
        //   93: invokevirtual 52	android/os/Parcel:recycle	()V
        //   96: return
        //   97: aconst_null
        //   98: astore 7
        //   100: goto -71 -> 29
        //   103: astore 6
        //   105: aload 5
        //   107: invokevirtual 52	android/os/Parcel:recycle	()V
        //   110: aload 4
        //   112: invokevirtual 52	android/os/Parcel:recycle	()V
        //   115: aload 6
        //   117: athrow
        // Local variable table:
        //   start	length	slot	name	signature
        //   0	118	0	this	zza
        //   0	118	1	paramzzaz	zzaz
        //   0	118	2	paramzzaw	zzaw
        //   0	118	3	paramString	String
        //   3	108	4	localParcel1	Parcel
        //   8	98	5	localParcel2	Parcel
        //   103	13	6	localObject	Object
        //   27	72	7	localIBinder1	IBinder
        //   37	17	8	localIBinder2	IBinder
        // Exception table:
        //   from	to	target	type
        //   10	17	103	finally
        //   21	29	103	finally
        //   29	36	103	finally
        //   43	51	103	finally
        //   51	86	103	finally
      }
      
      /* Error */
      public final void zzb(zzaz paramzzaz, String paramString)
        throws RemoteException
      {
        // Byte code:
        //   0: invokestatic 27	android/os/Parcel:obtain	()Landroid/os/Parcel;
        //   3: astore_3
        //   4: invokestatic 27	android/os/Parcel:obtain	()Landroid/os/Parcel;
        //   7: astore 4
        //   9: aload_3
        //   10: ldc 29
        //   12: invokevirtual 33	android/os/Parcel:writeInterfaceToken	(Ljava/lang/String;)V
        //   15: aload_1
        //   16: ifnull +53 -> 69
        //   19: aload_1
        //   20: invokeinterface 37 1 0
        //   25: astore 6
        //   27: aload_3
        //   28: aload 6
        //   30: invokevirtual 40	android/os/Parcel:writeStrongBinder	(Landroid/os/IBinder;)V
        //   33: aload_3
        //   34: aload_2
        //   35: invokevirtual 113	android/os/Parcel:writeString	(Ljava/lang/String;)V
        //   38: aload_0
        //   39: getfield 15	com/google/android/gms/wearable/internal/zzbb$zza$zza:zzop	Landroid/os/IBinder;
        //   42: bipush 23
        //   44: aload_3
        //   45: aload 4
        //   47: iconst_0
        //   48: invokeinterface 46 5 0
        //   53: pop
        //   54: aload 4
        //   56: invokevirtual 49	android/os/Parcel:readException	()V
        //   59: aload 4
        //   61: invokevirtual 52	android/os/Parcel:recycle	()V
        //   64: aload_3
        //   65: invokevirtual 52	android/os/Parcel:recycle	()V
        //   68: return
        //   69: aconst_null
        //   70: astore 6
        //   72: goto -45 -> 27
        //   75: astore 5
        //   77: aload 4
        //   79: invokevirtual 52	android/os/Parcel:recycle	()V
        //   82: aload_3
        //   83: invokevirtual 52	android/os/Parcel:recycle	()V
        //   86: aload 5
        //   88: athrow
        // Local variable table:
        //   start	length	slot	name	signature
        //   0	89	0	this	zza
        //   0	89	1	paramzzaz	zzaz
        //   0	89	2	paramString	String
        //   3	80	3	localParcel1	Parcel
        //   7	71	4	localParcel2	Parcel
        //   75	12	5	localObject	Object
        //   25	46	6	localIBinder	IBinder
        // Exception table:
        //   from	to	target	type
        //   9	15	75	finally
        //   19	27	75	finally
        //   27	59	75	finally
      }
      
      /* Error */
      public final void zzb(zzaz paramzzaz, String paramString, int paramInt)
        throws RemoteException
      {
        // Byte code:
        //   0: invokestatic 27	android/os/Parcel:obtain	()Landroid/os/Parcel;
        //   3: astore 4
        //   5: invokestatic 27	android/os/Parcel:obtain	()Landroid/os/Parcel;
        //   8: astore 5
        //   10: aload 4
        //   12: ldc 29
        //   14: invokevirtual 33	android/os/Parcel:writeInterfaceToken	(Ljava/lang/String;)V
        //   17: aload_1
        //   18: ifnull +63 -> 81
        //   21: aload_1
        //   22: invokeinterface 37 1 0
        //   27: astore 7
        //   29: aload 4
        //   31: aload 7
        //   33: invokevirtual 40	android/os/Parcel:writeStrongBinder	(Landroid/os/IBinder;)V
        //   36: aload 4
        //   38: aload_2
        //   39: invokevirtual 113	android/os/Parcel:writeString	(Ljava/lang/String;)V
        //   42: aload 4
        //   44: iload_3
        //   45: invokevirtual 62	android/os/Parcel:writeInt	(I)V
        //   48: aload_0
        //   49: getfield 15	com/google/android/gms/wearable/internal/zzbb$zza$zza:zzop	Landroid/os/IBinder;
        //   52: bipush 33
        //   54: aload 4
        //   56: aload 5
        //   58: iconst_0
        //   59: invokeinterface 46 5 0
        //   64: pop
        //   65: aload 5
        //   67: invokevirtual 49	android/os/Parcel:readException	()V
        //   70: aload 5
        //   72: invokevirtual 52	android/os/Parcel:recycle	()V
        //   75: aload 4
        //   77: invokevirtual 52	android/os/Parcel:recycle	()V
        //   80: return
        //   81: aconst_null
        //   82: astore 7
        //   84: goto -55 -> 29
        //   87: astore 6
        //   89: aload 5
        //   91: invokevirtual 52	android/os/Parcel:recycle	()V
        //   94: aload 4
        //   96: invokevirtual 52	android/os/Parcel:recycle	()V
        //   99: aload 6
        //   101: athrow
        // Local variable table:
        //   start	length	slot	name	signature
        //   0	102	0	this	zza
        //   0	102	1	paramzzaz	zzaz
        //   0	102	2	paramString	String
        //   0	102	3	paramInt	int
        //   3	92	4	localParcel1	Parcel
        //   8	82	5	localParcel2	Parcel
        //   87	13	6	localObject	Object
        //   27	56	7	localIBinder	IBinder
        // Exception table:
        //   from	to	target	type
        //   10	17	87	finally
        //   21	29	87	finally
        //   29	70	87	finally
      }
      
      /* Error */
      public final void zzb(zzaz paramzzaz, boolean paramBoolean)
        throws RemoteException
      {
        // Byte code:
        //   0: invokestatic 27	android/os/Parcel:obtain	()Landroid/os/Parcel;
        //   3: astore_3
        //   4: invokestatic 27	android/os/Parcel:obtain	()Landroid/os/Parcel;
        //   7: astore 4
        //   9: aload_3
        //   10: ldc 29
        //   12: invokevirtual 33	android/os/Parcel:writeInterfaceToken	(Ljava/lang/String;)V
        //   15: aload_1
        //   16: ifnull +64 -> 80
        //   19: aload_1
        //   20: invokeinterface 37 1 0
        //   25: astore 6
        //   27: aload_3
        //   28: aload 6
        //   30: invokevirtual 40	android/os/Parcel:writeStrongBinder	(Landroid/os/IBinder;)V
        //   33: iconst_0
        //   34: istore 7
        //   36: iload_2
        //   37: ifeq +6 -> 43
        //   40: iconst_1
        //   41: istore 7
        //   43: aload_3
        //   44: iload 7
        //   46: invokevirtual 62	android/os/Parcel:writeInt	(I)V
        //   49: aload_0
        //   50: getfield 15	com/google/android/gms/wearable/internal/zzbb$zza$zza:zzop	Landroid/os/IBinder;
        //   53: bipush 50
        //   55: aload_3
        //   56: aload 4
        //   58: iconst_0
        //   59: invokeinterface 46 5 0
        //   64: pop
        //   65: aload 4
        //   67: invokevirtual 49	android/os/Parcel:readException	()V
        //   70: aload 4
        //   72: invokevirtual 52	android/os/Parcel:recycle	()V
        //   75: aload_3
        //   76: invokevirtual 52	android/os/Parcel:recycle	()V
        //   79: return
        //   80: aconst_null
        //   81: astore 6
        //   83: goto -56 -> 27
        //   86: astore 5
        //   88: aload 4
        //   90: invokevirtual 52	android/os/Parcel:recycle	()V
        //   93: aload_3
        //   94: invokevirtual 52	android/os/Parcel:recycle	()V
        //   97: aload 5
        //   99: athrow
        // Local variable table:
        //   start	length	slot	name	signature
        //   0	100	0	this	zza
        //   0	100	1	paramzzaz	zzaz
        //   0	100	2	paramBoolean	boolean
        //   3	91	3	localParcel1	Parcel
        //   7	82	4	localParcel2	Parcel
        //   86	12	5	localObject	Object
        //   25	57	6	localIBinder	IBinder
        //   34	11	7	i	int
        // Exception table:
        //   from	to	target	type
        //   9	15	86	finally
        //   19	27	86	finally
        //   27	33	86	finally
        //   43	70	86	finally
      }
      
      /* Error */
      public final void zzc(zzaz paramzzaz)
        throws RemoteException
      {
        // Byte code:
        //   0: invokestatic 27	android/os/Parcel:obtain	()Landroid/os/Parcel;
        //   3: astore_2
        //   4: invokestatic 27	android/os/Parcel:obtain	()Landroid/os/Parcel;
        //   7: astore_3
        //   8: aload_2
        //   9: ldc 29
        //   11: invokevirtual 33	android/os/Parcel:writeInterfaceToken	(Ljava/lang/String;)V
        //   14: aload_1
        //   15: ifnull +45 -> 60
        //   18: aload_1
        //   19: invokeinterface 37 1 0
        //   24: astore 5
        //   26: aload_2
        //   27: aload 5
        //   29: invokevirtual 40	android/os/Parcel:writeStrongBinder	(Landroid/os/IBinder;)V
        //   32: aload_0
        //   33: getfield 15	com/google/android/gms/wearable/internal/zzbb$zza$zza:zzop	Landroid/os/IBinder;
        //   36: bipush 14
        //   38: aload_2
        //   39: aload_3
        //   40: iconst_0
        //   41: invokeinterface 46 5 0
        //   46: pop
        //   47: aload_3
        //   48: invokevirtual 49	android/os/Parcel:readException	()V
        //   51: aload_3
        //   52: invokevirtual 52	android/os/Parcel:recycle	()V
        //   55: aload_2
        //   56: invokevirtual 52	android/os/Parcel:recycle	()V
        //   59: return
        //   60: aconst_null
        //   61: astore 5
        //   63: goto -37 -> 26
        //   66: astore 4
        //   68: aload_3
        //   69: invokevirtual 52	android/os/Parcel:recycle	()V
        //   72: aload_2
        //   73: invokevirtual 52	android/os/Parcel:recycle	()V
        //   76: aload 4
        //   78: athrow
        // Local variable table:
        //   start	length	slot	name	signature
        //   0	79	0	this	zza
        //   0	79	1	paramzzaz	zzaz
        //   3	70	2	localParcel1	Parcel
        //   7	62	3	localParcel2	Parcel
        //   66	11	4	localObject	Object
        //   24	38	5	localIBinder	IBinder
        // Exception table:
        //   from	to	target	type
        //   8	14	66	finally
        //   18	26	66	finally
        //   26	51	66	finally
      }
      
      /* Error */
      public final void zzc(zzaz paramzzaz, int paramInt)
        throws RemoteException
      {
        // Byte code:
        //   0: invokestatic 27	android/os/Parcel:obtain	()Landroid/os/Parcel;
        //   3: astore_3
        //   4: invokestatic 27	android/os/Parcel:obtain	()Landroid/os/Parcel;
        //   7: astore 4
        //   9: aload_3
        //   10: ldc 29
        //   12: invokevirtual 33	android/os/Parcel:writeInterfaceToken	(Ljava/lang/String;)V
        //   15: aload_1
        //   16: ifnull +53 -> 69
        //   19: aload_1
        //   20: invokeinterface 37 1 0
        //   25: astore 6
        //   27: aload_3
        //   28: aload 6
        //   30: invokevirtual 40	android/os/Parcel:writeStrongBinder	(Landroid/os/IBinder;)V
        //   33: aload_3
        //   34: iload_2
        //   35: invokevirtual 62	android/os/Parcel:writeInt	(I)V
        //   38: aload_0
        //   39: getfield 15	com/google/android/gms/wearable/internal/zzbb$zza$zza:zzop	Landroid/os/IBinder;
        //   42: bipush 29
        //   44: aload_3
        //   45: aload 4
        //   47: iconst_0
        //   48: invokeinterface 46 5 0
        //   53: pop
        //   54: aload 4
        //   56: invokevirtual 49	android/os/Parcel:readException	()V
        //   59: aload 4
        //   61: invokevirtual 52	android/os/Parcel:recycle	()V
        //   64: aload_3
        //   65: invokevirtual 52	android/os/Parcel:recycle	()V
        //   68: return
        //   69: aconst_null
        //   70: astore 6
        //   72: goto -45 -> 27
        //   75: astore 5
        //   77: aload 4
        //   79: invokevirtual 52	android/os/Parcel:recycle	()V
        //   82: aload_3
        //   83: invokevirtual 52	android/os/Parcel:recycle	()V
        //   86: aload 5
        //   88: athrow
        // Local variable table:
        //   start	length	slot	name	signature
        //   0	89	0	this	zza
        //   0	89	1	paramzzaz	zzaz
        //   0	89	2	paramInt	int
        //   3	80	3	localParcel1	Parcel
        //   7	71	4	localParcel2	Parcel
        //   75	12	5	localObject	Object
        //   25	46	6	localIBinder	IBinder
        // Exception table:
        //   from	to	target	type
        //   9	15	75	finally
        //   19	27	75	finally
        //   27	59	75	finally
      }
      
      /* Error */
      public final void zzc(zzaz paramzzaz, Uri paramUri)
        throws RemoteException
      {
        // Byte code:
        //   0: invokestatic 27	android/os/Parcel:obtain	()Landroid/os/Parcel;
        //   3: astore_3
        //   4: invokestatic 27	android/os/Parcel:obtain	()Landroid/os/Parcel;
        //   7: astore 4
        //   9: aload_3
        //   10: ldc 29
        //   12: invokevirtual 33	android/os/Parcel:writeInterfaceToken	(Ljava/lang/String;)V
        //   15: aload_1
        //   16: ifnull +63 -> 79
        //   19: aload_1
        //   20: invokeinterface 37 1 0
        //   25: astore 6
        //   27: aload_3
        //   28: aload 6
        //   30: invokevirtual 40	android/os/Parcel:writeStrongBinder	(Landroid/os/IBinder;)V
        //   33: aload_2
        //   34: ifnull +51 -> 85
        //   37: aload_3
        //   38: iconst_1
        //   39: invokevirtual 62	android/os/Parcel:writeInt	(I)V
        //   42: aload_2
        //   43: aload_3
        //   44: iconst_0
        //   45: invokevirtual 69	android/net/Uri:writeToParcel	(Landroid/os/Parcel;I)V
        //   48: aload_0
        //   49: getfield 15	com/google/android/gms/wearable/internal/zzbb$zza$zza:zzop	Landroid/os/IBinder;
        //   52: bipush 11
        //   54: aload_3
        //   55: aload 4
        //   57: iconst_0
        //   58: invokeinterface 46 5 0
        //   63: pop
        //   64: aload 4
        //   66: invokevirtual 49	android/os/Parcel:readException	()V
        //   69: aload 4
        //   71: invokevirtual 52	android/os/Parcel:recycle	()V
        //   74: aload_3
        //   75: invokevirtual 52	android/os/Parcel:recycle	()V
        //   78: return
        //   79: aconst_null
        //   80: astore 6
        //   82: goto -55 -> 27
        //   85: aload_3
        //   86: iconst_0
        //   87: invokevirtual 62	android/os/Parcel:writeInt	(I)V
        //   90: goto -42 -> 48
        //   93: astore 5
        //   95: aload 4
        //   97: invokevirtual 52	android/os/Parcel:recycle	()V
        //   100: aload_3
        //   101: invokevirtual 52	android/os/Parcel:recycle	()V
        //   104: aload 5
        //   106: athrow
        // Local variable table:
        //   start	length	slot	name	signature
        //   0	107	0	this	zza
        //   0	107	1	paramzzaz	zzaz
        //   0	107	2	paramUri	Uri
        //   3	98	3	localParcel1	Parcel
        //   7	89	4	localParcel2	Parcel
        //   93	12	5	localObject	Object
        //   25	56	6	localIBinder	IBinder
        // Exception table:
        //   from	to	target	type
        //   9	15	93	finally
        //   19	27	93	finally
        //   27	33	93	finally
        //   37	48	93	finally
        //   48	69	93	finally
        //   85	90	93	finally
      }
      
      /* Error */
      public final void zzc(zzaz paramzzaz, String paramString)
        throws RemoteException
      {
        // Byte code:
        //   0: invokestatic 27	android/os/Parcel:obtain	()Landroid/os/Parcel;
        //   3: astore_3
        //   4: invokestatic 27	android/os/Parcel:obtain	()Landroid/os/Parcel;
        //   7: astore 4
        //   9: aload_3
        //   10: ldc 29
        //   12: invokevirtual 33	android/os/Parcel:writeInterfaceToken	(Ljava/lang/String;)V
        //   15: aload_1
        //   16: ifnull +53 -> 69
        //   19: aload_1
        //   20: invokeinterface 37 1 0
        //   25: astore 6
        //   27: aload_3
        //   28: aload 6
        //   30: invokevirtual 40	android/os/Parcel:writeStrongBinder	(Landroid/os/IBinder;)V
        //   33: aload_3
        //   34: aload_2
        //   35: invokevirtual 113	android/os/Parcel:writeString	(Ljava/lang/String;)V
        //   38: aload_0
        //   39: getfield 15	com/google/android/gms/wearable/internal/zzbb$zza$zza:zzop	Landroid/os/IBinder;
        //   42: bipush 24
        //   44: aload_3
        //   45: aload 4
        //   47: iconst_0
        //   48: invokeinterface 46 5 0
        //   53: pop
        //   54: aload 4
        //   56: invokevirtual 49	android/os/Parcel:readException	()V
        //   59: aload 4
        //   61: invokevirtual 52	android/os/Parcel:recycle	()V
        //   64: aload_3
        //   65: invokevirtual 52	android/os/Parcel:recycle	()V
        //   68: return
        //   69: aconst_null
        //   70: astore 6
        //   72: goto -45 -> 27
        //   75: astore 5
        //   77: aload 4
        //   79: invokevirtual 52	android/os/Parcel:recycle	()V
        //   82: aload_3
        //   83: invokevirtual 52	android/os/Parcel:recycle	()V
        //   86: aload 5
        //   88: athrow
        // Local variable table:
        //   start	length	slot	name	signature
        //   0	89	0	this	zza
        //   0	89	1	paramzzaz	zzaz
        //   0	89	2	paramString	String
        //   3	80	3	localParcel1	Parcel
        //   7	71	4	localParcel2	Parcel
        //   75	12	5	localObject	Object
        //   25	46	6	localIBinder	IBinder
        // Exception table:
        //   from	to	target	type
        //   9	15	75	finally
        //   19	27	75	finally
        //   27	59	75	finally
      }
      
      /* Error */
      public final void zzd(zzaz paramzzaz)
        throws RemoteException
      {
        // Byte code:
        //   0: invokestatic 27	android/os/Parcel:obtain	()Landroid/os/Parcel;
        //   3: astore_2
        //   4: invokestatic 27	android/os/Parcel:obtain	()Landroid/os/Parcel;
        //   7: astore_3
        //   8: aload_2
        //   9: ldc 29
        //   11: invokevirtual 33	android/os/Parcel:writeInterfaceToken	(Ljava/lang/String;)V
        //   14: aload_1
        //   15: ifnull +45 -> 60
        //   18: aload_1
        //   19: invokeinterface 37 1 0
        //   24: astore 5
        //   26: aload_2
        //   27: aload 5
        //   29: invokevirtual 40	android/os/Parcel:writeStrongBinder	(Landroid/os/IBinder;)V
        //   32: aload_0
        //   33: getfield 15	com/google/android/gms/wearable/internal/zzbb$zza$zza:zzop	Landroid/os/IBinder;
        //   36: bipush 15
        //   38: aload_2
        //   39: aload_3
        //   40: iconst_0
        //   41: invokeinterface 46 5 0
        //   46: pop
        //   47: aload_3
        //   48: invokevirtual 49	android/os/Parcel:readException	()V
        //   51: aload_3
        //   52: invokevirtual 52	android/os/Parcel:recycle	()V
        //   55: aload_2
        //   56: invokevirtual 52	android/os/Parcel:recycle	()V
        //   59: return
        //   60: aconst_null
        //   61: astore 5
        //   63: goto -37 -> 26
        //   66: astore 4
        //   68: aload_3
        //   69: invokevirtual 52	android/os/Parcel:recycle	()V
        //   72: aload_2
        //   73: invokevirtual 52	android/os/Parcel:recycle	()V
        //   76: aload 4
        //   78: athrow
        // Local variable table:
        //   start	length	slot	name	signature
        //   0	79	0	this	zza
        //   0	79	1	paramzzaz	zzaz
        //   3	70	2	localParcel1	Parcel
        //   7	62	3	localParcel2	Parcel
        //   66	11	4	localObject	Object
        //   24	38	5	localIBinder	IBinder
        // Exception table:
        //   from	to	target	type
        //   8	14	66	finally
        //   18	26	66	finally
        //   26	51	66	finally
      }
      
      /* Error */
      public final void zzd(zzaz paramzzaz, String paramString)
        throws RemoteException
      {
        // Byte code:
        //   0: invokestatic 27	android/os/Parcel:obtain	()Landroid/os/Parcel;
        //   3: astore_3
        //   4: invokestatic 27	android/os/Parcel:obtain	()Landroid/os/Parcel;
        //   7: astore 4
        //   9: aload_3
        //   10: ldc 29
        //   12: invokevirtual 33	android/os/Parcel:writeInterfaceToken	(Ljava/lang/String;)V
        //   15: aload_1
        //   16: ifnull +53 -> 69
        //   19: aload_1
        //   20: invokeinterface 37 1 0
        //   25: astore 6
        //   27: aload_3
        //   28: aload 6
        //   30: invokevirtual 40	android/os/Parcel:writeStrongBinder	(Landroid/os/IBinder;)V
        //   33: aload_3
        //   34: aload_2
        //   35: invokevirtual 113	android/os/Parcel:writeString	(Ljava/lang/String;)V
        //   38: aload_0
        //   39: getfield 15	com/google/android/gms/wearable/internal/zzbb$zza$zza:zzop	Landroid/os/IBinder;
        //   42: bipush 46
        //   44: aload_3
        //   45: aload 4
        //   47: iconst_0
        //   48: invokeinterface 46 5 0
        //   53: pop
        //   54: aload 4
        //   56: invokevirtual 49	android/os/Parcel:readException	()V
        //   59: aload 4
        //   61: invokevirtual 52	android/os/Parcel:recycle	()V
        //   64: aload_3
        //   65: invokevirtual 52	android/os/Parcel:recycle	()V
        //   68: return
        //   69: aconst_null
        //   70: astore 6
        //   72: goto -45 -> 27
        //   75: astore 5
        //   77: aload 4
        //   79: invokevirtual 52	android/os/Parcel:recycle	()V
        //   82: aload_3
        //   83: invokevirtual 52	android/os/Parcel:recycle	()V
        //   86: aload 5
        //   88: athrow
        // Local variable table:
        //   start	length	slot	name	signature
        //   0	89	0	this	zza
        //   0	89	1	paramzzaz	zzaz
        //   0	89	2	paramString	String
        //   3	80	3	localParcel1	Parcel
        //   7	71	4	localParcel2	Parcel
        //   75	12	5	localObject	Object
        //   25	46	6	localIBinder	IBinder
        // Exception table:
        //   from	to	target	type
        //   9	15	75	finally
        //   19	27	75	finally
        //   27	59	75	finally
      }
      
      /* Error */
      public final void zze(zzaz paramzzaz)
        throws RemoteException
      {
        // Byte code:
        //   0: invokestatic 27	android/os/Parcel:obtain	()Landroid/os/Parcel;
        //   3: astore_2
        //   4: invokestatic 27	android/os/Parcel:obtain	()Landroid/os/Parcel;
        //   7: astore_3
        //   8: aload_2
        //   9: ldc 29
        //   11: invokevirtual 33	android/os/Parcel:writeInterfaceToken	(Ljava/lang/String;)V
        //   14: aload_1
        //   15: ifnull +45 -> 60
        //   18: aload_1
        //   19: invokeinterface 37 1 0
        //   24: astore 5
        //   26: aload_2
        //   27: aload 5
        //   29: invokevirtual 40	android/os/Parcel:writeStrongBinder	(Landroid/os/IBinder;)V
        //   32: aload_0
        //   33: getfield 15	com/google/android/gms/wearable/internal/zzbb$zza$zza:zzop	Landroid/os/IBinder;
        //   36: bipush 18
        //   38: aload_2
        //   39: aload_3
        //   40: iconst_0
        //   41: invokeinterface 46 5 0
        //   46: pop
        //   47: aload_3
        //   48: invokevirtual 49	android/os/Parcel:readException	()V
        //   51: aload_3
        //   52: invokevirtual 52	android/os/Parcel:recycle	()V
        //   55: aload_2
        //   56: invokevirtual 52	android/os/Parcel:recycle	()V
        //   59: return
        //   60: aconst_null
        //   61: astore 5
        //   63: goto -37 -> 26
        //   66: astore 4
        //   68: aload_3
        //   69: invokevirtual 52	android/os/Parcel:recycle	()V
        //   72: aload_2
        //   73: invokevirtual 52	android/os/Parcel:recycle	()V
        //   76: aload 4
        //   78: athrow
        // Local variable table:
        //   start	length	slot	name	signature
        //   0	79	0	this	zza
        //   0	79	1	paramzzaz	zzaz
        //   3	70	2	localParcel1	Parcel
        //   7	62	3	localParcel2	Parcel
        //   66	11	4	localObject	Object
        //   24	38	5	localIBinder	IBinder
        // Exception table:
        //   from	to	target	type
        //   8	14	66	finally
        //   18	26	66	finally
        //   26	51	66	finally
      }
      
      /* Error */
      public final void zze(zzaz paramzzaz, String paramString)
        throws RemoteException
      {
        // Byte code:
        //   0: invokestatic 27	android/os/Parcel:obtain	()Landroid/os/Parcel;
        //   3: astore_3
        //   4: invokestatic 27	android/os/Parcel:obtain	()Landroid/os/Parcel;
        //   7: astore 4
        //   9: aload_3
        //   10: ldc 29
        //   12: invokevirtual 33	android/os/Parcel:writeInterfaceToken	(Ljava/lang/String;)V
        //   15: aload_1
        //   16: ifnull +53 -> 69
        //   19: aload_1
        //   20: invokeinterface 37 1 0
        //   25: astore 6
        //   27: aload_3
        //   28: aload 6
        //   30: invokevirtual 40	android/os/Parcel:writeStrongBinder	(Landroid/os/IBinder;)V
        //   33: aload_3
        //   34: aload_2
        //   35: invokevirtual 113	android/os/Parcel:writeString	(Ljava/lang/String;)V
        //   38: aload_0
        //   39: getfield 15	com/google/android/gms/wearable/internal/zzbb$zza$zza:zzop	Landroid/os/IBinder;
        //   42: bipush 47
        //   44: aload_3
        //   45: aload 4
        //   47: iconst_0
        //   48: invokeinterface 46 5 0
        //   53: pop
        //   54: aload 4
        //   56: invokevirtual 49	android/os/Parcel:readException	()V
        //   59: aload 4
        //   61: invokevirtual 52	android/os/Parcel:recycle	()V
        //   64: aload_3
        //   65: invokevirtual 52	android/os/Parcel:recycle	()V
        //   68: return
        //   69: aconst_null
        //   70: astore 6
        //   72: goto -45 -> 27
        //   75: astore 5
        //   77: aload 4
        //   79: invokevirtual 52	android/os/Parcel:recycle	()V
        //   82: aload_3
        //   83: invokevirtual 52	android/os/Parcel:recycle	()V
        //   86: aload 5
        //   88: athrow
        // Local variable table:
        //   start	length	slot	name	signature
        //   0	89	0	this	zza
        //   0	89	1	paramzzaz	zzaz
        //   0	89	2	paramString	String
        //   3	80	3	localParcel1	Parcel
        //   7	71	4	localParcel2	Parcel
        //   75	12	5	localObject	Object
        //   25	46	6	localIBinder	IBinder
        // Exception table:
        //   from	to	target	type
        //   9	15	75	finally
        //   19	27	75	finally
        //   27	59	75	finally
      }
      
      /* Error */
      public final void zzf(zzaz paramzzaz)
        throws RemoteException
      {
        // Byte code:
        //   0: invokestatic 27	android/os/Parcel:obtain	()Landroid/os/Parcel;
        //   3: astore_2
        //   4: invokestatic 27	android/os/Parcel:obtain	()Landroid/os/Parcel;
        //   7: astore_3
        //   8: aload_2
        //   9: ldc 29
        //   11: invokevirtual 33	android/os/Parcel:writeInterfaceToken	(Ljava/lang/String;)V
        //   14: aload_1
        //   15: ifnull +45 -> 60
        //   18: aload_1
        //   19: invokeinterface 37 1 0
        //   24: astore 5
        //   26: aload_2
        //   27: aload 5
        //   29: invokevirtual 40	android/os/Parcel:writeStrongBinder	(Landroid/os/IBinder;)V
        //   32: aload_0
        //   33: getfield 15	com/google/android/gms/wearable/internal/zzbb$zza$zza:zzop	Landroid/os/IBinder;
        //   36: bipush 19
        //   38: aload_2
        //   39: aload_3
        //   40: iconst_0
        //   41: invokeinterface 46 5 0
        //   46: pop
        //   47: aload_3
        //   48: invokevirtual 49	android/os/Parcel:readException	()V
        //   51: aload_3
        //   52: invokevirtual 52	android/os/Parcel:recycle	()V
        //   55: aload_2
        //   56: invokevirtual 52	android/os/Parcel:recycle	()V
        //   59: return
        //   60: aconst_null
        //   61: astore 5
        //   63: goto -37 -> 26
        //   66: astore 4
        //   68: aload_3
        //   69: invokevirtual 52	android/os/Parcel:recycle	()V
        //   72: aload_2
        //   73: invokevirtual 52	android/os/Parcel:recycle	()V
        //   76: aload 4
        //   78: athrow
        // Local variable table:
        //   start	length	slot	name	signature
        //   0	79	0	this	zza
        //   0	79	1	paramzzaz	zzaz
        //   3	70	2	localParcel1	Parcel
        //   7	62	3	localParcel2	Parcel
        //   66	11	4	localObject	Object
        //   24	38	5	localIBinder	IBinder
        // Exception table:
        //   from	to	target	type
        //   8	14	66	finally
        //   18	26	66	finally
        //   26	51	66	finally
      }
      
      /* Error */
      public final void zzf(zzaz paramzzaz, String paramString)
        throws RemoteException
      {
        // Byte code:
        //   0: invokestatic 27	android/os/Parcel:obtain	()Landroid/os/Parcel;
        //   3: astore_3
        //   4: invokestatic 27	android/os/Parcel:obtain	()Landroid/os/Parcel;
        //   7: astore 4
        //   9: aload_3
        //   10: ldc 29
        //   12: invokevirtual 33	android/os/Parcel:writeInterfaceToken	(Ljava/lang/String;)V
        //   15: aload_1
        //   16: ifnull +53 -> 69
        //   19: aload_1
        //   20: invokeinterface 37 1 0
        //   25: astore 6
        //   27: aload_3
        //   28: aload 6
        //   30: invokevirtual 40	android/os/Parcel:writeStrongBinder	(Landroid/os/IBinder;)V
        //   33: aload_3
        //   34: aload_2
        //   35: invokevirtual 113	android/os/Parcel:writeString	(Ljava/lang/String;)V
        //   38: aload_0
        //   39: getfield 15	com/google/android/gms/wearable/internal/zzbb$zza$zza:zzop	Landroid/os/IBinder;
        //   42: bipush 32
        //   44: aload_3
        //   45: aload 4
        //   47: iconst_0
        //   48: invokeinterface 46 5 0
        //   53: pop
        //   54: aload 4
        //   56: invokevirtual 49	android/os/Parcel:readException	()V
        //   59: aload 4
        //   61: invokevirtual 52	android/os/Parcel:recycle	()V
        //   64: aload_3
        //   65: invokevirtual 52	android/os/Parcel:recycle	()V
        //   68: return
        //   69: aconst_null
        //   70: astore 6
        //   72: goto -45 -> 27
        //   75: astore 5
        //   77: aload 4
        //   79: invokevirtual 52	android/os/Parcel:recycle	()V
        //   82: aload_3
        //   83: invokevirtual 52	android/os/Parcel:recycle	()V
        //   86: aload 5
        //   88: athrow
        // Local variable table:
        //   start	length	slot	name	signature
        //   0	89	0	this	zza
        //   0	89	1	paramzzaz	zzaz
        //   0	89	2	paramString	String
        //   3	80	3	localParcel1	Parcel
        //   7	71	4	localParcel2	Parcel
        //   75	12	5	localObject	Object
        //   25	46	6	localIBinder	IBinder
        // Exception table:
        //   from	to	target	type
        //   9	15	75	finally
        //   19	27	75	finally
        //   27	59	75	finally
      }
      
      /* Error */
      public final void zzg(zzaz paramzzaz)
        throws RemoteException
      {
        // Byte code:
        //   0: invokestatic 27	android/os/Parcel:obtain	()Landroid/os/Parcel;
        //   3: astore_2
        //   4: invokestatic 27	android/os/Parcel:obtain	()Landroid/os/Parcel;
        //   7: astore_3
        //   8: aload_2
        //   9: ldc 29
        //   11: invokevirtual 33	android/os/Parcel:writeInterfaceToken	(Ljava/lang/String;)V
        //   14: aload_1
        //   15: ifnull +45 -> 60
        //   18: aload_1
        //   19: invokeinterface 37 1 0
        //   24: astore 5
        //   26: aload_2
        //   27: aload 5
        //   29: invokevirtual 40	android/os/Parcel:writeStrongBinder	(Landroid/os/IBinder;)V
        //   32: aload_0
        //   33: getfield 15	com/google/android/gms/wearable/internal/zzbb$zza$zza:zzop	Landroid/os/IBinder;
        //   36: bipush 25
        //   38: aload_2
        //   39: aload_3
        //   40: iconst_0
        //   41: invokeinterface 46 5 0
        //   46: pop
        //   47: aload_3
        //   48: invokevirtual 49	android/os/Parcel:readException	()V
        //   51: aload_3
        //   52: invokevirtual 52	android/os/Parcel:recycle	()V
        //   55: aload_2
        //   56: invokevirtual 52	android/os/Parcel:recycle	()V
        //   59: return
        //   60: aconst_null
        //   61: astore 5
        //   63: goto -37 -> 26
        //   66: astore 4
        //   68: aload_3
        //   69: invokevirtual 52	android/os/Parcel:recycle	()V
        //   72: aload_2
        //   73: invokevirtual 52	android/os/Parcel:recycle	()V
        //   76: aload 4
        //   78: athrow
        // Local variable table:
        //   start	length	slot	name	signature
        //   0	79	0	this	zza
        //   0	79	1	paramzzaz	zzaz
        //   3	70	2	localParcel1	Parcel
        //   7	62	3	localParcel2	Parcel
        //   66	11	4	localObject	Object
        //   24	38	5	localIBinder	IBinder
        // Exception table:
        //   from	to	target	type
        //   8	14	66	finally
        //   18	26	66	finally
        //   26	51	66	finally
      }
      
      /* Error */
      public final void zzh(zzaz paramzzaz)
        throws RemoteException
      {
        // Byte code:
        //   0: invokestatic 27	android/os/Parcel:obtain	()Landroid/os/Parcel;
        //   3: astore_2
        //   4: invokestatic 27	android/os/Parcel:obtain	()Landroid/os/Parcel;
        //   7: astore_3
        //   8: aload_2
        //   9: ldc 29
        //   11: invokevirtual 33	android/os/Parcel:writeInterfaceToken	(Ljava/lang/String;)V
        //   14: aload_1
        //   15: ifnull +45 -> 60
        //   18: aload_1
        //   19: invokeinterface 37 1 0
        //   24: astore 5
        //   26: aload_2
        //   27: aload 5
        //   29: invokevirtual 40	android/os/Parcel:writeStrongBinder	(Landroid/os/IBinder;)V
        //   32: aload_0
        //   33: getfield 15	com/google/android/gms/wearable/internal/zzbb$zza$zza:zzop	Landroid/os/IBinder;
        //   36: bipush 26
        //   38: aload_2
        //   39: aload_3
        //   40: iconst_0
        //   41: invokeinterface 46 5 0
        //   46: pop
        //   47: aload_3
        //   48: invokevirtual 49	android/os/Parcel:readException	()V
        //   51: aload_3
        //   52: invokevirtual 52	android/os/Parcel:recycle	()V
        //   55: aload_2
        //   56: invokevirtual 52	android/os/Parcel:recycle	()V
        //   59: return
        //   60: aconst_null
        //   61: astore 5
        //   63: goto -37 -> 26
        //   66: astore 4
        //   68: aload_3
        //   69: invokevirtual 52	android/os/Parcel:recycle	()V
        //   72: aload_2
        //   73: invokevirtual 52	android/os/Parcel:recycle	()V
        //   76: aload 4
        //   78: athrow
        // Local variable table:
        //   start	length	slot	name	signature
        //   0	79	0	this	zza
        //   0	79	1	paramzzaz	zzaz
        //   3	70	2	localParcel1	Parcel
        //   7	62	3	localParcel2	Parcel
        //   66	11	4	localObject	Object
        //   24	38	5	localIBinder	IBinder
        // Exception table:
        //   from	to	target	type
        //   8	14	66	finally
        //   18	26	66	finally
        //   26	51	66	finally
      }
      
      /* Error */
      public final void zzi(zzaz paramzzaz)
        throws RemoteException
      {
        // Byte code:
        //   0: invokestatic 27	android/os/Parcel:obtain	()Landroid/os/Parcel;
        //   3: astore_2
        //   4: invokestatic 27	android/os/Parcel:obtain	()Landroid/os/Parcel;
        //   7: astore_3
        //   8: aload_2
        //   9: ldc 29
        //   11: invokevirtual 33	android/os/Parcel:writeInterfaceToken	(Ljava/lang/String;)V
        //   14: aload_1
        //   15: ifnull +45 -> 60
        //   18: aload_1
        //   19: invokeinterface 37 1 0
        //   24: astore 5
        //   26: aload_2
        //   27: aload 5
        //   29: invokevirtual 40	android/os/Parcel:writeStrongBinder	(Landroid/os/IBinder;)V
        //   32: aload_0
        //   33: getfield 15	com/google/android/gms/wearable/internal/zzbb$zza$zza:zzop	Landroid/os/IBinder;
        //   36: bipush 30
        //   38: aload_2
        //   39: aload_3
        //   40: iconst_0
        //   41: invokeinterface 46 5 0
        //   46: pop
        //   47: aload_3
        //   48: invokevirtual 49	android/os/Parcel:readException	()V
        //   51: aload_3
        //   52: invokevirtual 52	android/os/Parcel:recycle	()V
        //   55: aload_2
        //   56: invokevirtual 52	android/os/Parcel:recycle	()V
        //   59: return
        //   60: aconst_null
        //   61: astore 5
        //   63: goto -37 -> 26
        //   66: astore 4
        //   68: aload_3
        //   69: invokevirtual 52	android/os/Parcel:recycle	()V
        //   72: aload_2
        //   73: invokevirtual 52	android/os/Parcel:recycle	()V
        //   76: aload 4
        //   78: athrow
        // Local variable table:
        //   start	length	slot	name	signature
        //   0	79	0	this	zza
        //   0	79	1	paramzzaz	zzaz
        //   3	70	2	localParcel1	Parcel
        //   7	62	3	localParcel2	Parcel
        //   66	11	4	localObject	Object
        //   24	38	5	localIBinder	IBinder
        // Exception table:
        //   from	to	target	type
        //   8	14	66	finally
        //   18	26	66	finally
        //   26	51	66	finally
      }
      
      /* Error */
      public final void zzj(zzaz paramzzaz)
        throws RemoteException
      {
        // Byte code:
        //   0: invokestatic 27	android/os/Parcel:obtain	()Landroid/os/Parcel;
        //   3: astore_2
        //   4: invokestatic 27	android/os/Parcel:obtain	()Landroid/os/Parcel;
        //   7: astore_3
        //   8: aload_2
        //   9: ldc 29
        //   11: invokevirtual 33	android/os/Parcel:writeInterfaceToken	(Ljava/lang/String;)V
        //   14: aload_1
        //   15: ifnull +45 -> 60
        //   18: aload_1
        //   19: invokeinterface 37 1 0
        //   24: astore 5
        //   26: aload_2
        //   27: aload 5
        //   29: invokevirtual 40	android/os/Parcel:writeStrongBinder	(Landroid/os/IBinder;)V
        //   32: aload_0
        //   33: getfield 15	com/google/android/gms/wearable/internal/zzbb$zza$zza:zzop	Landroid/os/IBinder;
        //   36: bipush 57
        //   38: aload_2
        //   39: aload_3
        //   40: iconst_0
        //   41: invokeinterface 46 5 0
        //   46: pop
        //   47: aload_3
        //   48: invokevirtual 49	android/os/Parcel:readException	()V
        //   51: aload_3
        //   52: invokevirtual 52	android/os/Parcel:recycle	()V
        //   55: aload_2
        //   56: invokevirtual 52	android/os/Parcel:recycle	()V
        //   59: return
        //   60: aconst_null
        //   61: astore 5
        //   63: goto -37 -> 26
        //   66: astore 4
        //   68: aload_3
        //   69: invokevirtual 52	android/os/Parcel:recycle	()V
        //   72: aload_2
        //   73: invokevirtual 52	android/os/Parcel:recycle	()V
        //   76: aload 4
        //   78: athrow
        // Local variable table:
        //   start	length	slot	name	signature
        //   0	79	0	this	zza
        //   0	79	1	paramzzaz	zzaz
        //   3	70	2	localParcel1	Parcel
        //   7	62	3	localParcel2	Parcel
        //   66	11	4	localObject	Object
        //   24	38	5	localIBinder	IBinder
        // Exception table:
        //   from	to	target	type
        //   8	14	66	finally
        //   18	26	66	finally
        //   26	51	66	finally
      }
      
      /* Error */
      public final void zzk(zzaz paramzzaz)
        throws RemoteException
      {
        // Byte code:
        //   0: invokestatic 27	android/os/Parcel:obtain	()Landroid/os/Parcel;
        //   3: astore_2
        //   4: invokestatic 27	android/os/Parcel:obtain	()Landroid/os/Parcel;
        //   7: astore_3
        //   8: aload_2
        //   9: ldc 29
        //   11: invokevirtual 33	android/os/Parcel:writeInterfaceToken	(Ljava/lang/String;)V
        //   14: aload_1
        //   15: ifnull +45 -> 60
        //   18: aload_1
        //   19: invokeinterface 37 1 0
        //   24: astore 5
        //   26: aload_2
        //   27: aload 5
        //   29: invokevirtual 40	android/os/Parcel:writeStrongBinder	(Landroid/os/IBinder;)V
        //   32: aload_0
        //   33: getfield 15	com/google/android/gms/wearable/internal/zzbb$zza$zza:zzop	Landroid/os/IBinder;
        //   36: bipush 37
        //   38: aload_2
        //   39: aload_3
        //   40: iconst_0
        //   41: invokeinterface 46 5 0
        //   46: pop
        //   47: aload_3
        //   48: invokevirtual 49	android/os/Parcel:readException	()V
        //   51: aload_3
        //   52: invokevirtual 52	android/os/Parcel:recycle	()V
        //   55: aload_2
        //   56: invokevirtual 52	android/os/Parcel:recycle	()V
        //   59: return
        //   60: aconst_null
        //   61: astore 5
        //   63: goto -37 -> 26
        //   66: astore 4
        //   68: aload_3
        //   69: invokevirtual 52	android/os/Parcel:recycle	()V
        //   72: aload_2
        //   73: invokevirtual 52	android/os/Parcel:recycle	()V
        //   76: aload 4
        //   78: athrow
        // Local variable table:
        //   start	length	slot	name	signature
        //   0	79	0	this	zza
        //   0	79	1	paramzzaz	zzaz
        //   3	70	2	localParcel1	Parcel
        //   7	62	3	localParcel2	Parcel
        //   66	11	4	localObject	Object
        //   24	38	5	localIBinder	IBinder
        // Exception table:
        //   from	to	target	type
        //   8	14	66	finally
        //   18	26	66	finally
        //   26	51	66	finally
      }
      
      /* Error */
      public final void zzl(zzaz paramzzaz)
        throws RemoteException
      {
        // Byte code:
        //   0: invokestatic 27	android/os/Parcel:obtain	()Landroid/os/Parcel;
        //   3: astore_2
        //   4: invokestatic 27	android/os/Parcel:obtain	()Landroid/os/Parcel;
        //   7: astore_3
        //   8: aload_2
        //   9: ldc 29
        //   11: invokevirtual 33	android/os/Parcel:writeInterfaceToken	(Ljava/lang/String;)V
        //   14: aload_1
        //   15: ifnull +45 -> 60
        //   18: aload_1
        //   19: invokeinterface 37 1 0
        //   24: astore 5
        //   26: aload_2
        //   27: aload 5
        //   29: invokevirtual 40	android/os/Parcel:writeStrongBinder	(Landroid/os/IBinder;)V
        //   32: aload_0
        //   33: getfield 15	com/google/android/gms/wearable/internal/zzbb$zza$zza:zzop	Landroid/os/IBinder;
        //   36: bipush 49
        //   38: aload_2
        //   39: aload_3
        //   40: iconst_0
        //   41: invokeinterface 46 5 0
        //   46: pop
        //   47: aload_3
        //   48: invokevirtual 49	android/os/Parcel:readException	()V
        //   51: aload_3
        //   52: invokevirtual 52	android/os/Parcel:recycle	()V
        //   55: aload_2
        //   56: invokevirtual 52	android/os/Parcel:recycle	()V
        //   59: return
        //   60: aconst_null
        //   61: astore 5
        //   63: goto -37 -> 26
        //   66: astore 4
        //   68: aload_3
        //   69: invokevirtual 52	android/os/Parcel:recycle	()V
        //   72: aload_2
        //   73: invokevirtual 52	android/os/Parcel:recycle	()V
        //   76: aload 4
        //   78: athrow
        // Local variable table:
        //   start	length	slot	name	signature
        //   0	79	0	this	zza
        //   0	79	1	paramzzaz	zzaz
        //   3	70	2	localParcel1	Parcel
        //   7	62	3	localParcel2	Parcel
        //   66	11	4	localObject	Object
        //   24	38	5	localIBinder	IBinder
        // Exception table:
        //   from	to	target	type
        //   8	14	66	finally
        //   18	26	66	finally
        //   26	51	66	finally
      }
      
      /* Error */
      public final void zzm(zzaz paramzzaz)
        throws RemoteException
      {
        // Byte code:
        //   0: invokestatic 27	android/os/Parcel:obtain	()Landroid/os/Parcel;
        //   3: astore_2
        //   4: invokestatic 27	android/os/Parcel:obtain	()Landroid/os/Parcel;
        //   7: astore_3
        //   8: aload_2
        //   9: ldc 29
        //   11: invokevirtual 33	android/os/Parcel:writeInterfaceToken	(Ljava/lang/String;)V
        //   14: aload_1
        //   15: ifnull +45 -> 60
        //   18: aload_1
        //   19: invokeinterface 37 1 0
        //   24: astore 5
        //   26: aload_2
        //   27: aload 5
        //   29: invokevirtual 40	android/os/Parcel:writeStrongBinder	(Landroid/os/IBinder;)V
        //   32: aload_0
        //   33: getfield 15	com/google/android/gms/wearable/internal/zzbb$zza$zza:zzop	Landroid/os/IBinder;
        //   36: bipush 51
        //   38: aload_2
        //   39: aload_3
        //   40: iconst_0
        //   41: invokeinterface 46 5 0
        //   46: pop
        //   47: aload_3
        //   48: invokevirtual 49	android/os/Parcel:readException	()V
        //   51: aload_3
        //   52: invokevirtual 52	android/os/Parcel:recycle	()V
        //   55: aload_2
        //   56: invokevirtual 52	android/os/Parcel:recycle	()V
        //   59: return
        //   60: aconst_null
        //   61: astore 5
        //   63: goto -37 -> 26
        //   66: astore 4
        //   68: aload_3
        //   69: invokevirtual 52	android/os/Parcel:recycle	()V
        //   72: aload_2
        //   73: invokevirtual 52	android/os/Parcel:recycle	()V
        //   76: aload 4
        //   78: athrow
        // Local variable table:
        //   start	length	slot	name	signature
        //   0	79	0	this	zza
        //   0	79	1	paramzzaz	zzaz
        //   3	70	2	localParcel1	Parcel
        //   7	62	3	localParcel2	Parcel
        //   66	11	4	localObject	Object
        //   24	38	5	localIBinder	IBinder
        // Exception table:
        //   from	to	target	type
        //   8	14	66	finally
        //   18	26	66	finally
        //   26	51	66	finally
      }
      
      /* Error */
      public final void zzn(zzaz paramzzaz)
        throws RemoteException
      {
        // Byte code:
        //   0: invokestatic 27	android/os/Parcel:obtain	()Landroid/os/Parcel;
        //   3: astore_2
        //   4: invokestatic 27	android/os/Parcel:obtain	()Landroid/os/Parcel;
        //   7: astore_3
        //   8: aload_2
        //   9: ldc 29
        //   11: invokevirtual 33	android/os/Parcel:writeInterfaceToken	(Ljava/lang/String;)V
        //   14: aload_1
        //   15: ifnull +45 -> 60
        //   18: aload_1
        //   19: invokeinterface 37 1 0
        //   24: astore 5
        //   26: aload_2
        //   27: aload 5
        //   29: invokevirtual 40	android/os/Parcel:writeStrongBinder	(Landroid/os/IBinder;)V
        //   32: aload_0
        //   33: getfield 15	com/google/android/gms/wearable/internal/zzbb$zza$zza:zzop	Landroid/os/IBinder;
        //   36: bipush 52
        //   38: aload_2
        //   39: aload_3
        //   40: iconst_0
        //   41: invokeinterface 46 5 0
        //   46: pop
        //   47: aload_3
        //   48: invokevirtual 49	android/os/Parcel:readException	()V
        //   51: aload_3
        //   52: invokevirtual 52	android/os/Parcel:recycle	()V
        //   55: aload_2
        //   56: invokevirtual 52	android/os/Parcel:recycle	()V
        //   59: return
        //   60: aconst_null
        //   61: astore 5
        //   63: goto -37 -> 26
        //   66: astore 4
        //   68: aload_3
        //   69: invokevirtual 52	android/os/Parcel:recycle	()V
        //   72: aload_2
        //   73: invokevirtual 52	android/os/Parcel:recycle	()V
        //   76: aload 4
        //   78: athrow
        // Local variable table:
        //   start	length	slot	name	signature
        //   0	79	0	this	zza
        //   0	79	1	paramzzaz	zzaz
        //   3	70	2	localParcel1	Parcel
        //   7	62	3	localParcel2	Parcel
        //   66	11	4	localObject	Object
        //   24	38	5	localIBinder	IBinder
        // Exception table:
        //   from	to	target	type
        //   8	14	66	finally
        //   18	26	66	finally
        //   26	51	66	finally
      }
      
      /* Error */
      public final void zzo(zzaz paramzzaz)
        throws RemoteException
      {
        // Byte code:
        //   0: invokestatic 27	android/os/Parcel:obtain	()Landroid/os/Parcel;
        //   3: astore_2
        //   4: invokestatic 27	android/os/Parcel:obtain	()Landroid/os/Parcel;
        //   7: astore_3
        //   8: aload_2
        //   9: ldc 29
        //   11: invokevirtual 33	android/os/Parcel:writeInterfaceToken	(Ljava/lang/String;)V
        //   14: aload_1
        //   15: ifnull +44 -> 59
        //   18: aload_1
        //   19: invokeinterface 37 1 0
        //   24: astore 5
        //   26: aload_2
        //   27: aload 5
        //   29: invokevirtual 40	android/os/Parcel:writeStrongBinder	(Landroid/os/IBinder;)V
        //   32: aload_0
        //   33: getfield 15	com/google/android/gms/wearable/internal/zzbb$zza$zza:zzop	Landroid/os/IBinder;
        //   36: iconst_3
        //   37: aload_2
        //   38: aload_3
        //   39: iconst_0
        //   40: invokeinterface 46 5 0
        //   45: pop
        //   46: aload_3
        //   47: invokevirtual 49	android/os/Parcel:readException	()V
        //   50: aload_3
        //   51: invokevirtual 52	android/os/Parcel:recycle	()V
        //   54: aload_2
        //   55: invokevirtual 52	android/os/Parcel:recycle	()V
        //   58: return
        //   59: aconst_null
        //   60: astore 5
        //   62: goto -36 -> 26
        //   65: astore 4
        //   67: aload_3
        //   68: invokevirtual 52	android/os/Parcel:recycle	()V
        //   71: aload_2
        //   72: invokevirtual 52	android/os/Parcel:recycle	()V
        //   75: aload 4
        //   77: athrow
        // Local variable table:
        //   start	length	slot	name	signature
        //   0	78	0	this	zza
        //   0	78	1	paramzzaz	zzaz
        //   3	69	2	localParcel1	Parcel
        //   7	61	3	localParcel2	Parcel
        //   65	11	4	localObject	Object
        //   24	37	5	localIBinder	IBinder
        // Exception table:
        //   from	to	target	type
        //   8	14	65	finally
        //   18	26	65	finally
        //   26	50	65	finally
      }
      
      /* Error */
      public final void zzp(zzaz paramzzaz)
        throws RemoteException
      {
        // Byte code:
        //   0: invokestatic 27	android/os/Parcel:obtain	()Landroid/os/Parcel;
        //   3: astore_2
        //   4: invokestatic 27	android/os/Parcel:obtain	()Landroid/os/Parcel;
        //   7: astore_3
        //   8: aload_2
        //   9: ldc 29
        //   11: invokevirtual 33	android/os/Parcel:writeInterfaceToken	(Ljava/lang/String;)V
        //   14: aload_1
        //   15: ifnull +44 -> 59
        //   18: aload_1
        //   19: invokeinterface 37 1 0
        //   24: astore 5
        //   26: aload_2
        //   27: aload 5
        //   29: invokevirtual 40	android/os/Parcel:writeStrongBinder	(Landroid/os/IBinder;)V
        //   32: aload_0
        //   33: getfield 15	com/google/android/gms/wearable/internal/zzbb$zza$zza:zzop	Landroid/os/IBinder;
        //   36: iconst_4
        //   37: aload_2
        //   38: aload_3
        //   39: iconst_0
        //   40: invokeinterface 46 5 0
        //   45: pop
        //   46: aload_3
        //   47: invokevirtual 49	android/os/Parcel:readException	()V
        //   50: aload_3
        //   51: invokevirtual 52	android/os/Parcel:recycle	()V
        //   54: aload_2
        //   55: invokevirtual 52	android/os/Parcel:recycle	()V
        //   58: return
        //   59: aconst_null
        //   60: astore 5
        //   62: goto -36 -> 26
        //   65: astore 4
        //   67: aload_3
        //   68: invokevirtual 52	android/os/Parcel:recycle	()V
        //   71: aload_2
        //   72: invokevirtual 52	android/os/Parcel:recycle	()V
        //   75: aload 4
        //   77: athrow
        // Local variable table:
        //   start	length	slot	name	signature
        //   0	78	0	this	zza
        //   0	78	1	paramzzaz	zzaz
        //   3	69	2	localParcel1	Parcel
        //   7	61	3	localParcel2	Parcel
        //   65	11	4	localObject	Object
        //   24	37	5	localIBinder	IBinder
        // Exception table:
        //   from	to	target	type
        //   8	14	65	finally
        //   18	26	65	finally
        //   26	50	65	finally
      }
      
      /* Error */
      public final void zzq(zzaz paramzzaz)
        throws RemoteException
      {
        // Byte code:
        //   0: invokestatic 27	android/os/Parcel:obtain	()Landroid/os/Parcel;
        //   3: astore_2
        //   4: invokestatic 27	android/os/Parcel:obtain	()Landroid/os/Parcel;
        //   7: astore_3
        //   8: aload_2
        //   9: ldc 29
        //   11: invokevirtual 33	android/os/Parcel:writeInterfaceToken	(Ljava/lang/String;)V
        //   14: aload_1
        //   15: ifnull +44 -> 59
        //   18: aload_1
        //   19: invokeinterface 37 1 0
        //   24: astore 5
        //   26: aload_2
        //   27: aload 5
        //   29: invokevirtual 40	android/os/Parcel:writeStrongBinder	(Landroid/os/IBinder;)V
        //   32: aload_0
        //   33: getfield 15	com/google/android/gms/wearable/internal/zzbb$zza$zza:zzop	Landroid/os/IBinder;
        //   36: iconst_5
        //   37: aload_2
        //   38: aload_3
        //   39: iconst_0
        //   40: invokeinterface 46 5 0
        //   45: pop
        //   46: aload_3
        //   47: invokevirtual 49	android/os/Parcel:readException	()V
        //   50: aload_3
        //   51: invokevirtual 52	android/os/Parcel:recycle	()V
        //   54: aload_2
        //   55: invokevirtual 52	android/os/Parcel:recycle	()V
        //   58: return
        //   59: aconst_null
        //   60: astore 5
        //   62: goto -36 -> 26
        //   65: astore 4
        //   67: aload_3
        //   68: invokevirtual 52	android/os/Parcel:recycle	()V
        //   71: aload_2
        //   72: invokevirtual 52	android/os/Parcel:recycle	()V
        //   75: aload 4
        //   77: athrow
        // Local variable table:
        //   start	length	slot	name	signature
        //   0	78	0	this	zza
        //   0	78	1	paramzzaz	zzaz
        //   3	69	2	localParcel1	Parcel
        //   7	61	3	localParcel2	Parcel
        //   65	11	4	localObject	Object
        //   24	37	5	localIBinder	IBinder
        // Exception table:
        //   from	to	target	type
        //   8	14	65	finally
        //   18	26	65	finally
        //   26	50	65	finally
      }
    }
  }
}


/* Location:           F:\apktool\apktool\Google_Play_Store6.0.5\classes-dex2jar.jar
 * Qualified Name:     com.google.android.gms.wearable.internal.zzbb
 * JD-Core Version:    0.7.0.1
 */