package com.google.android.gms.internal;

import android.content.Context;
import android.util.DisplayMetrics;
import android.view.MotionEvent;
import com.google.ads.afma.nano.NanoAdshieldEvent.AdShieldEvent;
import com.google.android.gms.clearcut.ClearcutLogger;
import com.google.android.gms.clearcut.ClearcutLogger.LogEventBuilder;
import com.google.android.gms.clearcut.ClearcutLoggerApi;
import com.google.android.gms.common.GoogleApiAvailability;
import com.google.android.gms.common.api.GoogleApiClient;
import java.io.IOException;
import java.io.UnsupportedEncodingException;
import java.lang.reflect.InvocationTargetException;
import java.lang.reflect.Method;
import java.nio.ByteBuffer;
import java.util.ArrayList;
import java.util.Random;
import java.util.concurrent.TimeUnit;

public abstract class zzam
  extends zzak
{
  private static long startTime = 0L;
  private static Method zznA;
  private static Method zznB;
  private static Method zznC;
  private static Method zznD;
  private static Method zznE;
  private static Method zznF;
  private static Method zznG;
  private static String zznH;
  private static String zznI;
  private static String zznJ;
  private static zzas zznK;
  static boolean zznL = false;
  protected static ClearcutLogger zznM = null;
  protected static NanoAdshieldEvent.AdShieldEvent zznN;
  protected static int zznO;
  private static Random zznP;
  private static GoogleApiAvailability zznQ;
  private static boolean zznR;
  protected static boolean zznS = false;
  protected static boolean zznT = false;
  protected static boolean zznU = false;
  protected static boolean zznV = false;
  private static Method zznu;
  private static Method zznv;
  private static Method zznw;
  private static Method zznx;
  private static Method zzny;
  private static Method zznz;
  
  protected zzam(Context paramContext, zzaq paramzzaq, zzar paramzzar)
  {
    super(paramContext, paramzzaq, paramzzar);
    NanoAdshieldEvent.AdShieldEvent localAdShieldEvent = new NanoAdshieldEvent.AdShieldEvent();
    zznN = localAdShieldEvent;
    localAdShieldEvent.appId = paramContext.getPackageName();
  }
  
  private static void zzS()
  {
    if (zznV)
    {
      ClearcutLogger localClearcutLogger = zznM;
      TimeUnit localTimeUnit = TimeUnit.MILLISECONDS;
      localClearcutLogger.zzamv.flush$708acd79(100L, localTimeUnit);
      zznq.disconnect();
    }
  }
  
  public static void zzT()
  {
    zznT = true;
  }
  
  public static void zzU()
  {
    zznU = true;
  }
  
  private static String zzV()
    throws zzam.zza
  {
    if (zznH == null) {
      throw new zza();
    }
    return zznH;
  }
  
  private static Long zzW()
    throws zzam.zza
  {
    if (zznu == null) {
      throw new zza();
    }
    try
    {
      Long localLong = (Long)zznu.invoke(null, new Object[0]);
      return localLong;
    }
    catch (IllegalAccessException localIllegalAccessException)
    {
      throw new zza(localIllegalAccessException);
    }
    catch (InvocationTargetException localInvocationTargetException)
    {
      throw new zza(localInvocationTargetException);
    }
  }
  
  private static String zzX()
    throws zzam.zza
  {
    if (zznw == null) {
      throw new zza();
    }
    try
    {
      String str = (String)zznw.invoke(null, new Object[0]);
      return str;
    }
    catch (IllegalAccessException localIllegalAccessException)
    {
      throw new zza(localIllegalAccessException);
    }
    catch (InvocationTargetException localInvocationTargetException)
    {
      throw new zza(localInvocationTargetException);
    }
  }
  
  private static Long zzY()
    throws zzam.zza
  {
    if (zznv == null) {
      throw new zza();
    }
    try
    {
      Long localLong = (Long)zznv.invoke(null, new Object[0]);
      return localLong;
    }
    catch (IllegalAccessException localIllegalAccessException)
    {
      throw new zza(localIllegalAccessException);
    }
    catch (InvocationTargetException localInvocationTargetException)
    {
      throw new zza(localInvocationTargetException);
    }
  }
  
  private static String zza(Context paramContext, zzaq paramzzaq)
    throws zzam.zza
  {
    if (zznI != null) {
      return zznI;
    }
    if (zznx == null) {
      throw new zza();
    }
    try
    {
      localByteBuffer = (ByteBuffer)zznx.invoke(null, new Object[] { paramContext });
      if (localByteBuffer == null) {
        throw new zza();
      }
    }
    catch (IllegalAccessException localIllegalAccessException)
    {
      ByteBuffer localByteBuffer;
      throw new zza(localIllegalAccessException);
      String str = paramzzaq.zza$5a238448(localByteBuffer.array());
      zznI = str;
      return str;
    }
    catch (InvocationTargetException localInvocationTargetException)
    {
      throw new zza(localInvocationTargetException);
    }
  }
  
  private static ArrayList<Long> zza(MotionEvent paramMotionEvent, DisplayMetrics paramDisplayMetrics)
    throws zzam.zza
  {
    if ((zzny == null) || (paramMotionEvent == null)) {
      throw new zza();
    }
    try
    {
      ArrayList localArrayList = (ArrayList)zzny.invoke(null, new Object[] { paramMotionEvent, paramDisplayMetrics });
      return localArrayList;
    }
    catch (IllegalAccessException localIllegalAccessException)
    {
      throw new zza(localIllegalAccessException);
    }
    catch (InvocationTargetException localInvocationTargetException)
    {
      throw new zza(localInvocationTargetException);
    }
  }
  
  protected static void zza(int paramInt1, int paramInt2)
    throws IOException
  {
    if ((zznV) && (zznS))
    {
      ClearcutLogger.LogEventBuilder localLogEventBuilder = zznM.newEvent(zzaik.toByteArray(zznN));
      localLogEventBuilder.zzamA.zznO = paramInt2;
      localLogEventBuilder.zzamA.eventCode = paramInt1;
      localLogEventBuilder.log(zznq);
    }
  }
  
  /* Error */
  protected static void zza(String paramString, Context paramContext, zzaq paramzzaq)
  {
    // Byte code:
    //   0: ldc 2
    //   2: monitorenter
    //   3: getstatic 49	com/google/android/gms/internal/zzam:zznL	Z
    //   6: istore 4
    //   8: iload 4
    //   10: ifne +91 -> 101
    //   13: new 215	com/google/android/gms/internal/zzas
    //   16: dup
    //   17: aload_2
    //   18: invokespecial 218	com/google/android/gms/internal/zzas:<init>	(Lcom/google/android/gms/internal/zzaq;)V
    //   21: putstatic 220	com/google/android/gms/internal/zzam:zznK	Lcom/google/android/gms/internal/zzas;
    //   24: aload_0
    //   25: putstatic 115	com/google/android/gms/internal/zzam:zznH	Ljava/lang/String;
    //   28: aload_1
    //   29: invokestatic 226	com/google/android/gms/ads/internal/config/Flags:initialize	(Landroid/content/Context;)V
    //   32: getstatic 220	com/google/android/gms/internal/zzam:zznK	Lcom/google/android/gms/internal/zzas;
    //   35: ldc 228
    //   37: invokevirtual 232	com/google/android/gms/internal/zzas:zzl	(Ljava/lang/String;)[B
    //   40: astore 13
    //   42: getstatic 220	com/google/android/gms/internal/zzam:zznK	Lcom/google/android/gms/internal/zzas;
    //   45: aload 13
    //   47: ldc 234
    //   49: invokevirtual 238	com/google/android/gms/internal/zzas:zzc	([BLjava/lang/String;)[B
    //   52: astore 14
    //   54: aload_1
    //   55: invokevirtual 242	android/content/Context:getCacheDir	()Ljava/io/File;
    //   58: astore 15
    //   60: aload 15
    //   62: ifnonnull +43 -> 105
    //   65: aload_1
    //   66: ldc 244
    //   68: iconst_0
    //   69: invokevirtual 248	android/content/Context:getDir	(Ljava/lang/String;I)Ljava/io/File;
    //   72: astore 15
    //   74: aload 15
    //   76: ifnonnull +29 -> 105
    //   79: new 113	com/google/android/gms/internal/zzam$zza
    //   82: dup
    //   83: invokespecial 116	com/google/android/gms/internal/zzam$zza:<init>	()V
    //   86: athrow
    //   87: astore 12
    //   89: new 113	com/google/android/gms/internal/zzam$zza
    //   92: dup
    //   93: aload 12
    //   95: invokespecial 137	com/google/android/gms/internal/zzam$zza:<init>	(Ljava/lang/Throwable;)V
    //   98: athrow
    //   99: astore 6
    //   101: ldc 2
    //   103: monitorexit
    //   104: return
    //   105: aload 15
    //   107: astore 16
    //   109: ldc 250
    //   111: ldc 252
    //   113: aload 16
    //   115: invokestatic 258	java/io/File:createTempFile	(Ljava/lang/String;Ljava/lang/String;Ljava/io/File;)Ljava/io/File;
    //   118: astore 17
    //   120: new 260	java/io/FileOutputStream
    //   123: dup
    //   124: aload 17
    //   126: invokespecial 263	java/io/FileOutputStream:<init>	(Ljava/io/File;)V
    //   129: astore 18
    //   131: aload 18
    //   133: aload 14
    //   135: iconst_0
    //   136: aload 14
    //   138: arraylength
    //   139: invokevirtual 267	java/io/FileOutputStream:write	([BII)V
    //   142: aload 18
    //   144: invokevirtual 270	java/io/FileOutputStream:close	()V
    //   147: new 272	dalvik/system/DexClassLoader
    //   150: dup
    //   151: aload 17
    //   153: invokevirtual 275	java/io/File:getAbsolutePath	()Ljava/lang/String;
    //   156: aload 16
    //   158: invokevirtual 275	java/io/File:getAbsolutePath	()Ljava/lang/String;
    //   161: aconst_null
    //   162: aload_1
    //   163: invokevirtual 279	android/content/Context:getClassLoader	()Ljava/lang/ClassLoader;
    //   166: invokespecial 282	dalvik/system/DexClassLoader:<init>	(Ljava/lang/String;Ljava/lang/String;Ljava/lang/String;Ljava/lang/ClassLoader;)V
    //   169: astore 19
    //   171: aload 19
    //   173: aload 13
    //   175: ldc_w 284
    //   178: invokestatic 288	com/google/android/gms/internal/zzam:zzb	([BLjava/lang/String;)Ljava/lang/String;
    //   181: invokevirtual 292	dalvik/system/DexClassLoader:loadClass	(Ljava/lang/String;)Ljava/lang/Class;
    //   184: astore 24
    //   186: aload 19
    //   188: aload 13
    //   190: ldc_w 294
    //   193: invokestatic 288	com/google/android/gms/internal/zzam:zzb	([BLjava/lang/String;)Ljava/lang/String;
    //   196: invokevirtual 292	dalvik/system/DexClassLoader:loadClass	(Ljava/lang/String;)Ljava/lang/Class;
    //   199: astore 25
    //   201: aload 19
    //   203: aload 13
    //   205: ldc_w 296
    //   208: invokestatic 288	com/google/android/gms/internal/zzam:zzb	([BLjava/lang/String;)Ljava/lang/String;
    //   211: invokevirtual 292	dalvik/system/DexClassLoader:loadClass	(Ljava/lang/String;)Ljava/lang/Class;
    //   214: astore 26
    //   216: aload 19
    //   218: aload 13
    //   220: ldc_w 298
    //   223: invokestatic 288	com/google/android/gms/internal/zzam:zzb	([BLjava/lang/String;)Ljava/lang/String;
    //   226: invokevirtual 292	dalvik/system/DexClassLoader:loadClass	(Ljava/lang/String;)Ljava/lang/Class;
    //   229: astore 27
    //   231: aload 19
    //   233: aload 13
    //   235: ldc_w 300
    //   238: invokestatic 288	com/google/android/gms/internal/zzam:zzb	([BLjava/lang/String;)Ljava/lang/String;
    //   241: invokevirtual 292	dalvik/system/DexClassLoader:loadClass	(Ljava/lang/String;)Ljava/lang/Class;
    //   244: astore 28
    //   246: aload 19
    //   248: aload 13
    //   250: ldc_w 302
    //   253: invokestatic 288	com/google/android/gms/internal/zzam:zzb	([BLjava/lang/String;)Ljava/lang/String;
    //   256: invokevirtual 292	dalvik/system/DexClassLoader:loadClass	(Ljava/lang/String;)Ljava/lang/Class;
    //   259: astore 29
    //   261: aload 19
    //   263: aload 13
    //   265: ldc_w 304
    //   268: invokestatic 288	com/google/android/gms/internal/zzam:zzb	([BLjava/lang/String;)Ljava/lang/String;
    //   271: invokevirtual 292	dalvik/system/DexClassLoader:loadClass	(Ljava/lang/String;)Ljava/lang/Class;
    //   274: astore 30
    //   276: aload 19
    //   278: aload 13
    //   280: ldc_w 306
    //   283: invokestatic 288	com/google/android/gms/internal/zzam:zzb	([BLjava/lang/String;)Ljava/lang/String;
    //   286: invokevirtual 292	dalvik/system/DexClassLoader:loadClass	(Ljava/lang/String;)Ljava/lang/Class;
    //   289: astore 31
    //   291: aload 19
    //   293: aload 13
    //   295: ldc_w 308
    //   298: invokestatic 288	com/google/android/gms/internal/zzam:zzb	([BLjava/lang/String;)Ljava/lang/String;
    //   301: invokevirtual 292	dalvik/system/DexClassLoader:loadClass	(Ljava/lang/String;)Ljava/lang/Class;
    //   304: astore 32
    //   306: aload 19
    //   308: aload 13
    //   310: ldc_w 310
    //   313: invokestatic 288	com/google/android/gms/internal/zzam:zzb	([BLjava/lang/String;)Ljava/lang/String;
    //   316: invokevirtual 292	dalvik/system/DexClassLoader:loadClass	(Ljava/lang/String;)Ljava/lang/Class;
    //   319: astore 33
    //   321: aload 19
    //   323: aload 13
    //   325: ldc_w 312
    //   328: invokestatic 288	com/google/android/gms/internal/zzam:zzb	([BLjava/lang/String;)Ljava/lang/String;
    //   331: invokevirtual 292	dalvik/system/DexClassLoader:loadClass	(Ljava/lang/String;)Ljava/lang/Class;
    //   334: astore 34
    //   336: aload 19
    //   338: aload 13
    //   340: ldc_w 314
    //   343: invokestatic 288	com/google/android/gms/internal/zzam:zzb	([BLjava/lang/String;)Ljava/lang/String;
    //   346: invokevirtual 292	dalvik/system/DexClassLoader:loadClass	(Ljava/lang/String;)Ljava/lang/Class;
    //   349: astore 35
    //   351: aload 19
    //   353: aload 13
    //   355: ldc_w 316
    //   358: invokestatic 288	com/google/android/gms/internal/zzam:zzb	([BLjava/lang/String;)Ljava/lang/String;
    //   361: invokevirtual 292	dalvik/system/DexClassLoader:loadClass	(Ljava/lang/String;)Ljava/lang/Class;
    //   364: astore 36
    //   366: aload 24
    //   368: aload 13
    //   370: ldc_w 318
    //   373: invokestatic 288	com/google/android/gms/internal/zzam:zzb	([BLjava/lang/String;)Ljava/lang/String;
    //   376: iconst_0
    //   377: anewarray 320	java/lang/Class
    //   380: invokevirtual 324	java/lang/Class:getMethod	(Ljava/lang/String;[Ljava/lang/Class;)Ljava/lang/reflect/Method;
    //   383: putstatic 124	com/google/android/gms/internal/zzam:zznu	Ljava/lang/reflect/Method;
    //   386: aload 25
    //   388: aload 13
    //   390: ldc_w 326
    //   393: invokestatic 288	com/google/android/gms/internal/zzam:zzb	([BLjava/lang/String;)Ljava/lang/String;
    //   396: iconst_0
    //   397: anewarray 320	java/lang/Class
    //   400: invokevirtual 324	java/lang/Class:getMethod	(Ljava/lang/String;[Ljava/lang/Class;)Ljava/lang/reflect/Method;
    //   403: putstatic 145	com/google/android/gms/internal/zzam:zznv	Ljava/lang/reflect/Method;
    //   406: aload 26
    //   408: aload 13
    //   410: ldc_w 328
    //   413: invokestatic 288	com/google/android/gms/internal/zzam:zzb	([BLjava/lang/String;)Ljava/lang/String;
    //   416: iconst_0
    //   417: anewarray 320	java/lang/Class
    //   420: invokevirtual 324	java/lang/Class:getMethod	(Ljava/lang/String;[Ljava/lang/Class;)Ljava/lang/reflect/Method;
    //   423: putstatic 140	com/google/android/gms/internal/zzam:zznw	Ljava/lang/reflect/Method;
    //   426: aload 27
    //   428: aload 13
    //   430: ldc_w 330
    //   433: invokestatic 288	com/google/android/gms/internal/zzam:zzb	([BLjava/lang/String;)Ljava/lang/String;
    //   436: iconst_1
    //   437: anewarray 320	java/lang/Class
    //   440: dup
    //   441: iconst_0
    //   442: ldc 71
    //   444: aastore
    //   445: invokevirtual 324	java/lang/Class:getMethod	(Ljava/lang/String;[Ljava/lang/Class;)Ljava/lang/reflect/Method;
    //   448: putstatic 151	com/google/android/gms/internal/zzam:zznx	Ljava/lang/reflect/Method;
    //   451: aload 28
    //   453: aload 13
    //   455: ldc_w 332
    //   458: invokestatic 288	com/google/android/gms/internal/zzam:zzb	([BLjava/lang/String;)Ljava/lang/String;
    //   461: iconst_2
    //   462: anewarray 320	java/lang/Class
    //   465: dup
    //   466: iconst_0
    //   467: ldc_w 334
    //   470: aastore
    //   471: dup
    //   472: iconst_1
    //   473: ldc_w 336
    //   476: aastore
    //   477: invokevirtual 324	java/lang/Class:getMethod	(Ljava/lang/String;[Ljava/lang/Class;)Ljava/lang/reflect/Method;
    //   480: putstatic 166	com/google/android/gms/internal/zzam:zzny	Ljava/lang/reflect/Method;
    //   483: aload 29
    //   485: aload 13
    //   487: ldc_w 338
    //   490: invokestatic 288	com/google/android/gms/internal/zzam:zzb	([BLjava/lang/String;)Ljava/lang/String;
    //   493: iconst_1
    //   494: anewarray 320	java/lang/Class
    //   497: dup
    //   498: iconst_0
    //   499: ldc 71
    //   501: aastore
    //   502: invokevirtual 324	java/lang/Class:getMethod	(Ljava/lang/String;[Ljava/lang/Class;)Ljava/lang/reflect/Method;
    //   505: putstatic 340	com/google/android/gms/internal/zzam:zznz	Ljava/lang/reflect/Method;
    //   508: aload 30
    //   510: aload 13
    //   512: ldc_w 342
    //   515: invokestatic 288	com/google/android/gms/internal/zzam:zzb	([BLjava/lang/String;)Ljava/lang/String;
    //   518: iconst_1
    //   519: anewarray 320	java/lang/Class
    //   522: dup
    //   523: iconst_0
    //   524: ldc 71
    //   526: aastore
    //   527: invokevirtual 324	java/lang/Class:getMethod	(Ljava/lang/String;[Ljava/lang/Class;)Ljava/lang/reflect/Method;
    //   530: putstatic 344	com/google/android/gms/internal/zzam:zznA	Ljava/lang/reflect/Method;
    //   533: aload 31
    //   535: aload 13
    //   537: ldc_w 346
    //   540: invokestatic 288	com/google/android/gms/internal/zzam:zzb	([BLjava/lang/String;)Ljava/lang/String;
    //   543: iconst_1
    //   544: anewarray 320	java/lang/Class
    //   547: dup
    //   548: iconst_0
    //   549: ldc 71
    //   551: aastore
    //   552: invokevirtual 324	java/lang/Class:getMethod	(Ljava/lang/String;[Ljava/lang/Class;)Ljava/lang/reflect/Method;
    //   555: putstatic 348	com/google/android/gms/internal/zzam:zznB	Ljava/lang/reflect/Method;
    //   558: aload 32
    //   560: aload 13
    //   562: ldc_w 350
    //   565: invokestatic 288	com/google/android/gms/internal/zzam:zzb	([BLjava/lang/String;)Ljava/lang/String;
    //   568: iconst_1
    //   569: anewarray 320	java/lang/Class
    //   572: dup
    //   573: iconst_0
    //   574: ldc 71
    //   576: aastore
    //   577: invokevirtual 324	java/lang/Class:getMethod	(Ljava/lang/String;[Ljava/lang/Class;)Ljava/lang/reflect/Method;
    //   580: putstatic 352	com/google/android/gms/internal/zzam:zznC	Ljava/lang/reflect/Method;
    //   583: aload 33
    //   585: aload 13
    //   587: ldc_w 354
    //   590: invokestatic 288	com/google/android/gms/internal/zzam:zzb	([BLjava/lang/String;)Ljava/lang/String;
    //   593: iconst_1
    //   594: anewarray 320	java/lang/Class
    //   597: dup
    //   598: iconst_0
    //   599: ldc 71
    //   601: aastore
    //   602: invokevirtual 324	java/lang/Class:getMethod	(Ljava/lang/String;[Ljava/lang/Class;)Ljava/lang/reflect/Method;
    //   605: putstatic 356	com/google/android/gms/internal/zzam:zznD	Ljava/lang/reflect/Method;
    //   608: aload 34
    //   610: aload 13
    //   612: ldc_w 358
    //   615: invokestatic 288	com/google/android/gms/internal/zzam:zzb	([BLjava/lang/String;)Ljava/lang/String;
    //   618: iconst_1
    //   619: anewarray 320	java/lang/Class
    //   622: dup
    //   623: iconst_0
    //   624: ldc 71
    //   626: aastore
    //   627: invokevirtual 324	java/lang/Class:getMethod	(Ljava/lang/String;[Ljava/lang/Class;)Ljava/lang/reflect/Method;
    //   630: putstatic 360	com/google/android/gms/internal/zzam:zznE	Ljava/lang/reflect/Method;
    //   633: aload 35
    //   635: aload 13
    //   637: ldc_w 362
    //   640: invokestatic 288	com/google/android/gms/internal/zzam:zzb	([BLjava/lang/String;)Ljava/lang/String;
    //   643: iconst_1
    //   644: anewarray 320	java/lang/Class
    //   647: dup
    //   648: iconst_0
    //   649: ldc 71
    //   651: aastore
    //   652: invokevirtual 324	java/lang/Class:getMethod	(Ljava/lang/String;[Ljava/lang/Class;)Ljava/lang/reflect/Method;
    //   655: putstatic 364	com/google/android/gms/internal/zzam:zznF	Ljava/lang/reflect/Method;
    //   658: aload 36
    //   660: aload 13
    //   662: ldc_w 366
    //   665: invokestatic 288	com/google/android/gms/internal/zzam:zzb	([BLjava/lang/String;)Ljava/lang/String;
    //   668: iconst_1
    //   669: anewarray 320	java/lang/Class
    //   672: dup
    //   673: iconst_0
    //   674: ldc 71
    //   676: aastore
    //   677: invokevirtual 324	java/lang/Class:getMethod	(Ljava/lang/String;[Ljava/lang/Class;)Ljava/lang/reflect/Method;
    //   680: putstatic 368	com/google/android/gms/internal/zzam:zznG	Ljava/lang/reflect/Method;
    //   683: aload 17
    //   685: invokevirtual 371	java/io/File:getName	()Ljava/lang/String;
    //   688: astore 37
    //   690: aload 17
    //   692: invokevirtual 375	java/io/File:delete	()Z
    //   695: pop
    //   696: new 254	java/io/File
    //   699: dup
    //   700: aload 16
    //   702: aload 37
    //   704: ldc 252
    //   706: ldc_w 377
    //   709: invokevirtual 381	java/lang/String:replace	(Ljava/lang/CharSequence;Ljava/lang/CharSequence;)Ljava/lang/String;
    //   712: invokespecial 384	java/io/File:<init>	(Ljava/io/File;Ljava/lang/String;)V
    //   715: invokevirtual 375	java/io/File:delete	()Z
    //   718: pop
    //   719: invokestatic 386	com/google/android/gms/internal/zzam:zzW	()Ljava/lang/Long;
    //   722: invokevirtual 390	java/lang/Long:longValue	()J
    //   725: putstatic 47	com/google/android/gms/internal/zzam:startTime	J
    //   728: new 392	java/util/Random
    //   731: dup
    //   732: invokespecial 393	java/util/Random:<init>	()V
    //   735: putstatic 395	com/google/android/gms/internal/zzam:zznP	Ljava/util/Random;
    //   738: new 397	com/google/android/gms/common/api/GoogleApiClient$Builder
    //   741: dup
    //   742: aload_1
    //   743: invokespecial 399	com/google/android/gms/common/api/GoogleApiClient$Builder:<init>	(Landroid/content/Context;)V
    //   746: getstatic 403	com/google/android/gms/clearcut/ClearcutLogger:API	Lcom/google/android/gms/common/api/Api;
    //   749: invokevirtual 407	com/google/android/gms/common/api/GoogleApiClient$Builder:addApi	(Lcom/google/android/gms/common/api/Api;)Lcom/google/android/gms/common/api/GoogleApiClient$Builder;
    //   752: invokevirtual 411	com/google/android/gms/common/api/GoogleApiClient$Builder:build	()Lcom/google/android/gms/common/api/GoogleApiClient;
    //   755: putstatic 103	com/google/android/gms/internal/zzam:zznq	Lcom/google/android/gms/common/api/GoogleApiClient;
    //   758: invokestatic 417	com/google/android/gms/common/GoogleApiAvailability:getInstance	()Lcom/google/android/gms/common/GoogleApiAvailability;
    //   761: putstatic 419	com/google/android/gms/internal/zzam:zznQ	Lcom/google/android/gms/common/GoogleApiAvailability;
    //   764: aload_1
    //   765: invokestatic 423	com/google/android/gms/common/GoogleApiAvailability:isGooglePlayServicesAvailable	(Landroid/content/Context;)I
    //   768: ifne +170 -> 938
    //   771: iconst_1
    //   772: istore 41
    //   774: iload 41
    //   776: putstatic 425	com/google/android/gms/internal/zzam:zznR	Z
    //   779: aload_1
    //   780: invokestatic 226	com/google/android/gms/ads/internal/config/Flags:initialize	(Landroid/content/Context;)V
    //   783: getstatic 429	com/google/android/gms/ads/internal/config/Flags:adShieldInstrumentationEnabled	Lcom/google/android/gms/ads/internal/config/Flag;
    //   786: astore 42
    //   788: invokestatic 435	com/google/android/gms/ads/internal/zzp:zzbR	()Lcom/google/android/gms/ads/internal/config/zzf;
    //   791: aload 42
    //   793: invokevirtual 441	com/google/android/gms/ads/internal/config/zzf:zzd	(Lcom/google/android/gms/ads/internal/config/Flag;)Ljava/lang/Object;
    //   796: checkcast 443	java/lang/Boolean
    //   799: invokevirtual 446	java/lang/Boolean:booleanValue	()Z
    //   802: putstatic 53	com/google/android/gms/internal/zzam:zznS	Z
    //   805: new 87	com/google/android/gms/clearcut/ClearcutLogger
    //   808: dup
    //   809: aload_1
    //   810: ldc_w 448
    //   813: invokespecial 451	com/google/android/gms/clearcut/ClearcutLogger:<init>	(Landroid/content/Context;Ljava/lang/String;)V
    //   816: putstatic 51	com/google/android/gms/internal/zzam:zznM	Lcom/google/android/gms/clearcut/ClearcutLogger;
    //   819: iconst_1
    //   820: putstatic 49	com/google/android/gms/internal/zzam:zznL	Z
    //   823: goto -722 -> 101
    //   826: astore 5
    //   828: goto -727 -> 101
    //   831: astore 20
    //   833: aload 17
    //   835: invokevirtual 371	java/io/File:getName	()Ljava/lang/String;
    //   838: astore 21
    //   840: aload 17
    //   842: invokevirtual 375	java/io/File:delete	()Z
    //   845: pop
    //   846: new 254	java/io/File
    //   849: dup
    //   850: aload 16
    //   852: aload 21
    //   854: ldc 252
    //   856: ldc_w 377
    //   859: invokevirtual 381	java/lang/String:replace	(Ljava/lang/CharSequence;Ljava/lang/CharSequence;)Ljava/lang/String;
    //   862: invokespecial 384	java/io/File:<init>	(Ljava/io/File;Ljava/lang/String;)V
    //   865: invokevirtual 375	java/io/File:delete	()Z
    //   868: pop
    //   869: aload 20
    //   871: athrow
    //   872: astore 11
    //   874: new 113	com/google/android/gms/internal/zzam$zza
    //   877: dup
    //   878: aload 11
    //   880: invokespecial 137	com/google/android/gms/internal/zzam$zza:<init>	(Ljava/lang/Throwable;)V
    //   883: athrow
    //   884: astore_3
    //   885: ldc 2
    //   887: monitorexit
    //   888: aload_3
    //   889: athrow
    //   890: astore 10
    //   892: new 113	com/google/android/gms/internal/zzam$zza
    //   895: dup
    //   896: aload 10
    //   898: invokespecial 137	com/google/android/gms/internal/zzam$zza:<init>	(Ljava/lang/Throwable;)V
    //   901: athrow
    //   902: astore 9
    //   904: new 113	com/google/android/gms/internal/zzam$zza
    //   907: dup
    //   908: aload 9
    //   910: invokespecial 137	com/google/android/gms/internal/zzam$zza:<init>	(Ljava/lang/Throwable;)V
    //   913: athrow
    //   914: astore 8
    //   916: new 113	com/google/android/gms/internal/zzam$zza
    //   919: dup
    //   920: aload 8
    //   922: invokespecial 137	com/google/android/gms/internal/zzam$zza:<init>	(Ljava/lang/Throwable;)V
    //   925: athrow
    //   926: astore 7
    //   928: new 113	com/google/android/gms/internal/zzam$zza
    //   931: dup
    //   932: aload 7
    //   934: invokespecial 137	com/google/android/gms/internal/zzam$zza:<init>	(Ljava/lang/Throwable;)V
    //   937: athrow
    //   938: iconst_0
    //   939: istore 41
    //   941: goto -167 -> 774
    //   944: astore 40
    //   946: goto -127 -> 819
    // Local variable table:
    //   start	length	slot	name	signature
    //   0	949	0	paramString	String
    //   0	949	1	paramContext	Context
    //   0	949	2	paramzzaq	zzaq
    //   884	5	3	localObject1	Object
    //   6	3	4	bool1	boolean
    //   826	1	5	localUnsupportedOperationException	java.lang.UnsupportedOperationException
    //   99	1	6	localzza	zza
    //   926	7	7	localNullPointerException	java.lang.NullPointerException
    //   914	7	8	localNoSuchMethodException	java.lang.NoSuchMethodException
    //   902	7	9	localzza1	zzas.zza
    //   890	7	10	localClassNotFoundException	java.lang.ClassNotFoundException
    //   872	7	11	localIOException	IOException
    //   87	7	12	localFileNotFoundException	java.io.FileNotFoundException
    //   40	621	13	arrayOfByte1	byte[]
    //   52	85	14	arrayOfByte2	byte[]
    //   58	48	15	localFile1	java.io.File
    //   107	744	16	localFile2	java.io.File
    //   118	723	17	localFile3	java.io.File
    //   129	14	18	localFileOutputStream	java.io.FileOutputStream
    //   169	183	19	localDexClassLoader	dalvik.system.DexClassLoader
    //   831	39	20	localObject2	Object
    //   838	15	21	str1	String
    //   184	183	24	localClass1	java.lang.Class
    //   199	188	25	localClass2	java.lang.Class
    //   214	193	26	localClass3	java.lang.Class
    //   229	198	27	localClass4	java.lang.Class
    //   244	208	28	localClass5	java.lang.Class
    //   259	225	29	localClass6	java.lang.Class
    //   274	235	30	localClass7	java.lang.Class
    //   289	245	31	localClass8	java.lang.Class
    //   304	255	32	localClass9	java.lang.Class
    //   319	265	33	localClass10	java.lang.Class
    //   334	275	34	localClass11	java.lang.Class
    //   349	285	35	localClass12	java.lang.Class
    //   364	295	36	localClass13	java.lang.Class
    //   688	15	37	str2	String
    //   944	1	40	localNoClassDefFoundError	java.lang.NoClassDefFoundError
    //   772	168	41	bool2	boolean
    //   786	6	42	localFlag	com.google.android.gms.ads.internal.config.Flag
    // Exception table:
    //   from	to	target	type
    //   32	60	87	java/io/FileNotFoundException
    //   65	74	87	java/io/FileNotFoundException
    //   79	87	87	java/io/FileNotFoundException
    //   109	147	87	java/io/FileNotFoundException
    //   683	719	87	java/io/FileNotFoundException
    //   833	872	87	java/io/FileNotFoundException
    //   13	32	99	com/google/android/gms/internal/zzam$zza
    //   32	60	99	com/google/android/gms/internal/zzam$zza
    //   65	74	99	com/google/android/gms/internal/zzam$zza
    //   79	87	99	com/google/android/gms/internal/zzam$zza
    //   89	99	99	com/google/android/gms/internal/zzam$zza
    //   109	147	99	com/google/android/gms/internal/zzam$zza
    //   683	719	99	com/google/android/gms/internal/zzam$zza
    //   719	738	99	com/google/android/gms/internal/zzam$zza
    //   738	771	99	com/google/android/gms/internal/zzam$zza
    //   774	819	99	com/google/android/gms/internal/zzam$zza
    //   819	823	99	com/google/android/gms/internal/zzam$zza
    //   833	872	99	com/google/android/gms/internal/zzam$zza
    //   874	884	99	com/google/android/gms/internal/zzam$zza
    //   892	902	99	com/google/android/gms/internal/zzam$zza
    //   904	914	99	com/google/android/gms/internal/zzam$zza
    //   916	926	99	com/google/android/gms/internal/zzam$zza
    //   928	938	99	com/google/android/gms/internal/zzam$zza
    //   13	32	826	java/lang/UnsupportedOperationException
    //   32	60	826	java/lang/UnsupportedOperationException
    //   65	74	826	java/lang/UnsupportedOperationException
    //   79	87	826	java/lang/UnsupportedOperationException
    //   89	99	826	java/lang/UnsupportedOperationException
    //   109	147	826	java/lang/UnsupportedOperationException
    //   683	719	826	java/lang/UnsupportedOperationException
    //   719	738	826	java/lang/UnsupportedOperationException
    //   738	771	826	java/lang/UnsupportedOperationException
    //   774	819	826	java/lang/UnsupportedOperationException
    //   819	823	826	java/lang/UnsupportedOperationException
    //   833	872	826	java/lang/UnsupportedOperationException
    //   874	884	826	java/lang/UnsupportedOperationException
    //   892	902	826	java/lang/UnsupportedOperationException
    //   904	914	826	java/lang/UnsupportedOperationException
    //   916	926	826	java/lang/UnsupportedOperationException
    //   928	938	826	java/lang/UnsupportedOperationException
    //   147	683	831	finally
    //   32	60	872	java/io/IOException
    //   65	74	872	java/io/IOException
    //   79	87	872	java/io/IOException
    //   109	147	872	java/io/IOException
    //   683	719	872	java/io/IOException
    //   833	872	872	java/io/IOException
    //   3	8	884	finally
    //   13	32	884	finally
    //   32	60	884	finally
    //   65	74	884	finally
    //   79	87	884	finally
    //   89	99	884	finally
    //   109	147	884	finally
    //   683	719	884	finally
    //   719	738	884	finally
    //   738	771	884	finally
    //   774	819	884	finally
    //   819	823	884	finally
    //   833	872	884	finally
    //   874	884	884	finally
    //   892	902	884	finally
    //   904	914	884	finally
    //   916	926	884	finally
    //   928	938	884	finally
    //   32	60	890	java/lang/ClassNotFoundException
    //   65	74	890	java/lang/ClassNotFoundException
    //   79	87	890	java/lang/ClassNotFoundException
    //   109	147	890	java/lang/ClassNotFoundException
    //   683	719	890	java/lang/ClassNotFoundException
    //   833	872	890	java/lang/ClassNotFoundException
    //   32	60	902	com/google/android/gms/internal/zzas$zza
    //   65	74	902	com/google/android/gms/internal/zzas$zza
    //   79	87	902	com/google/android/gms/internal/zzas$zza
    //   109	147	902	com/google/android/gms/internal/zzas$zza
    //   683	719	902	com/google/android/gms/internal/zzas$zza
    //   833	872	902	com/google/android/gms/internal/zzas$zza
    //   32	60	914	java/lang/NoSuchMethodException
    //   65	74	914	java/lang/NoSuchMethodException
    //   79	87	914	java/lang/NoSuchMethodException
    //   109	147	914	java/lang/NoSuchMethodException
    //   683	719	914	java/lang/NoSuchMethodException
    //   833	872	914	java/lang/NoSuchMethodException
    //   32	60	926	java/lang/NullPointerException
    //   65	74	926	java/lang/NullPointerException
    //   79	87	926	java/lang/NullPointerException
    //   109	147	926	java/lang/NullPointerException
    //   683	719	926	java/lang/NullPointerException
    //   833	872	926	java/lang/NullPointerException
    //   738	771	944	java/lang/NoClassDefFoundError
    //   774	819	944	java/lang/NoClassDefFoundError
  }
  
  private static String zzb(Context paramContext, zzaq paramzzaq)
    throws zzam.zza
  {
    if (zznJ != null) {
      return zznJ;
    }
    if (zznA == null) {
      throw new zza();
    }
    try
    {
      localByteBuffer = (ByteBuffer)zznA.invoke(null, new Object[] { paramContext });
      if (localByteBuffer == null) {
        throw new zza();
      }
    }
    catch (IllegalAccessException localIllegalAccessException)
    {
      ByteBuffer localByteBuffer;
      throw new zza(localIllegalAccessException);
      String str = paramzzaq.zza$5a238448(localByteBuffer.array());
      zznJ = str;
      return str;
    }
    catch (InvocationTargetException localInvocationTargetException)
    {
      throw new zza(localInvocationTargetException);
    }
  }
  
  private static String zzb(byte[] paramArrayOfByte, String paramString)
    throws zzam.zza
  {
    try
    {
      String str = new String(zznK.zzc(paramArrayOfByte, paramString), "UTF-8");
      return str;
    }
    catch (zzas.zza localzza)
    {
      throw new zza(localzza);
    }
    catch (UnsupportedEncodingException localUnsupportedEncodingException)
    {
      throw new zza(localUnsupportedEncodingException);
    }
  }
  
  private static void zzf$faab20d()
  {
    if (zznR)
    {
      zznq.connect();
      zznV = true;
      return;
    }
    zznV = false;
  }
  
  static String zzg(Context paramContext)
    throws zzam.zza
  {
    if (zznz == null) {
      throw new zza();
    }
    String str;
    try
    {
      str = (String)zznz.invoke(null, new Object[] { paramContext });
      if (str == null) {
        throw new zza();
      }
    }
    catch (IllegalAccessException localIllegalAccessException)
    {
      throw new zza(localIllegalAccessException);
    }
    catch (InvocationTargetException localInvocationTargetException)
    {
      throw new zza(localInvocationTargetException);
    }
    return str;
  }
  
  private static String zzh(Context paramContext)
    throws zzam.zza
  {
    if (zznD == null) {
      throw new zza();
    }
    try
    {
      String str = (String)zznD.invoke(null, new Object[] { paramContext });
      return str;
    }
    catch (IllegalAccessException localIllegalAccessException)
    {
      throw new zza(localIllegalAccessException);
    }
    catch (InvocationTargetException localInvocationTargetException)
    {
      throw new zza(localInvocationTargetException);
    }
  }
  
  private static Long zzi(Context paramContext)
    throws zzam.zza
  {
    if (zznE == null) {
      throw new zza();
    }
    try
    {
      Long localLong = (Long)zznE.invoke(null, new Object[] { paramContext });
      return localLong;
    }
    catch (IllegalAccessException localIllegalAccessException)
    {
      throw new zza(localIllegalAccessException);
    }
    catch (InvocationTargetException localInvocationTargetException)
    {
      throw new zza(localInvocationTargetException);
    }
  }
  
  private static ArrayList<Long> zzj(Context paramContext)
    throws zzam.zza
  {
    if (zznB == null) {
      throw new zza();
    }
    ArrayList localArrayList;
    try
    {
      localArrayList = (ArrayList)zznB.invoke(null, new Object[] { paramContext });
      if ((localArrayList == null) || (localArrayList.size() != 2)) {
        throw new zza();
      }
    }
    catch (IllegalAccessException localIllegalAccessException)
    {
      throw new zza(localIllegalAccessException);
    }
    catch (InvocationTargetException localInvocationTargetException)
    {
      throw new zza(localInvocationTargetException);
    }
    return localArrayList;
  }
  
  private static int[] zzk(Context paramContext)
    throws zzam.zza
  {
    if (zznC == null) {
      throw new zza();
    }
    try
    {
      int[] arrayOfInt = (int[])zznC.invoke(null, new Object[] { paramContext });
      return arrayOfInt;
    }
    catch (IllegalAccessException localIllegalAccessException)
    {
      throw new zza(localIllegalAccessException);
    }
    catch (InvocationTargetException localInvocationTargetException)
    {
      throw new zza(localInvocationTargetException);
    }
  }
  
  private static int zzl(Context paramContext)
    throws zzam.zza
  {
    if (zznF == null) {
      throw new zza();
    }
    try
    {
      int i = ((Integer)zznF.invoke(null, new Object[] { paramContext })).intValue();
      return i;
    }
    catch (IllegalAccessException localIllegalAccessException)
    {
      throw new zza(localIllegalAccessException);
    }
    catch (InvocationTargetException localInvocationTargetException)
    {
      throw new zza(localInvocationTargetException);
    }
  }
  
  private static int zzm(Context paramContext)
    throws zzam.zza
  {
    if (zznG == null) {
      throw new zza();
    }
    try
    {
      int i = ((Integer)zznG.invoke(null, new Object[] { paramContext })).intValue();
      return i;
    }
    catch (IllegalAccessException localIllegalAccessException)
    {
      throw new zza(localIllegalAccessException);
    }
    catch (InvocationTargetException localInvocationTargetException)
    {
      throw new zza(localInvocationTargetException);
    }
  }
  
  /* Error */
  protected void zzc(Context paramContext)
  {
    // Byte code:
    //   0: invokestatic 487	com/google/android/gms/internal/zzam:zzf$faab20d	()V
    //   3: getstatic 395	com/google/android/gms/internal/zzam:zznP	Ljava/util/Random;
    //   6: invokevirtual 490	java/util/Random:nextInt	()I
    //   9: putstatic 491	com/google/android/gms/internal/zzam:zznO	I
    //   12: iconst_0
    //   13: getstatic 491	com/google/android/gms/internal/zzam:zznO	I
    //   16: invokestatic 493	com/google/android/gms/internal/zzam:zza	(II)V
    //   19: iconst_1
    //   20: invokestatic 495	com/google/android/gms/internal/zzam:zzX	()Ljava/lang/String;
    //   23: invokestatic 498	com/google/android/gms/internal/zzam:zza	(ILjava/lang/String;)V
    //   26: iconst_1
    //   27: getstatic 491	com/google/android/gms/internal/zzam:zznO	I
    //   30: invokestatic 493	com/google/android/gms/internal/zzam:zza	(II)V
    //   33: iconst_2
    //   34: invokestatic 500	com/google/android/gms/internal/zzam:zzV	()Ljava/lang/String;
    //   37: invokestatic 498	com/google/android/gms/internal/zzam:zza	(ILjava/lang/String;)V
    //   40: iconst_2
    //   41: getstatic 491	com/google/android/gms/internal/zzam:zznO	I
    //   44: invokestatic 493	com/google/android/gms/internal/zzam:zza	(II)V
    //   47: invokestatic 386	com/google/android/gms/internal/zzam:zzW	()Ljava/lang/Long;
    //   50: invokevirtual 390	java/lang/Long:longValue	()J
    //   53: lstore 17
    //   55: bipush 25
    //   57: lload 17
    //   59: invokestatic 503	com/google/android/gms/internal/zzam:zza	(IJ)V
    //   62: getstatic 47	com/google/android/gms/internal/zzam:startTime	J
    //   65: lconst_0
    //   66: lcmp
    //   67: ifeq +22 -> 89
    //   70: bipush 17
    //   72: lload 17
    //   74: getstatic 47	com/google/android/gms/internal/zzam:startTime	J
    //   77: lsub
    //   78: invokestatic 503	com/google/android/gms/internal/zzam:zza	(IJ)V
    //   81: bipush 23
    //   83: getstatic 47	com/google/android/gms/internal/zzam:startTime	J
    //   86: invokestatic 503	com/google/android/gms/internal/zzam:zza	(IJ)V
    //   89: bipush 25
    //   91: getstatic 491	com/google/android/gms/internal/zzam:zznO	I
    //   94: invokestatic 493	com/google/android/gms/internal/zzam:zza	(II)V
    //   97: aload_1
    //   98: invokestatic 505	com/google/android/gms/internal/zzam:zzj	(Landroid/content/Context;)Ljava/util/ArrayList;
    //   101: astore 16
    //   103: bipush 31
    //   105: aload 16
    //   107: iconst_0
    //   108: invokevirtual 509	java/util/ArrayList:get	(I)Ljava/lang/Object;
    //   111: checkcast 134	java/lang/Long
    //   114: invokevirtual 390	java/lang/Long:longValue	()J
    //   117: invokestatic 503	com/google/android/gms/internal/zzam:zza	(IJ)V
    //   120: bipush 32
    //   122: aload 16
    //   124: iconst_1
    //   125: invokevirtual 509	java/util/ArrayList:get	(I)Ljava/lang/Object;
    //   128: checkcast 134	java/lang/Long
    //   131: invokevirtual 390	java/lang/Long:longValue	()J
    //   134: invokestatic 503	com/google/android/gms/internal/zzam:zza	(IJ)V
    //   137: bipush 31
    //   139: getstatic 491	com/google/android/gms/internal/zzam:zznO	I
    //   142: invokestatic 493	com/google/android/gms/internal/zzam:zza	(II)V
    //   145: bipush 33
    //   147: invokestatic 511	com/google/android/gms/internal/zzam:zzY	()Ljava/lang/Long;
    //   150: invokevirtual 390	java/lang/Long:longValue	()J
    //   153: invokestatic 503	com/google/android/gms/internal/zzam:zza	(IJ)V
    //   156: bipush 33
    //   158: getstatic 491	com/google/android/gms/internal/zzam:zznO	I
    //   161: invokestatic 493	com/google/android/gms/internal/zzam:zza	(II)V
    //   164: getstatic 55	com/google/android/gms/internal/zzam:zznT	Z
    //   167: ifeq +9 -> 176
    //   170: getstatic 57	com/google/android/gms/internal/zzam:zznU	Z
    //   173: ifne +16 -> 189
    //   176: bipush 27
    //   178: aload_1
    //   179: aload_0
    //   180: getfield 515	com/google/android/gms/internal/zzam:zznp	Lcom/google/android/gms/internal/zzaq;
    //   183: invokestatic 517	com/google/android/gms/internal/zzam:zza	(Landroid/content/Context;Lcom/google/android/gms/internal/zzaq;)Ljava/lang/String;
    //   186: invokestatic 498	com/google/android/gms/internal/zzam:zza	(ILjava/lang/String;)V
    //   189: bipush 27
    //   191: getstatic 491	com/google/android/gms/internal/zzam:zznO	I
    //   194: invokestatic 493	com/google/android/gms/internal/zzam:zza	(II)V
    //   197: bipush 29
    //   199: aload_1
    //   200: aload_0
    //   201: getfield 515	com/google/android/gms/internal/zzam:zznp	Lcom/google/android/gms/internal/zzaq;
    //   204: invokestatic 519	com/google/android/gms/internal/zzam:zzb	(Landroid/content/Context;Lcom/google/android/gms/internal/zzaq;)Ljava/lang/String;
    //   207: invokestatic 498	com/google/android/gms/internal/zzam:zza	(ILjava/lang/String;)V
    //   210: bipush 29
    //   212: getstatic 491	com/google/android/gms/internal/zzam:zznO	I
    //   215: invokestatic 493	com/google/android/gms/internal/zzam:zza	(II)V
    //   218: aload_1
    //   219: invokestatic 521	com/google/android/gms/internal/zzam:zzk	(Landroid/content/Context;)[I
    //   222: astore 15
    //   224: iconst_5
    //   225: aload 15
    //   227: iconst_0
    //   228: iaload
    //   229: i2l
    //   230: invokestatic 503	com/google/android/gms/internal/zzam:zza	(IJ)V
    //   233: bipush 6
    //   235: aload 15
    //   237: iconst_1
    //   238: iaload
    //   239: i2l
    //   240: invokestatic 503	com/google/android/gms/internal/zzam:zza	(IJ)V
    //   243: iconst_5
    //   244: getstatic 491	com/google/android/gms/internal/zzam:zznO	I
    //   247: invokestatic 493	com/google/android/gms/internal/zzam:zza	(II)V
    //   250: bipush 12
    //   252: aload_1
    //   253: invokestatic 523	com/google/android/gms/internal/zzam:zzl	(Landroid/content/Context;)I
    //   256: i2l
    //   257: invokestatic 503	com/google/android/gms/internal/zzam:zza	(IJ)V
    //   260: bipush 12
    //   262: getstatic 491	com/google/android/gms/internal/zzam:zznO	I
    //   265: invokestatic 493	com/google/android/gms/internal/zzam:zza	(II)V
    //   268: iconst_3
    //   269: aload_1
    //   270: invokestatic 525	com/google/android/gms/internal/zzam:zzm	(Landroid/content/Context;)I
    //   273: i2l
    //   274: invokestatic 503	com/google/android/gms/internal/zzam:zza	(IJ)V
    //   277: iconst_3
    //   278: getstatic 491	com/google/android/gms/internal/zzam:zznO	I
    //   281: invokestatic 493	com/google/android/gms/internal/zzam:zza	(II)V
    //   284: bipush 34
    //   286: aload_1
    //   287: invokestatic 527	com/google/android/gms/internal/zzam:zzh	(Landroid/content/Context;)Ljava/lang/String;
    //   290: invokestatic 498	com/google/android/gms/internal/zzam:zza	(ILjava/lang/String;)V
    //   293: bipush 34
    //   295: getstatic 491	com/google/android/gms/internal/zzam:zznO	I
    //   298: invokestatic 493	com/google/android/gms/internal/zzam:zza	(II)V
    //   301: bipush 35
    //   303: aload_1
    //   304: invokestatic 529	com/google/android/gms/internal/zzam:zzi	(Landroid/content/Context;)Ljava/lang/Long;
    //   307: invokevirtual 390	java/lang/Long:longValue	()J
    //   310: invokestatic 503	com/google/android/gms/internal/zzam:zza	(IJ)V
    //   313: bipush 35
    //   315: getstatic 491	com/google/android/gms/internal/zzam:zznO	I
    //   318: invokestatic 493	com/google/android/gms/internal/zzam:zza	(II)V
    //   321: invokestatic 531	com/google/android/gms/internal/zzam:zzS	()V
    //   324: return
    //   325: astore_2
    //   326: return
    //   327: astore 14
    //   329: goto -8 -> 321
    //   332: astore 13
    //   334: goto -33 -> 301
    //   337: astore 12
    //   339: goto -55 -> 284
    //   342: astore 11
    //   344: goto -76 -> 268
    //   347: astore 10
    //   349: goto -99 -> 250
    //   352: astore 9
    //   354: goto -136 -> 218
    //   357: astore 8
    //   359: goto -162 -> 197
    //   362: astore 7
    //   364: goto -200 -> 164
    //   367: astore 6
    //   369: goto -224 -> 145
    //   372: astore 5
    //   374: goto -277 -> 97
    //   377: astore 4
    //   379: goto -332 -> 47
    //   382: astore_3
    //   383: goto -350 -> 33
    // Local variable table:
    //   start	length	slot	name	signature
    //   0	386	0	this	zzam
    //   0	386	1	paramContext	Context
    //   325	1	2	localIOException	IOException
    //   382	1	3	localzza1	zza
    //   377	1	4	localzza2	zza
    //   372	1	5	localzza3	zza
    //   367	1	6	localzza4	zza
    //   362	1	7	localzza5	zza
    //   357	1	8	localzza6	zza
    //   352	1	9	localzza7	zza
    //   347	1	10	localzza8	zza
    //   342	1	11	localzza9	zza
    //   337	1	12	localzza10	zza
    //   332	1	13	localzza11	zza
    //   327	1	14	localzza12	zza
    //   222	14	15	arrayOfInt	int[]
    //   101	22	16	localArrayList	ArrayList
    //   53	20	17	l	long
    // Exception table:
    //   from	to	target	type
    //   0	19	325	java/io/IOException
    //   19	33	325	java/io/IOException
    //   33	47	325	java/io/IOException
    //   47	89	325	java/io/IOException
    //   89	97	325	java/io/IOException
    //   97	145	325	java/io/IOException
    //   145	164	325	java/io/IOException
    //   164	176	325	java/io/IOException
    //   176	189	325	java/io/IOException
    //   189	197	325	java/io/IOException
    //   197	218	325	java/io/IOException
    //   218	250	325	java/io/IOException
    //   250	268	325	java/io/IOException
    //   268	284	325	java/io/IOException
    //   284	301	325	java/io/IOException
    //   301	321	325	java/io/IOException
    //   321	324	325	java/io/IOException
    //   301	321	327	com/google/android/gms/internal/zzam$zza
    //   284	301	332	com/google/android/gms/internal/zzam$zza
    //   268	284	337	com/google/android/gms/internal/zzam$zza
    //   250	268	342	com/google/android/gms/internal/zzam$zza
    //   218	250	347	com/google/android/gms/internal/zzam$zza
    //   197	218	352	com/google/android/gms/internal/zzam$zza
    //   164	176	357	com/google/android/gms/internal/zzam$zza
    //   176	189	357	com/google/android/gms/internal/zzam$zza
    //   189	197	357	com/google/android/gms/internal/zzam$zza
    //   145	164	362	com/google/android/gms/internal/zzam$zza
    //   97	145	367	com/google/android/gms/internal/zzam$zza
    //   47	89	372	com/google/android/gms/internal/zzam$zza
    //   89	97	372	com/google/android/gms/internal/zzam$zza
    //   33	47	377	com/google/android/gms/internal/zzam$zza
    //   19	33	382	com/google/android/gms/internal/zzam$zza
  }
  
  /* Error */
  protected final void zzd(Context paramContext)
  {
    // Byte code:
    //   0: invokestatic 487	com/google/android/gms/internal/zzam:zzf$faab20d	()V
    //   3: getstatic 395	com/google/android/gms/internal/zzam:zznP	Ljava/util/Random;
    //   6: invokevirtual 490	java/util/Random:nextInt	()I
    //   9: putstatic 491	com/google/android/gms/internal/zzam:zznO	I
    //   12: iconst_2
    //   13: invokestatic 500	com/google/android/gms/internal/zzam:zzV	()Ljava/lang/String;
    //   16: invokestatic 498	com/google/android/gms/internal/zzam:zza	(ILjava/lang/String;)V
    //   19: iconst_1
    //   20: invokestatic 495	com/google/android/gms/internal/zzam:zzX	()Ljava/lang/String;
    //   23: invokestatic 498	com/google/android/gms/internal/zzam:zza	(ILjava/lang/String;)V
    //   26: bipush 25
    //   28: invokestatic 386	com/google/android/gms/internal/zzam:zzW	()Ljava/lang/Long;
    //   31: invokevirtual 390	java/lang/Long:longValue	()J
    //   34: invokestatic 503	com/google/android/gms/internal/zzam:zza	(IJ)V
    //   37: iconst_0
    //   38: getstatic 491	com/google/android/gms/internal/zzam:zznO	I
    //   41: invokestatic 493	com/google/android/gms/internal/zzam:zza	(II)V
    //   44: aload_0
    //   45: getfield 535	com/google/android/gms/internal/zzam:zznn	Landroid/view/MotionEvent;
    //   48: aload_0
    //   49: getfield 539	com/google/android/gms/internal/zzam:zzno	Landroid/util/DisplayMetrics;
    //   52: invokestatic 541	com/google/android/gms/internal/zzam:zza	(Landroid/view/MotionEvent;Landroid/util/DisplayMetrics;)Ljava/util/ArrayList;
    //   55: astore 9
    //   57: bipush 14
    //   59: aload 9
    //   61: iconst_0
    //   62: invokevirtual 509	java/util/ArrayList:get	(I)Ljava/lang/Object;
    //   65: checkcast 134	java/lang/Long
    //   68: invokevirtual 390	java/lang/Long:longValue	()J
    //   71: invokestatic 503	com/google/android/gms/internal/zzam:zza	(IJ)V
    //   74: bipush 15
    //   76: aload 9
    //   78: iconst_1
    //   79: invokevirtual 509	java/util/ArrayList:get	(I)Ljava/lang/Object;
    //   82: checkcast 134	java/lang/Long
    //   85: invokevirtual 390	java/lang/Long:longValue	()J
    //   88: invokestatic 503	com/google/android/gms/internal/zzam:zza	(IJ)V
    //   91: aload 9
    //   93: invokevirtual 475	java/util/ArrayList:size	()I
    //   96: iconst_3
    //   97: if_icmplt +20 -> 117
    //   100: bipush 16
    //   102: aload 9
    //   104: iconst_2
    //   105: invokevirtual 509	java/util/ArrayList:get	(I)Ljava/lang/Object;
    //   108: checkcast 134	java/lang/Long
    //   111: invokevirtual 390	java/lang/Long:longValue	()J
    //   114: invokestatic 503	com/google/android/gms/internal/zzam:zza	(IJ)V
    //   117: bipush 14
    //   119: getstatic 491	com/google/android/gms/internal/zzam:zznO	I
    //   122: invokestatic 493	com/google/android/gms/internal/zzam:zza	(II)V
    //   125: bipush 34
    //   127: aload_1
    //   128: invokestatic 527	com/google/android/gms/internal/zzam:zzh	(Landroid/content/Context;)Ljava/lang/String;
    //   131: invokestatic 498	com/google/android/gms/internal/zzam:zza	(ILjava/lang/String;)V
    //   134: bipush 35
    //   136: aload_1
    //   137: invokestatic 529	com/google/android/gms/internal/zzam:zzi	(Landroid/content/Context;)Ljava/lang/Long;
    //   140: invokevirtual 390	java/lang/Long:longValue	()J
    //   143: invokestatic 503	com/google/android/gms/internal/zzam:zza	(IJ)V
    //   146: invokestatic 531	com/google/android/gms/internal/zzam:zzS	()V
    //   149: return
    //   150: astore_2
    //   151: return
    //   152: astore 8
    //   154: goto -8 -> 146
    //   157: astore 7
    //   159: goto -25 -> 134
    //   162: astore 6
    //   164: goto -39 -> 125
    //   167: astore 5
    //   169: goto -132 -> 37
    //   172: astore 4
    //   174: goto -148 -> 26
    //   177: astore_3
    //   178: goto -159 -> 19
    // Local variable table:
    //   start	length	slot	name	signature
    //   0	181	0	this	zzam
    //   0	181	1	paramContext	Context
    //   150	1	2	localIOException	IOException
    //   177	1	3	localzza1	zza
    //   172	1	4	localzza2	zza
    //   167	1	5	localzza3	zza
    //   162	1	6	localzza4	zza
    //   157	1	7	localzza5	zza
    //   152	1	8	localzza6	zza
    //   55	48	9	localArrayList	ArrayList
    // Exception table:
    //   from	to	target	type
    //   0	12	150	java/io/IOException
    //   12	19	150	java/io/IOException
    //   19	26	150	java/io/IOException
    //   26	37	150	java/io/IOException
    //   37	44	150	java/io/IOException
    //   44	117	150	java/io/IOException
    //   117	125	150	java/io/IOException
    //   125	134	150	java/io/IOException
    //   134	146	150	java/io/IOException
    //   146	149	150	java/io/IOException
    //   134	146	152	com/google/android/gms/internal/zzam$zza
    //   125	134	157	com/google/android/gms/internal/zzam$zza
    //   44	117	162	com/google/android/gms/internal/zzam$zza
    //   117	125	162	com/google/android/gms/internal/zzam$zza
    //   26	37	167	com/google/android/gms/internal/zzam$zza
    //   19	26	172	com/google/android/gms/internal/zzam$zza
    //   12	19	177	com/google/android/gms/internal/zzam$zza
  }
  
  static final class zza
    extends Exception
  {
    public zza() {}
    
    public zza(Throwable paramThrowable)
    {
      super();
    }
  }
}


/* Location:           F:\apktool\apktool\Google_Play_Store6.0.5\classes-dex2jar.jar
 * Qualified Name:     com.google.android.gms.internal.zzam
 * JD-Core Version:    0.7.0.1
 */