package com.google.android.gms.internal;

import android.os.Binder;
import android.os.IBinder;
import android.os.IInterface;
import android.os.Parcel;
import android.os.RemoteException;
import com.google.android.gms.dynamic.zzd;
import com.google.android.gms.dynamic.zzd.zza;

public abstract interface zzbb
  extends IInterface
{
  public abstract String getSignalsUrlKey()
    throws RemoteException;
  
  public abstract void setAdSenseDomainAndPath(String paramString1, String paramString2)
    throws RemoteException;
  
  public abstract void setGoogleAdUrlSuffixes(String paramString)
    throws RemoteException;
  
  public abstract zzd zza(zzd paramzzd1, zzd paramzzd2)
    throws RemoteException;
  
  public abstract String zza(zzd paramzzd, String paramString)
    throws RemoteException;
  
  public abstract boolean zza(zzd paramzzd)
    throws RemoteException;
  
  public abstract zzd zzb(zzd paramzzd1, zzd paramzzd2)
    throws RemoteException;
  
  public abstract boolean zzb(zzd paramzzd)
    throws RemoteException;
  
  public abstract boolean zzb(String paramString, boolean paramBoolean)
    throws RemoteException;
  
  public abstract String zzc(zzd paramzzd)
    throws RemoteException;
  
  public abstract void zzd(zzd paramzzd)
    throws RemoteException;
  
  public static abstract class zza
    extends Binder
    implements zzbb
  {
    public zza()
    {
      attachInterface(this, "com.google.android.gms.ads.adshield.internal.IAdShieldClient");
    }
    
    public static zzbb zze(IBinder paramIBinder)
    {
      if (paramIBinder == null) {
        return null;
      }
      IInterface localIInterface = paramIBinder.queryLocalInterface("com.google.android.gms.ads.adshield.internal.IAdShieldClient");
      if ((localIInterface != null) && ((localIInterface instanceof zzbb))) {
        return (zzbb)localIInterface;
      }
      return new zza(paramIBinder);
    }
    
    public IBinder asBinder()
    {
      return this;
    }
    
    public boolean onTransact(int paramInt1, Parcel paramParcel1, Parcel paramParcel2, int paramInt2)
      throws RemoteException
    {
      switch (paramInt1)
      {
      default: 
        return super.onTransact(paramInt1, paramParcel1, paramParcel2, paramInt2);
      case 1598968902: 
        paramParcel2.writeString("com.google.android.gms.ads.adshield.internal.IAdShieldClient");
        return true;
      case 1: 
        paramParcel1.enforceInterface("com.google.android.gms.ads.adshield.internal.IAdShieldClient");
        String str4 = getSignalsUrlKey();
        paramParcel2.writeNoException();
        paramParcel2.writeString(str4);
        return true;
      case 2: 
        paramParcel1.enforceInterface("com.google.android.gms.ads.adshield.internal.IAdShieldClient");
        setAdSenseDomainAndPath(paramParcel1.readString(), paramParcel1.readString());
        paramParcel2.writeNoException();
        return true;
      case 3: 
        paramParcel1.enforceInterface("com.google.android.gms.ads.adshield.internal.IAdShieldClient");
        boolean bool4 = zza(zzd.zza.zzdb(paramParcel1.readStrongBinder()));
        paramParcel2.writeNoException();
        int k = 0;
        if (bool4) {
          k = 1;
        }
        paramParcel2.writeInt(k);
        return true;
      case 4: 
        paramParcel1.enforceInterface("com.google.android.gms.ads.adshield.internal.IAdShieldClient");
        boolean bool3 = zzb(zzd.zza.zzdb(paramParcel1.readStrongBinder()));
        paramParcel2.writeNoException();
        int j = 0;
        if (bool3) {
          j = 1;
        }
        paramParcel2.writeInt(j);
        return true;
      case 5: 
        paramParcel1.enforceInterface("com.google.android.gms.ads.adshield.internal.IAdShieldClient");
        setGoogleAdUrlSuffixes(paramParcel1.readString());
        paramParcel2.writeNoException();
        return true;
      case 6: 
        paramParcel1.enforceInterface("com.google.android.gms.ads.adshield.internal.IAdShieldClient");
        zzd localzzd2 = zza(zzd.zza.zzdb(paramParcel1.readStrongBinder()), zzd.zza.zzdb(paramParcel1.readStrongBinder()));
        paramParcel2.writeNoException();
        if (localzzd2 != null) {}
        for (IBinder localIBinder2 = localzzd2.asBinder();; localIBinder2 = null)
        {
          paramParcel2.writeStrongBinder(localIBinder2);
          return true;
        }
      case 7: 
        paramParcel1.enforceInterface("com.google.android.gms.ads.adshield.internal.IAdShieldClient");
        String str3 = zzc(zzd.zza.zzdb(paramParcel1.readStrongBinder()));
        paramParcel2.writeNoException();
        paramParcel2.writeString(str3);
        return true;
      case 8: 
        paramParcel1.enforceInterface("com.google.android.gms.ads.adshield.internal.IAdShieldClient");
        String str2 = zza(zzd.zza.zzdb(paramParcel1.readStrongBinder()), paramParcel1.readString());
        paramParcel2.writeNoException();
        paramParcel2.writeString(str2);
        return true;
      case 9: 
        paramParcel1.enforceInterface("com.google.android.gms.ads.adshield.internal.IAdShieldClient");
        zzd(zzd.zza.zzdb(paramParcel1.readStrongBinder()));
        paramParcel2.writeNoException();
        return true;
      case 10: 
        paramParcel1.enforceInterface("com.google.android.gms.ads.adshield.internal.IAdShieldClient");
        zzd localzzd1 = zzb(zzd.zza.zzdb(paramParcel1.readStrongBinder()), zzd.zza.zzdb(paramParcel1.readStrongBinder()));
        paramParcel2.writeNoException();
        IBinder localIBinder1 = null;
        if (localzzd1 != null) {
          localIBinder1 = localzzd1.asBinder();
        }
        paramParcel2.writeStrongBinder(localIBinder1);
        return true;
      }
      paramParcel1.enforceInterface("com.google.android.gms.ads.adshield.internal.IAdShieldClient");
      String str1 = paramParcel1.readString();
      if (paramParcel1.readInt() != 0) {}
      for (boolean bool1 = true;; bool1 = false)
      {
        boolean bool2 = zzb(str1, bool1);
        paramParcel2.writeNoException();
        int i = 0;
        if (bool2) {
          i = 1;
        }
        paramParcel2.writeInt(i);
        return true;
      }
    }
    
    private static final class zza
      implements zzbb
    {
      private IBinder zzop;
      
      zza(IBinder paramIBinder)
      {
        this.zzop = paramIBinder;
      }
      
      public final IBinder asBinder()
      {
        return this.zzop;
      }
      
      public final String getSignalsUrlKey()
        throws RemoteException
      {
        Parcel localParcel1 = Parcel.obtain();
        Parcel localParcel2 = Parcel.obtain();
        try
        {
          localParcel1.writeInterfaceToken("com.google.android.gms.ads.adshield.internal.IAdShieldClient");
          this.zzop.transact(1, localParcel1, localParcel2, 0);
          localParcel2.readException();
          String str = localParcel2.readString();
          return str;
        }
        finally
        {
          localParcel2.recycle();
          localParcel1.recycle();
        }
      }
      
      public final void setAdSenseDomainAndPath(String paramString1, String paramString2)
        throws RemoteException
      {
        Parcel localParcel1 = Parcel.obtain();
        Parcel localParcel2 = Parcel.obtain();
        try
        {
          localParcel1.writeInterfaceToken("com.google.android.gms.ads.adshield.internal.IAdShieldClient");
          localParcel1.writeString(paramString1);
          localParcel1.writeString(paramString2);
          this.zzop.transact(2, localParcel1, localParcel2, 0);
          localParcel2.readException();
          return;
        }
        finally
        {
          localParcel2.recycle();
          localParcel1.recycle();
        }
      }
      
      public final void setGoogleAdUrlSuffixes(String paramString)
        throws RemoteException
      {
        Parcel localParcel1 = Parcel.obtain();
        Parcel localParcel2 = Parcel.obtain();
        try
        {
          localParcel1.writeInterfaceToken("com.google.android.gms.ads.adshield.internal.IAdShieldClient");
          localParcel1.writeString(paramString);
          this.zzop.transact(5, localParcel1, localParcel2, 0);
          localParcel2.readException();
          return;
        }
        finally
        {
          localParcel2.recycle();
          localParcel1.recycle();
        }
      }
      
      /* Error */
      public final zzd zza(zzd paramzzd1, zzd paramzzd2)
        throws RemoteException
      {
        // Byte code:
        //   0: invokestatic 27	android/os/Parcel:obtain	()Landroid/os/Parcel;
        //   3: astore_3
        //   4: invokestatic 27	android/os/Parcel:obtain	()Landroid/os/Parcel;
        //   7: astore 4
        //   9: aload_3
        //   10: ldc 29
        //   12: invokevirtual 33	android/os/Parcel:writeInterfaceToken	(Ljava/lang/String;)V
        //   15: aload_1
        //   16: ifnull +81 -> 97
        //   19: aload_1
        //   20: invokeinterface 60 1 0
        //   25: astore 6
        //   27: aload_3
        //   28: aload 6
        //   30: invokevirtual 63	android/os/Parcel:writeStrongBinder	(Landroid/os/IBinder;)V
        //   33: aconst_null
        //   34: astore 7
        //   36: aload_2
        //   37: ifnull +11 -> 48
        //   40: aload_2
        //   41: invokeinterface 60 1 0
        //   46: astore 7
        //   48: aload_3
        //   49: aload 7
        //   51: invokevirtual 63	android/os/Parcel:writeStrongBinder	(Landroid/os/IBinder;)V
        //   54: aload_0
        //   55: getfield 15	com/google/android/gms/internal/zzbb$zza$zza:zzop	Landroid/os/IBinder;
        //   58: bipush 6
        //   60: aload_3
        //   61: aload 4
        //   63: iconst_0
        //   64: invokeinterface 39 5 0
        //   69: pop
        //   70: aload 4
        //   72: invokevirtual 42	android/os/Parcel:readException	()V
        //   75: aload 4
        //   77: invokevirtual 66	android/os/Parcel:readStrongBinder	()Landroid/os/IBinder;
        //   80: invokestatic 72	com/google/android/gms/dynamic/zzd$zza:zzdb	(Landroid/os/IBinder;)Lcom/google/android/gms/dynamic/zzd;
        //   83: astore 9
        //   85: aload 4
        //   87: invokevirtual 48	android/os/Parcel:recycle	()V
        //   90: aload_3
        //   91: invokevirtual 48	android/os/Parcel:recycle	()V
        //   94: aload 9
        //   96: areturn
        //   97: aconst_null
        //   98: astore 6
        //   100: goto -73 -> 27
        //   103: astore 5
        //   105: aload 4
        //   107: invokevirtual 48	android/os/Parcel:recycle	()V
        //   110: aload_3
        //   111: invokevirtual 48	android/os/Parcel:recycle	()V
        //   114: aload 5
        //   116: athrow
        // Local variable table:
        //   start	length	slot	name	signature
        //   0	117	0	this	zza
        //   0	117	1	paramzzd1	zzd
        //   0	117	2	paramzzd2	zzd
        //   3	108	3	localParcel1	Parcel
        //   7	99	4	localParcel2	Parcel
        //   103	12	5	localObject	Object
        //   25	74	6	localIBinder1	IBinder
        //   34	16	7	localIBinder2	IBinder
        //   83	12	9	localzzd	zzd
        // Exception table:
        //   from	to	target	type
        //   9	15	103	finally
        //   19	27	103	finally
        //   27	33	103	finally
        //   40	48	103	finally
        //   48	85	103	finally
      }
      
      /* Error */
      public final String zza(zzd paramzzd, String paramString)
        throws RemoteException
      {
        // Byte code:
        //   0: invokestatic 27	android/os/Parcel:obtain	()Landroid/os/Parcel;
        //   3: astore_3
        //   4: invokestatic 27	android/os/Parcel:obtain	()Landroid/os/Parcel;
        //   7: astore 4
        //   9: aload_3
        //   10: ldc 29
        //   12: invokevirtual 33	android/os/Parcel:writeInterfaceToken	(Ljava/lang/String;)V
        //   15: aload_1
        //   16: ifnull +62 -> 78
        //   19: aload_1
        //   20: invokeinterface 60 1 0
        //   25: astore 6
        //   27: aload_3
        //   28: aload 6
        //   30: invokevirtual 63	android/os/Parcel:writeStrongBinder	(Landroid/os/IBinder;)V
        //   33: aload_3
        //   34: aload_2
        //   35: invokevirtual 53	android/os/Parcel:writeString	(Ljava/lang/String;)V
        //   38: aload_0
        //   39: getfield 15	com/google/android/gms/internal/zzbb$zza$zza:zzop	Landroid/os/IBinder;
        //   42: bipush 8
        //   44: aload_3
        //   45: aload 4
        //   47: iconst_0
        //   48: invokeinterface 39 5 0
        //   53: pop
        //   54: aload 4
        //   56: invokevirtual 42	android/os/Parcel:readException	()V
        //   59: aload 4
        //   61: invokevirtual 45	android/os/Parcel:readString	()Ljava/lang/String;
        //   64: astore 8
        //   66: aload 4
        //   68: invokevirtual 48	android/os/Parcel:recycle	()V
        //   71: aload_3
        //   72: invokevirtual 48	android/os/Parcel:recycle	()V
        //   75: aload 8
        //   77: areturn
        //   78: aconst_null
        //   79: astore 6
        //   81: goto -54 -> 27
        //   84: astore 5
        //   86: aload 4
        //   88: invokevirtual 48	android/os/Parcel:recycle	()V
        //   91: aload_3
        //   92: invokevirtual 48	android/os/Parcel:recycle	()V
        //   95: aload 5
        //   97: athrow
        // Local variable table:
        //   start	length	slot	name	signature
        //   0	98	0	this	zza
        //   0	98	1	paramzzd	zzd
        //   0	98	2	paramString	String
        //   3	89	3	localParcel1	Parcel
        //   7	80	4	localParcel2	Parcel
        //   84	12	5	localObject	Object
        //   25	55	6	localIBinder	IBinder
        //   64	12	8	str	String
        // Exception table:
        //   from	to	target	type
        //   9	15	84	finally
        //   19	27	84	finally
        //   27	66	84	finally
      }
      
      /* Error */
      public final boolean zza(zzd paramzzd)
        throws RemoteException
      {
        // Byte code:
        //   0: invokestatic 27	android/os/Parcel:obtain	()Landroid/os/Parcel;
        //   3: astore_2
        //   4: invokestatic 27	android/os/Parcel:obtain	()Landroid/os/Parcel;
        //   7: astore_3
        //   8: aload_2
        //   9: ldc 29
        //   11: invokevirtual 33	android/os/Parcel:writeInterfaceToken	(Ljava/lang/String;)V
        //   14: aload_1
        //   15: ifnull +63 -> 78
        //   18: aload_1
        //   19: invokeinterface 60 1 0
        //   24: astore 5
        //   26: aload_2
        //   27: aload 5
        //   29: invokevirtual 63	android/os/Parcel:writeStrongBinder	(Landroid/os/IBinder;)V
        //   32: aload_0
        //   33: getfield 15	com/google/android/gms/internal/zzbb$zza$zza:zzop	Landroid/os/IBinder;
        //   36: iconst_3
        //   37: aload_2
        //   38: aload_3
        //   39: iconst_0
        //   40: invokeinterface 39 5 0
        //   45: pop
        //   46: aload_3
        //   47: invokevirtual 42	android/os/Parcel:readException	()V
        //   50: aload_3
        //   51: invokevirtual 78	android/os/Parcel:readInt	()I
        //   54: istore 7
        //   56: iconst_0
        //   57: istore 8
        //   59: iload 7
        //   61: ifeq +6 -> 67
        //   64: iconst_1
        //   65: istore 8
        //   67: aload_3
        //   68: invokevirtual 48	android/os/Parcel:recycle	()V
        //   71: aload_2
        //   72: invokevirtual 48	android/os/Parcel:recycle	()V
        //   75: iload 8
        //   77: ireturn
        //   78: aconst_null
        //   79: astore 5
        //   81: goto -55 -> 26
        //   84: astore 4
        //   86: aload_3
        //   87: invokevirtual 48	android/os/Parcel:recycle	()V
        //   90: aload_2
        //   91: invokevirtual 48	android/os/Parcel:recycle	()V
        //   94: aload 4
        //   96: athrow
        // Local variable table:
        //   start	length	slot	name	signature
        //   0	97	0	this	zza
        //   0	97	1	paramzzd	zzd
        //   3	88	2	localParcel1	Parcel
        //   7	80	3	localParcel2	Parcel
        //   84	11	4	localObject	Object
        //   24	56	5	localIBinder	IBinder
        //   54	6	7	i	int
        //   57	19	8	bool	boolean
        // Exception table:
        //   from	to	target	type
        //   8	14	84	finally
        //   18	26	84	finally
        //   26	56	84	finally
      }
      
      /* Error */
      public final zzd zzb(zzd paramzzd1, zzd paramzzd2)
        throws RemoteException
      {
        // Byte code:
        //   0: invokestatic 27	android/os/Parcel:obtain	()Landroid/os/Parcel;
        //   3: astore_3
        //   4: invokestatic 27	android/os/Parcel:obtain	()Landroid/os/Parcel;
        //   7: astore 4
        //   9: aload_3
        //   10: ldc 29
        //   12: invokevirtual 33	android/os/Parcel:writeInterfaceToken	(Ljava/lang/String;)V
        //   15: aload_1
        //   16: ifnull +81 -> 97
        //   19: aload_1
        //   20: invokeinterface 60 1 0
        //   25: astore 6
        //   27: aload_3
        //   28: aload 6
        //   30: invokevirtual 63	android/os/Parcel:writeStrongBinder	(Landroid/os/IBinder;)V
        //   33: aconst_null
        //   34: astore 7
        //   36: aload_2
        //   37: ifnull +11 -> 48
        //   40: aload_2
        //   41: invokeinterface 60 1 0
        //   46: astore 7
        //   48: aload_3
        //   49: aload 7
        //   51: invokevirtual 63	android/os/Parcel:writeStrongBinder	(Landroid/os/IBinder;)V
        //   54: aload_0
        //   55: getfield 15	com/google/android/gms/internal/zzbb$zza$zza:zzop	Landroid/os/IBinder;
        //   58: bipush 10
        //   60: aload_3
        //   61: aload 4
        //   63: iconst_0
        //   64: invokeinterface 39 5 0
        //   69: pop
        //   70: aload 4
        //   72: invokevirtual 42	android/os/Parcel:readException	()V
        //   75: aload 4
        //   77: invokevirtual 66	android/os/Parcel:readStrongBinder	()Landroid/os/IBinder;
        //   80: invokestatic 72	com/google/android/gms/dynamic/zzd$zza:zzdb	(Landroid/os/IBinder;)Lcom/google/android/gms/dynamic/zzd;
        //   83: astore 9
        //   85: aload 4
        //   87: invokevirtual 48	android/os/Parcel:recycle	()V
        //   90: aload_3
        //   91: invokevirtual 48	android/os/Parcel:recycle	()V
        //   94: aload 9
        //   96: areturn
        //   97: aconst_null
        //   98: astore 6
        //   100: goto -73 -> 27
        //   103: astore 5
        //   105: aload 4
        //   107: invokevirtual 48	android/os/Parcel:recycle	()V
        //   110: aload_3
        //   111: invokevirtual 48	android/os/Parcel:recycle	()V
        //   114: aload 5
        //   116: athrow
        // Local variable table:
        //   start	length	slot	name	signature
        //   0	117	0	this	zza
        //   0	117	1	paramzzd1	zzd
        //   0	117	2	paramzzd2	zzd
        //   3	108	3	localParcel1	Parcel
        //   7	99	4	localParcel2	Parcel
        //   103	12	5	localObject	Object
        //   25	74	6	localIBinder1	IBinder
        //   34	16	7	localIBinder2	IBinder
        //   83	12	9	localzzd	zzd
        // Exception table:
        //   from	to	target	type
        //   9	15	103	finally
        //   19	27	103	finally
        //   27	33	103	finally
        //   40	48	103	finally
        //   48	85	103	finally
      }
      
      /* Error */
      public final boolean zzb(zzd paramzzd)
        throws RemoteException
      {
        // Byte code:
        //   0: invokestatic 27	android/os/Parcel:obtain	()Landroid/os/Parcel;
        //   3: astore_2
        //   4: invokestatic 27	android/os/Parcel:obtain	()Landroid/os/Parcel;
        //   7: astore_3
        //   8: aload_2
        //   9: ldc 29
        //   11: invokevirtual 33	android/os/Parcel:writeInterfaceToken	(Ljava/lang/String;)V
        //   14: aload_1
        //   15: ifnull +63 -> 78
        //   18: aload_1
        //   19: invokeinterface 60 1 0
        //   24: astore 5
        //   26: aload_2
        //   27: aload 5
        //   29: invokevirtual 63	android/os/Parcel:writeStrongBinder	(Landroid/os/IBinder;)V
        //   32: aload_0
        //   33: getfield 15	com/google/android/gms/internal/zzbb$zza$zza:zzop	Landroid/os/IBinder;
        //   36: iconst_4
        //   37: aload_2
        //   38: aload_3
        //   39: iconst_0
        //   40: invokeinterface 39 5 0
        //   45: pop
        //   46: aload_3
        //   47: invokevirtual 42	android/os/Parcel:readException	()V
        //   50: aload_3
        //   51: invokevirtual 78	android/os/Parcel:readInt	()I
        //   54: istore 7
        //   56: iconst_0
        //   57: istore 8
        //   59: iload 7
        //   61: ifeq +6 -> 67
        //   64: iconst_1
        //   65: istore 8
        //   67: aload_3
        //   68: invokevirtual 48	android/os/Parcel:recycle	()V
        //   71: aload_2
        //   72: invokevirtual 48	android/os/Parcel:recycle	()V
        //   75: iload 8
        //   77: ireturn
        //   78: aconst_null
        //   79: astore 5
        //   81: goto -55 -> 26
        //   84: astore 4
        //   86: aload_3
        //   87: invokevirtual 48	android/os/Parcel:recycle	()V
        //   90: aload_2
        //   91: invokevirtual 48	android/os/Parcel:recycle	()V
        //   94: aload 4
        //   96: athrow
        // Local variable table:
        //   start	length	slot	name	signature
        //   0	97	0	this	zza
        //   0	97	1	paramzzd	zzd
        //   3	88	2	localParcel1	Parcel
        //   7	80	3	localParcel2	Parcel
        //   84	11	4	localObject	Object
        //   24	56	5	localIBinder	IBinder
        //   54	6	7	i	int
        //   57	19	8	bool	boolean
        // Exception table:
        //   from	to	target	type
        //   8	14	84	finally
        //   18	26	84	finally
        //   26	56	84	finally
      }
      
      /* Error */
      public final boolean zzb(String paramString, boolean paramBoolean)
        throws RemoteException
      {
        // Byte code:
        //   0: iconst_1
        //   1: istore_3
        //   2: invokestatic 27	android/os/Parcel:obtain	()Landroid/os/Parcel;
        //   5: astore 4
        //   7: invokestatic 27	android/os/Parcel:obtain	()Landroid/os/Parcel;
        //   10: astore 5
        //   12: aload 4
        //   14: ldc 29
        //   16: invokevirtual 33	android/os/Parcel:writeInterfaceToken	(Ljava/lang/String;)V
        //   19: aload 4
        //   21: aload_1
        //   22: invokevirtual 53	android/os/Parcel:writeString	(Ljava/lang/String;)V
        //   25: iload_2
        //   26: ifeq +59 -> 85
        //   29: iload_3
        //   30: istore 7
        //   32: aload 4
        //   34: iload 7
        //   36: invokevirtual 84	android/os/Parcel:writeInt	(I)V
        //   39: aload_0
        //   40: getfield 15	com/google/android/gms/internal/zzbb$zza$zza:zzop	Landroid/os/IBinder;
        //   43: bipush 11
        //   45: aload 4
        //   47: aload 5
        //   49: iconst_0
        //   50: invokeinterface 39 5 0
        //   55: pop
        //   56: aload 5
        //   58: invokevirtual 42	android/os/Parcel:readException	()V
        //   61: aload 5
        //   63: invokevirtual 78	android/os/Parcel:readInt	()I
        //   66: istore 9
        //   68: iload 9
        //   70: ifeq +21 -> 91
        //   73: aload 5
        //   75: invokevirtual 48	android/os/Parcel:recycle	()V
        //   78: aload 4
        //   80: invokevirtual 48	android/os/Parcel:recycle	()V
        //   83: iload_3
        //   84: ireturn
        //   85: iconst_0
        //   86: istore 7
        //   88: goto -56 -> 32
        //   91: iconst_0
        //   92: istore_3
        //   93: goto -20 -> 73
        //   96: astore 6
        //   98: aload 5
        //   100: invokevirtual 48	android/os/Parcel:recycle	()V
        //   103: aload 4
        //   105: invokevirtual 48	android/os/Parcel:recycle	()V
        //   108: aload 6
        //   110: athrow
        // Local variable table:
        //   start	length	slot	name	signature
        //   0	111	0	this	zza
        //   0	111	1	paramString	String
        //   0	111	2	paramBoolean	boolean
        //   1	92	3	i	int
        //   5	99	4	localParcel1	Parcel
        //   10	89	5	localParcel2	Parcel
        //   96	13	6	localObject	Object
        //   30	5	7	j	int
        //   86	1	7	k	int
        //   66	3	9	m	int
        // Exception table:
        //   from	to	target	type
        //   12	25	96	finally
        //   32	68	96	finally
      }
      
      /* Error */
      public final String zzc(zzd paramzzd)
        throws RemoteException
      {
        // Byte code:
        //   0: invokestatic 27	android/os/Parcel:obtain	()Landroid/os/Parcel;
        //   3: astore_2
        //   4: invokestatic 27	android/os/Parcel:obtain	()Landroid/os/Parcel;
        //   7: astore_3
        //   8: aload_2
        //   9: ldc 29
        //   11: invokevirtual 33	android/os/Parcel:writeInterfaceToken	(Ljava/lang/String;)V
        //   14: aload_1
        //   15: ifnull +53 -> 68
        //   18: aload_1
        //   19: invokeinterface 60 1 0
        //   24: astore 5
        //   26: aload_2
        //   27: aload 5
        //   29: invokevirtual 63	android/os/Parcel:writeStrongBinder	(Landroid/os/IBinder;)V
        //   32: aload_0
        //   33: getfield 15	com/google/android/gms/internal/zzbb$zza$zza:zzop	Landroid/os/IBinder;
        //   36: bipush 7
        //   38: aload_2
        //   39: aload_3
        //   40: iconst_0
        //   41: invokeinterface 39 5 0
        //   46: pop
        //   47: aload_3
        //   48: invokevirtual 42	android/os/Parcel:readException	()V
        //   51: aload_3
        //   52: invokevirtual 45	android/os/Parcel:readString	()Ljava/lang/String;
        //   55: astore 7
        //   57: aload_3
        //   58: invokevirtual 48	android/os/Parcel:recycle	()V
        //   61: aload_2
        //   62: invokevirtual 48	android/os/Parcel:recycle	()V
        //   65: aload 7
        //   67: areturn
        //   68: aconst_null
        //   69: astore 5
        //   71: goto -45 -> 26
        //   74: astore 4
        //   76: aload_3
        //   77: invokevirtual 48	android/os/Parcel:recycle	()V
        //   80: aload_2
        //   81: invokevirtual 48	android/os/Parcel:recycle	()V
        //   84: aload 4
        //   86: athrow
        // Local variable table:
        //   start	length	slot	name	signature
        //   0	87	0	this	zza
        //   0	87	1	paramzzd	zzd
        //   3	78	2	localParcel1	Parcel
        //   7	70	3	localParcel2	Parcel
        //   74	11	4	localObject	Object
        //   24	46	5	localIBinder	IBinder
        //   55	11	7	str	String
        // Exception table:
        //   from	to	target	type
        //   8	14	74	finally
        //   18	26	74	finally
        //   26	57	74	finally
      }
      
      /* Error */
      public final void zzd(zzd paramzzd)
        throws RemoteException
      {
        // Byte code:
        //   0: invokestatic 27	android/os/Parcel:obtain	()Landroid/os/Parcel;
        //   3: astore_2
        //   4: invokestatic 27	android/os/Parcel:obtain	()Landroid/os/Parcel;
        //   7: astore_3
        //   8: aload_2
        //   9: ldc 29
        //   11: invokevirtual 33	android/os/Parcel:writeInterfaceToken	(Ljava/lang/String;)V
        //   14: aload_1
        //   15: ifnull +45 -> 60
        //   18: aload_1
        //   19: invokeinterface 60 1 0
        //   24: astore 5
        //   26: aload_2
        //   27: aload 5
        //   29: invokevirtual 63	android/os/Parcel:writeStrongBinder	(Landroid/os/IBinder;)V
        //   32: aload_0
        //   33: getfield 15	com/google/android/gms/internal/zzbb$zza$zza:zzop	Landroid/os/IBinder;
        //   36: bipush 9
        //   38: aload_2
        //   39: aload_3
        //   40: iconst_0
        //   41: invokeinterface 39 5 0
        //   46: pop
        //   47: aload_3
        //   48: invokevirtual 42	android/os/Parcel:readException	()V
        //   51: aload_3
        //   52: invokevirtual 48	android/os/Parcel:recycle	()V
        //   55: aload_2
        //   56: invokevirtual 48	android/os/Parcel:recycle	()V
        //   59: return
        //   60: aconst_null
        //   61: astore 5
        //   63: goto -37 -> 26
        //   66: astore 4
        //   68: aload_3
        //   69: invokevirtual 48	android/os/Parcel:recycle	()V
        //   72: aload_2
        //   73: invokevirtual 48	android/os/Parcel:recycle	()V
        //   76: aload 4
        //   78: athrow
        // Local variable table:
        //   start	length	slot	name	signature
        //   0	79	0	this	zza
        //   0	79	1	paramzzd	zzd
        //   3	70	2	localParcel1	Parcel
        //   7	62	3	localParcel2	Parcel
        //   66	11	4	localObject	Object
        //   24	38	5	localIBinder	IBinder
        // Exception table:
        //   from	to	target	type
        //   8	14	66	finally
        //   18	26	66	finally
        //   26	51	66	finally
      }
    }
  }
}


/* Location:           F:\apktool\apktool\Google_Play_Store6.0.5\classes-dex2jar.jar
 * Qualified Name:     com.google.android.gms.internal.zzbb
 * JD-Core Version:    0.7.0.1
 */