package com.google.android.gms.internal;

import android.support.v4.util.ArrayMap;
import com.google.android.gms.ads.internal.zze;
import java.util.Collections;
import java.util.Map;

@zzhb
public final class zzds
  implements zzdm
{
  static final Map<String, Integer> zzzD;
  private final zze zzzB;
  private final zzfn zzzC;
  
  static
  {
    Integer localInteger1 = Integer.valueOf(1);
    Integer localInteger2 = Integer.valueOf(2);
    Integer localInteger3 = Integer.valueOf(3);
    Integer localInteger4 = Integer.valueOf(4);
    Integer localInteger5 = Integer.valueOf(5);
    Integer localInteger6 = Integer.valueOf(6);
    ArrayMap localArrayMap = new ArrayMap(6);
    localArrayMap.put("resize", localInteger1);
    localArrayMap.put("playVideo", localInteger2);
    localArrayMap.put("storePicture", localInteger3);
    localArrayMap.put("createCalendarEvent", localInteger4);
    localArrayMap.put("setOrientationProperties", localInteger5);
    localArrayMap.put("closeResizedAd", localInteger6);
    zzzD = Collections.unmodifiableMap(localArrayMap);
  }
  
  public zzds(zze paramzze, zzfn paramzzfn)
  {
    this.zzzB = paramzze;
    this.zzzC = paramzzfn;
  }
  
  /* Error */
  public final void zza(zzjo paramzzjo, Map<String, String> paramMap)
  {
    // Byte code:
    //   0: iconst_m1
    //   1: istore_3
    //   2: aload_2
    //   3: ldc 69
    //   5: invokeinterface 73 2 0
    //   10: checkcast 75	java/lang/String
    //   13: astore 4
    //   15: getstatic 54	com/google/android/gms/internal/zzds:zzzD	Ljava/util/Map;
    //   18: aload 4
    //   20: invokeinterface 73 2 0
    //   25: checkcast 18	java/lang/Integer
    //   28: invokevirtual 79	java/lang/Integer:intValue	()I
    //   31: istore 5
    //   33: iload 5
    //   35: iconst_5
    //   36: if_icmpeq +26 -> 62
    //   39: aload_0
    //   40: getfield 59	com/google/android/gms/internal/zzds:zzzB	Lcom/google/android/gms/ads/internal/zze;
    //   43: ifnull +19 -> 62
    //   46: aload_0
    //   47: getfield 59	com/google/android/gms/internal/zzds:zzzB	Lcom/google/android/gms/ads/internal/zze;
    //   50: invokevirtual 85	com/google/android/gms/ads/internal/zze:zzbs	()Z
    //   53: ifne +9 -> 62
    //   56: ldc 87
    //   58: invokestatic 93	com/google/android/gms/ads/internal/util/client/zzb:d	(Ljava/lang/String;)V
    //   61: return
    //   62: iload 5
    //   64: tableswitch	default:+40 -> 104, 1:+46->110, 2:+40->104, 3:+2501->2565, 4:+2333->2397, 5:+2786->2850, 6:+2897->2961
    //   105: swap
    //   106: invokestatic 98	com/google/android/gms/ads/internal/util/client/zzb:i	(Ljava/lang/String;)V
    //   109: return
    //   110: aload_0
    //   111: getfield 61	com/google/android/gms/internal/zzds:zzzC	Lcom/google/android/gms/internal/zzfn;
    //   114: astore 27
    //   116: aload 27
    //   118: getfield 104	com/google/android/gms/internal/zzfn:zzqp	Ljava/lang/Object;
    //   121: astore 28
    //   123: aload 28
    //   125: monitorenter
    //   126: aload 27
    //   128: getfield 108	com/google/android/gms/internal/zzfn:zzCH	Landroid/app/Activity;
    //   131: ifnonnull +22 -> 153
    //   134: aload 27
    //   136: ldc 110
    //   138: invokevirtual 113	com/google/android/gms/internal/zzfn:zzal	(Ljava/lang/String;)V
    //   141: aload 28
    //   143: monitorexit
    //   144: return
    //   145: astore 29
    //   147: aload 28
    //   149: monitorexit
    //   150: aload 29
    //   152: athrow
    //   153: aload 27
    //   155: getfield 117	com/google/android/gms/internal/zzfn:zzpX	Lcom/google/android/gms/internal/zzjo;
    //   158: invokeinterface 123 1 0
    //   163: ifnonnull +14 -> 177
    //   166: aload 27
    //   168: ldc 125
    //   170: invokevirtual 113	com/google/android/gms/internal/zzfn:zzal	(Ljava/lang/String;)V
    //   173: aload 28
    //   175: monitorexit
    //   176: return
    //   177: aload 27
    //   179: getfield 117	com/google/android/gms/internal/zzfn:zzpX	Lcom/google/android/gms/internal/zzjo;
    //   182: invokeinterface 123 1 0
    //   187: getfield 131	com/google/android/gms/ads/internal/client/AdSizeParcel:zzuB	Z
    //   190: ifeq +14 -> 204
    //   193: aload 27
    //   195: ldc 133
    //   197: invokevirtual 113	com/google/android/gms/internal/zzfn:zzal	(Ljava/lang/String;)V
    //   200: aload 28
    //   202: monitorexit
    //   203: return
    //   204: aload 27
    //   206: getfield 117	com/google/android/gms/internal/zzfn:zzpX	Lcom/google/android/gms/internal/zzjo;
    //   209: invokeinterface 136 1 0
    //   214: ifeq +14 -> 228
    //   217: aload 27
    //   219: ldc 138
    //   221: invokevirtual 113	com/google/android/gms/internal/zzfn:zzal	(Ljava/lang/String;)V
    //   224: aload 28
    //   226: monitorexit
    //   227: return
    //   228: aload_2
    //   229: ldc 140
    //   231: invokeinterface 73 2 0
    //   236: checkcast 142	java/lang/CharSequence
    //   239: invokestatic 148	android/text/TextUtils:isEmpty	(Ljava/lang/CharSequence;)Z
    //   242: ifne +26 -> 268
    //   245: invokestatic 154	com/google/android/gms/ads/internal/zzp:zzbI	()Lcom/google/android/gms/internal/zziq;
    //   248: pop
    //   249: aload 27
    //   251: aload_2
    //   252: ldc 140
    //   254: invokeinterface 73 2 0
    //   259: checkcast 75	java/lang/String
    //   262: invokestatic 160	com/google/android/gms/internal/zziq:zzaA	(Ljava/lang/String;)I
    //   265: putfield 164	com/google/android/gms/internal/zzfn:zzoM	I
    //   268: aload_2
    //   269: ldc 166
    //   271: invokeinterface 73 2 0
    //   276: checkcast 142	java/lang/CharSequence
    //   279: invokestatic 148	android/text/TextUtils:isEmpty	(Ljava/lang/CharSequence;)Z
    //   282: ifne +26 -> 308
    //   285: invokestatic 154	com/google/android/gms/ads/internal/zzp:zzbI	()Lcom/google/android/gms/internal/zziq;
    //   288: pop
    //   289: aload 27
    //   291: aload_2
    //   292: ldc 166
    //   294: invokeinterface 73 2 0
    //   299: checkcast 75	java/lang/String
    //   302: invokestatic 160	com/google/android/gms/internal/zziq:zzaA	(Ljava/lang/String;)I
    //   305: putfield 169	com/google/android/gms/internal/zzfn:zzoN	I
    //   308: aload_2
    //   309: ldc 171
    //   311: invokeinterface 73 2 0
    //   316: checkcast 142	java/lang/CharSequence
    //   319: invokestatic 148	android/text/TextUtils:isEmpty	(Ljava/lang/CharSequence;)Z
    //   322: ifne +26 -> 348
    //   325: invokestatic 154	com/google/android/gms/ads/internal/zzp:zzbI	()Lcom/google/android/gms/internal/zziq;
    //   328: pop
    //   329: aload 27
    //   331: aload_2
    //   332: ldc 171
    //   334: invokeinterface 73 2 0
    //   339: checkcast 75	java/lang/String
    //   342: invokestatic 160	com/google/android/gms/internal/zziq:zzaA	(Ljava/lang/String;)I
    //   345: putfield 174	com/google/android/gms/internal/zzfn:zzCF	I
    //   348: aload_2
    //   349: ldc 176
    //   351: invokeinterface 73 2 0
    //   356: checkcast 142	java/lang/CharSequence
    //   359: invokestatic 148	android/text/TextUtils:isEmpty	(Ljava/lang/CharSequence;)Z
    //   362: ifne +26 -> 388
    //   365: invokestatic 154	com/google/android/gms/ads/internal/zzp:zzbI	()Lcom/google/android/gms/internal/zziq;
    //   368: pop
    //   369: aload 27
    //   371: aload_2
    //   372: ldc 176
    //   374: invokeinterface 73 2 0
    //   379: checkcast 75	java/lang/String
    //   382: invokestatic 160	com/google/android/gms/internal/zziq:zzaA	(Ljava/lang/String;)I
    //   385: putfield 179	com/google/android/gms/internal/zzfn:zzCG	I
    //   388: aload_2
    //   389: ldc 181
    //   391: invokeinterface 73 2 0
    //   396: checkcast 142	java/lang/CharSequence
    //   399: invokestatic 148	android/text/TextUtils:isEmpty	(Ljava/lang/CharSequence;)Z
    //   402: ifne +22 -> 424
    //   405: aload 27
    //   407: aload_2
    //   408: ldc 181
    //   410: invokeinterface 73 2 0
    //   415: checkcast 75	java/lang/String
    //   418: invokestatic 187	java/lang/Boolean:parseBoolean	(Ljava/lang/String;)Z
    //   421: putfield 190	com/google/android/gms/internal/zzfn:zzCC	Z
    //   424: aload_2
    //   425: ldc 192
    //   427: invokeinterface 73 2 0
    //   432: checkcast 75	java/lang/String
    //   435: astore 30
    //   437: aload 30
    //   439: invokestatic 148	android/text/TextUtils:isEmpty	(Ljava/lang/CharSequence;)Z
    //   442: ifne +10 -> 452
    //   445: aload 27
    //   447: aload 30
    //   449: putfield 196	com/google/android/gms/internal/zzfn:zzCB	Ljava/lang/String;
    //   452: aload 27
    //   454: getfield 164	com/google/android/gms/internal/zzfn:zzoM	I
    //   457: iflt +2527 -> 2984
    //   460: aload 27
    //   462: getfield 169	com/google/android/gms/internal/zzfn:zzoN	I
    //   465: iflt +2519 -> 2984
    //   468: iconst_1
    //   469: istore 31
    //   471: iload 31
    //   473: ifne +14 -> 487
    //   476: aload 27
    //   478: ldc 198
    //   480: invokevirtual 113	com/google/android/gms/internal/zzfn:zzal	(Ljava/lang/String;)V
    //   483: aload 28
    //   485: monitorexit
    //   486: return
    //   487: aload 27
    //   489: getfield 108	com/google/android/gms/internal/zzfn:zzCH	Landroid/app/Activity;
    //   492: invokevirtual 204	android/app/Activity:getWindow	()Landroid/view/Window;
    //   495: astore 32
    //   497: aload 32
    //   499: ifnull +11 -> 510
    //   502: aload 32
    //   504: invokevirtual 210	android/view/Window:getDecorView	()Landroid/view/View;
    //   507: ifnonnull +14 -> 521
    //   510: aload 27
    //   512: ldc 212
    //   514: invokevirtual 113	com/google/android/gms/internal/zzfn:zzal	(Ljava/lang/String;)V
    //   517: aload 28
    //   519: monitorexit
    //   520: return
    //   521: invokestatic 154	com/google/android/gms/ads/internal/zzp:zzbI	()Lcom/google/android/gms/internal/zziq;
    //   524: aload 27
    //   526: getfield 108	com/google/android/gms/internal/zzfn:zzCH	Landroid/app/Activity;
    //   529: invokevirtual 216	com/google/android/gms/internal/zziq:zzh	(Landroid/app/Activity;)[I
    //   532: astore 33
    //   534: invokestatic 154	com/google/android/gms/ads/internal/zzp:zzbI	()Lcom/google/android/gms/internal/zziq;
    //   537: aload 27
    //   539: getfield 108	com/google/android/gms/internal/zzfn:zzCH	Landroid/app/Activity;
    //   542: invokevirtual 219	com/google/android/gms/internal/zziq:zzj	(Landroid/app/Activity;)[I
    //   545: astore 34
    //   547: aload 33
    //   549: iconst_0
    //   550: iaload
    //   551: istore 35
    //   553: aload 33
    //   555: iconst_1
    //   556: iaload
    //   557: istore 36
    //   559: aload 27
    //   561: getfield 164	com/google/android/gms/internal/zzfn:zzoM	I
    //   564: bipush 50
    //   566: if_icmplt +13 -> 579
    //   569: aload 27
    //   571: getfield 164	com/google/android/gms/internal/zzfn:zzoM	I
    //   574: iload 35
    //   576: if_icmple +30 -> 606
    //   579: ldc 221
    //   581: invokestatic 224	com/google/android/gms/ads/internal/util/client/zzb:w	(Ljava/lang/String;)V
    //   584: iconst_0
    //   585: istore 37
    //   587: goto +2403 -> 2990
    //   590: aload 38
    //   592: ifnonnull +785 -> 1377
    //   595: aload 27
    //   597: ldc 226
    //   599: invokevirtual 113	com/google/android/gms/internal/zzfn:zzal	(Ljava/lang/String;)V
    //   602: aload 28
    //   604: monitorexit
    //   605: return
    //   606: aload 27
    //   608: getfield 169	com/google/android/gms/internal/zzfn:zzoN	I
    //   611: bipush 50
    //   613: if_icmplt +13 -> 626
    //   616: aload 27
    //   618: getfield 169	com/google/android/gms/internal/zzfn:zzoN	I
    //   621: iload 36
    //   623: if_icmple +14 -> 637
    //   626: ldc 228
    //   628: invokestatic 224	com/google/android/gms/ads/internal/util/client/zzb:w	(Ljava/lang/String;)V
    //   631: iconst_0
    //   632: istore 37
    //   634: goto +2356 -> 2990
    //   637: aload 27
    //   639: getfield 169	com/google/android/gms/internal/zzfn:zzoN	I
    //   642: iload 36
    //   644: if_icmpne +24 -> 668
    //   647: aload 27
    //   649: getfield 164	com/google/android/gms/internal/zzfn:zzoM	I
    //   652: iload 35
    //   654: if_icmpne +14 -> 668
    //   657: ldc 230
    //   659: invokestatic 224	com/google/android/gms/ads/internal/util/client/zzb:w	(Ljava/lang/String;)V
    //   662: iconst_0
    //   663: istore 37
    //   665: goto +2325 -> 2990
    //   668: aload 27
    //   670: getfield 190	com/google/android/gms/internal/zzfn:zzCC	Z
    //   673: ifeq +2377 -> 3050
    //   676: aload 27
    //   678: getfield 196	com/google/android/gms/internal/zzfn:zzCB	Ljava/lang/String;
    //   681: astore 74
    //   683: aload 74
    //   685: invokevirtual 233	java/lang/String:hashCode	()I
    //   688: lookupswitch	default:+2313->3001, -1364013995:+166->854, -1012429441:+134->822, -655373719:+182->870, 1163912186:+214->902, 1288627767:+198->886, 1755462605:+150->838
    //   749: <illegal opcode>
    //   750: aload 27
    //   752: getfield 236	com/google/android/gms/internal/zzfn:zzCD	I
    //   755: aload 27
    //   757: getfield 174	com/google/android/gms/internal/zzfn:zzCF	I
    //   760: iadd
    //   761: aload 27
    //   763: getfield 164	com/google/android/gms/internal/zzfn:zzoM	I
    //   766: iadd
    //   767: iadd
    //   768: istore 76
    //   770: aload 27
    //   772: getfield 239	com/google/android/gms/internal/zzfn:zzCE	I
    //   775: aload 27
    //   777: getfield 179	com/google/android/gms/internal/zzfn:zzCG	I
    //   780: iadd
    //   781: istore 77
    //   783: iload 76
    //   785: iflt +2259 -> 3044
    //   788: iload 76
    //   790: bipush 50
    //   792: iadd
    //   793: iload 35
    //   795: if_icmpgt +2249 -> 3044
    //   798: iload 77
    //   800: aload 34
    //   802: iconst_0
    //   803: iaload
    //   804: if_icmplt +2240 -> 3044
    //   807: iload 77
    //   809: bipush 50
    //   811: iadd
    //   812: aload 34
    //   814: iconst_1
    //   815: iaload
    //   816: if_icmple +2234 -> 3050
    //   819: goto +2225 -> 3044
    //   822: aload 74
    //   824: ldc 241
    //   826: invokevirtual 245	java/lang/String:equals	(Ljava/lang/Object;)Z
    //   829: ifeq +2172 -> 3001
    //   832: iconst_0
    //   833: istore 75
    //   835: goto +2169 -> 3004
    //   838: aload 74
    //   840: ldc 247
    //   842: invokevirtual 245	java/lang/String:equals	(Ljava/lang/Object;)Z
    //   845: ifeq +2156 -> 3001
    //   848: iconst_1
    //   849: istore 75
    //   851: goto +2153 -> 3004
    //   854: aload 74
    //   856: ldc 249
    //   858: invokevirtual 245	java/lang/String:equals	(Ljava/lang/Object;)Z
    //   861: ifeq +2140 -> 3001
    //   864: iconst_2
    //   865: istore 75
    //   867: goto +2137 -> 3004
    //   870: aload 74
    //   872: ldc 251
    //   874: invokevirtual 245	java/lang/String:equals	(Ljava/lang/Object;)Z
    //   877: ifeq +2124 -> 3001
    //   880: iconst_3
    //   881: istore 75
    //   883: goto +2121 -> 3004
    //   886: aload 74
    //   888: ldc 253
    //   890: invokevirtual 245	java/lang/String:equals	(Ljava/lang/Object;)Z
    //   893: ifeq +2108 -> 3001
    //   896: iconst_4
    //   897: istore 75
    //   899: goto +2105 -> 3004
    //   902: aload 74
    //   904: ldc 255
    //   906: invokevirtual 245	java/lang/String:equals	(Ljava/lang/Object;)Z
    //   909: ifeq +2092 -> 3001
    //   912: iconst_5
    //   913: istore 75
    //   915: goto +2089 -> 3004
    //   918: aload 27
    //   920: getfield 236	com/google/android/gms/internal/zzfn:zzCD	I
    //   923: aload 27
    //   925: getfield 174	com/google/android/gms/internal/zzfn:zzCF	I
    //   928: iadd
    //   929: istore 76
    //   931: aload 27
    //   933: getfield 239	com/google/android/gms/internal/zzfn:zzCE	I
    //   936: aload 27
    //   938: getfield 179	com/google/android/gms/internal/zzfn:zzCG	I
    //   941: iadd
    //   942: istore 77
    //   944: goto -161 -> 783
    //   947: bipush 231
    //   949: aload 27
    //   951: getfield 236	com/google/android/gms/internal/zzfn:zzCD	I
    //   954: aload 27
    //   956: getfield 174	com/google/android/gms/internal/zzfn:zzCF	I
    //   959: iadd
    //   960: aload 27
    //   962: getfield 164	com/google/android/gms/internal/zzfn:zzoM	I
    //   965: iconst_2
    //   966: idiv
    //   967: iadd
    //   968: iadd
    //   969: istore 76
    //   971: aload 27
    //   973: getfield 239	com/google/android/gms/internal/zzfn:zzCE	I
    //   976: aload 27
    //   978: getfield 179	com/google/android/gms/internal/zzfn:zzCG	I
    //   981: iadd
    //   982: istore 77
    //   984: goto -201 -> 783
    //   987: bipush 231
    //   989: aload 27
    //   991: getfield 236	com/google/android/gms/internal/zzfn:zzCD	I
    //   994: aload 27
    //   996: getfield 174	com/google/android/gms/internal/zzfn:zzCF	I
    //   999: iadd
    //   1000: aload 27
    //   1002: getfield 164	com/google/android/gms/internal/zzfn:zzoM	I
    //   1005: iconst_2
    //   1006: idiv
    //   1007: iadd
    //   1008: iadd
    //   1009: istore 76
    //   1011: bipush 231
    //   1013: aload 27
    //   1015: getfield 239	com/google/android/gms/internal/zzfn:zzCE	I
    //   1018: aload 27
    //   1020: getfield 179	com/google/android/gms/internal/zzfn:zzCG	I
    //   1023: iadd
    //   1024: aload 27
    //   1026: getfield 169	com/google/android/gms/internal/zzfn:zzoN	I
    //   1029: iconst_2
    //   1030: idiv
    //   1031: iadd
    //   1032: iadd
    //   1033: istore 77
    //   1035: goto -252 -> 783
    //   1038: aload 27
    //   1040: getfield 236	com/google/android/gms/internal/zzfn:zzCD	I
    //   1043: aload 27
    //   1045: getfield 174	com/google/android/gms/internal/zzfn:zzCF	I
    //   1048: iadd
    //   1049: istore 76
    //   1051: bipush 206
    //   1053: aload 27
    //   1055: getfield 239	com/google/android/gms/internal/zzfn:zzCE	I
    //   1058: aload 27
    //   1060: getfield 179	com/google/android/gms/internal/zzfn:zzCG	I
    //   1063: iadd
    //   1064: aload 27
    //   1066: getfield 169	com/google/android/gms/internal/zzfn:zzoN	I
    //   1069: iadd
    //   1070: iadd
    //   1071: istore 77
    //   1073: goto -290 -> 783
    //   1076: bipush 231
    //   1078: aload 27
    //   1080: getfield 236	com/google/android/gms/internal/zzfn:zzCD	I
    //   1083: aload 27
    //   1085: getfield 174	com/google/android/gms/internal/zzfn:zzCF	I
    //   1088: iadd
    //   1089: aload 27
    //   1091: getfield 164	com/google/android/gms/internal/zzfn:zzoM	I
    //   1094: iconst_2
    //   1095: idiv
    //   1096: iadd
    //   1097: iadd
    //   1098: istore 76
    //   1100: bipush 206
    //   1102: aload 27
    //   1104: getfield 239	com/google/android/gms/internal/zzfn:zzCE	I
    //   1107: aload 27
    //   1109: getfield 179	com/google/android/gms/internal/zzfn:zzCG	I
    //   1112: iadd
    //   1113: aload 27
    //   1115: getfield 169	com/google/android/gms/internal/zzfn:zzoN	I
    //   1118: iadd
    //   1119: iadd
    //   1120: istore 77
    //   1122: goto -339 -> 783
    //   1125: bipush 206
    //   1127: aload 27
    //   1129: getfield 236	com/google/android/gms/internal/zzfn:zzCD	I
    //   1132: aload 27
    //   1134: getfield 174	com/google/android/gms/internal/zzfn:zzCF	I
    //   1137: iadd
    //   1138: aload 27
    //   1140: getfield 164	com/google/android/gms/internal/zzfn:zzoM	I
    //   1143: iadd
    //   1144: iadd
    //   1145: istore 76
    //   1147: bipush 206
    //   1149: aload 27
    //   1151: getfield 239	com/google/android/gms/internal/zzfn:zzCE	I
    //   1154: aload 27
    //   1156: getfield 179	com/google/android/gms/internal/zzfn:zzCG	I
    //   1159: iadd
    //   1160: aload 27
    //   1162: getfield 169	com/google/android/gms/internal/zzfn:zzoN	I
    //   1165: iadd
    //   1166: iadd
    //   1167: istore 77
    //   1169: goto -386 -> 783
    //   1172: aload 27
    //   1174: getfield 190	com/google/android/gms/internal/zzfn:zzCC	Z
    //   1177: ifeq +45 -> 1222
    //   1180: iconst_2
    //   1181: newarray int
    //   1183: astore 73
    //   1185: aload 73
    //   1187: iconst_0
    //   1188: aload 27
    //   1190: getfield 236	com/google/android/gms/internal/zzfn:zzCD	I
    //   1193: aload 27
    //   1195: getfield 174	com/google/android/gms/internal/zzfn:zzCF	I
    //   1198: iadd
    //   1199: iastore
    //   1200: aload 73
    //   1202: iconst_1
    //   1203: aload 27
    //   1205: getfield 239	com/google/android/gms/internal/zzfn:zzCE	I
    //   1208: aload 27
    //   1210: getfield 179	com/google/android/gms/internal/zzfn:zzCG	I
    //   1213: iadd
    //   1214: iastore
    //   1215: aload 73
    //   1217: astore 38
    //   1219: goto -629 -> 590
    //   1222: invokestatic 154	com/google/android/gms/ads/internal/zzp:zzbI	()Lcom/google/android/gms/internal/zziq;
    //   1225: aload 27
    //   1227: getfield 108	com/google/android/gms/internal/zzfn:zzCH	Landroid/app/Activity;
    //   1230: invokevirtual 216	com/google/android/gms/internal/zziq:zzh	(Landroid/app/Activity;)[I
    //   1233: astore 66
    //   1235: invokestatic 154	com/google/android/gms/ads/internal/zzp:zzbI	()Lcom/google/android/gms/internal/zziq;
    //   1238: aload 27
    //   1240: getfield 108	com/google/android/gms/internal/zzfn:zzCH	Landroid/app/Activity;
    //   1243: invokevirtual 219	com/google/android/gms/internal/zziq:zzj	(Landroid/app/Activity;)[I
    //   1246: astore 67
    //   1248: aload 66
    //   1250: iconst_0
    //   1251: iaload
    //   1252: istore 68
    //   1254: aload 27
    //   1256: getfield 236	com/google/android/gms/internal/zzfn:zzCD	I
    //   1259: aload 27
    //   1261: getfield 174	com/google/android/gms/internal/zzfn:zzCF	I
    //   1264: iadd
    //   1265: istore 69
    //   1267: aload 27
    //   1269: getfield 239	com/google/android/gms/internal/zzfn:zzCE	I
    //   1272: aload 27
    //   1274: getfield 179	com/google/android/gms/internal/zzfn:zzCG	I
    //   1277: iadd
    //   1278: istore 70
    //   1280: iload 69
    //   1282: ifge +39 -> 1321
    //   1285: iconst_0
    //   1286: istore 71
    //   1288: iload 70
    //   1290: aload 67
    //   1292: iconst_0
    //   1293: iaload
    //   1294: if_icmpge +53 -> 1347
    //   1297: aload 67
    //   1299: iconst_0
    //   1300: iaload
    //   1301: istore 72
    //   1303: iconst_2
    //   1304: newarray int
    //   1306: dup
    //   1307: iconst_0
    //   1308: iload 71
    //   1310: iastore
    //   1311: dup
    //   1312: iconst_1
    //   1313: iload 72
    //   1315: iastore
    //   1316: astore 38
    //   1318: goto -728 -> 590
    //   1321: iload 69
    //   1323: aload 27
    //   1325: getfield 164	com/google/android/gms/internal/zzfn:zzoM	I
    //   1328: iadd
    //   1329: iload 68
    //   1331: if_icmple +1646 -> 2977
    //   1334: iload 68
    //   1336: aload 27
    //   1338: getfield 164	com/google/android/gms/internal/zzfn:zzoM	I
    //   1341: isub
    //   1342: istore 71
    //   1344: goto -56 -> 1288
    //   1347: iload 70
    //   1349: aload 27
    //   1351: getfield 169	com/google/android/gms/internal/zzfn:zzoN	I
    //   1354: iadd
    //   1355: aload 67
    //   1357: iconst_1
    //   1358: iaload
    //   1359: if_icmple +1611 -> 2970
    //   1362: aload 67
    //   1364: iconst_1
    //   1365: iaload
    //   1366: aload 27
    //   1368: getfield 169	com/google/android/gms/internal/zzfn:zzoN	I
    //   1371: isub
    //   1372: istore 72
    //   1374: goto -71 -> 1303
    //   1377: invokestatic 261	com/google/android/gms/ads/internal/client/zzl:zzcX	()Lcom/google/android/gms/ads/internal/util/client/zza;
    //   1380: pop
    //   1381: aload 27
    //   1383: getfield 108	com/google/android/gms/internal/zzfn:zzCH	Landroid/app/Activity;
    //   1386: aload 27
    //   1388: getfield 164	com/google/android/gms/internal/zzfn:zzoM	I
    //   1391: invokestatic 267	com/google/android/gms/ads/internal/util/client/zza:zzb	(Landroid/content/Context;I)I
    //   1394: istore 40
    //   1396: invokestatic 261	com/google/android/gms/ads/internal/client/zzl:zzcX	()Lcom/google/android/gms/ads/internal/util/client/zza;
    //   1399: pop
    //   1400: aload 27
    //   1402: getfield 108	com/google/android/gms/internal/zzfn:zzCH	Landroid/app/Activity;
    //   1405: aload 27
    //   1407: getfield 169	com/google/android/gms/internal/zzfn:zzoN	I
    //   1410: invokestatic 267	com/google/android/gms/ads/internal/util/client/zza:zzb	(Landroid/content/Context;I)I
    //   1413: istore 42
    //   1415: aload 27
    //   1417: getfield 117	com/google/android/gms/internal/zzfn:zzpX	Lcom/google/android/gms/internal/zzjo;
    //   1420: invokeinterface 270 1 0
    //   1425: invokevirtual 276	android/view/View:getParent	()Landroid/view/ViewParent;
    //   1428: astore 43
    //   1430: aload 43
    //   1432: ifnull +651 -> 2083
    //   1435: aload 43
    //   1437: instanceof 278
    //   1440: ifeq +643 -> 2083
    //   1443: aload 43
    //   1445: checkcast 278	android/view/ViewGroup
    //   1448: aload 27
    //   1450: getfield 117	com/google/android/gms/internal/zzfn:zzpX	Lcom/google/android/gms/internal/zzjo;
    //   1453: invokeinterface 270 1 0
    //   1458: invokevirtual 282	android/view/ViewGroup:removeView	(Landroid/view/View;)V
    //   1461: aload 27
    //   1463: getfield 286	com/google/android/gms/internal/zzfn:zzCL	Landroid/widget/PopupWindow;
    //   1466: ifnonnull +606 -> 2072
    //   1469: aload 27
    //   1471: aload 43
    //   1473: checkcast 278	android/view/ViewGroup
    //   1476: putfield 290	com/google/android/gms/internal/zzfn:zzCN	Landroid/view/ViewGroup;
    //   1479: invokestatic 154	com/google/android/gms/ads/internal/zzp:zzbI	()Lcom/google/android/gms/internal/zziq;
    //   1482: pop
    //   1483: aload 27
    //   1485: getfield 117	com/google/android/gms/internal/zzfn:zzpX	Lcom/google/android/gms/internal/zzjo;
    //   1488: invokeinterface 270 1 0
    //   1493: invokestatic 294	com/google/android/gms/internal/zziq:zzl	(Landroid/view/View;)Landroid/graphics/Bitmap;
    //   1496: astore 65
    //   1498: aload 27
    //   1500: new 296	android/widget/ImageView
    //   1503: dup
    //   1504: aload 27
    //   1506: getfield 108	com/google/android/gms/internal/zzfn:zzCH	Landroid/app/Activity;
    //   1509: invokespecial 299	android/widget/ImageView:<init>	(Landroid/content/Context;)V
    //   1512: putfield 303	com/google/android/gms/internal/zzfn:zzCI	Landroid/widget/ImageView;
    //   1515: aload 27
    //   1517: getfield 303	com/google/android/gms/internal/zzfn:zzCI	Landroid/widget/ImageView;
    //   1520: aload 65
    //   1522: invokevirtual 307	android/widget/ImageView:setImageBitmap	(Landroid/graphics/Bitmap;)V
    //   1525: aload 27
    //   1527: aload 27
    //   1529: getfield 117	com/google/android/gms/internal/zzfn:zzpX	Lcom/google/android/gms/internal/zzjo;
    //   1532: invokeinterface 123 1 0
    //   1537: putfield 311	com/google/android/gms/internal/zzfn:zzBH	Lcom/google/android/gms/ads/internal/client/AdSizeParcel;
    //   1540: aload 27
    //   1542: getfield 290	com/google/android/gms/internal/zzfn:zzCN	Landroid/view/ViewGroup;
    //   1545: aload 27
    //   1547: getfield 303	com/google/android/gms/internal/zzfn:zzCI	Landroid/widget/ImageView;
    //   1550: invokevirtual 314	android/view/ViewGroup:addView	(Landroid/view/View;)V
    //   1553: aload 27
    //   1555: new 316	android/widget/RelativeLayout
    //   1558: dup
    //   1559: aload 27
    //   1561: getfield 108	com/google/android/gms/internal/zzfn:zzCH	Landroid/app/Activity;
    //   1564: invokespecial 317	android/widget/RelativeLayout:<init>	(Landroid/content/Context;)V
    //   1567: putfield 321	com/google/android/gms/internal/zzfn:zzCM	Landroid/widget/RelativeLayout;
    //   1570: aload 27
    //   1572: getfield 321	com/google/android/gms/internal/zzfn:zzCM	Landroid/widget/RelativeLayout;
    //   1575: iconst_0
    //   1576: invokevirtual 324	android/widget/RelativeLayout:setBackgroundColor	(I)V
    //   1579: aload 27
    //   1581: getfield 321	com/google/android/gms/internal/zzfn:zzCM	Landroid/widget/RelativeLayout;
    //   1584: new 326	android/view/ViewGroup$LayoutParams
    //   1587: dup
    //   1588: iload 40
    //   1590: iload 42
    //   1592: invokespecial 329	android/view/ViewGroup$LayoutParams:<init>	(II)V
    //   1595: invokevirtual 333	android/widget/RelativeLayout:setLayoutParams	(Landroid/view/ViewGroup$LayoutParams;)V
    //   1598: invokestatic 154	com/google/android/gms/ads/internal/zzp:zzbI	()Lcom/google/android/gms/internal/zziq;
    //   1601: pop
    //   1602: aload 27
    //   1604: aload 27
    //   1606: getfield 321	com/google/android/gms/internal/zzfn:zzCM	Landroid/widget/RelativeLayout;
    //   1609: iload 40
    //   1611: iload 42
    //   1613: invokestatic 337	com/google/android/gms/internal/zziq:zza$490f73c3	(Landroid/view/View;II)Landroid/widget/PopupWindow;
    //   1616: putfield 286	com/google/android/gms/internal/zzfn:zzCL	Landroid/widget/PopupWindow;
    //   1619: aload 27
    //   1621: getfield 286	com/google/android/gms/internal/zzfn:zzCL	Landroid/widget/PopupWindow;
    //   1624: iconst_1
    //   1625: invokevirtual 343	android/widget/PopupWindow:setOutsideTouchable	(Z)V
    //   1628: aload 27
    //   1630: getfield 286	com/google/android/gms/internal/zzfn:zzCL	Landroid/widget/PopupWindow;
    //   1633: iconst_1
    //   1634: invokevirtual 346	android/widget/PopupWindow:setTouchable	(Z)V
    //   1637: aload 27
    //   1639: getfield 286	com/google/android/gms/internal/zzfn:zzCL	Landroid/widget/PopupWindow;
    //   1642: astore 45
    //   1644: aload 27
    //   1646: getfield 190	com/google/android/gms/internal/zzfn:zzCC	Z
    //   1649: ifne +1447 -> 3096
    //   1652: iconst_1
    //   1653: istore 46
    //   1655: aload 45
    //   1657: iload 46
    //   1659: invokevirtual 349	android/widget/PopupWindow:setClippingEnabled	(Z)V
    //   1662: aload 27
    //   1664: getfield 321	com/google/android/gms/internal/zzfn:zzCM	Landroid/widget/RelativeLayout;
    //   1667: aload 27
    //   1669: getfield 117	com/google/android/gms/internal/zzfn:zzpX	Lcom/google/android/gms/internal/zzjo;
    //   1672: invokeinterface 270 1 0
    //   1677: iconst_m1
    //   1678: iconst_m1
    //   1679: invokevirtual 352	android/widget/RelativeLayout:addView	(Landroid/view/View;II)V
    //   1682: aload 27
    //   1684: new 354	android/widget/LinearLayout
    //   1687: dup
    //   1688: aload 27
    //   1690: getfield 108	com/google/android/gms/internal/zzfn:zzCH	Landroid/app/Activity;
    //   1693: invokespecial 355	android/widget/LinearLayout:<init>	(Landroid/content/Context;)V
    //   1696: putfield 359	com/google/android/gms/internal/zzfn:zzCJ	Landroid/widget/LinearLayout;
    //   1699: invokestatic 261	com/google/android/gms/ads/internal/client/zzl:zzcX	()Lcom/google/android/gms/ads/internal/util/client/zza;
    //   1702: pop
    //   1703: aload 27
    //   1705: getfield 108	com/google/android/gms/internal/zzfn:zzCH	Landroid/app/Activity;
    //   1708: bipush 50
    //   1710: invokestatic 267	com/google/android/gms/ads/internal/util/client/zza:zzb	(Landroid/content/Context;I)I
    //   1713: istore 48
    //   1715: invokestatic 261	com/google/android/gms/ads/internal/client/zzl:zzcX	()Lcom/google/android/gms/ads/internal/util/client/zza;
    //   1718: pop
    //   1719: new 361	android/widget/RelativeLayout$LayoutParams
    //   1722: dup
    //   1723: iload 48
    //   1725: aload 27
    //   1727: getfield 108	com/google/android/gms/internal/zzfn:zzCH	Landroid/app/Activity;
    //   1730: bipush 50
    //   1732: invokestatic 267	com/google/android/gms/ads/internal/util/client/zza:zzb	(Landroid/content/Context;I)I
    //   1735: invokespecial 362	android/widget/RelativeLayout$LayoutParams:<init>	(II)V
    //   1738: astore 50
    //   1740: aload 27
    //   1742: getfield 196	com/google/android/gms/internal/zzfn:zzCB	Ljava/lang/String;
    //   1745: astore 51
    //   1747: aload 51
    //   1749: invokevirtual 233	java/lang/String:hashCode	()I
    //   1752: lookupswitch	default:+1304->3056, -1364013995:+373->2125, -1012429441:+343->2095, -655373719:+388->2140, 1163912186:+418->2170, 1288627767:+403->2155, 1755462605:+358->2110
    //   1813: aaload
    //   1814: bipush 10
    //   1816: invokevirtual 365	android/widget/RelativeLayout$LayoutParams:addRule	(I)V
    //   1819: aload 50
    //   1821: bipush 11
    //   1823: invokevirtual 365	android/widget/RelativeLayout$LayoutParams:addRule	(I)V
    //   1826: aload 27
    //   1828: getfield 359	com/google/android/gms/internal/zzfn:zzCJ	Landroid/widget/LinearLayout;
    //   1831: new 367	com/google/android/gms/internal/zzfn$1
    //   1834: dup
    //   1835: aload 27
    //   1837: invokespecial 370	com/google/android/gms/internal/zzfn$1:<init>	(Lcom/google/android/gms/internal/zzfn;)V
    //   1840: invokevirtual 374	android/widget/LinearLayout:setOnClickListener	(Landroid/view/View$OnClickListener;)V
    //   1843: aload 27
    //   1845: getfield 359	com/google/android/gms/internal/zzfn:zzCJ	Landroid/widget/LinearLayout;
    //   1848: ldc_w 376
    //   1851: invokevirtual 380	android/widget/LinearLayout:setContentDescription	(Ljava/lang/CharSequence;)V
    //   1854: aload 27
    //   1856: getfield 321	com/google/android/gms/internal/zzfn:zzCM	Landroid/widget/RelativeLayout;
    //   1859: aload 27
    //   1861: getfield 359	com/google/android/gms/internal/zzfn:zzCJ	Landroid/widget/LinearLayout;
    //   1864: aload 50
    //   1866: invokevirtual 383	android/widget/RelativeLayout:addView	(Landroid/view/View;Landroid/view/ViewGroup$LayoutParams;)V
    //   1869: aload 27
    //   1871: getfield 286	com/google/android/gms/internal/zzfn:zzCL	Landroid/widget/PopupWindow;
    //   1874: astore 53
    //   1876: aload 32
    //   1878: invokevirtual 210	android/view/Window:getDecorView	()Landroid/view/View;
    //   1881: astore 54
    //   1883: invokestatic 261	com/google/android/gms/ads/internal/client/zzl:zzcX	()Lcom/google/android/gms/ads/internal/util/client/zza;
    //   1886: pop
    //   1887: aload 27
    //   1889: getfield 108	com/google/android/gms/internal/zzfn:zzCH	Landroid/app/Activity;
    //   1892: aload 38
    //   1894: iconst_0
    //   1895: iaload
    //   1896: invokestatic 267	com/google/android/gms/ads/internal/util/client/zza:zzb	(Landroid/content/Context;I)I
    //   1899: istore 56
    //   1901: invokestatic 261	com/google/android/gms/ads/internal/client/zzl:zzcX	()Lcom/google/android/gms/ads/internal/util/client/zza;
    //   1904: pop
    //   1905: aload 53
    //   1907: aload 54
    //   1909: iconst_0
    //   1910: iload 56
    //   1912: aload 27
    //   1914: getfield 108	com/google/android/gms/internal/zzfn:zzCH	Landroid/app/Activity;
    //   1917: aload 38
    //   1919: iconst_1
    //   1920: iaload
    //   1921: invokestatic 267	com/google/android/gms/ads/internal/util/client/zza:zzb	(Landroid/content/Context;I)I
    //   1924: invokevirtual 387	android/widget/PopupWindow:showAtLocation	(Landroid/view/View;III)V
    //   1927: aload 27
    //   1929: getfield 117	com/google/android/gms/internal/zzfn:zzpX	Lcom/google/android/gms/internal/zzjo;
    //   1932: new 127	com/google/android/gms/ads/internal/client/AdSizeParcel
    //   1935: dup
    //   1936: aload 27
    //   1938: getfield 108	com/google/android/gms/internal/zzfn:zzCH	Landroid/app/Activity;
    //   1941: new 389	com/google/android/gms/ads/AdSize
    //   1944: dup
    //   1945: aload 27
    //   1947: getfield 164	com/google/android/gms/internal/zzfn:zzoM	I
    //   1950: aload 27
    //   1952: getfield 169	com/google/android/gms/internal/zzfn:zzoN	I
    //   1955: invokespecial 390	com/google/android/gms/ads/AdSize:<init>	(II)V
    //   1958: invokespecial 393	com/google/android/gms/ads/internal/client/AdSizeParcel:<init>	(Landroid/content/Context;Lcom/google/android/gms/ads/AdSize;)V
    //   1961: invokeinterface 396 2 0
    //   1966: aload 38
    //   1968: iconst_0
    //   1969: iaload
    //   1970: istore 58
    //   1972: aload 38
    //   1974: iconst_1
    //   1975: iaload
    //   1976: invokestatic 154	com/google/android/gms/ads/internal/zzp:zzbI	()Lcom/google/android/gms/internal/zziq;
    //   1979: aload 27
    //   1981: getfield 108	com/google/android/gms/internal/zzfn:zzCH	Landroid/app/Activity;
    //   1984: invokevirtual 219	com/google/android/gms/internal/zziq:zzj	(Landroid/app/Activity;)[I
    //   1987: iconst_0
    //   1988: iaload
    //   1989: isub
    //   1990: istore 59
    //   1992: aload 27
    //   1994: getfield 164	com/google/android/gms/internal/zzfn:zzoM	I
    //   1997: istore 60
    //   1999: aload 27
    //   2001: getfield 169	com/google/android/gms/internal/zzfn:zzoN	I
    //   2004: istore 61
    //   2006: new 398	org/json/JSONObject
    //   2009: dup
    //   2010: invokespecial 399	org/json/JSONObject:<init>	()V
    //   2013: ldc_w 401
    //   2016: iload 58
    //   2018: invokevirtual 404	org/json/JSONObject:put	(Ljava/lang/String;I)Lorg/json/JSONObject;
    //   2021: ldc_w 406
    //   2024: iload 59
    //   2026: invokevirtual 404	org/json/JSONObject:put	(Ljava/lang/String;I)Lorg/json/JSONObject;
    //   2029: ldc 140
    //   2031: iload 60
    //   2033: invokevirtual 404	org/json/JSONObject:put	(Ljava/lang/String;I)Lorg/json/JSONObject;
    //   2036: ldc 166
    //   2038: iload 61
    //   2040: invokevirtual 404	org/json/JSONObject:put	(Ljava/lang/String;I)Lorg/json/JSONObject;
    //   2043: astore 63
    //   2045: aload 27
    //   2047: getfield 409	com/google/android/gms/internal/zzfs:zzpX	Lcom/google/android/gms/internal/zzjo;
    //   2050: ldc_w 411
    //   2053: aload 63
    //   2055: invokeinterface 414 3 0
    //   2060: aload 27
    //   2062: ldc_w 416
    //   2065: invokevirtual 419	com/google/android/gms/internal/zzfn:zzan	(Ljava/lang/String;)V
    //   2068: aload 28
    //   2070: monitorexit
    //   2071: return
    //   2072: aload 27
    //   2074: getfield 286	com/google/android/gms/internal/zzfn:zzCL	Landroid/widget/PopupWindow;
    //   2077: invokevirtual 422	android/widget/PopupWindow:dismiss	()V
    //   2080: goto -527 -> 1553
    //   2083: aload 27
    //   2085: ldc_w 424
    //   2088: invokevirtual 113	com/google/android/gms/internal/zzfn:zzal	(Ljava/lang/String;)V
    //   2091: aload 28
    //   2093: monitorexit
    //   2094: return
    //   2095: aload 51
    //   2097: ldc 241
    //   2099: invokevirtual 245	java/lang/String:equals	(Ljava/lang/Object;)Z
    //   2102: ifeq +954 -> 3056
    //   2105: iconst_0
    //   2106: istore_3
    //   2107: goto +949 -> 3056
    //   2110: aload 51
    //   2112: ldc 247
    //   2114: invokevirtual 245	java/lang/String:equals	(Ljava/lang/Object;)Z
    //   2117: ifeq +939 -> 3056
    //   2120: iconst_1
    //   2121: istore_3
    //   2122: goto +934 -> 3056
    //   2125: aload 51
    //   2127: ldc 249
    //   2129: invokevirtual 245	java/lang/String:equals	(Ljava/lang/Object;)Z
    //   2132: ifeq +924 -> 3056
    //   2135: iconst_2
    //   2136: istore_3
    //   2137: goto +919 -> 3056
    //   2140: aload 51
    //   2142: ldc 251
    //   2144: invokevirtual 245	java/lang/String:equals	(Ljava/lang/Object;)Z
    //   2147: ifeq +909 -> 3056
    //   2150: iconst_3
    //   2151: istore_3
    //   2152: goto +904 -> 3056
    //   2155: aload 51
    //   2157: ldc 253
    //   2159: invokevirtual 245	java/lang/String:equals	(Ljava/lang/Object;)Z
    //   2162: ifeq +894 -> 3056
    //   2165: iconst_4
    //   2166: istore_3
    //   2167: goto +889 -> 3056
    //   2170: aload 51
    //   2172: ldc 255
    //   2174: invokevirtual 245	java/lang/String:equals	(Ljava/lang/Object;)Z
    //   2177: ifeq +879 -> 3056
    //   2180: iconst_5
    //   2181: istore_3
    //   2182: goto +874 -> 3056
    //   2185: aload 50
    //   2187: bipush 10
    //   2189: invokevirtual 365	android/widget/RelativeLayout$LayoutParams:addRule	(I)V
    //   2192: aload 50
    //   2194: bipush 9
    //   2196: invokevirtual 365	android/widget/RelativeLayout$LayoutParams:addRule	(I)V
    //   2199: goto -373 -> 1826
    //   2202: aload 50
    //   2204: bipush 10
    //   2206: invokevirtual 365	android/widget/RelativeLayout$LayoutParams:addRule	(I)V
    //   2209: aload 50
    //   2211: bipush 14
    //   2213: invokevirtual 365	android/widget/RelativeLayout$LayoutParams:addRule	(I)V
    //   2216: goto -390 -> 1826
    //   2219: aload 50
    //   2221: bipush 13
    //   2223: invokevirtual 365	android/widget/RelativeLayout$LayoutParams:addRule	(I)V
    //   2226: goto -400 -> 1826
    //   2229: aload 50
    //   2231: bipush 12
    //   2233: invokevirtual 365	android/widget/RelativeLayout$LayoutParams:addRule	(I)V
    //   2236: aload 50
    //   2238: bipush 9
    //   2240: invokevirtual 365	android/widget/RelativeLayout$LayoutParams:addRule	(I)V
    //   2243: goto -417 -> 1826
    //   2246: aload 50
    //   2248: bipush 12
    //   2250: invokevirtual 365	android/widget/RelativeLayout$LayoutParams:addRule	(I)V
    //   2253: aload 50
    //   2255: bipush 14
    //   2257: invokevirtual 365	android/widget/RelativeLayout$LayoutParams:addRule	(I)V
    //   2260: goto -434 -> 1826
    //   2263: aload 50
    //   2265: bipush 12
    //   2267: invokevirtual 365	android/widget/RelativeLayout$LayoutParams:addRule	(I)V
    //   2270: aload 50
    //   2272: bipush 11
    //   2274: invokevirtual 365	android/widget/RelativeLayout$LayoutParams:addRule	(I)V
    //   2277: goto -451 -> 1826
    //   2280: astore 52
    //   2282: aload 27
    //   2284: new 426	java/lang/StringBuilder
    //   2287: dup
    //   2288: ldc_w 428
    //   2291: invokespecial 430	java/lang/StringBuilder:<init>	(Ljava/lang/String;)V
    //   2294: aload 52
    //   2296: invokevirtual 434	java/lang/RuntimeException:getMessage	()Ljava/lang/String;
    //   2299: invokevirtual 438	java/lang/StringBuilder:append	(Ljava/lang/String;)Ljava/lang/StringBuilder;
    //   2302: invokevirtual 441	java/lang/StringBuilder:toString	()Ljava/lang/String;
    //   2305: invokevirtual 113	com/google/android/gms/internal/zzfn:zzal	(Ljava/lang/String;)V
    //   2308: aload 27
    //   2310: getfield 321	com/google/android/gms/internal/zzfn:zzCM	Landroid/widget/RelativeLayout;
    //   2313: aload 27
    //   2315: getfield 117	com/google/android/gms/internal/zzfn:zzpX	Lcom/google/android/gms/internal/zzjo;
    //   2318: invokeinterface 270 1 0
    //   2323: invokevirtual 442	android/widget/RelativeLayout:removeView	(Landroid/view/View;)V
    //   2326: aload 27
    //   2328: getfield 290	com/google/android/gms/internal/zzfn:zzCN	Landroid/view/ViewGroup;
    //   2331: ifnull +49 -> 2380
    //   2334: aload 27
    //   2336: getfield 290	com/google/android/gms/internal/zzfn:zzCN	Landroid/view/ViewGroup;
    //   2339: aload 27
    //   2341: getfield 303	com/google/android/gms/internal/zzfn:zzCI	Landroid/widget/ImageView;
    //   2344: invokevirtual 282	android/view/ViewGroup:removeView	(Landroid/view/View;)V
    //   2347: aload 27
    //   2349: getfield 290	com/google/android/gms/internal/zzfn:zzCN	Landroid/view/ViewGroup;
    //   2352: aload 27
    //   2354: getfield 117	com/google/android/gms/internal/zzfn:zzpX	Lcom/google/android/gms/internal/zzjo;
    //   2357: invokeinterface 270 1 0
    //   2362: invokevirtual 314	android/view/ViewGroup:addView	(Landroid/view/View;)V
    //   2365: aload 27
    //   2367: getfield 117	com/google/android/gms/internal/zzfn:zzpX	Lcom/google/android/gms/internal/zzjo;
    //   2370: aload 27
    //   2372: getfield 311	com/google/android/gms/internal/zzfn:zzBH	Lcom/google/android/gms/ads/internal/client/AdSizeParcel;
    //   2375: invokeinterface 396 2 0
    //   2380: aload 28
    //   2382: monitorexit
    //   2383: return
    //   2384: astore 62
    //   2386: ldc_w 444
    //   2389: aload 62
    //   2391: invokestatic 448	com/google/android/gms/ads/internal/util/client/zzb:e	(Ljava/lang/String;Ljava/lang/Throwable;)V
    //   2394: goto -334 -> 2060
    //   2397: new 450	com/google/android/gms/internal/zzfm
    //   2400: dup
    //   2401: aload_1
    //   2402: aload_2
    //   2403: invokespecial 452	com/google/android/gms/internal/zzfm:<init>	(Lcom/google/android/gms/internal/zzjo;Ljava/util/Map;)V
    //   2406: astore 19
    //   2408: aload 19
    //   2410: getfield 456	com/google/android/gms/internal/zzfm:mContext	Landroid/content/Context;
    //   2413: ifnonnull +12 -> 2425
    //   2416: aload 19
    //   2418: ldc_w 458
    //   2421: invokevirtual 459	com/google/android/gms/internal/zzfm:zzal	(Ljava/lang/String;)V
    //   2424: return
    //   2425: invokestatic 154	com/google/android/gms/ads/internal/zzp:zzbI	()Lcom/google/android/gms/internal/zziq;
    //   2428: pop
    //   2429: aload 19
    //   2431: getfield 456	com/google/android/gms/internal/zzfm:mContext	Landroid/content/Context;
    //   2434: invokestatic 463	com/google/android/gms/internal/zziq:zzO	(Landroid/content/Context;)Lcom/google/android/gms/internal/zzca;
    //   2437: invokevirtual 468	com/google/android/gms/internal/zzca:zzds	()Z
    //   2440: ifne +12 -> 2452
    //   2443: aload 19
    //   2445: ldc_w 470
    //   2448: invokevirtual 459	com/google/android/gms/internal/zzfm:zzal	(Ljava/lang/String;)V
    //   2451: return
    //   2452: invokestatic 154	com/google/android/gms/ads/internal/zzp:zzbI	()Lcom/google/android/gms/internal/zziq;
    //   2455: pop
    //   2456: aload 19
    //   2458: getfield 456	com/google/android/gms/internal/zzfm:mContext	Landroid/content/Context;
    //   2461: invokestatic 474	com/google/android/gms/internal/zziq:zzN	(Landroid/content/Context;)Landroid/app/AlertDialog$Builder;
    //   2464: astore 22
    //   2466: aload 22
    //   2468: invokestatic 478	com/google/android/gms/ads/internal/zzp:zzbL	()Lcom/google/android/gms/internal/zzih;
    //   2471: getstatic 483	com/google/android/gms/R$string:create_calendar_title	I
    //   2474: ldc_w 485
    //   2477: invokevirtual 491	com/google/android/gms/internal/zzih:zzf	(ILjava/lang/String;)Ljava/lang/String;
    //   2480: invokevirtual 497	android/app/AlertDialog$Builder:setTitle	(Ljava/lang/CharSequence;)Landroid/app/AlertDialog$Builder;
    //   2483: pop
    //   2484: aload 22
    //   2486: invokestatic 478	com/google/android/gms/ads/internal/zzp:zzbL	()Lcom/google/android/gms/internal/zzih;
    //   2489: getstatic 500	com/google/android/gms/R$string:create_calendar_message	I
    //   2492: ldc_w 502
    //   2495: invokevirtual 491	com/google/android/gms/internal/zzih:zzf	(ILjava/lang/String;)Ljava/lang/String;
    //   2498: invokevirtual 505	android/app/AlertDialog$Builder:setMessage	(Ljava/lang/CharSequence;)Landroid/app/AlertDialog$Builder;
    //   2501: pop
    //   2502: aload 22
    //   2504: invokestatic 478	com/google/android/gms/ads/internal/zzp:zzbL	()Lcom/google/android/gms/internal/zzih;
    //   2507: getstatic 508	com/google/android/gms/R$string:accept	I
    //   2510: ldc_w 510
    //   2513: invokevirtual 491	com/google/android/gms/internal/zzih:zzf	(ILjava/lang/String;)Ljava/lang/String;
    //   2516: new 512	com/google/android/gms/internal/zzfm$1
    //   2519: dup
    //   2520: aload 19
    //   2522: invokespecial 515	com/google/android/gms/internal/zzfm$1:<init>	(Lcom/google/android/gms/internal/zzfm;)V
    //   2525: invokevirtual 519	android/app/AlertDialog$Builder:setPositiveButton	(Ljava/lang/CharSequence;Landroid/content/DialogInterface$OnClickListener;)Landroid/app/AlertDialog$Builder;
    //   2528: pop
    //   2529: aload 22
    //   2531: invokestatic 478	com/google/android/gms/ads/internal/zzp:zzbL	()Lcom/google/android/gms/internal/zzih;
    //   2534: getstatic 522	com/google/android/gms/R$string:decline	I
    //   2537: ldc_w 524
    //   2540: invokevirtual 491	com/google/android/gms/internal/zzih:zzf	(ILjava/lang/String;)Ljava/lang/String;
    //   2543: new 526	com/google/android/gms/internal/zzfm$2
    //   2546: dup
    //   2547: aload 19
    //   2549: invokespecial 527	com/google/android/gms/internal/zzfm$2:<init>	(Lcom/google/android/gms/internal/zzfm;)V
    //   2552: invokevirtual 530	android/app/AlertDialog$Builder:setNegativeButton	(Ljava/lang/CharSequence;Landroid/content/DialogInterface$OnClickListener;)Landroid/app/AlertDialog$Builder;
    //   2555: pop
    //   2556: aload 22
    //   2558: invokevirtual 534	android/app/AlertDialog$Builder:create	()Landroid/app/AlertDialog;
    //   2561: invokevirtual 539	android/app/AlertDialog:show	()V
    //   2564: return
    //   2565: new 541	com/google/android/gms/internal/zzfp
    //   2568: dup
    //   2569: aload_1
    //   2570: aload_2
    //   2571: invokespecial 542	com/google/android/gms/internal/zzfp:<init>	(Lcom/google/android/gms/internal/zzjo;Ljava/util/Map;)V
    //   2574: astore 8
    //   2576: aload 8
    //   2578: getfield 543	com/google/android/gms/internal/zzfp:mContext	Landroid/content/Context;
    //   2581: ifnonnull +12 -> 2593
    //   2584: aload 8
    //   2586: ldc_w 545
    //   2589: invokevirtual 546	com/google/android/gms/internal/zzfp:zzal	(Ljava/lang/String;)V
    //   2592: return
    //   2593: invokestatic 154	com/google/android/gms/ads/internal/zzp:zzbI	()Lcom/google/android/gms/internal/zziq;
    //   2596: pop
    //   2597: aload 8
    //   2599: getfield 543	com/google/android/gms/internal/zzfp:mContext	Landroid/content/Context;
    //   2602: invokestatic 463	com/google/android/gms/internal/zziq:zzO	(Landroid/content/Context;)Lcom/google/android/gms/internal/zzca;
    //   2605: invokevirtual 549	com/google/android/gms/internal/zzca:zzdp	()Z
    //   2608: ifne +12 -> 2620
    //   2611: aload 8
    //   2613: ldc_w 551
    //   2616: invokevirtual 546	com/google/android/gms/internal/zzfp:zzal	(Ljava/lang/String;)V
    //   2619: return
    //   2620: aload 8
    //   2622: getfield 554	com/google/android/gms/internal/zzfp:zzxC	Ljava/util/Map;
    //   2625: ldc_w 556
    //   2628: invokeinterface 73 2 0
    //   2633: checkcast 75	java/lang/String
    //   2636: astore 10
    //   2638: aload 10
    //   2640: invokestatic 148	android/text/TextUtils:isEmpty	(Ljava/lang/CharSequence;)Z
    //   2643: ifeq +12 -> 2655
    //   2646: aload 8
    //   2648: ldc_w 558
    //   2651: invokevirtual 546	com/google/android/gms/internal/zzfp:zzal	(Ljava/lang/String;)V
    //   2654: return
    //   2655: aload 10
    //   2657: invokestatic 563	android/webkit/URLUtil:isValidUrl	(Ljava/lang/String;)Z
    //   2660: ifne +27 -> 2687
    //   2663: aload 8
    //   2665: new 426	java/lang/StringBuilder
    //   2668: dup
    //   2669: ldc_w 565
    //   2672: invokespecial 430	java/lang/StringBuilder:<init>	(Ljava/lang/String;)V
    //   2675: aload 10
    //   2677: invokevirtual 438	java/lang/StringBuilder:append	(Ljava/lang/String;)Ljava/lang/StringBuilder;
    //   2680: invokevirtual 441	java/lang/StringBuilder:toString	()Ljava/lang/String;
    //   2683: invokevirtual 546	com/google/android/gms/internal/zzfp:zzal	(Ljava/lang/String;)V
    //   2686: return
    //   2687: aload 10
    //   2689: invokestatic 571	android/net/Uri:parse	(Ljava/lang/String;)Landroid/net/Uri;
    //   2692: invokevirtual 574	android/net/Uri:getLastPathSegment	()Ljava/lang/String;
    //   2695: astore 11
    //   2697: invokestatic 154	com/google/android/gms/ads/internal/zzp:zzbI	()Lcom/google/android/gms/internal/zziq;
    //   2700: pop
    //   2701: aload 11
    //   2703: invokestatic 577	com/google/android/gms/internal/zziq:zzaB	(Ljava/lang/String;)Z
    //   2706: ifne +27 -> 2733
    //   2709: aload 8
    //   2711: new 426	java/lang/StringBuilder
    //   2714: dup
    //   2715: ldc_w 579
    //   2718: invokespecial 430	java/lang/StringBuilder:<init>	(Ljava/lang/String;)V
    //   2721: aload 11
    //   2723: invokevirtual 438	java/lang/StringBuilder:append	(Ljava/lang/String;)Ljava/lang/StringBuilder;
    //   2726: invokevirtual 441	java/lang/StringBuilder:toString	()Ljava/lang/String;
    //   2729: invokevirtual 546	com/google/android/gms/internal/zzfp:zzal	(Ljava/lang/String;)V
    //   2732: return
    //   2733: invokestatic 154	com/google/android/gms/ads/internal/zzp:zzbI	()Lcom/google/android/gms/internal/zziq;
    //   2736: pop
    //   2737: aload 8
    //   2739: getfield 543	com/google/android/gms/internal/zzfp:mContext	Landroid/content/Context;
    //   2742: invokestatic 474	com/google/android/gms/internal/zziq:zzN	(Landroid/content/Context;)Landroid/app/AlertDialog$Builder;
    //   2745: astore 14
    //   2747: aload 14
    //   2749: invokestatic 478	com/google/android/gms/ads/internal/zzp:zzbL	()Lcom/google/android/gms/internal/zzih;
    //   2752: getstatic 582	com/google/android/gms/R$string:store_picture_title	I
    //   2755: ldc_w 584
    //   2758: invokevirtual 491	com/google/android/gms/internal/zzih:zzf	(ILjava/lang/String;)Ljava/lang/String;
    //   2761: invokevirtual 497	android/app/AlertDialog$Builder:setTitle	(Ljava/lang/CharSequence;)Landroid/app/AlertDialog$Builder;
    //   2764: pop
    //   2765: aload 14
    //   2767: invokestatic 478	com/google/android/gms/ads/internal/zzp:zzbL	()Lcom/google/android/gms/internal/zzih;
    //   2770: getstatic 587	com/google/android/gms/R$string:store_picture_message	I
    //   2773: ldc_w 589
    //   2776: invokevirtual 491	com/google/android/gms/internal/zzih:zzf	(ILjava/lang/String;)Ljava/lang/String;
    //   2779: invokevirtual 505	android/app/AlertDialog$Builder:setMessage	(Ljava/lang/CharSequence;)Landroid/app/AlertDialog$Builder;
    //   2782: pop
    //   2783: aload 14
    //   2785: invokestatic 478	com/google/android/gms/ads/internal/zzp:zzbL	()Lcom/google/android/gms/internal/zzih;
    //   2788: getstatic 508	com/google/android/gms/R$string:accept	I
    //   2791: ldc_w 510
    //   2794: invokevirtual 491	com/google/android/gms/internal/zzih:zzf	(ILjava/lang/String;)Ljava/lang/String;
    //   2797: new 591	com/google/android/gms/internal/zzfp$1
    //   2800: dup
    //   2801: aload 8
    //   2803: aload 10
    //   2805: aload 11
    //   2807: invokespecial 594	com/google/android/gms/internal/zzfp$1:<init>	(Lcom/google/android/gms/internal/zzfp;Ljava/lang/String;Ljava/lang/String;)V
    //   2810: invokevirtual 519	android/app/AlertDialog$Builder:setPositiveButton	(Ljava/lang/CharSequence;Landroid/content/DialogInterface$OnClickListener;)Landroid/app/AlertDialog$Builder;
    //   2813: pop
    //   2814: aload 14
    //   2816: invokestatic 478	com/google/android/gms/ads/internal/zzp:zzbL	()Lcom/google/android/gms/internal/zzih;
    //   2819: getstatic 522	com/google/android/gms/R$string:decline	I
    //   2822: ldc_w 524
    //   2825: invokevirtual 491	com/google/android/gms/internal/zzih:zzf	(ILjava/lang/String;)Ljava/lang/String;
    //   2828: new 596	com/google/android/gms/internal/zzfp$2
    //   2831: dup
    //   2832: aload 8
    //   2834: invokespecial 599	com/google/android/gms/internal/zzfp$2:<init>	(Lcom/google/android/gms/internal/zzfp;)V
    //   2837: invokevirtual 530	android/app/AlertDialog$Builder:setNegativeButton	(Ljava/lang/CharSequence;Landroid/content/DialogInterface$OnClickListener;)Landroid/app/AlertDialog$Builder;
    //   2840: pop
    //   2841: aload 14
    //   2843: invokevirtual 534	android/app/AlertDialog$Builder:create	()Landroid/app/AlertDialog;
    //   2846: invokevirtual 539	android/app/AlertDialog:show	()V
    //   2849: return
    //   2850: new 601	com/google/android/gms/internal/zzfo
    //   2853: dup
    //   2854: aload_1
    //   2855: aload_2
    //   2856: invokespecial 602	com/google/android/gms/internal/zzfo:<init>	(Lcom/google/android/gms/internal/zzjo;Ljava/util/Map;)V
    //   2859: astore 6
    //   2861: aload 6
    //   2863: getfield 603	com/google/android/gms/internal/zzfo:zzpX	Lcom/google/android/gms/internal/zzjo;
    //   2866: ifnonnull +10 -> 2876
    //   2869: ldc_w 605
    //   2872: invokestatic 224	com/google/android/gms/ads/internal/util/client/zzb:w	(Ljava/lang/String;)V
    //   2875: return
    //   2876: ldc_w 607
    //   2879: aload 6
    //   2881: getfield 610	com/google/android/gms/internal/zzfo:zzCQ	Ljava/lang/String;
    //   2884: invokevirtual 613	java/lang/String:equalsIgnoreCase	(Ljava/lang/String;)Z
    //   2887: ifeq +24 -> 2911
    //   2890: invokestatic 617	com/google/android/gms/ads/internal/zzp:zzbK	()Lcom/google/android/gms/internal/zzir;
    //   2893: invokevirtual 622	com/google/android/gms/internal/zzir:zzhm	()I
    //   2896: istore 7
    //   2898: aload 6
    //   2900: getfield 603	com/google/android/gms/internal/zzfo:zzpX	Lcom/google/android/gms/internal/zzjo;
    //   2903: iload 7
    //   2905: invokeinterface 625 2 0
    //   2910: return
    //   2911: ldc_w 627
    //   2914: aload 6
    //   2916: getfield 610	com/google/android/gms/internal/zzfo:zzCQ	Ljava/lang/String;
    //   2919: invokevirtual 613	java/lang/String:equalsIgnoreCase	(Ljava/lang/String;)Z
    //   2922: ifeq +14 -> 2936
    //   2925: invokestatic 617	com/google/android/gms/ads/internal/zzp:zzbK	()Lcom/google/android/gms/internal/zzir;
    //   2928: invokevirtual 630	com/google/android/gms/internal/zzir:zzhl	()I
    //   2931: istore 7
    //   2933: goto -35 -> 2898
    //   2936: aload 6
    //   2938: getfield 633	com/google/android/gms/internal/zzfo:zzCP	Z
    //   2941: ifeq +9 -> 2950
    //   2944: iload_3
    //   2945: istore 7
    //   2947: goto -49 -> 2898
    //   2950: invokestatic 617	com/google/android/gms/ads/internal/zzp:zzbK	()Lcom/google/android/gms/internal/zzir;
    //   2953: invokevirtual 636	com/google/android/gms/internal/zzir:zzhn	()I
    //   2956: istore 7
    //   2958: goto -60 -> 2898
    //   2961: aload_0
    //   2962: getfield 61	com/google/android/gms/internal/zzds:zzzC	Lcom/google/android/gms/internal/zzfn;
    //   2965: iconst_1
    //   2966: invokevirtual 639	com/google/android/gms/internal/zzfn:zzp	(Z)V
    //   2969: return
    //   2970: iload 70
    //   2972: istore 72
    //   2974: goto -1671 -> 1303
    //   2977: iload 69
    //   2979: istore 71
    //   2981: goto -1693 -> 1288
    //   2984: iconst_0
    //   2985: istore 31
    //   2987: goto -2516 -> 471
    //   2990: iload 37
    //   2992: ifne -1820 -> 1172
    //   2995: aconst_null
    //   2996: astore 38
    //   2998: goto -2408 -> 590
    //   3001: iload_3
    //   3002: istore 75
    //   3004: iload 75
    //   3006: tableswitch	default:+-2258 -> 748, 0:+-2088->918, 1:+-2059->947, 2:+-2019->987, 3:+-1968->1038, 4:+-1930->1076, 5:+-1881->1125
    //   3045: istore 37
    //   3047: goto -57 -> 2990
    //   3050: iconst_1
    //   3051: istore 37
    //   3053: goto -63 -> 2990
    //   3056: iload_3
    //   3057: tableswitch	default:+-1245 -> 1812, 0:+-872->2185, 1:+-855->2202, 2:+-838->2219, 3:+-828->2229, 4:+-811->2246, 5:+-794->2263
    //   3097: istore 46
    //   3099: goto -1444 -> 1655
    // Local variable table:
    //   start	length	slot	name	signature
    //   0	3102	0	this	zzds
    //   0	3102	1	paramzzjo	zzjo
    //   0	3102	2	paramMap	Map<String, String>
    //   1	3056	3	i	int
    //   13	6	4	str1	String
    //   31	32	5	j	int
    //   2859	78	6	localzzfo	zzfo
    //   2896	61	7	k	int
    //   2574	259	8	localzzfp	zzfp
    //   2636	168	10	str2	String
    //   2695	111	11	str3	String
    //   2745	97	14	localBuilder1	android.app.AlertDialog.Builder
    //   2406	142	19	localzzfm	zzfm
    //   2464	93	22	localBuilder2	android.app.AlertDialog.Builder
    //   114	2257	27	localzzfn	zzfn
    //   121	2260	28	localObject1	Object
    //   145	6	29	localObject2	Object
    //   435	13	30	str4	String
    //   469	2517	31	m	int
    //   495	1382	32	localWindow	android.view.Window
    //   532	22	33	arrayOfInt1	int[]
    //   545	268	34	arrayOfInt2	int[]
    //   551	245	35	n	int
    //   557	88	36	i1	int
    //   585	2467	37	i2	int
    //   590	2407	38	localObject3	Object
    //   1394	216	40	i3	int
    //   1413	199	42	i4	int
    //   1428	44	43	localViewParent	android.view.ViewParent
    //   1642	14	45	localPopupWindow1	android.widget.PopupWindow
    //   1653	1445	46	bool	boolean
    //   1713	11	48	i5	int
    //   1738	533	50	localLayoutParams	android.widget.RelativeLayout.LayoutParams
    //   1745	426	51	str5	String
    //   2280	15	52	localRuntimeException	java.lang.RuntimeException
    //   1874	32	53	localPopupWindow2	android.widget.PopupWindow
    //   1881	27	54	localView	android.view.View
    //   1899	12	56	i6	int
    //   1970	47	58	i7	int
    //   1990	35	59	i8	int
    //   1997	35	60	i9	int
    //   2004	35	61	i10	int
    //   2384	6	62	localJSONException	org.json.JSONException
    //   2043	11	63	localJSONObject	org.json.JSONObject
    //   1496	25	65	localBitmap	android.graphics.Bitmap
    //   1233	16	66	arrayOfInt3	int[]
    //   1246	117	67	arrayOfInt4	int[]
    //   1252	90	68	i11	int
    //   1265	1713	69	i12	int
    //   1278	1693	70	i13	int
    //   1286	1694	71	i14	int
    //   1301	1672	72	i15	int
    //   1183	33	73	arrayOfInt5	int[]
    //   681	222	74	str6	String
    //   833	2172	75	i16	int
    //   768	378	76	i17	int
    //   781	387	77	i18	int
    // Exception table:
    //   from	to	target	type
    //   126	144	145	finally
    //   147	150	145	finally
    //   153	176	145	finally
    //   177	203	145	finally
    //   204	227	145	finally
    //   228	268	145	finally
    //   268	308	145	finally
    //   308	348	145	finally
    //   348	388	145	finally
    //   388	424	145	finally
    //   424	452	145	finally
    //   452	468	145	finally
    //   476	486	145	finally
    //   487	497	145	finally
    //   502	510	145	finally
    //   510	520	145	finally
    //   521	579	145	finally
    //   579	584	145	finally
    //   595	605	145	finally
    //   606	626	145	finally
    //   626	631	145	finally
    //   637	662	145	finally
    //   668	748	145	finally
    //   748	783	145	finally
    //   798	819	145	finally
    //   822	832	145	finally
    //   838	848	145	finally
    //   854	864	145	finally
    //   870	880	145	finally
    //   886	896	145	finally
    //   902	912	145	finally
    //   918	944	145	finally
    //   947	984	145	finally
    //   987	1035	145	finally
    //   1038	1073	145	finally
    //   1076	1122	145	finally
    //   1125	1169	145	finally
    //   1172	1215	145	finally
    //   1222	1280	145	finally
    //   1288	1303	145	finally
    //   1303	1318	145	finally
    //   1321	1344	145	finally
    //   1347	1374	145	finally
    //   1377	1430	145	finally
    //   1435	1553	145	finally
    //   1553	1652	145	finally
    //   1655	1812	145	finally
    //   1812	1826	145	finally
    //   1826	1869	145	finally
    //   1869	1927	145	finally
    //   1927	2006	145	finally
    //   2006	2060	145	finally
    //   2060	2071	145	finally
    //   2072	2080	145	finally
    //   2083	2094	145	finally
    //   2095	2105	145	finally
    //   2110	2120	145	finally
    //   2125	2135	145	finally
    //   2140	2150	145	finally
    //   2155	2165	145	finally
    //   2170	2180	145	finally
    //   2185	2199	145	finally
    //   2202	2216	145	finally
    //   2219	2226	145	finally
    //   2229	2243	145	finally
    //   2246	2260	145	finally
    //   2263	2277	145	finally
    //   2282	2380	145	finally
    //   2380	2383	145	finally
    //   2386	2394	145	finally
    //   1869	1927	2280	java/lang/RuntimeException
    //   2006	2060	2384	org/json/JSONException
  }
}


/* Location:           F:\apktool\apktool\Google_Play_Store6.0.5\classes-dex2jar.jar
 * Qualified Name:     com.google.android.gms.internal.zzds
 * JD-Core Version:    0.7.0.1
 */