package com.google.android.gms.internal;

import android.os.Binder;
import android.os.Bundle;
import android.os.IBinder;
import android.os.IInterface;
import android.os.Parcel;
import android.os.RemoteException;
import com.google.android.gms.ads.internal.client.AdRequestParcel;
import com.google.android.gms.ads.internal.client.AdSizeParcel;
import com.google.android.gms.ads.internal.client.zzg;
import com.google.android.gms.ads.internal.formats.NativeAdOptionsParcel;
import com.google.android.gms.ads.internal.reward.mediation.client.zza;
import com.google.android.gms.ads.internal.reward.mediation.client.zza.zza.zza;
import com.google.android.gms.dynamic.zzd;
import com.google.android.gms.dynamic.zzd.zza;
import java.util.List;

public abstract interface zzey
  extends IInterface
{
  public abstract void destroy()
    throws RemoteException;
  
  public abstract Bundle getInterstitialAdapterInfo()
    throws RemoteException;
  
  public abstract zzd getView()
    throws RemoteException;
  
  public abstract boolean isInitialized()
    throws RemoteException;
  
  public abstract void pause()
    throws RemoteException;
  
  public abstract void resume()
    throws RemoteException;
  
  public abstract void showInterstitial()
    throws RemoteException;
  
  public abstract void showVideo()
    throws RemoteException;
  
  public abstract void zza(zzd paramzzd, AdRequestParcel paramAdRequestParcel, String paramString1, zza paramzza, String paramString2)
    throws RemoteException;
  
  public abstract void zza(zzd paramzzd, AdRequestParcel paramAdRequestParcel, String paramString, zzez paramzzez)
    throws RemoteException;
  
  public abstract void zza(zzd paramzzd, AdRequestParcel paramAdRequestParcel, String paramString1, String paramString2, zzez paramzzez)
    throws RemoteException;
  
  public abstract void zza(zzd paramzzd, AdRequestParcel paramAdRequestParcel, String paramString1, String paramString2, zzez paramzzez, NativeAdOptionsParcel paramNativeAdOptionsParcel, List<String> paramList)
    throws RemoteException;
  
  public abstract void zza(zzd paramzzd, AdSizeParcel paramAdSizeParcel, AdRequestParcel paramAdRequestParcel, String paramString, zzez paramzzez)
    throws RemoteException;
  
  public abstract void zza(zzd paramzzd, AdSizeParcel paramAdSizeParcel, AdRequestParcel paramAdRequestParcel, String paramString1, String paramString2, zzez paramzzez)
    throws RemoteException;
  
  public abstract void zzc(AdRequestParcel paramAdRequestParcel, String paramString)
    throws RemoteException;
  
  public abstract zzfb zzeD()
    throws RemoteException;
  
  public abstract zzfc zzeE()
    throws RemoteException;
  
  public abstract Bundle zzeF()
    throws RemoteException;
  
  public abstract Bundle zzeG()
    throws RemoteException;
  
  public static abstract class zza
    extends Binder
    implements zzey
  {
    public static zzey zzJ(IBinder paramIBinder)
    {
      if (paramIBinder == null) {
        return null;
      }
      IInterface localIInterface = paramIBinder.queryLocalInterface("com.google.android.gms.ads.internal.mediation.client.IMediationAdapter");
      if ((localIInterface != null) && ((localIInterface instanceof zzey))) {
        return (zzey)localIInterface;
      }
      return new zza(paramIBinder);
    }
    
    public boolean onTransact(int paramInt1, Parcel paramParcel1, Parcel paramParcel2, int paramInt2)
      throws RemoteException
    {
      switch (paramInt1)
      {
      default: 
        return super.onTransact(paramInt1, paramParcel1, paramParcel2, paramInt2);
      case 1598968902: 
        paramParcel2.writeString("com.google.android.gms.ads.internal.mediation.client.IMediationAdapter");
        return true;
      case 1: 
        paramParcel1.enforceInterface("com.google.android.gms.ads.internal.mediation.client.IMediationAdapter");
        zzd localzzd7 = zzd.zza.zzdb(paramParcel1.readStrongBinder());
        AdSizeParcel localAdSizeParcel2;
        if (paramParcel1.readInt() != 0)
        {
          localAdSizeParcel2 = com.google.android.gms.ads.internal.client.zzi.zzd(paramParcel1);
          if (paramParcel1.readInt() == 0) {
            break label272;
          }
        }
        for (AdRequestParcel localAdRequestParcel7 = zzg.zzc(paramParcel1);; localAdRequestParcel7 = null)
        {
          zza(localzzd7, localAdSizeParcel2, localAdRequestParcel7, paramParcel1.readString(), zzez.zza.zzK(paramParcel1.readStrongBinder()));
          paramParcel2.writeNoException();
          return true;
          localAdSizeParcel2 = null;
          break;
        }
      case 2: 
        paramParcel1.enforceInterface("com.google.android.gms.ads.internal.mediation.client.IMediationAdapter");
        zzd localzzd6 = getView();
        paramParcel2.writeNoException();
        IBinder localIBinder4 = null;
        if (localzzd6 != null) {
          localIBinder4 = localzzd6.asBinder();
        }
        paramParcel2.writeStrongBinder(localIBinder4);
        return true;
      case 3: 
        paramParcel1.enforceInterface("com.google.android.gms.ads.internal.mediation.client.IMediationAdapter");
        zzd localzzd5 = zzd.zza.zzdb(paramParcel1.readStrongBinder());
        int k = paramParcel1.readInt();
        AdRequestParcel localAdRequestParcel6 = null;
        if (k != 0) {
          localAdRequestParcel6 = zzg.zzc(paramParcel1);
        }
        zza(localzzd5, localAdRequestParcel6, paramParcel1.readString(), zzez.zza.zzK(paramParcel1.readStrongBinder()));
        paramParcel2.writeNoException();
        return true;
      case 4: 
        paramParcel1.enforceInterface("com.google.android.gms.ads.internal.mediation.client.IMediationAdapter");
        showInterstitial();
        paramParcel2.writeNoException();
        return true;
      case 5: 
        paramParcel1.enforceInterface("com.google.android.gms.ads.internal.mediation.client.IMediationAdapter");
        destroy();
        paramParcel2.writeNoException();
        return true;
      case 6: 
        paramParcel1.enforceInterface("com.google.android.gms.ads.internal.mediation.client.IMediationAdapter");
        zzd localzzd4 = zzd.zza.zzdb(paramParcel1.readStrongBinder());
        AdSizeParcel localAdSizeParcel1;
        if (paramParcel1.readInt() != 0)
        {
          localAdSizeParcel1 = com.google.android.gms.ads.internal.client.zzi.zzd(paramParcel1);
          if (paramParcel1.readInt() == 0) {
            break label501;
          }
        }
        for (AdRequestParcel localAdRequestParcel5 = zzg.zzc(paramParcel1);; localAdRequestParcel5 = null)
        {
          zza(localzzd4, localAdSizeParcel1, localAdRequestParcel5, paramParcel1.readString(), paramParcel1.readString(), zzez.zza.zzK(paramParcel1.readStrongBinder()));
          paramParcel2.writeNoException();
          return true;
          localAdSizeParcel1 = null;
          break;
        }
      case 7: 
        paramParcel1.enforceInterface("com.google.android.gms.ads.internal.mediation.client.IMediationAdapter");
        zzd localzzd3 = zzd.zza.zzdb(paramParcel1.readStrongBinder());
        if (paramParcel1.readInt() != 0) {}
        for (AdRequestParcel localAdRequestParcel4 = zzg.zzc(paramParcel1);; localAdRequestParcel4 = null)
        {
          zza(localzzd3, localAdRequestParcel4, paramParcel1.readString(), paramParcel1.readString(), zzez.zza.zzK(paramParcel1.readStrongBinder()));
          paramParcel2.writeNoException();
          return true;
        }
      case 8: 
        paramParcel1.enforceInterface("com.google.android.gms.ads.internal.mediation.client.IMediationAdapter");
        pause();
        paramParcel2.writeNoException();
        return true;
      case 9: 
        paramParcel1.enforceInterface("com.google.android.gms.ads.internal.mediation.client.IMediationAdapter");
        resume();
        paramParcel2.writeNoException();
        return true;
      case 10: 
        paramParcel1.enforceInterface("com.google.android.gms.ads.internal.mediation.client.IMediationAdapter");
        zzd localzzd2 = zzd.zza.zzdb(paramParcel1.readStrongBinder());
        AdRequestParcel localAdRequestParcel3;
        String str3;
        IBinder localIBinder3;
        Object localObject;
        if (paramParcel1.readInt() != 0)
        {
          localAdRequestParcel3 = zzg.zzc(paramParcel1);
          str3 = paramParcel1.readString();
          localIBinder3 = paramParcel1.readStrongBinder();
          if (localIBinder3 != null) {
            break label686;
          }
          localObject = null;
        }
        for (;;)
        {
          zza(localzzd2, localAdRequestParcel3, str3, (zza)localObject, paramParcel1.readString());
          paramParcel2.writeNoException();
          return true;
          localAdRequestParcel3 = null;
          break;
          IInterface localIInterface = localIBinder3.queryLocalInterface("com.google.android.gms.ads.internal.reward.mediation.client.IMediationRewardedVideoAdListener");
          if ((localIInterface != null) && ((localIInterface instanceof zza))) {
            localObject = (zza)localIInterface;
          } else {
            localObject = new zza.zza.zza(localIBinder3);
          }
        }
      case 11: 
        paramParcel1.enforceInterface("com.google.android.gms.ads.internal.mediation.client.IMediationAdapter");
        int j = paramParcel1.readInt();
        AdRequestParcel localAdRequestParcel2 = null;
        if (j != 0) {
          localAdRequestParcel2 = zzg.zzc(paramParcel1);
        }
        zzc(localAdRequestParcel2, paramParcel1.readString());
        paramParcel2.writeNoException();
        return true;
      case 12: 
        paramParcel1.enforceInterface("com.google.android.gms.ads.internal.mediation.client.IMediationAdapter");
        showVideo();
        paramParcel2.writeNoException();
        return true;
      case 13: 
        paramParcel1.enforceInterface("com.google.android.gms.ads.internal.mediation.client.IMediationAdapter");
        boolean bool = isInitialized();
        paramParcel2.writeNoException();
        if (bool) {}
        for (int i = 1;; i = 0)
        {
          paramParcel2.writeInt(i);
          return true;
        }
      case 14: 
        paramParcel1.enforceInterface("com.google.android.gms.ads.internal.mediation.client.IMediationAdapter");
        zzd localzzd1 = zzd.zza.zzdb(paramParcel1.readStrongBinder());
        AdRequestParcel localAdRequestParcel1;
        String str1;
        String str2;
        zzez localzzez;
        if (paramParcel1.readInt() != 0)
        {
          localAdRequestParcel1 = zzg.zzc(paramParcel1);
          str1 = paramParcel1.readString();
          str2 = paramParcel1.readString();
          localzzez = zzez.zza.zzK(paramParcel1.readStrongBinder());
          if (paramParcel1.readInt() == 0) {
            break label936;
          }
        }
        for (NativeAdOptionsParcel localNativeAdOptionsParcel = com.google.android.gms.ads.internal.formats.zzi.zzf(paramParcel1);; localNativeAdOptionsParcel = null)
        {
          zza(localzzd1, localAdRequestParcel1, str1, str2, localzzez, localNativeAdOptionsParcel, paramParcel1.createStringArrayList());
          paramParcel2.writeNoException();
          return true;
          localAdRequestParcel1 = null;
          break;
        }
      case 15: 
        paramParcel1.enforceInterface("com.google.android.gms.ads.internal.mediation.client.IMediationAdapter");
        zzfb localzzfb = zzeD();
        paramParcel2.writeNoException();
        IBinder localIBinder2 = null;
        if (localzzfb != null) {
          localIBinder2 = localzzfb.asBinder();
        }
        paramParcel2.writeStrongBinder(localIBinder2);
        return true;
      case 16: 
        paramParcel1.enforceInterface("com.google.android.gms.ads.internal.mediation.client.IMediationAdapter");
        zzfc localzzfc = zzeE();
        paramParcel2.writeNoException();
        IBinder localIBinder1 = null;
        if (localzzfc != null) {
          localIBinder1 = localzzfc.asBinder();
        }
        paramParcel2.writeStrongBinder(localIBinder1);
        return true;
      case 17: 
        paramParcel1.enforceInterface("com.google.android.gms.ads.internal.mediation.client.IMediationAdapter");
        Bundle localBundle3 = zzeF();
        paramParcel2.writeNoException();
        if (localBundle3 != null)
        {
          paramParcel2.writeInt(1);
          localBundle3.writeToParcel(paramParcel2, 1);
          return true;
        }
        paramParcel2.writeInt(0);
        return true;
      case 18: 
        label272:
        label501:
        paramParcel1.enforceInterface("com.google.android.gms.ads.internal.mediation.client.IMediationAdapter");
        label686:
        Bundle localBundle2 = getInterstitialAdapterInfo();
        label936:
        paramParcel2.writeNoException();
        if (localBundle2 != null)
        {
          paramParcel2.writeInt(1);
          localBundle2.writeToParcel(paramParcel2, 1);
          return true;
        }
        paramParcel2.writeInt(0);
        return true;
      }
      paramParcel1.enforceInterface("com.google.android.gms.ads.internal.mediation.client.IMediationAdapter");
      Bundle localBundle1 = zzeG();
      paramParcel2.writeNoException();
      if (localBundle1 != null)
      {
        paramParcel2.writeInt(1);
        localBundle1.writeToParcel(paramParcel2, 1);
        return true;
      }
      paramParcel2.writeInt(0);
      return true;
    }
    
    private static final class zza
      implements zzey
    {
      private IBinder zzop;
      
      zza(IBinder paramIBinder)
      {
        this.zzop = paramIBinder;
      }
      
      public final IBinder asBinder()
      {
        return this.zzop;
      }
      
      public final void destroy()
        throws RemoteException
      {
        Parcel localParcel1 = Parcel.obtain();
        Parcel localParcel2 = Parcel.obtain();
        try
        {
          localParcel1.writeInterfaceToken("com.google.android.gms.ads.internal.mediation.client.IMediationAdapter");
          this.zzop.transact(5, localParcel1, localParcel2, 0);
          localParcel2.readException();
          return;
        }
        finally
        {
          localParcel2.recycle();
          localParcel1.recycle();
        }
      }
      
      /* Error */
      public final Bundle getInterstitialAdapterInfo()
        throws RemoteException
      {
        // Byte code:
        //   0: invokestatic 26	android/os/Parcel:obtain	()Landroid/os/Parcel;
        //   3: astore_1
        //   4: invokestatic 26	android/os/Parcel:obtain	()Landroid/os/Parcel;
        //   7: astore_2
        //   8: aload_1
        //   9: ldc 28
        //   11: invokevirtual 32	android/os/Parcel:writeInterfaceToken	(Ljava/lang/String;)V
        //   14: aload_0
        //   15: getfield 15	com/google/android/gms/internal/zzey$zza$zza:zzop	Landroid/os/IBinder;
        //   18: bipush 18
        //   20: aload_1
        //   21: aload_2
        //   22: iconst_0
        //   23: invokeinterface 38 5 0
        //   28: pop
        //   29: aload_2
        //   30: invokevirtual 41	android/os/Parcel:readException	()V
        //   33: aload_2
        //   34: invokevirtual 50	android/os/Parcel:readInt	()I
        //   37: ifeq +28 -> 65
        //   40: getstatic 56	android/os/Bundle:CREATOR	Landroid/os/Parcelable$Creator;
        //   43: aload_2
        //   44: invokeinterface 62 2 0
        //   49: checkcast 52	android/os/Bundle
        //   52: astore 5
        //   54: aload_2
        //   55: invokevirtual 44	android/os/Parcel:recycle	()V
        //   58: aload_1
        //   59: invokevirtual 44	android/os/Parcel:recycle	()V
        //   62: aload 5
        //   64: areturn
        //   65: aconst_null
        //   66: astore 5
        //   68: goto -14 -> 54
        //   71: astore_3
        //   72: aload_2
        //   73: invokevirtual 44	android/os/Parcel:recycle	()V
        //   76: aload_1
        //   77: invokevirtual 44	android/os/Parcel:recycle	()V
        //   80: aload_3
        //   81: athrow
        // Local variable table:
        //   start	length	slot	name	signature
        //   0	82	0	this	zza
        //   3	74	1	localParcel1	Parcel
        //   7	66	2	localParcel2	Parcel
        //   71	10	3	localObject	Object
        //   52	15	5	localBundle	Bundle
        // Exception table:
        //   from	to	target	type
        //   8	54	71	finally
      }
      
      public final zzd getView()
        throws RemoteException
      {
        Parcel localParcel1 = Parcel.obtain();
        Parcel localParcel2 = Parcel.obtain();
        try
        {
          localParcel1.writeInterfaceToken("com.google.android.gms.ads.internal.mediation.client.IMediationAdapter");
          this.zzop.transact(2, localParcel1, localParcel2, 0);
          localParcel2.readException();
          zzd localzzd = zzd.zza.zzdb(localParcel2.readStrongBinder());
          return localzzd;
        }
        finally
        {
          localParcel2.recycle();
          localParcel1.recycle();
        }
      }
      
      public final boolean isInitialized()
        throws RemoteException
      {
        Parcel localParcel1 = Parcel.obtain();
        Parcel localParcel2 = Parcel.obtain();
        try
        {
          localParcel1.writeInterfaceToken("com.google.android.gms.ads.internal.mediation.client.IMediationAdapter");
          this.zzop.transact(13, localParcel1, localParcel2, 0);
          localParcel2.readException();
          int i = localParcel2.readInt();
          boolean bool = false;
          if (i != 0) {
            bool = true;
          }
          return bool;
        }
        finally
        {
          localParcel2.recycle();
          localParcel1.recycle();
        }
      }
      
      public final void pause()
        throws RemoteException
      {
        Parcel localParcel1 = Parcel.obtain();
        Parcel localParcel2 = Parcel.obtain();
        try
        {
          localParcel1.writeInterfaceToken("com.google.android.gms.ads.internal.mediation.client.IMediationAdapter");
          this.zzop.transact(8, localParcel1, localParcel2, 0);
          localParcel2.readException();
          return;
        }
        finally
        {
          localParcel2.recycle();
          localParcel1.recycle();
        }
      }
      
      public final void resume()
        throws RemoteException
      {
        Parcel localParcel1 = Parcel.obtain();
        Parcel localParcel2 = Parcel.obtain();
        try
        {
          localParcel1.writeInterfaceToken("com.google.android.gms.ads.internal.mediation.client.IMediationAdapter");
          this.zzop.transact(9, localParcel1, localParcel2, 0);
          localParcel2.readException();
          return;
        }
        finally
        {
          localParcel2.recycle();
          localParcel1.recycle();
        }
      }
      
      public final void showInterstitial()
        throws RemoteException
      {
        Parcel localParcel1 = Parcel.obtain();
        Parcel localParcel2 = Parcel.obtain();
        try
        {
          localParcel1.writeInterfaceToken("com.google.android.gms.ads.internal.mediation.client.IMediationAdapter");
          this.zzop.transact(4, localParcel1, localParcel2, 0);
          localParcel2.readException();
          return;
        }
        finally
        {
          localParcel2.recycle();
          localParcel1.recycle();
        }
      }
      
      public final void showVideo()
        throws RemoteException
      {
        Parcel localParcel1 = Parcel.obtain();
        Parcel localParcel2 = Parcel.obtain();
        try
        {
          localParcel1.writeInterfaceToken("com.google.android.gms.ads.internal.mediation.client.IMediationAdapter");
          this.zzop.transact(12, localParcel1, localParcel2, 0);
          localParcel2.readException();
          return;
        }
        finally
        {
          localParcel2.recycle();
          localParcel1.recycle();
        }
      }
      
      /* Error */
      public final void zza(zzd paramzzd, AdRequestParcel paramAdRequestParcel, String paramString1, zza paramzza, String paramString2)
        throws RemoteException
      {
        // Byte code:
        //   0: invokestatic 26	android/os/Parcel:obtain	()Landroid/os/Parcel;
        //   3: astore 6
        //   5: invokestatic 26	android/os/Parcel:obtain	()Landroid/os/Parcel;
        //   8: astore 7
        //   10: aload 6
        //   12: ldc 28
        //   14: invokevirtual 32	android/os/Parcel:writeInterfaceToken	(Ljava/lang/String;)V
        //   17: aload_1
        //   18: ifnull +105 -> 123
        //   21: aload_1
        //   22: invokeinterface 85 1 0
        //   27: astore 9
        //   29: aload 6
        //   31: aload 9
        //   33: invokevirtual 88	android/os/Parcel:writeStrongBinder	(Landroid/os/IBinder;)V
        //   36: aload_2
        //   37: ifnull +92 -> 129
        //   40: aload 6
        //   42: iconst_1
        //   43: invokevirtual 92	android/os/Parcel:writeInt	(I)V
        //   46: aload_2
        //   47: aload 6
        //   49: iconst_0
        //   50: invokevirtual 98	com/google/android/gms/ads/internal/client/AdRequestParcel:writeToParcel	(Landroid/os/Parcel;I)V
        //   53: aload 6
        //   55: aload_3
        //   56: invokevirtual 101	android/os/Parcel:writeString	(Ljava/lang/String;)V
        //   59: aconst_null
        //   60: astore 10
        //   62: aload 4
        //   64: ifnull +12 -> 76
        //   67: aload 4
        //   69: invokeinterface 104 1 0
        //   74: astore 10
        //   76: aload 6
        //   78: aload 10
        //   80: invokevirtual 88	android/os/Parcel:writeStrongBinder	(Landroid/os/IBinder;)V
        //   83: aload 6
        //   85: aload 5
        //   87: invokevirtual 101	android/os/Parcel:writeString	(Ljava/lang/String;)V
        //   90: aload_0
        //   91: getfield 15	com/google/android/gms/internal/zzey$zza$zza:zzop	Landroid/os/IBinder;
        //   94: bipush 10
        //   96: aload 6
        //   98: aload 7
        //   100: iconst_0
        //   101: invokeinterface 38 5 0
        //   106: pop
        //   107: aload 7
        //   109: invokevirtual 41	android/os/Parcel:readException	()V
        //   112: aload 7
        //   114: invokevirtual 44	android/os/Parcel:recycle	()V
        //   117: aload 6
        //   119: invokevirtual 44	android/os/Parcel:recycle	()V
        //   122: return
        //   123: aconst_null
        //   124: astore 9
        //   126: goto -97 -> 29
        //   129: aload 6
        //   131: iconst_0
        //   132: invokevirtual 92	android/os/Parcel:writeInt	(I)V
        //   135: goto -82 -> 53
        //   138: astore 8
        //   140: aload 7
        //   142: invokevirtual 44	android/os/Parcel:recycle	()V
        //   145: aload 6
        //   147: invokevirtual 44	android/os/Parcel:recycle	()V
        //   150: aload 8
        //   152: athrow
        // Local variable table:
        //   start	length	slot	name	signature
        //   0	153	0	this	zza
        //   0	153	1	paramzzd	zzd
        //   0	153	2	paramAdRequestParcel	AdRequestParcel
        //   0	153	3	paramString1	String
        //   0	153	4	paramzza	zza
        //   0	153	5	paramString2	String
        //   3	143	6	localParcel1	Parcel
        //   8	133	7	localParcel2	Parcel
        //   138	13	8	localObject	Object
        //   27	98	9	localIBinder1	IBinder
        //   60	19	10	localIBinder2	IBinder
        // Exception table:
        //   from	to	target	type
        //   10	17	138	finally
        //   21	29	138	finally
        //   29	36	138	finally
        //   40	53	138	finally
        //   53	59	138	finally
        //   67	76	138	finally
        //   76	112	138	finally
        //   129	135	138	finally
      }
      
      /* Error */
      public final void zza(zzd paramzzd, AdRequestParcel paramAdRequestParcel, String paramString, zzez paramzzez)
        throws RemoteException
      {
        // Byte code:
        //   0: invokestatic 26	android/os/Parcel:obtain	()Landroid/os/Parcel;
        //   3: astore 5
        //   5: invokestatic 26	android/os/Parcel:obtain	()Landroid/os/Parcel;
        //   8: astore 6
        //   10: aload 5
        //   12: ldc 28
        //   14: invokevirtual 32	android/os/Parcel:writeInterfaceToken	(Ljava/lang/String;)V
        //   17: aload_1
        //   18: ifnull +97 -> 115
        //   21: aload_1
        //   22: invokeinterface 85 1 0
        //   27: astore 8
        //   29: aload 5
        //   31: aload 8
        //   33: invokevirtual 88	android/os/Parcel:writeStrongBinder	(Landroid/os/IBinder;)V
        //   36: aload_2
        //   37: ifnull +84 -> 121
        //   40: aload 5
        //   42: iconst_1
        //   43: invokevirtual 92	android/os/Parcel:writeInt	(I)V
        //   46: aload_2
        //   47: aload 5
        //   49: iconst_0
        //   50: invokevirtual 98	com/google/android/gms/ads/internal/client/AdRequestParcel:writeToParcel	(Landroid/os/Parcel;I)V
        //   53: aload 5
        //   55: aload_3
        //   56: invokevirtual 101	android/os/Parcel:writeString	(Ljava/lang/String;)V
        //   59: aconst_null
        //   60: astore 9
        //   62: aload 4
        //   64: ifnull +12 -> 76
        //   67: aload 4
        //   69: invokeinterface 108 1 0
        //   74: astore 9
        //   76: aload 5
        //   78: aload 9
        //   80: invokevirtual 88	android/os/Parcel:writeStrongBinder	(Landroid/os/IBinder;)V
        //   83: aload_0
        //   84: getfield 15	com/google/android/gms/internal/zzey$zza$zza:zzop	Landroid/os/IBinder;
        //   87: iconst_3
        //   88: aload 5
        //   90: aload 6
        //   92: iconst_0
        //   93: invokeinterface 38 5 0
        //   98: pop
        //   99: aload 6
        //   101: invokevirtual 41	android/os/Parcel:readException	()V
        //   104: aload 6
        //   106: invokevirtual 44	android/os/Parcel:recycle	()V
        //   109: aload 5
        //   111: invokevirtual 44	android/os/Parcel:recycle	()V
        //   114: return
        //   115: aconst_null
        //   116: astore 8
        //   118: goto -89 -> 29
        //   121: aload 5
        //   123: iconst_0
        //   124: invokevirtual 92	android/os/Parcel:writeInt	(I)V
        //   127: goto -74 -> 53
        //   130: astore 7
        //   132: aload 6
        //   134: invokevirtual 44	android/os/Parcel:recycle	()V
        //   137: aload 5
        //   139: invokevirtual 44	android/os/Parcel:recycle	()V
        //   142: aload 7
        //   144: athrow
        // Local variable table:
        //   start	length	slot	name	signature
        //   0	145	0	this	zza
        //   0	145	1	paramzzd	zzd
        //   0	145	2	paramAdRequestParcel	AdRequestParcel
        //   0	145	3	paramString	String
        //   0	145	4	paramzzez	zzez
        //   3	135	5	localParcel1	Parcel
        //   8	125	6	localParcel2	Parcel
        //   130	13	7	localObject	Object
        //   27	90	8	localIBinder1	IBinder
        //   60	19	9	localIBinder2	IBinder
        // Exception table:
        //   from	to	target	type
        //   10	17	130	finally
        //   21	29	130	finally
        //   29	36	130	finally
        //   40	53	130	finally
        //   53	59	130	finally
        //   67	76	130	finally
        //   76	104	130	finally
        //   121	127	130	finally
      }
      
      /* Error */
      public final void zza(zzd paramzzd, AdRequestParcel paramAdRequestParcel, String paramString1, String paramString2, zzez paramzzez)
        throws RemoteException
      {
        // Byte code:
        //   0: invokestatic 26	android/os/Parcel:obtain	()Landroid/os/Parcel;
        //   3: astore 6
        //   5: invokestatic 26	android/os/Parcel:obtain	()Landroid/os/Parcel;
        //   8: astore 7
        //   10: aload 6
        //   12: ldc 28
        //   14: invokevirtual 32	android/os/Parcel:writeInterfaceToken	(Ljava/lang/String;)V
        //   17: aload_1
        //   18: ifnull +105 -> 123
        //   21: aload_1
        //   22: invokeinterface 85 1 0
        //   27: astore 9
        //   29: aload 6
        //   31: aload 9
        //   33: invokevirtual 88	android/os/Parcel:writeStrongBinder	(Landroid/os/IBinder;)V
        //   36: aload_2
        //   37: ifnull +92 -> 129
        //   40: aload 6
        //   42: iconst_1
        //   43: invokevirtual 92	android/os/Parcel:writeInt	(I)V
        //   46: aload_2
        //   47: aload 6
        //   49: iconst_0
        //   50: invokevirtual 98	com/google/android/gms/ads/internal/client/AdRequestParcel:writeToParcel	(Landroid/os/Parcel;I)V
        //   53: aload 6
        //   55: aload_3
        //   56: invokevirtual 101	android/os/Parcel:writeString	(Ljava/lang/String;)V
        //   59: aload 6
        //   61: aload 4
        //   63: invokevirtual 101	android/os/Parcel:writeString	(Ljava/lang/String;)V
        //   66: aconst_null
        //   67: astore 10
        //   69: aload 5
        //   71: ifnull +12 -> 83
        //   74: aload 5
        //   76: invokeinterface 108 1 0
        //   81: astore 10
        //   83: aload 6
        //   85: aload 10
        //   87: invokevirtual 88	android/os/Parcel:writeStrongBinder	(Landroid/os/IBinder;)V
        //   90: aload_0
        //   91: getfield 15	com/google/android/gms/internal/zzey$zza$zza:zzop	Landroid/os/IBinder;
        //   94: bipush 7
        //   96: aload 6
        //   98: aload 7
        //   100: iconst_0
        //   101: invokeinterface 38 5 0
        //   106: pop
        //   107: aload 7
        //   109: invokevirtual 41	android/os/Parcel:readException	()V
        //   112: aload 7
        //   114: invokevirtual 44	android/os/Parcel:recycle	()V
        //   117: aload 6
        //   119: invokevirtual 44	android/os/Parcel:recycle	()V
        //   122: return
        //   123: aconst_null
        //   124: astore 9
        //   126: goto -97 -> 29
        //   129: aload 6
        //   131: iconst_0
        //   132: invokevirtual 92	android/os/Parcel:writeInt	(I)V
        //   135: goto -82 -> 53
        //   138: astore 8
        //   140: aload 7
        //   142: invokevirtual 44	android/os/Parcel:recycle	()V
        //   145: aload 6
        //   147: invokevirtual 44	android/os/Parcel:recycle	()V
        //   150: aload 8
        //   152: athrow
        // Local variable table:
        //   start	length	slot	name	signature
        //   0	153	0	this	zza
        //   0	153	1	paramzzd	zzd
        //   0	153	2	paramAdRequestParcel	AdRequestParcel
        //   0	153	3	paramString1	String
        //   0	153	4	paramString2	String
        //   0	153	5	paramzzez	zzez
        //   3	143	6	localParcel1	Parcel
        //   8	133	7	localParcel2	Parcel
        //   138	13	8	localObject	Object
        //   27	98	9	localIBinder1	IBinder
        //   67	19	10	localIBinder2	IBinder
        // Exception table:
        //   from	to	target	type
        //   10	17	138	finally
        //   21	29	138	finally
        //   29	36	138	finally
        //   40	53	138	finally
        //   53	66	138	finally
        //   74	83	138	finally
        //   83	112	138	finally
        //   129	135	138	finally
      }
      
      public final void zza(zzd paramzzd, AdRequestParcel paramAdRequestParcel, String paramString1, String paramString2, zzez paramzzez, NativeAdOptionsParcel paramNativeAdOptionsParcel, List<String> paramList)
        throws RemoteException
      {
        Parcel localParcel1 = Parcel.obtain();
        Parcel localParcel2 = Parcel.obtain();
        label179:
        for (;;)
        {
          try
          {
            localParcel1.writeInterfaceToken("com.google.android.gms.ads.internal.mediation.client.IMediationAdapter");
            IBinder localIBinder1;
            if (paramzzd != null)
            {
              localIBinder1 = paramzzd.asBinder();
              localParcel1.writeStrongBinder(localIBinder1);
              if (paramAdRequestParcel != null)
              {
                localParcel1.writeInt(1);
                paramAdRequestParcel.writeToParcel(localParcel1, 0);
                localParcel1.writeString(paramString1);
                localParcel1.writeString(paramString2);
                IBinder localIBinder2 = null;
                if (paramzzez != null) {
                  localIBinder2 = paramzzez.asBinder();
                }
                localParcel1.writeStrongBinder(localIBinder2);
                if (paramNativeAdOptionsParcel == null) {
                  break label179;
                }
                localParcel1.writeInt(1);
                paramNativeAdOptionsParcel.writeToParcel(localParcel1, 0);
                localParcel1.writeStringList(paramList);
                this.zzop.transact(14, localParcel1, localParcel2, 0);
                localParcel2.readException();
              }
            }
            else
            {
              localIBinder1 = null;
              continue;
            }
            localParcel1.writeInt(0);
            continue;
            localParcel1.writeInt(0);
          }
          finally
          {
            localParcel2.recycle();
            localParcel1.recycle();
          }
        }
      }
      
      public final void zza(zzd paramzzd, AdSizeParcel paramAdSizeParcel, AdRequestParcel paramAdRequestParcel, String paramString, zzez paramzzez)
        throws RemoteException
      {
        Parcel localParcel1 = Parcel.obtain();
        Parcel localParcel2 = Parcel.obtain();
        label163:
        for (;;)
        {
          try
          {
            localParcel1.writeInterfaceToken("com.google.android.gms.ads.internal.mediation.client.IMediationAdapter");
            IBinder localIBinder1;
            if (paramzzd != null)
            {
              localIBinder1 = paramzzd.asBinder();
              localParcel1.writeStrongBinder(localIBinder1);
              if (paramAdSizeParcel != null)
              {
                localParcel1.writeInt(1);
                paramAdSizeParcel.writeToParcel(localParcel1, 0);
                if (paramAdRequestParcel == null) {
                  break label163;
                }
                localParcel1.writeInt(1);
                paramAdRequestParcel.writeToParcel(localParcel1, 0);
                localParcel1.writeString(paramString);
                IBinder localIBinder2 = null;
                if (paramzzez != null) {
                  localIBinder2 = paramzzez.asBinder();
                }
                localParcel1.writeStrongBinder(localIBinder2);
                this.zzop.transact(1, localParcel1, localParcel2, 0);
                localParcel2.readException();
              }
            }
            else
            {
              localIBinder1 = null;
              continue;
            }
            localParcel1.writeInt(0);
            continue;
            localParcel1.writeInt(0);
          }
          finally
          {
            localParcel2.recycle();
            localParcel1.recycle();
          }
        }
      }
      
      public final void zza(zzd paramzzd, AdSizeParcel paramAdSizeParcel, AdRequestParcel paramAdRequestParcel, String paramString1, String paramString2, zzez paramzzez)
        throws RemoteException
      {
        Parcel localParcel1 = Parcel.obtain();
        Parcel localParcel2 = Parcel.obtain();
        label171:
        for (;;)
        {
          try
          {
            localParcel1.writeInterfaceToken("com.google.android.gms.ads.internal.mediation.client.IMediationAdapter");
            IBinder localIBinder1;
            if (paramzzd != null)
            {
              localIBinder1 = paramzzd.asBinder();
              localParcel1.writeStrongBinder(localIBinder1);
              if (paramAdSizeParcel != null)
              {
                localParcel1.writeInt(1);
                paramAdSizeParcel.writeToParcel(localParcel1, 0);
                if (paramAdRequestParcel == null) {
                  break label171;
                }
                localParcel1.writeInt(1);
                paramAdRequestParcel.writeToParcel(localParcel1, 0);
                localParcel1.writeString(paramString1);
                localParcel1.writeString(paramString2);
                IBinder localIBinder2 = null;
                if (paramzzez != null) {
                  localIBinder2 = paramzzez.asBinder();
                }
                localParcel1.writeStrongBinder(localIBinder2);
                this.zzop.transact(6, localParcel1, localParcel2, 0);
                localParcel2.readException();
              }
            }
            else
            {
              localIBinder1 = null;
              continue;
            }
            localParcel1.writeInt(0);
            continue;
            localParcel1.writeInt(0);
          }
          finally
          {
            localParcel2.recycle();
            localParcel1.recycle();
          }
        }
      }
      
      /* Error */
      public final void zzc(AdRequestParcel paramAdRequestParcel, String paramString)
        throws RemoteException
      {
        // Byte code:
        //   0: invokestatic 26	android/os/Parcel:obtain	()Landroid/os/Parcel;
        //   3: astore_3
        //   4: invokestatic 26	android/os/Parcel:obtain	()Landroid/os/Parcel;
        //   7: astore 4
        //   9: aload_3
        //   10: ldc 28
        //   12: invokevirtual 32	android/os/Parcel:writeInterfaceToken	(Ljava/lang/String;)V
        //   15: aload_1
        //   16: ifnull +50 -> 66
        //   19: aload_3
        //   20: iconst_1
        //   21: invokevirtual 92	android/os/Parcel:writeInt	(I)V
        //   24: aload_1
        //   25: aload_3
        //   26: iconst_0
        //   27: invokevirtual 98	com/google/android/gms/ads/internal/client/AdRequestParcel:writeToParcel	(Landroid/os/Parcel;I)V
        //   30: aload_3
        //   31: aload_2
        //   32: invokevirtual 101	android/os/Parcel:writeString	(Ljava/lang/String;)V
        //   35: aload_0
        //   36: getfield 15	com/google/android/gms/internal/zzey$zza$zza:zzop	Landroid/os/IBinder;
        //   39: bipush 11
        //   41: aload_3
        //   42: aload 4
        //   44: iconst_0
        //   45: invokeinterface 38 5 0
        //   50: pop
        //   51: aload 4
        //   53: invokevirtual 41	android/os/Parcel:readException	()V
        //   56: aload 4
        //   58: invokevirtual 44	android/os/Parcel:recycle	()V
        //   61: aload_3
        //   62: invokevirtual 44	android/os/Parcel:recycle	()V
        //   65: return
        //   66: aload_3
        //   67: iconst_0
        //   68: invokevirtual 92	android/os/Parcel:writeInt	(I)V
        //   71: goto -41 -> 30
        //   74: astore 5
        //   76: aload 4
        //   78: invokevirtual 44	android/os/Parcel:recycle	()V
        //   81: aload_3
        //   82: invokevirtual 44	android/os/Parcel:recycle	()V
        //   85: aload 5
        //   87: athrow
        // Local variable table:
        //   start	length	slot	name	signature
        //   0	88	0	this	zza
        //   0	88	1	paramAdRequestParcel	AdRequestParcel
        //   0	88	2	paramString	String
        //   3	79	3	localParcel1	Parcel
        //   7	70	4	localParcel2	Parcel
        //   74	12	5	localObject	Object
        // Exception table:
        //   from	to	target	type
        //   9	15	74	finally
        //   19	30	74	finally
        //   30	56	74	finally
        //   66	71	74	finally
      }
      
      public final zzfb zzeD()
        throws RemoteException
      {
        Parcel localParcel1 = Parcel.obtain();
        Parcel localParcel2 = Parcel.obtain();
        try
        {
          localParcel1.writeInterfaceToken("com.google.android.gms.ads.internal.mediation.client.IMediationAdapter");
          this.zzop.transact(15, localParcel1, localParcel2, 0);
          localParcel2.readException();
          zzfb localzzfb = zzfb.zza.zzM(localParcel2.readStrongBinder());
          return localzzfb;
        }
        finally
        {
          localParcel2.recycle();
          localParcel1.recycle();
        }
      }
      
      public final zzfc zzeE()
        throws RemoteException
      {
        Parcel localParcel1 = Parcel.obtain();
        Parcel localParcel2 = Parcel.obtain();
        try
        {
          localParcel1.writeInterfaceToken("com.google.android.gms.ads.internal.mediation.client.IMediationAdapter");
          this.zzop.transact(16, localParcel1, localParcel2, 0);
          localParcel2.readException();
          zzfc localzzfc = zzfc.zza.zzN(localParcel2.readStrongBinder());
          return localzzfc;
        }
        finally
        {
          localParcel2.recycle();
          localParcel1.recycle();
        }
      }
      
      /* Error */
      public final Bundle zzeF()
        throws RemoteException
      {
        // Byte code:
        //   0: invokestatic 26	android/os/Parcel:obtain	()Landroid/os/Parcel;
        //   3: astore_1
        //   4: invokestatic 26	android/os/Parcel:obtain	()Landroid/os/Parcel;
        //   7: astore_2
        //   8: aload_1
        //   9: ldc 28
        //   11: invokevirtual 32	android/os/Parcel:writeInterfaceToken	(Ljava/lang/String;)V
        //   14: aload_0
        //   15: getfield 15	com/google/android/gms/internal/zzey$zza$zza:zzop	Landroid/os/IBinder;
        //   18: bipush 17
        //   20: aload_1
        //   21: aload_2
        //   22: iconst_0
        //   23: invokeinterface 38 5 0
        //   28: pop
        //   29: aload_2
        //   30: invokevirtual 41	android/os/Parcel:readException	()V
        //   33: aload_2
        //   34: invokevirtual 50	android/os/Parcel:readInt	()I
        //   37: ifeq +28 -> 65
        //   40: getstatic 56	android/os/Bundle:CREATOR	Landroid/os/Parcelable$Creator;
        //   43: aload_2
        //   44: invokeinterface 62 2 0
        //   49: checkcast 52	android/os/Bundle
        //   52: astore 5
        //   54: aload_2
        //   55: invokevirtual 44	android/os/Parcel:recycle	()V
        //   58: aload_1
        //   59: invokevirtual 44	android/os/Parcel:recycle	()V
        //   62: aload 5
        //   64: areturn
        //   65: aconst_null
        //   66: astore 5
        //   68: goto -14 -> 54
        //   71: astore_3
        //   72: aload_2
        //   73: invokevirtual 44	android/os/Parcel:recycle	()V
        //   76: aload_1
        //   77: invokevirtual 44	android/os/Parcel:recycle	()V
        //   80: aload_3
        //   81: athrow
        // Local variable table:
        //   start	length	slot	name	signature
        //   0	82	0	this	zza
        //   3	74	1	localParcel1	Parcel
        //   7	66	2	localParcel2	Parcel
        //   71	10	3	localObject	Object
        //   52	15	5	localBundle	Bundle
        // Exception table:
        //   from	to	target	type
        //   8	54	71	finally
      }
      
      /* Error */
      public final Bundle zzeG()
        throws RemoteException
      {
        // Byte code:
        //   0: invokestatic 26	android/os/Parcel:obtain	()Landroid/os/Parcel;
        //   3: astore_1
        //   4: invokestatic 26	android/os/Parcel:obtain	()Landroid/os/Parcel;
        //   7: astore_2
        //   8: aload_1
        //   9: ldc 28
        //   11: invokevirtual 32	android/os/Parcel:writeInterfaceToken	(Ljava/lang/String;)V
        //   14: aload_0
        //   15: getfield 15	com/google/android/gms/internal/zzey$zza$zza:zzop	Landroid/os/IBinder;
        //   18: bipush 19
        //   20: aload_1
        //   21: aload_2
        //   22: iconst_0
        //   23: invokeinterface 38 5 0
        //   28: pop
        //   29: aload_2
        //   30: invokevirtual 41	android/os/Parcel:readException	()V
        //   33: aload_2
        //   34: invokevirtual 50	android/os/Parcel:readInt	()I
        //   37: ifeq +28 -> 65
        //   40: getstatic 56	android/os/Bundle:CREATOR	Landroid/os/Parcelable$Creator;
        //   43: aload_2
        //   44: invokeinterface 62 2 0
        //   49: checkcast 52	android/os/Bundle
        //   52: astore 5
        //   54: aload_2
        //   55: invokevirtual 44	android/os/Parcel:recycle	()V
        //   58: aload_1
        //   59: invokevirtual 44	android/os/Parcel:recycle	()V
        //   62: aload 5
        //   64: areturn
        //   65: aconst_null
        //   66: astore 5
        //   68: goto -14 -> 54
        //   71: astore_3
        //   72: aload_2
        //   73: invokevirtual 44	android/os/Parcel:recycle	()V
        //   76: aload_1
        //   77: invokevirtual 44	android/os/Parcel:recycle	()V
        //   80: aload_3
        //   81: athrow
        // Local variable table:
        //   start	length	slot	name	signature
        //   0	82	0	this	zza
        //   3	74	1	localParcel1	Parcel
        //   7	66	2	localParcel2	Parcel
        //   71	10	3	localObject	Object
        //   52	15	5	localBundle	Bundle
        // Exception table:
        //   from	to	target	type
        //   8	54	71	finally
      }
    }
  }
}


/* Location:           F:\apktool\apktool\Google_Play_Store6.0.5\classes-dex2jar.jar
 * Qualified Name:     com.google.android.gms.internal.zzey
 * JD-Core Version:    0.7.0.1
 */