package com.google.android.gms.internal;

import android.content.Intent;
import android.os.Binder;
import android.os.IBinder;
import android.os.IInterface;
import android.os.Parcel;
import android.os.Parcelable.Creator;
import android.os.RemoteException;

public abstract interface zzge
  extends IInterface
{
  public abstract void onActivityResult(int paramInt1, int paramInt2, Intent paramIntent)
    throws RemoteException;
  
  public abstract void onCreate()
    throws RemoteException;
  
  public abstract void onDestroy()
    throws RemoteException;
  
  public static abstract class zza
    extends Binder
    implements zzge
  {
    public zza()
    {
      attachInterface(this, "com.google.android.gms.ads.internal.purchase.client.IInAppPurchaseManager");
    }
    
    public static zzge zzU(IBinder paramIBinder)
    {
      if (paramIBinder == null) {
        return null;
      }
      IInterface localIInterface = paramIBinder.queryLocalInterface("com.google.android.gms.ads.internal.purchase.client.IInAppPurchaseManager");
      if ((localIInterface != null) && ((localIInterface instanceof zzge))) {
        return (zzge)localIInterface;
      }
      return new zza(paramIBinder);
    }
    
    public IBinder asBinder()
    {
      return this;
    }
    
    public boolean onTransact(int paramInt1, Parcel paramParcel1, Parcel paramParcel2, int paramInt2)
      throws RemoteException
    {
      switch (paramInt1)
      {
      default: 
        return super.onTransact(paramInt1, paramParcel1, paramParcel2, paramInt2);
      case 1598968902: 
        paramParcel2.writeString("com.google.android.gms.ads.internal.purchase.client.IInAppPurchaseManager");
        return true;
      case 1: 
        paramParcel1.enforceInterface("com.google.android.gms.ads.internal.purchase.client.IInAppPurchaseManager");
        onCreate();
        paramParcel2.writeNoException();
        return true;
      case 2: 
        paramParcel1.enforceInterface("com.google.android.gms.ads.internal.purchase.client.IInAppPurchaseManager");
        onDestroy();
        paramParcel2.writeNoException();
        return true;
      }
      paramParcel1.enforceInterface("com.google.android.gms.ads.internal.purchase.client.IInAppPurchaseManager");
      int i = paramParcel1.readInt();
      int j = paramParcel1.readInt();
      if (paramParcel1.readInt() != 0) {}
      for (Intent localIntent = (Intent)Intent.CREATOR.createFromParcel(paramParcel1);; localIntent = null)
      {
        onActivityResult(i, j, localIntent);
        paramParcel2.writeNoException();
        return true;
      }
    }
    
    private static final class zza
      implements zzge
    {
      private IBinder zzop;
      
      zza(IBinder paramIBinder)
      {
        this.zzop = paramIBinder;
      }
      
      public final IBinder asBinder()
      {
        return this.zzop;
      }
      
      /* Error */
      public final void onActivityResult(int paramInt1, int paramInt2, Intent paramIntent)
        throws RemoteException
      {
        // Byte code:
        //   0: invokestatic 27	android/os/Parcel:obtain	()Landroid/os/Parcel;
        //   3: astore 4
        //   5: invokestatic 27	android/os/Parcel:obtain	()Landroid/os/Parcel;
        //   8: astore 5
        //   10: aload 4
        //   12: ldc 29
        //   14: invokevirtual 33	android/os/Parcel:writeInterfaceToken	(Ljava/lang/String;)V
        //   17: aload 4
        //   19: iload_1
        //   20: invokevirtual 37	android/os/Parcel:writeInt	(I)V
        //   23: aload 4
        //   25: iload_2
        //   26: invokevirtual 37	android/os/Parcel:writeInt	(I)V
        //   29: aload_3
        //   30: ifnull +48 -> 78
        //   33: aload 4
        //   35: iconst_1
        //   36: invokevirtual 37	android/os/Parcel:writeInt	(I)V
        //   39: aload_3
        //   40: aload 4
        //   42: iconst_0
        //   43: invokevirtual 43	android/content/Intent:writeToParcel	(Landroid/os/Parcel;I)V
        //   46: aload_0
        //   47: getfield 15	com/google/android/gms/internal/zzge$zza$zza:zzop	Landroid/os/IBinder;
        //   50: iconst_3
        //   51: aload 4
        //   53: aload 5
        //   55: iconst_0
        //   56: invokeinterface 49 5 0
        //   61: pop
        //   62: aload 5
        //   64: invokevirtual 52	android/os/Parcel:readException	()V
        //   67: aload 5
        //   69: invokevirtual 55	android/os/Parcel:recycle	()V
        //   72: aload 4
        //   74: invokevirtual 55	android/os/Parcel:recycle	()V
        //   77: return
        //   78: aload 4
        //   80: iconst_0
        //   81: invokevirtual 37	android/os/Parcel:writeInt	(I)V
        //   84: goto -38 -> 46
        //   87: astore 6
        //   89: aload 5
        //   91: invokevirtual 55	android/os/Parcel:recycle	()V
        //   94: aload 4
        //   96: invokevirtual 55	android/os/Parcel:recycle	()V
        //   99: aload 6
        //   101: athrow
        // Local variable table:
        //   start	length	slot	name	signature
        //   0	102	0	this	zza
        //   0	102	1	paramInt1	int
        //   0	102	2	paramInt2	int
        //   0	102	3	paramIntent	Intent
        //   3	92	4	localParcel1	Parcel
        //   8	82	5	localParcel2	Parcel
        //   87	13	6	localObject	Object
        // Exception table:
        //   from	to	target	type
        //   10	29	87	finally
        //   33	46	87	finally
        //   46	67	87	finally
        //   78	84	87	finally
      }
      
      public final void onCreate()
        throws RemoteException
      {
        Parcel localParcel1 = Parcel.obtain();
        Parcel localParcel2 = Parcel.obtain();
        try
        {
          localParcel1.writeInterfaceToken("com.google.android.gms.ads.internal.purchase.client.IInAppPurchaseManager");
          this.zzop.transact(1, localParcel1, localParcel2, 0);
          localParcel2.readException();
          return;
        }
        finally
        {
          localParcel2.recycle();
          localParcel1.recycle();
        }
      }
      
      public final void onDestroy()
        throws RemoteException
      {
        Parcel localParcel1 = Parcel.obtain();
        Parcel localParcel2 = Parcel.obtain();
        try
        {
          localParcel1.writeInterfaceToken("com.google.android.gms.ads.internal.purchase.client.IInAppPurchaseManager");
          this.zzop.transact(2, localParcel1, localParcel2, 0);
          localParcel2.readException();
          return;
        }
        finally
        {
          localParcel2.recycle();
          localParcel1.recycle();
        }
      }
    }
  }
}


/* Location:           F:\apktool\apktool\Google_Play_Store6.0.5\classes-dex2jar.jar
 * Qualified Name:     com.google.android.gms.internal.zzge
 * JD-Core Version:    0.7.0.1
 */