package com.android.i18n.addressinput;

public final class NotifyingListener
  implements DataLoadListener
{
  private boolean mDone;
  private Object mSleeper;
  
  NotifyingListener(Object paramObject)
  {
    this.mSleeper = paramObject;
    this.mDone = false;
  }
  
  /* Error */
  public final void dataLoadingEnd()
  {
    // Byte code:
    //   0: aload_0
    //   1: monitorenter
    //   2: aload_0
    //   3: iconst_1
    //   4: putfield 19	com/android/i18n/addressinput/NotifyingListener:mDone	Z
    //   7: aload_0
    //   8: monitorexit
    //   9: aload_0
    //   10: getfield 17	com/android/i18n/addressinput/NotifyingListener:mSleeper	Ljava/lang/Object;
    //   13: astore_2
    //   14: aload_2
    //   15: monitorenter
    //   16: aload_0
    //   17: getfield 17	com/android/i18n/addressinput/NotifyingListener:mSleeper	Ljava/lang/Object;
    //   20: invokevirtual 23	java/lang/Object:notify	()V
    //   23: aload_2
    //   24: monitorexit
    //   25: return
    //   26: astore_1
    //   27: aload_0
    //   28: monitorexit
    //   29: aload_1
    //   30: athrow
    //   31: astore_3
    //   32: aload_2
    //   33: monitorexit
    //   34: aload_3
    //   35: athrow
    // Local variable table:
    //   start	length	slot	name	signature
    //   0	36	0	this	NotifyingListener
    //   26	4	1	localObject1	Object
    //   31	4	3	localObject3	Object
    // Exception table:
    //   from	to	target	type
    //   2	9	26	finally
    //   27	29	26	finally
    //   16	25	31	finally
    //   32	34	31	finally
  }
  
  /* Error */
  final void waitLoadingEnd()
    throws java.lang.InterruptedException
  {
    // Byte code:
    //   0: aload_0
    //   1: monitorenter
    //   2: aload_0
    //   3: getfield 19	com/android/i18n/addressinput/NotifyingListener:mDone	Z
    //   6: ifeq +6 -> 12
    //   9: aload_0
    //   10: monitorexit
    //   11: return
    //   12: aload_0
    //   13: monitorexit
    //   14: aload_0
    //   15: getfield 17	com/android/i18n/addressinput/NotifyingListener:mSleeper	Ljava/lang/Object;
    //   18: astore_2
    //   19: aload_2
    //   20: monitorenter
    //   21: aload_0
    //   22: getfield 17	com/android/i18n/addressinput/NotifyingListener:mSleeper	Ljava/lang/Object;
    //   25: invokevirtual 29	java/lang/Object:wait	()V
    //   28: aload_2
    //   29: monitorexit
    //   30: return
    //   31: astore_3
    //   32: aload_2
    //   33: monitorexit
    //   34: aload_3
    //   35: athrow
    //   36: astore_1
    //   37: aload_0
    //   38: monitorexit
    //   39: aload_1
    //   40: athrow
    // Local variable table:
    //   start	length	slot	name	signature
    //   0	41	0	this	NotifyingListener
    //   36	4	1	localObject1	Object
    //   31	4	3	localObject3	Object
    // Exception table:
    //   from	to	target	type
    //   21	30	31	finally
    //   32	34	31	finally
    //   2	11	36	finally
    //   12	14	36	finally
    //   37	39	36	finally
  }
}


/* Location:           F:\apktool\apktool\Google_Play_Store6.0.5\classes-dex2jar.jar
 * Qualified Name:     com.android.i18n.addressinput.NotifyingListener
 * JD-Core Version:    0.7.0.1
 */