package com.google.android.gms.googlehelp.internal.common;

import android.os.Binder;
import android.os.IBinder;
import android.os.IInterface;
import android.os.Parcel;
import android.os.Parcelable.Creator;
import android.os.RemoteException;
import com.google.android.gms.googlehelp.GoogleHelp;

public abstract interface zze
  extends IInterface
{
  public abstract void onGoogleHelpProcessed(GoogleHelp paramGoogleHelp)
    throws RemoteException;
  
  public abstract void onPipClick()
    throws RemoteException;
  
  public abstract void onPipInCallingAppDisabled()
    throws RemoteException;
  
  public abstract void onPipInCallingAppHidden()
    throws RemoteException;
  
  public abstract void onPipShown()
    throws RemoteException;
  
  public abstract void onTogglingPipProcessed(TogglingData paramTogglingData)
    throws RemoteException;
  
  public static abstract class zza
    extends Binder
    implements zze
  {
    public zza()
    {
      attachInterface(this, "com.google.android.gms.googlehelp.internal.common.IGoogleHelpCallbacks");
    }
    
    public static zze zzdN(IBinder paramIBinder)
    {
      if (paramIBinder == null) {
        return null;
      }
      IInterface localIInterface = paramIBinder.queryLocalInterface("com.google.android.gms.googlehelp.internal.common.IGoogleHelpCallbacks");
      if ((localIInterface != null) && ((localIInterface instanceof zze))) {
        return (zze)localIInterface;
      }
      return new zza(paramIBinder);
    }
    
    public IBinder asBinder()
    {
      return this;
    }
    
    public boolean onTransact(int paramInt1, Parcel paramParcel1, Parcel paramParcel2, int paramInt2)
      throws RemoteException
    {
      switch (paramInt1)
      {
      default: 
        return super.onTransact(paramInt1, paramParcel1, paramParcel2, paramInt2);
      case 1598968902: 
        paramParcel2.writeString("com.google.android.gms.googlehelp.internal.common.IGoogleHelpCallbacks");
        return true;
      case 1: 
        paramParcel1.enforceInterface("com.google.android.gms.googlehelp.internal.common.IGoogleHelpCallbacks");
        int j = paramParcel1.readInt();
        GoogleHelp localGoogleHelp = null;
        if (j != 0) {
          localGoogleHelp = (GoogleHelp)GoogleHelp.CREATOR.createFromParcel(paramParcel1);
        }
        onGoogleHelpProcessed(localGoogleHelp);
        paramParcel2.writeNoException();
        return true;
      case 2: 
        paramParcel1.enforceInterface("com.google.android.gms.googlehelp.internal.common.IGoogleHelpCallbacks");
        int i = paramParcel1.readInt();
        TogglingData localTogglingData = null;
        if (i != 0) {
          localTogglingData = (TogglingData)TogglingData.CREATOR.createFromParcel(paramParcel1);
        }
        onTogglingPipProcessed(localTogglingData);
        paramParcel2.writeNoException();
        return true;
      case 3: 
        paramParcel1.enforceInterface("com.google.android.gms.googlehelp.internal.common.IGoogleHelpCallbacks");
        onPipShown();
        paramParcel2.writeNoException();
        return true;
      case 4: 
        paramParcel1.enforceInterface("com.google.android.gms.googlehelp.internal.common.IGoogleHelpCallbacks");
        onPipClick();
        paramParcel2.writeNoException();
        return true;
      case 5: 
        paramParcel1.enforceInterface("com.google.android.gms.googlehelp.internal.common.IGoogleHelpCallbacks");
        onPipInCallingAppHidden();
        paramParcel2.writeNoException();
        return true;
      }
      paramParcel1.enforceInterface("com.google.android.gms.googlehelp.internal.common.IGoogleHelpCallbacks");
      onPipInCallingAppDisabled();
      paramParcel2.writeNoException();
      return true;
    }
    
    private static final class zza
      implements zze
    {
      private IBinder zzop;
      
      zza(IBinder paramIBinder)
      {
        this.zzop = paramIBinder;
      }
      
      public final IBinder asBinder()
      {
        return this.zzop;
      }
      
      /* Error */
      public final void onGoogleHelpProcessed(GoogleHelp paramGoogleHelp)
        throws RemoteException
      {
        // Byte code:
        //   0: invokestatic 27	android/os/Parcel:obtain	()Landroid/os/Parcel;
        //   3: astore_2
        //   4: invokestatic 27	android/os/Parcel:obtain	()Landroid/os/Parcel;
        //   7: astore_3
        //   8: aload_2
        //   9: ldc 29
        //   11: invokevirtual 33	android/os/Parcel:writeInterfaceToken	(Ljava/lang/String;)V
        //   14: aload_1
        //   15: ifnull +41 -> 56
        //   18: aload_2
        //   19: iconst_1
        //   20: invokevirtual 37	android/os/Parcel:writeInt	(I)V
        //   23: aload_1
        //   24: aload_2
        //   25: iconst_0
        //   26: invokevirtual 43	com/google/android/gms/googlehelp/GoogleHelp:writeToParcel	(Landroid/os/Parcel;I)V
        //   29: aload_0
        //   30: getfield 15	com/google/android/gms/googlehelp/internal/common/zze$zza$zza:zzop	Landroid/os/IBinder;
        //   33: iconst_1
        //   34: aload_2
        //   35: aload_3
        //   36: iconst_0
        //   37: invokeinterface 49 5 0
        //   42: pop
        //   43: aload_3
        //   44: invokevirtual 52	android/os/Parcel:readException	()V
        //   47: aload_3
        //   48: invokevirtual 55	android/os/Parcel:recycle	()V
        //   51: aload_2
        //   52: invokevirtual 55	android/os/Parcel:recycle	()V
        //   55: return
        //   56: aload_2
        //   57: iconst_0
        //   58: invokevirtual 37	android/os/Parcel:writeInt	(I)V
        //   61: goto -32 -> 29
        //   64: astore 4
        //   66: aload_3
        //   67: invokevirtual 55	android/os/Parcel:recycle	()V
        //   70: aload_2
        //   71: invokevirtual 55	android/os/Parcel:recycle	()V
        //   74: aload 4
        //   76: athrow
        // Local variable table:
        //   start	length	slot	name	signature
        //   0	77	0	this	zza
        //   0	77	1	paramGoogleHelp	GoogleHelp
        //   3	68	2	localParcel1	Parcel
        //   7	60	3	localParcel2	Parcel
        //   64	11	4	localObject	Object
        // Exception table:
        //   from	to	target	type
        //   8	14	64	finally
        //   18	29	64	finally
        //   29	47	64	finally
        //   56	61	64	finally
      }
      
      public final void onPipClick()
        throws RemoteException
      {
        Parcel localParcel1 = Parcel.obtain();
        Parcel localParcel2 = Parcel.obtain();
        try
        {
          localParcel1.writeInterfaceToken("com.google.android.gms.googlehelp.internal.common.IGoogleHelpCallbacks");
          this.zzop.transact(4, localParcel1, localParcel2, 0);
          localParcel2.readException();
          return;
        }
        finally
        {
          localParcel2.recycle();
          localParcel1.recycle();
        }
      }
      
      public final void onPipInCallingAppDisabled()
        throws RemoteException
      {
        Parcel localParcel1 = Parcel.obtain();
        Parcel localParcel2 = Parcel.obtain();
        try
        {
          localParcel1.writeInterfaceToken("com.google.android.gms.googlehelp.internal.common.IGoogleHelpCallbacks");
          this.zzop.transact(6, localParcel1, localParcel2, 0);
          localParcel2.readException();
          return;
        }
        finally
        {
          localParcel2.recycle();
          localParcel1.recycle();
        }
      }
      
      public final void onPipInCallingAppHidden()
        throws RemoteException
      {
        Parcel localParcel1 = Parcel.obtain();
        Parcel localParcel2 = Parcel.obtain();
        try
        {
          localParcel1.writeInterfaceToken("com.google.android.gms.googlehelp.internal.common.IGoogleHelpCallbacks");
          this.zzop.transact(5, localParcel1, localParcel2, 0);
          localParcel2.readException();
          return;
        }
        finally
        {
          localParcel2.recycle();
          localParcel1.recycle();
        }
      }
      
      public final void onPipShown()
        throws RemoteException
      {
        Parcel localParcel1 = Parcel.obtain();
        Parcel localParcel2 = Parcel.obtain();
        try
        {
          localParcel1.writeInterfaceToken("com.google.android.gms.googlehelp.internal.common.IGoogleHelpCallbacks");
          this.zzop.transact(3, localParcel1, localParcel2, 0);
          localParcel2.readException();
          return;
        }
        finally
        {
          localParcel2.recycle();
          localParcel1.recycle();
        }
      }
      
      /* Error */
      public final void onTogglingPipProcessed(TogglingData paramTogglingData)
        throws RemoteException
      {
        // Byte code:
        //   0: invokestatic 27	android/os/Parcel:obtain	()Landroid/os/Parcel;
        //   3: astore_2
        //   4: invokestatic 27	android/os/Parcel:obtain	()Landroid/os/Parcel;
        //   7: astore_3
        //   8: aload_2
        //   9: ldc 29
        //   11: invokevirtual 33	android/os/Parcel:writeInterfaceToken	(Ljava/lang/String;)V
        //   14: aload_1
        //   15: ifnull +41 -> 56
        //   18: aload_2
        //   19: iconst_1
        //   20: invokevirtual 37	android/os/Parcel:writeInt	(I)V
        //   23: aload_1
        //   24: aload_2
        //   25: iconst_0
        //   26: invokevirtual 64	com/google/android/gms/googlehelp/internal/common/TogglingData:writeToParcel	(Landroid/os/Parcel;I)V
        //   29: aload_0
        //   30: getfield 15	com/google/android/gms/googlehelp/internal/common/zze$zza$zza:zzop	Landroid/os/IBinder;
        //   33: iconst_2
        //   34: aload_2
        //   35: aload_3
        //   36: iconst_0
        //   37: invokeinterface 49 5 0
        //   42: pop
        //   43: aload_3
        //   44: invokevirtual 52	android/os/Parcel:readException	()V
        //   47: aload_3
        //   48: invokevirtual 55	android/os/Parcel:recycle	()V
        //   51: aload_2
        //   52: invokevirtual 55	android/os/Parcel:recycle	()V
        //   55: return
        //   56: aload_2
        //   57: iconst_0
        //   58: invokevirtual 37	android/os/Parcel:writeInt	(I)V
        //   61: goto -32 -> 29
        //   64: astore 4
        //   66: aload_3
        //   67: invokevirtual 55	android/os/Parcel:recycle	()V
        //   70: aload_2
        //   71: invokevirtual 55	android/os/Parcel:recycle	()V
        //   74: aload 4
        //   76: athrow
        // Local variable table:
        //   start	length	slot	name	signature
        //   0	77	0	this	zza
        //   0	77	1	paramTogglingData	TogglingData
        //   3	68	2	localParcel1	Parcel
        //   7	60	3	localParcel2	Parcel
        //   64	11	4	localObject	Object
        // Exception table:
        //   from	to	target	type
        //   8	14	64	finally
        //   18	29	64	finally
        //   29	47	64	finally
        //   56	61	64	finally
      }
    }
  }
}


/* Location:           F:\apktool\apktool\Google_Play_Store6.0.5\classes-dex2jar.jar
 * Qualified Name:     com.google.android.gms.googlehelp.internal.common.zze
 * JD-Core Version:    0.7.0.1
 */