package com.google.android.gms.common.internal;

import android.os.Binder;
import android.os.Bundle;
import android.os.IBinder;
import android.os.IInterface;
import android.os.Parcel;
import android.os.Parcelable.Creator;
import android.os.RemoteException;

public abstract interface zzs
  extends IInterface
{
  public abstract void zza(zzr paramzzr, int paramInt)
    throws RemoteException;
  
  public abstract void zza(zzr paramzzr, int paramInt, String paramString)
    throws RemoteException;
  
  public abstract void zza(zzr paramzzr, int paramInt, String paramString, Bundle paramBundle)
    throws RemoteException;
  
  public abstract void zza(zzr paramzzr, int paramInt, String paramString, IBinder paramIBinder, Bundle paramBundle)
    throws RemoteException;
  
  public abstract void zza(zzr paramzzr, int paramInt, String paramString1, String paramString2)
    throws RemoteException;
  
  public abstract void zza(zzr paramzzr, int paramInt, String paramString1, String paramString2, String paramString3, String[] paramArrayOfString)
    throws RemoteException;
  
  public abstract void zza(zzr paramzzr, int paramInt, String paramString1, String paramString2, String[] paramArrayOfString)
    throws RemoteException;
  
  public abstract void zza(zzr paramzzr, int paramInt, String paramString1, String paramString2, String[] paramArrayOfString, Bundle paramBundle)
    throws RemoteException;
  
  public abstract void zza(zzr paramzzr, int paramInt, String paramString1, String paramString2, String[] paramArrayOfString, String paramString3, Bundle paramBundle)
    throws RemoteException;
  
  public abstract void zza(zzr paramzzr, int paramInt, String paramString1, String paramString2, String[] paramArrayOfString, String paramString3, IBinder paramIBinder, String paramString4, Bundle paramBundle)
    throws RemoteException;
  
  public abstract void zza(zzr paramzzr, int paramInt, String paramString1, String[] paramArrayOfString, String paramString2, Bundle paramBundle)
    throws RemoteException;
  
  public abstract void zza(zzr paramzzr, GetServiceRequest paramGetServiceRequest)
    throws RemoteException;
  
  public abstract void zza(zzr paramzzr, ValidateAccountRequest paramValidateAccountRequest)
    throws RemoteException;
  
  public abstract void zzb(zzr paramzzr, int paramInt, String paramString)
    throws RemoteException;
  
  public abstract void zzb(zzr paramzzr, int paramInt, String paramString, Bundle paramBundle)
    throws RemoteException;
  
  public abstract void zzc(zzr paramzzr, int paramInt, String paramString)
    throws RemoteException;
  
  public abstract void zzc(zzr paramzzr, int paramInt, String paramString, Bundle paramBundle)
    throws RemoteException;
  
  public abstract void zzd(zzr paramzzr, int paramInt, String paramString)
    throws RemoteException;
  
  public abstract void zzd(zzr paramzzr, int paramInt, String paramString, Bundle paramBundle)
    throws RemoteException;
  
  public abstract void zze(zzr paramzzr, int paramInt, String paramString)
    throws RemoteException;
  
  public abstract void zze(zzr paramzzr, int paramInt, String paramString, Bundle paramBundle)
    throws RemoteException;
  
  public abstract void zzf(zzr paramzzr, int paramInt, String paramString)
    throws RemoteException;
  
  public abstract void zzf(zzr paramzzr, int paramInt, String paramString, Bundle paramBundle)
    throws RemoteException;
  
  public abstract void zzg(zzr paramzzr, int paramInt, String paramString)
    throws RemoteException;
  
  public abstract void zzg(zzr paramzzr, int paramInt, String paramString, Bundle paramBundle)
    throws RemoteException;
  
  public abstract void zzh(zzr paramzzr, int paramInt, String paramString)
    throws RemoteException;
  
  public abstract void zzh(zzr paramzzr, int paramInt, String paramString, Bundle paramBundle)
    throws RemoteException;
  
  public abstract void zzi(zzr paramzzr, int paramInt, String paramString)
    throws RemoteException;
  
  public abstract void zzi(zzr paramzzr, int paramInt, String paramString, Bundle paramBundle)
    throws RemoteException;
  
  public abstract void zzj(zzr paramzzr, int paramInt, String paramString)
    throws RemoteException;
  
  public abstract void zzj(zzr paramzzr, int paramInt, String paramString, Bundle paramBundle)
    throws RemoteException;
  
  public abstract void zzk(zzr paramzzr, int paramInt, String paramString)
    throws RemoteException;
  
  public abstract void zzk(zzr paramzzr, int paramInt, String paramString, Bundle paramBundle)
    throws RemoteException;
  
  public abstract void zzl(zzr paramzzr, int paramInt, String paramString)
    throws RemoteException;
  
  public abstract void zzl(zzr paramzzr, int paramInt, String paramString, Bundle paramBundle)
    throws RemoteException;
  
  public abstract void zzm(zzr paramzzr, int paramInt, String paramString)
    throws RemoteException;
  
  public abstract void zzm(zzr paramzzr, int paramInt, String paramString, Bundle paramBundle)
    throws RemoteException;
  
  public abstract void zzn(zzr paramzzr, int paramInt, String paramString, Bundle paramBundle)
    throws RemoteException;
  
  public abstract void zzo(zzr paramzzr, int paramInt, String paramString, Bundle paramBundle)
    throws RemoteException;
  
  public abstract void zzp(zzr paramzzr, int paramInt, String paramString, Bundle paramBundle)
    throws RemoteException;
  
  public abstract void zzq(zzr paramzzr, int paramInt, String paramString, Bundle paramBundle)
    throws RemoteException;
  
  public abstract void zzqA()
    throws RemoteException;
  
  public abstract void zzr(zzr paramzzr, int paramInt, String paramString, Bundle paramBundle)
    throws RemoteException;
  
  public abstract void zzs(zzr paramzzr, int paramInt, String paramString, Bundle paramBundle)
    throws RemoteException;
  
  public abstract void zzt(zzr paramzzr, int paramInt, String paramString, Bundle paramBundle)
    throws RemoteException;
  
  public static abstract class zza
    extends Binder
    implements zzs
  {
    public static zzs zzcm(IBinder paramIBinder)
    {
      if (paramIBinder == null) {
        return null;
      }
      IInterface localIInterface = paramIBinder.queryLocalInterface("com.google.android.gms.common.internal.IGmsServiceBroker");
      if ((localIInterface != null) && ((localIInterface instanceof zzs))) {
        return (zzs)localIInterface;
      }
      return new zza(paramIBinder);
    }
    
    public boolean onTransact(int paramInt1, Parcel paramParcel1, Parcel paramParcel2, int paramInt2)
      throws RemoteException
    {
      switch (paramInt1)
      {
      default: 
        return super.onTransact(paramInt1, paramParcel1, paramParcel2, paramInt2);
      case 1598968902: 
        paramParcel2.writeString("com.google.android.gms.common.internal.IGmsServiceBroker");
        return true;
      case 1: 
        paramParcel1.enforceInterface("com.google.android.gms.common.internal.IGmsServiceBroker");
        zzr localzzr27 = zzr.zza.zzcl(paramParcel1.readStrongBinder());
        int i42 = paramParcel1.readInt();
        String str30 = paramParcel1.readString();
        String str31 = paramParcel1.readString();
        String[] arrayOfString4 = paramParcel1.createStringArray();
        String str32 = paramParcel1.readString();
        if (paramParcel1.readInt() != 0) {}
        for (Bundle localBundle25 = (Bundle)Bundle.CREATOR.createFromParcel(paramParcel1);; localBundle25 = null)
        {
          zza(localzzr27, i42, str30, str31, arrayOfString4, str32, localBundle25);
          paramParcel2.writeNoException();
          return true;
        }
      case 2: 
        paramParcel1.enforceInterface("com.google.android.gms.common.internal.IGmsServiceBroker");
        zzr localzzr26 = zzr.zza.zzcl(paramParcel1.readStrongBinder());
        int i40 = paramParcel1.readInt();
        String str29 = paramParcel1.readString();
        int i41 = paramParcel1.readInt();
        Bundle localBundle24 = null;
        if (i41 != 0) {
          localBundle24 = (Bundle)Bundle.CREATOR.createFromParcel(paramParcel1);
        }
        zza(localzzr26, i40, str29, localBundle24);
        paramParcel2.writeNoException();
        return true;
      case 3: 
        paramParcel1.enforceInterface("com.google.android.gms.common.internal.IGmsServiceBroker");
        zza(zzr.zza.zzcl(paramParcel1.readStrongBinder()), paramParcel1.readInt(), paramParcel1.readString());
        paramParcel2.writeNoException();
        return true;
      case 4: 
        paramParcel1.enforceInterface("com.google.android.gms.common.internal.IGmsServiceBroker");
        zza(zzr.zza.zzcl(paramParcel1.readStrongBinder()), paramParcel1.readInt());
        paramParcel2.writeNoException();
        return true;
      case 5: 
        paramParcel1.enforceInterface("com.google.android.gms.common.internal.IGmsServiceBroker");
        zzr localzzr25 = zzr.zza.zzcl(paramParcel1.readStrongBinder());
        int i38 = paramParcel1.readInt();
        String str28 = paramParcel1.readString();
        int i39 = paramParcel1.readInt();
        Bundle localBundle23 = null;
        if (i39 != 0) {
          localBundle23 = (Bundle)Bundle.CREATOR.createFromParcel(paramParcel1);
        }
        zzb(localzzr25, i38, str28, localBundle23);
        paramParcel2.writeNoException();
        return true;
      case 6: 
        paramParcel1.enforceInterface("com.google.android.gms.common.internal.IGmsServiceBroker");
        zzr localzzr24 = zzr.zza.zzcl(paramParcel1.readStrongBinder());
        int i36 = paramParcel1.readInt();
        String str27 = paramParcel1.readString();
        int i37 = paramParcel1.readInt();
        Bundle localBundle22 = null;
        if (i37 != 0) {
          localBundle22 = (Bundle)Bundle.CREATOR.createFromParcel(paramParcel1);
        }
        zzc(localzzr24, i36, str27, localBundle22);
        paramParcel2.writeNoException();
        return true;
      case 7: 
        paramParcel1.enforceInterface("com.google.android.gms.common.internal.IGmsServiceBroker");
        zzr localzzr23 = zzr.zza.zzcl(paramParcel1.readStrongBinder());
        int i34 = paramParcel1.readInt();
        String str26 = paramParcel1.readString();
        int i35 = paramParcel1.readInt();
        Bundle localBundle21 = null;
        if (i35 != 0) {
          localBundle21 = (Bundle)Bundle.CREATOR.createFromParcel(paramParcel1);
        }
        zzd(localzzr23, i34, str26, localBundle21);
        paramParcel2.writeNoException();
        return true;
      case 8: 
        paramParcel1.enforceInterface("com.google.android.gms.common.internal.IGmsServiceBroker");
        zzr localzzr22 = zzr.zza.zzcl(paramParcel1.readStrongBinder());
        int i32 = paramParcel1.readInt();
        String str25 = paramParcel1.readString();
        int i33 = paramParcel1.readInt();
        Bundle localBundle20 = null;
        if (i33 != 0) {
          localBundle20 = (Bundle)Bundle.CREATOR.createFromParcel(paramParcel1);
        }
        zze(localzzr22, i32, str25, localBundle20);
        paramParcel2.writeNoException();
        return true;
      case 9: 
        paramParcel1.enforceInterface("com.google.android.gms.common.internal.IGmsServiceBroker");
        zzr localzzr21 = zzr.zza.zzcl(paramParcel1.readStrongBinder());
        int i31 = paramParcel1.readInt();
        String str21 = paramParcel1.readString();
        String str22 = paramParcel1.readString();
        String[] arrayOfString3 = paramParcel1.createStringArray();
        String str23 = paramParcel1.readString();
        IBinder localIBinder2 = paramParcel1.readStrongBinder();
        String str24 = paramParcel1.readString();
        if (paramParcel1.readInt() != 0) {}
        for (Bundle localBundle19 = (Bundle)Bundle.CREATOR.createFromParcel(paramParcel1);; localBundle19 = null)
        {
          zza(localzzr21, i31, str21, str22, arrayOfString3, str23, localIBinder2, str24, localBundle19);
          paramParcel2.writeNoException();
          return true;
        }
      case 10: 
        paramParcel1.enforceInterface("com.google.android.gms.common.internal.IGmsServiceBroker");
        zza(zzr.zza.zzcl(paramParcel1.readStrongBinder()), paramParcel1.readInt(), paramParcel1.readString(), paramParcel1.readString(), paramParcel1.createStringArray());
        paramParcel2.writeNoException();
        return true;
      case 11: 
        paramParcel1.enforceInterface("com.google.android.gms.common.internal.IGmsServiceBroker");
        zzr localzzr20 = zzr.zza.zzcl(paramParcel1.readStrongBinder());
        int i29 = paramParcel1.readInt();
        String str20 = paramParcel1.readString();
        int i30 = paramParcel1.readInt();
        Bundle localBundle18 = null;
        if (i30 != 0) {
          localBundle18 = (Bundle)Bundle.CREATOR.createFromParcel(paramParcel1);
        }
        zzf(localzzr20, i29, str20, localBundle18);
        paramParcel2.writeNoException();
        return true;
      case 12: 
        paramParcel1.enforceInterface("com.google.android.gms.common.internal.IGmsServiceBroker");
        zzr localzzr19 = zzr.zza.zzcl(paramParcel1.readStrongBinder());
        int i27 = paramParcel1.readInt();
        String str19 = paramParcel1.readString();
        int i28 = paramParcel1.readInt();
        Bundle localBundle17 = null;
        if (i28 != 0) {
          localBundle17 = (Bundle)Bundle.CREATOR.createFromParcel(paramParcel1);
        }
        zzg(localzzr19, i27, str19, localBundle17);
        paramParcel2.writeNoException();
        return true;
      case 13: 
        paramParcel1.enforceInterface("com.google.android.gms.common.internal.IGmsServiceBroker");
        zzr localzzr18 = zzr.zza.zzcl(paramParcel1.readStrongBinder());
        int i25 = paramParcel1.readInt();
        String str18 = paramParcel1.readString();
        int i26 = paramParcel1.readInt();
        Bundle localBundle16 = null;
        if (i26 != 0) {
          localBundle16 = (Bundle)Bundle.CREATOR.createFromParcel(paramParcel1);
        }
        zzh(localzzr18, i25, str18, localBundle16);
        paramParcel2.writeNoException();
        return true;
      case 14: 
        paramParcel1.enforceInterface("com.google.android.gms.common.internal.IGmsServiceBroker");
        zzr localzzr17 = zzr.zza.zzcl(paramParcel1.readStrongBinder());
        int i23 = paramParcel1.readInt();
        String str17 = paramParcel1.readString();
        int i24 = paramParcel1.readInt();
        Bundle localBundle15 = null;
        if (i24 != 0) {
          localBundle15 = (Bundle)Bundle.CREATOR.createFromParcel(paramParcel1);
        }
        zzi(localzzr17, i23, str17, localBundle15);
        paramParcel2.writeNoException();
        return true;
      case 15: 
        paramParcel1.enforceInterface("com.google.android.gms.common.internal.IGmsServiceBroker");
        zzr localzzr16 = zzr.zza.zzcl(paramParcel1.readStrongBinder());
        int i21 = paramParcel1.readInt();
        String str16 = paramParcel1.readString();
        int i22 = paramParcel1.readInt();
        Bundle localBundle14 = null;
        if (i22 != 0) {
          localBundle14 = (Bundle)Bundle.CREATOR.createFromParcel(paramParcel1);
        }
        zzj(localzzr16, i21, str16, localBundle14);
        paramParcel2.writeNoException();
        return true;
      case 16: 
        paramParcel1.enforceInterface("com.google.android.gms.common.internal.IGmsServiceBroker");
        zzr localzzr15 = zzr.zza.zzcl(paramParcel1.readStrongBinder());
        int i19 = paramParcel1.readInt();
        String str15 = paramParcel1.readString();
        int i20 = paramParcel1.readInt();
        Bundle localBundle13 = null;
        if (i20 != 0) {
          localBundle13 = (Bundle)Bundle.CREATOR.createFromParcel(paramParcel1);
        }
        zzk(localzzr15, i19, str15, localBundle13);
        paramParcel2.writeNoException();
        return true;
      case 17: 
        paramParcel1.enforceInterface("com.google.android.gms.common.internal.IGmsServiceBroker");
        zzr localzzr14 = zzr.zza.zzcl(paramParcel1.readStrongBinder());
        int i17 = paramParcel1.readInt();
        String str14 = paramParcel1.readString();
        int i18 = paramParcel1.readInt();
        Bundle localBundle12 = null;
        if (i18 != 0) {
          localBundle12 = (Bundle)Bundle.CREATOR.createFromParcel(paramParcel1);
        }
        zzl(localzzr14, i17, str14, localBundle12);
        paramParcel2.writeNoException();
        return true;
      case 18: 
        paramParcel1.enforceInterface("com.google.android.gms.common.internal.IGmsServiceBroker");
        zzr localzzr13 = zzr.zza.zzcl(paramParcel1.readStrongBinder());
        int i15 = paramParcel1.readInt();
        String str13 = paramParcel1.readString();
        int i16 = paramParcel1.readInt();
        Bundle localBundle11 = null;
        if (i16 != 0) {
          localBundle11 = (Bundle)Bundle.CREATOR.createFromParcel(paramParcel1);
        }
        zzm(localzzr13, i15, str13, localBundle11);
        paramParcel2.writeNoException();
        return true;
      case 19: 
        paramParcel1.enforceInterface("com.google.android.gms.common.internal.IGmsServiceBroker");
        zzr localzzr12 = zzr.zza.zzcl(paramParcel1.readStrongBinder());
        int i14 = paramParcel1.readInt();
        String str12 = paramParcel1.readString();
        IBinder localIBinder1 = paramParcel1.readStrongBinder();
        if (paramParcel1.readInt() != 0) {}
        for (Bundle localBundle10 = (Bundle)Bundle.CREATOR.createFromParcel(paramParcel1);; localBundle10 = null)
        {
          zza(localzzr12, i14, str12, localIBinder1, localBundle10);
          paramParcel2.writeNoException();
          return true;
        }
      case 20: 
        paramParcel1.enforceInterface("com.google.android.gms.common.internal.IGmsServiceBroker");
        zzr localzzr11 = zzr.zza.zzcl(paramParcel1.readStrongBinder());
        int i13 = paramParcel1.readInt();
        String str10 = paramParcel1.readString();
        String[] arrayOfString2 = paramParcel1.createStringArray();
        String str11 = paramParcel1.readString();
        if (paramParcel1.readInt() != 0) {}
        for (Bundle localBundle9 = (Bundle)Bundle.CREATOR.createFromParcel(paramParcel1);; localBundle9 = null)
        {
          zza(localzzr11, i13, str10, arrayOfString2, str11, localBundle9);
          paramParcel2.writeNoException();
          return true;
        }
      case 21: 
        paramParcel1.enforceInterface("com.google.android.gms.common.internal.IGmsServiceBroker");
        zzb(zzr.zza.zzcl(paramParcel1.readStrongBinder()), paramParcel1.readInt(), paramParcel1.readString());
        paramParcel2.writeNoException();
        return true;
      case 22: 
        paramParcel1.enforceInterface("com.google.android.gms.common.internal.IGmsServiceBroker");
        zzc(zzr.zza.zzcl(paramParcel1.readStrongBinder()), paramParcel1.readInt(), paramParcel1.readString());
        paramParcel2.writeNoException();
        return true;
      case 23: 
        paramParcel1.enforceInterface("com.google.android.gms.common.internal.IGmsServiceBroker");
        zzr localzzr10 = zzr.zza.zzcl(paramParcel1.readStrongBinder());
        int i11 = paramParcel1.readInt();
        String str9 = paramParcel1.readString();
        int i12 = paramParcel1.readInt();
        Bundle localBundle8 = null;
        if (i12 != 0) {
          localBundle8 = (Bundle)Bundle.CREATOR.createFromParcel(paramParcel1);
        }
        zzn(localzzr10, i11, str9, localBundle8);
        paramParcel2.writeNoException();
        return true;
      case 24: 
        paramParcel1.enforceInterface("com.google.android.gms.common.internal.IGmsServiceBroker");
        zzd(zzr.zza.zzcl(paramParcel1.readStrongBinder()), paramParcel1.readInt(), paramParcel1.readString());
        paramParcel2.writeNoException();
        return true;
      case 25: 
        paramParcel1.enforceInterface("com.google.android.gms.common.internal.IGmsServiceBroker");
        zzr localzzr9 = zzr.zza.zzcl(paramParcel1.readStrongBinder());
        int i9 = paramParcel1.readInt();
        String str8 = paramParcel1.readString();
        int i10 = paramParcel1.readInt();
        Bundle localBundle7 = null;
        if (i10 != 0) {
          localBundle7 = (Bundle)Bundle.CREATOR.createFromParcel(paramParcel1);
        }
        zzo(localzzr9, i9, str8, localBundle7);
        paramParcel2.writeNoException();
        return true;
      case 26: 
        paramParcel1.enforceInterface("com.google.android.gms.common.internal.IGmsServiceBroker");
        zze(zzr.zza.zzcl(paramParcel1.readStrongBinder()), paramParcel1.readInt(), paramParcel1.readString());
        paramParcel2.writeNoException();
        return true;
      case 27: 
        paramParcel1.enforceInterface("com.google.android.gms.common.internal.IGmsServiceBroker");
        zzr localzzr8 = zzr.zza.zzcl(paramParcel1.readStrongBinder());
        int i7 = paramParcel1.readInt();
        String str7 = paramParcel1.readString();
        int i8 = paramParcel1.readInt();
        Bundle localBundle6 = null;
        if (i8 != 0) {
          localBundle6 = (Bundle)Bundle.CREATOR.createFromParcel(paramParcel1);
        }
        zzp(localzzr8, i7, str7, localBundle6);
        paramParcel2.writeNoException();
        return true;
      case 28: 
        paramParcel1.enforceInterface("com.google.android.gms.common.internal.IGmsServiceBroker");
        zzqA();
        paramParcel2.writeNoException();
        return true;
      case 30: 
        paramParcel1.enforceInterface("com.google.android.gms.common.internal.IGmsServiceBroker");
        zzr localzzr7 = zzr.zza.zzcl(paramParcel1.readStrongBinder());
        int i6 = paramParcel1.readInt();
        String str5 = paramParcel1.readString();
        String str6 = paramParcel1.readString();
        String[] arrayOfString1 = paramParcel1.createStringArray();
        if (paramParcel1.readInt() != 0) {}
        for (Bundle localBundle5 = (Bundle)Bundle.CREATOR.createFromParcel(paramParcel1);; localBundle5 = null)
        {
          zza(localzzr7, i6, str5, str6, arrayOfString1, localBundle5);
          paramParcel2.writeNoException();
          return true;
        }
      case 31: 
        paramParcel1.enforceInterface("com.google.android.gms.common.internal.IGmsServiceBroker");
        zzf(zzr.zza.zzcl(paramParcel1.readStrongBinder()), paramParcel1.readInt(), paramParcel1.readString());
        paramParcel2.writeNoException();
        return true;
      case 32: 
        paramParcel1.enforceInterface("com.google.android.gms.common.internal.IGmsServiceBroker");
        zzg(zzr.zza.zzcl(paramParcel1.readStrongBinder()), paramParcel1.readInt(), paramParcel1.readString());
        paramParcel2.writeNoException();
        return true;
      case 33: 
        paramParcel1.enforceInterface("com.google.android.gms.common.internal.IGmsServiceBroker");
        zza(zzr.zza.zzcl(paramParcel1.readStrongBinder()), paramParcel1.readInt(), paramParcel1.readString(), paramParcel1.readString(), paramParcel1.readString(), paramParcel1.createStringArray());
        paramParcel2.writeNoException();
        return true;
      case 34: 
        paramParcel1.enforceInterface("com.google.android.gms.common.internal.IGmsServiceBroker");
        zza(zzr.zza.zzcl(paramParcel1.readStrongBinder()), paramParcel1.readInt(), paramParcel1.readString(), paramParcel1.readString());
        paramParcel2.writeNoException();
        return true;
      case 35: 
        paramParcel1.enforceInterface("com.google.android.gms.common.internal.IGmsServiceBroker");
        zzh(zzr.zza.zzcl(paramParcel1.readStrongBinder()), paramParcel1.readInt(), paramParcel1.readString());
        paramParcel2.writeNoException();
        return true;
      case 36: 
        paramParcel1.enforceInterface("com.google.android.gms.common.internal.IGmsServiceBroker");
        zzi(zzr.zza.zzcl(paramParcel1.readStrongBinder()), paramParcel1.readInt(), paramParcel1.readString());
        paramParcel2.writeNoException();
        return true;
      case 37: 
        paramParcel1.enforceInterface("com.google.android.gms.common.internal.IGmsServiceBroker");
        zzr localzzr6 = zzr.zza.zzcl(paramParcel1.readStrongBinder());
        int i4 = paramParcel1.readInt();
        String str4 = paramParcel1.readString();
        int i5 = paramParcel1.readInt();
        Bundle localBundle4 = null;
        if (i5 != 0) {
          localBundle4 = (Bundle)Bundle.CREATOR.createFromParcel(paramParcel1);
        }
        zzq(localzzr6, i4, str4, localBundle4);
        paramParcel2.writeNoException();
        return true;
      case 38: 
        paramParcel1.enforceInterface("com.google.android.gms.common.internal.IGmsServiceBroker");
        zzr localzzr5 = zzr.zza.zzcl(paramParcel1.readStrongBinder());
        int i2 = paramParcel1.readInt();
        String str3 = paramParcel1.readString();
        int i3 = paramParcel1.readInt();
        Bundle localBundle3 = null;
        if (i3 != 0) {
          localBundle3 = (Bundle)Bundle.CREATOR.createFromParcel(paramParcel1);
        }
        zzr(localzzr5, i2, str3, localBundle3);
        paramParcel2.writeNoException();
        return true;
      case 40: 
        paramParcel1.enforceInterface("com.google.android.gms.common.internal.IGmsServiceBroker");
        zzj(zzr.zza.zzcl(paramParcel1.readStrongBinder()), paramParcel1.readInt(), paramParcel1.readString());
        paramParcel2.writeNoException();
        return true;
      case 41: 
        paramParcel1.enforceInterface("com.google.android.gms.common.internal.IGmsServiceBroker");
        zzr localzzr4 = zzr.zza.zzcl(paramParcel1.readStrongBinder());
        int n = paramParcel1.readInt();
        String str2 = paramParcel1.readString();
        int i1 = paramParcel1.readInt();
        Bundle localBundle2 = null;
        if (i1 != 0) {
          localBundle2 = (Bundle)Bundle.CREATOR.createFromParcel(paramParcel1);
        }
        zzs(localzzr4, n, str2, localBundle2);
        paramParcel2.writeNoException();
        return true;
      case 42: 
        paramParcel1.enforceInterface("com.google.android.gms.common.internal.IGmsServiceBroker");
        zzk(zzr.zza.zzcl(paramParcel1.readStrongBinder()), paramParcel1.readInt(), paramParcel1.readString());
        paramParcel2.writeNoException();
        return true;
      case 43: 
        paramParcel1.enforceInterface("com.google.android.gms.common.internal.IGmsServiceBroker");
        zzr localzzr3 = zzr.zza.zzcl(paramParcel1.readStrongBinder());
        int k = paramParcel1.readInt();
        String str1 = paramParcel1.readString();
        int m = paramParcel1.readInt();
        Bundle localBundle1 = null;
        if (m != 0) {
          localBundle1 = (Bundle)Bundle.CREATOR.createFromParcel(paramParcel1);
        }
        zzt(localzzr3, k, str1, localBundle1);
        paramParcel2.writeNoException();
        return true;
      case 44: 
        paramParcel1.enforceInterface("com.google.android.gms.common.internal.IGmsServiceBroker");
        zzl(zzr.zza.zzcl(paramParcel1.readStrongBinder()), paramParcel1.readInt(), paramParcel1.readString());
        paramParcel2.writeNoException();
        return true;
      case 45: 
        paramParcel1.enforceInterface("com.google.android.gms.common.internal.IGmsServiceBroker");
        zzm(zzr.zza.zzcl(paramParcel1.readStrongBinder()), paramParcel1.readInt(), paramParcel1.readString());
        paramParcel2.writeNoException();
        return true;
      case 46: 
        paramParcel1.enforceInterface("com.google.android.gms.common.internal.IGmsServiceBroker");
        zzr localzzr2 = zzr.zza.zzcl(paramParcel1.readStrongBinder());
        int j = paramParcel1.readInt();
        GetServiceRequest localGetServiceRequest = null;
        if (j != 0) {
          localGetServiceRequest = (GetServiceRequest)GetServiceRequest.CREATOR.createFromParcel(paramParcel1);
        }
        zza(localzzr2, localGetServiceRequest);
        paramParcel2.writeNoException();
        return true;
      }
      paramParcel1.enforceInterface("com.google.android.gms.common.internal.IGmsServiceBroker");
      zzr localzzr1 = zzr.zza.zzcl(paramParcel1.readStrongBinder());
      int i = paramParcel1.readInt();
      ValidateAccountRequest localValidateAccountRequest = null;
      if (i != 0) {
        localValidateAccountRequest = (ValidateAccountRequest)ValidateAccountRequest.CREATOR.createFromParcel(paramParcel1);
      }
      zza(localzzr1, localValidateAccountRequest);
      paramParcel2.writeNoException();
      return true;
    }
    
    private static final class zza
      implements zzs
    {
      private IBinder zzop;
      
      zza(IBinder paramIBinder)
      {
        this.zzop = paramIBinder;
      }
      
      public final IBinder asBinder()
      {
        return this.zzop;
      }
      
      /* Error */
      public final void zza(zzr paramzzr, int paramInt)
        throws RemoteException
      {
        // Byte code:
        //   0: invokestatic 27	android/os/Parcel:obtain	()Landroid/os/Parcel;
        //   3: astore_3
        //   4: invokestatic 27	android/os/Parcel:obtain	()Landroid/os/Parcel;
        //   7: astore 4
        //   9: aload_3
        //   10: ldc 29
        //   12: invokevirtual 33	android/os/Parcel:writeInterfaceToken	(Ljava/lang/String;)V
        //   15: aload_1
        //   16: ifnull +52 -> 68
        //   19: aload_1
        //   20: invokeinterface 37 1 0
        //   25: astore 6
        //   27: aload_3
        //   28: aload 6
        //   30: invokevirtual 40	android/os/Parcel:writeStrongBinder	(Landroid/os/IBinder;)V
        //   33: aload_3
        //   34: iload_2
        //   35: invokevirtual 44	android/os/Parcel:writeInt	(I)V
        //   38: aload_0
        //   39: getfield 15	com/google/android/gms/common/internal/zzs$zza$zza:zzop	Landroid/os/IBinder;
        //   42: iconst_4
        //   43: aload_3
        //   44: aload 4
        //   46: iconst_0
        //   47: invokeinterface 50 5 0
        //   52: pop
        //   53: aload 4
        //   55: invokevirtual 53	android/os/Parcel:readException	()V
        //   58: aload 4
        //   60: invokevirtual 56	android/os/Parcel:recycle	()V
        //   63: aload_3
        //   64: invokevirtual 56	android/os/Parcel:recycle	()V
        //   67: return
        //   68: aconst_null
        //   69: astore 6
        //   71: goto -44 -> 27
        //   74: astore 5
        //   76: aload 4
        //   78: invokevirtual 56	android/os/Parcel:recycle	()V
        //   81: aload_3
        //   82: invokevirtual 56	android/os/Parcel:recycle	()V
        //   85: aload 5
        //   87: athrow
        // Local variable table:
        //   start	length	slot	name	signature
        //   0	88	0	this	zza
        //   0	88	1	paramzzr	zzr
        //   0	88	2	paramInt	int
        //   3	79	3	localParcel1	Parcel
        //   7	70	4	localParcel2	Parcel
        //   74	12	5	localObject	Object
        //   25	45	6	localIBinder	IBinder
        // Exception table:
        //   from	to	target	type
        //   9	15	74	finally
        //   19	27	74	finally
        //   27	58	74	finally
      }
      
      /* Error */
      public final void zza(zzr paramzzr, int paramInt, String paramString)
        throws RemoteException
      {
        // Byte code:
        //   0: invokestatic 27	android/os/Parcel:obtain	()Landroid/os/Parcel;
        //   3: astore 4
        //   5: invokestatic 27	android/os/Parcel:obtain	()Landroid/os/Parcel;
        //   8: astore 5
        //   10: aload 4
        //   12: ldc 29
        //   14: invokevirtual 33	android/os/Parcel:writeInterfaceToken	(Ljava/lang/String;)V
        //   17: aload_1
        //   18: ifnull +62 -> 80
        //   21: aload_1
        //   22: invokeinterface 37 1 0
        //   27: astore 7
        //   29: aload 4
        //   31: aload 7
        //   33: invokevirtual 40	android/os/Parcel:writeStrongBinder	(Landroid/os/IBinder;)V
        //   36: aload 4
        //   38: iload_2
        //   39: invokevirtual 44	android/os/Parcel:writeInt	(I)V
        //   42: aload 4
        //   44: aload_3
        //   45: invokevirtual 60	android/os/Parcel:writeString	(Ljava/lang/String;)V
        //   48: aload_0
        //   49: getfield 15	com/google/android/gms/common/internal/zzs$zza$zza:zzop	Landroid/os/IBinder;
        //   52: iconst_3
        //   53: aload 4
        //   55: aload 5
        //   57: iconst_0
        //   58: invokeinterface 50 5 0
        //   63: pop
        //   64: aload 5
        //   66: invokevirtual 53	android/os/Parcel:readException	()V
        //   69: aload 5
        //   71: invokevirtual 56	android/os/Parcel:recycle	()V
        //   74: aload 4
        //   76: invokevirtual 56	android/os/Parcel:recycle	()V
        //   79: return
        //   80: aconst_null
        //   81: astore 7
        //   83: goto -54 -> 29
        //   86: astore 6
        //   88: aload 5
        //   90: invokevirtual 56	android/os/Parcel:recycle	()V
        //   93: aload 4
        //   95: invokevirtual 56	android/os/Parcel:recycle	()V
        //   98: aload 6
        //   100: athrow
        // Local variable table:
        //   start	length	slot	name	signature
        //   0	101	0	this	zza
        //   0	101	1	paramzzr	zzr
        //   0	101	2	paramInt	int
        //   0	101	3	paramString	String
        //   3	91	4	localParcel1	Parcel
        //   8	81	5	localParcel2	Parcel
        //   86	13	6	localObject	Object
        //   27	55	7	localIBinder	IBinder
        // Exception table:
        //   from	to	target	type
        //   10	17	86	finally
        //   21	29	86	finally
        //   29	69	86	finally
      }
      
      /* Error */
      public final void zza(zzr paramzzr, int paramInt, String paramString, Bundle paramBundle)
        throws RemoteException
      {
        // Byte code:
        //   0: invokestatic 27	android/os/Parcel:obtain	()Landroid/os/Parcel;
        //   3: astore 5
        //   5: invokestatic 27	android/os/Parcel:obtain	()Landroid/os/Parcel;
        //   8: astore 6
        //   10: aload 5
        //   12: ldc 29
        //   14: invokevirtual 33	android/os/Parcel:writeInterfaceToken	(Ljava/lang/String;)V
        //   17: aload_1
        //   18: ifnull +81 -> 99
        //   21: aload_1
        //   22: invokeinterface 37 1 0
        //   27: astore 8
        //   29: aload 5
        //   31: aload 8
        //   33: invokevirtual 40	android/os/Parcel:writeStrongBinder	(Landroid/os/IBinder;)V
        //   36: aload 5
        //   38: iload_2
        //   39: invokevirtual 44	android/os/Parcel:writeInt	(I)V
        //   42: aload 5
        //   44: aload_3
        //   45: invokevirtual 60	android/os/Parcel:writeString	(Ljava/lang/String;)V
        //   48: aload 4
        //   50: ifnull +55 -> 105
        //   53: aload 5
        //   55: iconst_1
        //   56: invokevirtual 44	android/os/Parcel:writeInt	(I)V
        //   59: aload 4
        //   61: aload 5
        //   63: iconst_0
        //   64: invokevirtual 67	android/os/Bundle:writeToParcel	(Landroid/os/Parcel;I)V
        //   67: aload_0
        //   68: getfield 15	com/google/android/gms/common/internal/zzs$zza$zza:zzop	Landroid/os/IBinder;
        //   71: iconst_2
        //   72: aload 5
        //   74: aload 6
        //   76: iconst_0
        //   77: invokeinterface 50 5 0
        //   82: pop
        //   83: aload 6
        //   85: invokevirtual 53	android/os/Parcel:readException	()V
        //   88: aload 6
        //   90: invokevirtual 56	android/os/Parcel:recycle	()V
        //   93: aload 5
        //   95: invokevirtual 56	android/os/Parcel:recycle	()V
        //   98: return
        //   99: aconst_null
        //   100: astore 8
        //   102: goto -73 -> 29
        //   105: aload 5
        //   107: iconst_0
        //   108: invokevirtual 44	android/os/Parcel:writeInt	(I)V
        //   111: goto -44 -> 67
        //   114: astore 7
        //   116: aload 6
        //   118: invokevirtual 56	android/os/Parcel:recycle	()V
        //   121: aload 5
        //   123: invokevirtual 56	android/os/Parcel:recycle	()V
        //   126: aload 7
        //   128: athrow
        // Local variable table:
        //   start	length	slot	name	signature
        //   0	129	0	this	zza
        //   0	129	1	paramzzr	zzr
        //   0	129	2	paramInt	int
        //   0	129	3	paramString	String
        //   0	129	4	paramBundle	Bundle
        //   3	119	5	localParcel1	Parcel
        //   8	109	6	localParcel2	Parcel
        //   114	13	7	localObject	Object
        //   27	74	8	localIBinder	IBinder
        // Exception table:
        //   from	to	target	type
        //   10	17	114	finally
        //   21	29	114	finally
        //   29	48	114	finally
        //   53	67	114	finally
        //   67	88	114	finally
        //   105	111	114	finally
      }
      
      /* Error */
      public final void zza(zzr paramzzr, int paramInt, String paramString, IBinder paramIBinder, Bundle paramBundle)
        throws RemoteException
      {
        // Byte code:
        //   0: invokestatic 27	android/os/Parcel:obtain	()Landroid/os/Parcel;
        //   3: astore 6
        //   5: invokestatic 27	android/os/Parcel:obtain	()Landroid/os/Parcel;
        //   8: astore 7
        //   10: aload 6
        //   12: ldc 29
        //   14: invokevirtual 33	android/os/Parcel:writeInterfaceToken	(Ljava/lang/String;)V
        //   17: aload_1
        //   18: ifnull +89 -> 107
        //   21: aload_1
        //   22: invokeinterface 37 1 0
        //   27: astore 9
        //   29: aload 6
        //   31: aload 9
        //   33: invokevirtual 40	android/os/Parcel:writeStrongBinder	(Landroid/os/IBinder;)V
        //   36: aload 6
        //   38: iload_2
        //   39: invokevirtual 44	android/os/Parcel:writeInt	(I)V
        //   42: aload 6
        //   44: aload_3
        //   45: invokevirtual 60	android/os/Parcel:writeString	(Ljava/lang/String;)V
        //   48: aload 6
        //   50: aload 4
        //   52: invokevirtual 40	android/os/Parcel:writeStrongBinder	(Landroid/os/IBinder;)V
        //   55: aload 5
        //   57: ifnull +56 -> 113
        //   60: aload 6
        //   62: iconst_1
        //   63: invokevirtual 44	android/os/Parcel:writeInt	(I)V
        //   66: aload 5
        //   68: aload 6
        //   70: iconst_0
        //   71: invokevirtual 67	android/os/Bundle:writeToParcel	(Landroid/os/Parcel;I)V
        //   74: aload_0
        //   75: getfield 15	com/google/android/gms/common/internal/zzs$zza$zza:zzop	Landroid/os/IBinder;
        //   78: bipush 19
        //   80: aload 6
        //   82: aload 7
        //   84: iconst_0
        //   85: invokeinterface 50 5 0
        //   90: pop
        //   91: aload 7
        //   93: invokevirtual 53	android/os/Parcel:readException	()V
        //   96: aload 7
        //   98: invokevirtual 56	android/os/Parcel:recycle	()V
        //   101: aload 6
        //   103: invokevirtual 56	android/os/Parcel:recycle	()V
        //   106: return
        //   107: aconst_null
        //   108: astore 9
        //   110: goto -81 -> 29
        //   113: aload 6
        //   115: iconst_0
        //   116: invokevirtual 44	android/os/Parcel:writeInt	(I)V
        //   119: goto -45 -> 74
        //   122: astore 8
        //   124: aload 7
        //   126: invokevirtual 56	android/os/Parcel:recycle	()V
        //   129: aload 6
        //   131: invokevirtual 56	android/os/Parcel:recycle	()V
        //   134: aload 8
        //   136: athrow
        // Local variable table:
        //   start	length	slot	name	signature
        //   0	137	0	this	zza
        //   0	137	1	paramzzr	zzr
        //   0	137	2	paramInt	int
        //   0	137	3	paramString	String
        //   0	137	4	paramIBinder	IBinder
        //   0	137	5	paramBundle	Bundle
        //   3	127	6	localParcel1	Parcel
        //   8	117	7	localParcel2	Parcel
        //   122	13	8	localObject	Object
        //   27	82	9	localIBinder	IBinder
        // Exception table:
        //   from	to	target	type
        //   10	17	122	finally
        //   21	29	122	finally
        //   29	55	122	finally
        //   60	74	122	finally
        //   74	96	122	finally
        //   113	119	122	finally
      }
      
      /* Error */
      public final void zza(zzr paramzzr, int paramInt, String paramString1, String paramString2)
        throws RemoteException
      {
        // Byte code:
        //   0: invokestatic 27	android/os/Parcel:obtain	()Landroid/os/Parcel;
        //   3: astore 5
        //   5: invokestatic 27	android/os/Parcel:obtain	()Landroid/os/Parcel;
        //   8: astore 6
        //   10: aload 5
        //   12: ldc 29
        //   14: invokevirtual 33	android/os/Parcel:writeInterfaceToken	(Ljava/lang/String;)V
        //   17: aload_1
        //   18: ifnull +70 -> 88
        //   21: aload_1
        //   22: invokeinterface 37 1 0
        //   27: astore 8
        //   29: aload 5
        //   31: aload 8
        //   33: invokevirtual 40	android/os/Parcel:writeStrongBinder	(Landroid/os/IBinder;)V
        //   36: aload 5
        //   38: iload_2
        //   39: invokevirtual 44	android/os/Parcel:writeInt	(I)V
        //   42: aload 5
        //   44: aload_3
        //   45: invokevirtual 60	android/os/Parcel:writeString	(Ljava/lang/String;)V
        //   48: aload 5
        //   50: aload 4
        //   52: invokevirtual 60	android/os/Parcel:writeString	(Ljava/lang/String;)V
        //   55: aload_0
        //   56: getfield 15	com/google/android/gms/common/internal/zzs$zza$zza:zzop	Landroid/os/IBinder;
        //   59: bipush 34
        //   61: aload 5
        //   63: aload 6
        //   65: iconst_0
        //   66: invokeinterface 50 5 0
        //   71: pop
        //   72: aload 6
        //   74: invokevirtual 53	android/os/Parcel:readException	()V
        //   77: aload 6
        //   79: invokevirtual 56	android/os/Parcel:recycle	()V
        //   82: aload 5
        //   84: invokevirtual 56	android/os/Parcel:recycle	()V
        //   87: return
        //   88: aconst_null
        //   89: astore 8
        //   91: goto -62 -> 29
        //   94: astore 7
        //   96: aload 6
        //   98: invokevirtual 56	android/os/Parcel:recycle	()V
        //   101: aload 5
        //   103: invokevirtual 56	android/os/Parcel:recycle	()V
        //   106: aload 7
        //   108: athrow
        // Local variable table:
        //   start	length	slot	name	signature
        //   0	109	0	this	zza
        //   0	109	1	paramzzr	zzr
        //   0	109	2	paramInt	int
        //   0	109	3	paramString1	String
        //   0	109	4	paramString2	String
        //   3	99	5	localParcel1	Parcel
        //   8	89	6	localParcel2	Parcel
        //   94	13	7	localObject	Object
        //   27	63	8	localIBinder	IBinder
        // Exception table:
        //   from	to	target	type
        //   10	17	94	finally
        //   21	29	94	finally
        //   29	77	94	finally
      }
      
      /* Error */
      public final void zza(zzr paramzzr, int paramInt, String paramString1, String paramString2, String paramString3, String[] paramArrayOfString)
        throws RemoteException
      {
        // Byte code:
        //   0: invokestatic 27	android/os/Parcel:obtain	()Landroid/os/Parcel;
        //   3: astore 7
        //   5: invokestatic 27	android/os/Parcel:obtain	()Landroid/os/Parcel;
        //   8: astore 8
        //   10: aload 7
        //   12: ldc 29
        //   14: invokevirtual 33	android/os/Parcel:writeInterfaceToken	(Ljava/lang/String;)V
        //   17: aload_1
        //   18: ifnull +84 -> 102
        //   21: aload_1
        //   22: invokeinterface 37 1 0
        //   27: astore 10
        //   29: aload 7
        //   31: aload 10
        //   33: invokevirtual 40	android/os/Parcel:writeStrongBinder	(Landroid/os/IBinder;)V
        //   36: aload 7
        //   38: iload_2
        //   39: invokevirtual 44	android/os/Parcel:writeInt	(I)V
        //   42: aload 7
        //   44: aload_3
        //   45: invokevirtual 60	android/os/Parcel:writeString	(Ljava/lang/String;)V
        //   48: aload 7
        //   50: aload 4
        //   52: invokevirtual 60	android/os/Parcel:writeString	(Ljava/lang/String;)V
        //   55: aload 7
        //   57: aload 5
        //   59: invokevirtual 60	android/os/Parcel:writeString	(Ljava/lang/String;)V
        //   62: aload 7
        //   64: aload 6
        //   66: invokevirtual 74	android/os/Parcel:writeStringArray	([Ljava/lang/String;)V
        //   69: aload_0
        //   70: getfield 15	com/google/android/gms/common/internal/zzs$zza$zza:zzop	Landroid/os/IBinder;
        //   73: bipush 33
        //   75: aload 7
        //   77: aload 8
        //   79: iconst_0
        //   80: invokeinterface 50 5 0
        //   85: pop
        //   86: aload 8
        //   88: invokevirtual 53	android/os/Parcel:readException	()V
        //   91: aload 8
        //   93: invokevirtual 56	android/os/Parcel:recycle	()V
        //   96: aload 7
        //   98: invokevirtual 56	android/os/Parcel:recycle	()V
        //   101: return
        //   102: aconst_null
        //   103: astore 10
        //   105: goto -76 -> 29
        //   108: astore 9
        //   110: aload 8
        //   112: invokevirtual 56	android/os/Parcel:recycle	()V
        //   115: aload 7
        //   117: invokevirtual 56	android/os/Parcel:recycle	()V
        //   120: aload 9
        //   122: athrow
        // Local variable table:
        //   start	length	slot	name	signature
        //   0	123	0	this	zza
        //   0	123	1	paramzzr	zzr
        //   0	123	2	paramInt	int
        //   0	123	3	paramString1	String
        //   0	123	4	paramString2	String
        //   0	123	5	paramString3	String
        //   0	123	6	paramArrayOfString	String[]
        //   3	113	7	localParcel1	Parcel
        //   8	103	8	localParcel2	Parcel
        //   108	13	9	localObject	Object
        //   27	77	10	localIBinder	IBinder
        // Exception table:
        //   from	to	target	type
        //   10	17	108	finally
        //   21	29	108	finally
        //   29	91	108	finally
      }
      
      /* Error */
      public final void zza(zzr paramzzr, int paramInt, String paramString1, String paramString2, String[] paramArrayOfString)
        throws RemoteException
      {
        // Byte code:
        //   0: invokestatic 27	android/os/Parcel:obtain	()Landroid/os/Parcel;
        //   3: astore 6
        //   5: invokestatic 27	android/os/Parcel:obtain	()Landroid/os/Parcel;
        //   8: astore 7
        //   10: aload 6
        //   12: ldc 29
        //   14: invokevirtual 33	android/os/Parcel:writeInterfaceToken	(Ljava/lang/String;)V
        //   17: aload_1
        //   18: ifnull +77 -> 95
        //   21: aload_1
        //   22: invokeinterface 37 1 0
        //   27: astore 9
        //   29: aload 6
        //   31: aload 9
        //   33: invokevirtual 40	android/os/Parcel:writeStrongBinder	(Landroid/os/IBinder;)V
        //   36: aload 6
        //   38: iload_2
        //   39: invokevirtual 44	android/os/Parcel:writeInt	(I)V
        //   42: aload 6
        //   44: aload_3
        //   45: invokevirtual 60	android/os/Parcel:writeString	(Ljava/lang/String;)V
        //   48: aload 6
        //   50: aload 4
        //   52: invokevirtual 60	android/os/Parcel:writeString	(Ljava/lang/String;)V
        //   55: aload 6
        //   57: aload 5
        //   59: invokevirtual 74	android/os/Parcel:writeStringArray	([Ljava/lang/String;)V
        //   62: aload_0
        //   63: getfield 15	com/google/android/gms/common/internal/zzs$zza$zza:zzop	Landroid/os/IBinder;
        //   66: bipush 10
        //   68: aload 6
        //   70: aload 7
        //   72: iconst_0
        //   73: invokeinterface 50 5 0
        //   78: pop
        //   79: aload 7
        //   81: invokevirtual 53	android/os/Parcel:readException	()V
        //   84: aload 7
        //   86: invokevirtual 56	android/os/Parcel:recycle	()V
        //   89: aload 6
        //   91: invokevirtual 56	android/os/Parcel:recycle	()V
        //   94: return
        //   95: aconst_null
        //   96: astore 9
        //   98: goto -69 -> 29
        //   101: astore 8
        //   103: aload 7
        //   105: invokevirtual 56	android/os/Parcel:recycle	()V
        //   108: aload 6
        //   110: invokevirtual 56	android/os/Parcel:recycle	()V
        //   113: aload 8
        //   115: athrow
        // Local variable table:
        //   start	length	slot	name	signature
        //   0	116	0	this	zza
        //   0	116	1	paramzzr	zzr
        //   0	116	2	paramInt	int
        //   0	116	3	paramString1	String
        //   0	116	4	paramString2	String
        //   0	116	5	paramArrayOfString	String[]
        //   3	106	6	localParcel1	Parcel
        //   8	96	7	localParcel2	Parcel
        //   101	13	8	localObject	Object
        //   27	70	9	localIBinder	IBinder
        // Exception table:
        //   from	to	target	type
        //   10	17	101	finally
        //   21	29	101	finally
        //   29	84	101	finally
      }
      
      /* Error */
      public final void zza(zzr paramzzr, int paramInt, String paramString1, String paramString2, String[] paramArrayOfString, Bundle paramBundle)
        throws RemoteException
      {
        // Byte code:
        //   0: invokestatic 27	android/os/Parcel:obtain	()Landroid/os/Parcel;
        //   3: astore 7
        //   5: invokestatic 27	android/os/Parcel:obtain	()Landroid/os/Parcel;
        //   8: astore 8
        //   10: aload 7
        //   12: ldc 29
        //   14: invokevirtual 33	android/os/Parcel:writeInterfaceToken	(Ljava/lang/String;)V
        //   17: aload_1
        //   18: ifnull +96 -> 114
        //   21: aload_1
        //   22: invokeinterface 37 1 0
        //   27: astore 10
        //   29: aload 7
        //   31: aload 10
        //   33: invokevirtual 40	android/os/Parcel:writeStrongBinder	(Landroid/os/IBinder;)V
        //   36: aload 7
        //   38: iload_2
        //   39: invokevirtual 44	android/os/Parcel:writeInt	(I)V
        //   42: aload 7
        //   44: aload_3
        //   45: invokevirtual 60	android/os/Parcel:writeString	(Ljava/lang/String;)V
        //   48: aload 7
        //   50: aload 4
        //   52: invokevirtual 60	android/os/Parcel:writeString	(Ljava/lang/String;)V
        //   55: aload 7
        //   57: aload 5
        //   59: invokevirtual 74	android/os/Parcel:writeStringArray	([Ljava/lang/String;)V
        //   62: aload 6
        //   64: ifnull +56 -> 120
        //   67: aload 7
        //   69: iconst_1
        //   70: invokevirtual 44	android/os/Parcel:writeInt	(I)V
        //   73: aload 6
        //   75: aload 7
        //   77: iconst_0
        //   78: invokevirtual 67	android/os/Bundle:writeToParcel	(Landroid/os/Parcel;I)V
        //   81: aload_0
        //   82: getfield 15	com/google/android/gms/common/internal/zzs$zza$zza:zzop	Landroid/os/IBinder;
        //   85: bipush 30
        //   87: aload 7
        //   89: aload 8
        //   91: iconst_0
        //   92: invokeinterface 50 5 0
        //   97: pop
        //   98: aload 8
        //   100: invokevirtual 53	android/os/Parcel:readException	()V
        //   103: aload 8
        //   105: invokevirtual 56	android/os/Parcel:recycle	()V
        //   108: aload 7
        //   110: invokevirtual 56	android/os/Parcel:recycle	()V
        //   113: return
        //   114: aconst_null
        //   115: astore 10
        //   117: goto -88 -> 29
        //   120: aload 7
        //   122: iconst_0
        //   123: invokevirtual 44	android/os/Parcel:writeInt	(I)V
        //   126: goto -45 -> 81
        //   129: astore 9
        //   131: aload 8
        //   133: invokevirtual 56	android/os/Parcel:recycle	()V
        //   136: aload 7
        //   138: invokevirtual 56	android/os/Parcel:recycle	()V
        //   141: aload 9
        //   143: athrow
        // Local variable table:
        //   start	length	slot	name	signature
        //   0	144	0	this	zza
        //   0	144	1	paramzzr	zzr
        //   0	144	2	paramInt	int
        //   0	144	3	paramString1	String
        //   0	144	4	paramString2	String
        //   0	144	5	paramArrayOfString	String[]
        //   0	144	6	paramBundle	Bundle
        //   3	134	7	localParcel1	Parcel
        //   8	124	8	localParcel2	Parcel
        //   129	13	9	localObject	Object
        //   27	89	10	localIBinder	IBinder
        // Exception table:
        //   from	to	target	type
        //   10	17	129	finally
        //   21	29	129	finally
        //   29	62	129	finally
        //   67	81	129	finally
        //   81	103	129	finally
        //   120	126	129	finally
      }
      
      /* Error */
      public final void zza(zzr paramzzr, int paramInt, String paramString1, String paramString2, String[] paramArrayOfString, String paramString3, Bundle paramBundle)
        throws RemoteException
      {
        // Byte code:
        //   0: invokestatic 27	android/os/Parcel:obtain	()Landroid/os/Parcel;
        //   3: astore 8
        //   5: invokestatic 27	android/os/Parcel:obtain	()Landroid/os/Parcel;
        //   8: astore 9
        //   10: aload 8
        //   12: ldc 29
        //   14: invokevirtual 33	android/os/Parcel:writeInterfaceToken	(Ljava/lang/String;)V
        //   17: aload_1
        //   18: ifnull +102 -> 120
        //   21: aload_1
        //   22: invokeinterface 37 1 0
        //   27: astore 11
        //   29: aload 8
        //   31: aload 11
        //   33: invokevirtual 40	android/os/Parcel:writeStrongBinder	(Landroid/os/IBinder;)V
        //   36: aload 8
        //   38: iload_2
        //   39: invokevirtual 44	android/os/Parcel:writeInt	(I)V
        //   42: aload 8
        //   44: aload_3
        //   45: invokevirtual 60	android/os/Parcel:writeString	(Ljava/lang/String;)V
        //   48: aload 8
        //   50: aload 4
        //   52: invokevirtual 60	android/os/Parcel:writeString	(Ljava/lang/String;)V
        //   55: aload 8
        //   57: aload 5
        //   59: invokevirtual 74	android/os/Parcel:writeStringArray	([Ljava/lang/String;)V
        //   62: aload 8
        //   64: aload 6
        //   66: invokevirtual 60	android/os/Parcel:writeString	(Ljava/lang/String;)V
        //   69: aload 7
        //   71: ifnull +55 -> 126
        //   74: aload 8
        //   76: iconst_1
        //   77: invokevirtual 44	android/os/Parcel:writeInt	(I)V
        //   80: aload 7
        //   82: aload 8
        //   84: iconst_0
        //   85: invokevirtual 67	android/os/Bundle:writeToParcel	(Landroid/os/Parcel;I)V
        //   88: aload_0
        //   89: getfield 15	com/google/android/gms/common/internal/zzs$zza$zza:zzop	Landroid/os/IBinder;
        //   92: iconst_1
        //   93: aload 8
        //   95: aload 9
        //   97: iconst_0
        //   98: invokeinterface 50 5 0
        //   103: pop
        //   104: aload 9
        //   106: invokevirtual 53	android/os/Parcel:readException	()V
        //   109: aload 9
        //   111: invokevirtual 56	android/os/Parcel:recycle	()V
        //   114: aload 8
        //   116: invokevirtual 56	android/os/Parcel:recycle	()V
        //   119: return
        //   120: aconst_null
        //   121: astore 11
        //   123: goto -94 -> 29
        //   126: aload 8
        //   128: iconst_0
        //   129: invokevirtual 44	android/os/Parcel:writeInt	(I)V
        //   132: goto -44 -> 88
        //   135: astore 10
        //   137: aload 9
        //   139: invokevirtual 56	android/os/Parcel:recycle	()V
        //   142: aload 8
        //   144: invokevirtual 56	android/os/Parcel:recycle	()V
        //   147: aload 10
        //   149: athrow
        // Local variable table:
        //   start	length	slot	name	signature
        //   0	150	0	this	zza
        //   0	150	1	paramzzr	zzr
        //   0	150	2	paramInt	int
        //   0	150	3	paramString1	String
        //   0	150	4	paramString2	String
        //   0	150	5	paramArrayOfString	String[]
        //   0	150	6	paramString3	String
        //   0	150	7	paramBundle	Bundle
        //   3	140	8	localParcel1	Parcel
        //   8	130	9	localParcel2	Parcel
        //   135	13	10	localObject	Object
        //   27	95	11	localIBinder	IBinder
        // Exception table:
        //   from	to	target	type
        //   10	17	135	finally
        //   21	29	135	finally
        //   29	69	135	finally
        //   74	88	135	finally
        //   88	109	135	finally
        //   126	132	135	finally
      }
      
      /* Error */
      public final void zza(zzr paramzzr, int paramInt, String paramString1, String paramString2, String[] paramArrayOfString, String paramString3, IBinder paramIBinder, String paramString4, Bundle paramBundle)
        throws RemoteException
      {
        // Byte code:
        //   0: invokestatic 27	android/os/Parcel:obtain	()Landroid/os/Parcel;
        //   3: astore 10
        //   5: invokestatic 27	android/os/Parcel:obtain	()Landroid/os/Parcel;
        //   8: astore 11
        //   10: aload 10
        //   12: ldc 29
        //   14: invokevirtual 33	android/os/Parcel:writeInterfaceToken	(Ljava/lang/String;)V
        //   17: aload_1
        //   18: ifnull +117 -> 135
        //   21: aload_1
        //   22: invokeinterface 37 1 0
        //   27: astore 13
        //   29: aload 10
        //   31: aload 13
        //   33: invokevirtual 40	android/os/Parcel:writeStrongBinder	(Landroid/os/IBinder;)V
        //   36: aload 10
        //   38: iload_2
        //   39: invokevirtual 44	android/os/Parcel:writeInt	(I)V
        //   42: aload 10
        //   44: aload_3
        //   45: invokevirtual 60	android/os/Parcel:writeString	(Ljava/lang/String;)V
        //   48: aload 10
        //   50: aload 4
        //   52: invokevirtual 60	android/os/Parcel:writeString	(Ljava/lang/String;)V
        //   55: aload 10
        //   57: aload 5
        //   59: invokevirtual 74	android/os/Parcel:writeStringArray	([Ljava/lang/String;)V
        //   62: aload 10
        //   64: aload 6
        //   66: invokevirtual 60	android/os/Parcel:writeString	(Ljava/lang/String;)V
        //   69: aload 10
        //   71: aload 7
        //   73: invokevirtual 40	android/os/Parcel:writeStrongBinder	(Landroid/os/IBinder;)V
        //   76: aload 10
        //   78: aload 8
        //   80: invokevirtual 60	android/os/Parcel:writeString	(Ljava/lang/String;)V
        //   83: aload 9
        //   85: ifnull +56 -> 141
        //   88: aload 10
        //   90: iconst_1
        //   91: invokevirtual 44	android/os/Parcel:writeInt	(I)V
        //   94: aload 9
        //   96: aload 10
        //   98: iconst_0
        //   99: invokevirtual 67	android/os/Bundle:writeToParcel	(Landroid/os/Parcel;I)V
        //   102: aload_0
        //   103: getfield 15	com/google/android/gms/common/internal/zzs$zza$zza:zzop	Landroid/os/IBinder;
        //   106: bipush 9
        //   108: aload 10
        //   110: aload 11
        //   112: iconst_0
        //   113: invokeinterface 50 5 0
        //   118: pop
        //   119: aload 11
        //   121: invokevirtual 53	android/os/Parcel:readException	()V
        //   124: aload 11
        //   126: invokevirtual 56	android/os/Parcel:recycle	()V
        //   129: aload 10
        //   131: invokevirtual 56	android/os/Parcel:recycle	()V
        //   134: return
        //   135: aconst_null
        //   136: astore 13
        //   138: goto -109 -> 29
        //   141: aload 10
        //   143: iconst_0
        //   144: invokevirtual 44	android/os/Parcel:writeInt	(I)V
        //   147: goto -45 -> 102
        //   150: astore 12
        //   152: aload 11
        //   154: invokevirtual 56	android/os/Parcel:recycle	()V
        //   157: aload 10
        //   159: invokevirtual 56	android/os/Parcel:recycle	()V
        //   162: aload 12
        //   164: athrow
        // Local variable table:
        //   start	length	slot	name	signature
        //   0	165	0	this	zza
        //   0	165	1	paramzzr	zzr
        //   0	165	2	paramInt	int
        //   0	165	3	paramString1	String
        //   0	165	4	paramString2	String
        //   0	165	5	paramArrayOfString	String[]
        //   0	165	6	paramString3	String
        //   0	165	7	paramIBinder	IBinder
        //   0	165	8	paramString4	String
        //   0	165	9	paramBundle	Bundle
        //   3	155	10	localParcel1	Parcel
        //   8	145	11	localParcel2	Parcel
        //   150	13	12	localObject	Object
        //   27	110	13	localIBinder	IBinder
        // Exception table:
        //   from	to	target	type
        //   10	17	150	finally
        //   21	29	150	finally
        //   29	83	150	finally
        //   88	102	150	finally
        //   102	124	150	finally
        //   141	147	150	finally
      }
      
      /* Error */
      public final void zza(zzr paramzzr, int paramInt, String paramString1, String[] paramArrayOfString, String paramString2, Bundle paramBundle)
        throws RemoteException
      {
        // Byte code:
        //   0: invokestatic 27	android/os/Parcel:obtain	()Landroid/os/Parcel;
        //   3: astore 7
        //   5: invokestatic 27	android/os/Parcel:obtain	()Landroid/os/Parcel;
        //   8: astore 8
        //   10: aload 7
        //   12: ldc 29
        //   14: invokevirtual 33	android/os/Parcel:writeInterfaceToken	(Ljava/lang/String;)V
        //   17: aload_1
        //   18: ifnull +96 -> 114
        //   21: aload_1
        //   22: invokeinterface 37 1 0
        //   27: astore 10
        //   29: aload 7
        //   31: aload 10
        //   33: invokevirtual 40	android/os/Parcel:writeStrongBinder	(Landroid/os/IBinder;)V
        //   36: aload 7
        //   38: iload_2
        //   39: invokevirtual 44	android/os/Parcel:writeInt	(I)V
        //   42: aload 7
        //   44: aload_3
        //   45: invokevirtual 60	android/os/Parcel:writeString	(Ljava/lang/String;)V
        //   48: aload 7
        //   50: aload 4
        //   52: invokevirtual 74	android/os/Parcel:writeStringArray	([Ljava/lang/String;)V
        //   55: aload 7
        //   57: aload 5
        //   59: invokevirtual 60	android/os/Parcel:writeString	(Ljava/lang/String;)V
        //   62: aload 6
        //   64: ifnull +56 -> 120
        //   67: aload 7
        //   69: iconst_1
        //   70: invokevirtual 44	android/os/Parcel:writeInt	(I)V
        //   73: aload 6
        //   75: aload 7
        //   77: iconst_0
        //   78: invokevirtual 67	android/os/Bundle:writeToParcel	(Landroid/os/Parcel;I)V
        //   81: aload_0
        //   82: getfield 15	com/google/android/gms/common/internal/zzs$zza$zza:zzop	Landroid/os/IBinder;
        //   85: bipush 20
        //   87: aload 7
        //   89: aload 8
        //   91: iconst_0
        //   92: invokeinterface 50 5 0
        //   97: pop
        //   98: aload 8
        //   100: invokevirtual 53	android/os/Parcel:readException	()V
        //   103: aload 8
        //   105: invokevirtual 56	android/os/Parcel:recycle	()V
        //   108: aload 7
        //   110: invokevirtual 56	android/os/Parcel:recycle	()V
        //   113: return
        //   114: aconst_null
        //   115: astore 10
        //   117: goto -88 -> 29
        //   120: aload 7
        //   122: iconst_0
        //   123: invokevirtual 44	android/os/Parcel:writeInt	(I)V
        //   126: goto -45 -> 81
        //   129: astore 9
        //   131: aload 8
        //   133: invokevirtual 56	android/os/Parcel:recycle	()V
        //   136: aload 7
        //   138: invokevirtual 56	android/os/Parcel:recycle	()V
        //   141: aload 9
        //   143: athrow
        // Local variable table:
        //   start	length	slot	name	signature
        //   0	144	0	this	zza
        //   0	144	1	paramzzr	zzr
        //   0	144	2	paramInt	int
        //   0	144	3	paramString1	String
        //   0	144	4	paramArrayOfString	String[]
        //   0	144	5	paramString2	String
        //   0	144	6	paramBundle	Bundle
        //   3	134	7	localParcel1	Parcel
        //   8	124	8	localParcel2	Parcel
        //   129	13	9	localObject	Object
        //   27	89	10	localIBinder	IBinder
        // Exception table:
        //   from	to	target	type
        //   10	17	129	finally
        //   21	29	129	finally
        //   29	62	129	finally
        //   67	81	129	finally
        //   81	103	129	finally
        //   120	126	129	finally
      }
      
      /* Error */
      public final void zza(zzr paramzzr, GetServiceRequest paramGetServiceRequest)
        throws RemoteException
      {
        // Byte code:
        //   0: invokestatic 27	android/os/Parcel:obtain	()Landroid/os/Parcel;
        //   3: astore_3
        //   4: invokestatic 27	android/os/Parcel:obtain	()Landroid/os/Parcel;
        //   7: astore 4
        //   9: aload_3
        //   10: ldc 29
        //   12: invokevirtual 33	android/os/Parcel:writeInterfaceToken	(Ljava/lang/String;)V
        //   15: aload_1
        //   16: ifnull +63 -> 79
        //   19: aload_1
        //   20: invokeinterface 37 1 0
        //   25: astore 6
        //   27: aload_3
        //   28: aload 6
        //   30: invokevirtual 40	android/os/Parcel:writeStrongBinder	(Landroid/os/IBinder;)V
        //   33: aload_2
        //   34: ifnull +51 -> 85
        //   37: aload_3
        //   38: iconst_1
        //   39: invokevirtual 44	android/os/Parcel:writeInt	(I)V
        //   42: aload_2
        //   43: aload_3
        //   44: iconst_0
        //   45: invokevirtual 83	com/google/android/gms/common/internal/GetServiceRequest:writeToParcel	(Landroid/os/Parcel;I)V
        //   48: aload_0
        //   49: getfield 15	com/google/android/gms/common/internal/zzs$zza$zza:zzop	Landroid/os/IBinder;
        //   52: bipush 46
        //   54: aload_3
        //   55: aload 4
        //   57: iconst_0
        //   58: invokeinterface 50 5 0
        //   63: pop
        //   64: aload 4
        //   66: invokevirtual 53	android/os/Parcel:readException	()V
        //   69: aload 4
        //   71: invokevirtual 56	android/os/Parcel:recycle	()V
        //   74: aload_3
        //   75: invokevirtual 56	android/os/Parcel:recycle	()V
        //   78: return
        //   79: aconst_null
        //   80: astore 6
        //   82: goto -55 -> 27
        //   85: aload_3
        //   86: iconst_0
        //   87: invokevirtual 44	android/os/Parcel:writeInt	(I)V
        //   90: goto -42 -> 48
        //   93: astore 5
        //   95: aload 4
        //   97: invokevirtual 56	android/os/Parcel:recycle	()V
        //   100: aload_3
        //   101: invokevirtual 56	android/os/Parcel:recycle	()V
        //   104: aload 5
        //   106: athrow
        // Local variable table:
        //   start	length	slot	name	signature
        //   0	107	0	this	zza
        //   0	107	1	paramzzr	zzr
        //   0	107	2	paramGetServiceRequest	GetServiceRequest
        //   3	98	3	localParcel1	Parcel
        //   7	89	4	localParcel2	Parcel
        //   93	12	5	localObject	Object
        //   25	56	6	localIBinder	IBinder
        // Exception table:
        //   from	to	target	type
        //   9	15	93	finally
        //   19	27	93	finally
        //   27	33	93	finally
        //   37	48	93	finally
        //   48	69	93	finally
        //   85	90	93	finally
      }
      
      /* Error */
      public final void zza(zzr paramzzr, ValidateAccountRequest paramValidateAccountRequest)
        throws RemoteException
      {
        // Byte code:
        //   0: invokestatic 27	android/os/Parcel:obtain	()Landroid/os/Parcel;
        //   3: astore_3
        //   4: invokestatic 27	android/os/Parcel:obtain	()Landroid/os/Parcel;
        //   7: astore 4
        //   9: aload_3
        //   10: ldc 29
        //   12: invokevirtual 33	android/os/Parcel:writeInterfaceToken	(Ljava/lang/String;)V
        //   15: aload_1
        //   16: ifnull +63 -> 79
        //   19: aload_1
        //   20: invokeinterface 37 1 0
        //   25: astore 6
        //   27: aload_3
        //   28: aload 6
        //   30: invokevirtual 40	android/os/Parcel:writeStrongBinder	(Landroid/os/IBinder;)V
        //   33: aload_2
        //   34: ifnull +51 -> 85
        //   37: aload_3
        //   38: iconst_1
        //   39: invokevirtual 44	android/os/Parcel:writeInt	(I)V
        //   42: aload_2
        //   43: aload_3
        //   44: iconst_0
        //   45: invokevirtual 87	com/google/android/gms/common/internal/ValidateAccountRequest:writeToParcel	(Landroid/os/Parcel;I)V
        //   48: aload_0
        //   49: getfield 15	com/google/android/gms/common/internal/zzs$zza$zza:zzop	Landroid/os/IBinder;
        //   52: bipush 47
        //   54: aload_3
        //   55: aload 4
        //   57: iconst_0
        //   58: invokeinterface 50 5 0
        //   63: pop
        //   64: aload 4
        //   66: invokevirtual 53	android/os/Parcel:readException	()V
        //   69: aload 4
        //   71: invokevirtual 56	android/os/Parcel:recycle	()V
        //   74: aload_3
        //   75: invokevirtual 56	android/os/Parcel:recycle	()V
        //   78: return
        //   79: aconst_null
        //   80: astore 6
        //   82: goto -55 -> 27
        //   85: aload_3
        //   86: iconst_0
        //   87: invokevirtual 44	android/os/Parcel:writeInt	(I)V
        //   90: goto -42 -> 48
        //   93: astore 5
        //   95: aload 4
        //   97: invokevirtual 56	android/os/Parcel:recycle	()V
        //   100: aload_3
        //   101: invokevirtual 56	android/os/Parcel:recycle	()V
        //   104: aload 5
        //   106: athrow
        // Local variable table:
        //   start	length	slot	name	signature
        //   0	107	0	this	zza
        //   0	107	1	paramzzr	zzr
        //   0	107	2	paramValidateAccountRequest	ValidateAccountRequest
        //   3	98	3	localParcel1	Parcel
        //   7	89	4	localParcel2	Parcel
        //   93	12	5	localObject	Object
        //   25	56	6	localIBinder	IBinder
        // Exception table:
        //   from	to	target	type
        //   9	15	93	finally
        //   19	27	93	finally
        //   27	33	93	finally
        //   37	48	93	finally
        //   48	69	93	finally
        //   85	90	93	finally
      }
      
      /* Error */
      public final void zzb(zzr paramzzr, int paramInt, String paramString)
        throws RemoteException
      {
        // Byte code:
        //   0: invokestatic 27	android/os/Parcel:obtain	()Landroid/os/Parcel;
        //   3: astore 4
        //   5: invokestatic 27	android/os/Parcel:obtain	()Landroid/os/Parcel;
        //   8: astore 5
        //   10: aload 4
        //   12: ldc 29
        //   14: invokevirtual 33	android/os/Parcel:writeInterfaceToken	(Ljava/lang/String;)V
        //   17: aload_1
        //   18: ifnull +63 -> 81
        //   21: aload_1
        //   22: invokeinterface 37 1 0
        //   27: astore 7
        //   29: aload 4
        //   31: aload 7
        //   33: invokevirtual 40	android/os/Parcel:writeStrongBinder	(Landroid/os/IBinder;)V
        //   36: aload 4
        //   38: iload_2
        //   39: invokevirtual 44	android/os/Parcel:writeInt	(I)V
        //   42: aload 4
        //   44: aload_3
        //   45: invokevirtual 60	android/os/Parcel:writeString	(Ljava/lang/String;)V
        //   48: aload_0
        //   49: getfield 15	com/google/android/gms/common/internal/zzs$zza$zza:zzop	Landroid/os/IBinder;
        //   52: bipush 21
        //   54: aload 4
        //   56: aload 5
        //   58: iconst_0
        //   59: invokeinterface 50 5 0
        //   64: pop
        //   65: aload 5
        //   67: invokevirtual 53	android/os/Parcel:readException	()V
        //   70: aload 5
        //   72: invokevirtual 56	android/os/Parcel:recycle	()V
        //   75: aload 4
        //   77: invokevirtual 56	android/os/Parcel:recycle	()V
        //   80: return
        //   81: aconst_null
        //   82: astore 7
        //   84: goto -55 -> 29
        //   87: astore 6
        //   89: aload 5
        //   91: invokevirtual 56	android/os/Parcel:recycle	()V
        //   94: aload 4
        //   96: invokevirtual 56	android/os/Parcel:recycle	()V
        //   99: aload 6
        //   101: athrow
        // Local variable table:
        //   start	length	slot	name	signature
        //   0	102	0	this	zza
        //   0	102	1	paramzzr	zzr
        //   0	102	2	paramInt	int
        //   0	102	3	paramString	String
        //   3	92	4	localParcel1	Parcel
        //   8	82	5	localParcel2	Parcel
        //   87	13	6	localObject	Object
        //   27	56	7	localIBinder	IBinder
        // Exception table:
        //   from	to	target	type
        //   10	17	87	finally
        //   21	29	87	finally
        //   29	70	87	finally
      }
      
      /* Error */
      public final void zzb(zzr paramzzr, int paramInt, String paramString, Bundle paramBundle)
        throws RemoteException
      {
        // Byte code:
        //   0: invokestatic 27	android/os/Parcel:obtain	()Landroid/os/Parcel;
        //   3: astore 5
        //   5: invokestatic 27	android/os/Parcel:obtain	()Landroid/os/Parcel;
        //   8: astore 6
        //   10: aload 5
        //   12: ldc 29
        //   14: invokevirtual 33	android/os/Parcel:writeInterfaceToken	(Ljava/lang/String;)V
        //   17: aload_1
        //   18: ifnull +81 -> 99
        //   21: aload_1
        //   22: invokeinterface 37 1 0
        //   27: astore 8
        //   29: aload 5
        //   31: aload 8
        //   33: invokevirtual 40	android/os/Parcel:writeStrongBinder	(Landroid/os/IBinder;)V
        //   36: aload 5
        //   38: iload_2
        //   39: invokevirtual 44	android/os/Parcel:writeInt	(I)V
        //   42: aload 5
        //   44: aload_3
        //   45: invokevirtual 60	android/os/Parcel:writeString	(Ljava/lang/String;)V
        //   48: aload 4
        //   50: ifnull +55 -> 105
        //   53: aload 5
        //   55: iconst_1
        //   56: invokevirtual 44	android/os/Parcel:writeInt	(I)V
        //   59: aload 4
        //   61: aload 5
        //   63: iconst_0
        //   64: invokevirtual 67	android/os/Bundle:writeToParcel	(Landroid/os/Parcel;I)V
        //   67: aload_0
        //   68: getfield 15	com/google/android/gms/common/internal/zzs$zza$zza:zzop	Landroid/os/IBinder;
        //   71: iconst_5
        //   72: aload 5
        //   74: aload 6
        //   76: iconst_0
        //   77: invokeinterface 50 5 0
        //   82: pop
        //   83: aload 6
        //   85: invokevirtual 53	android/os/Parcel:readException	()V
        //   88: aload 6
        //   90: invokevirtual 56	android/os/Parcel:recycle	()V
        //   93: aload 5
        //   95: invokevirtual 56	android/os/Parcel:recycle	()V
        //   98: return
        //   99: aconst_null
        //   100: astore 8
        //   102: goto -73 -> 29
        //   105: aload 5
        //   107: iconst_0
        //   108: invokevirtual 44	android/os/Parcel:writeInt	(I)V
        //   111: goto -44 -> 67
        //   114: astore 7
        //   116: aload 6
        //   118: invokevirtual 56	android/os/Parcel:recycle	()V
        //   121: aload 5
        //   123: invokevirtual 56	android/os/Parcel:recycle	()V
        //   126: aload 7
        //   128: athrow
        // Local variable table:
        //   start	length	slot	name	signature
        //   0	129	0	this	zza
        //   0	129	1	paramzzr	zzr
        //   0	129	2	paramInt	int
        //   0	129	3	paramString	String
        //   0	129	4	paramBundle	Bundle
        //   3	119	5	localParcel1	Parcel
        //   8	109	6	localParcel2	Parcel
        //   114	13	7	localObject	Object
        //   27	74	8	localIBinder	IBinder
        // Exception table:
        //   from	to	target	type
        //   10	17	114	finally
        //   21	29	114	finally
        //   29	48	114	finally
        //   53	67	114	finally
        //   67	88	114	finally
        //   105	111	114	finally
      }
      
      /* Error */
      public final void zzc(zzr paramzzr, int paramInt, String paramString)
        throws RemoteException
      {
        // Byte code:
        //   0: invokestatic 27	android/os/Parcel:obtain	()Landroid/os/Parcel;
        //   3: astore 4
        //   5: invokestatic 27	android/os/Parcel:obtain	()Landroid/os/Parcel;
        //   8: astore 5
        //   10: aload 4
        //   12: ldc 29
        //   14: invokevirtual 33	android/os/Parcel:writeInterfaceToken	(Ljava/lang/String;)V
        //   17: aload_1
        //   18: ifnull +63 -> 81
        //   21: aload_1
        //   22: invokeinterface 37 1 0
        //   27: astore 7
        //   29: aload 4
        //   31: aload 7
        //   33: invokevirtual 40	android/os/Parcel:writeStrongBinder	(Landroid/os/IBinder;)V
        //   36: aload 4
        //   38: iload_2
        //   39: invokevirtual 44	android/os/Parcel:writeInt	(I)V
        //   42: aload 4
        //   44: aload_3
        //   45: invokevirtual 60	android/os/Parcel:writeString	(Ljava/lang/String;)V
        //   48: aload_0
        //   49: getfield 15	com/google/android/gms/common/internal/zzs$zza$zza:zzop	Landroid/os/IBinder;
        //   52: bipush 22
        //   54: aload 4
        //   56: aload 5
        //   58: iconst_0
        //   59: invokeinterface 50 5 0
        //   64: pop
        //   65: aload 5
        //   67: invokevirtual 53	android/os/Parcel:readException	()V
        //   70: aload 5
        //   72: invokevirtual 56	android/os/Parcel:recycle	()V
        //   75: aload 4
        //   77: invokevirtual 56	android/os/Parcel:recycle	()V
        //   80: return
        //   81: aconst_null
        //   82: astore 7
        //   84: goto -55 -> 29
        //   87: astore 6
        //   89: aload 5
        //   91: invokevirtual 56	android/os/Parcel:recycle	()V
        //   94: aload 4
        //   96: invokevirtual 56	android/os/Parcel:recycle	()V
        //   99: aload 6
        //   101: athrow
        // Local variable table:
        //   start	length	slot	name	signature
        //   0	102	0	this	zza
        //   0	102	1	paramzzr	zzr
        //   0	102	2	paramInt	int
        //   0	102	3	paramString	String
        //   3	92	4	localParcel1	Parcel
        //   8	82	5	localParcel2	Parcel
        //   87	13	6	localObject	Object
        //   27	56	7	localIBinder	IBinder
        // Exception table:
        //   from	to	target	type
        //   10	17	87	finally
        //   21	29	87	finally
        //   29	70	87	finally
      }
      
      /* Error */
      public final void zzc(zzr paramzzr, int paramInt, String paramString, Bundle paramBundle)
        throws RemoteException
      {
        // Byte code:
        //   0: invokestatic 27	android/os/Parcel:obtain	()Landroid/os/Parcel;
        //   3: astore 5
        //   5: invokestatic 27	android/os/Parcel:obtain	()Landroid/os/Parcel;
        //   8: astore 6
        //   10: aload 5
        //   12: ldc 29
        //   14: invokevirtual 33	android/os/Parcel:writeInterfaceToken	(Ljava/lang/String;)V
        //   17: aload_1
        //   18: ifnull +82 -> 100
        //   21: aload_1
        //   22: invokeinterface 37 1 0
        //   27: astore 8
        //   29: aload 5
        //   31: aload 8
        //   33: invokevirtual 40	android/os/Parcel:writeStrongBinder	(Landroid/os/IBinder;)V
        //   36: aload 5
        //   38: iload_2
        //   39: invokevirtual 44	android/os/Parcel:writeInt	(I)V
        //   42: aload 5
        //   44: aload_3
        //   45: invokevirtual 60	android/os/Parcel:writeString	(Ljava/lang/String;)V
        //   48: aload 4
        //   50: ifnull +56 -> 106
        //   53: aload 5
        //   55: iconst_1
        //   56: invokevirtual 44	android/os/Parcel:writeInt	(I)V
        //   59: aload 4
        //   61: aload 5
        //   63: iconst_0
        //   64: invokevirtual 67	android/os/Bundle:writeToParcel	(Landroid/os/Parcel;I)V
        //   67: aload_0
        //   68: getfield 15	com/google/android/gms/common/internal/zzs$zza$zza:zzop	Landroid/os/IBinder;
        //   71: bipush 6
        //   73: aload 5
        //   75: aload 6
        //   77: iconst_0
        //   78: invokeinterface 50 5 0
        //   83: pop
        //   84: aload 6
        //   86: invokevirtual 53	android/os/Parcel:readException	()V
        //   89: aload 6
        //   91: invokevirtual 56	android/os/Parcel:recycle	()V
        //   94: aload 5
        //   96: invokevirtual 56	android/os/Parcel:recycle	()V
        //   99: return
        //   100: aconst_null
        //   101: astore 8
        //   103: goto -74 -> 29
        //   106: aload 5
        //   108: iconst_0
        //   109: invokevirtual 44	android/os/Parcel:writeInt	(I)V
        //   112: goto -45 -> 67
        //   115: astore 7
        //   117: aload 6
        //   119: invokevirtual 56	android/os/Parcel:recycle	()V
        //   122: aload 5
        //   124: invokevirtual 56	android/os/Parcel:recycle	()V
        //   127: aload 7
        //   129: athrow
        // Local variable table:
        //   start	length	slot	name	signature
        //   0	130	0	this	zza
        //   0	130	1	paramzzr	zzr
        //   0	130	2	paramInt	int
        //   0	130	3	paramString	String
        //   0	130	4	paramBundle	Bundle
        //   3	120	5	localParcel1	Parcel
        //   8	110	6	localParcel2	Parcel
        //   115	13	7	localObject	Object
        //   27	75	8	localIBinder	IBinder
        // Exception table:
        //   from	to	target	type
        //   10	17	115	finally
        //   21	29	115	finally
        //   29	48	115	finally
        //   53	67	115	finally
        //   67	89	115	finally
        //   106	112	115	finally
      }
      
      /* Error */
      public final void zzd(zzr paramzzr, int paramInt, String paramString)
        throws RemoteException
      {
        // Byte code:
        //   0: invokestatic 27	android/os/Parcel:obtain	()Landroid/os/Parcel;
        //   3: astore 4
        //   5: invokestatic 27	android/os/Parcel:obtain	()Landroid/os/Parcel;
        //   8: astore 5
        //   10: aload 4
        //   12: ldc 29
        //   14: invokevirtual 33	android/os/Parcel:writeInterfaceToken	(Ljava/lang/String;)V
        //   17: aload_1
        //   18: ifnull +63 -> 81
        //   21: aload_1
        //   22: invokeinterface 37 1 0
        //   27: astore 7
        //   29: aload 4
        //   31: aload 7
        //   33: invokevirtual 40	android/os/Parcel:writeStrongBinder	(Landroid/os/IBinder;)V
        //   36: aload 4
        //   38: iload_2
        //   39: invokevirtual 44	android/os/Parcel:writeInt	(I)V
        //   42: aload 4
        //   44: aload_3
        //   45: invokevirtual 60	android/os/Parcel:writeString	(Ljava/lang/String;)V
        //   48: aload_0
        //   49: getfield 15	com/google/android/gms/common/internal/zzs$zza$zza:zzop	Landroid/os/IBinder;
        //   52: bipush 24
        //   54: aload 4
        //   56: aload 5
        //   58: iconst_0
        //   59: invokeinterface 50 5 0
        //   64: pop
        //   65: aload 5
        //   67: invokevirtual 53	android/os/Parcel:readException	()V
        //   70: aload 5
        //   72: invokevirtual 56	android/os/Parcel:recycle	()V
        //   75: aload 4
        //   77: invokevirtual 56	android/os/Parcel:recycle	()V
        //   80: return
        //   81: aconst_null
        //   82: astore 7
        //   84: goto -55 -> 29
        //   87: astore 6
        //   89: aload 5
        //   91: invokevirtual 56	android/os/Parcel:recycle	()V
        //   94: aload 4
        //   96: invokevirtual 56	android/os/Parcel:recycle	()V
        //   99: aload 6
        //   101: athrow
        // Local variable table:
        //   start	length	slot	name	signature
        //   0	102	0	this	zza
        //   0	102	1	paramzzr	zzr
        //   0	102	2	paramInt	int
        //   0	102	3	paramString	String
        //   3	92	4	localParcel1	Parcel
        //   8	82	5	localParcel2	Parcel
        //   87	13	6	localObject	Object
        //   27	56	7	localIBinder	IBinder
        // Exception table:
        //   from	to	target	type
        //   10	17	87	finally
        //   21	29	87	finally
        //   29	70	87	finally
      }
      
      /* Error */
      public final void zzd(zzr paramzzr, int paramInt, String paramString, Bundle paramBundle)
        throws RemoteException
      {
        // Byte code:
        //   0: invokestatic 27	android/os/Parcel:obtain	()Landroid/os/Parcel;
        //   3: astore 5
        //   5: invokestatic 27	android/os/Parcel:obtain	()Landroid/os/Parcel;
        //   8: astore 6
        //   10: aload 5
        //   12: ldc 29
        //   14: invokevirtual 33	android/os/Parcel:writeInterfaceToken	(Ljava/lang/String;)V
        //   17: aload_1
        //   18: ifnull +82 -> 100
        //   21: aload_1
        //   22: invokeinterface 37 1 0
        //   27: astore 8
        //   29: aload 5
        //   31: aload 8
        //   33: invokevirtual 40	android/os/Parcel:writeStrongBinder	(Landroid/os/IBinder;)V
        //   36: aload 5
        //   38: iload_2
        //   39: invokevirtual 44	android/os/Parcel:writeInt	(I)V
        //   42: aload 5
        //   44: aload_3
        //   45: invokevirtual 60	android/os/Parcel:writeString	(Ljava/lang/String;)V
        //   48: aload 4
        //   50: ifnull +56 -> 106
        //   53: aload 5
        //   55: iconst_1
        //   56: invokevirtual 44	android/os/Parcel:writeInt	(I)V
        //   59: aload 4
        //   61: aload 5
        //   63: iconst_0
        //   64: invokevirtual 67	android/os/Bundle:writeToParcel	(Landroid/os/Parcel;I)V
        //   67: aload_0
        //   68: getfield 15	com/google/android/gms/common/internal/zzs$zza$zza:zzop	Landroid/os/IBinder;
        //   71: bipush 7
        //   73: aload 5
        //   75: aload 6
        //   77: iconst_0
        //   78: invokeinterface 50 5 0
        //   83: pop
        //   84: aload 6
        //   86: invokevirtual 53	android/os/Parcel:readException	()V
        //   89: aload 6
        //   91: invokevirtual 56	android/os/Parcel:recycle	()V
        //   94: aload 5
        //   96: invokevirtual 56	android/os/Parcel:recycle	()V
        //   99: return
        //   100: aconst_null
        //   101: astore 8
        //   103: goto -74 -> 29
        //   106: aload 5
        //   108: iconst_0
        //   109: invokevirtual 44	android/os/Parcel:writeInt	(I)V
        //   112: goto -45 -> 67
        //   115: astore 7
        //   117: aload 6
        //   119: invokevirtual 56	android/os/Parcel:recycle	()V
        //   122: aload 5
        //   124: invokevirtual 56	android/os/Parcel:recycle	()V
        //   127: aload 7
        //   129: athrow
        // Local variable table:
        //   start	length	slot	name	signature
        //   0	130	0	this	zza
        //   0	130	1	paramzzr	zzr
        //   0	130	2	paramInt	int
        //   0	130	3	paramString	String
        //   0	130	4	paramBundle	Bundle
        //   3	120	5	localParcel1	Parcel
        //   8	110	6	localParcel2	Parcel
        //   115	13	7	localObject	Object
        //   27	75	8	localIBinder	IBinder
        // Exception table:
        //   from	to	target	type
        //   10	17	115	finally
        //   21	29	115	finally
        //   29	48	115	finally
        //   53	67	115	finally
        //   67	89	115	finally
        //   106	112	115	finally
      }
      
      /* Error */
      public final void zze(zzr paramzzr, int paramInt, String paramString)
        throws RemoteException
      {
        // Byte code:
        //   0: invokestatic 27	android/os/Parcel:obtain	()Landroid/os/Parcel;
        //   3: astore 4
        //   5: invokestatic 27	android/os/Parcel:obtain	()Landroid/os/Parcel;
        //   8: astore 5
        //   10: aload 4
        //   12: ldc 29
        //   14: invokevirtual 33	android/os/Parcel:writeInterfaceToken	(Ljava/lang/String;)V
        //   17: aload_1
        //   18: ifnull +63 -> 81
        //   21: aload_1
        //   22: invokeinterface 37 1 0
        //   27: astore 7
        //   29: aload 4
        //   31: aload 7
        //   33: invokevirtual 40	android/os/Parcel:writeStrongBinder	(Landroid/os/IBinder;)V
        //   36: aload 4
        //   38: iload_2
        //   39: invokevirtual 44	android/os/Parcel:writeInt	(I)V
        //   42: aload 4
        //   44: aload_3
        //   45: invokevirtual 60	android/os/Parcel:writeString	(Ljava/lang/String;)V
        //   48: aload_0
        //   49: getfield 15	com/google/android/gms/common/internal/zzs$zza$zza:zzop	Landroid/os/IBinder;
        //   52: bipush 26
        //   54: aload 4
        //   56: aload 5
        //   58: iconst_0
        //   59: invokeinterface 50 5 0
        //   64: pop
        //   65: aload 5
        //   67: invokevirtual 53	android/os/Parcel:readException	()V
        //   70: aload 5
        //   72: invokevirtual 56	android/os/Parcel:recycle	()V
        //   75: aload 4
        //   77: invokevirtual 56	android/os/Parcel:recycle	()V
        //   80: return
        //   81: aconst_null
        //   82: astore 7
        //   84: goto -55 -> 29
        //   87: astore 6
        //   89: aload 5
        //   91: invokevirtual 56	android/os/Parcel:recycle	()V
        //   94: aload 4
        //   96: invokevirtual 56	android/os/Parcel:recycle	()V
        //   99: aload 6
        //   101: athrow
        // Local variable table:
        //   start	length	slot	name	signature
        //   0	102	0	this	zza
        //   0	102	1	paramzzr	zzr
        //   0	102	2	paramInt	int
        //   0	102	3	paramString	String
        //   3	92	4	localParcel1	Parcel
        //   8	82	5	localParcel2	Parcel
        //   87	13	6	localObject	Object
        //   27	56	7	localIBinder	IBinder
        // Exception table:
        //   from	to	target	type
        //   10	17	87	finally
        //   21	29	87	finally
        //   29	70	87	finally
      }
      
      /* Error */
      public final void zze(zzr paramzzr, int paramInt, String paramString, Bundle paramBundle)
        throws RemoteException
      {
        // Byte code:
        //   0: invokestatic 27	android/os/Parcel:obtain	()Landroid/os/Parcel;
        //   3: astore 5
        //   5: invokestatic 27	android/os/Parcel:obtain	()Landroid/os/Parcel;
        //   8: astore 6
        //   10: aload 5
        //   12: ldc 29
        //   14: invokevirtual 33	android/os/Parcel:writeInterfaceToken	(Ljava/lang/String;)V
        //   17: aload_1
        //   18: ifnull +82 -> 100
        //   21: aload_1
        //   22: invokeinterface 37 1 0
        //   27: astore 8
        //   29: aload 5
        //   31: aload 8
        //   33: invokevirtual 40	android/os/Parcel:writeStrongBinder	(Landroid/os/IBinder;)V
        //   36: aload 5
        //   38: iload_2
        //   39: invokevirtual 44	android/os/Parcel:writeInt	(I)V
        //   42: aload 5
        //   44: aload_3
        //   45: invokevirtual 60	android/os/Parcel:writeString	(Ljava/lang/String;)V
        //   48: aload 4
        //   50: ifnull +56 -> 106
        //   53: aload 5
        //   55: iconst_1
        //   56: invokevirtual 44	android/os/Parcel:writeInt	(I)V
        //   59: aload 4
        //   61: aload 5
        //   63: iconst_0
        //   64: invokevirtual 67	android/os/Bundle:writeToParcel	(Landroid/os/Parcel;I)V
        //   67: aload_0
        //   68: getfield 15	com/google/android/gms/common/internal/zzs$zza$zza:zzop	Landroid/os/IBinder;
        //   71: bipush 8
        //   73: aload 5
        //   75: aload 6
        //   77: iconst_0
        //   78: invokeinterface 50 5 0
        //   83: pop
        //   84: aload 6
        //   86: invokevirtual 53	android/os/Parcel:readException	()V
        //   89: aload 6
        //   91: invokevirtual 56	android/os/Parcel:recycle	()V
        //   94: aload 5
        //   96: invokevirtual 56	android/os/Parcel:recycle	()V
        //   99: return
        //   100: aconst_null
        //   101: astore 8
        //   103: goto -74 -> 29
        //   106: aload 5
        //   108: iconst_0
        //   109: invokevirtual 44	android/os/Parcel:writeInt	(I)V
        //   112: goto -45 -> 67
        //   115: astore 7
        //   117: aload 6
        //   119: invokevirtual 56	android/os/Parcel:recycle	()V
        //   122: aload 5
        //   124: invokevirtual 56	android/os/Parcel:recycle	()V
        //   127: aload 7
        //   129: athrow
        // Local variable table:
        //   start	length	slot	name	signature
        //   0	130	0	this	zza
        //   0	130	1	paramzzr	zzr
        //   0	130	2	paramInt	int
        //   0	130	3	paramString	String
        //   0	130	4	paramBundle	Bundle
        //   3	120	5	localParcel1	Parcel
        //   8	110	6	localParcel2	Parcel
        //   115	13	7	localObject	Object
        //   27	75	8	localIBinder	IBinder
        // Exception table:
        //   from	to	target	type
        //   10	17	115	finally
        //   21	29	115	finally
        //   29	48	115	finally
        //   53	67	115	finally
        //   67	89	115	finally
        //   106	112	115	finally
      }
      
      /* Error */
      public final void zzf(zzr paramzzr, int paramInt, String paramString)
        throws RemoteException
      {
        // Byte code:
        //   0: invokestatic 27	android/os/Parcel:obtain	()Landroid/os/Parcel;
        //   3: astore 4
        //   5: invokestatic 27	android/os/Parcel:obtain	()Landroid/os/Parcel;
        //   8: astore 5
        //   10: aload 4
        //   12: ldc 29
        //   14: invokevirtual 33	android/os/Parcel:writeInterfaceToken	(Ljava/lang/String;)V
        //   17: aload_1
        //   18: ifnull +63 -> 81
        //   21: aload_1
        //   22: invokeinterface 37 1 0
        //   27: astore 7
        //   29: aload 4
        //   31: aload 7
        //   33: invokevirtual 40	android/os/Parcel:writeStrongBinder	(Landroid/os/IBinder;)V
        //   36: aload 4
        //   38: iload_2
        //   39: invokevirtual 44	android/os/Parcel:writeInt	(I)V
        //   42: aload 4
        //   44: aload_3
        //   45: invokevirtual 60	android/os/Parcel:writeString	(Ljava/lang/String;)V
        //   48: aload_0
        //   49: getfield 15	com/google/android/gms/common/internal/zzs$zza$zza:zzop	Landroid/os/IBinder;
        //   52: bipush 31
        //   54: aload 4
        //   56: aload 5
        //   58: iconst_0
        //   59: invokeinterface 50 5 0
        //   64: pop
        //   65: aload 5
        //   67: invokevirtual 53	android/os/Parcel:readException	()V
        //   70: aload 5
        //   72: invokevirtual 56	android/os/Parcel:recycle	()V
        //   75: aload 4
        //   77: invokevirtual 56	android/os/Parcel:recycle	()V
        //   80: return
        //   81: aconst_null
        //   82: astore 7
        //   84: goto -55 -> 29
        //   87: astore 6
        //   89: aload 5
        //   91: invokevirtual 56	android/os/Parcel:recycle	()V
        //   94: aload 4
        //   96: invokevirtual 56	android/os/Parcel:recycle	()V
        //   99: aload 6
        //   101: athrow
        // Local variable table:
        //   start	length	slot	name	signature
        //   0	102	0	this	zza
        //   0	102	1	paramzzr	zzr
        //   0	102	2	paramInt	int
        //   0	102	3	paramString	String
        //   3	92	4	localParcel1	Parcel
        //   8	82	5	localParcel2	Parcel
        //   87	13	6	localObject	Object
        //   27	56	7	localIBinder	IBinder
        // Exception table:
        //   from	to	target	type
        //   10	17	87	finally
        //   21	29	87	finally
        //   29	70	87	finally
      }
      
      /* Error */
      public final void zzf(zzr paramzzr, int paramInt, String paramString, Bundle paramBundle)
        throws RemoteException
      {
        // Byte code:
        //   0: invokestatic 27	android/os/Parcel:obtain	()Landroid/os/Parcel;
        //   3: astore 5
        //   5: invokestatic 27	android/os/Parcel:obtain	()Landroid/os/Parcel;
        //   8: astore 6
        //   10: aload 5
        //   12: ldc 29
        //   14: invokevirtual 33	android/os/Parcel:writeInterfaceToken	(Ljava/lang/String;)V
        //   17: aload_1
        //   18: ifnull +82 -> 100
        //   21: aload_1
        //   22: invokeinterface 37 1 0
        //   27: astore 8
        //   29: aload 5
        //   31: aload 8
        //   33: invokevirtual 40	android/os/Parcel:writeStrongBinder	(Landroid/os/IBinder;)V
        //   36: aload 5
        //   38: iload_2
        //   39: invokevirtual 44	android/os/Parcel:writeInt	(I)V
        //   42: aload 5
        //   44: aload_3
        //   45: invokevirtual 60	android/os/Parcel:writeString	(Ljava/lang/String;)V
        //   48: aload 4
        //   50: ifnull +56 -> 106
        //   53: aload 5
        //   55: iconst_1
        //   56: invokevirtual 44	android/os/Parcel:writeInt	(I)V
        //   59: aload 4
        //   61: aload 5
        //   63: iconst_0
        //   64: invokevirtual 67	android/os/Bundle:writeToParcel	(Landroid/os/Parcel;I)V
        //   67: aload_0
        //   68: getfield 15	com/google/android/gms/common/internal/zzs$zza$zza:zzop	Landroid/os/IBinder;
        //   71: bipush 11
        //   73: aload 5
        //   75: aload 6
        //   77: iconst_0
        //   78: invokeinterface 50 5 0
        //   83: pop
        //   84: aload 6
        //   86: invokevirtual 53	android/os/Parcel:readException	()V
        //   89: aload 6
        //   91: invokevirtual 56	android/os/Parcel:recycle	()V
        //   94: aload 5
        //   96: invokevirtual 56	android/os/Parcel:recycle	()V
        //   99: return
        //   100: aconst_null
        //   101: astore 8
        //   103: goto -74 -> 29
        //   106: aload 5
        //   108: iconst_0
        //   109: invokevirtual 44	android/os/Parcel:writeInt	(I)V
        //   112: goto -45 -> 67
        //   115: astore 7
        //   117: aload 6
        //   119: invokevirtual 56	android/os/Parcel:recycle	()V
        //   122: aload 5
        //   124: invokevirtual 56	android/os/Parcel:recycle	()V
        //   127: aload 7
        //   129: athrow
        // Local variable table:
        //   start	length	slot	name	signature
        //   0	130	0	this	zza
        //   0	130	1	paramzzr	zzr
        //   0	130	2	paramInt	int
        //   0	130	3	paramString	String
        //   0	130	4	paramBundle	Bundle
        //   3	120	5	localParcel1	Parcel
        //   8	110	6	localParcel2	Parcel
        //   115	13	7	localObject	Object
        //   27	75	8	localIBinder	IBinder
        // Exception table:
        //   from	to	target	type
        //   10	17	115	finally
        //   21	29	115	finally
        //   29	48	115	finally
        //   53	67	115	finally
        //   67	89	115	finally
        //   106	112	115	finally
      }
      
      /* Error */
      public final void zzg(zzr paramzzr, int paramInt, String paramString)
        throws RemoteException
      {
        // Byte code:
        //   0: invokestatic 27	android/os/Parcel:obtain	()Landroid/os/Parcel;
        //   3: astore 4
        //   5: invokestatic 27	android/os/Parcel:obtain	()Landroid/os/Parcel;
        //   8: astore 5
        //   10: aload 4
        //   12: ldc 29
        //   14: invokevirtual 33	android/os/Parcel:writeInterfaceToken	(Ljava/lang/String;)V
        //   17: aload_1
        //   18: ifnull +63 -> 81
        //   21: aload_1
        //   22: invokeinterface 37 1 0
        //   27: astore 7
        //   29: aload 4
        //   31: aload 7
        //   33: invokevirtual 40	android/os/Parcel:writeStrongBinder	(Landroid/os/IBinder;)V
        //   36: aload 4
        //   38: iload_2
        //   39: invokevirtual 44	android/os/Parcel:writeInt	(I)V
        //   42: aload 4
        //   44: aload_3
        //   45: invokevirtual 60	android/os/Parcel:writeString	(Ljava/lang/String;)V
        //   48: aload_0
        //   49: getfield 15	com/google/android/gms/common/internal/zzs$zza$zza:zzop	Landroid/os/IBinder;
        //   52: bipush 32
        //   54: aload 4
        //   56: aload 5
        //   58: iconst_0
        //   59: invokeinterface 50 5 0
        //   64: pop
        //   65: aload 5
        //   67: invokevirtual 53	android/os/Parcel:readException	()V
        //   70: aload 5
        //   72: invokevirtual 56	android/os/Parcel:recycle	()V
        //   75: aload 4
        //   77: invokevirtual 56	android/os/Parcel:recycle	()V
        //   80: return
        //   81: aconst_null
        //   82: astore 7
        //   84: goto -55 -> 29
        //   87: astore 6
        //   89: aload 5
        //   91: invokevirtual 56	android/os/Parcel:recycle	()V
        //   94: aload 4
        //   96: invokevirtual 56	android/os/Parcel:recycle	()V
        //   99: aload 6
        //   101: athrow
        // Local variable table:
        //   start	length	slot	name	signature
        //   0	102	0	this	zza
        //   0	102	1	paramzzr	zzr
        //   0	102	2	paramInt	int
        //   0	102	3	paramString	String
        //   3	92	4	localParcel1	Parcel
        //   8	82	5	localParcel2	Parcel
        //   87	13	6	localObject	Object
        //   27	56	7	localIBinder	IBinder
        // Exception table:
        //   from	to	target	type
        //   10	17	87	finally
        //   21	29	87	finally
        //   29	70	87	finally
      }
      
      /* Error */
      public final void zzg(zzr paramzzr, int paramInt, String paramString, Bundle paramBundle)
        throws RemoteException
      {
        // Byte code:
        //   0: invokestatic 27	android/os/Parcel:obtain	()Landroid/os/Parcel;
        //   3: astore 5
        //   5: invokestatic 27	android/os/Parcel:obtain	()Landroid/os/Parcel;
        //   8: astore 6
        //   10: aload 5
        //   12: ldc 29
        //   14: invokevirtual 33	android/os/Parcel:writeInterfaceToken	(Ljava/lang/String;)V
        //   17: aload_1
        //   18: ifnull +82 -> 100
        //   21: aload_1
        //   22: invokeinterface 37 1 0
        //   27: astore 8
        //   29: aload 5
        //   31: aload 8
        //   33: invokevirtual 40	android/os/Parcel:writeStrongBinder	(Landroid/os/IBinder;)V
        //   36: aload 5
        //   38: iload_2
        //   39: invokevirtual 44	android/os/Parcel:writeInt	(I)V
        //   42: aload 5
        //   44: aload_3
        //   45: invokevirtual 60	android/os/Parcel:writeString	(Ljava/lang/String;)V
        //   48: aload 4
        //   50: ifnull +56 -> 106
        //   53: aload 5
        //   55: iconst_1
        //   56: invokevirtual 44	android/os/Parcel:writeInt	(I)V
        //   59: aload 4
        //   61: aload 5
        //   63: iconst_0
        //   64: invokevirtual 67	android/os/Bundle:writeToParcel	(Landroid/os/Parcel;I)V
        //   67: aload_0
        //   68: getfield 15	com/google/android/gms/common/internal/zzs$zza$zza:zzop	Landroid/os/IBinder;
        //   71: bipush 12
        //   73: aload 5
        //   75: aload 6
        //   77: iconst_0
        //   78: invokeinterface 50 5 0
        //   83: pop
        //   84: aload 6
        //   86: invokevirtual 53	android/os/Parcel:readException	()V
        //   89: aload 6
        //   91: invokevirtual 56	android/os/Parcel:recycle	()V
        //   94: aload 5
        //   96: invokevirtual 56	android/os/Parcel:recycle	()V
        //   99: return
        //   100: aconst_null
        //   101: astore 8
        //   103: goto -74 -> 29
        //   106: aload 5
        //   108: iconst_0
        //   109: invokevirtual 44	android/os/Parcel:writeInt	(I)V
        //   112: goto -45 -> 67
        //   115: astore 7
        //   117: aload 6
        //   119: invokevirtual 56	android/os/Parcel:recycle	()V
        //   122: aload 5
        //   124: invokevirtual 56	android/os/Parcel:recycle	()V
        //   127: aload 7
        //   129: athrow
        // Local variable table:
        //   start	length	slot	name	signature
        //   0	130	0	this	zza
        //   0	130	1	paramzzr	zzr
        //   0	130	2	paramInt	int
        //   0	130	3	paramString	String
        //   0	130	4	paramBundle	Bundle
        //   3	120	5	localParcel1	Parcel
        //   8	110	6	localParcel2	Parcel
        //   115	13	7	localObject	Object
        //   27	75	8	localIBinder	IBinder
        // Exception table:
        //   from	to	target	type
        //   10	17	115	finally
        //   21	29	115	finally
        //   29	48	115	finally
        //   53	67	115	finally
        //   67	89	115	finally
        //   106	112	115	finally
      }
      
      /* Error */
      public final void zzh(zzr paramzzr, int paramInt, String paramString)
        throws RemoteException
      {
        // Byte code:
        //   0: invokestatic 27	android/os/Parcel:obtain	()Landroid/os/Parcel;
        //   3: astore 4
        //   5: invokestatic 27	android/os/Parcel:obtain	()Landroid/os/Parcel;
        //   8: astore 5
        //   10: aload 4
        //   12: ldc 29
        //   14: invokevirtual 33	android/os/Parcel:writeInterfaceToken	(Ljava/lang/String;)V
        //   17: aload_1
        //   18: ifnull +63 -> 81
        //   21: aload_1
        //   22: invokeinterface 37 1 0
        //   27: astore 7
        //   29: aload 4
        //   31: aload 7
        //   33: invokevirtual 40	android/os/Parcel:writeStrongBinder	(Landroid/os/IBinder;)V
        //   36: aload 4
        //   38: iload_2
        //   39: invokevirtual 44	android/os/Parcel:writeInt	(I)V
        //   42: aload 4
        //   44: aload_3
        //   45: invokevirtual 60	android/os/Parcel:writeString	(Ljava/lang/String;)V
        //   48: aload_0
        //   49: getfield 15	com/google/android/gms/common/internal/zzs$zza$zza:zzop	Landroid/os/IBinder;
        //   52: bipush 35
        //   54: aload 4
        //   56: aload 5
        //   58: iconst_0
        //   59: invokeinterface 50 5 0
        //   64: pop
        //   65: aload 5
        //   67: invokevirtual 53	android/os/Parcel:readException	()V
        //   70: aload 5
        //   72: invokevirtual 56	android/os/Parcel:recycle	()V
        //   75: aload 4
        //   77: invokevirtual 56	android/os/Parcel:recycle	()V
        //   80: return
        //   81: aconst_null
        //   82: astore 7
        //   84: goto -55 -> 29
        //   87: astore 6
        //   89: aload 5
        //   91: invokevirtual 56	android/os/Parcel:recycle	()V
        //   94: aload 4
        //   96: invokevirtual 56	android/os/Parcel:recycle	()V
        //   99: aload 6
        //   101: athrow
        // Local variable table:
        //   start	length	slot	name	signature
        //   0	102	0	this	zza
        //   0	102	1	paramzzr	zzr
        //   0	102	2	paramInt	int
        //   0	102	3	paramString	String
        //   3	92	4	localParcel1	Parcel
        //   8	82	5	localParcel2	Parcel
        //   87	13	6	localObject	Object
        //   27	56	7	localIBinder	IBinder
        // Exception table:
        //   from	to	target	type
        //   10	17	87	finally
        //   21	29	87	finally
        //   29	70	87	finally
      }
      
      /* Error */
      public final void zzh(zzr paramzzr, int paramInt, String paramString, Bundle paramBundle)
        throws RemoteException
      {
        // Byte code:
        //   0: invokestatic 27	android/os/Parcel:obtain	()Landroid/os/Parcel;
        //   3: astore 5
        //   5: invokestatic 27	android/os/Parcel:obtain	()Landroid/os/Parcel;
        //   8: astore 6
        //   10: aload 5
        //   12: ldc 29
        //   14: invokevirtual 33	android/os/Parcel:writeInterfaceToken	(Ljava/lang/String;)V
        //   17: aload_1
        //   18: ifnull +82 -> 100
        //   21: aload_1
        //   22: invokeinterface 37 1 0
        //   27: astore 8
        //   29: aload 5
        //   31: aload 8
        //   33: invokevirtual 40	android/os/Parcel:writeStrongBinder	(Landroid/os/IBinder;)V
        //   36: aload 5
        //   38: iload_2
        //   39: invokevirtual 44	android/os/Parcel:writeInt	(I)V
        //   42: aload 5
        //   44: aload_3
        //   45: invokevirtual 60	android/os/Parcel:writeString	(Ljava/lang/String;)V
        //   48: aload 4
        //   50: ifnull +56 -> 106
        //   53: aload 5
        //   55: iconst_1
        //   56: invokevirtual 44	android/os/Parcel:writeInt	(I)V
        //   59: aload 4
        //   61: aload 5
        //   63: iconst_0
        //   64: invokevirtual 67	android/os/Bundle:writeToParcel	(Landroid/os/Parcel;I)V
        //   67: aload_0
        //   68: getfield 15	com/google/android/gms/common/internal/zzs$zza$zza:zzop	Landroid/os/IBinder;
        //   71: bipush 13
        //   73: aload 5
        //   75: aload 6
        //   77: iconst_0
        //   78: invokeinterface 50 5 0
        //   83: pop
        //   84: aload 6
        //   86: invokevirtual 53	android/os/Parcel:readException	()V
        //   89: aload 6
        //   91: invokevirtual 56	android/os/Parcel:recycle	()V
        //   94: aload 5
        //   96: invokevirtual 56	android/os/Parcel:recycle	()V
        //   99: return
        //   100: aconst_null
        //   101: astore 8
        //   103: goto -74 -> 29
        //   106: aload 5
        //   108: iconst_0
        //   109: invokevirtual 44	android/os/Parcel:writeInt	(I)V
        //   112: goto -45 -> 67
        //   115: astore 7
        //   117: aload 6
        //   119: invokevirtual 56	android/os/Parcel:recycle	()V
        //   122: aload 5
        //   124: invokevirtual 56	android/os/Parcel:recycle	()V
        //   127: aload 7
        //   129: athrow
        // Local variable table:
        //   start	length	slot	name	signature
        //   0	130	0	this	zza
        //   0	130	1	paramzzr	zzr
        //   0	130	2	paramInt	int
        //   0	130	3	paramString	String
        //   0	130	4	paramBundle	Bundle
        //   3	120	5	localParcel1	Parcel
        //   8	110	6	localParcel2	Parcel
        //   115	13	7	localObject	Object
        //   27	75	8	localIBinder	IBinder
        // Exception table:
        //   from	to	target	type
        //   10	17	115	finally
        //   21	29	115	finally
        //   29	48	115	finally
        //   53	67	115	finally
        //   67	89	115	finally
        //   106	112	115	finally
      }
      
      /* Error */
      public final void zzi(zzr paramzzr, int paramInt, String paramString)
        throws RemoteException
      {
        // Byte code:
        //   0: invokestatic 27	android/os/Parcel:obtain	()Landroid/os/Parcel;
        //   3: astore 4
        //   5: invokestatic 27	android/os/Parcel:obtain	()Landroid/os/Parcel;
        //   8: astore 5
        //   10: aload 4
        //   12: ldc 29
        //   14: invokevirtual 33	android/os/Parcel:writeInterfaceToken	(Ljava/lang/String;)V
        //   17: aload_1
        //   18: ifnull +63 -> 81
        //   21: aload_1
        //   22: invokeinterface 37 1 0
        //   27: astore 7
        //   29: aload 4
        //   31: aload 7
        //   33: invokevirtual 40	android/os/Parcel:writeStrongBinder	(Landroid/os/IBinder;)V
        //   36: aload 4
        //   38: iload_2
        //   39: invokevirtual 44	android/os/Parcel:writeInt	(I)V
        //   42: aload 4
        //   44: aload_3
        //   45: invokevirtual 60	android/os/Parcel:writeString	(Ljava/lang/String;)V
        //   48: aload_0
        //   49: getfield 15	com/google/android/gms/common/internal/zzs$zza$zza:zzop	Landroid/os/IBinder;
        //   52: bipush 36
        //   54: aload 4
        //   56: aload 5
        //   58: iconst_0
        //   59: invokeinterface 50 5 0
        //   64: pop
        //   65: aload 5
        //   67: invokevirtual 53	android/os/Parcel:readException	()V
        //   70: aload 5
        //   72: invokevirtual 56	android/os/Parcel:recycle	()V
        //   75: aload 4
        //   77: invokevirtual 56	android/os/Parcel:recycle	()V
        //   80: return
        //   81: aconst_null
        //   82: astore 7
        //   84: goto -55 -> 29
        //   87: astore 6
        //   89: aload 5
        //   91: invokevirtual 56	android/os/Parcel:recycle	()V
        //   94: aload 4
        //   96: invokevirtual 56	android/os/Parcel:recycle	()V
        //   99: aload 6
        //   101: athrow
        // Local variable table:
        //   start	length	slot	name	signature
        //   0	102	0	this	zza
        //   0	102	1	paramzzr	zzr
        //   0	102	2	paramInt	int
        //   0	102	3	paramString	String
        //   3	92	4	localParcel1	Parcel
        //   8	82	5	localParcel2	Parcel
        //   87	13	6	localObject	Object
        //   27	56	7	localIBinder	IBinder
        // Exception table:
        //   from	to	target	type
        //   10	17	87	finally
        //   21	29	87	finally
        //   29	70	87	finally
      }
      
      /* Error */
      public final void zzi(zzr paramzzr, int paramInt, String paramString, Bundle paramBundle)
        throws RemoteException
      {
        // Byte code:
        //   0: invokestatic 27	android/os/Parcel:obtain	()Landroid/os/Parcel;
        //   3: astore 5
        //   5: invokestatic 27	android/os/Parcel:obtain	()Landroid/os/Parcel;
        //   8: astore 6
        //   10: aload 5
        //   12: ldc 29
        //   14: invokevirtual 33	android/os/Parcel:writeInterfaceToken	(Ljava/lang/String;)V
        //   17: aload_1
        //   18: ifnull +82 -> 100
        //   21: aload_1
        //   22: invokeinterface 37 1 0
        //   27: astore 8
        //   29: aload 5
        //   31: aload 8
        //   33: invokevirtual 40	android/os/Parcel:writeStrongBinder	(Landroid/os/IBinder;)V
        //   36: aload 5
        //   38: iload_2
        //   39: invokevirtual 44	android/os/Parcel:writeInt	(I)V
        //   42: aload 5
        //   44: aload_3
        //   45: invokevirtual 60	android/os/Parcel:writeString	(Ljava/lang/String;)V
        //   48: aload 4
        //   50: ifnull +56 -> 106
        //   53: aload 5
        //   55: iconst_1
        //   56: invokevirtual 44	android/os/Parcel:writeInt	(I)V
        //   59: aload 4
        //   61: aload 5
        //   63: iconst_0
        //   64: invokevirtual 67	android/os/Bundle:writeToParcel	(Landroid/os/Parcel;I)V
        //   67: aload_0
        //   68: getfield 15	com/google/android/gms/common/internal/zzs$zza$zza:zzop	Landroid/os/IBinder;
        //   71: bipush 14
        //   73: aload 5
        //   75: aload 6
        //   77: iconst_0
        //   78: invokeinterface 50 5 0
        //   83: pop
        //   84: aload 6
        //   86: invokevirtual 53	android/os/Parcel:readException	()V
        //   89: aload 6
        //   91: invokevirtual 56	android/os/Parcel:recycle	()V
        //   94: aload 5
        //   96: invokevirtual 56	android/os/Parcel:recycle	()V
        //   99: return
        //   100: aconst_null
        //   101: astore 8
        //   103: goto -74 -> 29
        //   106: aload 5
        //   108: iconst_0
        //   109: invokevirtual 44	android/os/Parcel:writeInt	(I)V
        //   112: goto -45 -> 67
        //   115: astore 7
        //   117: aload 6
        //   119: invokevirtual 56	android/os/Parcel:recycle	()V
        //   122: aload 5
        //   124: invokevirtual 56	android/os/Parcel:recycle	()V
        //   127: aload 7
        //   129: athrow
        // Local variable table:
        //   start	length	slot	name	signature
        //   0	130	0	this	zza
        //   0	130	1	paramzzr	zzr
        //   0	130	2	paramInt	int
        //   0	130	3	paramString	String
        //   0	130	4	paramBundle	Bundle
        //   3	120	5	localParcel1	Parcel
        //   8	110	6	localParcel2	Parcel
        //   115	13	7	localObject	Object
        //   27	75	8	localIBinder	IBinder
        // Exception table:
        //   from	to	target	type
        //   10	17	115	finally
        //   21	29	115	finally
        //   29	48	115	finally
        //   53	67	115	finally
        //   67	89	115	finally
        //   106	112	115	finally
      }
      
      /* Error */
      public final void zzj(zzr paramzzr, int paramInt, String paramString)
        throws RemoteException
      {
        // Byte code:
        //   0: invokestatic 27	android/os/Parcel:obtain	()Landroid/os/Parcel;
        //   3: astore 4
        //   5: invokestatic 27	android/os/Parcel:obtain	()Landroid/os/Parcel;
        //   8: astore 5
        //   10: aload 4
        //   12: ldc 29
        //   14: invokevirtual 33	android/os/Parcel:writeInterfaceToken	(Ljava/lang/String;)V
        //   17: aload_1
        //   18: ifnull +63 -> 81
        //   21: aload_1
        //   22: invokeinterface 37 1 0
        //   27: astore 7
        //   29: aload 4
        //   31: aload 7
        //   33: invokevirtual 40	android/os/Parcel:writeStrongBinder	(Landroid/os/IBinder;)V
        //   36: aload 4
        //   38: iload_2
        //   39: invokevirtual 44	android/os/Parcel:writeInt	(I)V
        //   42: aload 4
        //   44: aload_3
        //   45: invokevirtual 60	android/os/Parcel:writeString	(Ljava/lang/String;)V
        //   48: aload_0
        //   49: getfield 15	com/google/android/gms/common/internal/zzs$zza$zza:zzop	Landroid/os/IBinder;
        //   52: bipush 40
        //   54: aload 4
        //   56: aload 5
        //   58: iconst_0
        //   59: invokeinterface 50 5 0
        //   64: pop
        //   65: aload 5
        //   67: invokevirtual 53	android/os/Parcel:readException	()V
        //   70: aload 5
        //   72: invokevirtual 56	android/os/Parcel:recycle	()V
        //   75: aload 4
        //   77: invokevirtual 56	android/os/Parcel:recycle	()V
        //   80: return
        //   81: aconst_null
        //   82: astore 7
        //   84: goto -55 -> 29
        //   87: astore 6
        //   89: aload 5
        //   91: invokevirtual 56	android/os/Parcel:recycle	()V
        //   94: aload 4
        //   96: invokevirtual 56	android/os/Parcel:recycle	()V
        //   99: aload 6
        //   101: athrow
        // Local variable table:
        //   start	length	slot	name	signature
        //   0	102	0	this	zza
        //   0	102	1	paramzzr	zzr
        //   0	102	2	paramInt	int
        //   0	102	3	paramString	String
        //   3	92	4	localParcel1	Parcel
        //   8	82	5	localParcel2	Parcel
        //   87	13	6	localObject	Object
        //   27	56	7	localIBinder	IBinder
        // Exception table:
        //   from	to	target	type
        //   10	17	87	finally
        //   21	29	87	finally
        //   29	70	87	finally
      }
      
      /* Error */
      public final void zzj(zzr paramzzr, int paramInt, String paramString, Bundle paramBundle)
        throws RemoteException
      {
        // Byte code:
        //   0: invokestatic 27	android/os/Parcel:obtain	()Landroid/os/Parcel;
        //   3: astore 5
        //   5: invokestatic 27	android/os/Parcel:obtain	()Landroid/os/Parcel;
        //   8: astore 6
        //   10: aload 5
        //   12: ldc 29
        //   14: invokevirtual 33	android/os/Parcel:writeInterfaceToken	(Ljava/lang/String;)V
        //   17: aload_1
        //   18: ifnull +82 -> 100
        //   21: aload_1
        //   22: invokeinterface 37 1 0
        //   27: astore 8
        //   29: aload 5
        //   31: aload 8
        //   33: invokevirtual 40	android/os/Parcel:writeStrongBinder	(Landroid/os/IBinder;)V
        //   36: aload 5
        //   38: iload_2
        //   39: invokevirtual 44	android/os/Parcel:writeInt	(I)V
        //   42: aload 5
        //   44: aload_3
        //   45: invokevirtual 60	android/os/Parcel:writeString	(Ljava/lang/String;)V
        //   48: aload 4
        //   50: ifnull +56 -> 106
        //   53: aload 5
        //   55: iconst_1
        //   56: invokevirtual 44	android/os/Parcel:writeInt	(I)V
        //   59: aload 4
        //   61: aload 5
        //   63: iconst_0
        //   64: invokevirtual 67	android/os/Bundle:writeToParcel	(Landroid/os/Parcel;I)V
        //   67: aload_0
        //   68: getfield 15	com/google/android/gms/common/internal/zzs$zza$zza:zzop	Landroid/os/IBinder;
        //   71: bipush 15
        //   73: aload 5
        //   75: aload 6
        //   77: iconst_0
        //   78: invokeinterface 50 5 0
        //   83: pop
        //   84: aload 6
        //   86: invokevirtual 53	android/os/Parcel:readException	()V
        //   89: aload 6
        //   91: invokevirtual 56	android/os/Parcel:recycle	()V
        //   94: aload 5
        //   96: invokevirtual 56	android/os/Parcel:recycle	()V
        //   99: return
        //   100: aconst_null
        //   101: astore 8
        //   103: goto -74 -> 29
        //   106: aload 5
        //   108: iconst_0
        //   109: invokevirtual 44	android/os/Parcel:writeInt	(I)V
        //   112: goto -45 -> 67
        //   115: astore 7
        //   117: aload 6
        //   119: invokevirtual 56	android/os/Parcel:recycle	()V
        //   122: aload 5
        //   124: invokevirtual 56	android/os/Parcel:recycle	()V
        //   127: aload 7
        //   129: athrow
        // Local variable table:
        //   start	length	slot	name	signature
        //   0	130	0	this	zza
        //   0	130	1	paramzzr	zzr
        //   0	130	2	paramInt	int
        //   0	130	3	paramString	String
        //   0	130	4	paramBundle	Bundle
        //   3	120	5	localParcel1	Parcel
        //   8	110	6	localParcel2	Parcel
        //   115	13	7	localObject	Object
        //   27	75	8	localIBinder	IBinder
        // Exception table:
        //   from	to	target	type
        //   10	17	115	finally
        //   21	29	115	finally
        //   29	48	115	finally
        //   53	67	115	finally
        //   67	89	115	finally
        //   106	112	115	finally
      }
      
      /* Error */
      public final void zzk(zzr paramzzr, int paramInt, String paramString)
        throws RemoteException
      {
        // Byte code:
        //   0: invokestatic 27	android/os/Parcel:obtain	()Landroid/os/Parcel;
        //   3: astore 4
        //   5: invokestatic 27	android/os/Parcel:obtain	()Landroid/os/Parcel;
        //   8: astore 5
        //   10: aload 4
        //   12: ldc 29
        //   14: invokevirtual 33	android/os/Parcel:writeInterfaceToken	(Ljava/lang/String;)V
        //   17: aload_1
        //   18: ifnull +63 -> 81
        //   21: aload_1
        //   22: invokeinterface 37 1 0
        //   27: astore 7
        //   29: aload 4
        //   31: aload 7
        //   33: invokevirtual 40	android/os/Parcel:writeStrongBinder	(Landroid/os/IBinder;)V
        //   36: aload 4
        //   38: iload_2
        //   39: invokevirtual 44	android/os/Parcel:writeInt	(I)V
        //   42: aload 4
        //   44: aload_3
        //   45: invokevirtual 60	android/os/Parcel:writeString	(Ljava/lang/String;)V
        //   48: aload_0
        //   49: getfield 15	com/google/android/gms/common/internal/zzs$zza$zza:zzop	Landroid/os/IBinder;
        //   52: bipush 42
        //   54: aload 4
        //   56: aload 5
        //   58: iconst_0
        //   59: invokeinterface 50 5 0
        //   64: pop
        //   65: aload 5
        //   67: invokevirtual 53	android/os/Parcel:readException	()V
        //   70: aload 5
        //   72: invokevirtual 56	android/os/Parcel:recycle	()V
        //   75: aload 4
        //   77: invokevirtual 56	android/os/Parcel:recycle	()V
        //   80: return
        //   81: aconst_null
        //   82: astore 7
        //   84: goto -55 -> 29
        //   87: astore 6
        //   89: aload 5
        //   91: invokevirtual 56	android/os/Parcel:recycle	()V
        //   94: aload 4
        //   96: invokevirtual 56	android/os/Parcel:recycle	()V
        //   99: aload 6
        //   101: athrow
        // Local variable table:
        //   start	length	slot	name	signature
        //   0	102	0	this	zza
        //   0	102	1	paramzzr	zzr
        //   0	102	2	paramInt	int
        //   0	102	3	paramString	String
        //   3	92	4	localParcel1	Parcel
        //   8	82	5	localParcel2	Parcel
        //   87	13	6	localObject	Object
        //   27	56	7	localIBinder	IBinder
        // Exception table:
        //   from	to	target	type
        //   10	17	87	finally
        //   21	29	87	finally
        //   29	70	87	finally
      }
      
      /* Error */
      public final void zzk(zzr paramzzr, int paramInt, String paramString, Bundle paramBundle)
        throws RemoteException
      {
        // Byte code:
        //   0: invokestatic 27	android/os/Parcel:obtain	()Landroid/os/Parcel;
        //   3: astore 5
        //   5: invokestatic 27	android/os/Parcel:obtain	()Landroid/os/Parcel;
        //   8: astore 6
        //   10: aload 5
        //   12: ldc 29
        //   14: invokevirtual 33	android/os/Parcel:writeInterfaceToken	(Ljava/lang/String;)V
        //   17: aload_1
        //   18: ifnull +82 -> 100
        //   21: aload_1
        //   22: invokeinterface 37 1 0
        //   27: astore 8
        //   29: aload 5
        //   31: aload 8
        //   33: invokevirtual 40	android/os/Parcel:writeStrongBinder	(Landroid/os/IBinder;)V
        //   36: aload 5
        //   38: iload_2
        //   39: invokevirtual 44	android/os/Parcel:writeInt	(I)V
        //   42: aload 5
        //   44: aload_3
        //   45: invokevirtual 60	android/os/Parcel:writeString	(Ljava/lang/String;)V
        //   48: aload 4
        //   50: ifnull +56 -> 106
        //   53: aload 5
        //   55: iconst_1
        //   56: invokevirtual 44	android/os/Parcel:writeInt	(I)V
        //   59: aload 4
        //   61: aload 5
        //   63: iconst_0
        //   64: invokevirtual 67	android/os/Bundle:writeToParcel	(Landroid/os/Parcel;I)V
        //   67: aload_0
        //   68: getfield 15	com/google/android/gms/common/internal/zzs$zza$zza:zzop	Landroid/os/IBinder;
        //   71: bipush 16
        //   73: aload 5
        //   75: aload 6
        //   77: iconst_0
        //   78: invokeinterface 50 5 0
        //   83: pop
        //   84: aload 6
        //   86: invokevirtual 53	android/os/Parcel:readException	()V
        //   89: aload 6
        //   91: invokevirtual 56	android/os/Parcel:recycle	()V
        //   94: aload 5
        //   96: invokevirtual 56	android/os/Parcel:recycle	()V
        //   99: return
        //   100: aconst_null
        //   101: astore 8
        //   103: goto -74 -> 29
        //   106: aload 5
        //   108: iconst_0
        //   109: invokevirtual 44	android/os/Parcel:writeInt	(I)V
        //   112: goto -45 -> 67
        //   115: astore 7
        //   117: aload 6
        //   119: invokevirtual 56	android/os/Parcel:recycle	()V
        //   122: aload 5
        //   124: invokevirtual 56	android/os/Parcel:recycle	()V
        //   127: aload 7
        //   129: athrow
        // Local variable table:
        //   start	length	slot	name	signature
        //   0	130	0	this	zza
        //   0	130	1	paramzzr	zzr
        //   0	130	2	paramInt	int
        //   0	130	3	paramString	String
        //   0	130	4	paramBundle	Bundle
        //   3	120	5	localParcel1	Parcel
        //   8	110	6	localParcel2	Parcel
        //   115	13	7	localObject	Object
        //   27	75	8	localIBinder	IBinder
        // Exception table:
        //   from	to	target	type
        //   10	17	115	finally
        //   21	29	115	finally
        //   29	48	115	finally
        //   53	67	115	finally
        //   67	89	115	finally
        //   106	112	115	finally
      }
      
      /* Error */
      public final void zzl(zzr paramzzr, int paramInt, String paramString)
        throws RemoteException
      {
        // Byte code:
        //   0: invokestatic 27	android/os/Parcel:obtain	()Landroid/os/Parcel;
        //   3: astore 4
        //   5: invokestatic 27	android/os/Parcel:obtain	()Landroid/os/Parcel;
        //   8: astore 5
        //   10: aload 4
        //   12: ldc 29
        //   14: invokevirtual 33	android/os/Parcel:writeInterfaceToken	(Ljava/lang/String;)V
        //   17: aload_1
        //   18: ifnull +63 -> 81
        //   21: aload_1
        //   22: invokeinterface 37 1 0
        //   27: astore 7
        //   29: aload 4
        //   31: aload 7
        //   33: invokevirtual 40	android/os/Parcel:writeStrongBinder	(Landroid/os/IBinder;)V
        //   36: aload 4
        //   38: iload_2
        //   39: invokevirtual 44	android/os/Parcel:writeInt	(I)V
        //   42: aload 4
        //   44: aload_3
        //   45: invokevirtual 60	android/os/Parcel:writeString	(Ljava/lang/String;)V
        //   48: aload_0
        //   49: getfield 15	com/google/android/gms/common/internal/zzs$zza$zza:zzop	Landroid/os/IBinder;
        //   52: bipush 44
        //   54: aload 4
        //   56: aload 5
        //   58: iconst_0
        //   59: invokeinterface 50 5 0
        //   64: pop
        //   65: aload 5
        //   67: invokevirtual 53	android/os/Parcel:readException	()V
        //   70: aload 5
        //   72: invokevirtual 56	android/os/Parcel:recycle	()V
        //   75: aload 4
        //   77: invokevirtual 56	android/os/Parcel:recycle	()V
        //   80: return
        //   81: aconst_null
        //   82: astore 7
        //   84: goto -55 -> 29
        //   87: astore 6
        //   89: aload 5
        //   91: invokevirtual 56	android/os/Parcel:recycle	()V
        //   94: aload 4
        //   96: invokevirtual 56	android/os/Parcel:recycle	()V
        //   99: aload 6
        //   101: athrow
        // Local variable table:
        //   start	length	slot	name	signature
        //   0	102	0	this	zza
        //   0	102	1	paramzzr	zzr
        //   0	102	2	paramInt	int
        //   0	102	3	paramString	String
        //   3	92	4	localParcel1	Parcel
        //   8	82	5	localParcel2	Parcel
        //   87	13	6	localObject	Object
        //   27	56	7	localIBinder	IBinder
        // Exception table:
        //   from	to	target	type
        //   10	17	87	finally
        //   21	29	87	finally
        //   29	70	87	finally
      }
      
      /* Error */
      public final void zzl(zzr paramzzr, int paramInt, String paramString, Bundle paramBundle)
        throws RemoteException
      {
        // Byte code:
        //   0: invokestatic 27	android/os/Parcel:obtain	()Landroid/os/Parcel;
        //   3: astore 5
        //   5: invokestatic 27	android/os/Parcel:obtain	()Landroid/os/Parcel;
        //   8: astore 6
        //   10: aload 5
        //   12: ldc 29
        //   14: invokevirtual 33	android/os/Parcel:writeInterfaceToken	(Ljava/lang/String;)V
        //   17: aload_1
        //   18: ifnull +82 -> 100
        //   21: aload_1
        //   22: invokeinterface 37 1 0
        //   27: astore 8
        //   29: aload 5
        //   31: aload 8
        //   33: invokevirtual 40	android/os/Parcel:writeStrongBinder	(Landroid/os/IBinder;)V
        //   36: aload 5
        //   38: iload_2
        //   39: invokevirtual 44	android/os/Parcel:writeInt	(I)V
        //   42: aload 5
        //   44: aload_3
        //   45: invokevirtual 60	android/os/Parcel:writeString	(Ljava/lang/String;)V
        //   48: aload 4
        //   50: ifnull +56 -> 106
        //   53: aload 5
        //   55: iconst_1
        //   56: invokevirtual 44	android/os/Parcel:writeInt	(I)V
        //   59: aload 4
        //   61: aload 5
        //   63: iconst_0
        //   64: invokevirtual 67	android/os/Bundle:writeToParcel	(Landroid/os/Parcel;I)V
        //   67: aload_0
        //   68: getfield 15	com/google/android/gms/common/internal/zzs$zza$zza:zzop	Landroid/os/IBinder;
        //   71: bipush 17
        //   73: aload 5
        //   75: aload 6
        //   77: iconst_0
        //   78: invokeinterface 50 5 0
        //   83: pop
        //   84: aload 6
        //   86: invokevirtual 53	android/os/Parcel:readException	()V
        //   89: aload 6
        //   91: invokevirtual 56	android/os/Parcel:recycle	()V
        //   94: aload 5
        //   96: invokevirtual 56	android/os/Parcel:recycle	()V
        //   99: return
        //   100: aconst_null
        //   101: astore 8
        //   103: goto -74 -> 29
        //   106: aload 5
        //   108: iconst_0
        //   109: invokevirtual 44	android/os/Parcel:writeInt	(I)V
        //   112: goto -45 -> 67
        //   115: astore 7
        //   117: aload 6
        //   119: invokevirtual 56	android/os/Parcel:recycle	()V
        //   122: aload 5
        //   124: invokevirtual 56	android/os/Parcel:recycle	()V
        //   127: aload 7
        //   129: athrow
        // Local variable table:
        //   start	length	slot	name	signature
        //   0	130	0	this	zza
        //   0	130	1	paramzzr	zzr
        //   0	130	2	paramInt	int
        //   0	130	3	paramString	String
        //   0	130	4	paramBundle	Bundle
        //   3	120	5	localParcel1	Parcel
        //   8	110	6	localParcel2	Parcel
        //   115	13	7	localObject	Object
        //   27	75	8	localIBinder	IBinder
        // Exception table:
        //   from	to	target	type
        //   10	17	115	finally
        //   21	29	115	finally
        //   29	48	115	finally
        //   53	67	115	finally
        //   67	89	115	finally
        //   106	112	115	finally
      }
      
      /* Error */
      public final void zzm(zzr paramzzr, int paramInt, String paramString)
        throws RemoteException
      {
        // Byte code:
        //   0: invokestatic 27	android/os/Parcel:obtain	()Landroid/os/Parcel;
        //   3: astore 4
        //   5: invokestatic 27	android/os/Parcel:obtain	()Landroid/os/Parcel;
        //   8: astore 5
        //   10: aload 4
        //   12: ldc 29
        //   14: invokevirtual 33	android/os/Parcel:writeInterfaceToken	(Ljava/lang/String;)V
        //   17: aload_1
        //   18: ifnull +63 -> 81
        //   21: aload_1
        //   22: invokeinterface 37 1 0
        //   27: astore 7
        //   29: aload 4
        //   31: aload 7
        //   33: invokevirtual 40	android/os/Parcel:writeStrongBinder	(Landroid/os/IBinder;)V
        //   36: aload 4
        //   38: iload_2
        //   39: invokevirtual 44	android/os/Parcel:writeInt	(I)V
        //   42: aload 4
        //   44: aload_3
        //   45: invokevirtual 60	android/os/Parcel:writeString	(Ljava/lang/String;)V
        //   48: aload_0
        //   49: getfield 15	com/google/android/gms/common/internal/zzs$zza$zza:zzop	Landroid/os/IBinder;
        //   52: bipush 45
        //   54: aload 4
        //   56: aload 5
        //   58: iconst_0
        //   59: invokeinterface 50 5 0
        //   64: pop
        //   65: aload 5
        //   67: invokevirtual 53	android/os/Parcel:readException	()V
        //   70: aload 5
        //   72: invokevirtual 56	android/os/Parcel:recycle	()V
        //   75: aload 4
        //   77: invokevirtual 56	android/os/Parcel:recycle	()V
        //   80: return
        //   81: aconst_null
        //   82: astore 7
        //   84: goto -55 -> 29
        //   87: astore 6
        //   89: aload 5
        //   91: invokevirtual 56	android/os/Parcel:recycle	()V
        //   94: aload 4
        //   96: invokevirtual 56	android/os/Parcel:recycle	()V
        //   99: aload 6
        //   101: athrow
        // Local variable table:
        //   start	length	slot	name	signature
        //   0	102	0	this	zza
        //   0	102	1	paramzzr	zzr
        //   0	102	2	paramInt	int
        //   0	102	3	paramString	String
        //   3	92	4	localParcel1	Parcel
        //   8	82	5	localParcel2	Parcel
        //   87	13	6	localObject	Object
        //   27	56	7	localIBinder	IBinder
        // Exception table:
        //   from	to	target	type
        //   10	17	87	finally
        //   21	29	87	finally
        //   29	70	87	finally
      }
      
      /* Error */
      public final void zzm(zzr paramzzr, int paramInt, String paramString, Bundle paramBundle)
        throws RemoteException
      {
        // Byte code:
        //   0: invokestatic 27	android/os/Parcel:obtain	()Landroid/os/Parcel;
        //   3: astore 5
        //   5: invokestatic 27	android/os/Parcel:obtain	()Landroid/os/Parcel;
        //   8: astore 6
        //   10: aload 5
        //   12: ldc 29
        //   14: invokevirtual 33	android/os/Parcel:writeInterfaceToken	(Ljava/lang/String;)V
        //   17: aload_1
        //   18: ifnull +82 -> 100
        //   21: aload_1
        //   22: invokeinterface 37 1 0
        //   27: astore 8
        //   29: aload 5
        //   31: aload 8
        //   33: invokevirtual 40	android/os/Parcel:writeStrongBinder	(Landroid/os/IBinder;)V
        //   36: aload 5
        //   38: iload_2
        //   39: invokevirtual 44	android/os/Parcel:writeInt	(I)V
        //   42: aload 5
        //   44: aload_3
        //   45: invokevirtual 60	android/os/Parcel:writeString	(Ljava/lang/String;)V
        //   48: aload 4
        //   50: ifnull +56 -> 106
        //   53: aload 5
        //   55: iconst_1
        //   56: invokevirtual 44	android/os/Parcel:writeInt	(I)V
        //   59: aload 4
        //   61: aload 5
        //   63: iconst_0
        //   64: invokevirtual 67	android/os/Bundle:writeToParcel	(Landroid/os/Parcel;I)V
        //   67: aload_0
        //   68: getfield 15	com/google/android/gms/common/internal/zzs$zza$zza:zzop	Landroid/os/IBinder;
        //   71: bipush 18
        //   73: aload 5
        //   75: aload 6
        //   77: iconst_0
        //   78: invokeinterface 50 5 0
        //   83: pop
        //   84: aload 6
        //   86: invokevirtual 53	android/os/Parcel:readException	()V
        //   89: aload 6
        //   91: invokevirtual 56	android/os/Parcel:recycle	()V
        //   94: aload 5
        //   96: invokevirtual 56	android/os/Parcel:recycle	()V
        //   99: return
        //   100: aconst_null
        //   101: astore 8
        //   103: goto -74 -> 29
        //   106: aload 5
        //   108: iconst_0
        //   109: invokevirtual 44	android/os/Parcel:writeInt	(I)V
        //   112: goto -45 -> 67
        //   115: astore 7
        //   117: aload 6
        //   119: invokevirtual 56	android/os/Parcel:recycle	()V
        //   122: aload 5
        //   124: invokevirtual 56	android/os/Parcel:recycle	()V
        //   127: aload 7
        //   129: athrow
        // Local variable table:
        //   start	length	slot	name	signature
        //   0	130	0	this	zza
        //   0	130	1	paramzzr	zzr
        //   0	130	2	paramInt	int
        //   0	130	3	paramString	String
        //   0	130	4	paramBundle	Bundle
        //   3	120	5	localParcel1	Parcel
        //   8	110	6	localParcel2	Parcel
        //   115	13	7	localObject	Object
        //   27	75	8	localIBinder	IBinder
        // Exception table:
        //   from	to	target	type
        //   10	17	115	finally
        //   21	29	115	finally
        //   29	48	115	finally
        //   53	67	115	finally
        //   67	89	115	finally
        //   106	112	115	finally
      }
      
      /* Error */
      public final void zzn(zzr paramzzr, int paramInt, String paramString, Bundle paramBundle)
        throws RemoteException
      {
        // Byte code:
        //   0: invokestatic 27	android/os/Parcel:obtain	()Landroid/os/Parcel;
        //   3: astore 5
        //   5: invokestatic 27	android/os/Parcel:obtain	()Landroid/os/Parcel;
        //   8: astore 6
        //   10: aload 5
        //   12: ldc 29
        //   14: invokevirtual 33	android/os/Parcel:writeInterfaceToken	(Ljava/lang/String;)V
        //   17: aload_1
        //   18: ifnull +82 -> 100
        //   21: aload_1
        //   22: invokeinterface 37 1 0
        //   27: astore 8
        //   29: aload 5
        //   31: aload 8
        //   33: invokevirtual 40	android/os/Parcel:writeStrongBinder	(Landroid/os/IBinder;)V
        //   36: aload 5
        //   38: iload_2
        //   39: invokevirtual 44	android/os/Parcel:writeInt	(I)V
        //   42: aload 5
        //   44: aload_3
        //   45: invokevirtual 60	android/os/Parcel:writeString	(Ljava/lang/String;)V
        //   48: aload 4
        //   50: ifnull +56 -> 106
        //   53: aload 5
        //   55: iconst_1
        //   56: invokevirtual 44	android/os/Parcel:writeInt	(I)V
        //   59: aload 4
        //   61: aload 5
        //   63: iconst_0
        //   64: invokevirtual 67	android/os/Bundle:writeToParcel	(Landroid/os/Parcel;I)V
        //   67: aload_0
        //   68: getfield 15	com/google/android/gms/common/internal/zzs$zza$zza:zzop	Landroid/os/IBinder;
        //   71: bipush 23
        //   73: aload 5
        //   75: aload 6
        //   77: iconst_0
        //   78: invokeinterface 50 5 0
        //   83: pop
        //   84: aload 6
        //   86: invokevirtual 53	android/os/Parcel:readException	()V
        //   89: aload 6
        //   91: invokevirtual 56	android/os/Parcel:recycle	()V
        //   94: aload 5
        //   96: invokevirtual 56	android/os/Parcel:recycle	()V
        //   99: return
        //   100: aconst_null
        //   101: astore 8
        //   103: goto -74 -> 29
        //   106: aload 5
        //   108: iconst_0
        //   109: invokevirtual 44	android/os/Parcel:writeInt	(I)V
        //   112: goto -45 -> 67
        //   115: astore 7
        //   117: aload 6
        //   119: invokevirtual 56	android/os/Parcel:recycle	()V
        //   122: aload 5
        //   124: invokevirtual 56	android/os/Parcel:recycle	()V
        //   127: aload 7
        //   129: athrow
        // Local variable table:
        //   start	length	slot	name	signature
        //   0	130	0	this	zza
        //   0	130	1	paramzzr	zzr
        //   0	130	2	paramInt	int
        //   0	130	3	paramString	String
        //   0	130	4	paramBundle	Bundle
        //   3	120	5	localParcel1	Parcel
        //   8	110	6	localParcel2	Parcel
        //   115	13	7	localObject	Object
        //   27	75	8	localIBinder	IBinder
        // Exception table:
        //   from	to	target	type
        //   10	17	115	finally
        //   21	29	115	finally
        //   29	48	115	finally
        //   53	67	115	finally
        //   67	89	115	finally
        //   106	112	115	finally
      }
      
      /* Error */
      public final void zzo(zzr paramzzr, int paramInt, String paramString, Bundle paramBundle)
        throws RemoteException
      {
        // Byte code:
        //   0: invokestatic 27	android/os/Parcel:obtain	()Landroid/os/Parcel;
        //   3: astore 5
        //   5: invokestatic 27	android/os/Parcel:obtain	()Landroid/os/Parcel;
        //   8: astore 6
        //   10: aload 5
        //   12: ldc 29
        //   14: invokevirtual 33	android/os/Parcel:writeInterfaceToken	(Ljava/lang/String;)V
        //   17: aload_1
        //   18: ifnull +82 -> 100
        //   21: aload_1
        //   22: invokeinterface 37 1 0
        //   27: astore 8
        //   29: aload 5
        //   31: aload 8
        //   33: invokevirtual 40	android/os/Parcel:writeStrongBinder	(Landroid/os/IBinder;)V
        //   36: aload 5
        //   38: iload_2
        //   39: invokevirtual 44	android/os/Parcel:writeInt	(I)V
        //   42: aload 5
        //   44: aload_3
        //   45: invokevirtual 60	android/os/Parcel:writeString	(Ljava/lang/String;)V
        //   48: aload 4
        //   50: ifnull +56 -> 106
        //   53: aload 5
        //   55: iconst_1
        //   56: invokevirtual 44	android/os/Parcel:writeInt	(I)V
        //   59: aload 4
        //   61: aload 5
        //   63: iconst_0
        //   64: invokevirtual 67	android/os/Bundle:writeToParcel	(Landroid/os/Parcel;I)V
        //   67: aload_0
        //   68: getfield 15	com/google/android/gms/common/internal/zzs$zza$zza:zzop	Landroid/os/IBinder;
        //   71: bipush 25
        //   73: aload 5
        //   75: aload 6
        //   77: iconst_0
        //   78: invokeinterface 50 5 0
        //   83: pop
        //   84: aload 6
        //   86: invokevirtual 53	android/os/Parcel:readException	()V
        //   89: aload 6
        //   91: invokevirtual 56	android/os/Parcel:recycle	()V
        //   94: aload 5
        //   96: invokevirtual 56	android/os/Parcel:recycle	()V
        //   99: return
        //   100: aconst_null
        //   101: astore 8
        //   103: goto -74 -> 29
        //   106: aload 5
        //   108: iconst_0
        //   109: invokevirtual 44	android/os/Parcel:writeInt	(I)V
        //   112: goto -45 -> 67
        //   115: astore 7
        //   117: aload 6
        //   119: invokevirtual 56	android/os/Parcel:recycle	()V
        //   122: aload 5
        //   124: invokevirtual 56	android/os/Parcel:recycle	()V
        //   127: aload 7
        //   129: athrow
        // Local variable table:
        //   start	length	slot	name	signature
        //   0	130	0	this	zza
        //   0	130	1	paramzzr	zzr
        //   0	130	2	paramInt	int
        //   0	130	3	paramString	String
        //   0	130	4	paramBundle	Bundle
        //   3	120	5	localParcel1	Parcel
        //   8	110	6	localParcel2	Parcel
        //   115	13	7	localObject	Object
        //   27	75	8	localIBinder	IBinder
        // Exception table:
        //   from	to	target	type
        //   10	17	115	finally
        //   21	29	115	finally
        //   29	48	115	finally
        //   53	67	115	finally
        //   67	89	115	finally
        //   106	112	115	finally
      }
      
      /* Error */
      public final void zzp(zzr paramzzr, int paramInt, String paramString, Bundle paramBundle)
        throws RemoteException
      {
        // Byte code:
        //   0: invokestatic 27	android/os/Parcel:obtain	()Landroid/os/Parcel;
        //   3: astore 5
        //   5: invokestatic 27	android/os/Parcel:obtain	()Landroid/os/Parcel;
        //   8: astore 6
        //   10: aload 5
        //   12: ldc 29
        //   14: invokevirtual 33	android/os/Parcel:writeInterfaceToken	(Ljava/lang/String;)V
        //   17: aload_1
        //   18: ifnull +82 -> 100
        //   21: aload_1
        //   22: invokeinterface 37 1 0
        //   27: astore 8
        //   29: aload 5
        //   31: aload 8
        //   33: invokevirtual 40	android/os/Parcel:writeStrongBinder	(Landroid/os/IBinder;)V
        //   36: aload 5
        //   38: iload_2
        //   39: invokevirtual 44	android/os/Parcel:writeInt	(I)V
        //   42: aload 5
        //   44: aload_3
        //   45: invokevirtual 60	android/os/Parcel:writeString	(Ljava/lang/String;)V
        //   48: aload 4
        //   50: ifnull +56 -> 106
        //   53: aload 5
        //   55: iconst_1
        //   56: invokevirtual 44	android/os/Parcel:writeInt	(I)V
        //   59: aload 4
        //   61: aload 5
        //   63: iconst_0
        //   64: invokevirtual 67	android/os/Bundle:writeToParcel	(Landroid/os/Parcel;I)V
        //   67: aload_0
        //   68: getfield 15	com/google/android/gms/common/internal/zzs$zza$zza:zzop	Landroid/os/IBinder;
        //   71: bipush 27
        //   73: aload 5
        //   75: aload 6
        //   77: iconst_0
        //   78: invokeinterface 50 5 0
        //   83: pop
        //   84: aload 6
        //   86: invokevirtual 53	android/os/Parcel:readException	()V
        //   89: aload 6
        //   91: invokevirtual 56	android/os/Parcel:recycle	()V
        //   94: aload 5
        //   96: invokevirtual 56	android/os/Parcel:recycle	()V
        //   99: return
        //   100: aconst_null
        //   101: astore 8
        //   103: goto -74 -> 29
        //   106: aload 5
        //   108: iconst_0
        //   109: invokevirtual 44	android/os/Parcel:writeInt	(I)V
        //   112: goto -45 -> 67
        //   115: astore 7
        //   117: aload 6
        //   119: invokevirtual 56	android/os/Parcel:recycle	()V
        //   122: aload 5
        //   124: invokevirtual 56	android/os/Parcel:recycle	()V
        //   127: aload 7
        //   129: athrow
        // Local variable table:
        //   start	length	slot	name	signature
        //   0	130	0	this	zza
        //   0	130	1	paramzzr	zzr
        //   0	130	2	paramInt	int
        //   0	130	3	paramString	String
        //   0	130	4	paramBundle	Bundle
        //   3	120	5	localParcel1	Parcel
        //   8	110	6	localParcel2	Parcel
        //   115	13	7	localObject	Object
        //   27	75	8	localIBinder	IBinder
        // Exception table:
        //   from	to	target	type
        //   10	17	115	finally
        //   21	29	115	finally
        //   29	48	115	finally
        //   53	67	115	finally
        //   67	89	115	finally
        //   106	112	115	finally
      }
      
      /* Error */
      public final void zzq(zzr paramzzr, int paramInt, String paramString, Bundle paramBundle)
        throws RemoteException
      {
        // Byte code:
        //   0: invokestatic 27	android/os/Parcel:obtain	()Landroid/os/Parcel;
        //   3: astore 5
        //   5: invokestatic 27	android/os/Parcel:obtain	()Landroid/os/Parcel;
        //   8: astore 6
        //   10: aload 5
        //   12: ldc 29
        //   14: invokevirtual 33	android/os/Parcel:writeInterfaceToken	(Ljava/lang/String;)V
        //   17: aload_1
        //   18: ifnull +82 -> 100
        //   21: aload_1
        //   22: invokeinterface 37 1 0
        //   27: astore 8
        //   29: aload 5
        //   31: aload 8
        //   33: invokevirtual 40	android/os/Parcel:writeStrongBinder	(Landroid/os/IBinder;)V
        //   36: aload 5
        //   38: iload_2
        //   39: invokevirtual 44	android/os/Parcel:writeInt	(I)V
        //   42: aload 5
        //   44: aload_3
        //   45: invokevirtual 60	android/os/Parcel:writeString	(Ljava/lang/String;)V
        //   48: aload 4
        //   50: ifnull +56 -> 106
        //   53: aload 5
        //   55: iconst_1
        //   56: invokevirtual 44	android/os/Parcel:writeInt	(I)V
        //   59: aload 4
        //   61: aload 5
        //   63: iconst_0
        //   64: invokevirtual 67	android/os/Bundle:writeToParcel	(Landroid/os/Parcel;I)V
        //   67: aload_0
        //   68: getfield 15	com/google/android/gms/common/internal/zzs$zza$zza:zzop	Landroid/os/IBinder;
        //   71: bipush 37
        //   73: aload 5
        //   75: aload 6
        //   77: iconst_0
        //   78: invokeinterface 50 5 0
        //   83: pop
        //   84: aload 6
        //   86: invokevirtual 53	android/os/Parcel:readException	()V
        //   89: aload 6
        //   91: invokevirtual 56	android/os/Parcel:recycle	()V
        //   94: aload 5
        //   96: invokevirtual 56	android/os/Parcel:recycle	()V
        //   99: return
        //   100: aconst_null
        //   101: astore 8
        //   103: goto -74 -> 29
        //   106: aload 5
        //   108: iconst_0
        //   109: invokevirtual 44	android/os/Parcel:writeInt	(I)V
        //   112: goto -45 -> 67
        //   115: astore 7
        //   117: aload 6
        //   119: invokevirtual 56	android/os/Parcel:recycle	()V
        //   122: aload 5
        //   124: invokevirtual 56	android/os/Parcel:recycle	()V
        //   127: aload 7
        //   129: athrow
        // Local variable table:
        //   start	length	slot	name	signature
        //   0	130	0	this	zza
        //   0	130	1	paramzzr	zzr
        //   0	130	2	paramInt	int
        //   0	130	3	paramString	String
        //   0	130	4	paramBundle	Bundle
        //   3	120	5	localParcel1	Parcel
        //   8	110	6	localParcel2	Parcel
        //   115	13	7	localObject	Object
        //   27	75	8	localIBinder	IBinder
        // Exception table:
        //   from	to	target	type
        //   10	17	115	finally
        //   21	29	115	finally
        //   29	48	115	finally
        //   53	67	115	finally
        //   67	89	115	finally
        //   106	112	115	finally
      }
      
      public final void zzqA()
        throws RemoteException
      {
        Parcel localParcel1 = Parcel.obtain();
        Parcel localParcel2 = Parcel.obtain();
        try
        {
          localParcel1.writeInterfaceToken("com.google.android.gms.common.internal.IGmsServiceBroker");
          this.zzop.transact(28, localParcel1, localParcel2, 0);
          localParcel2.readException();
          return;
        }
        finally
        {
          localParcel2.recycle();
          localParcel1.recycle();
        }
      }
      
      /* Error */
      public final void zzr(zzr paramzzr, int paramInt, String paramString, Bundle paramBundle)
        throws RemoteException
      {
        // Byte code:
        //   0: invokestatic 27	android/os/Parcel:obtain	()Landroid/os/Parcel;
        //   3: astore 5
        //   5: invokestatic 27	android/os/Parcel:obtain	()Landroid/os/Parcel;
        //   8: astore 6
        //   10: aload 5
        //   12: ldc 29
        //   14: invokevirtual 33	android/os/Parcel:writeInterfaceToken	(Ljava/lang/String;)V
        //   17: aload_1
        //   18: ifnull +82 -> 100
        //   21: aload_1
        //   22: invokeinterface 37 1 0
        //   27: astore 8
        //   29: aload 5
        //   31: aload 8
        //   33: invokevirtual 40	android/os/Parcel:writeStrongBinder	(Landroid/os/IBinder;)V
        //   36: aload 5
        //   38: iload_2
        //   39: invokevirtual 44	android/os/Parcel:writeInt	(I)V
        //   42: aload 5
        //   44: aload_3
        //   45: invokevirtual 60	android/os/Parcel:writeString	(Ljava/lang/String;)V
        //   48: aload 4
        //   50: ifnull +56 -> 106
        //   53: aload 5
        //   55: iconst_1
        //   56: invokevirtual 44	android/os/Parcel:writeInt	(I)V
        //   59: aload 4
        //   61: aload 5
        //   63: iconst_0
        //   64: invokevirtual 67	android/os/Bundle:writeToParcel	(Landroid/os/Parcel;I)V
        //   67: aload_0
        //   68: getfield 15	com/google/android/gms/common/internal/zzs$zza$zza:zzop	Landroid/os/IBinder;
        //   71: bipush 38
        //   73: aload 5
        //   75: aload 6
        //   77: iconst_0
        //   78: invokeinterface 50 5 0
        //   83: pop
        //   84: aload 6
        //   86: invokevirtual 53	android/os/Parcel:readException	()V
        //   89: aload 6
        //   91: invokevirtual 56	android/os/Parcel:recycle	()V
        //   94: aload 5
        //   96: invokevirtual 56	android/os/Parcel:recycle	()V
        //   99: return
        //   100: aconst_null
        //   101: astore 8
        //   103: goto -74 -> 29
        //   106: aload 5
        //   108: iconst_0
        //   109: invokevirtual 44	android/os/Parcel:writeInt	(I)V
        //   112: goto -45 -> 67
        //   115: astore 7
        //   117: aload 6
        //   119: invokevirtual 56	android/os/Parcel:recycle	()V
        //   122: aload 5
        //   124: invokevirtual 56	android/os/Parcel:recycle	()V
        //   127: aload 7
        //   129: athrow
        // Local variable table:
        //   start	length	slot	name	signature
        //   0	130	0	this	zza
        //   0	130	1	paramzzr	zzr
        //   0	130	2	paramInt	int
        //   0	130	3	paramString	String
        //   0	130	4	paramBundle	Bundle
        //   3	120	5	localParcel1	Parcel
        //   8	110	6	localParcel2	Parcel
        //   115	13	7	localObject	Object
        //   27	75	8	localIBinder	IBinder
        // Exception table:
        //   from	to	target	type
        //   10	17	115	finally
        //   21	29	115	finally
        //   29	48	115	finally
        //   53	67	115	finally
        //   67	89	115	finally
        //   106	112	115	finally
      }
      
      /* Error */
      public final void zzs(zzr paramzzr, int paramInt, String paramString, Bundle paramBundle)
        throws RemoteException
      {
        // Byte code:
        //   0: invokestatic 27	android/os/Parcel:obtain	()Landroid/os/Parcel;
        //   3: astore 5
        //   5: invokestatic 27	android/os/Parcel:obtain	()Landroid/os/Parcel;
        //   8: astore 6
        //   10: aload 5
        //   12: ldc 29
        //   14: invokevirtual 33	android/os/Parcel:writeInterfaceToken	(Ljava/lang/String;)V
        //   17: aload_1
        //   18: ifnull +82 -> 100
        //   21: aload_1
        //   22: invokeinterface 37 1 0
        //   27: astore 8
        //   29: aload 5
        //   31: aload 8
        //   33: invokevirtual 40	android/os/Parcel:writeStrongBinder	(Landroid/os/IBinder;)V
        //   36: aload 5
        //   38: iload_2
        //   39: invokevirtual 44	android/os/Parcel:writeInt	(I)V
        //   42: aload 5
        //   44: aload_3
        //   45: invokevirtual 60	android/os/Parcel:writeString	(Ljava/lang/String;)V
        //   48: aload 4
        //   50: ifnull +56 -> 106
        //   53: aload 5
        //   55: iconst_1
        //   56: invokevirtual 44	android/os/Parcel:writeInt	(I)V
        //   59: aload 4
        //   61: aload 5
        //   63: iconst_0
        //   64: invokevirtual 67	android/os/Bundle:writeToParcel	(Landroid/os/Parcel;I)V
        //   67: aload_0
        //   68: getfield 15	com/google/android/gms/common/internal/zzs$zza$zza:zzop	Landroid/os/IBinder;
        //   71: bipush 41
        //   73: aload 5
        //   75: aload 6
        //   77: iconst_0
        //   78: invokeinterface 50 5 0
        //   83: pop
        //   84: aload 6
        //   86: invokevirtual 53	android/os/Parcel:readException	()V
        //   89: aload 6
        //   91: invokevirtual 56	android/os/Parcel:recycle	()V
        //   94: aload 5
        //   96: invokevirtual 56	android/os/Parcel:recycle	()V
        //   99: return
        //   100: aconst_null
        //   101: astore 8
        //   103: goto -74 -> 29
        //   106: aload 5
        //   108: iconst_0
        //   109: invokevirtual 44	android/os/Parcel:writeInt	(I)V
        //   112: goto -45 -> 67
        //   115: astore 7
        //   117: aload 6
        //   119: invokevirtual 56	android/os/Parcel:recycle	()V
        //   122: aload 5
        //   124: invokevirtual 56	android/os/Parcel:recycle	()V
        //   127: aload 7
        //   129: athrow
        // Local variable table:
        //   start	length	slot	name	signature
        //   0	130	0	this	zza
        //   0	130	1	paramzzr	zzr
        //   0	130	2	paramInt	int
        //   0	130	3	paramString	String
        //   0	130	4	paramBundle	Bundle
        //   3	120	5	localParcel1	Parcel
        //   8	110	6	localParcel2	Parcel
        //   115	13	7	localObject	Object
        //   27	75	8	localIBinder	IBinder
        // Exception table:
        //   from	to	target	type
        //   10	17	115	finally
        //   21	29	115	finally
        //   29	48	115	finally
        //   53	67	115	finally
        //   67	89	115	finally
        //   106	112	115	finally
      }
      
      /* Error */
      public final void zzt(zzr paramzzr, int paramInt, String paramString, Bundle paramBundle)
        throws RemoteException
      {
        // Byte code:
        //   0: invokestatic 27	android/os/Parcel:obtain	()Landroid/os/Parcel;
        //   3: astore 5
        //   5: invokestatic 27	android/os/Parcel:obtain	()Landroid/os/Parcel;
        //   8: astore 6
        //   10: aload 5
        //   12: ldc 29
        //   14: invokevirtual 33	android/os/Parcel:writeInterfaceToken	(Ljava/lang/String;)V
        //   17: aload_1
        //   18: ifnull +82 -> 100
        //   21: aload_1
        //   22: invokeinterface 37 1 0
        //   27: astore 8
        //   29: aload 5
        //   31: aload 8
        //   33: invokevirtual 40	android/os/Parcel:writeStrongBinder	(Landroid/os/IBinder;)V
        //   36: aload 5
        //   38: iload_2
        //   39: invokevirtual 44	android/os/Parcel:writeInt	(I)V
        //   42: aload 5
        //   44: aload_3
        //   45: invokevirtual 60	android/os/Parcel:writeString	(Ljava/lang/String;)V
        //   48: aload 4
        //   50: ifnull +56 -> 106
        //   53: aload 5
        //   55: iconst_1
        //   56: invokevirtual 44	android/os/Parcel:writeInt	(I)V
        //   59: aload 4
        //   61: aload 5
        //   63: iconst_0
        //   64: invokevirtual 67	android/os/Bundle:writeToParcel	(Landroid/os/Parcel;I)V
        //   67: aload_0
        //   68: getfield 15	com/google/android/gms/common/internal/zzs$zza$zza:zzop	Landroid/os/IBinder;
        //   71: bipush 43
        //   73: aload 5
        //   75: aload 6
        //   77: iconst_0
        //   78: invokeinterface 50 5 0
        //   83: pop
        //   84: aload 6
        //   86: invokevirtual 53	android/os/Parcel:readException	()V
        //   89: aload 6
        //   91: invokevirtual 56	android/os/Parcel:recycle	()V
        //   94: aload 5
        //   96: invokevirtual 56	android/os/Parcel:recycle	()V
        //   99: return
        //   100: aconst_null
        //   101: astore 8
        //   103: goto -74 -> 29
        //   106: aload 5
        //   108: iconst_0
        //   109: invokevirtual 44	android/os/Parcel:writeInt	(I)V
        //   112: goto -45 -> 67
        //   115: astore 7
        //   117: aload 6
        //   119: invokevirtual 56	android/os/Parcel:recycle	()V
        //   122: aload 5
        //   124: invokevirtual 56	android/os/Parcel:recycle	()V
        //   127: aload 7
        //   129: athrow
        // Local variable table:
        //   start	length	slot	name	signature
        //   0	130	0	this	zza
        //   0	130	1	paramzzr	zzr
        //   0	130	2	paramInt	int
        //   0	130	3	paramString	String
        //   0	130	4	paramBundle	Bundle
        //   3	120	5	localParcel1	Parcel
        //   8	110	6	localParcel2	Parcel
        //   115	13	7	localObject	Object
        //   27	75	8	localIBinder	IBinder
        // Exception table:
        //   from	to	target	type
        //   10	17	115	finally
        //   21	29	115	finally
        //   29	48	115	finally
        //   53	67	115	finally
        //   67	89	115	finally
        //   106	112	115	finally
      }
    }
  }
}


/* Location:           F:\apktool\apktool\Google_Play_Store6.0.5\classes-dex2jar.jar
 * Qualified Name:     com.google.android.gms.common.internal.zzs
 * JD-Core Version:    0.7.0.1
 */