package com.google.android.gms.measurement.internal;

import android.os.Binder;
import android.os.IBinder;
import android.os.IInterface;
import android.os.Parcel;
import android.os.RemoteException;

public abstract interface zzl
  extends IInterface
{
  public abstract void zza(AppMetadata paramAppMetadata)
    throws RemoteException;
  
  public abstract void zza(EventParcel paramEventParcel, AppMetadata paramAppMetadata)
    throws RemoteException;
  
  public abstract void zza(EventParcel paramEventParcel, String paramString1, String paramString2)
    throws RemoteException;
  
  public abstract void zza(UserAttributeParcel paramUserAttributeParcel, AppMetadata paramAppMetadata)
    throws RemoteException;
  
  public abstract void zzb(AppMetadata paramAppMetadata)
    throws RemoteException;
  
  public static abstract class zza
    extends Binder
    implements zzl
  {
    public zza()
    {
      attachInterface(this, "com.google.android.gms.measurement.internal.IMeasurementService");
    }
    
    public static zzl zzfs(IBinder paramIBinder)
    {
      if (paramIBinder == null) {
        return null;
      }
      IInterface localIInterface = paramIBinder.queryLocalInterface("com.google.android.gms.measurement.internal.IMeasurementService");
      if ((localIInterface != null) && ((localIInterface instanceof zzl))) {
        return (zzl)localIInterface;
      }
      return new zza(paramIBinder);
    }
    
    public IBinder asBinder()
    {
      return this;
    }
    
    public boolean onTransact(int paramInt1, Parcel paramParcel1, Parcel paramParcel2, int paramInt2)
      throws RemoteException
    {
      switch (paramInt1)
      {
      default: 
        return super.onTransact(paramInt1, paramParcel1, paramParcel2, paramInt2);
      case 1598968902: 
        paramParcel2.writeString("com.google.android.gms.measurement.internal.IMeasurementService");
        return true;
      case 1: 
        paramParcel1.enforceInterface("com.google.android.gms.measurement.internal.IMeasurementService");
        if (paramParcel1.readInt() != 0) {}
        for (EventParcel localEventParcel2 = zzj.zzgW(paramParcel1);; localEventParcel2 = null)
        {
          int n = paramParcel1.readInt();
          AppMetadata localAppMetadata4 = null;
          if (n != 0) {
            localAppMetadata4 = zzb.zzgU(paramParcel1);
          }
          zza(localEventParcel2, localAppMetadata4);
          paramParcel2.writeNoException();
          return true;
        }
      case 2: 
        paramParcel1.enforceInterface("com.google.android.gms.measurement.internal.IMeasurementService");
        if (paramParcel1.readInt() != 0) {}
        for (UserAttributeParcel localUserAttributeParcel = zzad.zzgX(paramParcel1);; localUserAttributeParcel = null)
        {
          int m = paramParcel1.readInt();
          AppMetadata localAppMetadata3 = null;
          if (m != 0) {
            localAppMetadata3 = zzb.zzgU(paramParcel1);
          }
          zza(localUserAttributeParcel, localAppMetadata3);
          paramParcel2.writeNoException();
          return true;
        }
      case 4: 
        paramParcel1.enforceInterface("com.google.android.gms.measurement.internal.IMeasurementService");
        int k = paramParcel1.readInt();
        AppMetadata localAppMetadata2 = null;
        if (k != 0) {
          localAppMetadata2 = zzb.zzgU(paramParcel1);
        }
        zza(localAppMetadata2);
        paramParcel2.writeNoException();
        return true;
      case 5: 
        paramParcel1.enforceInterface("com.google.android.gms.measurement.internal.IMeasurementService");
        int j = paramParcel1.readInt();
        EventParcel localEventParcel1 = null;
        if (j != 0) {
          localEventParcel1 = zzj.zzgW(paramParcel1);
        }
        zza(localEventParcel1, paramParcel1.readString(), paramParcel1.readString());
        paramParcel2.writeNoException();
        return true;
      }
      paramParcel1.enforceInterface("com.google.android.gms.measurement.internal.IMeasurementService");
      int i = paramParcel1.readInt();
      AppMetadata localAppMetadata1 = null;
      if (i != 0) {
        localAppMetadata1 = zzb.zzgU(paramParcel1);
      }
      zzb(localAppMetadata1);
      paramParcel2.writeNoException();
      return true;
    }
    
    private static final class zza
      implements zzl
    {
      private IBinder zzop;
      
      zza(IBinder paramIBinder)
      {
        this.zzop = paramIBinder;
      }
      
      public final IBinder asBinder()
      {
        return this.zzop;
      }
      
      /* Error */
      public final void zza(AppMetadata paramAppMetadata)
        throws RemoteException
      {
        // Byte code:
        //   0: invokestatic 27	android/os/Parcel:obtain	()Landroid/os/Parcel;
        //   3: astore_2
        //   4: invokestatic 27	android/os/Parcel:obtain	()Landroid/os/Parcel;
        //   7: astore_3
        //   8: aload_2
        //   9: ldc 29
        //   11: invokevirtual 33	android/os/Parcel:writeInterfaceToken	(Ljava/lang/String;)V
        //   14: aload_1
        //   15: ifnull +41 -> 56
        //   18: aload_2
        //   19: iconst_1
        //   20: invokevirtual 37	android/os/Parcel:writeInt	(I)V
        //   23: aload_1
        //   24: aload_2
        //   25: iconst_0
        //   26: invokevirtual 43	com/google/android/gms/measurement/internal/AppMetadata:writeToParcel	(Landroid/os/Parcel;I)V
        //   29: aload_0
        //   30: getfield 15	com/google/android/gms/measurement/internal/zzl$zza$zza:zzop	Landroid/os/IBinder;
        //   33: iconst_4
        //   34: aload_2
        //   35: aload_3
        //   36: iconst_0
        //   37: invokeinterface 49 5 0
        //   42: pop
        //   43: aload_3
        //   44: invokevirtual 52	android/os/Parcel:readException	()V
        //   47: aload_3
        //   48: invokevirtual 55	android/os/Parcel:recycle	()V
        //   51: aload_2
        //   52: invokevirtual 55	android/os/Parcel:recycle	()V
        //   55: return
        //   56: aload_2
        //   57: iconst_0
        //   58: invokevirtual 37	android/os/Parcel:writeInt	(I)V
        //   61: goto -32 -> 29
        //   64: astore 4
        //   66: aload_3
        //   67: invokevirtual 55	android/os/Parcel:recycle	()V
        //   70: aload_2
        //   71: invokevirtual 55	android/os/Parcel:recycle	()V
        //   74: aload 4
        //   76: athrow
        // Local variable table:
        //   start	length	slot	name	signature
        //   0	77	0	this	zza
        //   0	77	1	paramAppMetadata	AppMetadata
        //   3	68	2	localParcel1	Parcel
        //   7	60	3	localParcel2	Parcel
        //   64	11	4	localObject	Object
        // Exception table:
        //   from	to	target	type
        //   8	14	64	finally
        //   18	29	64	finally
        //   29	47	64	finally
        //   56	61	64	finally
      }
      
      public final void zza(EventParcel paramEventParcel, AppMetadata paramAppMetadata)
        throws RemoteException
      {
        Parcel localParcel1 = Parcel.obtain();
        Parcel localParcel2 = Parcel.obtain();
        for (;;)
        {
          try
          {
            localParcel1.writeInterfaceToken("com.google.android.gms.measurement.internal.IMeasurementService");
            if (paramEventParcel != null)
            {
              localParcel1.writeInt(1);
              paramEventParcel.writeToParcel(localParcel1, 0);
              if (paramAppMetadata != null)
              {
                localParcel1.writeInt(1);
                paramAppMetadata.writeToParcel(localParcel1, 0);
                this.zzop.transact(1, localParcel1, localParcel2, 0);
                localParcel2.readException();
              }
            }
            else
            {
              localParcel1.writeInt(0);
              continue;
            }
            localParcel1.writeInt(0);
          }
          finally
          {
            localParcel2.recycle();
            localParcel1.recycle();
          }
        }
      }
      
      /* Error */
      public final void zza(EventParcel paramEventParcel, String paramString1, String paramString2)
        throws RemoteException
      {
        // Byte code:
        //   0: invokestatic 27	android/os/Parcel:obtain	()Landroid/os/Parcel;
        //   3: astore 4
        //   5: invokestatic 27	android/os/Parcel:obtain	()Landroid/os/Parcel;
        //   8: astore 5
        //   10: aload 4
        //   12: ldc 29
        //   14: invokevirtual 33	android/os/Parcel:writeInterfaceToken	(Ljava/lang/String;)V
        //   17: aload_1
        //   18: ifnull +60 -> 78
        //   21: aload 4
        //   23: iconst_1
        //   24: invokevirtual 37	android/os/Parcel:writeInt	(I)V
        //   27: aload_1
        //   28: aload 4
        //   30: iconst_0
        //   31: invokevirtual 59	com/google/android/gms/measurement/internal/EventParcel:writeToParcel	(Landroid/os/Parcel;I)V
        //   34: aload 4
        //   36: aload_2
        //   37: invokevirtual 63	android/os/Parcel:writeString	(Ljava/lang/String;)V
        //   40: aload 4
        //   42: aload_3
        //   43: invokevirtual 63	android/os/Parcel:writeString	(Ljava/lang/String;)V
        //   46: aload_0
        //   47: getfield 15	com/google/android/gms/measurement/internal/zzl$zza$zza:zzop	Landroid/os/IBinder;
        //   50: iconst_5
        //   51: aload 4
        //   53: aload 5
        //   55: iconst_0
        //   56: invokeinterface 49 5 0
        //   61: pop
        //   62: aload 5
        //   64: invokevirtual 52	android/os/Parcel:readException	()V
        //   67: aload 5
        //   69: invokevirtual 55	android/os/Parcel:recycle	()V
        //   72: aload 4
        //   74: invokevirtual 55	android/os/Parcel:recycle	()V
        //   77: return
        //   78: aload 4
        //   80: iconst_0
        //   81: invokevirtual 37	android/os/Parcel:writeInt	(I)V
        //   84: goto -50 -> 34
        //   87: astore 6
        //   89: aload 5
        //   91: invokevirtual 55	android/os/Parcel:recycle	()V
        //   94: aload 4
        //   96: invokevirtual 55	android/os/Parcel:recycle	()V
        //   99: aload 6
        //   101: athrow
        // Local variable table:
        //   start	length	slot	name	signature
        //   0	102	0	this	zza
        //   0	102	1	paramEventParcel	EventParcel
        //   0	102	2	paramString1	String
        //   0	102	3	paramString2	String
        //   3	92	4	localParcel1	Parcel
        //   8	82	5	localParcel2	Parcel
        //   87	13	6	localObject	Object
        // Exception table:
        //   from	to	target	type
        //   10	17	87	finally
        //   21	34	87	finally
        //   34	67	87	finally
        //   78	84	87	finally
      }
      
      public final void zza(UserAttributeParcel paramUserAttributeParcel, AppMetadata paramAppMetadata)
        throws RemoteException
      {
        Parcel localParcel1 = Parcel.obtain();
        Parcel localParcel2 = Parcel.obtain();
        for (;;)
        {
          try
          {
            localParcel1.writeInterfaceToken("com.google.android.gms.measurement.internal.IMeasurementService");
            if (paramUserAttributeParcel != null)
            {
              localParcel1.writeInt(1);
              paramUserAttributeParcel.writeToParcel(localParcel1, 0);
              if (paramAppMetadata != null)
              {
                localParcel1.writeInt(1);
                paramAppMetadata.writeToParcel(localParcel1, 0);
                this.zzop.transact(2, localParcel1, localParcel2, 0);
                localParcel2.readException();
              }
            }
            else
            {
              localParcel1.writeInt(0);
              continue;
            }
            localParcel1.writeInt(0);
          }
          finally
          {
            localParcel2.recycle();
            localParcel1.recycle();
          }
        }
      }
      
      /* Error */
      public final void zzb(AppMetadata paramAppMetadata)
        throws RemoteException
      {
        // Byte code:
        //   0: invokestatic 27	android/os/Parcel:obtain	()Landroid/os/Parcel;
        //   3: astore_2
        //   4: invokestatic 27	android/os/Parcel:obtain	()Landroid/os/Parcel;
        //   7: astore_3
        //   8: aload_2
        //   9: ldc 29
        //   11: invokevirtual 33	android/os/Parcel:writeInterfaceToken	(Ljava/lang/String;)V
        //   14: aload_1
        //   15: ifnull +42 -> 57
        //   18: aload_2
        //   19: iconst_1
        //   20: invokevirtual 37	android/os/Parcel:writeInt	(I)V
        //   23: aload_1
        //   24: aload_2
        //   25: iconst_0
        //   26: invokevirtual 43	com/google/android/gms/measurement/internal/AppMetadata:writeToParcel	(Landroid/os/Parcel;I)V
        //   29: aload_0
        //   30: getfield 15	com/google/android/gms/measurement/internal/zzl$zza$zza:zzop	Landroid/os/IBinder;
        //   33: bipush 6
        //   35: aload_2
        //   36: aload_3
        //   37: iconst_0
        //   38: invokeinterface 49 5 0
        //   43: pop
        //   44: aload_3
        //   45: invokevirtual 52	android/os/Parcel:readException	()V
        //   48: aload_3
        //   49: invokevirtual 55	android/os/Parcel:recycle	()V
        //   52: aload_2
        //   53: invokevirtual 55	android/os/Parcel:recycle	()V
        //   56: return
        //   57: aload_2
        //   58: iconst_0
        //   59: invokevirtual 37	android/os/Parcel:writeInt	(I)V
        //   62: goto -33 -> 29
        //   65: astore 4
        //   67: aload_3
        //   68: invokevirtual 55	android/os/Parcel:recycle	()V
        //   71: aload_2
        //   72: invokevirtual 55	android/os/Parcel:recycle	()V
        //   75: aload 4
        //   77: athrow
        // Local variable table:
        //   start	length	slot	name	signature
        //   0	78	0	this	zza
        //   0	78	1	paramAppMetadata	AppMetadata
        //   3	69	2	localParcel1	Parcel
        //   7	61	3	localParcel2	Parcel
        //   65	11	4	localObject	Object
        // Exception table:
        //   from	to	target	type
        //   8	14	65	finally
        //   18	29	65	finally
        //   29	48	65	finally
        //   57	62	65	finally
      }
    }
  }
}


/* Location:           F:\apktool\apktool\Google_Play_Store6.0.5\classes-dex2jar.jar
 * Qualified Name:     com.google.android.gms.measurement.internal.zzl
 * JD-Core Version:    0.7.0.1
 */