package com.google.android.gms.ads.internal.reward.mediation.client;

import android.os.Binder;
import android.os.IBinder;
import android.os.IInterface;
import android.os.Parcel;
import android.os.RemoteException;
import com.google.android.gms.dynamic.zzd;
import com.google.android.gms.dynamic.zzd.zza;

public abstract interface zza
  extends IInterface
{
  public abstract void zza(zzd paramzzd, RewardItemParcel paramRewardItemParcel)
    throws RemoteException;
  
  public abstract void zzb(zzd paramzzd, int paramInt)
    throws RemoteException;
  
  public abstract void zzc(zzd paramzzd, int paramInt)
    throws RemoteException;
  
  public abstract void zzk(zzd paramzzd)
    throws RemoteException;
  
  public abstract void zzl(zzd paramzzd)
    throws RemoteException;
  
  public abstract void zzm(zzd paramzzd)
    throws RemoteException;
  
  public abstract void zzn(zzd paramzzd)
    throws RemoteException;
  
  public abstract void zzo(zzd paramzzd)
    throws RemoteException;
  
  public abstract void zzp(zzd paramzzd)
    throws RemoteException;
  
  public abstract void zzq(zzd paramzzd)
    throws RemoteException;
  
  public static abstract class zza
    extends Binder
    implements zza
  {
    public boolean onTransact(int paramInt1, Parcel paramParcel1, Parcel paramParcel2, int paramInt2)
      throws RemoteException
    {
      switch (paramInt1)
      {
      default: 
        return super.onTransact(paramInt1, paramParcel1, paramParcel2, paramInt2);
      case 1598968902: 
        paramParcel2.writeString("com.google.android.gms.ads.internal.reward.mediation.client.IMediationRewardedVideoAdListener");
        return true;
      case 1: 
        paramParcel1.enforceInterface("com.google.android.gms.ads.internal.reward.mediation.client.IMediationRewardedVideoAdListener");
        zzk(zzd.zza.zzdb(paramParcel1.readStrongBinder()));
        paramParcel2.writeNoException();
        return true;
      case 2: 
        paramParcel1.enforceInterface("com.google.android.gms.ads.internal.reward.mediation.client.IMediationRewardedVideoAdListener");
        zzb(zzd.zza.zzdb(paramParcel1.readStrongBinder()), paramParcel1.readInt());
        paramParcel2.writeNoException();
        return true;
      case 3: 
        paramParcel1.enforceInterface("com.google.android.gms.ads.internal.reward.mediation.client.IMediationRewardedVideoAdListener");
        zzl(zzd.zza.zzdb(paramParcel1.readStrongBinder()));
        paramParcel2.writeNoException();
        return true;
      case 4: 
        paramParcel1.enforceInterface("com.google.android.gms.ads.internal.reward.mediation.client.IMediationRewardedVideoAdListener");
        zzm(zzd.zza.zzdb(paramParcel1.readStrongBinder()));
        paramParcel2.writeNoException();
        return true;
      case 5: 
        paramParcel1.enforceInterface("com.google.android.gms.ads.internal.reward.mediation.client.IMediationRewardedVideoAdListener");
        zzn(zzd.zza.zzdb(paramParcel1.readStrongBinder()));
        paramParcel2.writeNoException();
        return true;
      case 6: 
        paramParcel1.enforceInterface("com.google.android.gms.ads.internal.reward.mediation.client.IMediationRewardedVideoAdListener");
        zzo(zzd.zza.zzdb(paramParcel1.readStrongBinder()));
        paramParcel2.writeNoException();
        return true;
      case 7: 
        paramParcel1.enforceInterface("com.google.android.gms.ads.internal.reward.mediation.client.IMediationRewardedVideoAdListener");
        zzd localzzd = zzd.zza.zzdb(paramParcel1.readStrongBinder());
        if (paramParcel1.readInt() != 0) {}
        for (RewardItemParcel localRewardItemParcel = zzc.zzp(paramParcel1);; localRewardItemParcel = null)
        {
          zza(localzzd, localRewardItemParcel);
          paramParcel2.writeNoException();
          return true;
        }
      case 8: 
        paramParcel1.enforceInterface("com.google.android.gms.ads.internal.reward.mediation.client.IMediationRewardedVideoAdListener");
        zzp(zzd.zza.zzdb(paramParcel1.readStrongBinder()));
        paramParcel2.writeNoException();
        return true;
      case 9: 
        paramParcel1.enforceInterface("com.google.android.gms.ads.internal.reward.mediation.client.IMediationRewardedVideoAdListener");
        zzc(zzd.zza.zzdb(paramParcel1.readStrongBinder()), paramParcel1.readInt());
        paramParcel2.writeNoException();
        return true;
      }
      paramParcel1.enforceInterface("com.google.android.gms.ads.internal.reward.mediation.client.IMediationRewardedVideoAdListener");
      zzq(zzd.zza.zzdb(paramParcel1.readStrongBinder()));
      paramParcel2.writeNoException();
      return true;
    }
    
    private static final class zza
      implements zza
    {
      private IBinder zzop;
      
      public zza(IBinder paramIBinder)
      {
        this.zzop = paramIBinder;
      }
      
      public final IBinder asBinder()
      {
        return this.zzop;
      }
      
      /* Error */
      public final void zza(zzd paramzzd, RewardItemParcel paramRewardItemParcel)
        throws RemoteException
      {
        // Byte code:
        //   0: invokestatic 27	android/os/Parcel:obtain	()Landroid/os/Parcel;
        //   3: astore_3
        //   4: invokestatic 27	android/os/Parcel:obtain	()Landroid/os/Parcel;
        //   7: astore 4
        //   9: aload_3
        //   10: ldc 29
        //   12: invokevirtual 33	android/os/Parcel:writeInterfaceToken	(Ljava/lang/String;)V
        //   15: aload_1
        //   16: ifnull +63 -> 79
        //   19: aload_1
        //   20: invokeinterface 37 1 0
        //   25: astore 6
        //   27: aload_3
        //   28: aload 6
        //   30: invokevirtual 40	android/os/Parcel:writeStrongBinder	(Landroid/os/IBinder;)V
        //   33: aload_2
        //   34: ifnull +51 -> 85
        //   37: aload_3
        //   38: iconst_1
        //   39: invokevirtual 44	android/os/Parcel:writeInt	(I)V
        //   42: aload_2
        //   43: aload_3
        //   44: iconst_0
        //   45: invokevirtual 50	com/google/android/gms/ads/internal/reward/mediation/client/RewardItemParcel:writeToParcel	(Landroid/os/Parcel;I)V
        //   48: aload_0
        //   49: getfield 15	com/google/android/gms/ads/internal/reward/mediation/client/zza$zza$zza:zzop	Landroid/os/IBinder;
        //   52: bipush 7
        //   54: aload_3
        //   55: aload 4
        //   57: iconst_0
        //   58: invokeinterface 56 5 0
        //   63: pop
        //   64: aload 4
        //   66: invokevirtual 59	android/os/Parcel:readException	()V
        //   69: aload 4
        //   71: invokevirtual 62	android/os/Parcel:recycle	()V
        //   74: aload_3
        //   75: invokevirtual 62	android/os/Parcel:recycle	()V
        //   78: return
        //   79: aconst_null
        //   80: astore 6
        //   82: goto -55 -> 27
        //   85: aload_3
        //   86: iconst_0
        //   87: invokevirtual 44	android/os/Parcel:writeInt	(I)V
        //   90: goto -42 -> 48
        //   93: astore 5
        //   95: aload 4
        //   97: invokevirtual 62	android/os/Parcel:recycle	()V
        //   100: aload_3
        //   101: invokevirtual 62	android/os/Parcel:recycle	()V
        //   104: aload 5
        //   106: athrow
        // Local variable table:
        //   start	length	slot	name	signature
        //   0	107	0	this	zza
        //   0	107	1	paramzzd	zzd
        //   0	107	2	paramRewardItemParcel	RewardItemParcel
        //   3	98	3	localParcel1	Parcel
        //   7	89	4	localParcel2	Parcel
        //   93	12	5	localObject	Object
        //   25	56	6	localIBinder	IBinder
        // Exception table:
        //   from	to	target	type
        //   9	15	93	finally
        //   19	27	93	finally
        //   27	33	93	finally
        //   37	48	93	finally
        //   48	69	93	finally
        //   85	90	93	finally
      }
      
      /* Error */
      public final void zzb(zzd paramzzd, int paramInt)
        throws RemoteException
      {
        // Byte code:
        //   0: invokestatic 27	android/os/Parcel:obtain	()Landroid/os/Parcel;
        //   3: astore_3
        //   4: invokestatic 27	android/os/Parcel:obtain	()Landroid/os/Parcel;
        //   7: astore 4
        //   9: aload_3
        //   10: ldc 29
        //   12: invokevirtual 33	android/os/Parcel:writeInterfaceToken	(Ljava/lang/String;)V
        //   15: aload_1
        //   16: ifnull +52 -> 68
        //   19: aload_1
        //   20: invokeinterface 37 1 0
        //   25: astore 6
        //   27: aload_3
        //   28: aload 6
        //   30: invokevirtual 40	android/os/Parcel:writeStrongBinder	(Landroid/os/IBinder;)V
        //   33: aload_3
        //   34: iload_2
        //   35: invokevirtual 44	android/os/Parcel:writeInt	(I)V
        //   38: aload_0
        //   39: getfield 15	com/google/android/gms/ads/internal/reward/mediation/client/zza$zza$zza:zzop	Landroid/os/IBinder;
        //   42: iconst_2
        //   43: aload_3
        //   44: aload 4
        //   46: iconst_0
        //   47: invokeinterface 56 5 0
        //   52: pop
        //   53: aload 4
        //   55: invokevirtual 59	android/os/Parcel:readException	()V
        //   58: aload 4
        //   60: invokevirtual 62	android/os/Parcel:recycle	()V
        //   63: aload_3
        //   64: invokevirtual 62	android/os/Parcel:recycle	()V
        //   67: return
        //   68: aconst_null
        //   69: astore 6
        //   71: goto -44 -> 27
        //   74: astore 5
        //   76: aload 4
        //   78: invokevirtual 62	android/os/Parcel:recycle	()V
        //   81: aload_3
        //   82: invokevirtual 62	android/os/Parcel:recycle	()V
        //   85: aload 5
        //   87: athrow
        // Local variable table:
        //   start	length	slot	name	signature
        //   0	88	0	this	zza
        //   0	88	1	paramzzd	zzd
        //   0	88	2	paramInt	int
        //   3	79	3	localParcel1	Parcel
        //   7	70	4	localParcel2	Parcel
        //   74	12	5	localObject	Object
        //   25	45	6	localIBinder	IBinder
        // Exception table:
        //   from	to	target	type
        //   9	15	74	finally
        //   19	27	74	finally
        //   27	58	74	finally
      }
      
      /* Error */
      public final void zzc(zzd paramzzd, int paramInt)
        throws RemoteException
      {
        // Byte code:
        //   0: invokestatic 27	android/os/Parcel:obtain	()Landroid/os/Parcel;
        //   3: astore_3
        //   4: invokestatic 27	android/os/Parcel:obtain	()Landroid/os/Parcel;
        //   7: astore 4
        //   9: aload_3
        //   10: ldc 29
        //   12: invokevirtual 33	android/os/Parcel:writeInterfaceToken	(Ljava/lang/String;)V
        //   15: aload_1
        //   16: ifnull +53 -> 69
        //   19: aload_1
        //   20: invokeinterface 37 1 0
        //   25: astore 6
        //   27: aload_3
        //   28: aload 6
        //   30: invokevirtual 40	android/os/Parcel:writeStrongBinder	(Landroid/os/IBinder;)V
        //   33: aload_3
        //   34: iload_2
        //   35: invokevirtual 44	android/os/Parcel:writeInt	(I)V
        //   38: aload_0
        //   39: getfield 15	com/google/android/gms/ads/internal/reward/mediation/client/zza$zza$zza:zzop	Landroid/os/IBinder;
        //   42: bipush 9
        //   44: aload_3
        //   45: aload 4
        //   47: iconst_0
        //   48: invokeinterface 56 5 0
        //   53: pop
        //   54: aload 4
        //   56: invokevirtual 59	android/os/Parcel:readException	()V
        //   59: aload 4
        //   61: invokevirtual 62	android/os/Parcel:recycle	()V
        //   64: aload_3
        //   65: invokevirtual 62	android/os/Parcel:recycle	()V
        //   68: return
        //   69: aconst_null
        //   70: astore 6
        //   72: goto -45 -> 27
        //   75: astore 5
        //   77: aload 4
        //   79: invokevirtual 62	android/os/Parcel:recycle	()V
        //   82: aload_3
        //   83: invokevirtual 62	android/os/Parcel:recycle	()V
        //   86: aload 5
        //   88: athrow
        // Local variable table:
        //   start	length	slot	name	signature
        //   0	89	0	this	zza
        //   0	89	1	paramzzd	zzd
        //   0	89	2	paramInt	int
        //   3	80	3	localParcel1	Parcel
        //   7	71	4	localParcel2	Parcel
        //   75	12	5	localObject	Object
        //   25	46	6	localIBinder	IBinder
        // Exception table:
        //   from	to	target	type
        //   9	15	75	finally
        //   19	27	75	finally
        //   27	59	75	finally
      }
      
      /* Error */
      public final void zzk(zzd paramzzd)
        throws RemoteException
      {
        // Byte code:
        //   0: invokestatic 27	android/os/Parcel:obtain	()Landroid/os/Parcel;
        //   3: astore_2
        //   4: invokestatic 27	android/os/Parcel:obtain	()Landroid/os/Parcel;
        //   7: astore_3
        //   8: aload_2
        //   9: ldc 29
        //   11: invokevirtual 33	android/os/Parcel:writeInterfaceToken	(Ljava/lang/String;)V
        //   14: aload_1
        //   15: ifnull +44 -> 59
        //   18: aload_1
        //   19: invokeinterface 37 1 0
        //   24: astore 5
        //   26: aload_2
        //   27: aload 5
        //   29: invokevirtual 40	android/os/Parcel:writeStrongBinder	(Landroid/os/IBinder;)V
        //   32: aload_0
        //   33: getfield 15	com/google/android/gms/ads/internal/reward/mediation/client/zza$zza$zza:zzop	Landroid/os/IBinder;
        //   36: iconst_1
        //   37: aload_2
        //   38: aload_3
        //   39: iconst_0
        //   40: invokeinterface 56 5 0
        //   45: pop
        //   46: aload_3
        //   47: invokevirtual 59	android/os/Parcel:readException	()V
        //   50: aload_3
        //   51: invokevirtual 62	android/os/Parcel:recycle	()V
        //   54: aload_2
        //   55: invokevirtual 62	android/os/Parcel:recycle	()V
        //   58: return
        //   59: aconst_null
        //   60: astore 5
        //   62: goto -36 -> 26
        //   65: astore 4
        //   67: aload_3
        //   68: invokevirtual 62	android/os/Parcel:recycle	()V
        //   71: aload_2
        //   72: invokevirtual 62	android/os/Parcel:recycle	()V
        //   75: aload 4
        //   77: athrow
        // Local variable table:
        //   start	length	slot	name	signature
        //   0	78	0	this	zza
        //   0	78	1	paramzzd	zzd
        //   3	69	2	localParcel1	Parcel
        //   7	61	3	localParcel2	Parcel
        //   65	11	4	localObject	Object
        //   24	37	5	localIBinder	IBinder
        // Exception table:
        //   from	to	target	type
        //   8	14	65	finally
        //   18	26	65	finally
        //   26	50	65	finally
      }
      
      /* Error */
      public final void zzl(zzd paramzzd)
        throws RemoteException
      {
        // Byte code:
        //   0: invokestatic 27	android/os/Parcel:obtain	()Landroid/os/Parcel;
        //   3: astore_2
        //   4: invokestatic 27	android/os/Parcel:obtain	()Landroid/os/Parcel;
        //   7: astore_3
        //   8: aload_2
        //   9: ldc 29
        //   11: invokevirtual 33	android/os/Parcel:writeInterfaceToken	(Ljava/lang/String;)V
        //   14: aload_1
        //   15: ifnull +44 -> 59
        //   18: aload_1
        //   19: invokeinterface 37 1 0
        //   24: astore 5
        //   26: aload_2
        //   27: aload 5
        //   29: invokevirtual 40	android/os/Parcel:writeStrongBinder	(Landroid/os/IBinder;)V
        //   32: aload_0
        //   33: getfield 15	com/google/android/gms/ads/internal/reward/mediation/client/zza$zza$zza:zzop	Landroid/os/IBinder;
        //   36: iconst_3
        //   37: aload_2
        //   38: aload_3
        //   39: iconst_0
        //   40: invokeinterface 56 5 0
        //   45: pop
        //   46: aload_3
        //   47: invokevirtual 59	android/os/Parcel:readException	()V
        //   50: aload_3
        //   51: invokevirtual 62	android/os/Parcel:recycle	()V
        //   54: aload_2
        //   55: invokevirtual 62	android/os/Parcel:recycle	()V
        //   58: return
        //   59: aconst_null
        //   60: astore 5
        //   62: goto -36 -> 26
        //   65: astore 4
        //   67: aload_3
        //   68: invokevirtual 62	android/os/Parcel:recycle	()V
        //   71: aload_2
        //   72: invokevirtual 62	android/os/Parcel:recycle	()V
        //   75: aload 4
        //   77: athrow
        // Local variable table:
        //   start	length	slot	name	signature
        //   0	78	0	this	zza
        //   0	78	1	paramzzd	zzd
        //   3	69	2	localParcel1	Parcel
        //   7	61	3	localParcel2	Parcel
        //   65	11	4	localObject	Object
        //   24	37	5	localIBinder	IBinder
        // Exception table:
        //   from	to	target	type
        //   8	14	65	finally
        //   18	26	65	finally
        //   26	50	65	finally
      }
      
      /* Error */
      public final void zzm(zzd paramzzd)
        throws RemoteException
      {
        // Byte code:
        //   0: invokestatic 27	android/os/Parcel:obtain	()Landroid/os/Parcel;
        //   3: astore_2
        //   4: invokestatic 27	android/os/Parcel:obtain	()Landroid/os/Parcel;
        //   7: astore_3
        //   8: aload_2
        //   9: ldc 29
        //   11: invokevirtual 33	android/os/Parcel:writeInterfaceToken	(Ljava/lang/String;)V
        //   14: aload_1
        //   15: ifnull +44 -> 59
        //   18: aload_1
        //   19: invokeinterface 37 1 0
        //   24: astore 5
        //   26: aload_2
        //   27: aload 5
        //   29: invokevirtual 40	android/os/Parcel:writeStrongBinder	(Landroid/os/IBinder;)V
        //   32: aload_0
        //   33: getfield 15	com/google/android/gms/ads/internal/reward/mediation/client/zza$zza$zza:zzop	Landroid/os/IBinder;
        //   36: iconst_4
        //   37: aload_2
        //   38: aload_3
        //   39: iconst_0
        //   40: invokeinterface 56 5 0
        //   45: pop
        //   46: aload_3
        //   47: invokevirtual 59	android/os/Parcel:readException	()V
        //   50: aload_3
        //   51: invokevirtual 62	android/os/Parcel:recycle	()V
        //   54: aload_2
        //   55: invokevirtual 62	android/os/Parcel:recycle	()V
        //   58: return
        //   59: aconst_null
        //   60: astore 5
        //   62: goto -36 -> 26
        //   65: astore 4
        //   67: aload_3
        //   68: invokevirtual 62	android/os/Parcel:recycle	()V
        //   71: aload_2
        //   72: invokevirtual 62	android/os/Parcel:recycle	()V
        //   75: aload 4
        //   77: athrow
        // Local variable table:
        //   start	length	slot	name	signature
        //   0	78	0	this	zza
        //   0	78	1	paramzzd	zzd
        //   3	69	2	localParcel1	Parcel
        //   7	61	3	localParcel2	Parcel
        //   65	11	4	localObject	Object
        //   24	37	5	localIBinder	IBinder
        // Exception table:
        //   from	to	target	type
        //   8	14	65	finally
        //   18	26	65	finally
        //   26	50	65	finally
      }
      
      /* Error */
      public final void zzn(zzd paramzzd)
        throws RemoteException
      {
        // Byte code:
        //   0: invokestatic 27	android/os/Parcel:obtain	()Landroid/os/Parcel;
        //   3: astore_2
        //   4: invokestatic 27	android/os/Parcel:obtain	()Landroid/os/Parcel;
        //   7: astore_3
        //   8: aload_2
        //   9: ldc 29
        //   11: invokevirtual 33	android/os/Parcel:writeInterfaceToken	(Ljava/lang/String;)V
        //   14: aload_1
        //   15: ifnull +44 -> 59
        //   18: aload_1
        //   19: invokeinterface 37 1 0
        //   24: astore 5
        //   26: aload_2
        //   27: aload 5
        //   29: invokevirtual 40	android/os/Parcel:writeStrongBinder	(Landroid/os/IBinder;)V
        //   32: aload_0
        //   33: getfield 15	com/google/android/gms/ads/internal/reward/mediation/client/zza$zza$zza:zzop	Landroid/os/IBinder;
        //   36: iconst_5
        //   37: aload_2
        //   38: aload_3
        //   39: iconst_0
        //   40: invokeinterface 56 5 0
        //   45: pop
        //   46: aload_3
        //   47: invokevirtual 59	android/os/Parcel:readException	()V
        //   50: aload_3
        //   51: invokevirtual 62	android/os/Parcel:recycle	()V
        //   54: aload_2
        //   55: invokevirtual 62	android/os/Parcel:recycle	()V
        //   58: return
        //   59: aconst_null
        //   60: astore 5
        //   62: goto -36 -> 26
        //   65: astore 4
        //   67: aload_3
        //   68: invokevirtual 62	android/os/Parcel:recycle	()V
        //   71: aload_2
        //   72: invokevirtual 62	android/os/Parcel:recycle	()V
        //   75: aload 4
        //   77: athrow
        // Local variable table:
        //   start	length	slot	name	signature
        //   0	78	0	this	zza
        //   0	78	1	paramzzd	zzd
        //   3	69	2	localParcel1	Parcel
        //   7	61	3	localParcel2	Parcel
        //   65	11	4	localObject	Object
        //   24	37	5	localIBinder	IBinder
        // Exception table:
        //   from	to	target	type
        //   8	14	65	finally
        //   18	26	65	finally
        //   26	50	65	finally
      }
      
      /* Error */
      public final void zzo(zzd paramzzd)
        throws RemoteException
      {
        // Byte code:
        //   0: invokestatic 27	android/os/Parcel:obtain	()Landroid/os/Parcel;
        //   3: astore_2
        //   4: invokestatic 27	android/os/Parcel:obtain	()Landroid/os/Parcel;
        //   7: astore_3
        //   8: aload_2
        //   9: ldc 29
        //   11: invokevirtual 33	android/os/Parcel:writeInterfaceToken	(Ljava/lang/String;)V
        //   14: aload_1
        //   15: ifnull +45 -> 60
        //   18: aload_1
        //   19: invokeinterface 37 1 0
        //   24: astore 5
        //   26: aload_2
        //   27: aload 5
        //   29: invokevirtual 40	android/os/Parcel:writeStrongBinder	(Landroid/os/IBinder;)V
        //   32: aload_0
        //   33: getfield 15	com/google/android/gms/ads/internal/reward/mediation/client/zza$zza$zza:zzop	Landroid/os/IBinder;
        //   36: bipush 6
        //   38: aload_2
        //   39: aload_3
        //   40: iconst_0
        //   41: invokeinterface 56 5 0
        //   46: pop
        //   47: aload_3
        //   48: invokevirtual 59	android/os/Parcel:readException	()V
        //   51: aload_3
        //   52: invokevirtual 62	android/os/Parcel:recycle	()V
        //   55: aload_2
        //   56: invokevirtual 62	android/os/Parcel:recycle	()V
        //   59: return
        //   60: aconst_null
        //   61: astore 5
        //   63: goto -37 -> 26
        //   66: astore 4
        //   68: aload_3
        //   69: invokevirtual 62	android/os/Parcel:recycle	()V
        //   72: aload_2
        //   73: invokevirtual 62	android/os/Parcel:recycle	()V
        //   76: aload 4
        //   78: athrow
        // Local variable table:
        //   start	length	slot	name	signature
        //   0	79	0	this	zza
        //   0	79	1	paramzzd	zzd
        //   3	70	2	localParcel1	Parcel
        //   7	62	3	localParcel2	Parcel
        //   66	11	4	localObject	Object
        //   24	38	5	localIBinder	IBinder
        // Exception table:
        //   from	to	target	type
        //   8	14	66	finally
        //   18	26	66	finally
        //   26	51	66	finally
      }
      
      /* Error */
      public final void zzp(zzd paramzzd)
        throws RemoteException
      {
        // Byte code:
        //   0: invokestatic 27	android/os/Parcel:obtain	()Landroid/os/Parcel;
        //   3: astore_2
        //   4: invokestatic 27	android/os/Parcel:obtain	()Landroid/os/Parcel;
        //   7: astore_3
        //   8: aload_2
        //   9: ldc 29
        //   11: invokevirtual 33	android/os/Parcel:writeInterfaceToken	(Ljava/lang/String;)V
        //   14: aload_1
        //   15: ifnull +45 -> 60
        //   18: aload_1
        //   19: invokeinterface 37 1 0
        //   24: astore 5
        //   26: aload_2
        //   27: aload 5
        //   29: invokevirtual 40	android/os/Parcel:writeStrongBinder	(Landroid/os/IBinder;)V
        //   32: aload_0
        //   33: getfield 15	com/google/android/gms/ads/internal/reward/mediation/client/zza$zza$zza:zzop	Landroid/os/IBinder;
        //   36: bipush 8
        //   38: aload_2
        //   39: aload_3
        //   40: iconst_0
        //   41: invokeinterface 56 5 0
        //   46: pop
        //   47: aload_3
        //   48: invokevirtual 59	android/os/Parcel:readException	()V
        //   51: aload_3
        //   52: invokevirtual 62	android/os/Parcel:recycle	()V
        //   55: aload_2
        //   56: invokevirtual 62	android/os/Parcel:recycle	()V
        //   59: return
        //   60: aconst_null
        //   61: astore 5
        //   63: goto -37 -> 26
        //   66: astore 4
        //   68: aload_3
        //   69: invokevirtual 62	android/os/Parcel:recycle	()V
        //   72: aload_2
        //   73: invokevirtual 62	android/os/Parcel:recycle	()V
        //   76: aload 4
        //   78: athrow
        // Local variable table:
        //   start	length	slot	name	signature
        //   0	79	0	this	zza
        //   0	79	1	paramzzd	zzd
        //   3	70	2	localParcel1	Parcel
        //   7	62	3	localParcel2	Parcel
        //   66	11	4	localObject	Object
        //   24	38	5	localIBinder	IBinder
        // Exception table:
        //   from	to	target	type
        //   8	14	66	finally
        //   18	26	66	finally
        //   26	51	66	finally
      }
      
      /* Error */
      public final void zzq(zzd paramzzd)
        throws RemoteException
      {
        // Byte code:
        //   0: invokestatic 27	android/os/Parcel:obtain	()Landroid/os/Parcel;
        //   3: astore_2
        //   4: invokestatic 27	android/os/Parcel:obtain	()Landroid/os/Parcel;
        //   7: astore_3
        //   8: aload_2
        //   9: ldc 29
        //   11: invokevirtual 33	android/os/Parcel:writeInterfaceToken	(Ljava/lang/String;)V
        //   14: aload_1
        //   15: ifnull +45 -> 60
        //   18: aload_1
        //   19: invokeinterface 37 1 0
        //   24: astore 5
        //   26: aload_2
        //   27: aload 5
        //   29: invokevirtual 40	android/os/Parcel:writeStrongBinder	(Landroid/os/IBinder;)V
        //   32: aload_0
        //   33: getfield 15	com/google/android/gms/ads/internal/reward/mediation/client/zza$zza$zza:zzop	Landroid/os/IBinder;
        //   36: bipush 10
        //   38: aload_2
        //   39: aload_3
        //   40: iconst_0
        //   41: invokeinterface 56 5 0
        //   46: pop
        //   47: aload_3
        //   48: invokevirtual 59	android/os/Parcel:readException	()V
        //   51: aload_3
        //   52: invokevirtual 62	android/os/Parcel:recycle	()V
        //   55: aload_2
        //   56: invokevirtual 62	android/os/Parcel:recycle	()V
        //   59: return
        //   60: aconst_null
        //   61: astore 5
        //   63: goto -37 -> 26
        //   66: astore 4
        //   68: aload_3
        //   69: invokevirtual 62	android/os/Parcel:recycle	()V
        //   72: aload_2
        //   73: invokevirtual 62	android/os/Parcel:recycle	()V
        //   76: aload 4
        //   78: athrow
        // Local variable table:
        //   start	length	slot	name	signature
        //   0	79	0	this	zza
        //   0	79	1	paramzzd	zzd
        //   3	70	2	localParcel1	Parcel
        //   7	62	3	localParcel2	Parcel
        //   66	11	4	localObject	Object
        //   24	38	5	localIBinder	IBinder
        // Exception table:
        //   from	to	target	type
        //   8	14	66	finally
        //   18	26	66	finally
        //   26	51	66	finally
      }
    }
  }
}


/* Location:           F:\apktool\apktool\Google_Play_Store6.0.5\classes-dex2jar.jar
 * Qualified Name:     com.google.android.gms.ads.internal.reward.mediation.client.zza
 * JD-Core Version:    0.7.0.1
 */