package com.google.android.gms.people.internal;

import android.net.Uri;
import android.os.Binder;
import android.os.Bundle;
import android.os.IBinder;
import android.os.IInterface;
import android.os.Parcel;
import android.os.Parcelable.Creator;
import android.os.RemoteException;
import com.google.android.gms.common.data.DataHolder;
import com.google.android.gms.common.data.DataHolderCreator;
import com.google.android.gms.common.internal.zzq;
import com.google.android.gms.common.internal.zzq.zza;
import com.google.android.gms.common.server.FavaDiagnosticsEntity;
import com.google.android.gms.people.identity.internal.AccountToken;
import com.google.android.gms.people.identity.internal.ParcelableGetOptions;
import com.google.android.gms.people.identity.internal.ParcelableListOptions;
import com.google.android.gms.people.identity.internal.zzi;
import com.google.android.gms.people.identity.internal.zzj;
import com.google.android.gms.people.model.AvatarReference;
import com.google.android.gms.people.model.ParcelableAvatarReference;
import java.util.ArrayList;
import java.util.List;

public abstract interface zzg
  extends IInterface
{
  public abstract boolean isSyncToContactsEnabled()
    throws RemoteException;
  
  public abstract Bundle zza(zzf paramzzf, boolean paramBoolean, String paramString1, String paramString2, int paramInt)
    throws RemoteException;
  
  public abstract Bundle zza(String paramString1, String paramString2, long paramLong, boolean paramBoolean)
    throws RemoteException;
  
  public abstract Bundle zza(String paramString1, String paramString2, long paramLong, boolean paramBoolean1, boolean paramBoolean2)
    throws RemoteException;
  
  public abstract zzq zza(zzf paramzzf, DataHolder paramDataHolder, int paramInt1, int paramInt2, long paramLong)
    throws RemoteException;
  
  public abstract zzq zza(zzf paramzzf, AccountToken paramAccountToken, ParcelableListOptions paramParcelableListOptions)
    throws RemoteException;
  
  public abstract zzq zza(zzf paramzzf, AvatarReference paramAvatarReference, ParcelableLoadImageOptions paramParcelableLoadImageOptions)
    throws RemoteException;
  
  public abstract zzq zza(zzf paramzzf, String paramString, int paramInt)
    throws RemoteException;
  
  public abstract zzq zza(zzf paramzzf, String paramString1, String paramString2, Bundle paramBundle)
    throws RemoteException;
  
  public abstract zzq zza(zzf paramzzf, String paramString1, String paramString2, boolean paramBoolean1, String paramString3, String paramString4, int paramInt1, int paramInt2, int paramInt3, boolean paramBoolean2)
    throws RemoteException;
  
  public abstract void zza(zzf paramzzf, long paramLong, boolean paramBoolean)
    throws RemoteException;
  
  public abstract void zza(zzf paramzzf, Bundle paramBundle)
    throws RemoteException;
  
  public abstract void zza(zzf paramzzf, AccountToken paramAccountToken, List<String> paramList, ParcelableGetOptions paramParcelableGetOptions)
    throws RemoteException;
  
  public abstract void zza(zzf paramzzf, String paramString)
    throws RemoteException;
  
  public abstract void zza(zzf paramzzf, String paramString, int paramInt1, int paramInt2)
    throws RemoteException;
  
  public abstract void zza(zzf paramzzf, String paramString1, String paramString2)
    throws RemoteException;
  
  public abstract void zza(zzf paramzzf, String paramString1, String paramString2, int paramInt)
    throws RemoteException;
  
  public abstract void zza(zzf paramzzf, String paramString1, String paramString2, int paramInt1, int paramInt2)
    throws RemoteException;
  
  public abstract void zza(zzf paramzzf, String paramString1, String paramString2, Uri paramUri)
    throws RemoteException;
  
  public abstract void zza(zzf paramzzf, String paramString1, String paramString2, Uri paramUri, boolean paramBoolean)
    throws RemoteException;
  
  public abstract void zza(zzf paramzzf, String paramString1, String paramString2, String paramString3)
    throws RemoteException;
  
  public abstract void zza(zzf paramzzf, String paramString1, String paramString2, String paramString3, int paramInt, String paramString4)
    throws RemoteException;
  
  public abstract void zza(zzf paramzzf, String paramString1, String paramString2, String paramString3, int paramInt, String paramString4, boolean paramBoolean)
    throws RemoteException;
  
  public abstract void zza(zzf paramzzf, String paramString1, String paramString2, String paramString3, int paramInt1, boolean paramBoolean, int paramInt2, int paramInt3, String paramString4)
    throws RemoteException;
  
  public abstract void zza(zzf paramzzf, String paramString1, String paramString2, String paramString3, int paramInt1, boolean paramBoolean1, int paramInt2, int paramInt3, String paramString4, boolean paramBoolean2)
    throws RemoteException;
  
  public abstract void zza(zzf paramzzf, String paramString1, String paramString2, String paramString3, int paramInt1, boolean paramBoolean1, int paramInt2, int paramInt3, String paramString4, boolean paramBoolean2, int paramInt4, int paramInt5)
    throws RemoteException;
  
  public abstract void zza(zzf paramzzf, String paramString1, String paramString2, String paramString3, String paramString4)
    throws RemoteException;
  
  public abstract void zza(zzf paramzzf, String paramString1, String paramString2, String paramString3, String paramString4, int paramInt, String paramString5)
    throws RemoteException;
  
  public abstract void zza(zzf paramzzf, String paramString1, String paramString2, String paramString3, String paramString4, boolean paramBoolean)
    throws RemoteException;
  
  public abstract void zza(zzf paramzzf, String paramString1, String paramString2, String paramString3, List<String> paramList)
    throws RemoteException;
  
  public abstract void zza(zzf paramzzf, String paramString1, String paramString2, String paramString3, List<String> paramList, int paramInt, boolean paramBoolean, long paramLong)
    throws RemoteException;
  
  public abstract void zza(zzf paramzzf, String paramString1, String paramString2, String paramString3, List<String> paramList, int paramInt1, boolean paramBoolean, long paramLong, String paramString4, int paramInt2)
    throws RemoteException;
  
  public abstract void zza(zzf paramzzf, String paramString1, String paramString2, String paramString3, List<String> paramList, int paramInt1, boolean paramBoolean, long paramLong, String paramString4, int paramInt2, int paramInt3)
    throws RemoteException;
  
  public abstract void zza(zzf paramzzf, String paramString1, String paramString2, String paramString3, List<String> paramList, int paramInt1, boolean paramBoolean, long paramLong, String paramString4, int paramInt2, int paramInt3, int paramInt4)
    throws RemoteException;
  
  public abstract void zza(zzf paramzzf, String paramString1, String paramString2, String paramString3, List<String> paramList1, List<String> paramList2)
    throws RemoteException;
  
  public abstract void zza(zzf paramzzf, String paramString1, String paramString2, String paramString3, List<String> paramList1, List<String> paramList2, FavaDiagnosticsEntity paramFavaDiagnosticsEntity)
    throws RemoteException;
  
  public abstract void zza(zzf paramzzf, String paramString1, String paramString2, String paramString3, boolean paramBoolean)
    throws RemoteException;
  
  public abstract void zza(zzf paramzzf, String paramString1, String paramString2, String paramString3, boolean paramBoolean, int paramInt)
    throws RemoteException;
  
  public abstract void zza(zzf paramzzf, String paramString1, String paramString2, String paramString3, boolean paramBoolean, int paramInt1, int paramInt2)
    throws RemoteException;
  
  public abstract void zza(zzf paramzzf, String paramString, boolean paramBoolean, String[] paramArrayOfString)
    throws RemoteException;
  
  public abstract void zza(zzf paramzzf, boolean paramBoolean1, boolean paramBoolean2, String paramString1, String paramString2)
    throws RemoteException;
  
  public abstract void zza(zzf paramzzf, boolean paramBoolean1, boolean paramBoolean2, String paramString1, String paramString2, int paramInt)
    throws RemoteException;
  
  public abstract void zzaQ(boolean paramBoolean)
    throws RemoteException;
  
  public abstract Bundle zzac(String paramString1, String paramString2)
    throws RemoteException;
  
  public abstract Bundle zzad(String paramString1, String paramString2)
    throws RemoteException;
  
  public abstract zzq zzb(zzf paramzzf, long paramLong, boolean paramBoolean)
    throws RemoteException;
  
  public abstract zzq zzb(zzf paramzzf, String paramString)
    throws RemoteException;
  
  public abstract zzq zzb(zzf paramzzf, String paramString, int paramInt1, int paramInt2)
    throws RemoteException;
  
  public abstract zzq zzb(zzf paramzzf, String paramString1, String paramString2, int paramInt1, int paramInt2)
    throws RemoteException;
  
  public abstract void zzb(zzf paramzzf, Bundle paramBundle)
    throws RemoteException;
  
  public abstract void zzb(zzf paramzzf, String paramString1, String paramString2)
    throws RemoteException;
  
  public abstract void zzb(zzf paramzzf, String paramString1, String paramString2, int paramInt)
    throws RemoteException;
  
  public abstract void zzb(zzf paramzzf, String paramString1, String paramString2, String paramString3, int paramInt, String paramString4)
    throws RemoteException;
  
  public abstract void zzb(zzf paramzzf, String paramString1, String paramString2, String paramString3, boolean paramBoolean)
    throws RemoteException;
  
  public abstract Bundle zzc(String paramString1, String paramString2, long paramLong)
    throws RemoteException;
  
  public abstract zzq zzc(zzf paramzzf, String paramString1, String paramString2, int paramInt)
    throws RemoteException;
  
  public abstract void zzc(zzf paramzzf, String paramString1, String paramString2)
    throws RemoteException;
  
  public abstract Bundle zzp(Uri paramUri)
    throws RemoteException;
  
  public static abstract class zza
    extends Binder
    implements zzg
  {
    public static zzg zzfT(IBinder paramIBinder)
    {
      if (paramIBinder == null) {
        return null;
      }
      IInterface localIInterface = paramIBinder.queryLocalInterface("com.google.android.gms.people.internal.IPeopleService");
      if ((localIInterface != null) && ((localIInterface instanceof zzg))) {
        return (zzg)localIInterface;
      }
      return new zza(paramIBinder);
    }
    
    public boolean onTransact(int paramInt1, Parcel paramParcel1, Parcel paramParcel2, int paramInt2)
      throws RemoteException
    {
      switch (paramInt1)
      {
      default: 
        return super.onTransact(paramInt1, paramParcel1, paramParcel2, paramInt2);
      case 1598968902: 
        paramParcel2.writeString("com.google.android.gms.people.internal.IPeopleService");
        return true;
      case 2: 
        paramParcel1.enforceInterface("com.google.android.gms.people.internal.IPeopleService");
        zzf localzzf30 = zzf.zza.zzfS(paramParcel1.readStrongBinder());
        boolean bool30;
        if (paramParcel1.readInt() != 0)
        {
          bool30 = true;
          if (paramParcel1.readInt() == 0) {
            break label567;
          }
        }
        for (boolean bool31 = true;; bool31 = false)
        {
          zza(localzzf30, bool30, bool31, paramParcel1.readString(), paramParcel1.readString());
          paramParcel2.writeNoException();
          return true;
          bool30 = false;
          break;
        }
      case 305: 
        paramParcel1.enforceInterface("com.google.android.gms.people.internal.IPeopleService");
        zzf localzzf29 = zzf.zza.zzfS(paramParcel1.readStrongBinder());
        boolean bool28;
        if (paramParcel1.readInt() != 0)
        {
          bool28 = true;
          if (paramParcel1.readInt() == 0) {
            break label642;
          }
        }
        for (boolean bool29 = true;; bool29 = false)
        {
          zza(localzzf29, bool28, bool29, paramParcel1.readString(), paramParcel1.readString(), paramParcel1.readInt());
          paramParcel2.writeNoException();
          return true;
          bool28 = false;
          break;
        }
      case 3: 
        paramParcel1.enforceInterface("com.google.android.gms.people.internal.IPeopleService");
        zza(zzf.zza.zzfS(paramParcel1.readStrongBinder()), paramParcel1.readString(), paramParcel1.readString(), paramParcel1.readString(), paramParcel1.readInt(), paramParcel1.readString());
        paramParcel2.writeNoException();
        return true;
      case 4: 
        paramParcel1.enforceInterface("com.google.android.gms.people.internal.IPeopleService");
        zzf localzzf28 = zzf.zza.zzfS(paramParcel1.readStrongBinder());
        String str59 = paramParcel1.readString();
        String str60 = paramParcel1.readString();
        String str61 = paramParcel1.readString();
        ArrayList localArrayList7 = paramParcel1.createStringArrayList();
        int i11 = paramParcel1.readInt();
        if (paramParcel1.readInt() != 0) {}
        for (boolean bool27 = true;; bool27 = false)
        {
          zza(localzzf28, str59, str60, str61, localArrayList7, i11, bool27, paramParcel1.readLong());
          paramParcel2.writeNoException();
          return true;
        }
      case 5: 
        paramParcel1.enforceInterface("com.google.android.gms.people.internal.IPeopleService");
        zza(zzf.zza.zzfS(paramParcel1.readStrongBinder()), paramParcel1.readString(), paramParcel1.readInt(), paramParcel1.readInt());
        paramParcel2.writeNoException();
        return true;
      case 6: 
        paramParcel1.enforceInterface("com.google.android.gms.people.internal.IPeopleService");
        zzf localzzf27 = zzf.zza.zzfS(paramParcel1.readStrongBinder());
        long l4 = paramParcel1.readLong();
        if (paramParcel1.readInt() != 0) {}
        for (boolean bool26 = true;; bool26 = false)
        {
          zza(localzzf27, l4, bool26);
          paramParcel2.writeNoException();
          return true;
        }
      case 7: 
        paramParcel1.enforceInterface("com.google.android.gms.people.internal.IPeopleService");
        zzf localzzf26 = zzf.zza.zzfS(paramParcel1.readStrongBinder());
        String str56 = paramParcel1.readString();
        String str57 = paramParcel1.readString();
        String str58 = paramParcel1.readString();
        if (paramParcel1.readInt() != 0) {}
        for (boolean bool25 = true;; bool25 = false)
        {
          zza(localzzf26, str56, str57, str58, bool25);
          paramParcel2.writeNoException();
          return true;
        }
      case 603: 
        paramParcel1.enforceInterface("com.google.android.gms.people.internal.IPeopleService");
        zzf localzzf25 = zzf.zza.zzfS(paramParcel1.readStrongBinder());
        String str53 = paramParcel1.readString();
        String str54 = paramParcel1.readString();
        String str55 = paramParcel1.readString();
        if (paramParcel1.readInt() != 0) {}
        for (boolean bool24 = true;; bool24 = false)
        {
          zzb(localzzf25, str53, str54, str55, bool24);
          paramParcel2.writeNoException();
          return true;
        }
      case 8: 
        paramParcel1.enforceInterface("com.google.android.gms.people.internal.IPeopleService");
        Uri localUri3;
        if (paramParcel1.readInt() != 0)
        {
          localUri3 = (Uri)Uri.CREATOR.createFromParcel(paramParcel1);
          Bundle localBundle10 = zzp(localUri3);
          paramParcel2.writeNoException();
          if (localBundle10 == null) {
            break label1070;
          }
          paramParcel2.writeInt(1);
          localBundle10.writeToParcel(paramParcel2, 1);
        }
        for (;;)
        {
          return true;
          localUri3 = null;
          break;
          paramParcel2.writeInt(0);
        }
      case 9: 
        paramParcel1.enforceInterface("com.google.android.gms.people.internal.IPeopleService");
        zzf localzzf24 = zzf.zza.zzfS(paramParcel1.readStrongBinder());
        String str50 = paramParcel1.readString();
        String str51 = paramParcel1.readString();
        String str52 = paramParcel1.readString();
        if (paramParcel1.readInt() != 0) {}
        for (boolean bool23 = true;; bool23 = false)
        {
          zza(localzzf24, str50, str51, str52, bool23, paramParcel1.readInt());
          paramParcel2.writeNoException();
          return true;
        }
      case 201: 
        paramParcel1.enforceInterface("com.google.android.gms.people.internal.IPeopleService");
        zzf localzzf23 = zzf.zza.zzfS(paramParcel1.readStrongBinder());
        String str47 = paramParcel1.readString();
        String str48 = paramParcel1.readString();
        String str49 = paramParcel1.readString();
        if (paramParcel1.readInt() != 0) {}
        for (boolean bool22 = true;; bool22 = false)
        {
          zza(localzzf23, str47, str48, str49, bool22, paramParcel1.readInt(), paramParcel1.readInt());
          paramParcel2.writeNoException();
          return true;
        }
      case 202: 
        paramParcel1.enforceInterface("com.google.android.gms.people.internal.IPeopleService");
        zzf localzzf22 = zzf.zza.zzfS(paramParcel1.readStrongBinder());
        String str44 = paramParcel1.readString();
        String str45 = paramParcel1.readString();
        String str46 = paramParcel1.readString();
        int i10 = paramParcel1.readInt();
        if (paramParcel1.readInt() != 0) {}
        for (boolean bool21 = true;; bool21 = false)
        {
          zza(localzzf22, str44, str45, str46, i10, bool21, paramParcel1.readInt(), paramParcel1.readInt(), paramParcel1.readString());
          paramParcel2.writeNoException();
          return true;
        }
      case 203: 
        paramParcel1.enforceInterface("com.google.android.gms.people.internal.IPeopleService");
        zzf localzzf21 = zzf.zza.zzfS(paramParcel1.readStrongBinder());
        String str40 = paramParcel1.readString();
        String str41 = paramParcel1.readString();
        String str42 = paramParcel1.readString();
        int i7 = paramParcel1.readInt();
        boolean bool19;
        int i8;
        int i9;
        String str43;
        if (paramParcel1.readInt() != 0)
        {
          bool19 = true;
          i8 = paramParcel1.readInt();
          i9 = paramParcel1.readInt();
          str43 = paramParcel1.readString();
          if (paramParcel1.readInt() == 0) {
            break label1430;
          }
        }
        for (boolean bool20 = true;; bool20 = false)
        {
          zza(localzzf21, str40, str41, str42, i7, bool19, i8, i9, str43, bool20);
          paramParcel2.writeNoException();
          return true;
          bool19 = false;
          break;
        }
      case 402: 
        paramParcel1.enforceInterface("com.google.android.gms.people.internal.IPeopleService");
        zzf localzzf20 = zzf.zza.zzfS(paramParcel1.readStrongBinder());
        String str36 = paramParcel1.readString();
        String str37 = paramParcel1.readString();
        String str38 = paramParcel1.readString();
        int i4 = paramParcel1.readInt();
        boolean bool17;
        int i5;
        int i6;
        String str39;
        if (paramParcel1.readInt() != 0)
        {
          bool17 = true;
          i5 = paramParcel1.readInt();
          i6 = paramParcel1.readInt();
          str39 = paramParcel1.readString();
          if (paramParcel1.readInt() == 0) {
            break label1557;
          }
        }
        for (boolean bool18 = true;; bool18 = false)
        {
          zza(localzzf20, str36, str37, str38, i4, bool17, i5, i6, str39, bool18, paramParcel1.readInt(), paramParcel1.readInt());
          paramParcel2.writeNoException();
          return true;
          bool17 = false;
          break;
        }
      case 10: 
        paramParcel1.enforceInterface("com.google.android.gms.people.internal.IPeopleService");
        zzf localzzf19 = zzf.zza.zzfS(paramParcel1.readStrongBinder());
        String str35 = paramParcel1.readString();
        if (paramParcel1.readInt() != 0) {}
        for (boolean bool16 = true;; bool16 = false)
        {
          zza(localzzf19, str35, bool16, paramParcel1.createStringArray());
          paramParcel2.writeNoException();
          return true;
        }
      case 11: 
        paramParcel1.enforceInterface("com.google.android.gms.people.internal.IPeopleService");
        zzf localzzf18 = zzf.zza.zzfS(paramParcel1.readStrongBinder());
        boolean bool15;
        if (paramParcel1.readInt() != 0)
        {
          bool15 = true;
          Bundle localBundle9 = zza(localzzf18, bool15, paramParcel1.readString(), paramParcel1.readString(), paramParcel1.readInt());
          paramParcel2.writeNoException();
          if (localBundle9 == null) {
            break label1696;
          }
          paramParcel2.writeInt(1);
          localBundle9.writeToParcel(paramParcel2, 1);
        }
        for (;;)
        {
          return true;
          bool15 = false;
          break;
          paramParcel2.writeInt(0);
        }
      case 12: 
        paramParcel1.enforceInterface("com.google.android.gms.people.internal.IPeopleService");
        Bundle localBundle8 = zzac(paramParcel1.readString(), paramParcel1.readString());
        paramParcel2.writeNoException();
        if (localBundle8 != null)
        {
          paramParcel2.writeInt(1);
          localBundle8.writeToParcel(paramParcel2, 1);
        }
        for (;;)
        {
          return true;
          paramParcel2.writeInt(0);
        }
      case 13: 
        paramParcel1.enforceInterface("com.google.android.gms.people.internal.IPeopleService");
        zzf localzzf17 = zzf.zza.zzfS(paramParcel1.readStrongBinder());
        String str33 = paramParcel1.readString();
        String str34 = paramParcel1.readString();
        if (paramParcel1.readInt() != 0) {}
        for (Uri localUri2 = (Uri)Uri.CREATOR.createFromParcel(paramParcel1);; localUri2 = null)
        {
          zza(localzzf17, str33, str34, localUri2);
          paramParcel2.writeNoException();
          return true;
        }
      case 14: 
        paramParcel1.enforceInterface("com.google.android.gms.people.internal.IPeopleService");
        zza(zzf.zza.zzfS(paramParcel1.readStrongBinder()), paramParcel1.readString(), paramParcel1.readString(), paramParcel1.readString(), paramParcel1.createStringArrayList(), paramParcel1.createStringArrayList());
        paramParcel2.writeNoException();
        return true;
      case 15: 
        paramParcel1.enforceInterface("com.google.android.gms.people.internal.IPeopleService");
        if (paramParcel1.readInt() != 0) {}
        for (boolean bool14 = true;; bool14 = false)
        {
          zzaQ(bool14);
          paramParcel2.writeNoException();
          return true;
        }
      case 16: 
        paramParcel1.enforceInterface("com.google.android.gms.people.internal.IPeopleService");
        boolean bool13 = isSyncToContactsEnabled();
        paramParcel2.writeNoException();
        if (bool13) {}
        for (int i3 = 1;; i3 = 0)
        {
          paramParcel2.writeInt(i3);
          return true;
        }
      case 17: 
        paramParcel1.enforceInterface("com.google.android.gms.people.internal.IPeopleService");
        Bundle localBundle7 = zzad(paramParcel1.readString(), paramParcel1.readString());
        paramParcel2.writeNoException();
        if (localBundle7 != null)
        {
          paramParcel2.writeInt(1);
          localBundle7.writeToParcel(paramParcel2, 1);
        }
        for (;;)
        {
          return true;
          paramParcel2.writeInt(0);
        }
      case 18: 
        paramParcel1.enforceInterface("com.google.android.gms.people.internal.IPeopleService");
        zzf localzzf16 = zzf.zza.zzfS(paramParcel1.readStrongBinder());
        String str31 = paramParcel1.readString();
        String str32 = paramParcel1.readString();
        Uri localUri1;
        if (paramParcel1.readInt() != 0)
        {
          localUri1 = (Uri)Uri.CREATOR.createFromParcel(paramParcel1);
          if (paramParcel1.readInt() == 0) {
            break label2077;
          }
        }
        for (boolean bool12 = true;; bool12 = false)
        {
          zza(localzzf16, str31, str32, localUri1, bool12);
          paramParcel2.writeNoException();
          return true;
          localUri1 = null;
          break;
        }
      case 19: 
        paramParcel1.enforceInterface("com.google.android.gms.people.internal.IPeopleService");
        zzf localzzf15 = zzf.zza.zzfS(paramParcel1.readStrongBinder());
        String str27 = paramParcel1.readString();
        String str28 = paramParcel1.readString();
        String str29 = paramParcel1.readString();
        int i2 = paramParcel1.readInt();
        String str30 = paramParcel1.readString();
        if (paramParcel1.readInt() != 0) {}
        for (boolean bool11 = true;; bool11 = false)
        {
          zza(localzzf15, str27, str28, str29, i2, str30, bool11);
          paramParcel2.writeNoException();
          return true;
        }
      case 20: 
        paramParcel1.enforceInterface("com.google.android.gms.people.internal.IPeopleService");
        Bundle localBundle6 = zzc(paramParcel1.readString(), paramParcel1.readString(), paramParcel1.readLong());
        paramParcel2.writeNoException();
        if (localBundle6 != null)
        {
          paramParcel2.writeInt(1);
          localBundle6.writeToParcel(paramParcel2, 1);
        }
        for (;;)
        {
          return true;
          paramParcel2.writeInt(0);
        }
      case 21: 
        paramParcel1.enforceInterface("com.google.android.gms.people.internal.IPeopleService");
        zzf localzzf14 = zzf.zza.zzfS(paramParcel1.readStrongBinder());
        String str24 = paramParcel1.readString();
        String str25 = paramParcel1.readString();
        String str26 = paramParcel1.readString();
        ArrayList localArrayList6 = paramParcel1.createStringArrayList();
        int i1 = paramParcel1.readInt();
        if (paramParcel1.readInt() != 0) {}
        for (boolean bool10 = true;; bool10 = false)
        {
          zza(localzzf14, str24, str25, str26, localArrayList6, i1, bool10, paramParcel1.readLong(), paramParcel1.readString(), paramParcel1.readInt());
          paramParcel2.writeNoException();
          return true;
        }
      case 401: 
        paramParcel1.enforceInterface("com.google.android.gms.people.internal.IPeopleService");
        zzf localzzf13 = zzf.zza.zzfS(paramParcel1.readStrongBinder());
        String str21 = paramParcel1.readString();
        String str22 = paramParcel1.readString();
        String str23 = paramParcel1.readString();
        ArrayList localArrayList5 = paramParcel1.createStringArrayList();
        int n = paramParcel1.readInt();
        if (paramParcel1.readInt() != 0) {}
        for (boolean bool9 = true;; bool9 = false)
        {
          zza(localzzf13, str21, str22, str23, localArrayList5, n, bool9, paramParcel1.readLong(), paramParcel1.readString(), paramParcel1.readInt(), paramParcel1.readInt());
          paramParcel2.writeNoException();
          return true;
        }
      case 404: 
        paramParcel1.enforceInterface("com.google.android.gms.people.internal.IPeopleService");
        zzf localzzf12 = zzf.zza.zzfS(paramParcel1.readStrongBinder());
        String str18 = paramParcel1.readString();
        String str19 = paramParcel1.readString();
        String str20 = paramParcel1.readString();
        ArrayList localArrayList4 = paramParcel1.createStringArrayList();
        int m = paramParcel1.readInt();
        if (paramParcel1.readInt() != 0) {}
        for (boolean bool8 = true;; bool8 = false)
        {
          zza(localzzf12, str18, str19, str20, localArrayList4, m, bool8, paramParcel1.readLong(), paramParcel1.readString(), paramParcel1.readInt(), paramParcel1.readInt(), paramParcel1.readInt());
          paramParcel2.writeNoException();
          return true;
        }
      case 22: 
        paramParcel1.enforceInterface("com.google.android.gms.people.internal.IPeopleService");
        zzb(zzf.zza.zzfS(paramParcel1.readStrongBinder()), paramParcel1.readString(), paramParcel1.readString(), paramParcel1.readString(), paramParcel1.readInt(), paramParcel1.readString());
        paramParcel2.writeNoException();
        return true;
      case 23: 
        paramParcel1.enforceInterface("com.google.android.gms.people.internal.IPeopleService");
        zzf localzzf11 = zzf.zza.zzfS(paramParcel1.readStrongBinder());
        String str15 = paramParcel1.readString();
        String str16 = paramParcel1.readString();
        String str17 = paramParcel1.readString();
        ArrayList localArrayList2 = paramParcel1.createStringArrayList();
        ArrayList localArrayList3 = paramParcel1.createStringArrayList();
        if (paramParcel1.readInt() != 0) {}
        for (FavaDiagnosticsEntity localFavaDiagnosticsEntity = com.google.android.gms.common.server.zza.zzbe(paramParcel1);; localFavaDiagnosticsEntity = null)
        {
          zza(localzzf11, str15, str16, str17, localArrayList2, localArrayList3, localFavaDiagnosticsEntity);
          paramParcel2.writeNoException();
          return true;
        }
      case 24: 
        paramParcel1.enforceInterface("com.google.android.gms.people.internal.IPeopleService");
        zza(zzf.zza.zzfS(paramParcel1.readStrongBinder()), paramParcel1.readString());
        paramParcel2.writeNoException();
        return true;
      case 25: 
        paramParcel1.enforceInterface("com.google.android.gms.people.internal.IPeopleService");
        zza(zzf.zza.zzfS(paramParcel1.readStrongBinder()), paramParcel1.readString(), paramParcel1.readString());
        paramParcel2.writeNoException();
        return true;
      case 403: 
        paramParcel1.enforceInterface("com.google.android.gms.people.internal.IPeopleService");
        zza(zzf.zza.zzfS(paramParcel1.readStrongBinder()), paramParcel1.readString(), paramParcel1.readString(), paramParcel1.readInt());
        paramParcel2.writeNoException();
        return true;
      case 26: 
        paramParcel1.enforceInterface("com.google.android.gms.people.internal.IPeopleService");
        String str13 = paramParcel1.readString();
        String str14 = paramParcel1.readString();
        long l3 = paramParcel1.readLong();
        boolean bool7;
        if (paramParcel1.readInt() != 0)
        {
          bool7 = true;
          Bundle localBundle5 = zza(str13, str14, l3, bool7);
          paramParcel2.writeNoException();
          if (localBundle5 == null) {
            break label2831;
          }
          paramParcel2.writeInt(1);
          localBundle5.writeToParcel(paramParcel2, 1);
        }
        for (;;)
        {
          return true;
          bool7 = false;
          break;
          paramParcel2.writeInt(0);
        }
      case 205: 
        paramParcel1.enforceInterface("com.google.android.gms.people.internal.IPeopleService");
        String str11 = paramParcel1.readString();
        String str12 = paramParcel1.readString();
        long l2 = paramParcel1.readLong();
        boolean bool5;
        boolean bool6;
        if (paramParcel1.readInt() != 0)
        {
          bool5 = true;
          if (paramParcel1.readInt() == 0) {
            break label2928;
          }
          bool6 = true;
          Bundle localBundle4 = zza(str11, str12, l2, bool5, bool6);
          paramParcel2.writeNoException();
          if (localBundle4 == null) {
            break label2934;
          }
          paramParcel2.writeInt(1);
          localBundle4.writeToParcel(paramParcel2, 1);
        }
        for (;;)
        {
          return true;
          bool5 = false;
          break;
          bool6 = false;
          break label2883;
          paramParcel2.writeInt(0);
        }
      case 101: 
        paramParcel1.enforceInterface("com.google.android.gms.people.internal.IPeopleService");
        zzb(zzf.zza.zzfS(paramParcel1.readStrongBinder()), paramParcel1.readString(), paramParcel1.readString());
        paramParcel2.writeNoException();
        return true;
      case 102: 
        paramParcel1.enforceInterface("com.google.android.gms.people.internal.IPeopleService");
        zzc(zzf.zza.zzfS(paramParcel1.readStrongBinder()), paramParcel1.readString(), paramParcel1.readString());
        paramParcel2.writeNoException();
        return true;
      case 27: 
        paramParcel1.enforceInterface("com.google.android.gms.people.internal.IPeopleService");
        zza(zzf.zza.zzfS(paramParcel1.readStrongBinder()), paramParcel1.readString(), paramParcel1.readString(), paramParcel1.readString(), paramParcel1.readString());
        paramParcel2.writeNoException();
        return true;
      case 701: 
        paramParcel1.enforceInterface("com.google.android.gms.people.internal.IPeopleService");
        zzf localzzf10 = zzf.zza.zzfS(paramParcel1.readStrongBinder());
        String str7 = paramParcel1.readString();
        String str8 = paramParcel1.readString();
        String str9 = paramParcel1.readString();
        String str10 = paramParcel1.readString();
        if (paramParcel1.readInt() != 0) {}
        for (boolean bool4 = true;; bool4 = false)
        {
          zza(localzzf10, str7, str8, str9, str10, bool4);
          paramParcel2.writeNoException();
          return true;
        }
      case 28: 
        paramParcel1.enforceInterface("com.google.android.gms.people.internal.IPeopleService");
        zza(zzf.zza.zzfS(paramParcel1.readStrongBinder()), paramParcel1.readString(), paramParcel1.readString(), paramParcel1.readString(), paramParcel1.createStringArrayList());
        paramParcel2.writeNoException();
        return true;
      case 29: 
        paramParcel1.enforceInterface("com.google.android.gms.people.internal.IPeopleService");
        zza(zzf.zza.zzfS(paramParcel1.readStrongBinder()), paramParcel1.readString(), paramParcel1.readString(), paramParcel1.readInt(), paramParcel1.readInt());
        paramParcel2.writeNoException();
        return true;
      case 204: 
        paramParcel1.enforceInterface("com.google.android.gms.people.internal.IPeopleService");
        zza(zzf.zza.zzfS(paramParcel1.readStrongBinder()), paramParcel1.readString(), paramParcel1.readString(), paramParcel1.readString());
        paramParcel2.writeNoException();
        return true;
      case 301: 
        paramParcel1.enforceInterface("com.google.android.gms.people.internal.IPeopleService");
        zzb(zzf.zza.zzfS(paramParcel1.readStrongBinder()), paramParcel1.readString(), paramParcel1.readString(), paramParcel1.readInt());
        paramParcel2.writeNoException();
        return true;
      case 302: 
        paramParcel1.enforceInterface("com.google.android.gms.people.internal.IPeopleService");
        zzf localzzf9 = zzf.zza.zzfS(paramParcel1.readStrongBinder());
        if (paramParcel1.readInt() != 0) {}
        for (Bundle localBundle3 = (Bundle)Bundle.CREATOR.createFromParcel(paramParcel1);; localBundle3 = null)
        {
          zza(localzzf9, localBundle3);
          paramParcel2.writeNoException();
          return true;
        }
      case 303: 
        paramParcel1.enforceInterface("com.google.android.gms.people.internal.IPeopleService");
        zza(zzf.zza.zzfS(paramParcel1.readStrongBinder()), paramParcel1.readString(), paramParcel1.readString(), paramParcel1.readString(), paramParcel1.readString(), paramParcel1.readInt(), paramParcel1.readString());
        paramParcel2.writeNoException();
        return true;
      case 304: 
        paramParcel1.enforceInterface("com.google.android.gms.people.internal.IPeopleService");
        zzf localzzf8 = zzf.zza.zzfS(paramParcel1.readStrongBinder());
        if (paramParcel1.readInt() != 0) {}
        for (Bundle localBundle2 = (Bundle)Bundle.CREATOR.createFromParcel(paramParcel1);; localBundle2 = null)
        {
          zzb(localzzf8, localBundle2);
          paramParcel2.writeNoException();
          return true;
        }
      case 501: 
        paramParcel1.enforceInterface("com.google.android.gms.people.internal.IPeopleService");
        zzf localzzf7 = zzf.zza.zzfS(paramParcel1.readStrongBinder());
        AccountToken localAccountToken2;
        ArrayList localArrayList1;
        if (paramParcel1.readInt() != 0)
        {
          localAccountToken2 = com.google.android.gms.people.identity.internal.zza.zzhG(paramParcel1);
          localArrayList1 = paramParcel1.createStringArrayList();
          if (paramParcel1.readInt() == 0) {
            break label3506;
          }
        }
        for (ParcelableGetOptions localParcelableGetOptions = zzi.zzhH(paramParcel1);; localParcelableGetOptions = null)
        {
          zza(localzzf7, localAccountToken2, localArrayList1, localParcelableGetOptions);
          paramParcel2.writeNoException();
          return true;
          localAccountToken2 = null;
          break;
        }
      case 502: 
        paramParcel1.enforceInterface("com.google.android.gms.people.internal.IPeopleService");
        zzq localzzq11 = zzb(zzf.zza.zzfS(paramParcel1.readStrongBinder()), paramParcel1.readString(), paramParcel1.readInt(), paramParcel1.readInt());
        paramParcel2.writeNoException();
        if (localzzq11 != null) {}
        for (IBinder localIBinder11 = localzzq11.asBinder();; localIBinder11 = null)
        {
          paramParcel2.writeStrongBinder(localIBinder11);
          return true;
        }
      case 503: 
        paramParcel1.enforceInterface("com.google.android.gms.people.internal.IPeopleService");
        zzf localzzf6 = zzf.zza.zzfS(paramParcel1.readStrongBinder());
        long l1 = paramParcel1.readLong();
        boolean bool3;
        zzq localzzq10;
        if (paramParcel1.readInt() != 0)
        {
          bool3 = true;
          localzzq10 = zzb(localzzf6, l1, bool3);
          paramParcel2.writeNoException();
          if (localzzq10 == null) {
            break label3650;
          }
        }
        for (IBinder localIBinder10 = localzzq10.asBinder();; localIBinder10 = null)
        {
          paramParcel2.writeStrongBinder(localIBinder10);
          return true;
          bool3 = false;
          break;
        }
      case 504: 
        paramParcel1.enforceInterface("com.google.android.gms.people.internal.IPeopleService");
        zzq localzzq9 = zzb(zzf.zza.zzfS(paramParcel1.readStrongBinder()), paramParcel1.readString());
        paramParcel2.writeNoException();
        if (localzzq9 != null) {}
        for (IBinder localIBinder9 = localzzq9.asBinder();; localIBinder9 = null)
        {
          paramParcel2.writeStrongBinder(localIBinder9);
          return true;
        }
      case 505: 
        paramParcel1.enforceInterface("com.google.android.gms.people.internal.IPeopleService");
        zzq localzzq8 = zzb(zzf.zza.zzfS(paramParcel1.readStrongBinder()), paramParcel1.readString(), paramParcel1.readString(), paramParcel1.readInt(), paramParcel1.readInt());
        paramParcel2.writeNoException();
        if (localzzq8 != null) {}
        for (IBinder localIBinder8 = localzzq8.asBinder();; localIBinder8 = null)
        {
          paramParcel2.writeStrongBinder(localIBinder8);
          return true;
        }
      case 506: 
        paramParcel1.enforceInterface("com.google.android.gms.people.internal.IPeopleService");
        zzq localzzq7 = zzc(zzf.zza.zzfS(paramParcel1.readStrongBinder()), paramParcel1.readString(), paramParcel1.readString(), paramParcel1.readInt());
        paramParcel2.writeNoException();
        if (localzzq7 != null) {}
        for (IBinder localIBinder7 = localzzq7.asBinder();; localIBinder7 = null)
        {
          paramParcel2.writeStrongBinder(localIBinder7);
          return true;
        }
      case 507: 
        paramParcel1.enforceInterface("com.google.android.gms.people.internal.IPeopleService");
        zzf localzzf5 = zzf.zza.zzfS(paramParcel1.readStrongBinder());
        String str3 = paramParcel1.readString();
        String str4 = paramParcel1.readString();
        boolean bool1;
        boolean bool2;
        zzq localzzq6;
        if (paramParcel1.readInt() != 0)
        {
          bool1 = true;
          String str5 = paramParcel1.readString();
          String str6 = paramParcel1.readString();
          int i = paramParcel1.readInt();
          int j = paramParcel1.readInt();
          int k = paramParcel1.readInt();
          if (paramParcel1.readInt() == 0) {
            break label3976;
          }
          bool2 = true;
          localzzq6 = zza(localzzf5, str3, str4, bool1, str5, str6, i, j, k, bool2);
          paramParcel2.writeNoException();
          if (localzzq6 == null) {
            break label3982;
          }
        }
        for (IBinder localIBinder6 = localzzq6.asBinder();; localIBinder6 = null)
        {
          paramParcel2.writeStrongBinder(localIBinder6);
          return true;
          bool1 = false;
          break;
          bool2 = false;
          break label3918;
        }
      case 508: 
        paramParcel1.enforceInterface("com.google.android.gms.people.internal.IPeopleService");
        zzf localzzf4 = zzf.zza.zzfS(paramParcel1.readStrongBinder());
        AvatarReference localAvatarReference;
        ParcelableLoadImageOptions localParcelableLoadImageOptions;
        zzq localzzq5;
        if (paramParcel1.readInt() != 0)
        {
          localAvatarReference = ParcelableAvatarReference.createFromParcel(paramParcel1);
          if (paramParcel1.readInt() == 0) {
            break label4081;
          }
          localParcelableLoadImageOptions = zzk.zziX(paramParcel1);
          localzzq5 = zza(localzzf4, localAvatarReference, localParcelableLoadImageOptions);
          paramParcel2.writeNoException();
          if (localzzq5 == null) {
            break label4087;
          }
        }
        for (IBinder localIBinder5 = localzzq5.asBinder();; localIBinder5 = null)
        {
          paramParcel2.writeStrongBinder(localIBinder5);
          return true;
          localAvatarReference = null;
          break;
          localParcelableLoadImageOptions = null;
          break label4037;
        }
      case 509: 
        paramParcel1.enforceInterface("com.google.android.gms.people.internal.IPeopleService");
        zzq localzzq4 = zza(zzf.zza.zzfS(paramParcel1.readStrongBinder()), paramParcel1.readString(), paramParcel1.readInt());
        paramParcel2.writeNoException();
        if (localzzq4 != null) {}
        for (IBinder localIBinder4 = localzzq4.asBinder();; localIBinder4 = null)
        {
          paramParcel2.writeStrongBinder(localIBinder4);
          return true;
        }
      case 601: 
        paramParcel1.enforceInterface("com.google.android.gms.people.internal.IPeopleService");
        zzf localzzf3 = zzf.zza.zzfS(paramParcel1.readStrongBinder());
        AccountToken localAccountToken1;
        ParcelableListOptions localParcelableListOptions;
        zzq localzzq3;
        if (paramParcel1.readInt() != 0)
        {
          localAccountToken1 = com.google.android.gms.people.identity.internal.zza.zzhG(paramParcel1);
          if (paramParcel1.readInt() == 0) {
            break label4245;
          }
          localParcelableListOptions = zzj.zzhI(paramParcel1);
          localzzq3 = zza(localzzf3, localAccountToken1, localParcelableListOptions);
          paramParcel2.writeNoException();
          if (localzzq3 == null) {
            break label4251;
          }
        }
        for (IBinder localIBinder3 = localzzq3.asBinder();; localIBinder3 = null)
        {
          paramParcel2.writeStrongBinder(localIBinder3);
          return true;
          localAccountToken1 = null;
          break;
          localParcelableListOptions = null;
          break label4201;
        }
      case 602: 
        label567:
        label2883:
        label2928:
        label2934:
        label4087:
        paramParcel1.enforceInterface("com.google.android.gms.people.internal.IPeopleService");
        label642:
        label1070:
        label3506:
        label3650:
        label3918:
        label4081:
        zzf localzzf2 = zzf.zza.zzfS(paramParcel1.readStrongBinder());
        label1430:
        label1696:
        label4037:
        label4201:
        DataHolder localDataHolder;
        label1557:
        label2077:
        zzq localzzq2;
        label2831:
        label4245:
        label4251:
        if (paramParcel1.readInt() != 0)
        {
          localDataHolder = DataHolderCreator.createFromParcel(paramParcel1);
          localzzq2 = zza(localzzf2, localDataHolder, paramParcel1.readInt(), paramParcel1.readInt(), paramParcel1.readLong());
          paramParcel2.writeNoException();
          if (localzzq2 == null) {
            break label4343;
          }
        }
        label3976:
        label3982:
        label4343:
        for (IBinder localIBinder2 = localzzq2.asBinder();; localIBinder2 = null)
        {
          paramParcel2.writeStrongBinder(localIBinder2);
          return true;
          localDataHolder = null;
          break;
        }
      }
      paramParcel1.enforceInterface("com.google.android.gms.people.internal.IPeopleService");
      zzf localzzf1 = zzf.zza.zzfS(paramParcel1.readStrongBinder());
      String str1 = paramParcel1.readString();
      String str2 = paramParcel1.readString();
      Bundle localBundle1;
      zzq localzzq1;
      if (paramParcel1.readInt() != 0)
      {
        localBundle1 = (Bundle)Bundle.CREATOR.createFromParcel(paramParcel1);
        localzzq1 = zza(localzzf1, str1, str2, localBundle1);
        paramParcel2.writeNoException();
        if (localzzq1 == null) {
          break label4443;
        }
      }
      label4443:
      for (IBinder localIBinder1 = localzzq1.asBinder();; localIBinder1 = null)
      {
        paramParcel2.writeStrongBinder(localIBinder1);
        return true;
        localBundle1 = null;
        break;
      }
    }
    
    private static final class zza
      implements zzg
    {
      private IBinder zzop;
      
      zza(IBinder paramIBinder)
      {
        this.zzop = paramIBinder;
      }
      
      public final IBinder asBinder()
      {
        return this.zzop;
      }
      
      public final boolean isSyncToContactsEnabled()
        throws RemoteException
      {
        Parcel localParcel1 = Parcel.obtain();
        Parcel localParcel2 = Parcel.obtain();
        try
        {
          localParcel1.writeInterfaceToken("com.google.android.gms.people.internal.IPeopleService");
          this.zzop.transact(16, localParcel1, localParcel2, 0);
          localParcel2.readException();
          int i = localParcel2.readInt();
          boolean bool = false;
          if (i != 0) {
            bool = true;
          }
          return bool;
        }
        finally
        {
          localParcel2.recycle();
          localParcel1.recycle();
        }
      }
      
      /* Error */
      public final Bundle zza(zzf paramzzf, boolean paramBoolean, String paramString1, String paramString2, int paramInt)
        throws RemoteException
      {
        // Byte code:
        //   0: invokestatic 27	android/os/Parcel:obtain	()Landroid/os/Parcel;
        //   3: astore 6
        //   5: invokestatic 27	android/os/Parcel:obtain	()Landroid/os/Parcel;
        //   8: astore 7
        //   10: aload 6
        //   12: ldc 29
        //   14: invokevirtual 33	android/os/Parcel:writeInterfaceToken	(Ljava/lang/String;)V
        //   17: aload_1
        //   18: ifnull +120 -> 138
        //   21: aload_1
        //   22: invokeinterface 55 1 0
        //   27: astore 9
        //   29: aload 6
        //   31: aload 9
        //   33: invokevirtual 58	android/os/Parcel:writeStrongBinder	(Landroid/os/IBinder;)V
        //   36: iconst_0
        //   37: istore 10
        //   39: iload_2
        //   40: ifeq +6 -> 46
        //   43: iconst_1
        //   44: istore 10
        //   46: aload 6
        //   48: iload 10
        //   50: invokevirtual 62	android/os/Parcel:writeInt	(I)V
        //   53: aload 6
        //   55: aload_3
        //   56: invokevirtual 65	android/os/Parcel:writeString	(Ljava/lang/String;)V
        //   59: aload 6
        //   61: aload 4
        //   63: invokevirtual 65	android/os/Parcel:writeString	(Ljava/lang/String;)V
        //   66: aload 6
        //   68: iload 5
        //   70: invokevirtual 62	android/os/Parcel:writeInt	(I)V
        //   73: aload_0
        //   74: getfield 15	com/google/android/gms/people/internal/zzg$zza$zza:zzop	Landroid/os/IBinder;
        //   77: bipush 11
        //   79: aload 6
        //   81: aload 7
        //   83: iconst_0
        //   84: invokeinterface 39 5 0
        //   89: pop
        //   90: aload 7
        //   92: invokevirtual 42	android/os/Parcel:readException	()V
        //   95: aload 7
        //   97: invokevirtual 46	android/os/Parcel:readInt	()I
        //   100: istore 12
        //   102: aconst_null
        //   103: astore 13
        //   105: iload 12
        //   107: ifeq +18 -> 125
        //   110: getstatic 71	android/os/Bundle:CREATOR	Landroid/os/Parcelable$Creator;
        //   113: aload 7
        //   115: invokeinterface 77 2 0
        //   120: checkcast 67	android/os/Bundle
        //   123: astore 13
        //   125: aload 7
        //   127: invokevirtual 49	android/os/Parcel:recycle	()V
        //   130: aload 6
        //   132: invokevirtual 49	android/os/Parcel:recycle	()V
        //   135: aload 13
        //   137: areturn
        //   138: aconst_null
        //   139: astore 9
        //   141: goto -112 -> 29
        //   144: astore 8
        //   146: aload 7
        //   148: invokevirtual 49	android/os/Parcel:recycle	()V
        //   151: aload 6
        //   153: invokevirtual 49	android/os/Parcel:recycle	()V
        //   156: aload 8
        //   158: athrow
        // Local variable table:
        //   start	length	slot	name	signature
        //   0	159	0	this	zza
        //   0	159	1	paramzzf	zzf
        //   0	159	2	paramBoolean	boolean
        //   0	159	3	paramString1	String
        //   0	159	4	paramString2	String
        //   0	159	5	paramInt	int
        //   3	149	6	localParcel1	Parcel
        //   8	139	7	localParcel2	Parcel
        //   144	13	8	localObject	Object
        //   27	113	9	localIBinder	IBinder
        //   37	12	10	i	int
        //   100	6	12	j	int
        //   103	33	13	localBundle	Bundle
        // Exception table:
        //   from	to	target	type
        //   10	17	144	finally
        //   21	29	144	finally
        //   29	36	144	finally
        //   46	102	144	finally
        //   110	125	144	finally
      }
      
      /* Error */
      public final Bundle zza(String paramString1, String paramString2, long paramLong, boolean paramBoolean)
        throws RemoteException
      {
        // Byte code:
        //   0: invokestatic 27	android/os/Parcel:obtain	()Landroid/os/Parcel;
        //   3: astore 6
        //   5: invokestatic 27	android/os/Parcel:obtain	()Landroid/os/Parcel;
        //   8: astore 7
        //   10: aload 6
        //   12: ldc 29
        //   14: invokevirtual 33	android/os/Parcel:writeInterfaceToken	(Ljava/lang/String;)V
        //   17: aload 6
        //   19: aload_1
        //   20: invokevirtual 65	android/os/Parcel:writeString	(Ljava/lang/String;)V
        //   23: aload 6
        //   25: aload_2
        //   26: invokevirtual 65	android/os/Parcel:writeString	(Ljava/lang/String;)V
        //   29: aload 6
        //   31: lload_3
        //   32: invokevirtual 82	android/os/Parcel:writeLong	(J)V
        //   35: iconst_0
        //   36: istore 9
        //   38: iload 5
        //   40: ifeq +6 -> 46
        //   43: iconst_1
        //   44: istore 9
        //   46: aload 6
        //   48: iload 9
        //   50: invokevirtual 62	android/os/Parcel:writeInt	(I)V
        //   53: aload_0
        //   54: getfield 15	com/google/android/gms/people/internal/zzg$zza$zza:zzop	Landroid/os/IBinder;
        //   57: bipush 26
        //   59: aload 6
        //   61: aload 7
        //   63: iconst_0
        //   64: invokeinterface 39 5 0
        //   69: pop
        //   70: aload 7
        //   72: invokevirtual 42	android/os/Parcel:readException	()V
        //   75: aload 7
        //   77: invokevirtual 46	android/os/Parcel:readInt	()I
        //   80: ifeq +31 -> 111
        //   83: getstatic 71	android/os/Bundle:CREATOR	Landroid/os/Parcelable$Creator;
        //   86: aload 7
        //   88: invokeinterface 77 2 0
        //   93: checkcast 67	android/os/Bundle
        //   96: astore 11
        //   98: aload 7
        //   100: invokevirtual 49	android/os/Parcel:recycle	()V
        //   103: aload 6
        //   105: invokevirtual 49	android/os/Parcel:recycle	()V
        //   108: aload 11
        //   110: areturn
        //   111: aconst_null
        //   112: astore 11
        //   114: goto -16 -> 98
        //   117: astore 8
        //   119: aload 7
        //   121: invokevirtual 49	android/os/Parcel:recycle	()V
        //   124: aload 6
        //   126: invokevirtual 49	android/os/Parcel:recycle	()V
        //   129: aload 8
        //   131: athrow
        // Local variable table:
        //   start	length	slot	name	signature
        //   0	132	0	this	zza
        //   0	132	1	paramString1	String
        //   0	132	2	paramString2	String
        //   0	132	3	paramLong	long
        //   0	132	5	paramBoolean	boolean
        //   3	122	6	localParcel1	Parcel
        //   8	112	7	localParcel2	Parcel
        //   117	13	8	localObject	Object
        //   36	13	9	i	int
        //   96	17	11	localBundle	Bundle
        // Exception table:
        //   from	to	target	type
        //   10	35	117	finally
        //   46	98	117	finally
      }
      
      /* Error */
      public final Bundle zza(String paramString1, String paramString2, long paramLong, boolean paramBoolean1, boolean paramBoolean2)
        throws RemoteException
      {
        // Byte code:
        //   0: iconst_1
        //   1: istore 7
        //   3: invokestatic 27	android/os/Parcel:obtain	()Landroid/os/Parcel;
        //   6: astore 8
        //   8: invokestatic 27	android/os/Parcel:obtain	()Landroid/os/Parcel;
        //   11: astore 9
        //   13: aload 8
        //   15: ldc 29
        //   17: invokevirtual 33	android/os/Parcel:writeInterfaceToken	(Ljava/lang/String;)V
        //   20: aload 8
        //   22: aload_1
        //   23: invokevirtual 65	android/os/Parcel:writeString	(Ljava/lang/String;)V
        //   26: aload 8
        //   28: aload_2
        //   29: invokevirtual 65	android/os/Parcel:writeString	(Ljava/lang/String;)V
        //   32: aload 8
        //   34: lload_3
        //   35: invokevirtual 82	android/os/Parcel:writeLong	(J)V
        //   38: iload 5
        //   40: ifeq +85 -> 125
        //   43: iload 7
        //   45: istore 11
        //   47: aload 8
        //   49: iload 11
        //   51: invokevirtual 62	android/os/Parcel:writeInt	(I)V
        //   54: iload 6
        //   56: ifeq +75 -> 131
        //   59: aload 8
        //   61: iload 7
        //   63: invokevirtual 62	android/os/Parcel:writeInt	(I)V
        //   66: aload_0
        //   67: getfield 15	com/google/android/gms/people/internal/zzg$zza$zza:zzop	Landroid/os/IBinder;
        //   70: sipush 205
        //   73: aload 8
        //   75: aload 9
        //   77: iconst_0
        //   78: invokeinterface 39 5 0
        //   83: pop
        //   84: aload 9
        //   86: invokevirtual 42	android/os/Parcel:readException	()V
        //   89: aload 9
        //   91: invokevirtual 46	android/os/Parcel:readInt	()I
        //   94: ifeq +43 -> 137
        //   97: getstatic 71	android/os/Bundle:CREATOR	Landroid/os/Parcelable$Creator;
        //   100: aload 9
        //   102: invokeinterface 77 2 0
        //   107: checkcast 67	android/os/Bundle
        //   110: astore 13
        //   112: aload 9
        //   114: invokevirtual 49	android/os/Parcel:recycle	()V
        //   117: aload 8
        //   119: invokevirtual 49	android/os/Parcel:recycle	()V
        //   122: aload 13
        //   124: areturn
        //   125: iconst_0
        //   126: istore 11
        //   128: goto -81 -> 47
        //   131: iconst_0
        //   132: istore 7
        //   134: goto -75 -> 59
        //   137: aconst_null
        //   138: astore 13
        //   140: goto -28 -> 112
        //   143: astore 10
        //   145: aload 9
        //   147: invokevirtual 49	android/os/Parcel:recycle	()V
        //   150: aload 8
        //   152: invokevirtual 49	android/os/Parcel:recycle	()V
        //   155: aload 10
        //   157: athrow
        // Local variable table:
        //   start	length	slot	name	signature
        //   0	158	0	this	zza
        //   0	158	1	paramString1	String
        //   0	158	2	paramString2	String
        //   0	158	3	paramLong	long
        //   0	158	5	paramBoolean1	boolean
        //   0	158	6	paramBoolean2	boolean
        //   1	132	7	i	int
        //   6	145	8	localParcel1	Parcel
        //   11	135	9	localParcel2	Parcel
        //   143	13	10	localObject	Object
        //   45	82	11	j	int
        //   110	29	13	localBundle	Bundle
        // Exception table:
        //   from	to	target	type
        //   13	38	143	finally
        //   47	54	143	finally
        //   59	112	143	finally
      }
      
      /* Error */
      public final zzq zza(zzf paramzzf, DataHolder paramDataHolder, int paramInt1, int paramInt2, long paramLong)
        throws RemoteException
      {
        // Byte code:
        //   0: invokestatic 27	android/os/Parcel:obtain	()Landroid/os/Parcel;
        //   3: astore 7
        //   5: invokestatic 27	android/os/Parcel:obtain	()Landroid/os/Parcel;
        //   8: astore 8
        //   10: aload 7
        //   12: ldc 29
        //   14: invokevirtual 33	android/os/Parcel:writeInterfaceToken	(Ljava/lang/String;)V
        //   17: aload_1
        //   18: ifnull +101 -> 119
        //   21: aload_1
        //   22: invokeinterface 55 1 0
        //   27: astore 10
        //   29: aload 7
        //   31: aload 10
        //   33: invokevirtual 58	android/os/Parcel:writeStrongBinder	(Landroid/os/IBinder;)V
        //   36: aload_2
        //   37: ifnull +88 -> 125
        //   40: aload 7
        //   42: iconst_1
        //   43: invokevirtual 62	android/os/Parcel:writeInt	(I)V
        //   46: aload_2
        //   47: aload 7
        //   49: iconst_0
        //   50: invokevirtual 90	com/google/android/gms/common/data/DataHolder:writeToParcel	(Landroid/os/Parcel;I)V
        //   53: aload 7
        //   55: iload_3
        //   56: invokevirtual 62	android/os/Parcel:writeInt	(I)V
        //   59: aload 7
        //   61: iload 4
        //   63: invokevirtual 62	android/os/Parcel:writeInt	(I)V
        //   66: aload 7
        //   68: lload 5
        //   70: invokevirtual 82	android/os/Parcel:writeLong	(J)V
        //   73: aload_0
        //   74: getfield 15	com/google/android/gms/people/internal/zzg$zza$zza:zzop	Landroid/os/IBinder;
        //   77: sipush 602
        //   80: aload 7
        //   82: aload 8
        //   84: iconst_0
        //   85: invokeinterface 39 5 0
        //   90: pop
        //   91: aload 8
        //   93: invokevirtual 42	android/os/Parcel:readException	()V
        //   96: aload 8
        //   98: invokevirtual 93	android/os/Parcel:readStrongBinder	()Landroid/os/IBinder;
        //   101: invokestatic 99	com/google/android/gms/common/internal/zzq$zza:zzck	(Landroid/os/IBinder;)Lcom/google/android/gms/common/internal/zzq;
        //   104: astore 12
        //   106: aload 8
        //   108: invokevirtual 49	android/os/Parcel:recycle	()V
        //   111: aload 7
        //   113: invokevirtual 49	android/os/Parcel:recycle	()V
        //   116: aload 12
        //   118: areturn
        //   119: aconst_null
        //   120: astore 10
        //   122: goto -93 -> 29
        //   125: aload 7
        //   127: iconst_0
        //   128: invokevirtual 62	android/os/Parcel:writeInt	(I)V
        //   131: goto -78 -> 53
        //   134: astore 9
        //   136: aload 8
        //   138: invokevirtual 49	android/os/Parcel:recycle	()V
        //   141: aload 7
        //   143: invokevirtual 49	android/os/Parcel:recycle	()V
        //   146: aload 9
        //   148: athrow
        // Local variable table:
        //   start	length	slot	name	signature
        //   0	149	0	this	zza
        //   0	149	1	paramzzf	zzf
        //   0	149	2	paramDataHolder	DataHolder
        //   0	149	3	paramInt1	int
        //   0	149	4	paramInt2	int
        //   0	149	5	paramLong	long
        //   3	139	7	localParcel1	Parcel
        //   8	129	8	localParcel2	Parcel
        //   134	13	9	localObject	Object
        //   27	94	10	localIBinder	IBinder
        //   104	13	12	localzzq	zzq
        // Exception table:
        //   from	to	target	type
        //   10	17	134	finally
        //   21	29	134	finally
        //   29	36	134	finally
        //   40	53	134	finally
        //   53	106	134	finally
        //   125	131	134	finally
      }
      
      public final zzq zza(zzf paramzzf, AccountToken paramAccountToken, ParcelableListOptions paramParcelableListOptions)
        throws RemoteException
      {
        Parcel localParcel1 = Parcel.obtain();
        Parcel localParcel2 = Parcel.obtain();
        label146:
        for (;;)
        {
          try
          {
            localParcel1.writeInterfaceToken("com.google.android.gms.people.internal.IPeopleService");
            IBinder localIBinder;
            if (paramzzf != null)
            {
              localIBinder = paramzzf.asBinder();
              localParcel1.writeStrongBinder(localIBinder);
              if (paramAccountToken != null)
              {
                localParcel1.writeInt(1);
                paramAccountToken.writeToParcel(localParcel1, 0);
                if (paramParcelableListOptions == null) {
                  break label146;
                }
                localParcel1.writeInt(1);
                paramParcelableListOptions.writeToParcel(localParcel1, 0);
                this.zzop.transact(601, localParcel1, localParcel2, 0);
                localParcel2.readException();
                zzq localzzq = zzq.zza.zzck(localParcel2.readStrongBinder());
                return localzzq;
              }
            }
            else
            {
              localIBinder = null;
              continue;
            }
            localParcel1.writeInt(0);
            continue;
            localParcel1.writeInt(0);
          }
          finally
          {
            localParcel2.recycle();
            localParcel1.recycle();
          }
        }
      }
      
      public final zzq zza(zzf paramzzf, AvatarReference paramAvatarReference, ParcelableLoadImageOptions paramParcelableLoadImageOptions)
        throws RemoteException
      {
        Parcel localParcel1 = Parcel.obtain();
        Parcel localParcel2 = Parcel.obtain();
        label146:
        for (;;)
        {
          try
          {
            localParcel1.writeInterfaceToken("com.google.android.gms.people.internal.IPeopleService");
            IBinder localIBinder;
            if (paramzzf != null)
            {
              localIBinder = paramzzf.asBinder();
              localParcel1.writeStrongBinder(localIBinder);
              if (paramAvatarReference != null)
              {
                localParcel1.writeInt(1);
                paramAvatarReference.writeToParcel(localParcel1, 0);
                if (paramParcelableLoadImageOptions == null) {
                  break label146;
                }
                localParcel1.writeInt(1);
                paramParcelableLoadImageOptions.writeToParcel(localParcel1, 0);
                this.zzop.transact(508, localParcel1, localParcel2, 0);
                localParcel2.readException();
                zzq localzzq = zzq.zza.zzck(localParcel2.readStrongBinder());
                return localzzq;
              }
            }
            else
            {
              localIBinder = null;
              continue;
            }
            localParcel1.writeInt(0);
            continue;
            localParcel1.writeInt(0);
          }
          finally
          {
            localParcel2.recycle();
            localParcel1.recycle();
          }
        }
      }
      
      /* Error */
      public final zzq zza(zzf paramzzf, String paramString, int paramInt)
        throws RemoteException
      {
        // Byte code:
        //   0: invokestatic 27	android/os/Parcel:obtain	()Landroid/os/Parcel;
        //   3: astore 4
        //   5: invokestatic 27	android/os/Parcel:obtain	()Landroid/os/Parcel;
        //   8: astore 5
        //   10: aload 4
        //   12: ldc 29
        //   14: invokevirtual 33	android/os/Parcel:writeInterfaceToken	(Ljava/lang/String;)V
        //   17: aload_1
        //   18: ifnull +76 -> 94
        //   21: aload_1
        //   22: invokeinterface 55 1 0
        //   27: astore 7
        //   29: aload 4
        //   31: aload 7
        //   33: invokevirtual 58	android/os/Parcel:writeStrongBinder	(Landroid/os/IBinder;)V
        //   36: aload 4
        //   38: aload_2
        //   39: invokevirtual 65	android/os/Parcel:writeString	(Ljava/lang/String;)V
        //   42: aload 4
        //   44: iload_3
        //   45: invokevirtual 62	android/os/Parcel:writeInt	(I)V
        //   48: aload_0
        //   49: getfield 15	com/google/android/gms/people/internal/zzg$zza$zza:zzop	Landroid/os/IBinder;
        //   52: sipush 509
        //   55: aload 4
        //   57: aload 5
        //   59: iconst_0
        //   60: invokeinterface 39 5 0
        //   65: pop
        //   66: aload 5
        //   68: invokevirtual 42	android/os/Parcel:readException	()V
        //   71: aload 5
        //   73: invokevirtual 93	android/os/Parcel:readStrongBinder	()Landroid/os/IBinder;
        //   76: invokestatic 99	com/google/android/gms/common/internal/zzq$zza:zzck	(Landroid/os/IBinder;)Lcom/google/android/gms/common/internal/zzq;
        //   79: astore 9
        //   81: aload 5
        //   83: invokevirtual 49	android/os/Parcel:recycle	()V
        //   86: aload 4
        //   88: invokevirtual 49	android/os/Parcel:recycle	()V
        //   91: aload 9
        //   93: areturn
        //   94: aconst_null
        //   95: astore 7
        //   97: goto -68 -> 29
        //   100: astore 6
        //   102: aload 5
        //   104: invokevirtual 49	android/os/Parcel:recycle	()V
        //   107: aload 4
        //   109: invokevirtual 49	android/os/Parcel:recycle	()V
        //   112: aload 6
        //   114: athrow
        // Local variable table:
        //   start	length	slot	name	signature
        //   0	115	0	this	zza
        //   0	115	1	paramzzf	zzf
        //   0	115	2	paramString	String
        //   0	115	3	paramInt	int
        //   3	105	4	localParcel1	Parcel
        //   8	95	5	localParcel2	Parcel
        //   100	13	6	localObject	Object
        //   27	69	7	localIBinder	IBinder
        //   79	13	9	localzzq	zzq
        // Exception table:
        //   from	to	target	type
        //   10	17	100	finally
        //   21	29	100	finally
        //   29	81	100	finally
      }
      
      /* Error */
      public final zzq zza(zzf paramzzf, String paramString1, String paramString2, Bundle paramBundle)
        throws RemoteException
      {
        // Byte code:
        //   0: invokestatic 27	android/os/Parcel:obtain	()Landroid/os/Parcel;
        //   3: astore 5
        //   5: invokestatic 27	android/os/Parcel:obtain	()Landroid/os/Parcel;
        //   8: astore 6
        //   10: aload 5
        //   12: ldc 29
        //   14: invokevirtual 33	android/os/Parcel:writeInterfaceToken	(Ljava/lang/String;)V
        //   17: aload_1
        //   18: ifnull +95 -> 113
        //   21: aload_1
        //   22: invokeinterface 55 1 0
        //   27: astore 8
        //   29: aload 5
        //   31: aload 8
        //   33: invokevirtual 58	android/os/Parcel:writeStrongBinder	(Landroid/os/IBinder;)V
        //   36: aload 5
        //   38: aload_2
        //   39: invokevirtual 65	android/os/Parcel:writeString	(Ljava/lang/String;)V
        //   42: aload 5
        //   44: aload_3
        //   45: invokevirtual 65	android/os/Parcel:writeString	(Ljava/lang/String;)V
        //   48: aload 4
        //   50: ifnull +69 -> 119
        //   53: aload 5
        //   55: iconst_1
        //   56: invokevirtual 62	android/os/Parcel:writeInt	(I)V
        //   59: aload 4
        //   61: aload 5
        //   63: iconst_0
        //   64: invokevirtual 116	android/os/Bundle:writeToParcel	(Landroid/os/Parcel;I)V
        //   67: aload_0
        //   68: getfield 15	com/google/android/gms/people/internal/zzg$zza$zza:zzop	Landroid/os/IBinder;
        //   71: sipush 1201
        //   74: aload 5
        //   76: aload 6
        //   78: iconst_0
        //   79: invokeinterface 39 5 0
        //   84: pop
        //   85: aload 6
        //   87: invokevirtual 42	android/os/Parcel:readException	()V
        //   90: aload 6
        //   92: invokevirtual 93	android/os/Parcel:readStrongBinder	()Landroid/os/IBinder;
        //   95: invokestatic 99	com/google/android/gms/common/internal/zzq$zza:zzck	(Landroid/os/IBinder;)Lcom/google/android/gms/common/internal/zzq;
        //   98: astore 10
        //   100: aload 6
        //   102: invokevirtual 49	android/os/Parcel:recycle	()V
        //   105: aload 5
        //   107: invokevirtual 49	android/os/Parcel:recycle	()V
        //   110: aload 10
        //   112: areturn
        //   113: aconst_null
        //   114: astore 8
        //   116: goto -87 -> 29
        //   119: aload 5
        //   121: iconst_0
        //   122: invokevirtual 62	android/os/Parcel:writeInt	(I)V
        //   125: goto -58 -> 67
        //   128: astore 7
        //   130: aload 6
        //   132: invokevirtual 49	android/os/Parcel:recycle	()V
        //   135: aload 5
        //   137: invokevirtual 49	android/os/Parcel:recycle	()V
        //   140: aload 7
        //   142: athrow
        // Local variable table:
        //   start	length	slot	name	signature
        //   0	143	0	this	zza
        //   0	143	1	paramzzf	zzf
        //   0	143	2	paramString1	String
        //   0	143	3	paramString2	String
        //   0	143	4	paramBundle	Bundle
        //   3	133	5	localParcel1	Parcel
        //   8	123	6	localParcel2	Parcel
        //   128	13	7	localObject	Object
        //   27	88	8	localIBinder	IBinder
        //   98	13	10	localzzq	zzq
        // Exception table:
        //   from	to	target	type
        //   10	17	128	finally
        //   21	29	128	finally
        //   29	48	128	finally
        //   53	67	128	finally
        //   67	100	128	finally
        //   119	125	128	finally
      }
      
      /* Error */
      public final zzq zza(zzf paramzzf, String paramString1, String paramString2, boolean paramBoolean1, String paramString3, String paramString4, int paramInt1, int paramInt2, int paramInt3, boolean paramBoolean2)
        throws RemoteException
      {
        // Byte code:
        //   0: iconst_1
        //   1: istore 11
        //   3: invokestatic 27	android/os/Parcel:obtain	()Landroid/os/Parcel;
        //   6: astore 12
        //   8: invokestatic 27	android/os/Parcel:obtain	()Landroid/os/Parcel;
        //   11: astore 13
        //   13: aload 12
        //   15: ldc 29
        //   17: invokevirtual 33	android/os/Parcel:writeInterfaceToken	(Ljava/lang/String;)V
        //   20: aload_1
        //   21: ifnull +139 -> 160
        //   24: aload_1
        //   25: invokeinterface 55 1 0
        //   30: astore 15
        //   32: aload 12
        //   34: aload 15
        //   36: invokevirtual 58	android/os/Parcel:writeStrongBinder	(Landroid/os/IBinder;)V
        //   39: aload 12
        //   41: aload_2
        //   42: invokevirtual 65	android/os/Parcel:writeString	(Ljava/lang/String;)V
        //   45: aload 12
        //   47: aload_3
        //   48: invokevirtual 65	android/os/Parcel:writeString	(Ljava/lang/String;)V
        //   51: iload 4
        //   53: ifeq +113 -> 166
        //   56: iload 11
        //   58: istore 16
        //   60: aload 12
        //   62: iload 16
        //   64: invokevirtual 62	android/os/Parcel:writeInt	(I)V
        //   67: aload 12
        //   69: aload 5
        //   71: invokevirtual 65	android/os/Parcel:writeString	(Ljava/lang/String;)V
        //   74: aload 12
        //   76: aload 6
        //   78: invokevirtual 65	android/os/Parcel:writeString	(Ljava/lang/String;)V
        //   81: aload 12
        //   83: iload 7
        //   85: invokevirtual 62	android/os/Parcel:writeInt	(I)V
        //   88: aload 12
        //   90: iload 8
        //   92: invokevirtual 62	android/os/Parcel:writeInt	(I)V
        //   95: aload 12
        //   97: iload 9
        //   99: invokevirtual 62	android/os/Parcel:writeInt	(I)V
        //   102: iload 10
        //   104: ifeq +68 -> 172
        //   107: aload 12
        //   109: iload 11
        //   111: invokevirtual 62	android/os/Parcel:writeInt	(I)V
        //   114: aload_0
        //   115: getfield 15	com/google/android/gms/people/internal/zzg$zza$zza:zzop	Landroid/os/IBinder;
        //   118: sipush 507
        //   121: aload 12
        //   123: aload 13
        //   125: iconst_0
        //   126: invokeinterface 39 5 0
        //   131: pop
        //   132: aload 13
        //   134: invokevirtual 42	android/os/Parcel:readException	()V
        //   137: aload 13
        //   139: invokevirtual 93	android/os/Parcel:readStrongBinder	()Landroid/os/IBinder;
        //   142: invokestatic 99	com/google/android/gms/common/internal/zzq$zza:zzck	(Landroid/os/IBinder;)Lcom/google/android/gms/common/internal/zzq;
        //   145: astore 18
        //   147: aload 13
        //   149: invokevirtual 49	android/os/Parcel:recycle	()V
        //   152: aload 12
        //   154: invokevirtual 49	android/os/Parcel:recycle	()V
        //   157: aload 18
        //   159: areturn
        //   160: aconst_null
        //   161: astore 15
        //   163: goto -131 -> 32
        //   166: iconst_0
        //   167: istore 16
        //   169: goto -109 -> 60
        //   172: iconst_0
        //   173: istore 11
        //   175: goto -68 -> 107
        //   178: astore 14
        //   180: aload 13
        //   182: invokevirtual 49	android/os/Parcel:recycle	()V
        //   185: aload 12
        //   187: invokevirtual 49	android/os/Parcel:recycle	()V
        //   190: aload 14
        //   192: athrow
        // Local variable table:
        //   start	length	slot	name	signature
        //   0	193	0	this	zza
        //   0	193	1	paramzzf	zzf
        //   0	193	2	paramString1	String
        //   0	193	3	paramString2	String
        //   0	193	4	paramBoolean1	boolean
        //   0	193	5	paramString3	String
        //   0	193	6	paramString4	String
        //   0	193	7	paramInt1	int
        //   0	193	8	paramInt2	int
        //   0	193	9	paramInt3	int
        //   0	193	10	paramBoolean2	boolean
        //   1	173	11	i	int
        //   6	180	12	localParcel1	Parcel
        //   11	170	13	localParcel2	Parcel
        //   178	13	14	localObject	Object
        //   30	132	15	localIBinder	IBinder
        //   58	110	16	j	int
        //   145	13	18	localzzq	zzq
        // Exception table:
        //   from	to	target	type
        //   13	20	178	finally
        //   24	32	178	finally
        //   32	51	178	finally
        //   60	102	178	finally
        //   107	147	178	finally
      }
      
      /* Error */
      public final void zza(zzf paramzzf, long paramLong, boolean paramBoolean)
        throws RemoteException
      {
        // Byte code:
        //   0: invokestatic 27	android/os/Parcel:obtain	()Landroid/os/Parcel;
        //   3: astore 5
        //   5: invokestatic 27	android/os/Parcel:obtain	()Landroid/os/Parcel;
        //   8: astore 6
        //   10: aload 5
        //   12: ldc 29
        //   14: invokevirtual 33	android/os/Parcel:writeInterfaceToken	(Ljava/lang/String;)V
        //   17: aload_1
        //   18: ifnull +75 -> 93
        //   21: aload_1
        //   22: invokeinterface 55 1 0
        //   27: astore 8
        //   29: aload 5
        //   31: aload 8
        //   33: invokevirtual 58	android/os/Parcel:writeStrongBinder	(Landroid/os/IBinder;)V
        //   36: aload 5
        //   38: lload_2
        //   39: invokevirtual 82	android/os/Parcel:writeLong	(J)V
        //   42: iconst_0
        //   43: istore 9
        //   45: iload 4
        //   47: ifeq +6 -> 53
        //   50: iconst_1
        //   51: istore 9
        //   53: aload 5
        //   55: iload 9
        //   57: invokevirtual 62	android/os/Parcel:writeInt	(I)V
        //   60: aload_0
        //   61: getfield 15	com/google/android/gms/people/internal/zzg$zza$zza:zzop	Landroid/os/IBinder;
        //   64: bipush 6
        //   66: aload 5
        //   68: aload 6
        //   70: iconst_0
        //   71: invokeinterface 39 5 0
        //   76: pop
        //   77: aload 6
        //   79: invokevirtual 42	android/os/Parcel:readException	()V
        //   82: aload 6
        //   84: invokevirtual 49	android/os/Parcel:recycle	()V
        //   87: aload 5
        //   89: invokevirtual 49	android/os/Parcel:recycle	()V
        //   92: return
        //   93: aconst_null
        //   94: astore 8
        //   96: goto -67 -> 29
        //   99: astore 7
        //   101: aload 6
        //   103: invokevirtual 49	android/os/Parcel:recycle	()V
        //   106: aload 5
        //   108: invokevirtual 49	android/os/Parcel:recycle	()V
        //   111: aload 7
        //   113: athrow
        // Local variable table:
        //   start	length	slot	name	signature
        //   0	114	0	this	zza
        //   0	114	1	paramzzf	zzf
        //   0	114	2	paramLong	long
        //   0	114	4	paramBoolean	boolean
        //   3	104	5	localParcel1	Parcel
        //   8	94	6	localParcel2	Parcel
        //   99	13	7	localObject	Object
        //   27	68	8	localIBinder	IBinder
        //   43	13	9	i	int
        // Exception table:
        //   from	to	target	type
        //   10	17	99	finally
        //   21	29	99	finally
        //   29	42	99	finally
        //   53	82	99	finally
      }
      
      /* Error */
      public final void zza(zzf paramzzf, Bundle paramBundle)
        throws RemoteException
      {
        // Byte code:
        //   0: invokestatic 27	android/os/Parcel:obtain	()Landroid/os/Parcel;
        //   3: astore_3
        //   4: invokestatic 27	android/os/Parcel:obtain	()Landroid/os/Parcel;
        //   7: astore 4
        //   9: aload_3
        //   10: ldc 29
        //   12: invokevirtual 33	android/os/Parcel:writeInterfaceToken	(Ljava/lang/String;)V
        //   15: aload_1
        //   16: ifnull +64 -> 80
        //   19: aload_1
        //   20: invokeinterface 55 1 0
        //   25: astore 6
        //   27: aload_3
        //   28: aload 6
        //   30: invokevirtual 58	android/os/Parcel:writeStrongBinder	(Landroid/os/IBinder;)V
        //   33: aload_2
        //   34: ifnull +52 -> 86
        //   37: aload_3
        //   38: iconst_1
        //   39: invokevirtual 62	android/os/Parcel:writeInt	(I)V
        //   42: aload_2
        //   43: aload_3
        //   44: iconst_0
        //   45: invokevirtual 116	android/os/Bundle:writeToParcel	(Landroid/os/Parcel;I)V
        //   48: aload_0
        //   49: getfield 15	com/google/android/gms/people/internal/zzg$zza$zza:zzop	Landroid/os/IBinder;
        //   52: sipush 302
        //   55: aload_3
        //   56: aload 4
        //   58: iconst_0
        //   59: invokeinterface 39 5 0
        //   64: pop
        //   65: aload 4
        //   67: invokevirtual 42	android/os/Parcel:readException	()V
        //   70: aload 4
        //   72: invokevirtual 49	android/os/Parcel:recycle	()V
        //   75: aload_3
        //   76: invokevirtual 49	android/os/Parcel:recycle	()V
        //   79: return
        //   80: aconst_null
        //   81: astore 6
        //   83: goto -56 -> 27
        //   86: aload_3
        //   87: iconst_0
        //   88: invokevirtual 62	android/os/Parcel:writeInt	(I)V
        //   91: goto -43 -> 48
        //   94: astore 5
        //   96: aload 4
        //   98: invokevirtual 49	android/os/Parcel:recycle	()V
        //   101: aload_3
        //   102: invokevirtual 49	android/os/Parcel:recycle	()V
        //   105: aload 5
        //   107: athrow
        // Local variable table:
        //   start	length	slot	name	signature
        //   0	108	0	this	zza
        //   0	108	1	paramzzf	zzf
        //   0	108	2	paramBundle	Bundle
        //   3	99	3	localParcel1	Parcel
        //   7	90	4	localParcel2	Parcel
        //   94	12	5	localObject	Object
        //   25	57	6	localIBinder	IBinder
        // Exception table:
        //   from	to	target	type
        //   9	15	94	finally
        //   19	27	94	finally
        //   27	33	94	finally
        //   37	48	94	finally
        //   48	70	94	finally
        //   86	91	94	finally
      }
      
      public final void zza(zzf paramzzf, AccountToken paramAccountToken, List<String> paramList, ParcelableGetOptions paramParcelableGetOptions)
        throws RemoteException
      {
        Parcel localParcel1 = Parcel.obtain();
        Parcel localParcel2 = Parcel.obtain();
        label142:
        for (;;)
        {
          try
          {
            localParcel1.writeInterfaceToken("com.google.android.gms.people.internal.IPeopleService");
            IBinder localIBinder;
            if (paramzzf != null)
            {
              localIBinder = paramzzf.asBinder();
              localParcel1.writeStrongBinder(localIBinder);
              if (paramAccountToken != null)
              {
                localParcel1.writeInt(1);
                paramAccountToken.writeToParcel(localParcel1, 0);
                localParcel1.writeStringList(paramList);
                if (paramParcelableGetOptions == null) {
                  break label142;
                }
                localParcel1.writeInt(1);
                paramParcelableGetOptions.writeToParcel(localParcel1, 0);
                this.zzop.transact(501, localParcel1, localParcel2, 0);
                localParcel2.readException();
              }
            }
            else
            {
              localIBinder = null;
              continue;
            }
            localParcel1.writeInt(0);
            continue;
            localParcel1.writeInt(0);
          }
          finally
          {
            localParcel2.recycle();
            localParcel1.recycle();
          }
        }
      }
      
      /* Error */
      public final void zza(zzf paramzzf, String paramString)
        throws RemoteException
      {
        // Byte code:
        //   0: invokestatic 27	android/os/Parcel:obtain	()Landroid/os/Parcel;
        //   3: astore_3
        //   4: invokestatic 27	android/os/Parcel:obtain	()Landroid/os/Parcel;
        //   7: astore 4
        //   9: aload_3
        //   10: ldc 29
        //   12: invokevirtual 33	android/os/Parcel:writeInterfaceToken	(Ljava/lang/String;)V
        //   15: aload_1
        //   16: ifnull +53 -> 69
        //   19: aload_1
        //   20: invokeinterface 55 1 0
        //   25: astore 6
        //   27: aload_3
        //   28: aload 6
        //   30: invokevirtual 58	android/os/Parcel:writeStrongBinder	(Landroid/os/IBinder;)V
        //   33: aload_3
        //   34: aload_2
        //   35: invokevirtual 65	android/os/Parcel:writeString	(Ljava/lang/String;)V
        //   38: aload_0
        //   39: getfield 15	com/google/android/gms/people/internal/zzg$zza$zza:zzop	Landroid/os/IBinder;
        //   42: bipush 24
        //   44: aload_3
        //   45: aload 4
        //   47: iconst_0
        //   48: invokeinterface 39 5 0
        //   53: pop
        //   54: aload 4
        //   56: invokevirtual 42	android/os/Parcel:readException	()V
        //   59: aload 4
        //   61: invokevirtual 49	android/os/Parcel:recycle	()V
        //   64: aload_3
        //   65: invokevirtual 49	android/os/Parcel:recycle	()V
        //   68: return
        //   69: aconst_null
        //   70: astore 6
        //   72: goto -45 -> 27
        //   75: astore 5
        //   77: aload 4
        //   79: invokevirtual 49	android/os/Parcel:recycle	()V
        //   82: aload_3
        //   83: invokevirtual 49	android/os/Parcel:recycle	()V
        //   86: aload 5
        //   88: athrow
        // Local variable table:
        //   start	length	slot	name	signature
        //   0	89	0	this	zza
        //   0	89	1	paramzzf	zzf
        //   0	89	2	paramString	String
        //   3	80	3	localParcel1	Parcel
        //   7	71	4	localParcel2	Parcel
        //   75	12	5	localObject	Object
        //   25	46	6	localIBinder	IBinder
        // Exception table:
        //   from	to	target	type
        //   9	15	75	finally
        //   19	27	75	finally
        //   27	59	75	finally
      }
      
      /* Error */
      public final void zza(zzf paramzzf, String paramString, int paramInt1, int paramInt2)
        throws RemoteException
      {
        // Byte code:
        //   0: invokestatic 27	android/os/Parcel:obtain	()Landroid/os/Parcel;
        //   3: astore 5
        //   5: invokestatic 27	android/os/Parcel:obtain	()Landroid/os/Parcel;
        //   8: astore 6
        //   10: aload 5
        //   12: ldc 29
        //   14: invokevirtual 33	android/os/Parcel:writeInterfaceToken	(Ljava/lang/String;)V
        //   17: aload_1
        //   18: ifnull +69 -> 87
        //   21: aload_1
        //   22: invokeinterface 55 1 0
        //   27: astore 8
        //   29: aload 5
        //   31: aload 8
        //   33: invokevirtual 58	android/os/Parcel:writeStrongBinder	(Landroid/os/IBinder;)V
        //   36: aload 5
        //   38: aload_2
        //   39: invokevirtual 65	android/os/Parcel:writeString	(Ljava/lang/String;)V
        //   42: aload 5
        //   44: iload_3
        //   45: invokevirtual 62	android/os/Parcel:writeInt	(I)V
        //   48: aload 5
        //   50: iload 4
        //   52: invokevirtual 62	android/os/Parcel:writeInt	(I)V
        //   55: aload_0
        //   56: getfield 15	com/google/android/gms/people/internal/zzg$zza$zza:zzop	Landroid/os/IBinder;
        //   59: iconst_5
        //   60: aload 5
        //   62: aload 6
        //   64: iconst_0
        //   65: invokeinterface 39 5 0
        //   70: pop
        //   71: aload 6
        //   73: invokevirtual 42	android/os/Parcel:readException	()V
        //   76: aload 6
        //   78: invokevirtual 49	android/os/Parcel:recycle	()V
        //   81: aload 5
        //   83: invokevirtual 49	android/os/Parcel:recycle	()V
        //   86: return
        //   87: aconst_null
        //   88: astore 8
        //   90: goto -61 -> 29
        //   93: astore 7
        //   95: aload 6
        //   97: invokevirtual 49	android/os/Parcel:recycle	()V
        //   100: aload 5
        //   102: invokevirtual 49	android/os/Parcel:recycle	()V
        //   105: aload 7
        //   107: athrow
        // Local variable table:
        //   start	length	slot	name	signature
        //   0	108	0	this	zza
        //   0	108	1	paramzzf	zzf
        //   0	108	2	paramString	String
        //   0	108	3	paramInt1	int
        //   0	108	4	paramInt2	int
        //   3	98	5	localParcel1	Parcel
        //   8	88	6	localParcel2	Parcel
        //   93	13	7	localObject	Object
        //   27	62	8	localIBinder	IBinder
        // Exception table:
        //   from	to	target	type
        //   10	17	93	finally
        //   21	29	93	finally
        //   29	76	93	finally
      }
      
      /* Error */
      public final void zza(zzf paramzzf, String paramString1, String paramString2)
        throws RemoteException
      {
        // Byte code:
        //   0: invokestatic 27	android/os/Parcel:obtain	()Landroid/os/Parcel;
        //   3: astore 4
        //   5: invokestatic 27	android/os/Parcel:obtain	()Landroid/os/Parcel;
        //   8: astore 5
        //   10: aload 4
        //   12: ldc 29
        //   14: invokevirtual 33	android/os/Parcel:writeInterfaceToken	(Ljava/lang/String;)V
        //   17: aload_1
        //   18: ifnull +63 -> 81
        //   21: aload_1
        //   22: invokeinterface 55 1 0
        //   27: astore 7
        //   29: aload 4
        //   31: aload 7
        //   33: invokevirtual 58	android/os/Parcel:writeStrongBinder	(Landroid/os/IBinder;)V
        //   36: aload 4
        //   38: aload_2
        //   39: invokevirtual 65	android/os/Parcel:writeString	(Ljava/lang/String;)V
        //   42: aload 4
        //   44: aload_3
        //   45: invokevirtual 65	android/os/Parcel:writeString	(Ljava/lang/String;)V
        //   48: aload_0
        //   49: getfield 15	com/google/android/gms/people/internal/zzg$zza$zza:zzop	Landroid/os/IBinder;
        //   52: bipush 25
        //   54: aload 4
        //   56: aload 5
        //   58: iconst_0
        //   59: invokeinterface 39 5 0
        //   64: pop
        //   65: aload 5
        //   67: invokevirtual 42	android/os/Parcel:readException	()V
        //   70: aload 5
        //   72: invokevirtual 49	android/os/Parcel:recycle	()V
        //   75: aload 4
        //   77: invokevirtual 49	android/os/Parcel:recycle	()V
        //   80: return
        //   81: aconst_null
        //   82: astore 7
        //   84: goto -55 -> 29
        //   87: astore 6
        //   89: aload 5
        //   91: invokevirtual 49	android/os/Parcel:recycle	()V
        //   94: aload 4
        //   96: invokevirtual 49	android/os/Parcel:recycle	()V
        //   99: aload 6
        //   101: athrow
        // Local variable table:
        //   start	length	slot	name	signature
        //   0	102	0	this	zza
        //   0	102	1	paramzzf	zzf
        //   0	102	2	paramString1	String
        //   0	102	3	paramString2	String
        //   3	92	4	localParcel1	Parcel
        //   8	82	5	localParcel2	Parcel
        //   87	13	6	localObject	Object
        //   27	56	7	localIBinder	IBinder
        // Exception table:
        //   from	to	target	type
        //   10	17	87	finally
        //   21	29	87	finally
        //   29	70	87	finally
      }
      
      /* Error */
      public final void zza(zzf paramzzf, String paramString1, String paramString2, int paramInt)
        throws RemoteException
      {
        // Byte code:
        //   0: invokestatic 27	android/os/Parcel:obtain	()Landroid/os/Parcel;
        //   3: astore 5
        //   5: invokestatic 27	android/os/Parcel:obtain	()Landroid/os/Parcel;
        //   8: astore 6
        //   10: aload 5
        //   12: ldc 29
        //   14: invokevirtual 33	android/os/Parcel:writeInterfaceToken	(Ljava/lang/String;)V
        //   17: aload_1
        //   18: ifnull +71 -> 89
        //   21: aload_1
        //   22: invokeinterface 55 1 0
        //   27: astore 8
        //   29: aload 5
        //   31: aload 8
        //   33: invokevirtual 58	android/os/Parcel:writeStrongBinder	(Landroid/os/IBinder;)V
        //   36: aload 5
        //   38: aload_2
        //   39: invokevirtual 65	android/os/Parcel:writeString	(Ljava/lang/String;)V
        //   42: aload 5
        //   44: aload_3
        //   45: invokevirtual 65	android/os/Parcel:writeString	(Ljava/lang/String;)V
        //   48: aload 5
        //   50: iload 4
        //   52: invokevirtual 62	android/os/Parcel:writeInt	(I)V
        //   55: aload_0
        //   56: getfield 15	com/google/android/gms/people/internal/zzg$zza$zza:zzop	Landroid/os/IBinder;
        //   59: sipush 403
        //   62: aload 5
        //   64: aload 6
        //   66: iconst_0
        //   67: invokeinterface 39 5 0
        //   72: pop
        //   73: aload 6
        //   75: invokevirtual 42	android/os/Parcel:readException	()V
        //   78: aload 6
        //   80: invokevirtual 49	android/os/Parcel:recycle	()V
        //   83: aload 5
        //   85: invokevirtual 49	android/os/Parcel:recycle	()V
        //   88: return
        //   89: aconst_null
        //   90: astore 8
        //   92: goto -63 -> 29
        //   95: astore 7
        //   97: aload 6
        //   99: invokevirtual 49	android/os/Parcel:recycle	()V
        //   102: aload 5
        //   104: invokevirtual 49	android/os/Parcel:recycle	()V
        //   107: aload 7
        //   109: athrow
        // Local variable table:
        //   start	length	slot	name	signature
        //   0	110	0	this	zza
        //   0	110	1	paramzzf	zzf
        //   0	110	2	paramString1	String
        //   0	110	3	paramString2	String
        //   0	110	4	paramInt	int
        //   3	100	5	localParcel1	Parcel
        //   8	90	6	localParcel2	Parcel
        //   95	13	7	localObject	Object
        //   27	64	8	localIBinder	IBinder
        // Exception table:
        //   from	to	target	type
        //   10	17	95	finally
        //   21	29	95	finally
        //   29	78	95	finally
      }
      
      /* Error */
      public final void zza(zzf paramzzf, String paramString1, String paramString2, int paramInt1, int paramInt2)
        throws RemoteException
      {
        // Byte code:
        //   0: invokestatic 27	android/os/Parcel:obtain	()Landroid/os/Parcel;
        //   3: astore 6
        //   5: invokestatic 27	android/os/Parcel:obtain	()Landroid/os/Parcel;
        //   8: astore 7
        //   10: aload 6
        //   12: ldc 29
        //   14: invokevirtual 33	android/os/Parcel:writeInterfaceToken	(Ljava/lang/String;)V
        //   17: aload_1
        //   18: ifnull +77 -> 95
        //   21: aload_1
        //   22: invokeinterface 55 1 0
        //   27: astore 9
        //   29: aload 6
        //   31: aload 9
        //   33: invokevirtual 58	android/os/Parcel:writeStrongBinder	(Landroid/os/IBinder;)V
        //   36: aload 6
        //   38: aload_2
        //   39: invokevirtual 65	android/os/Parcel:writeString	(Ljava/lang/String;)V
        //   42: aload 6
        //   44: aload_3
        //   45: invokevirtual 65	android/os/Parcel:writeString	(Ljava/lang/String;)V
        //   48: aload 6
        //   50: iload 4
        //   52: invokevirtual 62	android/os/Parcel:writeInt	(I)V
        //   55: aload 6
        //   57: iload 5
        //   59: invokevirtual 62	android/os/Parcel:writeInt	(I)V
        //   62: aload_0
        //   63: getfield 15	com/google/android/gms/people/internal/zzg$zza$zza:zzop	Landroid/os/IBinder;
        //   66: bipush 29
        //   68: aload 6
        //   70: aload 7
        //   72: iconst_0
        //   73: invokeinterface 39 5 0
        //   78: pop
        //   79: aload 7
        //   81: invokevirtual 42	android/os/Parcel:readException	()V
        //   84: aload 7
        //   86: invokevirtual 49	android/os/Parcel:recycle	()V
        //   89: aload 6
        //   91: invokevirtual 49	android/os/Parcel:recycle	()V
        //   94: return
        //   95: aconst_null
        //   96: astore 9
        //   98: goto -69 -> 29
        //   101: astore 8
        //   103: aload 7
        //   105: invokevirtual 49	android/os/Parcel:recycle	()V
        //   108: aload 6
        //   110: invokevirtual 49	android/os/Parcel:recycle	()V
        //   113: aload 8
        //   115: athrow
        // Local variable table:
        //   start	length	slot	name	signature
        //   0	116	0	this	zza
        //   0	116	1	paramzzf	zzf
        //   0	116	2	paramString1	String
        //   0	116	3	paramString2	String
        //   0	116	4	paramInt1	int
        //   0	116	5	paramInt2	int
        //   3	106	6	localParcel1	Parcel
        //   8	96	7	localParcel2	Parcel
        //   101	13	8	localObject	Object
        //   27	70	9	localIBinder	IBinder
        // Exception table:
        //   from	to	target	type
        //   10	17	101	finally
        //   21	29	101	finally
        //   29	84	101	finally
      }
      
      /* Error */
      public final void zza(zzf paramzzf, String paramString1, String paramString2, Uri paramUri)
        throws RemoteException
      {
        // Byte code:
        //   0: invokestatic 27	android/os/Parcel:obtain	()Landroid/os/Parcel;
        //   3: astore 5
        //   5: invokestatic 27	android/os/Parcel:obtain	()Landroid/os/Parcel;
        //   8: astore 6
        //   10: aload 5
        //   12: ldc 29
        //   14: invokevirtual 33	android/os/Parcel:writeInterfaceToken	(Ljava/lang/String;)V
        //   17: aload_1
        //   18: ifnull +82 -> 100
        //   21: aload_1
        //   22: invokeinterface 55 1 0
        //   27: astore 8
        //   29: aload 5
        //   31: aload 8
        //   33: invokevirtual 58	android/os/Parcel:writeStrongBinder	(Landroid/os/IBinder;)V
        //   36: aload 5
        //   38: aload_2
        //   39: invokevirtual 65	android/os/Parcel:writeString	(Ljava/lang/String;)V
        //   42: aload 5
        //   44: aload_3
        //   45: invokevirtual 65	android/os/Parcel:writeString	(Ljava/lang/String;)V
        //   48: aload 4
        //   50: ifnull +56 -> 106
        //   53: aload 5
        //   55: iconst_1
        //   56: invokevirtual 62	android/os/Parcel:writeInt	(I)V
        //   59: aload 4
        //   61: aload 5
        //   63: iconst_0
        //   64: invokevirtual 136	android/net/Uri:writeToParcel	(Landroid/os/Parcel;I)V
        //   67: aload_0
        //   68: getfield 15	com/google/android/gms/people/internal/zzg$zza$zza:zzop	Landroid/os/IBinder;
        //   71: bipush 13
        //   73: aload 5
        //   75: aload 6
        //   77: iconst_0
        //   78: invokeinterface 39 5 0
        //   83: pop
        //   84: aload 6
        //   86: invokevirtual 42	android/os/Parcel:readException	()V
        //   89: aload 6
        //   91: invokevirtual 49	android/os/Parcel:recycle	()V
        //   94: aload 5
        //   96: invokevirtual 49	android/os/Parcel:recycle	()V
        //   99: return
        //   100: aconst_null
        //   101: astore 8
        //   103: goto -74 -> 29
        //   106: aload 5
        //   108: iconst_0
        //   109: invokevirtual 62	android/os/Parcel:writeInt	(I)V
        //   112: goto -45 -> 67
        //   115: astore 7
        //   117: aload 6
        //   119: invokevirtual 49	android/os/Parcel:recycle	()V
        //   122: aload 5
        //   124: invokevirtual 49	android/os/Parcel:recycle	()V
        //   127: aload 7
        //   129: athrow
        // Local variable table:
        //   start	length	slot	name	signature
        //   0	130	0	this	zza
        //   0	130	1	paramzzf	zzf
        //   0	130	2	paramString1	String
        //   0	130	3	paramString2	String
        //   0	130	4	paramUri	Uri
        //   3	120	5	localParcel1	Parcel
        //   8	110	6	localParcel2	Parcel
        //   115	13	7	localObject	Object
        //   27	75	8	localIBinder	IBinder
        // Exception table:
        //   from	to	target	type
        //   10	17	115	finally
        //   21	29	115	finally
        //   29	48	115	finally
        //   53	67	115	finally
        //   67	89	115	finally
        //   106	112	115	finally
      }
      
      public final void zza(zzf paramzzf, String paramString1, String paramString2, Uri paramUri, boolean paramBoolean)
        throws RemoteException
      {
        int i = 1;
        Parcel localParcel1 = Parcel.obtain();
        Parcel localParcel2 = Parcel.obtain();
        for (;;)
        {
          try
          {
            localParcel1.writeInterfaceToken("com.google.android.gms.people.internal.IPeopleService");
            IBinder localIBinder;
            if (paramzzf != null)
            {
              localIBinder = paramzzf.asBinder();
              localParcel1.writeStrongBinder(localIBinder);
              localParcel1.writeString(paramString1);
              localParcel1.writeString(paramString2);
              if (paramUri != null)
              {
                localParcel1.writeInt(1);
                paramUri.writeToParcel(localParcel1, 0);
                break label149;
                localParcel1.writeInt(i);
                this.zzop.transact(18, localParcel1, localParcel2, 0);
                localParcel2.readException();
              }
            }
            else
            {
              localIBinder = null;
              continue;
            }
            localParcel1.writeInt(0);
          }
          finally
          {
            localParcel2.recycle();
            localParcel1.recycle();
          }
          label149:
          while (!paramBoolean)
          {
            i = 0;
            break;
          }
        }
      }
      
      /* Error */
      public final void zza(zzf paramzzf, String paramString1, String paramString2, String paramString3)
        throws RemoteException
      {
        // Byte code:
        //   0: invokestatic 27	android/os/Parcel:obtain	()Landroid/os/Parcel;
        //   3: astore 5
        //   5: invokestatic 27	android/os/Parcel:obtain	()Landroid/os/Parcel;
        //   8: astore 6
        //   10: aload 5
        //   12: ldc 29
        //   14: invokevirtual 33	android/os/Parcel:writeInterfaceToken	(Ljava/lang/String;)V
        //   17: aload_1
        //   18: ifnull +71 -> 89
        //   21: aload_1
        //   22: invokeinterface 55 1 0
        //   27: astore 8
        //   29: aload 5
        //   31: aload 8
        //   33: invokevirtual 58	android/os/Parcel:writeStrongBinder	(Landroid/os/IBinder;)V
        //   36: aload 5
        //   38: aload_2
        //   39: invokevirtual 65	android/os/Parcel:writeString	(Ljava/lang/String;)V
        //   42: aload 5
        //   44: aload_3
        //   45: invokevirtual 65	android/os/Parcel:writeString	(Ljava/lang/String;)V
        //   48: aload 5
        //   50: aload 4
        //   52: invokevirtual 65	android/os/Parcel:writeString	(Ljava/lang/String;)V
        //   55: aload_0
        //   56: getfield 15	com/google/android/gms/people/internal/zzg$zza$zza:zzop	Landroid/os/IBinder;
        //   59: sipush 204
        //   62: aload 5
        //   64: aload 6
        //   66: iconst_0
        //   67: invokeinterface 39 5 0
        //   72: pop
        //   73: aload 6
        //   75: invokevirtual 42	android/os/Parcel:readException	()V
        //   78: aload 6
        //   80: invokevirtual 49	android/os/Parcel:recycle	()V
        //   83: aload 5
        //   85: invokevirtual 49	android/os/Parcel:recycle	()V
        //   88: return
        //   89: aconst_null
        //   90: astore 8
        //   92: goto -63 -> 29
        //   95: astore 7
        //   97: aload 6
        //   99: invokevirtual 49	android/os/Parcel:recycle	()V
        //   102: aload 5
        //   104: invokevirtual 49	android/os/Parcel:recycle	()V
        //   107: aload 7
        //   109: athrow
        // Local variable table:
        //   start	length	slot	name	signature
        //   0	110	0	this	zza
        //   0	110	1	paramzzf	zzf
        //   0	110	2	paramString1	String
        //   0	110	3	paramString2	String
        //   0	110	4	paramString3	String
        //   3	100	5	localParcel1	Parcel
        //   8	90	6	localParcel2	Parcel
        //   95	13	7	localObject	Object
        //   27	64	8	localIBinder	IBinder
        // Exception table:
        //   from	to	target	type
        //   10	17	95	finally
        //   21	29	95	finally
        //   29	78	95	finally
      }
      
      /* Error */
      public final void zza(zzf paramzzf, String paramString1, String paramString2, String paramString3, int paramInt, String paramString4)
        throws RemoteException
      {
        // Byte code:
        //   0: invokestatic 27	android/os/Parcel:obtain	()Landroid/os/Parcel;
        //   3: astore 7
        //   5: invokestatic 27	android/os/Parcel:obtain	()Landroid/os/Parcel;
        //   8: astore 8
        //   10: aload 7
        //   12: ldc 29
        //   14: invokevirtual 33	android/os/Parcel:writeInterfaceToken	(Ljava/lang/String;)V
        //   17: aload_1
        //   18: ifnull +83 -> 101
        //   21: aload_1
        //   22: invokeinterface 55 1 0
        //   27: astore 10
        //   29: aload 7
        //   31: aload 10
        //   33: invokevirtual 58	android/os/Parcel:writeStrongBinder	(Landroid/os/IBinder;)V
        //   36: aload 7
        //   38: aload_2
        //   39: invokevirtual 65	android/os/Parcel:writeString	(Ljava/lang/String;)V
        //   42: aload 7
        //   44: aload_3
        //   45: invokevirtual 65	android/os/Parcel:writeString	(Ljava/lang/String;)V
        //   48: aload 7
        //   50: aload 4
        //   52: invokevirtual 65	android/os/Parcel:writeString	(Ljava/lang/String;)V
        //   55: aload 7
        //   57: iload 5
        //   59: invokevirtual 62	android/os/Parcel:writeInt	(I)V
        //   62: aload 7
        //   64: aload 6
        //   66: invokevirtual 65	android/os/Parcel:writeString	(Ljava/lang/String;)V
        //   69: aload_0
        //   70: getfield 15	com/google/android/gms/people/internal/zzg$zza$zza:zzop	Landroid/os/IBinder;
        //   73: iconst_3
        //   74: aload 7
        //   76: aload 8
        //   78: iconst_0
        //   79: invokeinterface 39 5 0
        //   84: pop
        //   85: aload 8
        //   87: invokevirtual 42	android/os/Parcel:readException	()V
        //   90: aload 8
        //   92: invokevirtual 49	android/os/Parcel:recycle	()V
        //   95: aload 7
        //   97: invokevirtual 49	android/os/Parcel:recycle	()V
        //   100: return
        //   101: aconst_null
        //   102: astore 10
        //   104: goto -75 -> 29
        //   107: astore 9
        //   109: aload 8
        //   111: invokevirtual 49	android/os/Parcel:recycle	()V
        //   114: aload 7
        //   116: invokevirtual 49	android/os/Parcel:recycle	()V
        //   119: aload 9
        //   121: athrow
        // Local variable table:
        //   start	length	slot	name	signature
        //   0	122	0	this	zza
        //   0	122	1	paramzzf	zzf
        //   0	122	2	paramString1	String
        //   0	122	3	paramString2	String
        //   0	122	4	paramString3	String
        //   0	122	5	paramInt	int
        //   0	122	6	paramString4	String
        //   3	112	7	localParcel1	Parcel
        //   8	102	8	localParcel2	Parcel
        //   107	13	9	localObject	Object
        //   27	76	10	localIBinder	IBinder
        // Exception table:
        //   from	to	target	type
        //   10	17	107	finally
        //   21	29	107	finally
        //   29	90	107	finally
      }
      
      /* Error */
      public final void zza(zzf paramzzf, String paramString1, String paramString2, String paramString3, int paramInt, String paramString4, boolean paramBoolean)
        throws RemoteException
      {
        // Byte code:
        //   0: invokestatic 27	android/os/Parcel:obtain	()Landroid/os/Parcel;
        //   3: astore 8
        //   5: invokestatic 27	android/os/Parcel:obtain	()Landroid/os/Parcel;
        //   8: astore 9
        //   10: aload 8
        //   12: ldc 29
        //   14: invokevirtual 33	android/os/Parcel:writeInterfaceToken	(Ljava/lang/String;)V
        //   17: aload_1
        //   18: ifnull +102 -> 120
        //   21: aload_1
        //   22: invokeinterface 55 1 0
        //   27: astore 11
        //   29: aload 8
        //   31: aload 11
        //   33: invokevirtual 58	android/os/Parcel:writeStrongBinder	(Landroid/os/IBinder;)V
        //   36: aload 8
        //   38: aload_2
        //   39: invokevirtual 65	android/os/Parcel:writeString	(Ljava/lang/String;)V
        //   42: aload 8
        //   44: aload_3
        //   45: invokevirtual 65	android/os/Parcel:writeString	(Ljava/lang/String;)V
        //   48: aload 8
        //   50: aload 4
        //   52: invokevirtual 65	android/os/Parcel:writeString	(Ljava/lang/String;)V
        //   55: aload 8
        //   57: iload 5
        //   59: invokevirtual 62	android/os/Parcel:writeInt	(I)V
        //   62: aload 8
        //   64: aload 6
        //   66: invokevirtual 65	android/os/Parcel:writeString	(Ljava/lang/String;)V
        //   69: iconst_0
        //   70: istore 12
        //   72: iload 7
        //   74: ifeq +6 -> 80
        //   77: iconst_1
        //   78: istore 12
        //   80: aload 8
        //   82: iload 12
        //   84: invokevirtual 62	android/os/Parcel:writeInt	(I)V
        //   87: aload_0
        //   88: getfield 15	com/google/android/gms/people/internal/zzg$zza$zza:zzop	Landroid/os/IBinder;
        //   91: bipush 19
        //   93: aload 8
        //   95: aload 9
        //   97: iconst_0
        //   98: invokeinterface 39 5 0
        //   103: pop
        //   104: aload 9
        //   106: invokevirtual 42	android/os/Parcel:readException	()V
        //   109: aload 9
        //   111: invokevirtual 49	android/os/Parcel:recycle	()V
        //   114: aload 8
        //   116: invokevirtual 49	android/os/Parcel:recycle	()V
        //   119: return
        //   120: aconst_null
        //   121: astore 11
        //   123: goto -94 -> 29
        //   126: astore 10
        //   128: aload 9
        //   130: invokevirtual 49	android/os/Parcel:recycle	()V
        //   133: aload 8
        //   135: invokevirtual 49	android/os/Parcel:recycle	()V
        //   138: aload 10
        //   140: athrow
        // Local variable table:
        //   start	length	slot	name	signature
        //   0	141	0	this	zza
        //   0	141	1	paramzzf	zzf
        //   0	141	2	paramString1	String
        //   0	141	3	paramString2	String
        //   0	141	4	paramString3	String
        //   0	141	5	paramInt	int
        //   0	141	6	paramString4	String
        //   0	141	7	paramBoolean	boolean
        //   3	131	8	localParcel1	Parcel
        //   8	121	9	localParcel2	Parcel
        //   126	13	10	localObject	Object
        //   27	95	11	localIBinder	IBinder
        //   70	13	12	i	int
        // Exception table:
        //   from	to	target	type
        //   10	17	126	finally
        //   21	29	126	finally
        //   29	69	126	finally
        //   80	109	126	finally
      }
      
      /* Error */
      public final void zza(zzf paramzzf, String paramString1, String paramString2, String paramString3, int paramInt1, boolean paramBoolean, int paramInt2, int paramInt3, String paramString4)
        throws RemoteException
      {
        // Byte code:
        //   0: invokestatic 27	android/os/Parcel:obtain	()Landroid/os/Parcel;
        //   3: astore 10
        //   5: invokestatic 27	android/os/Parcel:obtain	()Landroid/os/Parcel;
        //   8: astore 11
        //   10: aload 10
        //   12: ldc 29
        //   14: invokevirtual 33	android/os/Parcel:writeInterfaceToken	(Ljava/lang/String;)V
        //   17: aload_1
        //   18: ifnull +117 -> 135
        //   21: aload_1
        //   22: invokeinterface 55 1 0
        //   27: astore 13
        //   29: aload 10
        //   31: aload 13
        //   33: invokevirtual 58	android/os/Parcel:writeStrongBinder	(Landroid/os/IBinder;)V
        //   36: aload 10
        //   38: aload_2
        //   39: invokevirtual 65	android/os/Parcel:writeString	(Ljava/lang/String;)V
        //   42: aload 10
        //   44: aload_3
        //   45: invokevirtual 65	android/os/Parcel:writeString	(Ljava/lang/String;)V
        //   48: aload 10
        //   50: aload 4
        //   52: invokevirtual 65	android/os/Parcel:writeString	(Ljava/lang/String;)V
        //   55: aload 10
        //   57: iload 5
        //   59: invokevirtual 62	android/os/Parcel:writeInt	(I)V
        //   62: iconst_0
        //   63: istore 14
        //   65: iload 6
        //   67: ifeq +6 -> 73
        //   70: iconst_1
        //   71: istore 14
        //   73: aload 10
        //   75: iload 14
        //   77: invokevirtual 62	android/os/Parcel:writeInt	(I)V
        //   80: aload 10
        //   82: iload 7
        //   84: invokevirtual 62	android/os/Parcel:writeInt	(I)V
        //   87: aload 10
        //   89: iload 8
        //   91: invokevirtual 62	android/os/Parcel:writeInt	(I)V
        //   94: aload 10
        //   96: aload 9
        //   98: invokevirtual 65	android/os/Parcel:writeString	(Ljava/lang/String;)V
        //   101: aload_0
        //   102: getfield 15	com/google/android/gms/people/internal/zzg$zza$zza:zzop	Landroid/os/IBinder;
        //   105: sipush 202
        //   108: aload 10
        //   110: aload 11
        //   112: iconst_0
        //   113: invokeinterface 39 5 0
        //   118: pop
        //   119: aload 11
        //   121: invokevirtual 42	android/os/Parcel:readException	()V
        //   124: aload 11
        //   126: invokevirtual 49	android/os/Parcel:recycle	()V
        //   129: aload 10
        //   131: invokevirtual 49	android/os/Parcel:recycle	()V
        //   134: return
        //   135: aconst_null
        //   136: astore 13
        //   138: goto -109 -> 29
        //   141: astore 12
        //   143: aload 11
        //   145: invokevirtual 49	android/os/Parcel:recycle	()V
        //   148: aload 10
        //   150: invokevirtual 49	android/os/Parcel:recycle	()V
        //   153: aload 12
        //   155: athrow
        // Local variable table:
        //   start	length	slot	name	signature
        //   0	156	0	this	zza
        //   0	156	1	paramzzf	zzf
        //   0	156	2	paramString1	String
        //   0	156	3	paramString2	String
        //   0	156	4	paramString3	String
        //   0	156	5	paramInt1	int
        //   0	156	6	paramBoolean	boolean
        //   0	156	7	paramInt2	int
        //   0	156	8	paramInt3	int
        //   0	156	9	paramString4	String
        //   3	146	10	localParcel1	Parcel
        //   8	136	11	localParcel2	Parcel
        //   141	13	12	localObject	Object
        //   27	110	13	localIBinder	IBinder
        //   63	13	14	i	int
        // Exception table:
        //   from	to	target	type
        //   10	17	141	finally
        //   21	29	141	finally
        //   29	62	141	finally
        //   73	124	141	finally
      }
      
      /* Error */
      public final void zza(zzf paramzzf, String paramString1, String paramString2, String paramString3, int paramInt1, boolean paramBoolean1, int paramInt2, int paramInt3, String paramString4, boolean paramBoolean2)
        throws RemoteException
      {
        // Byte code:
        //   0: iconst_1
        //   1: istore 11
        //   3: invokestatic 27	android/os/Parcel:obtain	()Landroid/os/Parcel;
        //   6: astore 12
        //   8: invokestatic 27	android/os/Parcel:obtain	()Landroid/os/Parcel;
        //   11: astore 13
        //   13: aload 12
        //   15: ldc 29
        //   17: invokevirtual 33	android/os/Parcel:writeInterfaceToken	(Ljava/lang/String;)V
        //   20: aload_1
        //   21: ifnull +127 -> 148
        //   24: aload_1
        //   25: invokeinterface 55 1 0
        //   30: astore 15
        //   32: aload 12
        //   34: aload 15
        //   36: invokevirtual 58	android/os/Parcel:writeStrongBinder	(Landroid/os/IBinder;)V
        //   39: aload 12
        //   41: aload_2
        //   42: invokevirtual 65	android/os/Parcel:writeString	(Ljava/lang/String;)V
        //   45: aload 12
        //   47: aload_3
        //   48: invokevirtual 65	android/os/Parcel:writeString	(Ljava/lang/String;)V
        //   51: aload 12
        //   53: aload 4
        //   55: invokevirtual 65	android/os/Parcel:writeString	(Ljava/lang/String;)V
        //   58: aload 12
        //   60: iload 5
        //   62: invokevirtual 62	android/os/Parcel:writeInt	(I)V
        //   65: iload 6
        //   67: ifeq +87 -> 154
        //   70: iload 11
        //   72: istore 16
        //   74: aload 12
        //   76: iload 16
        //   78: invokevirtual 62	android/os/Parcel:writeInt	(I)V
        //   81: aload 12
        //   83: iload 7
        //   85: invokevirtual 62	android/os/Parcel:writeInt	(I)V
        //   88: aload 12
        //   90: iload 8
        //   92: invokevirtual 62	android/os/Parcel:writeInt	(I)V
        //   95: aload 12
        //   97: aload 9
        //   99: invokevirtual 65	android/os/Parcel:writeString	(Ljava/lang/String;)V
        //   102: iload 10
        //   104: ifeq +56 -> 160
        //   107: aload 12
        //   109: iload 11
        //   111: invokevirtual 62	android/os/Parcel:writeInt	(I)V
        //   114: aload_0
        //   115: getfield 15	com/google/android/gms/people/internal/zzg$zza$zza:zzop	Landroid/os/IBinder;
        //   118: sipush 203
        //   121: aload 12
        //   123: aload 13
        //   125: iconst_0
        //   126: invokeinterface 39 5 0
        //   131: pop
        //   132: aload 13
        //   134: invokevirtual 42	android/os/Parcel:readException	()V
        //   137: aload 13
        //   139: invokevirtual 49	android/os/Parcel:recycle	()V
        //   142: aload 12
        //   144: invokevirtual 49	android/os/Parcel:recycle	()V
        //   147: return
        //   148: aconst_null
        //   149: astore 15
        //   151: goto -119 -> 32
        //   154: iconst_0
        //   155: istore 16
        //   157: goto -83 -> 74
        //   160: iconst_0
        //   161: istore 11
        //   163: goto -56 -> 107
        //   166: astore 14
        //   168: aload 13
        //   170: invokevirtual 49	android/os/Parcel:recycle	()V
        //   173: aload 12
        //   175: invokevirtual 49	android/os/Parcel:recycle	()V
        //   178: aload 14
        //   180: athrow
        // Local variable table:
        //   start	length	slot	name	signature
        //   0	181	0	this	zza
        //   0	181	1	paramzzf	zzf
        //   0	181	2	paramString1	String
        //   0	181	3	paramString2	String
        //   0	181	4	paramString3	String
        //   0	181	5	paramInt1	int
        //   0	181	6	paramBoolean1	boolean
        //   0	181	7	paramInt2	int
        //   0	181	8	paramInt3	int
        //   0	181	9	paramString4	String
        //   0	181	10	paramBoolean2	boolean
        //   1	161	11	i	int
        //   6	168	12	localParcel1	Parcel
        //   11	158	13	localParcel2	Parcel
        //   166	13	14	localObject	Object
        //   30	120	15	localIBinder	IBinder
        //   72	84	16	j	int
        // Exception table:
        //   from	to	target	type
        //   13	20	166	finally
        //   24	32	166	finally
        //   32	65	166	finally
        //   74	102	166	finally
        //   107	137	166	finally
      }
      
      /* Error */
      public final void zza(zzf paramzzf, String paramString1, String paramString2, String paramString3, int paramInt1, boolean paramBoolean1, int paramInt2, int paramInt3, String paramString4, boolean paramBoolean2, int paramInt4, int paramInt5)
        throws RemoteException
      {
        // Byte code:
        //   0: invokestatic 27	android/os/Parcel:obtain	()Landroid/os/Parcel;
        //   3: astore 13
        //   5: invokestatic 27	android/os/Parcel:obtain	()Landroid/os/Parcel;
        //   8: astore 14
        //   10: aload 13
        //   12: ldc 29
        //   14: invokevirtual 33	android/os/Parcel:writeInterfaceToken	(Ljava/lang/String;)V
        //   17: aload_1
        //   18: ifnull +143 -> 161
        //   21: aload_1
        //   22: invokeinterface 55 1 0
        //   27: astore 16
        //   29: aload 13
        //   31: aload 16
        //   33: invokevirtual 58	android/os/Parcel:writeStrongBinder	(Landroid/os/IBinder;)V
        //   36: aload 13
        //   38: aload_2
        //   39: invokevirtual 65	android/os/Parcel:writeString	(Ljava/lang/String;)V
        //   42: aload 13
        //   44: aload_3
        //   45: invokevirtual 65	android/os/Parcel:writeString	(Ljava/lang/String;)V
        //   48: aload 13
        //   50: aload 4
        //   52: invokevirtual 65	android/os/Parcel:writeString	(Ljava/lang/String;)V
        //   55: aload 13
        //   57: iload 5
        //   59: invokevirtual 62	android/os/Parcel:writeInt	(I)V
        //   62: iload 6
        //   64: ifeq +103 -> 167
        //   67: iconst_1
        //   68: istore 17
        //   70: aload 13
        //   72: iload 17
        //   74: invokevirtual 62	android/os/Parcel:writeInt	(I)V
        //   77: aload 13
        //   79: iload 7
        //   81: invokevirtual 62	android/os/Parcel:writeInt	(I)V
        //   84: aload 13
        //   86: iload 8
        //   88: invokevirtual 62	android/os/Parcel:writeInt	(I)V
        //   91: aload 13
        //   93: aload 9
        //   95: invokevirtual 65	android/os/Parcel:writeString	(Ljava/lang/String;)V
        //   98: iload 10
        //   100: ifeq +73 -> 173
        //   103: iconst_1
        //   104: istore 18
        //   106: aload 13
        //   108: iload 18
        //   110: invokevirtual 62	android/os/Parcel:writeInt	(I)V
        //   113: aload 13
        //   115: iload 11
        //   117: invokevirtual 62	android/os/Parcel:writeInt	(I)V
        //   120: aload 13
        //   122: iload 12
        //   124: invokevirtual 62	android/os/Parcel:writeInt	(I)V
        //   127: aload_0
        //   128: getfield 15	com/google/android/gms/people/internal/zzg$zza$zza:zzop	Landroid/os/IBinder;
        //   131: sipush 402
        //   134: aload 13
        //   136: aload 14
        //   138: iconst_0
        //   139: invokeinterface 39 5 0
        //   144: pop
        //   145: aload 14
        //   147: invokevirtual 42	android/os/Parcel:readException	()V
        //   150: aload 14
        //   152: invokevirtual 49	android/os/Parcel:recycle	()V
        //   155: aload 13
        //   157: invokevirtual 49	android/os/Parcel:recycle	()V
        //   160: return
        //   161: aconst_null
        //   162: astore 16
        //   164: goto -135 -> 29
        //   167: iconst_0
        //   168: istore 17
        //   170: goto -100 -> 70
        //   173: iconst_0
        //   174: istore 18
        //   176: goto -70 -> 106
        //   179: astore 15
        //   181: aload 14
        //   183: invokevirtual 49	android/os/Parcel:recycle	()V
        //   186: aload 13
        //   188: invokevirtual 49	android/os/Parcel:recycle	()V
        //   191: aload 15
        //   193: athrow
        // Local variable table:
        //   start	length	slot	name	signature
        //   0	194	0	this	zza
        //   0	194	1	paramzzf	zzf
        //   0	194	2	paramString1	String
        //   0	194	3	paramString2	String
        //   0	194	4	paramString3	String
        //   0	194	5	paramInt1	int
        //   0	194	6	paramBoolean1	boolean
        //   0	194	7	paramInt2	int
        //   0	194	8	paramInt3	int
        //   0	194	9	paramString4	String
        //   0	194	10	paramBoolean2	boolean
        //   0	194	11	paramInt4	int
        //   0	194	12	paramInt5	int
        //   3	184	13	localParcel1	Parcel
        //   8	174	14	localParcel2	Parcel
        //   179	13	15	localObject	Object
        //   27	136	16	localIBinder	IBinder
        //   68	101	17	i	int
        //   104	71	18	j	int
        // Exception table:
        //   from	to	target	type
        //   10	17	179	finally
        //   21	29	179	finally
        //   29	62	179	finally
        //   70	98	179	finally
        //   106	150	179	finally
      }
      
      /* Error */
      public final void zza(zzf paramzzf, String paramString1, String paramString2, String paramString3, String paramString4)
        throws RemoteException
      {
        // Byte code:
        //   0: invokestatic 27	android/os/Parcel:obtain	()Landroid/os/Parcel;
        //   3: astore 6
        //   5: invokestatic 27	android/os/Parcel:obtain	()Landroid/os/Parcel;
        //   8: astore 7
        //   10: aload 6
        //   12: ldc 29
        //   14: invokevirtual 33	android/os/Parcel:writeInterfaceToken	(Ljava/lang/String;)V
        //   17: aload_1
        //   18: ifnull +77 -> 95
        //   21: aload_1
        //   22: invokeinterface 55 1 0
        //   27: astore 9
        //   29: aload 6
        //   31: aload 9
        //   33: invokevirtual 58	android/os/Parcel:writeStrongBinder	(Landroid/os/IBinder;)V
        //   36: aload 6
        //   38: aload_2
        //   39: invokevirtual 65	android/os/Parcel:writeString	(Ljava/lang/String;)V
        //   42: aload 6
        //   44: aload_3
        //   45: invokevirtual 65	android/os/Parcel:writeString	(Ljava/lang/String;)V
        //   48: aload 6
        //   50: aload 4
        //   52: invokevirtual 65	android/os/Parcel:writeString	(Ljava/lang/String;)V
        //   55: aload 6
        //   57: aload 5
        //   59: invokevirtual 65	android/os/Parcel:writeString	(Ljava/lang/String;)V
        //   62: aload_0
        //   63: getfield 15	com/google/android/gms/people/internal/zzg$zza$zza:zzop	Landroid/os/IBinder;
        //   66: bipush 27
        //   68: aload 6
        //   70: aload 7
        //   72: iconst_0
        //   73: invokeinterface 39 5 0
        //   78: pop
        //   79: aload 7
        //   81: invokevirtual 42	android/os/Parcel:readException	()V
        //   84: aload 7
        //   86: invokevirtual 49	android/os/Parcel:recycle	()V
        //   89: aload 6
        //   91: invokevirtual 49	android/os/Parcel:recycle	()V
        //   94: return
        //   95: aconst_null
        //   96: astore 9
        //   98: goto -69 -> 29
        //   101: astore 8
        //   103: aload 7
        //   105: invokevirtual 49	android/os/Parcel:recycle	()V
        //   108: aload 6
        //   110: invokevirtual 49	android/os/Parcel:recycle	()V
        //   113: aload 8
        //   115: athrow
        // Local variable table:
        //   start	length	slot	name	signature
        //   0	116	0	this	zza
        //   0	116	1	paramzzf	zzf
        //   0	116	2	paramString1	String
        //   0	116	3	paramString2	String
        //   0	116	4	paramString3	String
        //   0	116	5	paramString4	String
        //   3	106	6	localParcel1	Parcel
        //   8	96	7	localParcel2	Parcel
        //   101	13	8	localObject	Object
        //   27	70	9	localIBinder	IBinder
        // Exception table:
        //   from	to	target	type
        //   10	17	101	finally
        //   21	29	101	finally
        //   29	84	101	finally
      }
      
      /* Error */
      public final void zza(zzf paramzzf, String paramString1, String paramString2, String paramString3, String paramString4, int paramInt, String paramString5)
        throws RemoteException
      {
        // Byte code:
        //   0: invokestatic 27	android/os/Parcel:obtain	()Landroid/os/Parcel;
        //   3: astore 8
        //   5: invokestatic 27	android/os/Parcel:obtain	()Landroid/os/Parcel;
        //   8: astore 9
        //   10: aload 8
        //   12: ldc 29
        //   14: invokevirtual 33	android/os/Parcel:writeInterfaceToken	(Ljava/lang/String;)V
        //   17: aload_1
        //   18: ifnull +92 -> 110
        //   21: aload_1
        //   22: invokeinterface 55 1 0
        //   27: astore 11
        //   29: aload 8
        //   31: aload 11
        //   33: invokevirtual 58	android/os/Parcel:writeStrongBinder	(Landroid/os/IBinder;)V
        //   36: aload 8
        //   38: aload_2
        //   39: invokevirtual 65	android/os/Parcel:writeString	(Ljava/lang/String;)V
        //   42: aload 8
        //   44: aload_3
        //   45: invokevirtual 65	android/os/Parcel:writeString	(Ljava/lang/String;)V
        //   48: aload 8
        //   50: aload 4
        //   52: invokevirtual 65	android/os/Parcel:writeString	(Ljava/lang/String;)V
        //   55: aload 8
        //   57: aload 5
        //   59: invokevirtual 65	android/os/Parcel:writeString	(Ljava/lang/String;)V
        //   62: aload 8
        //   64: iload 6
        //   66: invokevirtual 62	android/os/Parcel:writeInt	(I)V
        //   69: aload 8
        //   71: aload 7
        //   73: invokevirtual 65	android/os/Parcel:writeString	(Ljava/lang/String;)V
        //   76: aload_0
        //   77: getfield 15	com/google/android/gms/people/internal/zzg$zza$zza:zzop	Landroid/os/IBinder;
        //   80: sipush 303
        //   83: aload 8
        //   85: aload 9
        //   87: iconst_0
        //   88: invokeinterface 39 5 0
        //   93: pop
        //   94: aload 9
        //   96: invokevirtual 42	android/os/Parcel:readException	()V
        //   99: aload 9
        //   101: invokevirtual 49	android/os/Parcel:recycle	()V
        //   104: aload 8
        //   106: invokevirtual 49	android/os/Parcel:recycle	()V
        //   109: return
        //   110: aconst_null
        //   111: astore 11
        //   113: goto -84 -> 29
        //   116: astore 10
        //   118: aload 9
        //   120: invokevirtual 49	android/os/Parcel:recycle	()V
        //   123: aload 8
        //   125: invokevirtual 49	android/os/Parcel:recycle	()V
        //   128: aload 10
        //   130: athrow
        // Local variable table:
        //   start	length	slot	name	signature
        //   0	131	0	this	zza
        //   0	131	1	paramzzf	zzf
        //   0	131	2	paramString1	String
        //   0	131	3	paramString2	String
        //   0	131	4	paramString3	String
        //   0	131	5	paramString4	String
        //   0	131	6	paramInt	int
        //   0	131	7	paramString5	String
        //   3	121	8	localParcel1	Parcel
        //   8	111	9	localParcel2	Parcel
        //   116	13	10	localObject	Object
        //   27	85	11	localIBinder	IBinder
        // Exception table:
        //   from	to	target	type
        //   10	17	116	finally
        //   21	29	116	finally
        //   29	99	116	finally
      }
      
      /* Error */
      public final void zza(zzf paramzzf, String paramString1, String paramString2, String paramString3, String paramString4, boolean paramBoolean)
        throws RemoteException
      {
        // Byte code:
        //   0: invokestatic 27	android/os/Parcel:obtain	()Landroid/os/Parcel;
        //   3: astore 7
        //   5: invokestatic 27	android/os/Parcel:obtain	()Landroid/os/Parcel;
        //   8: astore 8
        //   10: aload 7
        //   12: ldc 29
        //   14: invokevirtual 33	android/os/Parcel:writeInterfaceToken	(Ljava/lang/String;)V
        //   17: aload_1
        //   18: ifnull +96 -> 114
        //   21: aload_1
        //   22: invokeinterface 55 1 0
        //   27: astore 10
        //   29: aload 7
        //   31: aload 10
        //   33: invokevirtual 58	android/os/Parcel:writeStrongBinder	(Landroid/os/IBinder;)V
        //   36: aload 7
        //   38: aload_2
        //   39: invokevirtual 65	android/os/Parcel:writeString	(Ljava/lang/String;)V
        //   42: aload 7
        //   44: aload_3
        //   45: invokevirtual 65	android/os/Parcel:writeString	(Ljava/lang/String;)V
        //   48: aload 7
        //   50: aload 4
        //   52: invokevirtual 65	android/os/Parcel:writeString	(Ljava/lang/String;)V
        //   55: aload 7
        //   57: aload 5
        //   59: invokevirtual 65	android/os/Parcel:writeString	(Ljava/lang/String;)V
        //   62: iconst_0
        //   63: istore 11
        //   65: iload 6
        //   67: ifeq +6 -> 73
        //   70: iconst_1
        //   71: istore 11
        //   73: aload 7
        //   75: iload 11
        //   77: invokevirtual 62	android/os/Parcel:writeInt	(I)V
        //   80: aload_0
        //   81: getfield 15	com/google/android/gms/people/internal/zzg$zza$zza:zzop	Landroid/os/IBinder;
        //   84: sipush 701
        //   87: aload 7
        //   89: aload 8
        //   91: iconst_0
        //   92: invokeinterface 39 5 0
        //   97: pop
        //   98: aload 8
        //   100: invokevirtual 42	android/os/Parcel:readException	()V
        //   103: aload 8
        //   105: invokevirtual 49	android/os/Parcel:recycle	()V
        //   108: aload 7
        //   110: invokevirtual 49	android/os/Parcel:recycle	()V
        //   113: return
        //   114: aconst_null
        //   115: astore 10
        //   117: goto -88 -> 29
        //   120: astore 9
        //   122: aload 8
        //   124: invokevirtual 49	android/os/Parcel:recycle	()V
        //   127: aload 7
        //   129: invokevirtual 49	android/os/Parcel:recycle	()V
        //   132: aload 9
        //   134: athrow
        // Local variable table:
        //   start	length	slot	name	signature
        //   0	135	0	this	zza
        //   0	135	1	paramzzf	zzf
        //   0	135	2	paramString1	String
        //   0	135	3	paramString2	String
        //   0	135	4	paramString3	String
        //   0	135	5	paramString4	String
        //   0	135	6	paramBoolean	boolean
        //   3	125	7	localParcel1	Parcel
        //   8	115	8	localParcel2	Parcel
        //   120	13	9	localObject	Object
        //   27	89	10	localIBinder	IBinder
        //   63	13	11	i	int
        // Exception table:
        //   from	to	target	type
        //   10	17	120	finally
        //   21	29	120	finally
        //   29	62	120	finally
        //   73	103	120	finally
      }
      
      /* Error */
      public final void zza(zzf paramzzf, String paramString1, String paramString2, String paramString3, List<String> paramList)
        throws RemoteException
      {
        // Byte code:
        //   0: invokestatic 27	android/os/Parcel:obtain	()Landroid/os/Parcel;
        //   3: astore 6
        //   5: invokestatic 27	android/os/Parcel:obtain	()Landroid/os/Parcel;
        //   8: astore 7
        //   10: aload 6
        //   12: ldc 29
        //   14: invokevirtual 33	android/os/Parcel:writeInterfaceToken	(Ljava/lang/String;)V
        //   17: aload_1
        //   18: ifnull +77 -> 95
        //   21: aload_1
        //   22: invokeinterface 55 1 0
        //   27: astore 9
        //   29: aload 6
        //   31: aload 9
        //   33: invokevirtual 58	android/os/Parcel:writeStrongBinder	(Landroid/os/IBinder;)V
        //   36: aload 6
        //   38: aload_2
        //   39: invokevirtual 65	android/os/Parcel:writeString	(Ljava/lang/String;)V
        //   42: aload 6
        //   44: aload_3
        //   45: invokevirtual 65	android/os/Parcel:writeString	(Ljava/lang/String;)V
        //   48: aload 6
        //   50: aload 4
        //   52: invokevirtual 65	android/os/Parcel:writeString	(Ljava/lang/String;)V
        //   55: aload 6
        //   57: aload 5
        //   59: invokevirtual 124	android/os/Parcel:writeStringList	(Ljava/util/List;)V
        //   62: aload_0
        //   63: getfield 15	com/google/android/gms/people/internal/zzg$zza$zza:zzop	Landroid/os/IBinder;
        //   66: bipush 28
        //   68: aload 6
        //   70: aload 7
        //   72: iconst_0
        //   73: invokeinterface 39 5 0
        //   78: pop
        //   79: aload 7
        //   81: invokevirtual 42	android/os/Parcel:readException	()V
        //   84: aload 7
        //   86: invokevirtual 49	android/os/Parcel:recycle	()V
        //   89: aload 6
        //   91: invokevirtual 49	android/os/Parcel:recycle	()V
        //   94: return
        //   95: aconst_null
        //   96: astore 9
        //   98: goto -69 -> 29
        //   101: astore 8
        //   103: aload 7
        //   105: invokevirtual 49	android/os/Parcel:recycle	()V
        //   108: aload 6
        //   110: invokevirtual 49	android/os/Parcel:recycle	()V
        //   113: aload 8
        //   115: athrow
        // Local variable table:
        //   start	length	slot	name	signature
        //   0	116	0	this	zza
        //   0	116	1	paramzzf	zzf
        //   0	116	2	paramString1	String
        //   0	116	3	paramString2	String
        //   0	116	4	paramString3	String
        //   0	116	5	paramList	List<String>
        //   3	106	6	localParcel1	Parcel
        //   8	96	7	localParcel2	Parcel
        //   101	13	8	localObject	Object
        //   27	70	9	localIBinder	IBinder
        // Exception table:
        //   from	to	target	type
        //   10	17	101	finally
        //   21	29	101	finally
        //   29	84	101	finally
      }
      
      /* Error */
      public final void zza(zzf paramzzf, String paramString1, String paramString2, String paramString3, List<String> paramList, int paramInt, boolean paramBoolean, long paramLong)
        throws RemoteException
      {
        // Byte code:
        //   0: invokestatic 27	android/os/Parcel:obtain	()Landroid/os/Parcel;
        //   3: astore 10
        //   5: invokestatic 27	android/os/Parcel:obtain	()Landroid/os/Parcel;
        //   8: astore 11
        //   10: aload 10
        //   12: ldc 29
        //   14: invokevirtual 33	android/os/Parcel:writeInterfaceToken	(Ljava/lang/String;)V
        //   17: aload_1
        //   18: ifnull +108 -> 126
        //   21: aload_1
        //   22: invokeinterface 55 1 0
        //   27: astore 13
        //   29: aload 10
        //   31: aload 13
        //   33: invokevirtual 58	android/os/Parcel:writeStrongBinder	(Landroid/os/IBinder;)V
        //   36: aload 10
        //   38: aload_2
        //   39: invokevirtual 65	android/os/Parcel:writeString	(Ljava/lang/String;)V
        //   42: aload 10
        //   44: aload_3
        //   45: invokevirtual 65	android/os/Parcel:writeString	(Ljava/lang/String;)V
        //   48: aload 10
        //   50: aload 4
        //   52: invokevirtual 65	android/os/Parcel:writeString	(Ljava/lang/String;)V
        //   55: aload 10
        //   57: aload 5
        //   59: invokevirtual 124	android/os/Parcel:writeStringList	(Ljava/util/List;)V
        //   62: aload 10
        //   64: iload 6
        //   66: invokevirtual 62	android/os/Parcel:writeInt	(I)V
        //   69: iconst_0
        //   70: istore 14
        //   72: iload 7
        //   74: ifeq +6 -> 80
        //   77: iconst_1
        //   78: istore 14
        //   80: aload 10
        //   82: iload 14
        //   84: invokevirtual 62	android/os/Parcel:writeInt	(I)V
        //   87: aload 10
        //   89: lload 8
        //   91: invokevirtual 82	android/os/Parcel:writeLong	(J)V
        //   94: aload_0
        //   95: getfield 15	com/google/android/gms/people/internal/zzg$zza$zza:zzop	Landroid/os/IBinder;
        //   98: iconst_4
        //   99: aload 10
        //   101: aload 11
        //   103: iconst_0
        //   104: invokeinterface 39 5 0
        //   109: pop
        //   110: aload 11
        //   112: invokevirtual 42	android/os/Parcel:readException	()V
        //   115: aload 11
        //   117: invokevirtual 49	android/os/Parcel:recycle	()V
        //   120: aload 10
        //   122: invokevirtual 49	android/os/Parcel:recycle	()V
        //   125: return
        //   126: aconst_null
        //   127: astore 13
        //   129: goto -100 -> 29
        //   132: astore 12
        //   134: aload 11
        //   136: invokevirtual 49	android/os/Parcel:recycle	()V
        //   139: aload 10
        //   141: invokevirtual 49	android/os/Parcel:recycle	()V
        //   144: aload 12
        //   146: athrow
        // Local variable table:
        //   start	length	slot	name	signature
        //   0	147	0	this	zza
        //   0	147	1	paramzzf	zzf
        //   0	147	2	paramString1	String
        //   0	147	3	paramString2	String
        //   0	147	4	paramString3	String
        //   0	147	5	paramList	List<String>
        //   0	147	6	paramInt	int
        //   0	147	7	paramBoolean	boolean
        //   0	147	8	paramLong	long
        //   3	137	10	localParcel1	Parcel
        //   8	127	11	localParcel2	Parcel
        //   132	13	12	localObject	Object
        //   27	101	13	localIBinder	IBinder
        //   70	13	14	i	int
        // Exception table:
        //   from	to	target	type
        //   10	17	132	finally
        //   21	29	132	finally
        //   29	69	132	finally
        //   80	115	132	finally
      }
      
      /* Error */
      public final void zza(zzf paramzzf, String paramString1, String paramString2, String paramString3, List<String> paramList, int paramInt1, boolean paramBoolean, long paramLong, String paramString4, int paramInt2)
        throws RemoteException
      {
        // Byte code:
        //   0: invokestatic 27	android/os/Parcel:obtain	()Landroid/os/Parcel;
        //   3: astore 12
        //   5: invokestatic 27	android/os/Parcel:obtain	()Landroid/os/Parcel;
        //   8: astore 13
        //   10: aload 12
        //   12: ldc 29
        //   14: invokevirtual 33	android/os/Parcel:writeInterfaceToken	(Ljava/lang/String;)V
        //   17: aload_1
        //   18: ifnull +120 -> 138
        //   21: aload_1
        //   22: invokeinterface 55 1 0
        //   27: astore 15
        //   29: aload 12
        //   31: aload 15
        //   33: invokevirtual 58	android/os/Parcel:writeStrongBinder	(Landroid/os/IBinder;)V
        //   36: aload 12
        //   38: aload_2
        //   39: invokevirtual 65	android/os/Parcel:writeString	(Ljava/lang/String;)V
        //   42: aload 12
        //   44: aload_3
        //   45: invokevirtual 65	android/os/Parcel:writeString	(Ljava/lang/String;)V
        //   48: aload 12
        //   50: aload 4
        //   52: invokevirtual 65	android/os/Parcel:writeString	(Ljava/lang/String;)V
        //   55: aload 12
        //   57: aload 5
        //   59: invokevirtual 124	android/os/Parcel:writeStringList	(Ljava/util/List;)V
        //   62: aload 12
        //   64: iload 6
        //   66: invokevirtual 62	android/os/Parcel:writeInt	(I)V
        //   69: iload 7
        //   71: ifeq +73 -> 144
        //   74: iconst_1
        //   75: istore 16
        //   77: aload 12
        //   79: iload 16
        //   81: invokevirtual 62	android/os/Parcel:writeInt	(I)V
        //   84: aload 12
        //   86: lload 8
        //   88: invokevirtual 82	android/os/Parcel:writeLong	(J)V
        //   91: aload 12
        //   93: aload 10
        //   95: invokevirtual 65	android/os/Parcel:writeString	(Ljava/lang/String;)V
        //   98: aload 12
        //   100: iload 11
        //   102: invokevirtual 62	android/os/Parcel:writeInt	(I)V
        //   105: aload_0
        //   106: getfield 15	com/google/android/gms/people/internal/zzg$zza$zza:zzop	Landroid/os/IBinder;
        //   109: bipush 21
        //   111: aload 12
        //   113: aload 13
        //   115: iconst_0
        //   116: invokeinterface 39 5 0
        //   121: pop
        //   122: aload 13
        //   124: invokevirtual 42	android/os/Parcel:readException	()V
        //   127: aload 13
        //   129: invokevirtual 49	android/os/Parcel:recycle	()V
        //   132: aload 12
        //   134: invokevirtual 49	android/os/Parcel:recycle	()V
        //   137: return
        //   138: aconst_null
        //   139: astore 15
        //   141: goto -112 -> 29
        //   144: iconst_0
        //   145: istore 16
        //   147: goto -70 -> 77
        //   150: astore 14
        //   152: aload 13
        //   154: invokevirtual 49	android/os/Parcel:recycle	()V
        //   157: aload 12
        //   159: invokevirtual 49	android/os/Parcel:recycle	()V
        //   162: aload 14
        //   164: athrow
        // Local variable table:
        //   start	length	slot	name	signature
        //   0	165	0	this	zza
        //   0	165	1	paramzzf	zzf
        //   0	165	2	paramString1	String
        //   0	165	3	paramString2	String
        //   0	165	4	paramString3	String
        //   0	165	5	paramList	List<String>
        //   0	165	6	paramInt1	int
        //   0	165	7	paramBoolean	boolean
        //   0	165	8	paramLong	long
        //   0	165	10	paramString4	String
        //   0	165	11	paramInt2	int
        //   3	155	12	localParcel1	Parcel
        //   8	145	13	localParcel2	Parcel
        //   150	13	14	localObject	Object
        //   27	113	15	localIBinder	IBinder
        //   75	71	16	i	int
        // Exception table:
        //   from	to	target	type
        //   10	17	150	finally
        //   21	29	150	finally
        //   29	69	150	finally
        //   77	127	150	finally
      }
      
      /* Error */
      public final void zza(zzf paramzzf, String paramString1, String paramString2, String paramString3, List<String> paramList, int paramInt1, boolean paramBoolean, long paramLong, String paramString4, int paramInt2, int paramInt3)
        throws RemoteException
      {
        // Byte code:
        //   0: invokestatic 27	android/os/Parcel:obtain	()Landroid/os/Parcel;
        //   3: astore 13
        //   5: invokestatic 27	android/os/Parcel:obtain	()Landroid/os/Parcel;
        //   8: astore 14
        //   10: aload 13
        //   12: ldc 29
        //   14: invokevirtual 33	android/os/Parcel:writeInterfaceToken	(Ljava/lang/String;)V
        //   17: aload_1
        //   18: ifnull +128 -> 146
        //   21: aload_1
        //   22: invokeinterface 55 1 0
        //   27: astore 16
        //   29: aload 13
        //   31: aload 16
        //   33: invokevirtual 58	android/os/Parcel:writeStrongBinder	(Landroid/os/IBinder;)V
        //   36: aload 13
        //   38: aload_2
        //   39: invokevirtual 65	android/os/Parcel:writeString	(Ljava/lang/String;)V
        //   42: aload 13
        //   44: aload_3
        //   45: invokevirtual 65	android/os/Parcel:writeString	(Ljava/lang/String;)V
        //   48: aload 13
        //   50: aload 4
        //   52: invokevirtual 65	android/os/Parcel:writeString	(Ljava/lang/String;)V
        //   55: aload 13
        //   57: aload 5
        //   59: invokevirtual 124	android/os/Parcel:writeStringList	(Ljava/util/List;)V
        //   62: aload 13
        //   64: iload 6
        //   66: invokevirtual 62	android/os/Parcel:writeInt	(I)V
        //   69: iload 7
        //   71: ifeq +81 -> 152
        //   74: iconst_1
        //   75: istore 17
        //   77: aload 13
        //   79: iload 17
        //   81: invokevirtual 62	android/os/Parcel:writeInt	(I)V
        //   84: aload 13
        //   86: lload 8
        //   88: invokevirtual 82	android/os/Parcel:writeLong	(J)V
        //   91: aload 13
        //   93: aload 10
        //   95: invokevirtual 65	android/os/Parcel:writeString	(Ljava/lang/String;)V
        //   98: aload 13
        //   100: iload 11
        //   102: invokevirtual 62	android/os/Parcel:writeInt	(I)V
        //   105: aload 13
        //   107: iload 12
        //   109: invokevirtual 62	android/os/Parcel:writeInt	(I)V
        //   112: aload_0
        //   113: getfield 15	com/google/android/gms/people/internal/zzg$zza$zza:zzop	Landroid/os/IBinder;
        //   116: sipush 401
        //   119: aload 13
        //   121: aload 14
        //   123: iconst_0
        //   124: invokeinterface 39 5 0
        //   129: pop
        //   130: aload 14
        //   132: invokevirtual 42	android/os/Parcel:readException	()V
        //   135: aload 14
        //   137: invokevirtual 49	android/os/Parcel:recycle	()V
        //   140: aload 13
        //   142: invokevirtual 49	android/os/Parcel:recycle	()V
        //   145: return
        //   146: aconst_null
        //   147: astore 16
        //   149: goto -120 -> 29
        //   152: iconst_0
        //   153: istore 17
        //   155: goto -78 -> 77
        //   158: astore 15
        //   160: aload 14
        //   162: invokevirtual 49	android/os/Parcel:recycle	()V
        //   165: aload 13
        //   167: invokevirtual 49	android/os/Parcel:recycle	()V
        //   170: aload 15
        //   172: athrow
        // Local variable table:
        //   start	length	slot	name	signature
        //   0	173	0	this	zza
        //   0	173	1	paramzzf	zzf
        //   0	173	2	paramString1	String
        //   0	173	3	paramString2	String
        //   0	173	4	paramString3	String
        //   0	173	5	paramList	List<String>
        //   0	173	6	paramInt1	int
        //   0	173	7	paramBoolean	boolean
        //   0	173	8	paramLong	long
        //   0	173	10	paramString4	String
        //   0	173	11	paramInt2	int
        //   0	173	12	paramInt3	int
        //   3	163	13	localParcel1	Parcel
        //   8	153	14	localParcel2	Parcel
        //   158	13	15	localObject	Object
        //   27	121	16	localIBinder	IBinder
        //   75	79	17	i	int
        // Exception table:
        //   from	to	target	type
        //   10	17	158	finally
        //   21	29	158	finally
        //   29	69	158	finally
        //   77	135	158	finally
      }
      
      /* Error */
      public final void zza(zzf paramzzf, String paramString1, String paramString2, String paramString3, List<String> paramList, int paramInt1, boolean paramBoolean, long paramLong, String paramString4, int paramInt2, int paramInt3, int paramInt4)
        throws RemoteException
      {
        // Byte code:
        //   0: invokestatic 27	android/os/Parcel:obtain	()Landroid/os/Parcel;
        //   3: astore 14
        //   5: invokestatic 27	android/os/Parcel:obtain	()Landroid/os/Parcel;
        //   8: astore 15
        //   10: aload 14
        //   12: ldc 29
        //   14: invokevirtual 33	android/os/Parcel:writeInterfaceToken	(Ljava/lang/String;)V
        //   17: aload_1
        //   18: ifnull +135 -> 153
        //   21: aload_1
        //   22: invokeinterface 55 1 0
        //   27: astore 17
        //   29: aload 14
        //   31: aload 17
        //   33: invokevirtual 58	android/os/Parcel:writeStrongBinder	(Landroid/os/IBinder;)V
        //   36: aload 14
        //   38: aload_2
        //   39: invokevirtual 65	android/os/Parcel:writeString	(Ljava/lang/String;)V
        //   42: aload 14
        //   44: aload_3
        //   45: invokevirtual 65	android/os/Parcel:writeString	(Ljava/lang/String;)V
        //   48: aload 14
        //   50: aload 4
        //   52: invokevirtual 65	android/os/Parcel:writeString	(Ljava/lang/String;)V
        //   55: aload 14
        //   57: aload 5
        //   59: invokevirtual 124	android/os/Parcel:writeStringList	(Ljava/util/List;)V
        //   62: aload 14
        //   64: iload 6
        //   66: invokevirtual 62	android/os/Parcel:writeInt	(I)V
        //   69: iload 7
        //   71: ifeq +88 -> 159
        //   74: iconst_1
        //   75: istore 18
        //   77: aload 14
        //   79: iload 18
        //   81: invokevirtual 62	android/os/Parcel:writeInt	(I)V
        //   84: aload 14
        //   86: lload 8
        //   88: invokevirtual 82	android/os/Parcel:writeLong	(J)V
        //   91: aload 14
        //   93: aload 10
        //   95: invokevirtual 65	android/os/Parcel:writeString	(Ljava/lang/String;)V
        //   98: aload 14
        //   100: iload 11
        //   102: invokevirtual 62	android/os/Parcel:writeInt	(I)V
        //   105: aload 14
        //   107: iload 12
        //   109: invokevirtual 62	android/os/Parcel:writeInt	(I)V
        //   112: aload 14
        //   114: iload 13
        //   116: invokevirtual 62	android/os/Parcel:writeInt	(I)V
        //   119: aload_0
        //   120: getfield 15	com/google/android/gms/people/internal/zzg$zza$zza:zzop	Landroid/os/IBinder;
        //   123: sipush 404
        //   126: aload 14
        //   128: aload 15
        //   130: iconst_0
        //   131: invokeinterface 39 5 0
        //   136: pop
        //   137: aload 15
        //   139: invokevirtual 42	android/os/Parcel:readException	()V
        //   142: aload 15
        //   144: invokevirtual 49	android/os/Parcel:recycle	()V
        //   147: aload 14
        //   149: invokevirtual 49	android/os/Parcel:recycle	()V
        //   152: return
        //   153: aconst_null
        //   154: astore 17
        //   156: goto -127 -> 29
        //   159: iconst_0
        //   160: istore 18
        //   162: goto -85 -> 77
        //   165: astore 16
        //   167: aload 15
        //   169: invokevirtual 49	android/os/Parcel:recycle	()V
        //   172: aload 14
        //   174: invokevirtual 49	android/os/Parcel:recycle	()V
        //   177: aload 16
        //   179: athrow
        // Local variable table:
        //   start	length	slot	name	signature
        //   0	180	0	this	zza
        //   0	180	1	paramzzf	zzf
        //   0	180	2	paramString1	String
        //   0	180	3	paramString2	String
        //   0	180	4	paramString3	String
        //   0	180	5	paramList	List<String>
        //   0	180	6	paramInt1	int
        //   0	180	7	paramBoolean	boolean
        //   0	180	8	paramLong	long
        //   0	180	10	paramString4	String
        //   0	180	11	paramInt2	int
        //   0	180	12	paramInt3	int
        //   0	180	13	paramInt4	int
        //   3	170	14	localParcel1	Parcel
        //   8	160	15	localParcel2	Parcel
        //   165	13	16	localObject	Object
        //   27	128	17	localIBinder	IBinder
        //   75	86	18	i	int
        // Exception table:
        //   from	to	target	type
        //   10	17	165	finally
        //   21	29	165	finally
        //   29	69	165	finally
        //   77	142	165	finally
      }
      
      /* Error */
      public final void zza(zzf paramzzf, String paramString1, String paramString2, String paramString3, List<String> paramList1, List<String> paramList2)
        throws RemoteException
      {
        // Byte code:
        //   0: invokestatic 27	android/os/Parcel:obtain	()Landroid/os/Parcel;
        //   3: astore 7
        //   5: invokestatic 27	android/os/Parcel:obtain	()Landroid/os/Parcel;
        //   8: astore 8
        //   10: aload 7
        //   12: ldc 29
        //   14: invokevirtual 33	android/os/Parcel:writeInterfaceToken	(Ljava/lang/String;)V
        //   17: aload_1
        //   18: ifnull +84 -> 102
        //   21: aload_1
        //   22: invokeinterface 55 1 0
        //   27: astore 10
        //   29: aload 7
        //   31: aload 10
        //   33: invokevirtual 58	android/os/Parcel:writeStrongBinder	(Landroid/os/IBinder;)V
        //   36: aload 7
        //   38: aload_2
        //   39: invokevirtual 65	android/os/Parcel:writeString	(Ljava/lang/String;)V
        //   42: aload 7
        //   44: aload_3
        //   45: invokevirtual 65	android/os/Parcel:writeString	(Ljava/lang/String;)V
        //   48: aload 7
        //   50: aload 4
        //   52: invokevirtual 65	android/os/Parcel:writeString	(Ljava/lang/String;)V
        //   55: aload 7
        //   57: aload 5
        //   59: invokevirtual 124	android/os/Parcel:writeStringList	(Ljava/util/List;)V
        //   62: aload 7
        //   64: aload 6
        //   66: invokevirtual 124	android/os/Parcel:writeStringList	(Ljava/util/List;)V
        //   69: aload_0
        //   70: getfield 15	com/google/android/gms/people/internal/zzg$zza$zza:zzop	Landroid/os/IBinder;
        //   73: bipush 14
        //   75: aload 7
        //   77: aload 8
        //   79: iconst_0
        //   80: invokeinterface 39 5 0
        //   85: pop
        //   86: aload 8
        //   88: invokevirtual 42	android/os/Parcel:readException	()V
        //   91: aload 8
        //   93: invokevirtual 49	android/os/Parcel:recycle	()V
        //   96: aload 7
        //   98: invokevirtual 49	android/os/Parcel:recycle	()V
        //   101: return
        //   102: aconst_null
        //   103: astore 10
        //   105: goto -76 -> 29
        //   108: astore 9
        //   110: aload 8
        //   112: invokevirtual 49	android/os/Parcel:recycle	()V
        //   115: aload 7
        //   117: invokevirtual 49	android/os/Parcel:recycle	()V
        //   120: aload 9
        //   122: athrow
        // Local variable table:
        //   start	length	slot	name	signature
        //   0	123	0	this	zza
        //   0	123	1	paramzzf	zzf
        //   0	123	2	paramString1	String
        //   0	123	3	paramString2	String
        //   0	123	4	paramString3	String
        //   0	123	5	paramList1	List<String>
        //   0	123	6	paramList2	List<String>
        //   3	113	7	localParcel1	Parcel
        //   8	103	8	localParcel2	Parcel
        //   108	13	9	localObject	Object
        //   27	77	10	localIBinder	IBinder
        // Exception table:
        //   from	to	target	type
        //   10	17	108	finally
        //   21	29	108	finally
        //   29	91	108	finally
      }
      
      /* Error */
      public final void zza(zzf paramzzf, String paramString1, String paramString2, String paramString3, List<String> paramList1, List<String> paramList2, FavaDiagnosticsEntity paramFavaDiagnosticsEntity)
        throws RemoteException
      {
        // Byte code:
        //   0: invokestatic 27	android/os/Parcel:obtain	()Landroid/os/Parcel;
        //   3: astore 8
        //   5: invokestatic 27	android/os/Parcel:obtain	()Landroid/os/Parcel;
        //   8: astore 9
        //   10: aload 8
        //   12: ldc 29
        //   14: invokevirtual 33	android/os/Parcel:writeInterfaceToken	(Ljava/lang/String;)V
        //   17: aload_1
        //   18: ifnull +103 -> 121
        //   21: aload_1
        //   22: invokeinterface 55 1 0
        //   27: astore 11
        //   29: aload 8
        //   31: aload 11
        //   33: invokevirtual 58	android/os/Parcel:writeStrongBinder	(Landroid/os/IBinder;)V
        //   36: aload 8
        //   38: aload_2
        //   39: invokevirtual 65	android/os/Parcel:writeString	(Ljava/lang/String;)V
        //   42: aload 8
        //   44: aload_3
        //   45: invokevirtual 65	android/os/Parcel:writeString	(Ljava/lang/String;)V
        //   48: aload 8
        //   50: aload 4
        //   52: invokevirtual 65	android/os/Parcel:writeString	(Ljava/lang/String;)V
        //   55: aload 8
        //   57: aload 5
        //   59: invokevirtual 124	android/os/Parcel:writeStringList	(Ljava/util/List;)V
        //   62: aload 8
        //   64: aload 6
        //   66: invokevirtual 124	android/os/Parcel:writeStringList	(Ljava/util/List;)V
        //   69: aload 7
        //   71: ifnull +56 -> 127
        //   74: aload 8
        //   76: iconst_1
        //   77: invokevirtual 62	android/os/Parcel:writeInt	(I)V
        //   80: aload 7
        //   82: aload 8
        //   84: iconst_0
        //   85: invokevirtual 156	com/google/android/gms/common/server/FavaDiagnosticsEntity:writeToParcel	(Landroid/os/Parcel;I)V
        //   88: aload_0
        //   89: getfield 15	com/google/android/gms/people/internal/zzg$zza$zza:zzop	Landroid/os/IBinder;
        //   92: bipush 23
        //   94: aload 8
        //   96: aload 9
        //   98: iconst_0
        //   99: invokeinterface 39 5 0
        //   104: pop
        //   105: aload 9
        //   107: invokevirtual 42	android/os/Parcel:readException	()V
        //   110: aload 9
        //   112: invokevirtual 49	android/os/Parcel:recycle	()V
        //   115: aload 8
        //   117: invokevirtual 49	android/os/Parcel:recycle	()V
        //   120: return
        //   121: aconst_null
        //   122: astore 11
        //   124: goto -95 -> 29
        //   127: aload 8
        //   129: iconst_0
        //   130: invokevirtual 62	android/os/Parcel:writeInt	(I)V
        //   133: goto -45 -> 88
        //   136: astore 10
        //   138: aload 9
        //   140: invokevirtual 49	android/os/Parcel:recycle	()V
        //   143: aload 8
        //   145: invokevirtual 49	android/os/Parcel:recycle	()V
        //   148: aload 10
        //   150: athrow
        // Local variable table:
        //   start	length	slot	name	signature
        //   0	151	0	this	zza
        //   0	151	1	paramzzf	zzf
        //   0	151	2	paramString1	String
        //   0	151	3	paramString2	String
        //   0	151	4	paramString3	String
        //   0	151	5	paramList1	List<String>
        //   0	151	6	paramList2	List<String>
        //   0	151	7	paramFavaDiagnosticsEntity	FavaDiagnosticsEntity
        //   3	141	8	localParcel1	Parcel
        //   8	131	9	localParcel2	Parcel
        //   136	13	10	localObject	Object
        //   27	96	11	localIBinder	IBinder
        // Exception table:
        //   from	to	target	type
        //   10	17	136	finally
        //   21	29	136	finally
        //   29	69	136	finally
        //   74	88	136	finally
        //   88	110	136	finally
        //   127	133	136	finally
      }
      
      /* Error */
      public final void zza(zzf paramzzf, String paramString1, String paramString2, String paramString3, boolean paramBoolean)
        throws RemoteException
      {
        // Byte code:
        //   0: invokestatic 27	android/os/Parcel:obtain	()Landroid/os/Parcel;
        //   3: astore 6
        //   5: invokestatic 27	android/os/Parcel:obtain	()Landroid/os/Parcel;
        //   8: astore 7
        //   10: aload 6
        //   12: ldc 29
        //   14: invokevirtual 33	android/os/Parcel:writeInterfaceToken	(Ljava/lang/String;)V
        //   17: aload_1
        //   18: ifnull +88 -> 106
        //   21: aload_1
        //   22: invokeinterface 55 1 0
        //   27: astore 9
        //   29: aload 6
        //   31: aload 9
        //   33: invokevirtual 58	android/os/Parcel:writeStrongBinder	(Landroid/os/IBinder;)V
        //   36: aload 6
        //   38: aload_2
        //   39: invokevirtual 65	android/os/Parcel:writeString	(Ljava/lang/String;)V
        //   42: aload 6
        //   44: aload_3
        //   45: invokevirtual 65	android/os/Parcel:writeString	(Ljava/lang/String;)V
        //   48: aload 6
        //   50: aload 4
        //   52: invokevirtual 65	android/os/Parcel:writeString	(Ljava/lang/String;)V
        //   55: iconst_0
        //   56: istore 10
        //   58: iload 5
        //   60: ifeq +6 -> 66
        //   63: iconst_1
        //   64: istore 10
        //   66: aload 6
        //   68: iload 10
        //   70: invokevirtual 62	android/os/Parcel:writeInt	(I)V
        //   73: aload_0
        //   74: getfield 15	com/google/android/gms/people/internal/zzg$zza$zza:zzop	Landroid/os/IBinder;
        //   77: bipush 7
        //   79: aload 6
        //   81: aload 7
        //   83: iconst_0
        //   84: invokeinterface 39 5 0
        //   89: pop
        //   90: aload 7
        //   92: invokevirtual 42	android/os/Parcel:readException	()V
        //   95: aload 7
        //   97: invokevirtual 49	android/os/Parcel:recycle	()V
        //   100: aload 6
        //   102: invokevirtual 49	android/os/Parcel:recycle	()V
        //   105: return
        //   106: aconst_null
        //   107: astore 9
        //   109: goto -80 -> 29
        //   112: astore 8
        //   114: aload 7
        //   116: invokevirtual 49	android/os/Parcel:recycle	()V
        //   119: aload 6
        //   121: invokevirtual 49	android/os/Parcel:recycle	()V
        //   124: aload 8
        //   126: athrow
        // Local variable table:
        //   start	length	slot	name	signature
        //   0	127	0	this	zza
        //   0	127	1	paramzzf	zzf
        //   0	127	2	paramString1	String
        //   0	127	3	paramString2	String
        //   0	127	4	paramString3	String
        //   0	127	5	paramBoolean	boolean
        //   3	117	6	localParcel1	Parcel
        //   8	107	7	localParcel2	Parcel
        //   112	13	8	localObject	Object
        //   27	81	9	localIBinder	IBinder
        //   56	13	10	i	int
        // Exception table:
        //   from	to	target	type
        //   10	17	112	finally
        //   21	29	112	finally
        //   29	55	112	finally
        //   66	95	112	finally
      }
      
      /* Error */
      public final void zza(zzf paramzzf, String paramString1, String paramString2, String paramString3, boolean paramBoolean, int paramInt)
        throws RemoteException
      {
        // Byte code:
        //   0: invokestatic 27	android/os/Parcel:obtain	()Landroid/os/Parcel;
        //   3: astore 7
        //   5: invokestatic 27	android/os/Parcel:obtain	()Landroid/os/Parcel;
        //   8: astore 8
        //   10: aload 7
        //   12: ldc 29
        //   14: invokevirtual 33	android/os/Parcel:writeInterfaceToken	(Ljava/lang/String;)V
        //   17: aload_1
        //   18: ifnull +95 -> 113
        //   21: aload_1
        //   22: invokeinterface 55 1 0
        //   27: astore 10
        //   29: aload 7
        //   31: aload 10
        //   33: invokevirtual 58	android/os/Parcel:writeStrongBinder	(Landroid/os/IBinder;)V
        //   36: aload 7
        //   38: aload_2
        //   39: invokevirtual 65	android/os/Parcel:writeString	(Ljava/lang/String;)V
        //   42: aload 7
        //   44: aload_3
        //   45: invokevirtual 65	android/os/Parcel:writeString	(Ljava/lang/String;)V
        //   48: aload 7
        //   50: aload 4
        //   52: invokevirtual 65	android/os/Parcel:writeString	(Ljava/lang/String;)V
        //   55: iconst_0
        //   56: istore 11
        //   58: iload 5
        //   60: ifeq +6 -> 66
        //   63: iconst_1
        //   64: istore 11
        //   66: aload 7
        //   68: iload 11
        //   70: invokevirtual 62	android/os/Parcel:writeInt	(I)V
        //   73: aload 7
        //   75: iload 6
        //   77: invokevirtual 62	android/os/Parcel:writeInt	(I)V
        //   80: aload_0
        //   81: getfield 15	com/google/android/gms/people/internal/zzg$zza$zza:zzop	Landroid/os/IBinder;
        //   84: bipush 9
        //   86: aload 7
        //   88: aload 8
        //   90: iconst_0
        //   91: invokeinterface 39 5 0
        //   96: pop
        //   97: aload 8
        //   99: invokevirtual 42	android/os/Parcel:readException	()V
        //   102: aload 8
        //   104: invokevirtual 49	android/os/Parcel:recycle	()V
        //   107: aload 7
        //   109: invokevirtual 49	android/os/Parcel:recycle	()V
        //   112: return
        //   113: aconst_null
        //   114: astore 10
        //   116: goto -87 -> 29
        //   119: astore 9
        //   121: aload 8
        //   123: invokevirtual 49	android/os/Parcel:recycle	()V
        //   126: aload 7
        //   128: invokevirtual 49	android/os/Parcel:recycle	()V
        //   131: aload 9
        //   133: athrow
        // Local variable table:
        //   start	length	slot	name	signature
        //   0	134	0	this	zza
        //   0	134	1	paramzzf	zzf
        //   0	134	2	paramString1	String
        //   0	134	3	paramString2	String
        //   0	134	4	paramString3	String
        //   0	134	5	paramBoolean	boolean
        //   0	134	6	paramInt	int
        //   3	124	7	localParcel1	Parcel
        //   8	114	8	localParcel2	Parcel
        //   119	13	9	localObject	Object
        //   27	88	10	localIBinder	IBinder
        //   56	13	11	i	int
        // Exception table:
        //   from	to	target	type
        //   10	17	119	finally
        //   21	29	119	finally
        //   29	55	119	finally
        //   66	102	119	finally
      }
      
      /* Error */
      public final void zza(zzf paramzzf, String paramString1, String paramString2, String paramString3, boolean paramBoolean, int paramInt1, int paramInt2)
        throws RemoteException
      {
        // Byte code:
        //   0: invokestatic 27	android/os/Parcel:obtain	()Landroid/os/Parcel;
        //   3: astore 8
        //   5: invokestatic 27	android/os/Parcel:obtain	()Landroid/os/Parcel;
        //   8: astore 9
        //   10: aload 8
        //   12: ldc 29
        //   14: invokevirtual 33	android/os/Parcel:writeInterfaceToken	(Ljava/lang/String;)V
        //   17: aload_1
        //   18: ifnull +103 -> 121
        //   21: aload_1
        //   22: invokeinterface 55 1 0
        //   27: astore 11
        //   29: aload 8
        //   31: aload 11
        //   33: invokevirtual 58	android/os/Parcel:writeStrongBinder	(Landroid/os/IBinder;)V
        //   36: aload 8
        //   38: aload_2
        //   39: invokevirtual 65	android/os/Parcel:writeString	(Ljava/lang/String;)V
        //   42: aload 8
        //   44: aload_3
        //   45: invokevirtual 65	android/os/Parcel:writeString	(Ljava/lang/String;)V
        //   48: aload 8
        //   50: aload 4
        //   52: invokevirtual 65	android/os/Parcel:writeString	(Ljava/lang/String;)V
        //   55: iconst_0
        //   56: istore 12
        //   58: iload 5
        //   60: ifeq +6 -> 66
        //   63: iconst_1
        //   64: istore 12
        //   66: aload 8
        //   68: iload 12
        //   70: invokevirtual 62	android/os/Parcel:writeInt	(I)V
        //   73: aload 8
        //   75: iload 6
        //   77: invokevirtual 62	android/os/Parcel:writeInt	(I)V
        //   80: aload 8
        //   82: iload 7
        //   84: invokevirtual 62	android/os/Parcel:writeInt	(I)V
        //   87: aload_0
        //   88: getfield 15	com/google/android/gms/people/internal/zzg$zza$zza:zzop	Landroid/os/IBinder;
        //   91: sipush 201
        //   94: aload 8
        //   96: aload 9
        //   98: iconst_0
        //   99: invokeinterface 39 5 0
        //   104: pop
        //   105: aload 9
        //   107: invokevirtual 42	android/os/Parcel:readException	()V
        //   110: aload 9
        //   112: invokevirtual 49	android/os/Parcel:recycle	()V
        //   115: aload 8
        //   117: invokevirtual 49	android/os/Parcel:recycle	()V
        //   120: return
        //   121: aconst_null
        //   122: astore 11
        //   124: goto -95 -> 29
        //   127: astore 10
        //   129: aload 9
        //   131: invokevirtual 49	android/os/Parcel:recycle	()V
        //   134: aload 8
        //   136: invokevirtual 49	android/os/Parcel:recycle	()V
        //   139: aload 10
        //   141: athrow
        // Local variable table:
        //   start	length	slot	name	signature
        //   0	142	0	this	zza
        //   0	142	1	paramzzf	zzf
        //   0	142	2	paramString1	String
        //   0	142	3	paramString2	String
        //   0	142	4	paramString3	String
        //   0	142	5	paramBoolean	boolean
        //   0	142	6	paramInt1	int
        //   0	142	7	paramInt2	int
        //   3	132	8	localParcel1	Parcel
        //   8	122	9	localParcel2	Parcel
        //   127	13	10	localObject	Object
        //   27	96	11	localIBinder	IBinder
        //   56	13	12	i	int
        // Exception table:
        //   from	to	target	type
        //   10	17	127	finally
        //   21	29	127	finally
        //   29	55	127	finally
        //   66	110	127	finally
      }
      
      /* Error */
      public final void zza(zzf paramzzf, String paramString, boolean paramBoolean, String[] paramArrayOfString)
        throws RemoteException
      {
        // Byte code:
        //   0: invokestatic 27	android/os/Parcel:obtain	()Landroid/os/Parcel;
        //   3: astore 5
        //   5: invokestatic 27	android/os/Parcel:obtain	()Landroid/os/Parcel;
        //   8: astore 6
        //   10: aload 5
        //   12: ldc 29
        //   14: invokevirtual 33	android/os/Parcel:writeInterfaceToken	(Ljava/lang/String;)V
        //   17: aload_1
        //   18: ifnull +81 -> 99
        //   21: aload_1
        //   22: invokeinterface 55 1 0
        //   27: astore 8
        //   29: aload 5
        //   31: aload 8
        //   33: invokevirtual 58	android/os/Parcel:writeStrongBinder	(Landroid/os/IBinder;)V
        //   36: aload 5
        //   38: aload_2
        //   39: invokevirtual 65	android/os/Parcel:writeString	(Ljava/lang/String;)V
        //   42: iconst_0
        //   43: istore 9
        //   45: iload_3
        //   46: ifeq +6 -> 52
        //   49: iconst_1
        //   50: istore 9
        //   52: aload 5
        //   54: iload 9
        //   56: invokevirtual 62	android/os/Parcel:writeInt	(I)V
        //   59: aload 5
        //   61: aload 4
        //   63: invokevirtual 164	android/os/Parcel:writeStringArray	([Ljava/lang/String;)V
        //   66: aload_0
        //   67: getfield 15	com/google/android/gms/people/internal/zzg$zza$zza:zzop	Landroid/os/IBinder;
        //   70: bipush 10
        //   72: aload 5
        //   74: aload 6
        //   76: iconst_0
        //   77: invokeinterface 39 5 0
        //   82: pop
        //   83: aload 6
        //   85: invokevirtual 42	android/os/Parcel:readException	()V
        //   88: aload 6
        //   90: invokevirtual 49	android/os/Parcel:recycle	()V
        //   93: aload 5
        //   95: invokevirtual 49	android/os/Parcel:recycle	()V
        //   98: return
        //   99: aconst_null
        //   100: astore 8
        //   102: goto -73 -> 29
        //   105: astore 7
        //   107: aload 6
        //   109: invokevirtual 49	android/os/Parcel:recycle	()V
        //   112: aload 5
        //   114: invokevirtual 49	android/os/Parcel:recycle	()V
        //   117: aload 7
        //   119: athrow
        // Local variable table:
        //   start	length	slot	name	signature
        //   0	120	0	this	zza
        //   0	120	1	paramzzf	zzf
        //   0	120	2	paramString	String
        //   0	120	3	paramBoolean	boolean
        //   0	120	4	paramArrayOfString	String[]
        //   3	110	5	localParcel1	Parcel
        //   8	100	6	localParcel2	Parcel
        //   105	13	7	localObject	Object
        //   27	74	8	localIBinder	IBinder
        //   43	12	9	i	int
        // Exception table:
        //   from	to	target	type
        //   10	17	105	finally
        //   21	29	105	finally
        //   29	42	105	finally
        //   52	88	105	finally
      }
      
      /* Error */
      public final void zza(zzf paramzzf, boolean paramBoolean1, boolean paramBoolean2, String paramString1, String paramString2)
        throws RemoteException
      {
        // Byte code:
        //   0: iconst_1
        //   1: istore 6
        //   3: invokestatic 27	android/os/Parcel:obtain	()Landroid/os/Parcel;
        //   6: astore 7
        //   8: invokestatic 27	android/os/Parcel:obtain	()Landroid/os/Parcel;
        //   11: astore 8
        //   13: aload 7
        //   15: ldc 29
        //   17: invokevirtual 33	android/os/Parcel:writeInterfaceToken	(Ljava/lang/String;)V
        //   20: aload_1
        //   21: ifnull +90 -> 111
        //   24: aload_1
        //   25: invokeinterface 55 1 0
        //   30: astore 10
        //   32: aload 7
        //   34: aload 10
        //   36: invokevirtual 58	android/os/Parcel:writeStrongBinder	(Landroid/os/IBinder;)V
        //   39: iload_2
        //   40: ifeq +77 -> 117
        //   43: iload 6
        //   45: istore 11
        //   47: aload 7
        //   49: iload 11
        //   51: invokevirtual 62	android/os/Parcel:writeInt	(I)V
        //   54: iload_3
        //   55: ifeq +68 -> 123
        //   58: aload 7
        //   60: iload 6
        //   62: invokevirtual 62	android/os/Parcel:writeInt	(I)V
        //   65: aload 7
        //   67: aload 4
        //   69: invokevirtual 65	android/os/Parcel:writeString	(Ljava/lang/String;)V
        //   72: aload 7
        //   74: aload 5
        //   76: invokevirtual 65	android/os/Parcel:writeString	(Ljava/lang/String;)V
        //   79: aload_0
        //   80: getfield 15	com/google/android/gms/people/internal/zzg$zza$zza:zzop	Landroid/os/IBinder;
        //   83: iconst_2
        //   84: aload 7
        //   86: aload 8
        //   88: iconst_0
        //   89: invokeinterface 39 5 0
        //   94: pop
        //   95: aload 8
        //   97: invokevirtual 42	android/os/Parcel:readException	()V
        //   100: aload 8
        //   102: invokevirtual 49	android/os/Parcel:recycle	()V
        //   105: aload 7
        //   107: invokevirtual 49	android/os/Parcel:recycle	()V
        //   110: return
        //   111: aconst_null
        //   112: astore 10
        //   114: goto -82 -> 32
        //   117: iconst_0
        //   118: istore 11
        //   120: goto -73 -> 47
        //   123: iconst_0
        //   124: istore 6
        //   126: goto -68 -> 58
        //   129: astore 9
        //   131: aload 8
        //   133: invokevirtual 49	android/os/Parcel:recycle	()V
        //   136: aload 7
        //   138: invokevirtual 49	android/os/Parcel:recycle	()V
        //   141: aload 9
        //   143: athrow
        // Local variable table:
        //   start	length	slot	name	signature
        //   0	144	0	this	zza
        //   0	144	1	paramzzf	zzf
        //   0	144	2	paramBoolean1	boolean
        //   0	144	3	paramBoolean2	boolean
        //   0	144	4	paramString1	String
        //   0	144	5	paramString2	String
        //   1	124	6	i	int
        //   6	131	7	localParcel1	Parcel
        //   11	121	8	localParcel2	Parcel
        //   129	13	9	localObject	Object
        //   30	83	10	localIBinder	IBinder
        //   45	74	11	j	int
        // Exception table:
        //   from	to	target	type
        //   13	20	129	finally
        //   24	32	129	finally
        //   32	39	129	finally
        //   47	54	129	finally
        //   58	100	129	finally
      }
      
      /* Error */
      public final void zza(zzf paramzzf, boolean paramBoolean1, boolean paramBoolean2, String paramString1, String paramString2, int paramInt)
        throws RemoteException
      {
        // Byte code:
        //   0: iconst_1
        //   1: istore 7
        //   3: invokestatic 27	android/os/Parcel:obtain	()Landroid/os/Parcel;
        //   6: astore 8
        //   8: invokestatic 27	android/os/Parcel:obtain	()Landroid/os/Parcel;
        //   11: astore 9
        //   13: aload 8
        //   15: ldc 29
        //   17: invokevirtual 33	android/os/Parcel:writeInterfaceToken	(Ljava/lang/String;)V
        //   20: aload_1
        //   21: ifnull +99 -> 120
        //   24: aload_1
        //   25: invokeinterface 55 1 0
        //   30: astore 11
        //   32: aload 8
        //   34: aload 11
        //   36: invokevirtual 58	android/os/Parcel:writeStrongBinder	(Landroid/os/IBinder;)V
        //   39: iload_2
        //   40: ifeq +86 -> 126
        //   43: iload 7
        //   45: istore 12
        //   47: aload 8
        //   49: iload 12
        //   51: invokevirtual 62	android/os/Parcel:writeInt	(I)V
        //   54: iload_3
        //   55: ifeq +77 -> 132
        //   58: aload 8
        //   60: iload 7
        //   62: invokevirtual 62	android/os/Parcel:writeInt	(I)V
        //   65: aload 8
        //   67: aload 4
        //   69: invokevirtual 65	android/os/Parcel:writeString	(Ljava/lang/String;)V
        //   72: aload 8
        //   74: aload 5
        //   76: invokevirtual 65	android/os/Parcel:writeString	(Ljava/lang/String;)V
        //   79: aload 8
        //   81: iload 6
        //   83: invokevirtual 62	android/os/Parcel:writeInt	(I)V
        //   86: aload_0
        //   87: getfield 15	com/google/android/gms/people/internal/zzg$zza$zza:zzop	Landroid/os/IBinder;
        //   90: sipush 305
        //   93: aload 8
        //   95: aload 9
        //   97: iconst_0
        //   98: invokeinterface 39 5 0
        //   103: pop
        //   104: aload 9
        //   106: invokevirtual 42	android/os/Parcel:readException	()V
        //   109: aload 9
        //   111: invokevirtual 49	android/os/Parcel:recycle	()V
        //   114: aload 8
        //   116: invokevirtual 49	android/os/Parcel:recycle	()V
        //   119: return
        //   120: aconst_null
        //   121: astore 11
        //   123: goto -91 -> 32
        //   126: iconst_0
        //   127: istore 12
        //   129: goto -82 -> 47
        //   132: iconst_0
        //   133: istore 7
        //   135: goto -77 -> 58
        //   138: astore 10
        //   140: aload 9
        //   142: invokevirtual 49	android/os/Parcel:recycle	()V
        //   145: aload 8
        //   147: invokevirtual 49	android/os/Parcel:recycle	()V
        //   150: aload 10
        //   152: athrow
        // Local variable table:
        //   start	length	slot	name	signature
        //   0	153	0	this	zza
        //   0	153	1	paramzzf	zzf
        //   0	153	2	paramBoolean1	boolean
        //   0	153	3	paramBoolean2	boolean
        //   0	153	4	paramString1	String
        //   0	153	5	paramString2	String
        //   0	153	6	paramInt	int
        //   1	133	7	i	int
        //   6	140	8	localParcel1	Parcel
        //   11	130	9	localParcel2	Parcel
        //   138	13	10	localObject	Object
        //   30	92	11	localIBinder	IBinder
        //   45	83	12	j	int
        // Exception table:
        //   from	to	target	type
        //   13	20	138	finally
        //   24	32	138	finally
        //   32	39	138	finally
        //   47	54	138	finally
        //   58	109	138	finally
      }
      
      public final void zzaQ(boolean paramBoolean)
        throws RemoteException
      {
        Parcel localParcel1 = Parcel.obtain();
        Parcel localParcel2 = Parcel.obtain();
        try
        {
          localParcel1.writeInterfaceToken("com.google.android.gms.people.internal.IPeopleService");
          int i = 0;
          if (paramBoolean) {
            i = 1;
          }
          localParcel1.writeInt(i);
          this.zzop.transact(15, localParcel1, localParcel2, 0);
          localParcel2.readException();
          return;
        }
        finally
        {
          localParcel2.recycle();
          localParcel1.recycle();
        }
      }
      
      /* Error */
      public final Bundle zzac(String paramString1, String paramString2)
        throws RemoteException
      {
        // Byte code:
        //   0: invokestatic 27	android/os/Parcel:obtain	()Landroid/os/Parcel;
        //   3: astore_3
        //   4: invokestatic 27	android/os/Parcel:obtain	()Landroid/os/Parcel;
        //   7: astore 4
        //   9: aload_3
        //   10: ldc 29
        //   12: invokevirtual 33	android/os/Parcel:writeInterfaceToken	(Ljava/lang/String;)V
        //   15: aload_3
        //   16: aload_1
        //   17: invokevirtual 65	android/os/Parcel:writeString	(Ljava/lang/String;)V
        //   20: aload_3
        //   21: aload_2
        //   22: invokevirtual 65	android/os/Parcel:writeString	(Ljava/lang/String;)V
        //   25: aload_0
        //   26: getfield 15	com/google/android/gms/people/internal/zzg$zza$zza:zzop	Landroid/os/IBinder;
        //   29: bipush 12
        //   31: aload_3
        //   32: aload 4
        //   34: iconst_0
        //   35: invokeinterface 39 5 0
        //   40: pop
        //   41: aload 4
        //   43: invokevirtual 42	android/os/Parcel:readException	()V
        //   46: aload 4
        //   48: invokevirtual 46	android/os/Parcel:readInt	()I
        //   51: ifeq +30 -> 81
        //   54: getstatic 71	android/os/Bundle:CREATOR	Landroid/os/Parcelable$Creator;
        //   57: aload 4
        //   59: invokeinterface 77 2 0
        //   64: checkcast 67	android/os/Bundle
        //   67: astore 7
        //   69: aload 4
        //   71: invokevirtual 49	android/os/Parcel:recycle	()V
        //   74: aload_3
        //   75: invokevirtual 49	android/os/Parcel:recycle	()V
        //   78: aload 7
        //   80: areturn
        //   81: aconst_null
        //   82: astore 7
        //   84: goto -15 -> 69
        //   87: astore 5
        //   89: aload 4
        //   91: invokevirtual 49	android/os/Parcel:recycle	()V
        //   94: aload_3
        //   95: invokevirtual 49	android/os/Parcel:recycle	()V
        //   98: aload 5
        //   100: athrow
        // Local variable table:
        //   start	length	slot	name	signature
        //   0	101	0	this	zza
        //   0	101	1	paramString1	String
        //   0	101	2	paramString2	String
        //   3	92	3	localParcel1	Parcel
        //   7	83	4	localParcel2	Parcel
        //   87	12	5	localObject	Object
        //   67	16	7	localBundle	Bundle
        // Exception table:
        //   from	to	target	type
        //   9	69	87	finally
      }
      
      /* Error */
      public final Bundle zzad(String paramString1, String paramString2)
        throws RemoteException
      {
        // Byte code:
        //   0: invokestatic 27	android/os/Parcel:obtain	()Landroid/os/Parcel;
        //   3: astore_3
        //   4: invokestatic 27	android/os/Parcel:obtain	()Landroid/os/Parcel;
        //   7: astore 4
        //   9: aload_3
        //   10: ldc 29
        //   12: invokevirtual 33	android/os/Parcel:writeInterfaceToken	(Ljava/lang/String;)V
        //   15: aload_3
        //   16: aload_1
        //   17: invokevirtual 65	android/os/Parcel:writeString	(Ljava/lang/String;)V
        //   20: aload_3
        //   21: aload_2
        //   22: invokevirtual 65	android/os/Parcel:writeString	(Ljava/lang/String;)V
        //   25: aload_0
        //   26: getfield 15	com/google/android/gms/people/internal/zzg$zza$zza:zzop	Landroid/os/IBinder;
        //   29: bipush 17
        //   31: aload_3
        //   32: aload 4
        //   34: iconst_0
        //   35: invokeinterface 39 5 0
        //   40: pop
        //   41: aload 4
        //   43: invokevirtual 42	android/os/Parcel:readException	()V
        //   46: aload 4
        //   48: invokevirtual 46	android/os/Parcel:readInt	()I
        //   51: ifeq +30 -> 81
        //   54: getstatic 71	android/os/Bundle:CREATOR	Landroid/os/Parcelable$Creator;
        //   57: aload 4
        //   59: invokeinterface 77 2 0
        //   64: checkcast 67	android/os/Bundle
        //   67: astore 7
        //   69: aload 4
        //   71: invokevirtual 49	android/os/Parcel:recycle	()V
        //   74: aload_3
        //   75: invokevirtual 49	android/os/Parcel:recycle	()V
        //   78: aload 7
        //   80: areturn
        //   81: aconst_null
        //   82: astore 7
        //   84: goto -15 -> 69
        //   87: astore 5
        //   89: aload 4
        //   91: invokevirtual 49	android/os/Parcel:recycle	()V
        //   94: aload_3
        //   95: invokevirtual 49	android/os/Parcel:recycle	()V
        //   98: aload 5
        //   100: athrow
        // Local variable table:
        //   start	length	slot	name	signature
        //   0	101	0	this	zza
        //   0	101	1	paramString1	String
        //   0	101	2	paramString2	String
        //   3	92	3	localParcel1	Parcel
        //   7	83	4	localParcel2	Parcel
        //   87	12	5	localObject	Object
        //   67	16	7	localBundle	Bundle
        // Exception table:
        //   from	to	target	type
        //   9	69	87	finally
      }
      
      /* Error */
      public final zzq zzb(zzf paramzzf, long paramLong, boolean paramBoolean)
        throws RemoteException
      {
        // Byte code:
        //   0: invokestatic 27	android/os/Parcel:obtain	()Landroid/os/Parcel;
        //   3: astore 5
        //   5: invokestatic 27	android/os/Parcel:obtain	()Landroid/os/Parcel;
        //   8: astore 6
        //   10: aload 5
        //   12: ldc 29
        //   14: invokevirtual 33	android/os/Parcel:writeInterfaceToken	(Ljava/lang/String;)V
        //   17: aload_1
        //   18: ifnull +88 -> 106
        //   21: aload_1
        //   22: invokeinterface 55 1 0
        //   27: astore 8
        //   29: aload 5
        //   31: aload 8
        //   33: invokevirtual 58	android/os/Parcel:writeStrongBinder	(Landroid/os/IBinder;)V
        //   36: aload 5
        //   38: lload_2
        //   39: invokevirtual 82	android/os/Parcel:writeLong	(J)V
        //   42: iconst_0
        //   43: istore 9
        //   45: iload 4
        //   47: ifeq +6 -> 53
        //   50: iconst_1
        //   51: istore 9
        //   53: aload 5
        //   55: iload 9
        //   57: invokevirtual 62	android/os/Parcel:writeInt	(I)V
        //   60: aload_0
        //   61: getfield 15	com/google/android/gms/people/internal/zzg$zza$zza:zzop	Landroid/os/IBinder;
        //   64: sipush 503
        //   67: aload 5
        //   69: aload 6
        //   71: iconst_0
        //   72: invokeinterface 39 5 0
        //   77: pop
        //   78: aload 6
        //   80: invokevirtual 42	android/os/Parcel:readException	()V
        //   83: aload 6
        //   85: invokevirtual 93	android/os/Parcel:readStrongBinder	()Landroid/os/IBinder;
        //   88: invokestatic 99	com/google/android/gms/common/internal/zzq$zza:zzck	(Landroid/os/IBinder;)Lcom/google/android/gms/common/internal/zzq;
        //   91: astore 11
        //   93: aload 6
        //   95: invokevirtual 49	android/os/Parcel:recycle	()V
        //   98: aload 5
        //   100: invokevirtual 49	android/os/Parcel:recycle	()V
        //   103: aload 11
        //   105: areturn
        //   106: aconst_null
        //   107: astore 8
        //   109: goto -80 -> 29
        //   112: astore 7
        //   114: aload 6
        //   116: invokevirtual 49	android/os/Parcel:recycle	()V
        //   119: aload 5
        //   121: invokevirtual 49	android/os/Parcel:recycle	()V
        //   124: aload 7
        //   126: athrow
        // Local variable table:
        //   start	length	slot	name	signature
        //   0	127	0	this	zza
        //   0	127	1	paramzzf	zzf
        //   0	127	2	paramLong	long
        //   0	127	4	paramBoolean	boolean
        //   3	117	5	localParcel1	Parcel
        //   8	107	6	localParcel2	Parcel
        //   112	13	7	localObject	Object
        //   27	81	8	localIBinder	IBinder
        //   43	13	9	i	int
        //   91	13	11	localzzq	zzq
        // Exception table:
        //   from	to	target	type
        //   10	17	112	finally
        //   21	29	112	finally
        //   29	42	112	finally
        //   53	93	112	finally
      }
      
      /* Error */
      public final zzq zzb(zzf paramzzf, String paramString)
        throws RemoteException
      {
        // Byte code:
        //   0: invokestatic 27	android/os/Parcel:obtain	()Landroid/os/Parcel;
        //   3: astore_3
        //   4: invokestatic 27	android/os/Parcel:obtain	()Landroid/os/Parcel;
        //   7: astore 4
        //   9: aload_3
        //   10: ldc 29
        //   12: invokevirtual 33	android/os/Parcel:writeInterfaceToken	(Ljava/lang/String;)V
        //   15: aload_1
        //   16: ifnull +66 -> 82
        //   19: aload_1
        //   20: invokeinterface 55 1 0
        //   25: astore 6
        //   27: aload_3
        //   28: aload 6
        //   30: invokevirtual 58	android/os/Parcel:writeStrongBinder	(Landroid/os/IBinder;)V
        //   33: aload_3
        //   34: aload_2
        //   35: invokevirtual 65	android/os/Parcel:writeString	(Ljava/lang/String;)V
        //   38: aload_0
        //   39: getfield 15	com/google/android/gms/people/internal/zzg$zza$zza:zzop	Landroid/os/IBinder;
        //   42: sipush 504
        //   45: aload_3
        //   46: aload 4
        //   48: iconst_0
        //   49: invokeinterface 39 5 0
        //   54: pop
        //   55: aload 4
        //   57: invokevirtual 42	android/os/Parcel:readException	()V
        //   60: aload 4
        //   62: invokevirtual 93	android/os/Parcel:readStrongBinder	()Landroid/os/IBinder;
        //   65: invokestatic 99	com/google/android/gms/common/internal/zzq$zza:zzck	(Landroid/os/IBinder;)Lcom/google/android/gms/common/internal/zzq;
        //   68: astore 8
        //   70: aload 4
        //   72: invokevirtual 49	android/os/Parcel:recycle	()V
        //   75: aload_3
        //   76: invokevirtual 49	android/os/Parcel:recycle	()V
        //   79: aload 8
        //   81: areturn
        //   82: aconst_null
        //   83: astore 6
        //   85: goto -58 -> 27
        //   88: astore 5
        //   90: aload 4
        //   92: invokevirtual 49	android/os/Parcel:recycle	()V
        //   95: aload_3
        //   96: invokevirtual 49	android/os/Parcel:recycle	()V
        //   99: aload 5
        //   101: athrow
        // Local variable table:
        //   start	length	slot	name	signature
        //   0	102	0	this	zza
        //   0	102	1	paramzzf	zzf
        //   0	102	2	paramString	String
        //   3	93	3	localParcel1	Parcel
        //   7	84	4	localParcel2	Parcel
        //   88	12	5	localObject	Object
        //   25	59	6	localIBinder	IBinder
        //   68	12	8	localzzq	zzq
        // Exception table:
        //   from	to	target	type
        //   9	15	88	finally
        //   19	27	88	finally
        //   27	70	88	finally
      }
      
      /* Error */
      public final zzq zzb(zzf paramzzf, String paramString, int paramInt1, int paramInt2)
        throws RemoteException
      {
        // Byte code:
        //   0: invokestatic 27	android/os/Parcel:obtain	()Landroid/os/Parcel;
        //   3: astore 5
        //   5: invokestatic 27	android/os/Parcel:obtain	()Landroid/os/Parcel;
        //   8: astore 6
        //   10: aload 5
        //   12: ldc 29
        //   14: invokevirtual 33	android/os/Parcel:writeInterfaceToken	(Ljava/lang/String;)V
        //   17: aload_1
        //   18: ifnull +83 -> 101
        //   21: aload_1
        //   22: invokeinterface 55 1 0
        //   27: astore 8
        //   29: aload 5
        //   31: aload 8
        //   33: invokevirtual 58	android/os/Parcel:writeStrongBinder	(Landroid/os/IBinder;)V
        //   36: aload 5
        //   38: aload_2
        //   39: invokevirtual 65	android/os/Parcel:writeString	(Ljava/lang/String;)V
        //   42: aload 5
        //   44: iload_3
        //   45: invokevirtual 62	android/os/Parcel:writeInt	(I)V
        //   48: aload 5
        //   50: iload 4
        //   52: invokevirtual 62	android/os/Parcel:writeInt	(I)V
        //   55: aload_0
        //   56: getfield 15	com/google/android/gms/people/internal/zzg$zza$zza:zzop	Landroid/os/IBinder;
        //   59: sipush 502
        //   62: aload 5
        //   64: aload 6
        //   66: iconst_0
        //   67: invokeinterface 39 5 0
        //   72: pop
        //   73: aload 6
        //   75: invokevirtual 42	android/os/Parcel:readException	()V
        //   78: aload 6
        //   80: invokevirtual 93	android/os/Parcel:readStrongBinder	()Landroid/os/IBinder;
        //   83: invokestatic 99	com/google/android/gms/common/internal/zzq$zza:zzck	(Landroid/os/IBinder;)Lcom/google/android/gms/common/internal/zzq;
        //   86: astore 10
        //   88: aload 6
        //   90: invokevirtual 49	android/os/Parcel:recycle	()V
        //   93: aload 5
        //   95: invokevirtual 49	android/os/Parcel:recycle	()V
        //   98: aload 10
        //   100: areturn
        //   101: aconst_null
        //   102: astore 8
        //   104: goto -75 -> 29
        //   107: astore 7
        //   109: aload 6
        //   111: invokevirtual 49	android/os/Parcel:recycle	()V
        //   114: aload 5
        //   116: invokevirtual 49	android/os/Parcel:recycle	()V
        //   119: aload 7
        //   121: athrow
        // Local variable table:
        //   start	length	slot	name	signature
        //   0	122	0	this	zza
        //   0	122	1	paramzzf	zzf
        //   0	122	2	paramString	String
        //   0	122	3	paramInt1	int
        //   0	122	4	paramInt2	int
        //   3	112	5	localParcel1	Parcel
        //   8	102	6	localParcel2	Parcel
        //   107	13	7	localObject	Object
        //   27	76	8	localIBinder	IBinder
        //   86	13	10	localzzq	zzq
        // Exception table:
        //   from	to	target	type
        //   10	17	107	finally
        //   21	29	107	finally
        //   29	88	107	finally
      }
      
      /* Error */
      public final zzq zzb(zzf paramzzf, String paramString1, String paramString2, int paramInt1, int paramInt2)
        throws RemoteException
      {
        // Byte code:
        //   0: invokestatic 27	android/os/Parcel:obtain	()Landroid/os/Parcel;
        //   3: astore 6
        //   5: invokestatic 27	android/os/Parcel:obtain	()Landroid/os/Parcel;
        //   8: astore 7
        //   10: aload 6
        //   12: ldc 29
        //   14: invokevirtual 33	android/os/Parcel:writeInterfaceToken	(Ljava/lang/String;)V
        //   17: aload_1
        //   18: ifnull +90 -> 108
        //   21: aload_1
        //   22: invokeinterface 55 1 0
        //   27: astore 9
        //   29: aload 6
        //   31: aload 9
        //   33: invokevirtual 58	android/os/Parcel:writeStrongBinder	(Landroid/os/IBinder;)V
        //   36: aload 6
        //   38: aload_2
        //   39: invokevirtual 65	android/os/Parcel:writeString	(Ljava/lang/String;)V
        //   42: aload 6
        //   44: aload_3
        //   45: invokevirtual 65	android/os/Parcel:writeString	(Ljava/lang/String;)V
        //   48: aload 6
        //   50: iload 4
        //   52: invokevirtual 62	android/os/Parcel:writeInt	(I)V
        //   55: aload 6
        //   57: iload 5
        //   59: invokevirtual 62	android/os/Parcel:writeInt	(I)V
        //   62: aload_0
        //   63: getfield 15	com/google/android/gms/people/internal/zzg$zza$zza:zzop	Landroid/os/IBinder;
        //   66: sipush 505
        //   69: aload 6
        //   71: aload 7
        //   73: iconst_0
        //   74: invokeinterface 39 5 0
        //   79: pop
        //   80: aload 7
        //   82: invokevirtual 42	android/os/Parcel:readException	()V
        //   85: aload 7
        //   87: invokevirtual 93	android/os/Parcel:readStrongBinder	()Landroid/os/IBinder;
        //   90: invokestatic 99	com/google/android/gms/common/internal/zzq$zza:zzck	(Landroid/os/IBinder;)Lcom/google/android/gms/common/internal/zzq;
        //   93: astore 11
        //   95: aload 7
        //   97: invokevirtual 49	android/os/Parcel:recycle	()V
        //   100: aload 6
        //   102: invokevirtual 49	android/os/Parcel:recycle	()V
        //   105: aload 11
        //   107: areturn
        //   108: aconst_null
        //   109: astore 9
        //   111: goto -82 -> 29
        //   114: astore 8
        //   116: aload 7
        //   118: invokevirtual 49	android/os/Parcel:recycle	()V
        //   121: aload 6
        //   123: invokevirtual 49	android/os/Parcel:recycle	()V
        //   126: aload 8
        //   128: athrow
        // Local variable table:
        //   start	length	slot	name	signature
        //   0	129	0	this	zza
        //   0	129	1	paramzzf	zzf
        //   0	129	2	paramString1	String
        //   0	129	3	paramString2	String
        //   0	129	4	paramInt1	int
        //   0	129	5	paramInt2	int
        //   3	119	6	localParcel1	Parcel
        //   8	109	7	localParcel2	Parcel
        //   114	13	8	localObject	Object
        //   27	83	9	localIBinder	IBinder
        //   93	13	11	localzzq	zzq
        // Exception table:
        //   from	to	target	type
        //   10	17	114	finally
        //   21	29	114	finally
        //   29	95	114	finally
      }
      
      /* Error */
      public final void zzb(zzf paramzzf, Bundle paramBundle)
        throws RemoteException
      {
        // Byte code:
        //   0: invokestatic 27	android/os/Parcel:obtain	()Landroid/os/Parcel;
        //   3: astore_3
        //   4: invokestatic 27	android/os/Parcel:obtain	()Landroid/os/Parcel;
        //   7: astore 4
        //   9: aload_3
        //   10: ldc 29
        //   12: invokevirtual 33	android/os/Parcel:writeInterfaceToken	(Ljava/lang/String;)V
        //   15: aload_1
        //   16: ifnull +64 -> 80
        //   19: aload_1
        //   20: invokeinterface 55 1 0
        //   25: astore 6
        //   27: aload_3
        //   28: aload 6
        //   30: invokevirtual 58	android/os/Parcel:writeStrongBinder	(Landroid/os/IBinder;)V
        //   33: aload_2
        //   34: ifnull +52 -> 86
        //   37: aload_3
        //   38: iconst_1
        //   39: invokevirtual 62	android/os/Parcel:writeInt	(I)V
        //   42: aload_2
        //   43: aload_3
        //   44: iconst_0
        //   45: invokevirtual 116	android/os/Bundle:writeToParcel	(Landroid/os/Parcel;I)V
        //   48: aload_0
        //   49: getfield 15	com/google/android/gms/people/internal/zzg$zza$zza:zzop	Landroid/os/IBinder;
        //   52: sipush 304
        //   55: aload_3
        //   56: aload 4
        //   58: iconst_0
        //   59: invokeinterface 39 5 0
        //   64: pop
        //   65: aload 4
        //   67: invokevirtual 42	android/os/Parcel:readException	()V
        //   70: aload 4
        //   72: invokevirtual 49	android/os/Parcel:recycle	()V
        //   75: aload_3
        //   76: invokevirtual 49	android/os/Parcel:recycle	()V
        //   79: return
        //   80: aconst_null
        //   81: astore 6
        //   83: goto -56 -> 27
        //   86: aload_3
        //   87: iconst_0
        //   88: invokevirtual 62	android/os/Parcel:writeInt	(I)V
        //   91: goto -43 -> 48
        //   94: astore 5
        //   96: aload 4
        //   98: invokevirtual 49	android/os/Parcel:recycle	()V
        //   101: aload_3
        //   102: invokevirtual 49	android/os/Parcel:recycle	()V
        //   105: aload 5
        //   107: athrow
        // Local variable table:
        //   start	length	slot	name	signature
        //   0	108	0	this	zza
        //   0	108	1	paramzzf	zzf
        //   0	108	2	paramBundle	Bundle
        //   3	99	3	localParcel1	Parcel
        //   7	90	4	localParcel2	Parcel
        //   94	12	5	localObject	Object
        //   25	57	6	localIBinder	IBinder
        // Exception table:
        //   from	to	target	type
        //   9	15	94	finally
        //   19	27	94	finally
        //   27	33	94	finally
        //   37	48	94	finally
        //   48	70	94	finally
        //   86	91	94	finally
      }
      
      /* Error */
      public final void zzb(zzf paramzzf, String paramString1, String paramString2)
        throws RemoteException
      {
        // Byte code:
        //   0: invokestatic 27	android/os/Parcel:obtain	()Landroid/os/Parcel;
        //   3: astore 4
        //   5: invokestatic 27	android/os/Parcel:obtain	()Landroid/os/Parcel;
        //   8: astore 5
        //   10: aload 4
        //   12: ldc 29
        //   14: invokevirtual 33	android/os/Parcel:writeInterfaceToken	(Ljava/lang/String;)V
        //   17: aload_1
        //   18: ifnull +63 -> 81
        //   21: aload_1
        //   22: invokeinterface 55 1 0
        //   27: astore 7
        //   29: aload 4
        //   31: aload 7
        //   33: invokevirtual 58	android/os/Parcel:writeStrongBinder	(Landroid/os/IBinder;)V
        //   36: aload 4
        //   38: aload_2
        //   39: invokevirtual 65	android/os/Parcel:writeString	(Ljava/lang/String;)V
        //   42: aload 4
        //   44: aload_3
        //   45: invokevirtual 65	android/os/Parcel:writeString	(Ljava/lang/String;)V
        //   48: aload_0
        //   49: getfield 15	com/google/android/gms/people/internal/zzg$zza$zza:zzop	Landroid/os/IBinder;
        //   52: bipush 101
        //   54: aload 4
        //   56: aload 5
        //   58: iconst_0
        //   59: invokeinterface 39 5 0
        //   64: pop
        //   65: aload 5
        //   67: invokevirtual 42	android/os/Parcel:readException	()V
        //   70: aload 5
        //   72: invokevirtual 49	android/os/Parcel:recycle	()V
        //   75: aload 4
        //   77: invokevirtual 49	android/os/Parcel:recycle	()V
        //   80: return
        //   81: aconst_null
        //   82: astore 7
        //   84: goto -55 -> 29
        //   87: astore 6
        //   89: aload 5
        //   91: invokevirtual 49	android/os/Parcel:recycle	()V
        //   94: aload 4
        //   96: invokevirtual 49	android/os/Parcel:recycle	()V
        //   99: aload 6
        //   101: athrow
        // Local variable table:
        //   start	length	slot	name	signature
        //   0	102	0	this	zza
        //   0	102	1	paramzzf	zzf
        //   0	102	2	paramString1	String
        //   0	102	3	paramString2	String
        //   3	92	4	localParcel1	Parcel
        //   8	82	5	localParcel2	Parcel
        //   87	13	6	localObject	Object
        //   27	56	7	localIBinder	IBinder
        // Exception table:
        //   from	to	target	type
        //   10	17	87	finally
        //   21	29	87	finally
        //   29	70	87	finally
      }
      
      /* Error */
      public final void zzb(zzf paramzzf, String paramString1, String paramString2, int paramInt)
        throws RemoteException
      {
        // Byte code:
        //   0: invokestatic 27	android/os/Parcel:obtain	()Landroid/os/Parcel;
        //   3: astore 5
        //   5: invokestatic 27	android/os/Parcel:obtain	()Landroid/os/Parcel;
        //   8: astore 6
        //   10: aload 5
        //   12: ldc 29
        //   14: invokevirtual 33	android/os/Parcel:writeInterfaceToken	(Ljava/lang/String;)V
        //   17: aload_1
        //   18: ifnull +71 -> 89
        //   21: aload_1
        //   22: invokeinterface 55 1 0
        //   27: astore 8
        //   29: aload 5
        //   31: aload 8
        //   33: invokevirtual 58	android/os/Parcel:writeStrongBinder	(Landroid/os/IBinder;)V
        //   36: aload 5
        //   38: aload_2
        //   39: invokevirtual 65	android/os/Parcel:writeString	(Ljava/lang/String;)V
        //   42: aload 5
        //   44: aload_3
        //   45: invokevirtual 65	android/os/Parcel:writeString	(Ljava/lang/String;)V
        //   48: aload 5
        //   50: iload 4
        //   52: invokevirtual 62	android/os/Parcel:writeInt	(I)V
        //   55: aload_0
        //   56: getfield 15	com/google/android/gms/people/internal/zzg$zza$zza:zzop	Landroid/os/IBinder;
        //   59: sipush 301
        //   62: aload 5
        //   64: aload 6
        //   66: iconst_0
        //   67: invokeinterface 39 5 0
        //   72: pop
        //   73: aload 6
        //   75: invokevirtual 42	android/os/Parcel:readException	()V
        //   78: aload 6
        //   80: invokevirtual 49	android/os/Parcel:recycle	()V
        //   83: aload 5
        //   85: invokevirtual 49	android/os/Parcel:recycle	()V
        //   88: return
        //   89: aconst_null
        //   90: astore 8
        //   92: goto -63 -> 29
        //   95: astore 7
        //   97: aload 6
        //   99: invokevirtual 49	android/os/Parcel:recycle	()V
        //   102: aload 5
        //   104: invokevirtual 49	android/os/Parcel:recycle	()V
        //   107: aload 7
        //   109: athrow
        // Local variable table:
        //   start	length	slot	name	signature
        //   0	110	0	this	zza
        //   0	110	1	paramzzf	zzf
        //   0	110	2	paramString1	String
        //   0	110	3	paramString2	String
        //   0	110	4	paramInt	int
        //   3	100	5	localParcel1	Parcel
        //   8	90	6	localParcel2	Parcel
        //   95	13	7	localObject	Object
        //   27	64	8	localIBinder	IBinder
        // Exception table:
        //   from	to	target	type
        //   10	17	95	finally
        //   21	29	95	finally
        //   29	78	95	finally
      }
      
      /* Error */
      public final void zzb(zzf paramzzf, String paramString1, String paramString2, String paramString3, int paramInt, String paramString4)
        throws RemoteException
      {
        // Byte code:
        //   0: invokestatic 27	android/os/Parcel:obtain	()Landroid/os/Parcel;
        //   3: astore 7
        //   5: invokestatic 27	android/os/Parcel:obtain	()Landroid/os/Parcel;
        //   8: astore 8
        //   10: aload 7
        //   12: ldc 29
        //   14: invokevirtual 33	android/os/Parcel:writeInterfaceToken	(Ljava/lang/String;)V
        //   17: aload_1
        //   18: ifnull +84 -> 102
        //   21: aload_1
        //   22: invokeinterface 55 1 0
        //   27: astore 10
        //   29: aload 7
        //   31: aload 10
        //   33: invokevirtual 58	android/os/Parcel:writeStrongBinder	(Landroid/os/IBinder;)V
        //   36: aload 7
        //   38: aload_2
        //   39: invokevirtual 65	android/os/Parcel:writeString	(Ljava/lang/String;)V
        //   42: aload 7
        //   44: aload_3
        //   45: invokevirtual 65	android/os/Parcel:writeString	(Ljava/lang/String;)V
        //   48: aload 7
        //   50: aload 4
        //   52: invokevirtual 65	android/os/Parcel:writeString	(Ljava/lang/String;)V
        //   55: aload 7
        //   57: iload 5
        //   59: invokevirtual 62	android/os/Parcel:writeInt	(I)V
        //   62: aload 7
        //   64: aload 6
        //   66: invokevirtual 65	android/os/Parcel:writeString	(Ljava/lang/String;)V
        //   69: aload_0
        //   70: getfield 15	com/google/android/gms/people/internal/zzg$zza$zza:zzop	Landroid/os/IBinder;
        //   73: bipush 22
        //   75: aload 7
        //   77: aload 8
        //   79: iconst_0
        //   80: invokeinterface 39 5 0
        //   85: pop
        //   86: aload 8
        //   88: invokevirtual 42	android/os/Parcel:readException	()V
        //   91: aload 8
        //   93: invokevirtual 49	android/os/Parcel:recycle	()V
        //   96: aload 7
        //   98: invokevirtual 49	android/os/Parcel:recycle	()V
        //   101: return
        //   102: aconst_null
        //   103: astore 10
        //   105: goto -76 -> 29
        //   108: astore 9
        //   110: aload 8
        //   112: invokevirtual 49	android/os/Parcel:recycle	()V
        //   115: aload 7
        //   117: invokevirtual 49	android/os/Parcel:recycle	()V
        //   120: aload 9
        //   122: athrow
        // Local variable table:
        //   start	length	slot	name	signature
        //   0	123	0	this	zza
        //   0	123	1	paramzzf	zzf
        //   0	123	2	paramString1	String
        //   0	123	3	paramString2	String
        //   0	123	4	paramString3	String
        //   0	123	5	paramInt	int
        //   0	123	6	paramString4	String
        //   3	113	7	localParcel1	Parcel
        //   8	103	8	localParcel2	Parcel
        //   108	13	9	localObject	Object
        //   27	77	10	localIBinder	IBinder
        // Exception table:
        //   from	to	target	type
        //   10	17	108	finally
        //   21	29	108	finally
        //   29	91	108	finally
      }
      
      /* Error */
      public final void zzb(zzf paramzzf, String paramString1, String paramString2, String paramString3, boolean paramBoolean)
        throws RemoteException
      {
        // Byte code:
        //   0: invokestatic 27	android/os/Parcel:obtain	()Landroid/os/Parcel;
        //   3: astore 6
        //   5: invokestatic 27	android/os/Parcel:obtain	()Landroid/os/Parcel;
        //   8: astore 7
        //   10: aload 6
        //   12: ldc 29
        //   14: invokevirtual 33	android/os/Parcel:writeInterfaceToken	(Ljava/lang/String;)V
        //   17: aload_1
        //   18: ifnull +89 -> 107
        //   21: aload_1
        //   22: invokeinterface 55 1 0
        //   27: astore 9
        //   29: aload 6
        //   31: aload 9
        //   33: invokevirtual 58	android/os/Parcel:writeStrongBinder	(Landroid/os/IBinder;)V
        //   36: aload 6
        //   38: aload_2
        //   39: invokevirtual 65	android/os/Parcel:writeString	(Ljava/lang/String;)V
        //   42: aload 6
        //   44: aload_3
        //   45: invokevirtual 65	android/os/Parcel:writeString	(Ljava/lang/String;)V
        //   48: aload 6
        //   50: aload 4
        //   52: invokevirtual 65	android/os/Parcel:writeString	(Ljava/lang/String;)V
        //   55: iconst_0
        //   56: istore 10
        //   58: iload 5
        //   60: ifeq +6 -> 66
        //   63: iconst_1
        //   64: istore 10
        //   66: aload 6
        //   68: iload 10
        //   70: invokevirtual 62	android/os/Parcel:writeInt	(I)V
        //   73: aload_0
        //   74: getfield 15	com/google/android/gms/people/internal/zzg$zza$zza:zzop	Landroid/os/IBinder;
        //   77: sipush 603
        //   80: aload 6
        //   82: aload 7
        //   84: iconst_0
        //   85: invokeinterface 39 5 0
        //   90: pop
        //   91: aload 7
        //   93: invokevirtual 42	android/os/Parcel:readException	()V
        //   96: aload 7
        //   98: invokevirtual 49	android/os/Parcel:recycle	()V
        //   101: aload 6
        //   103: invokevirtual 49	android/os/Parcel:recycle	()V
        //   106: return
        //   107: aconst_null
        //   108: astore 9
        //   110: goto -81 -> 29
        //   113: astore 8
        //   115: aload 7
        //   117: invokevirtual 49	android/os/Parcel:recycle	()V
        //   120: aload 6
        //   122: invokevirtual 49	android/os/Parcel:recycle	()V
        //   125: aload 8
        //   127: athrow
        // Local variable table:
        //   start	length	slot	name	signature
        //   0	128	0	this	zza
        //   0	128	1	paramzzf	zzf
        //   0	128	2	paramString1	String
        //   0	128	3	paramString2	String
        //   0	128	4	paramString3	String
        //   0	128	5	paramBoolean	boolean
        //   3	118	6	localParcel1	Parcel
        //   8	108	7	localParcel2	Parcel
        //   113	13	8	localObject	Object
        //   27	82	9	localIBinder	IBinder
        //   56	13	10	i	int
        // Exception table:
        //   from	to	target	type
        //   10	17	113	finally
        //   21	29	113	finally
        //   29	55	113	finally
        //   66	96	113	finally
      }
      
      /* Error */
      public final Bundle zzc(String paramString1, String paramString2, long paramLong)
        throws RemoteException
      {
        // Byte code:
        //   0: invokestatic 27	android/os/Parcel:obtain	()Landroid/os/Parcel;
        //   3: astore 5
        //   5: invokestatic 27	android/os/Parcel:obtain	()Landroid/os/Parcel;
        //   8: astore 6
        //   10: aload 5
        //   12: ldc 29
        //   14: invokevirtual 33	android/os/Parcel:writeInterfaceToken	(Ljava/lang/String;)V
        //   17: aload 5
        //   19: aload_1
        //   20: invokevirtual 65	android/os/Parcel:writeString	(Ljava/lang/String;)V
        //   23: aload 5
        //   25: aload_2
        //   26: invokevirtual 65	android/os/Parcel:writeString	(Ljava/lang/String;)V
        //   29: aload 5
        //   31: lload_3
        //   32: invokevirtual 82	android/os/Parcel:writeLong	(J)V
        //   35: aload_0
        //   36: getfield 15	com/google/android/gms/people/internal/zzg$zza$zza:zzop	Landroid/os/IBinder;
        //   39: bipush 20
        //   41: aload 5
        //   43: aload 6
        //   45: iconst_0
        //   46: invokeinterface 39 5 0
        //   51: pop
        //   52: aload 6
        //   54: invokevirtual 42	android/os/Parcel:readException	()V
        //   57: aload 6
        //   59: invokevirtual 46	android/os/Parcel:readInt	()I
        //   62: ifeq +31 -> 93
        //   65: getstatic 71	android/os/Bundle:CREATOR	Landroid/os/Parcelable$Creator;
        //   68: aload 6
        //   70: invokeinterface 77 2 0
        //   75: checkcast 67	android/os/Bundle
        //   78: astore 9
        //   80: aload 6
        //   82: invokevirtual 49	android/os/Parcel:recycle	()V
        //   85: aload 5
        //   87: invokevirtual 49	android/os/Parcel:recycle	()V
        //   90: aload 9
        //   92: areturn
        //   93: aconst_null
        //   94: astore 9
        //   96: goto -16 -> 80
        //   99: astore 7
        //   101: aload 6
        //   103: invokevirtual 49	android/os/Parcel:recycle	()V
        //   106: aload 5
        //   108: invokevirtual 49	android/os/Parcel:recycle	()V
        //   111: aload 7
        //   113: athrow
        // Local variable table:
        //   start	length	slot	name	signature
        //   0	114	0	this	zza
        //   0	114	1	paramString1	String
        //   0	114	2	paramString2	String
        //   0	114	3	paramLong	long
        //   3	104	5	localParcel1	Parcel
        //   8	94	6	localParcel2	Parcel
        //   99	13	7	localObject	Object
        //   78	17	9	localBundle	Bundle
        // Exception table:
        //   from	to	target	type
        //   10	80	99	finally
      }
      
      /* Error */
      public final zzq zzc(zzf paramzzf, String paramString1, String paramString2, int paramInt)
        throws RemoteException
      {
        // Byte code:
        //   0: invokestatic 27	android/os/Parcel:obtain	()Landroid/os/Parcel;
        //   3: astore 5
        //   5: invokestatic 27	android/os/Parcel:obtain	()Landroid/os/Parcel;
        //   8: astore 6
        //   10: aload 5
        //   12: ldc 29
        //   14: invokevirtual 33	android/os/Parcel:writeInterfaceToken	(Ljava/lang/String;)V
        //   17: aload_1
        //   18: ifnull +83 -> 101
        //   21: aload_1
        //   22: invokeinterface 55 1 0
        //   27: astore 8
        //   29: aload 5
        //   31: aload 8
        //   33: invokevirtual 58	android/os/Parcel:writeStrongBinder	(Landroid/os/IBinder;)V
        //   36: aload 5
        //   38: aload_2
        //   39: invokevirtual 65	android/os/Parcel:writeString	(Ljava/lang/String;)V
        //   42: aload 5
        //   44: aload_3
        //   45: invokevirtual 65	android/os/Parcel:writeString	(Ljava/lang/String;)V
        //   48: aload 5
        //   50: iload 4
        //   52: invokevirtual 62	android/os/Parcel:writeInt	(I)V
        //   55: aload_0
        //   56: getfield 15	com/google/android/gms/people/internal/zzg$zza$zza:zzop	Landroid/os/IBinder;
        //   59: sipush 506
        //   62: aload 5
        //   64: aload 6
        //   66: iconst_0
        //   67: invokeinterface 39 5 0
        //   72: pop
        //   73: aload 6
        //   75: invokevirtual 42	android/os/Parcel:readException	()V
        //   78: aload 6
        //   80: invokevirtual 93	android/os/Parcel:readStrongBinder	()Landroid/os/IBinder;
        //   83: invokestatic 99	com/google/android/gms/common/internal/zzq$zza:zzck	(Landroid/os/IBinder;)Lcom/google/android/gms/common/internal/zzq;
        //   86: astore 10
        //   88: aload 6
        //   90: invokevirtual 49	android/os/Parcel:recycle	()V
        //   93: aload 5
        //   95: invokevirtual 49	android/os/Parcel:recycle	()V
        //   98: aload 10
        //   100: areturn
        //   101: aconst_null
        //   102: astore 8
        //   104: goto -75 -> 29
        //   107: astore 7
        //   109: aload 6
        //   111: invokevirtual 49	android/os/Parcel:recycle	()V
        //   114: aload 5
        //   116: invokevirtual 49	android/os/Parcel:recycle	()V
        //   119: aload 7
        //   121: athrow
        // Local variable table:
        //   start	length	slot	name	signature
        //   0	122	0	this	zza
        //   0	122	1	paramzzf	zzf
        //   0	122	2	paramString1	String
        //   0	122	3	paramString2	String
        //   0	122	4	paramInt	int
        //   3	112	5	localParcel1	Parcel
        //   8	102	6	localParcel2	Parcel
        //   107	13	7	localObject	Object
        //   27	76	8	localIBinder	IBinder
        //   86	13	10	localzzq	zzq
        // Exception table:
        //   from	to	target	type
        //   10	17	107	finally
        //   21	29	107	finally
        //   29	88	107	finally
      }
      
      /* Error */
      public final void zzc(zzf paramzzf, String paramString1, String paramString2)
        throws RemoteException
      {
        // Byte code:
        //   0: invokestatic 27	android/os/Parcel:obtain	()Landroid/os/Parcel;
        //   3: astore 4
        //   5: invokestatic 27	android/os/Parcel:obtain	()Landroid/os/Parcel;
        //   8: astore 5
        //   10: aload 4
        //   12: ldc 29
        //   14: invokevirtual 33	android/os/Parcel:writeInterfaceToken	(Ljava/lang/String;)V
        //   17: aload_1
        //   18: ifnull +63 -> 81
        //   21: aload_1
        //   22: invokeinterface 55 1 0
        //   27: astore 7
        //   29: aload 4
        //   31: aload 7
        //   33: invokevirtual 58	android/os/Parcel:writeStrongBinder	(Landroid/os/IBinder;)V
        //   36: aload 4
        //   38: aload_2
        //   39: invokevirtual 65	android/os/Parcel:writeString	(Ljava/lang/String;)V
        //   42: aload 4
        //   44: aload_3
        //   45: invokevirtual 65	android/os/Parcel:writeString	(Ljava/lang/String;)V
        //   48: aload_0
        //   49: getfield 15	com/google/android/gms/people/internal/zzg$zza$zza:zzop	Landroid/os/IBinder;
        //   52: bipush 102
        //   54: aload 4
        //   56: aload 5
        //   58: iconst_0
        //   59: invokeinterface 39 5 0
        //   64: pop
        //   65: aload 5
        //   67: invokevirtual 42	android/os/Parcel:readException	()V
        //   70: aload 5
        //   72: invokevirtual 49	android/os/Parcel:recycle	()V
        //   75: aload 4
        //   77: invokevirtual 49	android/os/Parcel:recycle	()V
        //   80: return
        //   81: aconst_null
        //   82: astore 7
        //   84: goto -55 -> 29
        //   87: astore 6
        //   89: aload 5
        //   91: invokevirtual 49	android/os/Parcel:recycle	()V
        //   94: aload 4
        //   96: invokevirtual 49	android/os/Parcel:recycle	()V
        //   99: aload 6
        //   101: athrow
        // Local variable table:
        //   start	length	slot	name	signature
        //   0	102	0	this	zza
        //   0	102	1	paramzzf	zzf
        //   0	102	2	paramString1	String
        //   0	102	3	paramString2	String
        //   3	92	4	localParcel1	Parcel
        //   8	82	5	localParcel2	Parcel
        //   87	13	6	localObject	Object
        //   27	56	7	localIBinder	IBinder
        // Exception table:
        //   from	to	target	type
        //   10	17	87	finally
        //   21	29	87	finally
        //   29	70	87	finally
      }
      
      public final Bundle zzp(Uri paramUri)
        throws RemoteException
      {
        Parcel localParcel1 = Parcel.obtain();
        Parcel localParcel2 = Parcel.obtain();
        for (;;)
        {
          try
          {
            localParcel1.writeInterfaceToken("com.google.android.gms.people.internal.IPeopleService");
            if (paramUri != null)
            {
              localParcel1.writeInt(1);
              paramUri.writeToParcel(localParcel1, 0);
              this.zzop.transact(8, localParcel1, localParcel2, 0);
              localParcel2.readException();
              if (localParcel2.readInt() != 0)
              {
                localBundle = (Bundle)Bundle.CREATOR.createFromParcel(localParcel2);
                return localBundle;
              }
            }
            else
            {
              localParcel1.writeInt(0);
              continue;
            }
            Bundle localBundle = null;
          }
          finally
          {
            localParcel2.recycle();
            localParcel1.recycle();
          }
        }
      }
    }
  }
}


/* Location:           F:\apktool\apktool\Google_Play_Store6.0.5\classes-dex2jar.jar
 * Qualified Name:     com.google.android.gms.people.internal.zzg
 * JD-Core Version:    0.7.0.1
 */