package com.google.android.gms.car;

import android.os.Binder;
import android.os.IBinder;
import android.os.IInterface;
import android.os.Parcel;
import android.os.ParcelFileDescriptor;
import android.os.RemoteException;

public abstract interface zzad
  extends IInterface
{
  public abstract void zza(zzae paramzzae)
    throws RemoteException;
  
  public abstract void zza(zzae paramzzae, int paramInt)
    throws RemoteException;
  
  public abstract ParcelFileDescriptor zzb(zzae paramzzae)
    throws RemoteException;
  
  public abstract void zzb(zzae paramzzae, int paramInt)
    throws RemoteException;
  
  public abstract void zzc(zzae paramzzae)
    throws RemoteException;
  
  public abstract void zzd(zzae paramzzae)
    throws RemoteException;
  
  public abstract void zze(zzae paramzzae)
    throws RemoteException;
  
  public abstract void zzf(zzae paramzzae)
    throws RemoteException;
  
  public abstract void zzg(zzae paramzzae)
    throws RemoteException;
  
  public static abstract class zza
    extends Binder
    implements zzad
  {
    public static zzad zzbj(IBinder paramIBinder)
    {
      if (paramIBinder == null) {
        return null;
      }
      IInterface localIInterface = paramIBinder.queryLocalInterface("com.google.android.gms.car.ICarAudioTrack");
      if ((localIInterface != null) && ((localIInterface instanceof zzad))) {
        return (zzad)localIInterface;
      }
      return new zza(paramIBinder);
    }
    
    public boolean onTransact(int paramInt1, Parcel paramParcel1, Parcel paramParcel2, int paramInt2)
      throws RemoteException
    {
      switch (paramInt1)
      {
      default: 
        return super.onTransact(paramInt1, paramParcel1, paramParcel2, paramInt2);
      case 1598968902: 
        paramParcel2.writeString("com.google.android.gms.car.ICarAudioTrack");
        return true;
      case 1: 
        paramParcel1.enforceInterface("com.google.android.gms.car.ICarAudioTrack");
        zza(zzae.zza.zzbk(paramParcel1.readStrongBinder()));
        paramParcel2.writeNoException();
        return true;
      case 2: 
        paramParcel1.enforceInterface("com.google.android.gms.car.ICarAudioTrack");
        ParcelFileDescriptor localParcelFileDescriptor = zzb(zzae.zza.zzbk(paramParcel1.readStrongBinder()));
        paramParcel2.writeNoException();
        if (localParcelFileDescriptor != null)
        {
          paramParcel2.writeInt(1);
          localParcelFileDescriptor.writeToParcel(paramParcel2, 1);
          return true;
        }
        paramParcel2.writeInt(0);
        return true;
      case 3: 
        paramParcel1.enforceInterface("com.google.android.gms.car.ICarAudioTrack");
        zzc(zzae.zza.zzbk(paramParcel1.readStrongBinder()));
        paramParcel2.writeNoException();
        return true;
      case 4: 
        paramParcel1.enforceInterface("com.google.android.gms.car.ICarAudioTrack");
        zzd(zzae.zza.zzbk(paramParcel1.readStrongBinder()));
        paramParcel2.writeNoException();
        return true;
      case 5: 
        paramParcel1.enforceInterface("com.google.android.gms.car.ICarAudioTrack");
        zze(zzae.zza.zzbk(paramParcel1.readStrongBinder()));
        paramParcel2.writeNoException();
        return true;
      case 6: 
        paramParcel1.enforceInterface("com.google.android.gms.car.ICarAudioTrack");
        zzf(zzae.zza.zzbk(paramParcel1.readStrongBinder()));
        paramParcel2.writeNoException();
        return true;
      case 7: 
        paramParcel1.enforceInterface("com.google.android.gms.car.ICarAudioTrack");
        zzg(zzae.zza.zzbk(paramParcel1.readStrongBinder()));
        paramParcel2.writeNoException();
        return true;
      case 8: 
        paramParcel1.enforceInterface("com.google.android.gms.car.ICarAudioTrack");
        zza(zzae.zza.zzbk(paramParcel1.readStrongBinder()), paramParcel1.readInt());
        paramParcel2.writeNoException();
        return true;
      }
      paramParcel1.enforceInterface("com.google.android.gms.car.ICarAudioTrack");
      zzb(zzae.zza.zzbk(paramParcel1.readStrongBinder()), paramParcel1.readInt());
      paramParcel2.writeNoException();
      return true;
    }
    
    private static final class zza
      implements zzad
    {
      private IBinder zzop;
      
      zza(IBinder paramIBinder)
      {
        this.zzop = paramIBinder;
      }
      
      public final IBinder asBinder()
      {
        return this.zzop;
      }
      
      /* Error */
      public final void zza(zzae paramzzae)
        throws RemoteException
      {
        // Byte code:
        //   0: invokestatic 27	android/os/Parcel:obtain	()Landroid/os/Parcel;
        //   3: astore_2
        //   4: invokestatic 27	android/os/Parcel:obtain	()Landroid/os/Parcel;
        //   7: astore_3
        //   8: aload_2
        //   9: ldc 29
        //   11: invokevirtual 33	android/os/Parcel:writeInterfaceToken	(Ljava/lang/String;)V
        //   14: aload_1
        //   15: ifnull +44 -> 59
        //   18: aload_1
        //   19: invokeinterface 37 1 0
        //   24: astore 5
        //   26: aload_2
        //   27: aload 5
        //   29: invokevirtual 40	android/os/Parcel:writeStrongBinder	(Landroid/os/IBinder;)V
        //   32: aload_0
        //   33: getfield 15	com/google/android/gms/car/zzad$zza$zza:zzop	Landroid/os/IBinder;
        //   36: iconst_1
        //   37: aload_2
        //   38: aload_3
        //   39: iconst_0
        //   40: invokeinterface 46 5 0
        //   45: pop
        //   46: aload_3
        //   47: invokevirtual 49	android/os/Parcel:readException	()V
        //   50: aload_3
        //   51: invokevirtual 52	android/os/Parcel:recycle	()V
        //   54: aload_2
        //   55: invokevirtual 52	android/os/Parcel:recycle	()V
        //   58: return
        //   59: aconst_null
        //   60: astore 5
        //   62: goto -36 -> 26
        //   65: astore 4
        //   67: aload_3
        //   68: invokevirtual 52	android/os/Parcel:recycle	()V
        //   71: aload_2
        //   72: invokevirtual 52	android/os/Parcel:recycle	()V
        //   75: aload 4
        //   77: athrow
        // Local variable table:
        //   start	length	slot	name	signature
        //   0	78	0	this	zza
        //   0	78	1	paramzzae	zzae
        //   3	69	2	localParcel1	Parcel
        //   7	61	3	localParcel2	Parcel
        //   65	11	4	localObject	Object
        //   24	37	5	localIBinder	IBinder
        // Exception table:
        //   from	to	target	type
        //   8	14	65	finally
        //   18	26	65	finally
        //   26	50	65	finally
      }
      
      /* Error */
      public final void zza(zzae paramzzae, int paramInt)
        throws RemoteException
      {
        // Byte code:
        //   0: invokestatic 27	android/os/Parcel:obtain	()Landroid/os/Parcel;
        //   3: astore_3
        //   4: invokestatic 27	android/os/Parcel:obtain	()Landroid/os/Parcel;
        //   7: astore 4
        //   9: aload_3
        //   10: ldc 29
        //   12: invokevirtual 33	android/os/Parcel:writeInterfaceToken	(Ljava/lang/String;)V
        //   15: aload_1
        //   16: ifnull +53 -> 69
        //   19: aload_1
        //   20: invokeinterface 37 1 0
        //   25: astore 6
        //   27: aload_3
        //   28: aload 6
        //   30: invokevirtual 40	android/os/Parcel:writeStrongBinder	(Landroid/os/IBinder;)V
        //   33: aload_3
        //   34: iload_2
        //   35: invokevirtual 57	android/os/Parcel:writeInt	(I)V
        //   38: aload_0
        //   39: getfield 15	com/google/android/gms/car/zzad$zza$zza:zzop	Landroid/os/IBinder;
        //   42: bipush 8
        //   44: aload_3
        //   45: aload 4
        //   47: iconst_0
        //   48: invokeinterface 46 5 0
        //   53: pop
        //   54: aload 4
        //   56: invokevirtual 49	android/os/Parcel:readException	()V
        //   59: aload 4
        //   61: invokevirtual 52	android/os/Parcel:recycle	()V
        //   64: aload_3
        //   65: invokevirtual 52	android/os/Parcel:recycle	()V
        //   68: return
        //   69: aconst_null
        //   70: astore 6
        //   72: goto -45 -> 27
        //   75: astore 5
        //   77: aload 4
        //   79: invokevirtual 52	android/os/Parcel:recycle	()V
        //   82: aload_3
        //   83: invokevirtual 52	android/os/Parcel:recycle	()V
        //   86: aload 5
        //   88: athrow
        // Local variable table:
        //   start	length	slot	name	signature
        //   0	89	0	this	zza
        //   0	89	1	paramzzae	zzae
        //   0	89	2	paramInt	int
        //   3	80	3	localParcel1	Parcel
        //   7	71	4	localParcel2	Parcel
        //   75	12	5	localObject	Object
        //   25	46	6	localIBinder	IBinder
        // Exception table:
        //   from	to	target	type
        //   9	15	75	finally
        //   19	27	75	finally
        //   27	59	75	finally
      }
      
      /* Error */
      public final ParcelFileDescriptor zzb(zzae paramzzae)
        throws RemoteException
      {
        // Byte code:
        //   0: invokestatic 27	android/os/Parcel:obtain	()Landroid/os/Parcel;
        //   3: astore_2
        //   4: invokestatic 27	android/os/Parcel:obtain	()Landroid/os/Parcel;
        //   7: astore_3
        //   8: aload_2
        //   9: ldc 29
        //   11: invokevirtual 33	android/os/Parcel:writeInterfaceToken	(Ljava/lang/String;)V
        //   14: aload_1
        //   15: ifnull +74 -> 89
        //   18: aload_1
        //   19: invokeinterface 37 1 0
        //   24: astore 5
        //   26: aload_2
        //   27: aload 5
        //   29: invokevirtual 40	android/os/Parcel:writeStrongBinder	(Landroid/os/IBinder;)V
        //   32: aload_0
        //   33: getfield 15	com/google/android/gms/car/zzad$zza$zza:zzop	Landroid/os/IBinder;
        //   36: iconst_2
        //   37: aload_2
        //   38: aload_3
        //   39: iconst_0
        //   40: invokeinterface 46 5 0
        //   45: pop
        //   46: aload_3
        //   47: invokevirtual 49	android/os/Parcel:readException	()V
        //   50: aload_3
        //   51: invokevirtual 63	android/os/Parcel:readInt	()I
        //   54: istore 7
        //   56: aconst_null
        //   57: astore 8
        //   59: iload 7
        //   61: ifeq +17 -> 78
        //   64: getstatic 69	android/os/ParcelFileDescriptor:CREATOR	Landroid/os/Parcelable$Creator;
        //   67: aload_3
        //   68: invokeinterface 75 2 0
        //   73: checkcast 65	android/os/ParcelFileDescriptor
        //   76: astore 8
        //   78: aload_3
        //   79: invokevirtual 52	android/os/Parcel:recycle	()V
        //   82: aload_2
        //   83: invokevirtual 52	android/os/Parcel:recycle	()V
        //   86: aload 8
        //   88: areturn
        //   89: aconst_null
        //   90: astore 5
        //   92: goto -66 -> 26
        //   95: astore 4
        //   97: aload_3
        //   98: invokevirtual 52	android/os/Parcel:recycle	()V
        //   101: aload_2
        //   102: invokevirtual 52	android/os/Parcel:recycle	()V
        //   105: aload 4
        //   107: athrow
        // Local variable table:
        //   start	length	slot	name	signature
        //   0	108	0	this	zza
        //   0	108	1	paramzzae	zzae
        //   3	99	2	localParcel1	Parcel
        //   7	91	3	localParcel2	Parcel
        //   95	11	4	localObject	Object
        //   24	67	5	localIBinder	IBinder
        //   54	6	7	i	int
        //   57	30	8	localParcelFileDescriptor	ParcelFileDescriptor
        // Exception table:
        //   from	to	target	type
        //   8	14	95	finally
        //   18	26	95	finally
        //   26	56	95	finally
        //   64	78	95	finally
      }
      
      /* Error */
      public final void zzb(zzae paramzzae, int paramInt)
        throws RemoteException
      {
        // Byte code:
        //   0: invokestatic 27	android/os/Parcel:obtain	()Landroid/os/Parcel;
        //   3: astore_3
        //   4: invokestatic 27	android/os/Parcel:obtain	()Landroid/os/Parcel;
        //   7: astore 4
        //   9: aload_3
        //   10: ldc 29
        //   12: invokevirtual 33	android/os/Parcel:writeInterfaceToken	(Ljava/lang/String;)V
        //   15: aload_1
        //   16: ifnull +53 -> 69
        //   19: aload_1
        //   20: invokeinterface 37 1 0
        //   25: astore 6
        //   27: aload_3
        //   28: aload 6
        //   30: invokevirtual 40	android/os/Parcel:writeStrongBinder	(Landroid/os/IBinder;)V
        //   33: aload_3
        //   34: iload_2
        //   35: invokevirtual 57	android/os/Parcel:writeInt	(I)V
        //   38: aload_0
        //   39: getfield 15	com/google/android/gms/car/zzad$zza$zza:zzop	Landroid/os/IBinder;
        //   42: bipush 9
        //   44: aload_3
        //   45: aload 4
        //   47: iconst_0
        //   48: invokeinterface 46 5 0
        //   53: pop
        //   54: aload 4
        //   56: invokevirtual 49	android/os/Parcel:readException	()V
        //   59: aload 4
        //   61: invokevirtual 52	android/os/Parcel:recycle	()V
        //   64: aload_3
        //   65: invokevirtual 52	android/os/Parcel:recycle	()V
        //   68: return
        //   69: aconst_null
        //   70: astore 6
        //   72: goto -45 -> 27
        //   75: astore 5
        //   77: aload 4
        //   79: invokevirtual 52	android/os/Parcel:recycle	()V
        //   82: aload_3
        //   83: invokevirtual 52	android/os/Parcel:recycle	()V
        //   86: aload 5
        //   88: athrow
        // Local variable table:
        //   start	length	slot	name	signature
        //   0	89	0	this	zza
        //   0	89	1	paramzzae	zzae
        //   0	89	2	paramInt	int
        //   3	80	3	localParcel1	Parcel
        //   7	71	4	localParcel2	Parcel
        //   75	12	5	localObject	Object
        //   25	46	6	localIBinder	IBinder
        // Exception table:
        //   from	to	target	type
        //   9	15	75	finally
        //   19	27	75	finally
        //   27	59	75	finally
      }
      
      /* Error */
      public final void zzc(zzae paramzzae)
        throws RemoteException
      {
        // Byte code:
        //   0: invokestatic 27	android/os/Parcel:obtain	()Landroid/os/Parcel;
        //   3: astore_2
        //   4: invokestatic 27	android/os/Parcel:obtain	()Landroid/os/Parcel;
        //   7: astore_3
        //   8: aload_2
        //   9: ldc 29
        //   11: invokevirtual 33	android/os/Parcel:writeInterfaceToken	(Ljava/lang/String;)V
        //   14: aload_1
        //   15: ifnull +44 -> 59
        //   18: aload_1
        //   19: invokeinterface 37 1 0
        //   24: astore 5
        //   26: aload_2
        //   27: aload 5
        //   29: invokevirtual 40	android/os/Parcel:writeStrongBinder	(Landroid/os/IBinder;)V
        //   32: aload_0
        //   33: getfield 15	com/google/android/gms/car/zzad$zza$zza:zzop	Landroid/os/IBinder;
        //   36: iconst_3
        //   37: aload_2
        //   38: aload_3
        //   39: iconst_0
        //   40: invokeinterface 46 5 0
        //   45: pop
        //   46: aload_3
        //   47: invokevirtual 49	android/os/Parcel:readException	()V
        //   50: aload_3
        //   51: invokevirtual 52	android/os/Parcel:recycle	()V
        //   54: aload_2
        //   55: invokevirtual 52	android/os/Parcel:recycle	()V
        //   58: return
        //   59: aconst_null
        //   60: astore 5
        //   62: goto -36 -> 26
        //   65: astore 4
        //   67: aload_3
        //   68: invokevirtual 52	android/os/Parcel:recycle	()V
        //   71: aload_2
        //   72: invokevirtual 52	android/os/Parcel:recycle	()V
        //   75: aload 4
        //   77: athrow
        // Local variable table:
        //   start	length	slot	name	signature
        //   0	78	0	this	zza
        //   0	78	1	paramzzae	zzae
        //   3	69	2	localParcel1	Parcel
        //   7	61	3	localParcel2	Parcel
        //   65	11	4	localObject	Object
        //   24	37	5	localIBinder	IBinder
        // Exception table:
        //   from	to	target	type
        //   8	14	65	finally
        //   18	26	65	finally
        //   26	50	65	finally
      }
      
      /* Error */
      public final void zzd(zzae paramzzae)
        throws RemoteException
      {
        // Byte code:
        //   0: invokestatic 27	android/os/Parcel:obtain	()Landroid/os/Parcel;
        //   3: astore_2
        //   4: invokestatic 27	android/os/Parcel:obtain	()Landroid/os/Parcel;
        //   7: astore_3
        //   8: aload_2
        //   9: ldc 29
        //   11: invokevirtual 33	android/os/Parcel:writeInterfaceToken	(Ljava/lang/String;)V
        //   14: aload_1
        //   15: ifnull +44 -> 59
        //   18: aload_1
        //   19: invokeinterface 37 1 0
        //   24: astore 5
        //   26: aload_2
        //   27: aload 5
        //   29: invokevirtual 40	android/os/Parcel:writeStrongBinder	(Landroid/os/IBinder;)V
        //   32: aload_0
        //   33: getfield 15	com/google/android/gms/car/zzad$zza$zza:zzop	Landroid/os/IBinder;
        //   36: iconst_4
        //   37: aload_2
        //   38: aload_3
        //   39: iconst_0
        //   40: invokeinterface 46 5 0
        //   45: pop
        //   46: aload_3
        //   47: invokevirtual 49	android/os/Parcel:readException	()V
        //   50: aload_3
        //   51: invokevirtual 52	android/os/Parcel:recycle	()V
        //   54: aload_2
        //   55: invokevirtual 52	android/os/Parcel:recycle	()V
        //   58: return
        //   59: aconst_null
        //   60: astore 5
        //   62: goto -36 -> 26
        //   65: astore 4
        //   67: aload_3
        //   68: invokevirtual 52	android/os/Parcel:recycle	()V
        //   71: aload_2
        //   72: invokevirtual 52	android/os/Parcel:recycle	()V
        //   75: aload 4
        //   77: athrow
        // Local variable table:
        //   start	length	slot	name	signature
        //   0	78	0	this	zza
        //   0	78	1	paramzzae	zzae
        //   3	69	2	localParcel1	Parcel
        //   7	61	3	localParcel2	Parcel
        //   65	11	4	localObject	Object
        //   24	37	5	localIBinder	IBinder
        // Exception table:
        //   from	to	target	type
        //   8	14	65	finally
        //   18	26	65	finally
        //   26	50	65	finally
      }
      
      /* Error */
      public final void zze(zzae paramzzae)
        throws RemoteException
      {
        // Byte code:
        //   0: invokestatic 27	android/os/Parcel:obtain	()Landroid/os/Parcel;
        //   3: astore_2
        //   4: invokestatic 27	android/os/Parcel:obtain	()Landroid/os/Parcel;
        //   7: astore_3
        //   8: aload_2
        //   9: ldc 29
        //   11: invokevirtual 33	android/os/Parcel:writeInterfaceToken	(Ljava/lang/String;)V
        //   14: aload_1
        //   15: ifnull +44 -> 59
        //   18: aload_1
        //   19: invokeinterface 37 1 0
        //   24: astore 5
        //   26: aload_2
        //   27: aload 5
        //   29: invokevirtual 40	android/os/Parcel:writeStrongBinder	(Landroid/os/IBinder;)V
        //   32: aload_0
        //   33: getfield 15	com/google/android/gms/car/zzad$zza$zza:zzop	Landroid/os/IBinder;
        //   36: iconst_5
        //   37: aload_2
        //   38: aload_3
        //   39: iconst_0
        //   40: invokeinterface 46 5 0
        //   45: pop
        //   46: aload_3
        //   47: invokevirtual 49	android/os/Parcel:readException	()V
        //   50: aload_3
        //   51: invokevirtual 52	android/os/Parcel:recycle	()V
        //   54: aload_2
        //   55: invokevirtual 52	android/os/Parcel:recycle	()V
        //   58: return
        //   59: aconst_null
        //   60: astore 5
        //   62: goto -36 -> 26
        //   65: astore 4
        //   67: aload_3
        //   68: invokevirtual 52	android/os/Parcel:recycle	()V
        //   71: aload_2
        //   72: invokevirtual 52	android/os/Parcel:recycle	()V
        //   75: aload 4
        //   77: athrow
        // Local variable table:
        //   start	length	slot	name	signature
        //   0	78	0	this	zza
        //   0	78	1	paramzzae	zzae
        //   3	69	2	localParcel1	Parcel
        //   7	61	3	localParcel2	Parcel
        //   65	11	4	localObject	Object
        //   24	37	5	localIBinder	IBinder
        // Exception table:
        //   from	to	target	type
        //   8	14	65	finally
        //   18	26	65	finally
        //   26	50	65	finally
      }
      
      /* Error */
      public final void zzf(zzae paramzzae)
        throws RemoteException
      {
        // Byte code:
        //   0: invokestatic 27	android/os/Parcel:obtain	()Landroid/os/Parcel;
        //   3: astore_2
        //   4: invokestatic 27	android/os/Parcel:obtain	()Landroid/os/Parcel;
        //   7: astore_3
        //   8: aload_2
        //   9: ldc 29
        //   11: invokevirtual 33	android/os/Parcel:writeInterfaceToken	(Ljava/lang/String;)V
        //   14: aload_1
        //   15: ifnull +45 -> 60
        //   18: aload_1
        //   19: invokeinterface 37 1 0
        //   24: astore 5
        //   26: aload_2
        //   27: aload 5
        //   29: invokevirtual 40	android/os/Parcel:writeStrongBinder	(Landroid/os/IBinder;)V
        //   32: aload_0
        //   33: getfield 15	com/google/android/gms/car/zzad$zza$zza:zzop	Landroid/os/IBinder;
        //   36: bipush 6
        //   38: aload_2
        //   39: aload_3
        //   40: iconst_0
        //   41: invokeinterface 46 5 0
        //   46: pop
        //   47: aload_3
        //   48: invokevirtual 49	android/os/Parcel:readException	()V
        //   51: aload_3
        //   52: invokevirtual 52	android/os/Parcel:recycle	()V
        //   55: aload_2
        //   56: invokevirtual 52	android/os/Parcel:recycle	()V
        //   59: return
        //   60: aconst_null
        //   61: astore 5
        //   63: goto -37 -> 26
        //   66: astore 4
        //   68: aload_3
        //   69: invokevirtual 52	android/os/Parcel:recycle	()V
        //   72: aload_2
        //   73: invokevirtual 52	android/os/Parcel:recycle	()V
        //   76: aload 4
        //   78: athrow
        // Local variable table:
        //   start	length	slot	name	signature
        //   0	79	0	this	zza
        //   0	79	1	paramzzae	zzae
        //   3	70	2	localParcel1	Parcel
        //   7	62	3	localParcel2	Parcel
        //   66	11	4	localObject	Object
        //   24	38	5	localIBinder	IBinder
        // Exception table:
        //   from	to	target	type
        //   8	14	66	finally
        //   18	26	66	finally
        //   26	51	66	finally
      }
      
      /* Error */
      public final void zzg(zzae paramzzae)
        throws RemoteException
      {
        // Byte code:
        //   0: invokestatic 27	android/os/Parcel:obtain	()Landroid/os/Parcel;
        //   3: astore_2
        //   4: invokestatic 27	android/os/Parcel:obtain	()Landroid/os/Parcel;
        //   7: astore_3
        //   8: aload_2
        //   9: ldc 29
        //   11: invokevirtual 33	android/os/Parcel:writeInterfaceToken	(Ljava/lang/String;)V
        //   14: aload_1
        //   15: ifnull +45 -> 60
        //   18: aload_1
        //   19: invokeinterface 37 1 0
        //   24: astore 5
        //   26: aload_2
        //   27: aload 5
        //   29: invokevirtual 40	android/os/Parcel:writeStrongBinder	(Landroid/os/IBinder;)V
        //   32: aload_0
        //   33: getfield 15	com/google/android/gms/car/zzad$zza$zza:zzop	Landroid/os/IBinder;
        //   36: bipush 7
        //   38: aload_2
        //   39: aload_3
        //   40: iconst_0
        //   41: invokeinterface 46 5 0
        //   46: pop
        //   47: aload_3
        //   48: invokevirtual 49	android/os/Parcel:readException	()V
        //   51: aload_3
        //   52: invokevirtual 52	android/os/Parcel:recycle	()V
        //   55: aload_2
        //   56: invokevirtual 52	android/os/Parcel:recycle	()V
        //   59: return
        //   60: aconst_null
        //   61: astore 5
        //   63: goto -37 -> 26
        //   66: astore 4
        //   68: aload_3
        //   69: invokevirtual 52	android/os/Parcel:recycle	()V
        //   72: aload_2
        //   73: invokevirtual 52	android/os/Parcel:recycle	()V
        //   76: aload 4
        //   78: athrow
        // Local variable table:
        //   start	length	slot	name	signature
        //   0	79	0	this	zza
        //   0	79	1	paramzzae	zzae
        //   3	70	2	localParcel1	Parcel
        //   7	62	3	localParcel2	Parcel
        //   66	11	4	localObject	Object
        //   24	38	5	localIBinder	IBinder
        // Exception table:
        //   from	to	target	type
        //   8	14	66	finally
        //   18	26	66	finally
        //   26	51	66	finally
      }
    }
  }
}


/* Location:           F:\apktool\apktool\Google_Play_Store6.0.5\classes-dex2jar.jar
 * Qualified Name:     com.google.android.gms.car.zzad
 * JD-Core Version:    0.7.0.1
 */