package com.google.android.gms.car;

import android.os.Binder;
import android.os.IBinder;
import android.os.IInterface;
import android.os.Parcel;
import android.os.RemoteException;
import java.util.ArrayList;
import java.util.List;

public abstract interface zzax
  extends IInterface
{
  public abstract RadioState getCurrentRadioState()
    throws RemoteException;
  
  public abstract List<RadioProperties> getRadioProperties()
    throws RemoteException;
  
  public abstract void zza(int paramInt, boolean paramBoolean1, boolean paramBoolean2)
    throws RemoteException;
  
  public abstract void zza(int paramInt, boolean paramBoolean1, boolean paramBoolean2, boolean paramBoolean3)
    throws RemoteException;
  
  public abstract void zza(zzay paramzzay)
    throws RemoteException;
  
  public abstract void zzb(int paramInt, boolean paramBoolean1, boolean paramBoolean2)
    throws RemoteException;
  
  public abstract void zzb(zzay paramzzay)
    throws RemoteException;
  
  public abstract void zzbV(int paramInt)
    throws RemoteException;
  
  public abstract void zzbW(int paramInt)
    throws RemoteException;
  
  public abstract void zzbX(int paramInt)
    throws RemoteException;
  
  public abstract void zzbY(int paramInt)
    throws RemoteException;
  
  public abstract void zzc(int paramInt, boolean paramBoolean)
    throws RemoteException;
  
  public abstract void zze(int paramInt1, int paramInt2, int paramInt3)
    throws RemoteException;
  
  public abstract void zzmE()
    throws RemoteException;
  
  public abstract void zzr(int paramInt1, int paramInt2)
    throws RemoteException;
  
  public static abstract class zza
    extends Binder
    implements zzax
  {
    public static zzax zzbC(IBinder paramIBinder)
    {
      if (paramIBinder == null) {
        return null;
      }
      IInterface localIInterface = paramIBinder.queryLocalInterface("com.google.android.gms.car.ICarRadio");
      if ((localIInterface != null) && ((localIInterface instanceof zzax))) {
        return (zzax)localIInterface;
      }
      return new zza(paramIBinder);
    }
    
    public boolean onTransact(int paramInt1, Parcel paramParcel1, Parcel paramParcel2, int paramInt2)
      throws RemoteException
    {
      switch (paramInt1)
      {
      default: 
        return super.onTransact(paramInt1, paramParcel1, paramParcel2, paramInt2);
      case 1598968902: 
        paramParcel2.writeString("com.google.android.gms.car.ICarRadio");
        return true;
      case 1: 
        paramParcel1.enforceInterface("com.google.android.gms.car.ICarRadio");
        zza(zzay.zza.zzbD(paramParcel1.readStrongBinder()));
        paramParcel2.writeNoException();
        return true;
      case 2: 
        paramParcel1.enforceInterface("com.google.android.gms.car.ICarRadio");
        zzb(zzay.zza.zzbD(paramParcel1.readStrongBinder()));
        paramParcel2.writeNoException();
        return true;
      case 3: 
        paramParcel1.enforceInterface("com.google.android.gms.car.ICarRadio");
        int i2 = paramParcel1.readInt();
        if (paramParcel1.readInt() != 0) {}
        for (boolean bool7 = true;; bool7 = false)
        {
          int i3 = paramParcel1.readInt();
          boolean bool8 = false;
          if (i3 != 0) {
            bool8 = true;
          }
          zza(i2, bool7, bool8);
          paramParcel2.writeNoException();
          return true;
        }
      case 4: 
        paramParcel1.enforceInterface("com.google.android.gms.car.ICarRadio");
        int n = paramParcel1.readInt();
        if (paramParcel1.readInt() != 0) {}
        for (boolean bool5 = true;; bool5 = false)
        {
          int i1 = paramParcel1.readInt();
          boolean bool6 = false;
          if (i1 != 0) {
            bool6 = true;
          }
          zzb(n, bool5, bool6);
          paramParcel2.writeNoException();
          return true;
        }
      case 5: 
        paramParcel1.enforceInterface("com.google.android.gms.car.ICarRadio");
        int k = paramParcel1.readInt();
        boolean bool2;
        if (paramParcel1.readInt() != 0)
        {
          bool2 = true;
          if (paramParcel1.readInt() == 0) {
            break label399;
          }
        }
        for (boolean bool3 = true;; bool3 = false)
        {
          int m = paramParcel1.readInt();
          boolean bool4 = false;
          if (m != 0) {
            bool4 = true;
          }
          zza(k, bool2, bool3, bool4);
          paramParcel2.writeNoException();
          return true;
          bool2 = false;
          break;
        }
      case 6: 
        paramParcel1.enforceInterface("com.google.android.gms.car.ICarRadio");
        zze(paramParcel1.readInt(), paramParcel1.readInt(), paramParcel1.readInt());
        paramParcel2.writeNoException();
        return true;
      case 7: 
        paramParcel1.enforceInterface("com.google.android.gms.car.ICarRadio");
        int i = paramParcel1.readInt();
        int j = paramParcel1.readInt();
        boolean bool1 = false;
        if (j != 0) {
          bool1 = true;
        }
        zzc(i, bool1);
        paramParcel2.writeNoException();
        return true;
      case 8: 
        paramParcel1.enforceInterface("com.google.android.gms.car.ICarRadio");
        zzbV(paramParcel1.readInt());
        paramParcel2.writeNoException();
        return true;
      case 9: 
        paramParcel1.enforceInterface("com.google.android.gms.car.ICarRadio");
        zzr(paramParcel1.readInt(), paramParcel1.readInt());
        paramParcel2.writeNoException();
        return true;
      case 10: 
        paramParcel1.enforceInterface("com.google.android.gms.car.ICarRadio");
        zzmE();
        paramParcel2.writeNoException();
        return true;
      case 11: 
        paramParcel1.enforceInterface("com.google.android.gms.car.ICarRadio");
        zzbW(paramParcel1.readInt());
        paramParcel2.writeNoException();
        return true;
      case 12: 
        paramParcel1.enforceInterface("com.google.android.gms.car.ICarRadio");
        zzbX(paramParcel1.readInt());
        paramParcel2.writeNoException();
        return true;
      case 13: 
        paramParcel1.enforceInterface("com.google.android.gms.car.ICarRadio");
        zzbY(paramParcel1.readInt());
        paramParcel2.writeNoException();
        return true;
      case 14: 
        label399:
        paramParcel1.enforceInterface("com.google.android.gms.car.ICarRadio");
        List localList = getRadioProperties();
        paramParcel2.writeNoException();
        paramParcel2.writeTypedList(localList);
        return true;
      }
      paramParcel1.enforceInterface("com.google.android.gms.car.ICarRadio");
      RadioState localRadioState = getCurrentRadioState();
      paramParcel2.writeNoException();
      if (localRadioState != null)
      {
        paramParcel2.writeInt(1);
        localRadioState.writeToParcel(paramParcel2, 1);
        return true;
      }
      paramParcel2.writeInt(0);
      return true;
    }
    
    private static final class zza
      implements zzax
    {
      private IBinder zzop;
      
      zza(IBinder paramIBinder)
      {
        this.zzop = paramIBinder;
      }
      
      public final IBinder asBinder()
      {
        return this.zzop;
      }
      
      /* Error */
      public final RadioState getCurrentRadioState()
        throws RemoteException
      {
        // Byte code:
        //   0: invokestatic 27	android/os/Parcel:obtain	()Landroid/os/Parcel;
        //   3: astore_1
        //   4: invokestatic 27	android/os/Parcel:obtain	()Landroid/os/Parcel;
        //   7: astore_2
        //   8: aload_1
        //   9: ldc 29
        //   11: invokevirtual 33	android/os/Parcel:writeInterfaceToken	(Ljava/lang/String;)V
        //   14: aload_0
        //   15: getfield 15	com/google/android/gms/car/zzax$zza$zza:zzop	Landroid/os/IBinder;
        //   18: bipush 15
        //   20: aload_1
        //   21: aload_2
        //   22: iconst_0
        //   23: invokeinterface 39 5 0
        //   28: pop
        //   29: aload_2
        //   30: invokevirtual 42	android/os/Parcel:readException	()V
        //   33: aload_2
        //   34: invokevirtual 46	android/os/Parcel:readInt	()I
        //   37: ifeq +28 -> 65
        //   40: getstatic 52	com/google/android/gms/car/RadioState:CREATOR	Landroid/os/Parcelable$Creator;
        //   43: aload_2
        //   44: invokeinterface 58 2 0
        //   49: checkcast 48	com/google/android/gms/car/RadioState
        //   52: astore 5
        //   54: aload_2
        //   55: invokevirtual 61	android/os/Parcel:recycle	()V
        //   58: aload_1
        //   59: invokevirtual 61	android/os/Parcel:recycle	()V
        //   62: aload 5
        //   64: areturn
        //   65: aconst_null
        //   66: astore 5
        //   68: goto -14 -> 54
        //   71: astore_3
        //   72: aload_2
        //   73: invokevirtual 61	android/os/Parcel:recycle	()V
        //   76: aload_1
        //   77: invokevirtual 61	android/os/Parcel:recycle	()V
        //   80: aload_3
        //   81: athrow
        // Local variable table:
        //   start	length	slot	name	signature
        //   0	82	0	this	zza
        //   3	74	1	localParcel1	Parcel
        //   7	66	2	localParcel2	Parcel
        //   71	10	3	localObject	Object
        //   52	15	5	localRadioState	RadioState
        // Exception table:
        //   from	to	target	type
        //   8	54	71	finally
      }
      
      public final List<RadioProperties> getRadioProperties()
        throws RemoteException
      {
        Parcel localParcel1 = Parcel.obtain();
        Parcel localParcel2 = Parcel.obtain();
        try
        {
          localParcel1.writeInterfaceToken("com.google.android.gms.car.ICarRadio");
          this.zzop.transact(14, localParcel1, localParcel2, 0);
          localParcel2.readException();
          ArrayList localArrayList = localParcel2.createTypedArrayList(RadioProperties.CREATOR);
          return localArrayList;
        }
        finally
        {
          localParcel2.recycle();
          localParcel1.recycle();
        }
      }
      
      /* Error */
      public final void zza(int paramInt, boolean paramBoolean1, boolean paramBoolean2)
        throws RemoteException
      {
        // Byte code:
        //   0: iconst_1
        //   1: istore 4
        //   3: invokestatic 27	android/os/Parcel:obtain	()Landroid/os/Parcel;
        //   6: astore 5
        //   8: invokestatic 27	android/os/Parcel:obtain	()Landroid/os/Parcel;
        //   11: astore 6
        //   13: aload 5
        //   15: ldc 29
        //   17: invokevirtual 33	android/os/Parcel:writeInterfaceToken	(Ljava/lang/String;)V
        //   20: aload 5
        //   22: iload_1
        //   23: invokevirtual 76	android/os/Parcel:writeInt	(I)V
        //   26: iload_2
        //   27: ifeq +57 -> 84
        //   30: iload 4
        //   32: istore 8
        //   34: aload 5
        //   36: iload 8
        //   38: invokevirtual 76	android/os/Parcel:writeInt	(I)V
        //   41: iload_3
        //   42: ifeq +48 -> 90
        //   45: aload 5
        //   47: iload 4
        //   49: invokevirtual 76	android/os/Parcel:writeInt	(I)V
        //   52: aload_0
        //   53: getfield 15	com/google/android/gms/car/zzax$zza$zza:zzop	Landroid/os/IBinder;
        //   56: iconst_3
        //   57: aload 5
        //   59: aload 6
        //   61: iconst_0
        //   62: invokeinterface 39 5 0
        //   67: pop
        //   68: aload 6
        //   70: invokevirtual 42	android/os/Parcel:readException	()V
        //   73: aload 6
        //   75: invokevirtual 61	android/os/Parcel:recycle	()V
        //   78: aload 5
        //   80: invokevirtual 61	android/os/Parcel:recycle	()V
        //   83: return
        //   84: iconst_0
        //   85: istore 8
        //   87: goto -53 -> 34
        //   90: iconst_0
        //   91: istore 4
        //   93: goto -48 -> 45
        //   96: astore 7
        //   98: aload 6
        //   100: invokevirtual 61	android/os/Parcel:recycle	()V
        //   103: aload 5
        //   105: invokevirtual 61	android/os/Parcel:recycle	()V
        //   108: aload 7
        //   110: athrow
        // Local variable table:
        //   start	length	slot	name	signature
        //   0	111	0	this	zza
        //   0	111	1	paramInt	int
        //   0	111	2	paramBoolean1	boolean
        //   0	111	3	paramBoolean2	boolean
        //   1	91	4	i	int
        //   6	98	5	localParcel1	Parcel
        //   11	88	6	localParcel2	Parcel
        //   96	13	7	localObject	Object
        //   32	54	8	j	int
        // Exception table:
        //   from	to	target	type
        //   13	26	96	finally
        //   34	41	96	finally
        //   45	73	96	finally
      }
      
      /* Error */
      public final void zza(int paramInt, boolean paramBoolean1, boolean paramBoolean2, boolean paramBoolean3)
        throws RemoteException
      {
        // Byte code:
        //   0: iconst_1
        //   1: istore 5
        //   3: invokestatic 27	android/os/Parcel:obtain	()Landroid/os/Parcel;
        //   6: astore 6
        //   8: invokestatic 27	android/os/Parcel:obtain	()Landroid/os/Parcel;
        //   11: astore 7
        //   13: aload 6
        //   15: ldc 29
        //   17: invokevirtual 33	android/os/Parcel:writeInterfaceToken	(Ljava/lang/String;)V
        //   20: aload 6
        //   22: iload_1
        //   23: invokevirtual 76	android/os/Parcel:writeInt	(I)V
        //   26: iload_2
        //   27: ifeq +73 -> 100
        //   30: iload 5
        //   32: istore 9
        //   34: aload 6
        //   36: iload 9
        //   38: invokevirtual 76	android/os/Parcel:writeInt	(I)V
        //   41: iload_3
        //   42: ifeq +64 -> 106
        //   45: iload 5
        //   47: istore 10
        //   49: aload 6
        //   51: iload 10
        //   53: invokevirtual 76	android/os/Parcel:writeInt	(I)V
        //   56: iload 4
        //   58: ifeq +54 -> 112
        //   61: aload 6
        //   63: iload 5
        //   65: invokevirtual 76	android/os/Parcel:writeInt	(I)V
        //   68: aload_0
        //   69: getfield 15	com/google/android/gms/car/zzax$zza$zza:zzop	Landroid/os/IBinder;
        //   72: iconst_5
        //   73: aload 6
        //   75: aload 7
        //   77: iconst_0
        //   78: invokeinterface 39 5 0
        //   83: pop
        //   84: aload 7
        //   86: invokevirtual 42	android/os/Parcel:readException	()V
        //   89: aload 7
        //   91: invokevirtual 61	android/os/Parcel:recycle	()V
        //   94: aload 6
        //   96: invokevirtual 61	android/os/Parcel:recycle	()V
        //   99: return
        //   100: iconst_0
        //   101: istore 9
        //   103: goto -69 -> 34
        //   106: iconst_0
        //   107: istore 10
        //   109: goto -60 -> 49
        //   112: iconst_0
        //   113: istore 5
        //   115: goto -54 -> 61
        //   118: astore 8
        //   120: aload 7
        //   122: invokevirtual 61	android/os/Parcel:recycle	()V
        //   125: aload 6
        //   127: invokevirtual 61	android/os/Parcel:recycle	()V
        //   130: aload 8
        //   132: athrow
        // Local variable table:
        //   start	length	slot	name	signature
        //   0	133	0	this	zza
        //   0	133	1	paramInt	int
        //   0	133	2	paramBoolean1	boolean
        //   0	133	3	paramBoolean2	boolean
        //   0	133	4	paramBoolean3	boolean
        //   1	113	5	i	int
        //   6	120	6	localParcel1	Parcel
        //   11	110	7	localParcel2	Parcel
        //   118	13	8	localObject	Object
        //   32	70	9	j	int
        //   47	61	10	k	int
        // Exception table:
        //   from	to	target	type
        //   13	26	118	finally
        //   34	41	118	finally
        //   49	56	118	finally
        //   61	89	118	finally
      }
      
      /* Error */
      public final void zza(zzay paramzzay)
        throws RemoteException
      {
        // Byte code:
        //   0: invokestatic 27	android/os/Parcel:obtain	()Landroid/os/Parcel;
        //   3: astore_2
        //   4: invokestatic 27	android/os/Parcel:obtain	()Landroid/os/Parcel;
        //   7: astore_3
        //   8: aload_2
        //   9: ldc 29
        //   11: invokevirtual 33	android/os/Parcel:writeInterfaceToken	(Ljava/lang/String;)V
        //   14: aload_1
        //   15: ifnull +44 -> 59
        //   18: aload_1
        //   19: invokeinterface 82 1 0
        //   24: astore 5
        //   26: aload_2
        //   27: aload 5
        //   29: invokevirtual 85	android/os/Parcel:writeStrongBinder	(Landroid/os/IBinder;)V
        //   32: aload_0
        //   33: getfield 15	com/google/android/gms/car/zzax$zza$zza:zzop	Landroid/os/IBinder;
        //   36: iconst_1
        //   37: aload_2
        //   38: aload_3
        //   39: iconst_0
        //   40: invokeinterface 39 5 0
        //   45: pop
        //   46: aload_3
        //   47: invokevirtual 42	android/os/Parcel:readException	()V
        //   50: aload_3
        //   51: invokevirtual 61	android/os/Parcel:recycle	()V
        //   54: aload_2
        //   55: invokevirtual 61	android/os/Parcel:recycle	()V
        //   58: return
        //   59: aconst_null
        //   60: astore 5
        //   62: goto -36 -> 26
        //   65: astore 4
        //   67: aload_3
        //   68: invokevirtual 61	android/os/Parcel:recycle	()V
        //   71: aload_2
        //   72: invokevirtual 61	android/os/Parcel:recycle	()V
        //   75: aload 4
        //   77: athrow
        // Local variable table:
        //   start	length	slot	name	signature
        //   0	78	0	this	zza
        //   0	78	1	paramzzay	zzay
        //   3	69	2	localParcel1	Parcel
        //   7	61	3	localParcel2	Parcel
        //   65	11	4	localObject	Object
        //   24	37	5	localIBinder	IBinder
        // Exception table:
        //   from	to	target	type
        //   8	14	65	finally
        //   18	26	65	finally
        //   26	50	65	finally
      }
      
      /* Error */
      public final void zzb(int paramInt, boolean paramBoolean1, boolean paramBoolean2)
        throws RemoteException
      {
        // Byte code:
        //   0: iconst_1
        //   1: istore 4
        //   3: invokestatic 27	android/os/Parcel:obtain	()Landroid/os/Parcel;
        //   6: astore 5
        //   8: invokestatic 27	android/os/Parcel:obtain	()Landroid/os/Parcel;
        //   11: astore 6
        //   13: aload 5
        //   15: ldc 29
        //   17: invokevirtual 33	android/os/Parcel:writeInterfaceToken	(Ljava/lang/String;)V
        //   20: aload 5
        //   22: iload_1
        //   23: invokevirtual 76	android/os/Parcel:writeInt	(I)V
        //   26: iload_2
        //   27: ifeq +57 -> 84
        //   30: iload 4
        //   32: istore 8
        //   34: aload 5
        //   36: iload 8
        //   38: invokevirtual 76	android/os/Parcel:writeInt	(I)V
        //   41: iload_3
        //   42: ifeq +48 -> 90
        //   45: aload 5
        //   47: iload 4
        //   49: invokevirtual 76	android/os/Parcel:writeInt	(I)V
        //   52: aload_0
        //   53: getfield 15	com/google/android/gms/car/zzax$zza$zza:zzop	Landroid/os/IBinder;
        //   56: iconst_4
        //   57: aload 5
        //   59: aload 6
        //   61: iconst_0
        //   62: invokeinterface 39 5 0
        //   67: pop
        //   68: aload 6
        //   70: invokevirtual 42	android/os/Parcel:readException	()V
        //   73: aload 6
        //   75: invokevirtual 61	android/os/Parcel:recycle	()V
        //   78: aload 5
        //   80: invokevirtual 61	android/os/Parcel:recycle	()V
        //   83: return
        //   84: iconst_0
        //   85: istore 8
        //   87: goto -53 -> 34
        //   90: iconst_0
        //   91: istore 4
        //   93: goto -48 -> 45
        //   96: astore 7
        //   98: aload 6
        //   100: invokevirtual 61	android/os/Parcel:recycle	()V
        //   103: aload 5
        //   105: invokevirtual 61	android/os/Parcel:recycle	()V
        //   108: aload 7
        //   110: athrow
        // Local variable table:
        //   start	length	slot	name	signature
        //   0	111	0	this	zza
        //   0	111	1	paramInt	int
        //   0	111	2	paramBoolean1	boolean
        //   0	111	3	paramBoolean2	boolean
        //   1	91	4	i	int
        //   6	98	5	localParcel1	Parcel
        //   11	88	6	localParcel2	Parcel
        //   96	13	7	localObject	Object
        //   32	54	8	j	int
        // Exception table:
        //   from	to	target	type
        //   13	26	96	finally
        //   34	41	96	finally
        //   45	73	96	finally
      }
      
      /* Error */
      public final void zzb(zzay paramzzay)
        throws RemoteException
      {
        // Byte code:
        //   0: invokestatic 27	android/os/Parcel:obtain	()Landroid/os/Parcel;
        //   3: astore_2
        //   4: invokestatic 27	android/os/Parcel:obtain	()Landroid/os/Parcel;
        //   7: astore_3
        //   8: aload_2
        //   9: ldc 29
        //   11: invokevirtual 33	android/os/Parcel:writeInterfaceToken	(Ljava/lang/String;)V
        //   14: aload_1
        //   15: ifnull +44 -> 59
        //   18: aload_1
        //   19: invokeinterface 82 1 0
        //   24: astore 5
        //   26: aload_2
        //   27: aload 5
        //   29: invokevirtual 85	android/os/Parcel:writeStrongBinder	(Landroid/os/IBinder;)V
        //   32: aload_0
        //   33: getfield 15	com/google/android/gms/car/zzax$zza$zza:zzop	Landroid/os/IBinder;
        //   36: iconst_2
        //   37: aload_2
        //   38: aload_3
        //   39: iconst_0
        //   40: invokeinterface 39 5 0
        //   45: pop
        //   46: aload_3
        //   47: invokevirtual 42	android/os/Parcel:readException	()V
        //   50: aload_3
        //   51: invokevirtual 61	android/os/Parcel:recycle	()V
        //   54: aload_2
        //   55: invokevirtual 61	android/os/Parcel:recycle	()V
        //   58: return
        //   59: aconst_null
        //   60: astore 5
        //   62: goto -36 -> 26
        //   65: astore 4
        //   67: aload_3
        //   68: invokevirtual 61	android/os/Parcel:recycle	()V
        //   71: aload_2
        //   72: invokevirtual 61	android/os/Parcel:recycle	()V
        //   75: aload 4
        //   77: athrow
        // Local variable table:
        //   start	length	slot	name	signature
        //   0	78	0	this	zza
        //   0	78	1	paramzzay	zzay
        //   3	69	2	localParcel1	Parcel
        //   7	61	3	localParcel2	Parcel
        //   65	11	4	localObject	Object
        //   24	37	5	localIBinder	IBinder
        // Exception table:
        //   from	to	target	type
        //   8	14	65	finally
        //   18	26	65	finally
        //   26	50	65	finally
      }
      
      public final void zzbV(int paramInt)
        throws RemoteException
      {
        Parcel localParcel1 = Parcel.obtain();
        Parcel localParcel2 = Parcel.obtain();
        try
        {
          localParcel1.writeInterfaceToken("com.google.android.gms.car.ICarRadio");
          localParcel1.writeInt(paramInt);
          this.zzop.transact(8, localParcel1, localParcel2, 0);
          localParcel2.readException();
          return;
        }
        finally
        {
          localParcel2.recycle();
          localParcel1.recycle();
        }
      }
      
      public final void zzbW(int paramInt)
        throws RemoteException
      {
        Parcel localParcel1 = Parcel.obtain();
        Parcel localParcel2 = Parcel.obtain();
        try
        {
          localParcel1.writeInterfaceToken("com.google.android.gms.car.ICarRadio");
          localParcel1.writeInt(paramInt);
          this.zzop.transact(11, localParcel1, localParcel2, 0);
          localParcel2.readException();
          return;
        }
        finally
        {
          localParcel2.recycle();
          localParcel1.recycle();
        }
      }
      
      public final void zzbX(int paramInt)
        throws RemoteException
      {
        Parcel localParcel1 = Parcel.obtain();
        Parcel localParcel2 = Parcel.obtain();
        try
        {
          localParcel1.writeInterfaceToken("com.google.android.gms.car.ICarRadio");
          localParcel1.writeInt(paramInt);
          this.zzop.transact(12, localParcel1, localParcel2, 0);
          localParcel2.readException();
          return;
        }
        finally
        {
          localParcel2.recycle();
          localParcel1.recycle();
        }
      }
      
      public final void zzbY(int paramInt)
        throws RemoteException
      {
        Parcel localParcel1 = Parcel.obtain();
        Parcel localParcel2 = Parcel.obtain();
        try
        {
          localParcel1.writeInterfaceToken("com.google.android.gms.car.ICarRadio");
          localParcel1.writeInt(paramInt);
          this.zzop.transact(13, localParcel1, localParcel2, 0);
          localParcel2.readException();
          return;
        }
        finally
        {
          localParcel2.recycle();
          localParcel1.recycle();
        }
      }
      
      public final void zzc(int paramInt, boolean paramBoolean)
        throws RemoteException
      {
        Parcel localParcel1 = Parcel.obtain();
        Parcel localParcel2 = Parcel.obtain();
        try
        {
          localParcel1.writeInterfaceToken("com.google.android.gms.car.ICarRadio");
          localParcel1.writeInt(paramInt);
          int i = 0;
          if (paramBoolean) {
            i = 1;
          }
          localParcel1.writeInt(i);
          this.zzop.transact(7, localParcel1, localParcel2, 0);
          localParcel2.readException();
          return;
        }
        finally
        {
          localParcel2.recycle();
          localParcel1.recycle();
        }
      }
      
      public final void zze(int paramInt1, int paramInt2, int paramInt3)
        throws RemoteException
      {
        Parcel localParcel1 = Parcel.obtain();
        Parcel localParcel2 = Parcel.obtain();
        try
        {
          localParcel1.writeInterfaceToken("com.google.android.gms.car.ICarRadio");
          localParcel1.writeInt(paramInt1);
          localParcel1.writeInt(paramInt2);
          localParcel1.writeInt(paramInt3);
          this.zzop.transact(6, localParcel1, localParcel2, 0);
          localParcel2.readException();
          return;
        }
        finally
        {
          localParcel2.recycle();
          localParcel1.recycle();
        }
      }
      
      public final void zzmE()
        throws RemoteException
      {
        Parcel localParcel1 = Parcel.obtain();
        Parcel localParcel2 = Parcel.obtain();
        try
        {
          localParcel1.writeInterfaceToken("com.google.android.gms.car.ICarRadio");
          this.zzop.transact(10, localParcel1, localParcel2, 0);
          localParcel2.readException();
          return;
        }
        finally
        {
          localParcel2.recycle();
          localParcel1.recycle();
        }
      }
      
      public final void zzr(int paramInt1, int paramInt2)
        throws RemoteException
      {
        Parcel localParcel1 = Parcel.obtain();
        Parcel localParcel2 = Parcel.obtain();
        try
        {
          localParcel1.writeInterfaceToken("com.google.android.gms.car.ICarRadio");
          localParcel1.writeInt(paramInt1);
          localParcel1.writeInt(paramInt2);
          this.zzop.transact(9, localParcel1, localParcel2, 0);
          localParcel2.readException();
          return;
        }
        finally
        {
          localParcel2.recycle();
          localParcel1.recycle();
        }
      }
    }
  }
}


/* Location:           F:\apktool\apktool\Google_Play_Store6.0.5\classes-dex2jar.jar
 * Qualified Name:     com.google.android.gms.car.zzax
 * JD-Core Version:    0.7.0.1
 */