package com.google.android.gms.car;

import android.os.Binder;
import android.os.IBinder;
import android.os.IInterface;
import android.os.Parcel;
import android.os.ParcelFileDescriptor;
import android.os.RemoteException;

public abstract interface zzbb
  extends IInterface
{
  public abstract void zza(zzbc paramzzbc, int paramInt)
    throws RemoteException;
  
  public abstract boolean zza(zzbc paramzzbc)
    throws RemoteException;
  
  public abstract void zzb(zzbc paramzzbc)
    throws RemoteException;
  
  public abstract void zzb(zzbc paramzzbc, int paramInt)
    throws RemoteException;
  
  public abstract String zzc(zzbc paramzzbc)
    throws RemoteException;
  
  public abstract void zzc(zzbc paramzzbc, int paramInt)
    throws RemoteException;
  
  public abstract byte[] zzd(zzbc paramzzbc)
    throws RemoteException;
  
  public abstract ParcelFileDescriptor zze(zzbc paramzzbc)
    throws RemoteException;
  
  public abstract ParcelFileDescriptor zzf(zzbc paramzzbc)
    throws RemoteException;
  
  public static abstract class zza
    extends Binder
    implements zzbb
  {
    public static zzbb zzbI(IBinder paramIBinder)
    {
      if (paramIBinder == null) {
        return null;
      }
      IInterface localIInterface = paramIBinder.queryLocalInterface("com.google.android.gms.car.ICarVendorExtension");
      if ((localIInterface != null) && ((localIInterface instanceof zzbb))) {
        return (zzbb)localIInterface;
      }
      return new zza(paramIBinder);
    }
    
    public boolean onTransact(int paramInt1, Parcel paramParcel1, Parcel paramParcel2, int paramInt2)
      throws RemoteException
    {
      switch (paramInt1)
      {
      default: 
        return super.onTransact(paramInt1, paramParcel1, paramParcel2, paramInt2);
      case 1598968902: 
        paramParcel2.writeString("com.google.android.gms.car.ICarVendorExtension");
        return true;
      case 1: 
        paramParcel1.enforceInterface("com.google.android.gms.car.ICarVendorExtension");
        boolean bool = zza(zzbc.zza.zzbJ(paramParcel1.readStrongBinder()));
        paramParcel2.writeNoException();
        int i = 0;
        if (bool) {
          i = 1;
        }
        paramParcel2.writeInt(i);
        return true;
      case 2: 
        paramParcel1.enforceInterface("com.google.android.gms.car.ICarVendorExtension");
        zzb(zzbc.zza.zzbJ(paramParcel1.readStrongBinder()));
        paramParcel2.writeNoException();
        return true;
      case 3: 
        paramParcel1.enforceInterface("com.google.android.gms.car.ICarVendorExtension");
        String str = zzc(zzbc.zza.zzbJ(paramParcel1.readStrongBinder()));
        paramParcel2.writeNoException();
        paramParcel2.writeString(str);
        return true;
      case 4: 
        paramParcel1.enforceInterface("com.google.android.gms.car.ICarVendorExtension");
        byte[] arrayOfByte = zzd(zzbc.zza.zzbJ(paramParcel1.readStrongBinder()));
        paramParcel2.writeNoException();
        paramParcel2.writeByteArray(arrayOfByte);
        return true;
      case 5: 
        paramParcel1.enforceInterface("com.google.android.gms.car.ICarVendorExtension");
        ParcelFileDescriptor localParcelFileDescriptor2 = zze(zzbc.zza.zzbJ(paramParcel1.readStrongBinder()));
        paramParcel2.writeNoException();
        if (localParcelFileDescriptor2 != null)
        {
          paramParcel2.writeInt(1);
          localParcelFileDescriptor2.writeToParcel(paramParcel2, 1);
          return true;
        }
        paramParcel2.writeInt(0);
        return true;
      case 6: 
        paramParcel1.enforceInterface("com.google.android.gms.car.ICarVendorExtension");
        zza(zzbc.zza.zzbJ(paramParcel1.readStrongBinder()), paramParcel1.readInt());
        paramParcel2.writeNoException();
        return true;
      case 7: 
        paramParcel1.enforceInterface("com.google.android.gms.car.ICarVendorExtension");
        zzb(zzbc.zza.zzbJ(paramParcel1.readStrongBinder()), paramParcel1.readInt());
        paramParcel2.writeNoException();
        return true;
      case 8: 
        paramParcel1.enforceInterface("com.google.android.gms.car.ICarVendorExtension");
        ParcelFileDescriptor localParcelFileDescriptor1 = zzf(zzbc.zza.zzbJ(paramParcel1.readStrongBinder()));
        paramParcel2.writeNoException();
        if (localParcelFileDescriptor1 != null)
        {
          paramParcel2.writeInt(1);
          localParcelFileDescriptor1.writeToParcel(paramParcel2, 1);
          return true;
        }
        paramParcel2.writeInt(0);
        return true;
      }
      paramParcel1.enforceInterface("com.google.android.gms.car.ICarVendorExtension");
      zzc(zzbc.zza.zzbJ(paramParcel1.readStrongBinder()), paramParcel1.readInt());
      paramParcel2.writeNoException();
      return true;
    }
    
    private static final class zza
      implements zzbb
    {
      private IBinder zzop;
      
      zza(IBinder paramIBinder)
      {
        this.zzop = paramIBinder;
      }
      
      public final IBinder asBinder()
      {
        return this.zzop;
      }
      
      /* Error */
      public final void zza(zzbc paramzzbc, int paramInt)
        throws RemoteException
      {
        // Byte code:
        //   0: invokestatic 27	android/os/Parcel:obtain	()Landroid/os/Parcel;
        //   3: astore_3
        //   4: invokestatic 27	android/os/Parcel:obtain	()Landroid/os/Parcel;
        //   7: astore 4
        //   9: aload_3
        //   10: ldc 29
        //   12: invokevirtual 33	android/os/Parcel:writeInterfaceToken	(Ljava/lang/String;)V
        //   15: aload_1
        //   16: ifnull +53 -> 69
        //   19: aload_1
        //   20: invokeinterface 37 1 0
        //   25: astore 6
        //   27: aload_3
        //   28: aload 6
        //   30: invokevirtual 40	android/os/Parcel:writeStrongBinder	(Landroid/os/IBinder;)V
        //   33: aload_3
        //   34: iload_2
        //   35: invokevirtual 44	android/os/Parcel:writeInt	(I)V
        //   38: aload_0
        //   39: getfield 15	com/google/android/gms/car/zzbb$zza$zza:zzop	Landroid/os/IBinder;
        //   42: bipush 6
        //   44: aload_3
        //   45: aload 4
        //   47: iconst_0
        //   48: invokeinterface 50 5 0
        //   53: pop
        //   54: aload 4
        //   56: invokevirtual 53	android/os/Parcel:readException	()V
        //   59: aload 4
        //   61: invokevirtual 56	android/os/Parcel:recycle	()V
        //   64: aload_3
        //   65: invokevirtual 56	android/os/Parcel:recycle	()V
        //   68: return
        //   69: aconst_null
        //   70: astore 6
        //   72: goto -45 -> 27
        //   75: astore 5
        //   77: aload 4
        //   79: invokevirtual 56	android/os/Parcel:recycle	()V
        //   82: aload_3
        //   83: invokevirtual 56	android/os/Parcel:recycle	()V
        //   86: aload 5
        //   88: athrow
        // Local variable table:
        //   start	length	slot	name	signature
        //   0	89	0	this	zza
        //   0	89	1	paramzzbc	zzbc
        //   0	89	2	paramInt	int
        //   3	80	3	localParcel1	Parcel
        //   7	71	4	localParcel2	Parcel
        //   75	12	5	localObject	Object
        //   25	46	6	localIBinder	IBinder
        // Exception table:
        //   from	to	target	type
        //   9	15	75	finally
        //   19	27	75	finally
        //   27	59	75	finally
      }
      
      /* Error */
      public final boolean zza(zzbc paramzzbc)
        throws RemoteException
      {
        // Byte code:
        //   0: iconst_1
        //   1: istore_2
        //   2: invokestatic 27	android/os/Parcel:obtain	()Landroid/os/Parcel;
        //   5: astore_3
        //   6: invokestatic 27	android/os/Parcel:obtain	()Landroid/os/Parcel;
        //   9: astore 4
        //   11: aload_3
        //   12: ldc 29
        //   14: invokevirtual 33	android/os/Parcel:writeInterfaceToken	(Ljava/lang/String;)V
        //   17: aload_1
        //   18: ifnull +60 -> 78
        //   21: aload_1
        //   22: invokeinterface 37 1 0
        //   27: astore 6
        //   29: aload_3
        //   30: aload 6
        //   32: invokevirtual 40	android/os/Parcel:writeStrongBinder	(Landroid/os/IBinder;)V
        //   35: aload_0
        //   36: getfield 15	com/google/android/gms/car/zzbb$zza$zza:zzop	Landroid/os/IBinder;
        //   39: iconst_1
        //   40: aload_3
        //   41: aload 4
        //   43: iconst_0
        //   44: invokeinterface 50 5 0
        //   49: pop
        //   50: aload 4
        //   52: invokevirtual 53	android/os/Parcel:readException	()V
        //   55: aload 4
        //   57: invokevirtual 61	android/os/Parcel:readInt	()I
        //   60: istore 8
        //   62: iload 8
        //   64: ifeq +20 -> 84
        //   67: aload 4
        //   69: invokevirtual 56	android/os/Parcel:recycle	()V
        //   72: aload_3
        //   73: invokevirtual 56	android/os/Parcel:recycle	()V
        //   76: iload_2
        //   77: ireturn
        //   78: aconst_null
        //   79: astore 6
        //   81: goto -52 -> 29
        //   84: iconst_0
        //   85: istore_2
        //   86: goto -19 -> 67
        //   89: astore 5
        //   91: aload 4
        //   93: invokevirtual 56	android/os/Parcel:recycle	()V
        //   96: aload_3
        //   97: invokevirtual 56	android/os/Parcel:recycle	()V
        //   100: aload 5
        //   102: athrow
        // Local variable table:
        //   start	length	slot	name	signature
        //   0	103	0	this	zza
        //   0	103	1	paramzzbc	zzbc
        //   1	85	2	bool	boolean
        //   5	92	3	localParcel1	Parcel
        //   9	83	4	localParcel2	Parcel
        //   89	12	5	localObject	Object
        //   27	53	6	localIBinder	IBinder
        //   60	3	8	i	int
        // Exception table:
        //   from	to	target	type
        //   11	17	89	finally
        //   21	29	89	finally
        //   29	62	89	finally
      }
      
      /* Error */
      public final void zzb(zzbc paramzzbc)
        throws RemoteException
      {
        // Byte code:
        //   0: invokestatic 27	android/os/Parcel:obtain	()Landroid/os/Parcel;
        //   3: astore_2
        //   4: invokestatic 27	android/os/Parcel:obtain	()Landroid/os/Parcel;
        //   7: astore_3
        //   8: aload_2
        //   9: ldc 29
        //   11: invokevirtual 33	android/os/Parcel:writeInterfaceToken	(Ljava/lang/String;)V
        //   14: aload_1
        //   15: ifnull +44 -> 59
        //   18: aload_1
        //   19: invokeinterface 37 1 0
        //   24: astore 5
        //   26: aload_2
        //   27: aload 5
        //   29: invokevirtual 40	android/os/Parcel:writeStrongBinder	(Landroid/os/IBinder;)V
        //   32: aload_0
        //   33: getfield 15	com/google/android/gms/car/zzbb$zza$zza:zzop	Landroid/os/IBinder;
        //   36: iconst_2
        //   37: aload_2
        //   38: aload_3
        //   39: iconst_0
        //   40: invokeinterface 50 5 0
        //   45: pop
        //   46: aload_3
        //   47: invokevirtual 53	android/os/Parcel:readException	()V
        //   50: aload_3
        //   51: invokevirtual 56	android/os/Parcel:recycle	()V
        //   54: aload_2
        //   55: invokevirtual 56	android/os/Parcel:recycle	()V
        //   58: return
        //   59: aconst_null
        //   60: astore 5
        //   62: goto -36 -> 26
        //   65: astore 4
        //   67: aload_3
        //   68: invokevirtual 56	android/os/Parcel:recycle	()V
        //   71: aload_2
        //   72: invokevirtual 56	android/os/Parcel:recycle	()V
        //   75: aload 4
        //   77: athrow
        // Local variable table:
        //   start	length	slot	name	signature
        //   0	78	0	this	zza
        //   0	78	1	paramzzbc	zzbc
        //   3	69	2	localParcel1	Parcel
        //   7	61	3	localParcel2	Parcel
        //   65	11	4	localObject	Object
        //   24	37	5	localIBinder	IBinder
        // Exception table:
        //   from	to	target	type
        //   8	14	65	finally
        //   18	26	65	finally
        //   26	50	65	finally
      }
      
      /* Error */
      public final void zzb(zzbc paramzzbc, int paramInt)
        throws RemoteException
      {
        // Byte code:
        //   0: invokestatic 27	android/os/Parcel:obtain	()Landroid/os/Parcel;
        //   3: astore_3
        //   4: invokestatic 27	android/os/Parcel:obtain	()Landroid/os/Parcel;
        //   7: astore 4
        //   9: aload_3
        //   10: ldc 29
        //   12: invokevirtual 33	android/os/Parcel:writeInterfaceToken	(Ljava/lang/String;)V
        //   15: aload_1
        //   16: ifnull +53 -> 69
        //   19: aload_1
        //   20: invokeinterface 37 1 0
        //   25: astore 6
        //   27: aload_3
        //   28: aload 6
        //   30: invokevirtual 40	android/os/Parcel:writeStrongBinder	(Landroid/os/IBinder;)V
        //   33: aload_3
        //   34: iload_2
        //   35: invokevirtual 44	android/os/Parcel:writeInt	(I)V
        //   38: aload_0
        //   39: getfield 15	com/google/android/gms/car/zzbb$zza$zza:zzop	Landroid/os/IBinder;
        //   42: bipush 7
        //   44: aload_3
        //   45: aload 4
        //   47: iconst_0
        //   48: invokeinterface 50 5 0
        //   53: pop
        //   54: aload 4
        //   56: invokevirtual 53	android/os/Parcel:readException	()V
        //   59: aload 4
        //   61: invokevirtual 56	android/os/Parcel:recycle	()V
        //   64: aload_3
        //   65: invokevirtual 56	android/os/Parcel:recycle	()V
        //   68: return
        //   69: aconst_null
        //   70: astore 6
        //   72: goto -45 -> 27
        //   75: astore 5
        //   77: aload 4
        //   79: invokevirtual 56	android/os/Parcel:recycle	()V
        //   82: aload_3
        //   83: invokevirtual 56	android/os/Parcel:recycle	()V
        //   86: aload 5
        //   88: athrow
        // Local variable table:
        //   start	length	slot	name	signature
        //   0	89	0	this	zza
        //   0	89	1	paramzzbc	zzbc
        //   0	89	2	paramInt	int
        //   3	80	3	localParcel1	Parcel
        //   7	71	4	localParcel2	Parcel
        //   75	12	5	localObject	Object
        //   25	46	6	localIBinder	IBinder
        // Exception table:
        //   from	to	target	type
        //   9	15	75	finally
        //   19	27	75	finally
        //   27	59	75	finally
      }
      
      /* Error */
      public final String zzc(zzbc paramzzbc)
        throws RemoteException
      {
        // Byte code:
        //   0: invokestatic 27	android/os/Parcel:obtain	()Landroid/os/Parcel;
        //   3: astore_2
        //   4: invokestatic 27	android/os/Parcel:obtain	()Landroid/os/Parcel;
        //   7: astore_3
        //   8: aload_2
        //   9: ldc 29
        //   11: invokevirtual 33	android/os/Parcel:writeInterfaceToken	(Ljava/lang/String;)V
        //   14: aload_1
        //   15: ifnull +52 -> 67
        //   18: aload_1
        //   19: invokeinterface 37 1 0
        //   24: astore 5
        //   26: aload_2
        //   27: aload 5
        //   29: invokevirtual 40	android/os/Parcel:writeStrongBinder	(Landroid/os/IBinder;)V
        //   32: aload_0
        //   33: getfield 15	com/google/android/gms/car/zzbb$zza$zza:zzop	Landroid/os/IBinder;
        //   36: iconst_3
        //   37: aload_2
        //   38: aload_3
        //   39: iconst_0
        //   40: invokeinterface 50 5 0
        //   45: pop
        //   46: aload_3
        //   47: invokevirtual 53	android/os/Parcel:readException	()V
        //   50: aload_3
        //   51: invokevirtual 69	android/os/Parcel:readString	()Ljava/lang/String;
        //   54: astore 7
        //   56: aload_3
        //   57: invokevirtual 56	android/os/Parcel:recycle	()V
        //   60: aload_2
        //   61: invokevirtual 56	android/os/Parcel:recycle	()V
        //   64: aload 7
        //   66: areturn
        //   67: aconst_null
        //   68: astore 5
        //   70: goto -44 -> 26
        //   73: astore 4
        //   75: aload_3
        //   76: invokevirtual 56	android/os/Parcel:recycle	()V
        //   79: aload_2
        //   80: invokevirtual 56	android/os/Parcel:recycle	()V
        //   83: aload 4
        //   85: athrow
        // Local variable table:
        //   start	length	slot	name	signature
        //   0	86	0	this	zza
        //   0	86	1	paramzzbc	zzbc
        //   3	77	2	localParcel1	Parcel
        //   7	69	3	localParcel2	Parcel
        //   73	11	4	localObject	Object
        //   24	45	5	localIBinder	IBinder
        //   54	11	7	str	String
        // Exception table:
        //   from	to	target	type
        //   8	14	73	finally
        //   18	26	73	finally
        //   26	56	73	finally
      }
      
      /* Error */
      public final void zzc(zzbc paramzzbc, int paramInt)
        throws RemoteException
      {
        // Byte code:
        //   0: invokestatic 27	android/os/Parcel:obtain	()Landroid/os/Parcel;
        //   3: astore_3
        //   4: invokestatic 27	android/os/Parcel:obtain	()Landroid/os/Parcel;
        //   7: astore 4
        //   9: aload_3
        //   10: ldc 29
        //   12: invokevirtual 33	android/os/Parcel:writeInterfaceToken	(Ljava/lang/String;)V
        //   15: aload_1
        //   16: ifnull +53 -> 69
        //   19: aload_1
        //   20: invokeinterface 37 1 0
        //   25: astore 6
        //   27: aload_3
        //   28: aload 6
        //   30: invokevirtual 40	android/os/Parcel:writeStrongBinder	(Landroid/os/IBinder;)V
        //   33: aload_3
        //   34: iload_2
        //   35: invokevirtual 44	android/os/Parcel:writeInt	(I)V
        //   38: aload_0
        //   39: getfield 15	com/google/android/gms/car/zzbb$zza$zza:zzop	Landroid/os/IBinder;
        //   42: bipush 9
        //   44: aload_3
        //   45: aload 4
        //   47: iconst_0
        //   48: invokeinterface 50 5 0
        //   53: pop
        //   54: aload 4
        //   56: invokevirtual 53	android/os/Parcel:readException	()V
        //   59: aload 4
        //   61: invokevirtual 56	android/os/Parcel:recycle	()V
        //   64: aload_3
        //   65: invokevirtual 56	android/os/Parcel:recycle	()V
        //   68: return
        //   69: aconst_null
        //   70: astore 6
        //   72: goto -45 -> 27
        //   75: astore 5
        //   77: aload 4
        //   79: invokevirtual 56	android/os/Parcel:recycle	()V
        //   82: aload_3
        //   83: invokevirtual 56	android/os/Parcel:recycle	()V
        //   86: aload 5
        //   88: athrow
        // Local variable table:
        //   start	length	slot	name	signature
        //   0	89	0	this	zza
        //   0	89	1	paramzzbc	zzbc
        //   0	89	2	paramInt	int
        //   3	80	3	localParcel1	Parcel
        //   7	71	4	localParcel2	Parcel
        //   75	12	5	localObject	Object
        //   25	46	6	localIBinder	IBinder
        // Exception table:
        //   from	to	target	type
        //   9	15	75	finally
        //   19	27	75	finally
        //   27	59	75	finally
      }
      
      /* Error */
      public final byte[] zzd(zzbc paramzzbc)
        throws RemoteException
      {
        // Byte code:
        //   0: invokestatic 27	android/os/Parcel:obtain	()Landroid/os/Parcel;
        //   3: astore_2
        //   4: invokestatic 27	android/os/Parcel:obtain	()Landroid/os/Parcel;
        //   7: astore_3
        //   8: aload_2
        //   9: ldc 29
        //   11: invokevirtual 33	android/os/Parcel:writeInterfaceToken	(Ljava/lang/String;)V
        //   14: aload_1
        //   15: ifnull +52 -> 67
        //   18: aload_1
        //   19: invokeinterface 37 1 0
        //   24: astore 5
        //   26: aload_2
        //   27: aload 5
        //   29: invokevirtual 40	android/os/Parcel:writeStrongBinder	(Landroid/os/IBinder;)V
        //   32: aload_0
        //   33: getfield 15	com/google/android/gms/car/zzbb$zza$zza:zzop	Landroid/os/IBinder;
        //   36: iconst_4
        //   37: aload_2
        //   38: aload_3
        //   39: iconst_0
        //   40: invokeinterface 50 5 0
        //   45: pop
        //   46: aload_3
        //   47: invokevirtual 53	android/os/Parcel:readException	()V
        //   50: aload_3
        //   51: invokevirtual 75	android/os/Parcel:createByteArray	()[B
        //   54: astore 7
        //   56: aload_3
        //   57: invokevirtual 56	android/os/Parcel:recycle	()V
        //   60: aload_2
        //   61: invokevirtual 56	android/os/Parcel:recycle	()V
        //   64: aload 7
        //   66: areturn
        //   67: aconst_null
        //   68: astore 5
        //   70: goto -44 -> 26
        //   73: astore 4
        //   75: aload_3
        //   76: invokevirtual 56	android/os/Parcel:recycle	()V
        //   79: aload_2
        //   80: invokevirtual 56	android/os/Parcel:recycle	()V
        //   83: aload 4
        //   85: athrow
        // Local variable table:
        //   start	length	slot	name	signature
        //   0	86	0	this	zza
        //   0	86	1	paramzzbc	zzbc
        //   3	77	2	localParcel1	Parcel
        //   7	69	3	localParcel2	Parcel
        //   73	11	4	localObject	Object
        //   24	45	5	localIBinder	IBinder
        //   54	11	7	arrayOfByte	byte[]
        // Exception table:
        //   from	to	target	type
        //   8	14	73	finally
        //   18	26	73	finally
        //   26	56	73	finally
      }
      
      /* Error */
      public final ParcelFileDescriptor zze(zzbc paramzzbc)
        throws RemoteException
      {
        // Byte code:
        //   0: invokestatic 27	android/os/Parcel:obtain	()Landroid/os/Parcel;
        //   3: astore_2
        //   4: invokestatic 27	android/os/Parcel:obtain	()Landroid/os/Parcel;
        //   7: astore_3
        //   8: aload_2
        //   9: ldc 29
        //   11: invokevirtual 33	android/os/Parcel:writeInterfaceToken	(Ljava/lang/String;)V
        //   14: aload_1
        //   15: ifnull +74 -> 89
        //   18: aload_1
        //   19: invokeinterface 37 1 0
        //   24: astore 5
        //   26: aload_2
        //   27: aload 5
        //   29: invokevirtual 40	android/os/Parcel:writeStrongBinder	(Landroid/os/IBinder;)V
        //   32: aload_0
        //   33: getfield 15	com/google/android/gms/car/zzbb$zza$zza:zzop	Landroid/os/IBinder;
        //   36: iconst_5
        //   37: aload_2
        //   38: aload_3
        //   39: iconst_0
        //   40: invokeinterface 50 5 0
        //   45: pop
        //   46: aload_3
        //   47: invokevirtual 53	android/os/Parcel:readException	()V
        //   50: aload_3
        //   51: invokevirtual 61	android/os/Parcel:readInt	()I
        //   54: istore 7
        //   56: aconst_null
        //   57: astore 8
        //   59: iload 7
        //   61: ifeq +17 -> 78
        //   64: getstatic 83	android/os/ParcelFileDescriptor:CREATOR	Landroid/os/Parcelable$Creator;
        //   67: aload_3
        //   68: invokeinterface 89 2 0
        //   73: checkcast 79	android/os/ParcelFileDescriptor
        //   76: astore 8
        //   78: aload_3
        //   79: invokevirtual 56	android/os/Parcel:recycle	()V
        //   82: aload_2
        //   83: invokevirtual 56	android/os/Parcel:recycle	()V
        //   86: aload 8
        //   88: areturn
        //   89: aconst_null
        //   90: astore 5
        //   92: goto -66 -> 26
        //   95: astore 4
        //   97: aload_3
        //   98: invokevirtual 56	android/os/Parcel:recycle	()V
        //   101: aload_2
        //   102: invokevirtual 56	android/os/Parcel:recycle	()V
        //   105: aload 4
        //   107: athrow
        // Local variable table:
        //   start	length	slot	name	signature
        //   0	108	0	this	zza
        //   0	108	1	paramzzbc	zzbc
        //   3	99	2	localParcel1	Parcel
        //   7	91	3	localParcel2	Parcel
        //   95	11	4	localObject	Object
        //   24	67	5	localIBinder	IBinder
        //   54	6	7	i	int
        //   57	30	8	localParcelFileDescriptor	ParcelFileDescriptor
        // Exception table:
        //   from	to	target	type
        //   8	14	95	finally
        //   18	26	95	finally
        //   26	56	95	finally
        //   64	78	95	finally
      }
      
      /* Error */
      public final ParcelFileDescriptor zzf(zzbc paramzzbc)
        throws RemoteException
      {
        // Byte code:
        //   0: invokestatic 27	android/os/Parcel:obtain	()Landroid/os/Parcel;
        //   3: astore_2
        //   4: invokestatic 27	android/os/Parcel:obtain	()Landroid/os/Parcel;
        //   7: astore_3
        //   8: aload_2
        //   9: ldc 29
        //   11: invokevirtual 33	android/os/Parcel:writeInterfaceToken	(Ljava/lang/String;)V
        //   14: aload_1
        //   15: ifnull +75 -> 90
        //   18: aload_1
        //   19: invokeinterface 37 1 0
        //   24: astore 5
        //   26: aload_2
        //   27: aload 5
        //   29: invokevirtual 40	android/os/Parcel:writeStrongBinder	(Landroid/os/IBinder;)V
        //   32: aload_0
        //   33: getfield 15	com/google/android/gms/car/zzbb$zza$zza:zzop	Landroid/os/IBinder;
        //   36: bipush 8
        //   38: aload_2
        //   39: aload_3
        //   40: iconst_0
        //   41: invokeinterface 50 5 0
        //   46: pop
        //   47: aload_3
        //   48: invokevirtual 53	android/os/Parcel:readException	()V
        //   51: aload_3
        //   52: invokevirtual 61	android/os/Parcel:readInt	()I
        //   55: istore 7
        //   57: aconst_null
        //   58: astore 8
        //   60: iload 7
        //   62: ifeq +17 -> 79
        //   65: getstatic 83	android/os/ParcelFileDescriptor:CREATOR	Landroid/os/Parcelable$Creator;
        //   68: aload_3
        //   69: invokeinterface 89 2 0
        //   74: checkcast 79	android/os/ParcelFileDescriptor
        //   77: astore 8
        //   79: aload_3
        //   80: invokevirtual 56	android/os/Parcel:recycle	()V
        //   83: aload_2
        //   84: invokevirtual 56	android/os/Parcel:recycle	()V
        //   87: aload 8
        //   89: areturn
        //   90: aconst_null
        //   91: astore 5
        //   93: goto -67 -> 26
        //   96: astore 4
        //   98: aload_3
        //   99: invokevirtual 56	android/os/Parcel:recycle	()V
        //   102: aload_2
        //   103: invokevirtual 56	android/os/Parcel:recycle	()V
        //   106: aload 4
        //   108: athrow
        // Local variable table:
        //   start	length	slot	name	signature
        //   0	109	0	this	zza
        //   0	109	1	paramzzbc	zzbc
        //   3	100	2	localParcel1	Parcel
        //   7	92	3	localParcel2	Parcel
        //   96	11	4	localObject	Object
        //   24	68	5	localIBinder	IBinder
        //   55	6	7	i	int
        //   58	30	8	localParcelFileDescriptor	ParcelFileDescriptor
        // Exception table:
        //   from	to	target	type
        //   8	14	96	finally
        //   18	26	96	finally
        //   26	57	96	finally
        //   65	79	96	finally
      }
    }
  }
}


/* Location:           F:\apktool\apktool\Google_Play_Store6.0.5\classes-dex2jar.jar
 * Qualified Name:     com.google.android.gms.car.zzbb
 * JD-Core Version:    0.7.0.1
 */