package com.google.android.gms.car;

import android.content.Intent;
import android.content.pm.ResolveInfo;
import android.os.Binder;
import android.os.IBinder;
import android.os.IInterface;
import android.os.Parcel;
import android.os.Parcelable.Creator;
import android.os.RemoteException;
import com.google.android.gms.car.diagnostics.zzb;
import com.google.android.gms.car.diagnostics.zzb.zza;
import java.util.ArrayList;
import java.util.List;

public abstract interface zzx
  extends IInterface
{
  public abstract List<ResolveInfo> queryIntentCarProjectionServices(Intent paramIntent)
    throws RemoteException;
  
  public abstract String zzA(String paramString1, String paramString2)
    throws RemoteException;
  
  public abstract void zzB(String paramString1, String paramString2)
    throws RemoteException;
  
  public abstract List<ResolveInfo> zza(Intent paramIntent, int paramInt)
    throws RemoteException;
  
  public abstract void zza(CarFacet paramCarFacet)
    throws RemoteException;
  
  public abstract void zza(CarFrxEvent paramCarFrxEvent)
    throws RemoteException;
  
  public abstract void zza(CarInfo paramCarInfo)
    throws RemoteException;
  
  public abstract void zza(CarInfo paramCarInfo, String paramString)
    throws RemoteException;
  
  public abstract void zza(zzaj paramzzaj)
    throws RemoteException;
  
  public abstract void zza(zzak paramzzak)
    throws RemoteException;
  
  public abstract void zza(zzy paramzzy)
    throws RemoteException;
  
  public abstract void zzb(zzaj paramzzaj)
    throws RemoteException;
  
  public abstract void zzb(zzak paramzzak)
    throws RemoteException;
  
  public abstract void zzb(zzy paramzzy)
    throws RemoteException;
  
  public abstract String zzbR(String paramString)
    throws RemoteException;
  
  public abstract zzbb zzbS(String paramString)
    throws RemoteException;
  
  public abstract boolean zze(String paramString, int paramInt)
    throws RemoteException;
  
  public abstract boolean zzg(String paramString, boolean paramBoolean)
    throws RemoteException;
  
  public abstract void zzh(String paramString, boolean paramBoolean)
    throws RemoteException;
  
  public abstract boolean zzlG()
    throws RemoteException;
  
  public abstract int zzlH()
    throws RemoteException;
  
  public abstract CarInfo zzlI()
    throws RemoteException;
  
  public abstract CarUiInfo zzlJ()
    throws RemoteException;
  
  public abstract List<CarInfo> zzlT()
    throws RemoteException;
  
  public abstract List<CarInfo> zzlU()
    throws RemoteException;
  
  public abstract void zzlV()
    throws RemoteException;
  
  public abstract zzaz zzmg()
    throws RemoteException;
  
  public abstract zzz zzmh()
    throws RemoteException;
  
  public abstract zzar zzmi()
    throws RemoteException;
  
  public abstract zzah zzmj()
    throws RemoteException;
  
  public abstract zzan zzmk()
    throws RemoteException;
  
  public abstract zzal zzml()
    throws RemoteException;
  
  public abstract zzat zzmm()
    throws RemoteException;
  
  public abstract zzap zzmn()
    throws RemoteException;
  
  public abstract zzaf zzmo()
    throws RemoteException;
  
  public abstract void zzmp()
    throws RemoteException;
  
  public abstract void zzmq()
    throws RemoteException;
  
  public abstract zzb zzmr()
    throws RemoteException;
  
  public abstract zzax zzms()
    throws RemoteException;
  
  public abstract ICarRetailMode zzmt()
    throws RemoteException;
  
  public abstract boolean zzn(Intent paramIntent)
    throws RemoteException;
  
  public static abstract class zza
    extends Binder
    implements zzx
  {
    public static zzx zzbd(IBinder paramIBinder)
    {
      if (paramIBinder == null) {
        return null;
      }
      IInterface localIInterface = paramIBinder.queryLocalInterface("com.google.android.gms.car.ICar");
      if ((localIInterface != null) && ((localIInterface instanceof zzx))) {
        return (zzx)localIInterface;
      }
      return new zza(paramIBinder);
    }
    
    public boolean onTransact(int paramInt1, Parcel paramParcel1, Parcel paramParcel2, int paramInt2)
      throws RemoteException
    {
      switch (paramInt1)
      {
      default: 
        return super.onTransact(paramInt1, paramParcel1, paramParcel2, paramInt2);
      case 1598968902: 
        paramParcel2.writeString("com.google.android.gms.car.ICar");
        return true;
      case 1: 
        paramParcel1.enforceInterface("com.google.android.gms.car.ICar");
        CarInfo localCarInfo3 = zzlI();
        paramParcel2.writeNoException();
        if (localCarInfo3 != null)
        {
          paramParcel2.writeInt(1);
          localCarInfo3.writeToParcel(paramParcel2, 1);
          return true;
        }
        paramParcel2.writeInt(0);
        return true;
      case 2: 
        paramParcel1.enforceInterface("com.google.android.gms.car.ICar");
        CarUiInfo localCarUiInfo = zzlJ();
        paramParcel2.writeNoException();
        if (localCarUiInfo != null)
        {
          paramParcel2.writeInt(1);
          localCarUiInfo.writeToParcel(paramParcel2, 1);
          return true;
        }
        paramParcel2.writeInt(0);
        return true;
      case 3: 
        paramParcel1.enforceInterface("com.google.android.gms.car.ICar");
        boolean bool6 = zzlG();
        paramParcel2.writeNoException();
        if (bool6) {}
        for (int i8 = 1;; i8 = 0)
        {
          paramParcel2.writeInt(i8);
          return true;
        }
      case 4: 
        paramParcel1.enforceInterface("com.google.android.gms.car.ICar");
        int i7 = zzlH();
        paramParcel2.writeNoException();
        paramParcel2.writeInt(i7);
        return true;
      case 5: 
        paramParcel1.enforceInterface("com.google.android.gms.car.ICar");
        zza(zzak.zza.zzbq(paramParcel1.readStrongBinder()));
        paramParcel2.writeNoException();
        return true;
      case 6: 
        paramParcel1.enforceInterface("com.google.android.gms.car.ICar");
        zzb(zzak.zza.zzbq(paramParcel1.readStrongBinder()));
        paramParcel2.writeNoException();
        return true;
      case 7: 
        paramParcel1.enforceInterface("com.google.android.gms.car.ICar");
        zzaz localzzaz = zzmg();
        paramParcel2.writeNoException();
        IBinder localIBinder13 = null;
        if (localzzaz != null) {
          localIBinder13 = localzzaz.asBinder();
        }
        paramParcel2.writeStrongBinder(localIBinder13);
        return true;
      case 8: 
        paramParcel1.enforceInterface("com.google.android.gms.car.ICar");
        zzz localzzz = zzmh();
        paramParcel2.writeNoException();
        IBinder localIBinder12 = null;
        if (localzzz != null) {
          localIBinder12 = localzzz.asBinder();
        }
        paramParcel2.writeStrongBinder(localIBinder12);
        return true;
      case 9: 
        paramParcel1.enforceInterface("com.google.android.gms.car.ICar");
        zzar localzzar = zzmi();
        paramParcel2.writeNoException();
        IBinder localIBinder11 = null;
        if (localzzar != null) {
          localIBinder11 = localzzar.asBinder();
        }
        paramParcel2.writeStrongBinder(localIBinder11);
        return true;
      case 10: 
        paramParcel1.enforceInterface("com.google.android.gms.car.ICar");
        int i5 = paramParcel1.readInt();
        Intent localIntent3 = null;
        if (i5 != 0) {
          localIntent3 = (Intent)Intent.CREATOR.createFromParcel(paramParcel1);
        }
        boolean bool5 = zzn(localIntent3);
        paramParcel2.writeNoException();
        int i6 = 0;
        if (bool5) {
          i6 = 1;
        }
        paramParcel2.writeInt(i6);
        return true;
      case 11: 
        paramParcel1.enforceInterface("com.google.android.gms.car.ICar");
        int i4 = paramParcel1.readInt();
        Intent localIntent2 = null;
        if (i4 != 0) {
          localIntent2 = (Intent)Intent.CREATOR.createFromParcel(paramParcel1);
        }
        List localList4 = queryIntentCarProjectionServices(localIntent2);
        paramParcel2.writeNoException();
        paramParcel2.writeTypedList(localList4);
        return true;
      case 12: 
        paramParcel1.enforceInterface("com.google.android.gms.car.ICar");
        zzah localzzah = zzmj();
        paramParcel2.writeNoException();
        IBinder localIBinder10 = null;
        if (localzzah != null) {
          localIBinder10 = localzzah.asBinder();
        }
        paramParcel2.writeStrongBinder(localIBinder10);
        return true;
      case 13: 
        paramParcel1.enforceInterface("com.google.android.gms.car.ICar");
        zzbb localzzbb = zzbS(paramParcel1.readString());
        paramParcel2.writeNoException();
        IBinder localIBinder9 = null;
        if (localzzbb != null) {
          localIBinder9 = localzzbb.asBinder();
        }
        paramParcel2.writeStrongBinder(localIBinder9);
        return true;
      case 14: 
        paramParcel1.enforceInterface("com.google.android.gms.car.ICar");
        zzan localzzan = zzmk();
        paramParcel2.writeNoException();
        IBinder localIBinder8 = null;
        if (localzzan != null) {
          localIBinder8 = localzzan.asBinder();
        }
        paramParcel2.writeStrongBinder(localIBinder8);
        return true;
      case 15: 
        paramParcel1.enforceInterface("com.google.android.gms.car.ICar");
        zzal localzzal = zzml();
        paramParcel2.writeNoException();
        IBinder localIBinder7 = null;
        if (localzzal != null) {
          localIBinder7 = localzzal.asBinder();
        }
        paramParcel2.writeStrongBinder(localIBinder7);
        return true;
      case 16: 
        paramParcel1.enforceInterface("com.google.android.gms.car.ICar");
        zzat localzzat = zzmm();
        paramParcel2.writeNoException();
        IBinder localIBinder6 = null;
        if (localzzat != null) {
          localIBinder6 = localzzat.asBinder();
        }
        paramParcel2.writeStrongBinder(localIBinder6);
        return true;
      case 17: 
        paramParcel1.enforceInterface("com.google.android.gms.car.ICar");
        zzap localzzap = zzmn();
        paramParcel2.writeNoException();
        IBinder localIBinder5 = null;
        if (localzzap != null) {
          localIBinder5 = localzzap.asBinder();
        }
        paramParcel2.writeStrongBinder(localIBinder5);
        return true;
      case 18: 
        paramParcel1.enforceInterface("com.google.android.gms.car.ICar");
        zzaf localzzaf = zzmo();
        paramParcel2.writeNoException();
        IBinder localIBinder4 = null;
        if (localzzaf != null) {
          localIBinder4 = localzzaf.asBinder();
        }
        paramParcel2.writeStrongBinder(localIBinder4);
        return true;
      case 19: 
        paramParcel1.enforceInterface("com.google.android.gms.car.ICar");
        String str4 = paramParcel1.readString();
        if (paramParcel1.readInt() != 0) {}
        for (boolean bool3 = true;; bool3 = false)
        {
          boolean bool4 = zzg(str4, bool3);
          paramParcel2.writeNoException();
          int i3 = 0;
          if (bool4) {
            i3 = 1;
          }
          paramParcel2.writeInt(i3);
          return true;
        }
      case 20: 
        paramParcel1.enforceInterface("com.google.android.gms.car.ICar");
        zza(zzy.zza.zzbe(paramParcel1.readStrongBinder()));
        paramParcel2.writeNoException();
        return true;
      case 21: 
        paramParcel1.enforceInterface("com.google.android.gms.car.ICar");
        zzb(zzy.zza.zzbe(paramParcel1.readStrongBinder()));
        paramParcel2.writeNoException();
        return true;
      case 22: 
        paramParcel1.enforceInterface("com.google.android.gms.car.ICar");
        zzlV();
        paramParcel2.writeNoException();
        return true;
      case 23: 
        paramParcel1.enforceInterface("com.google.android.gms.car.ICar");
        String str3 = zzA(paramParcel1.readString(), paramParcel1.readString());
        paramParcel2.writeNoException();
        paramParcel2.writeString(str3);
        return true;
      case 24: 
        paramParcel1.enforceInterface("com.google.android.gms.car.ICar");
        zzB(paramParcel1.readString(), paramParcel1.readString());
        paramParcel2.writeNoException();
        return true;
      case 25: 
        paramParcel1.enforceInterface("com.google.android.gms.car.ICar");
        String str2 = paramParcel1.readString();
        int i2 = paramParcel1.readInt();
        boolean bool2 = false;
        if (i2 != 0) {
          bool2 = true;
        }
        zzh(str2, bool2);
        paramParcel2.writeNoException();
        return true;
      case 26: 
        paramParcel1.enforceInterface("com.google.android.gms.car.ICar");
        String str1 = zzbR(paramParcel1.readString());
        paramParcel2.writeNoException();
        paramParcel2.writeString(str1);
        return true;
      case 27: 
        paramParcel1.enforceInterface("com.google.android.gms.car.ICar");
        zzmp();
        paramParcel2.writeNoException();
        return true;
      case 28: 
        paramParcel1.enforceInterface("com.google.android.gms.car.ICar");
        int i1 = paramParcel1.readInt();
        CarFacet localCarFacet = null;
        if (i1 != 0) {
          localCarFacet = (CarFacet)CarFacet.CREATOR.createFromParcel(paramParcel1);
        }
        zza(localCarFacet);
        paramParcel2.writeNoException();
        return true;
      case 29: 
        paramParcel1.enforceInterface("com.google.android.gms.car.ICar");
        zza(zzaj.zza.zzbp(paramParcel1.readStrongBinder()));
        paramParcel2.writeNoException();
        return true;
      case 30: 
        paramParcel1.enforceInterface("com.google.android.gms.car.ICar");
        zzb(zzaj.zza.zzbp(paramParcel1.readStrongBinder()));
        paramParcel2.writeNoException();
        return true;
      case 31: 
        paramParcel1.enforceInterface("com.google.android.gms.car.ICar");
        zzmq();
        paramParcel2.writeNoException();
        return true;
      case 32: 
        paramParcel1.enforceInterface("com.google.android.gms.car.ICar");
        zzb localzzb = zzmr();
        paramParcel2.writeNoException();
        IBinder localIBinder3 = null;
        if (localzzb != null) {
          localIBinder3 = localzzb.asBinder();
        }
        paramParcel2.writeStrongBinder(localIBinder3);
        return true;
      case 34: 
        paramParcel1.enforceInterface("com.google.android.gms.car.ICar");
        int n = paramParcel1.readInt();
        CarFrxEvent localCarFrxEvent = null;
        if (n != 0) {
          localCarFrxEvent = (CarFrxEvent)CarFrxEvent.CREATOR.createFromParcel(paramParcel1);
        }
        zza(localCarFrxEvent);
        paramParcel2.writeNoException();
        return true;
      case 35: 
        paramParcel1.enforceInterface("com.google.android.gms.car.ICar");
        zzax localzzax = zzms();
        paramParcel2.writeNoException();
        IBinder localIBinder2 = null;
        if (localzzax != null) {
          localIBinder2 = localzzax.asBinder();
        }
        paramParcel2.writeStrongBinder(localIBinder2);
        return true;
      case 36: 
        paramParcel1.enforceInterface("com.google.android.gms.car.ICar");
        ICarRetailMode localICarRetailMode = zzmt();
        paramParcel2.writeNoException();
        IBinder localIBinder1 = null;
        if (localICarRetailMode != null) {
          localIBinder1 = localICarRetailMode.asBinder();
        }
        paramParcel2.writeStrongBinder(localIBinder1);
        return true;
      case 37: 
        paramParcel1.enforceInterface("com.google.android.gms.car.ICar");
        List localList3 = zzlT();
        paramParcel2.writeNoException();
        paramParcel2.writeTypedList(localList3);
        return true;
      case 38: 
        paramParcel1.enforceInterface("com.google.android.gms.car.ICar");
        List localList2 = zzlU();
        paramParcel2.writeNoException();
        paramParcel2.writeTypedList(localList2);
        return true;
      case 39: 
        paramParcel1.enforceInterface("com.google.android.gms.car.ICar");
        int m = paramParcel1.readInt();
        CarInfo localCarInfo2 = null;
        if (m != 0) {
          localCarInfo2 = (CarInfo)CarInfo.CREATOR.createFromParcel(paramParcel1);
        }
        zza(localCarInfo2);
        paramParcel2.writeNoException();
        return true;
      case 40: 
        paramParcel1.enforceInterface("com.google.android.gms.car.ICar");
        int k = paramParcel1.readInt();
        Intent localIntent1 = null;
        if (k != 0) {
          localIntent1 = (Intent)Intent.CREATOR.createFromParcel(paramParcel1);
        }
        List localList1 = zza(localIntent1, paramParcel1.readInt());
        paramParcel2.writeNoException();
        paramParcel2.writeTypedList(localList1);
        return true;
      case 41: 
        paramParcel1.enforceInterface("com.google.android.gms.car.ICar");
        boolean bool1 = zze(paramParcel1.readString(), paramParcel1.readInt());
        paramParcel2.writeNoException();
        int j = 0;
        if (bool1) {
          j = 1;
        }
        paramParcel2.writeInt(j);
        return true;
      }
      paramParcel1.enforceInterface("com.google.android.gms.car.ICar");
      int i = paramParcel1.readInt();
      CarInfo localCarInfo1 = null;
      if (i != 0) {
        localCarInfo1 = (CarInfo)CarInfo.CREATOR.createFromParcel(paramParcel1);
      }
      zza(localCarInfo1, paramParcel1.readString());
      paramParcel2.writeNoException();
      return true;
    }
    
    private static final class zza
      implements zzx
    {
      private IBinder zzop;
      
      zza(IBinder paramIBinder)
      {
        this.zzop = paramIBinder;
      }
      
      public final IBinder asBinder()
      {
        return this.zzop;
      }
      
      /* Error */
      public final List<ResolveInfo> queryIntentCarProjectionServices(Intent paramIntent)
        throws RemoteException
      {
        // Byte code:
        //   0: invokestatic 27	android/os/Parcel:obtain	()Landroid/os/Parcel;
        //   3: astore_2
        //   4: invokestatic 27	android/os/Parcel:obtain	()Landroid/os/Parcel;
        //   7: astore_3
        //   8: aload_2
        //   9: ldc 29
        //   11: invokevirtual 33	android/os/Parcel:writeInterfaceToken	(Ljava/lang/String;)V
        //   14: aload_1
        //   15: ifnull +53 -> 68
        //   18: aload_2
        //   19: iconst_1
        //   20: invokevirtual 37	android/os/Parcel:writeInt	(I)V
        //   23: aload_1
        //   24: aload_2
        //   25: iconst_0
        //   26: invokevirtual 43	android/content/Intent:writeToParcel	(Landroid/os/Parcel;I)V
        //   29: aload_0
        //   30: getfield 15	com/google/android/gms/car/zzx$zza$zza:zzop	Landroid/os/IBinder;
        //   33: bipush 11
        //   35: aload_2
        //   36: aload_3
        //   37: iconst_0
        //   38: invokeinterface 49 5 0
        //   43: pop
        //   44: aload_3
        //   45: invokevirtual 52	android/os/Parcel:readException	()V
        //   48: aload_3
        //   49: getstatic 58	android/content/pm/ResolveInfo:CREATOR	Landroid/os/Parcelable$Creator;
        //   52: invokevirtual 62	android/os/Parcel:createTypedArrayList	(Landroid/os/Parcelable$Creator;)Ljava/util/ArrayList;
        //   55: astore 6
        //   57: aload_3
        //   58: invokevirtual 65	android/os/Parcel:recycle	()V
        //   61: aload_2
        //   62: invokevirtual 65	android/os/Parcel:recycle	()V
        //   65: aload 6
        //   67: areturn
        //   68: aload_2
        //   69: iconst_0
        //   70: invokevirtual 37	android/os/Parcel:writeInt	(I)V
        //   73: goto -44 -> 29
        //   76: astore 4
        //   78: aload_3
        //   79: invokevirtual 65	android/os/Parcel:recycle	()V
        //   82: aload_2
        //   83: invokevirtual 65	android/os/Parcel:recycle	()V
        //   86: aload 4
        //   88: athrow
        // Local variable table:
        //   start	length	slot	name	signature
        //   0	89	0	this	zza
        //   0	89	1	paramIntent	Intent
        //   3	80	2	localParcel1	Parcel
        //   7	72	3	localParcel2	Parcel
        //   76	11	4	localObject	Object
        //   55	11	6	localArrayList	ArrayList
        // Exception table:
        //   from	to	target	type
        //   8	14	76	finally
        //   18	29	76	finally
        //   29	57	76	finally
        //   68	73	76	finally
      }
      
      public final String zzA(String paramString1, String paramString2)
        throws RemoteException
      {
        Parcel localParcel1 = Parcel.obtain();
        Parcel localParcel2 = Parcel.obtain();
        try
        {
          localParcel1.writeInterfaceToken("com.google.android.gms.car.ICar");
          localParcel1.writeString(paramString1);
          localParcel1.writeString(paramString2);
          this.zzop.transact(23, localParcel1, localParcel2, 0);
          localParcel2.readException();
          String str = localParcel2.readString();
          return str;
        }
        finally
        {
          localParcel2.recycle();
          localParcel1.recycle();
        }
      }
      
      public final void zzB(String paramString1, String paramString2)
        throws RemoteException
      {
        Parcel localParcel1 = Parcel.obtain();
        Parcel localParcel2 = Parcel.obtain();
        try
        {
          localParcel1.writeInterfaceToken("com.google.android.gms.car.ICar");
          localParcel1.writeString(paramString1);
          localParcel1.writeString(paramString2);
          this.zzop.transact(24, localParcel1, localParcel2, 0);
          localParcel2.readException();
          return;
        }
        finally
        {
          localParcel2.recycle();
          localParcel1.recycle();
        }
      }
      
      /* Error */
      public final List<ResolveInfo> zza(Intent paramIntent, int paramInt)
        throws RemoteException
      {
        // Byte code:
        //   0: invokestatic 27	android/os/Parcel:obtain	()Landroid/os/Parcel;
        //   3: astore_3
        //   4: invokestatic 27	android/os/Parcel:obtain	()Landroid/os/Parcel;
        //   7: astore 4
        //   9: aload_3
        //   10: ldc 29
        //   12: invokevirtual 33	android/os/Parcel:writeInterfaceToken	(Ljava/lang/String;)V
        //   15: aload_1
        //   16: ifnull +62 -> 78
        //   19: aload_3
        //   20: iconst_1
        //   21: invokevirtual 37	android/os/Parcel:writeInt	(I)V
        //   24: aload_1
        //   25: aload_3
        //   26: iconst_0
        //   27: invokevirtual 43	android/content/Intent:writeToParcel	(Landroid/os/Parcel;I)V
        //   30: aload_3
        //   31: iload_2
        //   32: invokevirtual 37	android/os/Parcel:writeInt	(I)V
        //   35: aload_0
        //   36: getfield 15	com/google/android/gms/car/zzx$zza$zza:zzop	Landroid/os/IBinder;
        //   39: bipush 40
        //   41: aload_3
        //   42: aload 4
        //   44: iconst_0
        //   45: invokeinterface 49 5 0
        //   50: pop
        //   51: aload 4
        //   53: invokevirtual 52	android/os/Parcel:readException	()V
        //   56: aload 4
        //   58: getstatic 58	android/content/pm/ResolveInfo:CREATOR	Landroid/os/Parcelable$Creator;
        //   61: invokevirtual 62	android/os/Parcel:createTypedArrayList	(Landroid/os/Parcelable$Creator;)Ljava/util/ArrayList;
        //   64: astore 7
        //   66: aload 4
        //   68: invokevirtual 65	android/os/Parcel:recycle	()V
        //   71: aload_3
        //   72: invokevirtual 65	android/os/Parcel:recycle	()V
        //   75: aload 7
        //   77: areturn
        //   78: aload_3
        //   79: iconst_0
        //   80: invokevirtual 37	android/os/Parcel:writeInt	(I)V
        //   83: goto -53 -> 30
        //   86: astore 5
        //   88: aload 4
        //   90: invokevirtual 65	android/os/Parcel:recycle	()V
        //   93: aload_3
        //   94: invokevirtual 65	android/os/Parcel:recycle	()V
        //   97: aload 5
        //   99: athrow
        // Local variable table:
        //   start	length	slot	name	signature
        //   0	100	0	this	zza
        //   0	100	1	paramIntent	Intent
        //   0	100	2	paramInt	int
        //   3	91	3	localParcel1	Parcel
        //   7	82	4	localParcel2	Parcel
        //   86	12	5	localObject	Object
        //   64	12	7	localArrayList	ArrayList
        // Exception table:
        //   from	to	target	type
        //   9	15	86	finally
        //   19	30	86	finally
        //   30	66	86	finally
        //   78	83	86	finally
      }
      
      /* Error */
      public final void zza(CarFacet paramCarFacet)
        throws RemoteException
      {
        // Byte code:
        //   0: invokestatic 27	android/os/Parcel:obtain	()Landroid/os/Parcel;
        //   3: astore_2
        //   4: invokestatic 27	android/os/Parcel:obtain	()Landroid/os/Parcel;
        //   7: astore_3
        //   8: aload_2
        //   9: ldc 29
        //   11: invokevirtual 33	android/os/Parcel:writeInterfaceToken	(Ljava/lang/String;)V
        //   14: aload_1
        //   15: ifnull +42 -> 57
        //   18: aload_2
        //   19: iconst_1
        //   20: invokevirtual 37	android/os/Parcel:writeInt	(I)V
        //   23: aload_1
        //   24: aload_2
        //   25: iconst_0
        //   26: invokevirtual 82	com/google/android/gms/car/CarFacet:writeToParcel	(Landroid/os/Parcel;I)V
        //   29: aload_0
        //   30: getfield 15	com/google/android/gms/car/zzx$zza$zza:zzop	Landroid/os/IBinder;
        //   33: bipush 28
        //   35: aload_2
        //   36: aload_3
        //   37: iconst_0
        //   38: invokeinterface 49 5 0
        //   43: pop
        //   44: aload_3
        //   45: invokevirtual 52	android/os/Parcel:readException	()V
        //   48: aload_3
        //   49: invokevirtual 65	android/os/Parcel:recycle	()V
        //   52: aload_2
        //   53: invokevirtual 65	android/os/Parcel:recycle	()V
        //   56: return
        //   57: aload_2
        //   58: iconst_0
        //   59: invokevirtual 37	android/os/Parcel:writeInt	(I)V
        //   62: goto -33 -> 29
        //   65: astore 4
        //   67: aload_3
        //   68: invokevirtual 65	android/os/Parcel:recycle	()V
        //   71: aload_2
        //   72: invokevirtual 65	android/os/Parcel:recycle	()V
        //   75: aload 4
        //   77: athrow
        // Local variable table:
        //   start	length	slot	name	signature
        //   0	78	0	this	zza
        //   0	78	1	paramCarFacet	CarFacet
        //   3	69	2	localParcel1	Parcel
        //   7	61	3	localParcel2	Parcel
        //   65	11	4	localObject	Object
        // Exception table:
        //   from	to	target	type
        //   8	14	65	finally
        //   18	29	65	finally
        //   29	48	65	finally
        //   57	62	65	finally
      }
      
      /* Error */
      public final void zza(CarFrxEvent paramCarFrxEvent)
        throws RemoteException
      {
        // Byte code:
        //   0: invokestatic 27	android/os/Parcel:obtain	()Landroid/os/Parcel;
        //   3: astore_2
        //   4: invokestatic 27	android/os/Parcel:obtain	()Landroid/os/Parcel;
        //   7: astore_3
        //   8: aload_2
        //   9: ldc 29
        //   11: invokevirtual 33	android/os/Parcel:writeInterfaceToken	(Ljava/lang/String;)V
        //   14: aload_1
        //   15: ifnull +42 -> 57
        //   18: aload_2
        //   19: iconst_1
        //   20: invokevirtual 37	android/os/Parcel:writeInt	(I)V
        //   23: aload_1
        //   24: aload_2
        //   25: iconst_0
        //   26: invokevirtual 86	com/google/android/gms/car/CarFrxEvent:writeToParcel	(Landroid/os/Parcel;I)V
        //   29: aload_0
        //   30: getfield 15	com/google/android/gms/car/zzx$zza$zza:zzop	Landroid/os/IBinder;
        //   33: bipush 34
        //   35: aload_2
        //   36: aload_3
        //   37: iconst_0
        //   38: invokeinterface 49 5 0
        //   43: pop
        //   44: aload_3
        //   45: invokevirtual 52	android/os/Parcel:readException	()V
        //   48: aload_3
        //   49: invokevirtual 65	android/os/Parcel:recycle	()V
        //   52: aload_2
        //   53: invokevirtual 65	android/os/Parcel:recycle	()V
        //   56: return
        //   57: aload_2
        //   58: iconst_0
        //   59: invokevirtual 37	android/os/Parcel:writeInt	(I)V
        //   62: goto -33 -> 29
        //   65: astore 4
        //   67: aload_3
        //   68: invokevirtual 65	android/os/Parcel:recycle	()V
        //   71: aload_2
        //   72: invokevirtual 65	android/os/Parcel:recycle	()V
        //   75: aload 4
        //   77: athrow
        // Local variable table:
        //   start	length	slot	name	signature
        //   0	78	0	this	zza
        //   0	78	1	paramCarFrxEvent	CarFrxEvent
        //   3	69	2	localParcel1	Parcel
        //   7	61	3	localParcel2	Parcel
        //   65	11	4	localObject	Object
        // Exception table:
        //   from	to	target	type
        //   8	14	65	finally
        //   18	29	65	finally
        //   29	48	65	finally
        //   57	62	65	finally
      }
      
      /* Error */
      public final void zza(CarInfo paramCarInfo)
        throws RemoteException
      {
        // Byte code:
        //   0: invokestatic 27	android/os/Parcel:obtain	()Landroid/os/Parcel;
        //   3: astore_2
        //   4: invokestatic 27	android/os/Parcel:obtain	()Landroid/os/Parcel;
        //   7: astore_3
        //   8: aload_2
        //   9: ldc 29
        //   11: invokevirtual 33	android/os/Parcel:writeInterfaceToken	(Ljava/lang/String;)V
        //   14: aload_1
        //   15: ifnull +42 -> 57
        //   18: aload_2
        //   19: iconst_1
        //   20: invokevirtual 37	android/os/Parcel:writeInt	(I)V
        //   23: aload_1
        //   24: aload_2
        //   25: iconst_0
        //   26: invokevirtual 90	com/google/android/gms/car/CarInfo:writeToParcel	(Landroid/os/Parcel;I)V
        //   29: aload_0
        //   30: getfield 15	com/google/android/gms/car/zzx$zza$zza:zzop	Landroid/os/IBinder;
        //   33: bipush 39
        //   35: aload_2
        //   36: aload_3
        //   37: iconst_0
        //   38: invokeinterface 49 5 0
        //   43: pop
        //   44: aload_3
        //   45: invokevirtual 52	android/os/Parcel:readException	()V
        //   48: aload_3
        //   49: invokevirtual 65	android/os/Parcel:recycle	()V
        //   52: aload_2
        //   53: invokevirtual 65	android/os/Parcel:recycle	()V
        //   56: return
        //   57: aload_2
        //   58: iconst_0
        //   59: invokevirtual 37	android/os/Parcel:writeInt	(I)V
        //   62: goto -33 -> 29
        //   65: astore 4
        //   67: aload_3
        //   68: invokevirtual 65	android/os/Parcel:recycle	()V
        //   71: aload_2
        //   72: invokevirtual 65	android/os/Parcel:recycle	()V
        //   75: aload 4
        //   77: athrow
        // Local variable table:
        //   start	length	slot	name	signature
        //   0	78	0	this	zza
        //   0	78	1	paramCarInfo	CarInfo
        //   3	69	2	localParcel1	Parcel
        //   7	61	3	localParcel2	Parcel
        //   65	11	4	localObject	Object
        // Exception table:
        //   from	to	target	type
        //   8	14	65	finally
        //   18	29	65	finally
        //   29	48	65	finally
        //   57	62	65	finally
      }
      
      /* Error */
      public final void zza(CarInfo paramCarInfo, String paramString)
        throws RemoteException
      {
        // Byte code:
        //   0: invokestatic 27	android/os/Parcel:obtain	()Landroid/os/Parcel;
        //   3: astore_3
        //   4: invokestatic 27	android/os/Parcel:obtain	()Landroid/os/Parcel;
        //   7: astore 4
        //   9: aload_3
        //   10: ldc 29
        //   12: invokevirtual 33	android/os/Parcel:writeInterfaceToken	(Ljava/lang/String;)V
        //   15: aload_1
        //   16: ifnull +50 -> 66
        //   19: aload_3
        //   20: iconst_1
        //   21: invokevirtual 37	android/os/Parcel:writeInt	(I)V
        //   24: aload_1
        //   25: aload_3
        //   26: iconst_0
        //   27: invokevirtual 90	com/google/android/gms/car/CarInfo:writeToParcel	(Landroid/os/Parcel;I)V
        //   30: aload_3
        //   31: aload_2
        //   32: invokevirtual 70	android/os/Parcel:writeString	(Ljava/lang/String;)V
        //   35: aload_0
        //   36: getfield 15	com/google/android/gms/car/zzx$zza$zza:zzop	Landroid/os/IBinder;
        //   39: bipush 42
        //   41: aload_3
        //   42: aload 4
        //   44: iconst_0
        //   45: invokeinterface 49 5 0
        //   50: pop
        //   51: aload 4
        //   53: invokevirtual 52	android/os/Parcel:readException	()V
        //   56: aload 4
        //   58: invokevirtual 65	android/os/Parcel:recycle	()V
        //   61: aload_3
        //   62: invokevirtual 65	android/os/Parcel:recycle	()V
        //   65: return
        //   66: aload_3
        //   67: iconst_0
        //   68: invokevirtual 37	android/os/Parcel:writeInt	(I)V
        //   71: goto -41 -> 30
        //   74: astore 5
        //   76: aload 4
        //   78: invokevirtual 65	android/os/Parcel:recycle	()V
        //   81: aload_3
        //   82: invokevirtual 65	android/os/Parcel:recycle	()V
        //   85: aload 5
        //   87: athrow
        // Local variable table:
        //   start	length	slot	name	signature
        //   0	88	0	this	zza
        //   0	88	1	paramCarInfo	CarInfo
        //   0	88	2	paramString	String
        //   3	79	3	localParcel1	Parcel
        //   7	70	4	localParcel2	Parcel
        //   74	12	5	localObject	Object
        // Exception table:
        //   from	to	target	type
        //   9	15	74	finally
        //   19	30	74	finally
        //   30	56	74	finally
        //   66	71	74	finally
      }
      
      /* Error */
      public final void zza(zzaj paramzzaj)
        throws RemoteException
      {
        // Byte code:
        //   0: invokestatic 27	android/os/Parcel:obtain	()Landroid/os/Parcel;
        //   3: astore_2
        //   4: invokestatic 27	android/os/Parcel:obtain	()Landroid/os/Parcel;
        //   7: astore_3
        //   8: aload_2
        //   9: ldc 29
        //   11: invokevirtual 33	android/os/Parcel:writeInterfaceToken	(Ljava/lang/String;)V
        //   14: aload_1
        //   15: ifnull +45 -> 60
        //   18: aload_1
        //   19: invokeinterface 96 1 0
        //   24: astore 5
        //   26: aload_2
        //   27: aload 5
        //   29: invokevirtual 99	android/os/Parcel:writeStrongBinder	(Landroid/os/IBinder;)V
        //   32: aload_0
        //   33: getfield 15	com/google/android/gms/car/zzx$zza$zza:zzop	Landroid/os/IBinder;
        //   36: bipush 29
        //   38: aload_2
        //   39: aload_3
        //   40: iconst_0
        //   41: invokeinterface 49 5 0
        //   46: pop
        //   47: aload_3
        //   48: invokevirtual 52	android/os/Parcel:readException	()V
        //   51: aload_3
        //   52: invokevirtual 65	android/os/Parcel:recycle	()V
        //   55: aload_2
        //   56: invokevirtual 65	android/os/Parcel:recycle	()V
        //   59: return
        //   60: aconst_null
        //   61: astore 5
        //   63: goto -37 -> 26
        //   66: astore 4
        //   68: aload_3
        //   69: invokevirtual 65	android/os/Parcel:recycle	()V
        //   72: aload_2
        //   73: invokevirtual 65	android/os/Parcel:recycle	()V
        //   76: aload 4
        //   78: athrow
        // Local variable table:
        //   start	length	slot	name	signature
        //   0	79	0	this	zza
        //   0	79	1	paramzzaj	zzaj
        //   3	70	2	localParcel1	Parcel
        //   7	62	3	localParcel2	Parcel
        //   66	11	4	localObject	Object
        //   24	38	5	localIBinder	IBinder
        // Exception table:
        //   from	to	target	type
        //   8	14	66	finally
        //   18	26	66	finally
        //   26	51	66	finally
      }
      
      /* Error */
      public final void zza(zzak paramzzak)
        throws RemoteException
      {
        // Byte code:
        //   0: invokestatic 27	android/os/Parcel:obtain	()Landroid/os/Parcel;
        //   3: astore_2
        //   4: invokestatic 27	android/os/Parcel:obtain	()Landroid/os/Parcel;
        //   7: astore_3
        //   8: aload_2
        //   9: ldc 29
        //   11: invokevirtual 33	android/os/Parcel:writeInterfaceToken	(Ljava/lang/String;)V
        //   14: aload_1
        //   15: ifnull +44 -> 59
        //   18: aload_1
        //   19: invokeinterface 103 1 0
        //   24: astore 5
        //   26: aload_2
        //   27: aload 5
        //   29: invokevirtual 99	android/os/Parcel:writeStrongBinder	(Landroid/os/IBinder;)V
        //   32: aload_0
        //   33: getfield 15	com/google/android/gms/car/zzx$zza$zza:zzop	Landroid/os/IBinder;
        //   36: iconst_5
        //   37: aload_2
        //   38: aload_3
        //   39: iconst_0
        //   40: invokeinterface 49 5 0
        //   45: pop
        //   46: aload_3
        //   47: invokevirtual 52	android/os/Parcel:readException	()V
        //   50: aload_3
        //   51: invokevirtual 65	android/os/Parcel:recycle	()V
        //   54: aload_2
        //   55: invokevirtual 65	android/os/Parcel:recycle	()V
        //   58: return
        //   59: aconst_null
        //   60: astore 5
        //   62: goto -36 -> 26
        //   65: astore 4
        //   67: aload_3
        //   68: invokevirtual 65	android/os/Parcel:recycle	()V
        //   71: aload_2
        //   72: invokevirtual 65	android/os/Parcel:recycle	()V
        //   75: aload 4
        //   77: athrow
        // Local variable table:
        //   start	length	slot	name	signature
        //   0	78	0	this	zza
        //   0	78	1	paramzzak	zzak
        //   3	69	2	localParcel1	Parcel
        //   7	61	3	localParcel2	Parcel
        //   65	11	4	localObject	Object
        //   24	37	5	localIBinder	IBinder
        // Exception table:
        //   from	to	target	type
        //   8	14	65	finally
        //   18	26	65	finally
        //   26	50	65	finally
      }
      
      /* Error */
      public final void zza(zzy paramzzy)
        throws RemoteException
      {
        // Byte code:
        //   0: invokestatic 27	android/os/Parcel:obtain	()Landroid/os/Parcel;
        //   3: astore_2
        //   4: invokestatic 27	android/os/Parcel:obtain	()Landroid/os/Parcel;
        //   7: astore_3
        //   8: aload_2
        //   9: ldc 29
        //   11: invokevirtual 33	android/os/Parcel:writeInterfaceToken	(Ljava/lang/String;)V
        //   14: aload_1
        //   15: ifnull +45 -> 60
        //   18: aload_1
        //   19: invokeinterface 107 1 0
        //   24: astore 5
        //   26: aload_2
        //   27: aload 5
        //   29: invokevirtual 99	android/os/Parcel:writeStrongBinder	(Landroid/os/IBinder;)V
        //   32: aload_0
        //   33: getfield 15	com/google/android/gms/car/zzx$zza$zza:zzop	Landroid/os/IBinder;
        //   36: bipush 20
        //   38: aload_2
        //   39: aload_3
        //   40: iconst_0
        //   41: invokeinterface 49 5 0
        //   46: pop
        //   47: aload_3
        //   48: invokevirtual 52	android/os/Parcel:readException	()V
        //   51: aload_3
        //   52: invokevirtual 65	android/os/Parcel:recycle	()V
        //   55: aload_2
        //   56: invokevirtual 65	android/os/Parcel:recycle	()V
        //   59: return
        //   60: aconst_null
        //   61: astore 5
        //   63: goto -37 -> 26
        //   66: astore 4
        //   68: aload_3
        //   69: invokevirtual 65	android/os/Parcel:recycle	()V
        //   72: aload_2
        //   73: invokevirtual 65	android/os/Parcel:recycle	()V
        //   76: aload 4
        //   78: athrow
        // Local variable table:
        //   start	length	slot	name	signature
        //   0	79	0	this	zza
        //   0	79	1	paramzzy	zzy
        //   3	70	2	localParcel1	Parcel
        //   7	62	3	localParcel2	Parcel
        //   66	11	4	localObject	Object
        //   24	38	5	localIBinder	IBinder
        // Exception table:
        //   from	to	target	type
        //   8	14	66	finally
        //   18	26	66	finally
        //   26	51	66	finally
      }
      
      /* Error */
      public final void zzb(zzaj paramzzaj)
        throws RemoteException
      {
        // Byte code:
        //   0: invokestatic 27	android/os/Parcel:obtain	()Landroid/os/Parcel;
        //   3: astore_2
        //   4: invokestatic 27	android/os/Parcel:obtain	()Landroid/os/Parcel;
        //   7: astore_3
        //   8: aload_2
        //   9: ldc 29
        //   11: invokevirtual 33	android/os/Parcel:writeInterfaceToken	(Ljava/lang/String;)V
        //   14: aload_1
        //   15: ifnull +45 -> 60
        //   18: aload_1
        //   19: invokeinterface 96 1 0
        //   24: astore 5
        //   26: aload_2
        //   27: aload 5
        //   29: invokevirtual 99	android/os/Parcel:writeStrongBinder	(Landroid/os/IBinder;)V
        //   32: aload_0
        //   33: getfield 15	com/google/android/gms/car/zzx$zza$zza:zzop	Landroid/os/IBinder;
        //   36: bipush 30
        //   38: aload_2
        //   39: aload_3
        //   40: iconst_0
        //   41: invokeinterface 49 5 0
        //   46: pop
        //   47: aload_3
        //   48: invokevirtual 52	android/os/Parcel:readException	()V
        //   51: aload_3
        //   52: invokevirtual 65	android/os/Parcel:recycle	()V
        //   55: aload_2
        //   56: invokevirtual 65	android/os/Parcel:recycle	()V
        //   59: return
        //   60: aconst_null
        //   61: astore 5
        //   63: goto -37 -> 26
        //   66: astore 4
        //   68: aload_3
        //   69: invokevirtual 65	android/os/Parcel:recycle	()V
        //   72: aload_2
        //   73: invokevirtual 65	android/os/Parcel:recycle	()V
        //   76: aload 4
        //   78: athrow
        // Local variable table:
        //   start	length	slot	name	signature
        //   0	79	0	this	zza
        //   0	79	1	paramzzaj	zzaj
        //   3	70	2	localParcel1	Parcel
        //   7	62	3	localParcel2	Parcel
        //   66	11	4	localObject	Object
        //   24	38	5	localIBinder	IBinder
        // Exception table:
        //   from	to	target	type
        //   8	14	66	finally
        //   18	26	66	finally
        //   26	51	66	finally
      }
      
      /* Error */
      public final void zzb(zzak paramzzak)
        throws RemoteException
      {
        // Byte code:
        //   0: invokestatic 27	android/os/Parcel:obtain	()Landroid/os/Parcel;
        //   3: astore_2
        //   4: invokestatic 27	android/os/Parcel:obtain	()Landroid/os/Parcel;
        //   7: astore_3
        //   8: aload_2
        //   9: ldc 29
        //   11: invokevirtual 33	android/os/Parcel:writeInterfaceToken	(Ljava/lang/String;)V
        //   14: aload_1
        //   15: ifnull +45 -> 60
        //   18: aload_1
        //   19: invokeinterface 103 1 0
        //   24: astore 5
        //   26: aload_2
        //   27: aload 5
        //   29: invokevirtual 99	android/os/Parcel:writeStrongBinder	(Landroid/os/IBinder;)V
        //   32: aload_0
        //   33: getfield 15	com/google/android/gms/car/zzx$zza$zza:zzop	Landroid/os/IBinder;
        //   36: bipush 6
        //   38: aload_2
        //   39: aload_3
        //   40: iconst_0
        //   41: invokeinterface 49 5 0
        //   46: pop
        //   47: aload_3
        //   48: invokevirtual 52	android/os/Parcel:readException	()V
        //   51: aload_3
        //   52: invokevirtual 65	android/os/Parcel:recycle	()V
        //   55: aload_2
        //   56: invokevirtual 65	android/os/Parcel:recycle	()V
        //   59: return
        //   60: aconst_null
        //   61: astore 5
        //   63: goto -37 -> 26
        //   66: astore 4
        //   68: aload_3
        //   69: invokevirtual 65	android/os/Parcel:recycle	()V
        //   72: aload_2
        //   73: invokevirtual 65	android/os/Parcel:recycle	()V
        //   76: aload 4
        //   78: athrow
        // Local variable table:
        //   start	length	slot	name	signature
        //   0	79	0	this	zza
        //   0	79	1	paramzzak	zzak
        //   3	70	2	localParcel1	Parcel
        //   7	62	3	localParcel2	Parcel
        //   66	11	4	localObject	Object
        //   24	38	5	localIBinder	IBinder
        // Exception table:
        //   from	to	target	type
        //   8	14	66	finally
        //   18	26	66	finally
        //   26	51	66	finally
      }
      
      /* Error */
      public final void zzb(zzy paramzzy)
        throws RemoteException
      {
        // Byte code:
        //   0: invokestatic 27	android/os/Parcel:obtain	()Landroid/os/Parcel;
        //   3: astore_2
        //   4: invokestatic 27	android/os/Parcel:obtain	()Landroid/os/Parcel;
        //   7: astore_3
        //   8: aload_2
        //   9: ldc 29
        //   11: invokevirtual 33	android/os/Parcel:writeInterfaceToken	(Ljava/lang/String;)V
        //   14: aload_1
        //   15: ifnull +45 -> 60
        //   18: aload_1
        //   19: invokeinterface 107 1 0
        //   24: astore 5
        //   26: aload_2
        //   27: aload 5
        //   29: invokevirtual 99	android/os/Parcel:writeStrongBinder	(Landroid/os/IBinder;)V
        //   32: aload_0
        //   33: getfield 15	com/google/android/gms/car/zzx$zza$zza:zzop	Landroid/os/IBinder;
        //   36: bipush 21
        //   38: aload_2
        //   39: aload_3
        //   40: iconst_0
        //   41: invokeinterface 49 5 0
        //   46: pop
        //   47: aload_3
        //   48: invokevirtual 52	android/os/Parcel:readException	()V
        //   51: aload_3
        //   52: invokevirtual 65	android/os/Parcel:recycle	()V
        //   55: aload_2
        //   56: invokevirtual 65	android/os/Parcel:recycle	()V
        //   59: return
        //   60: aconst_null
        //   61: astore 5
        //   63: goto -37 -> 26
        //   66: astore 4
        //   68: aload_3
        //   69: invokevirtual 65	android/os/Parcel:recycle	()V
        //   72: aload_2
        //   73: invokevirtual 65	android/os/Parcel:recycle	()V
        //   76: aload 4
        //   78: athrow
        // Local variable table:
        //   start	length	slot	name	signature
        //   0	79	0	this	zza
        //   0	79	1	paramzzy	zzy
        //   3	70	2	localParcel1	Parcel
        //   7	62	3	localParcel2	Parcel
        //   66	11	4	localObject	Object
        //   24	38	5	localIBinder	IBinder
        // Exception table:
        //   from	to	target	type
        //   8	14	66	finally
        //   18	26	66	finally
        //   26	51	66	finally
      }
      
      public final String zzbR(String paramString)
        throws RemoteException
      {
        Parcel localParcel1 = Parcel.obtain();
        Parcel localParcel2 = Parcel.obtain();
        try
        {
          localParcel1.writeInterfaceToken("com.google.android.gms.car.ICar");
          localParcel1.writeString(paramString);
          this.zzop.transact(26, localParcel1, localParcel2, 0);
          localParcel2.readException();
          String str = localParcel2.readString();
          return str;
        }
        finally
        {
          localParcel2.recycle();
          localParcel1.recycle();
        }
      }
      
      public final zzbb zzbS(String paramString)
        throws RemoteException
      {
        Parcel localParcel1 = Parcel.obtain();
        Parcel localParcel2 = Parcel.obtain();
        try
        {
          localParcel1.writeInterfaceToken("com.google.android.gms.car.ICar");
          localParcel1.writeString(paramString);
          this.zzop.transact(13, localParcel1, localParcel2, 0);
          localParcel2.readException();
          zzbb localzzbb = zzbb.zza.zzbI(localParcel2.readStrongBinder());
          return localzzbb;
        }
        finally
        {
          localParcel2.recycle();
          localParcel1.recycle();
        }
      }
      
      public final boolean zze(String paramString, int paramInt)
        throws RemoteException
      {
        Parcel localParcel1 = Parcel.obtain();
        Parcel localParcel2 = Parcel.obtain();
        try
        {
          localParcel1.writeInterfaceToken("com.google.android.gms.car.ICar");
          localParcel1.writeString(paramString);
          localParcel1.writeInt(paramInt);
          this.zzop.transact(41, localParcel1, localParcel2, 0);
          localParcel2.readException();
          int i = localParcel2.readInt();
          boolean bool = false;
          if (i != 0) {
            bool = true;
          }
          return bool;
        }
        finally
        {
          localParcel2.recycle();
          localParcel1.recycle();
        }
      }
      
      /* Error */
      public final boolean zzg(String paramString, boolean paramBoolean)
        throws RemoteException
      {
        // Byte code:
        //   0: iconst_1
        //   1: istore_3
        //   2: invokestatic 27	android/os/Parcel:obtain	()Landroid/os/Parcel;
        //   5: astore 4
        //   7: invokestatic 27	android/os/Parcel:obtain	()Landroid/os/Parcel;
        //   10: astore 5
        //   12: aload 4
        //   14: ldc 29
        //   16: invokevirtual 33	android/os/Parcel:writeInterfaceToken	(Ljava/lang/String;)V
        //   19: aload 4
        //   21: aload_1
        //   22: invokevirtual 70	android/os/Parcel:writeString	(Ljava/lang/String;)V
        //   25: iload_2
        //   26: ifeq +59 -> 85
        //   29: iload_3
        //   30: istore 7
        //   32: aload 4
        //   34: iload 7
        //   36: invokevirtual 37	android/os/Parcel:writeInt	(I)V
        //   39: aload_0
        //   40: getfield 15	com/google/android/gms/car/zzx$zza$zza:zzop	Landroid/os/IBinder;
        //   43: bipush 19
        //   45: aload 4
        //   47: aload 5
        //   49: iconst_0
        //   50: invokeinterface 49 5 0
        //   55: pop
        //   56: aload 5
        //   58: invokevirtual 52	android/os/Parcel:readException	()V
        //   61: aload 5
        //   63: invokevirtual 127	android/os/Parcel:readInt	()I
        //   66: istore 9
        //   68: iload 9
        //   70: ifeq +21 -> 91
        //   73: aload 5
        //   75: invokevirtual 65	android/os/Parcel:recycle	()V
        //   78: aload 4
        //   80: invokevirtual 65	android/os/Parcel:recycle	()V
        //   83: iload_3
        //   84: ireturn
        //   85: iconst_0
        //   86: istore 7
        //   88: goto -56 -> 32
        //   91: iconst_0
        //   92: istore_3
        //   93: goto -20 -> 73
        //   96: astore 6
        //   98: aload 5
        //   100: invokevirtual 65	android/os/Parcel:recycle	()V
        //   103: aload 4
        //   105: invokevirtual 65	android/os/Parcel:recycle	()V
        //   108: aload 6
        //   110: athrow
        // Local variable table:
        //   start	length	slot	name	signature
        //   0	111	0	this	zza
        //   0	111	1	paramString	String
        //   0	111	2	paramBoolean	boolean
        //   1	92	3	i	int
        //   5	99	4	localParcel1	Parcel
        //   10	89	5	localParcel2	Parcel
        //   96	13	6	localObject	Object
        //   30	5	7	j	int
        //   86	1	7	k	int
        //   66	3	9	m	int
        // Exception table:
        //   from	to	target	type
        //   12	25	96	finally
        //   32	68	96	finally
      }
      
      public final void zzh(String paramString, boolean paramBoolean)
        throws RemoteException
      {
        Parcel localParcel1 = Parcel.obtain();
        Parcel localParcel2 = Parcel.obtain();
        try
        {
          localParcel1.writeInterfaceToken("com.google.android.gms.car.ICar");
          localParcel1.writeString(paramString);
          int i = 0;
          if (paramBoolean) {
            i = 1;
          }
          localParcel1.writeInt(i);
          this.zzop.transact(25, localParcel1, localParcel2, 0);
          localParcel2.readException();
          return;
        }
        finally
        {
          localParcel2.recycle();
          localParcel1.recycle();
        }
      }
      
      public final boolean zzlG()
        throws RemoteException
      {
        Parcel localParcel1 = Parcel.obtain();
        Parcel localParcel2 = Parcel.obtain();
        try
        {
          localParcel1.writeInterfaceToken("com.google.android.gms.car.ICar");
          this.zzop.transact(3, localParcel1, localParcel2, 0);
          localParcel2.readException();
          int i = localParcel2.readInt();
          boolean bool = false;
          if (i != 0) {
            bool = true;
          }
          return bool;
        }
        finally
        {
          localParcel2.recycle();
          localParcel1.recycle();
        }
      }
      
      public final int zzlH()
        throws RemoteException
      {
        Parcel localParcel1 = Parcel.obtain();
        Parcel localParcel2 = Parcel.obtain();
        try
        {
          localParcel1.writeInterfaceToken("com.google.android.gms.car.ICar");
          this.zzop.transact(4, localParcel1, localParcel2, 0);
          localParcel2.readException();
          int i = localParcel2.readInt();
          return i;
        }
        finally
        {
          localParcel2.recycle();
          localParcel1.recycle();
        }
      }
      
      /* Error */
      public final CarInfo zzlI()
        throws RemoteException
      {
        // Byte code:
        //   0: invokestatic 27	android/os/Parcel:obtain	()Landroid/os/Parcel;
        //   3: astore_1
        //   4: invokestatic 27	android/os/Parcel:obtain	()Landroid/os/Parcel;
        //   7: astore_2
        //   8: aload_1
        //   9: ldc 29
        //   11: invokevirtual 33	android/os/Parcel:writeInterfaceToken	(Ljava/lang/String;)V
        //   14: aload_0
        //   15: getfield 15	com/google/android/gms/car/zzx$zza$zza:zzop	Landroid/os/IBinder;
        //   18: iconst_1
        //   19: aload_1
        //   20: aload_2
        //   21: iconst_0
        //   22: invokeinterface 49 5 0
        //   27: pop
        //   28: aload_2
        //   29: invokevirtual 52	android/os/Parcel:readException	()V
        //   32: aload_2
        //   33: invokevirtual 127	android/os/Parcel:readInt	()I
        //   36: ifeq +28 -> 64
        //   39: getstatic 137	com/google/android/gms/car/CarInfo:CREATOR	Landroid/os/Parcelable$Creator;
        //   42: aload_2
        //   43: invokeinterface 143 2 0
        //   48: checkcast 89	com/google/android/gms/car/CarInfo
        //   51: astore 5
        //   53: aload_2
        //   54: invokevirtual 65	android/os/Parcel:recycle	()V
        //   57: aload_1
        //   58: invokevirtual 65	android/os/Parcel:recycle	()V
        //   61: aload 5
        //   63: areturn
        //   64: aconst_null
        //   65: astore 5
        //   67: goto -14 -> 53
        //   70: astore_3
        //   71: aload_2
        //   72: invokevirtual 65	android/os/Parcel:recycle	()V
        //   75: aload_1
        //   76: invokevirtual 65	android/os/Parcel:recycle	()V
        //   79: aload_3
        //   80: athrow
        // Local variable table:
        //   start	length	slot	name	signature
        //   0	81	0	this	zza
        //   3	73	1	localParcel1	Parcel
        //   7	65	2	localParcel2	Parcel
        //   70	10	3	localObject	Object
        //   51	15	5	localCarInfo	CarInfo
        // Exception table:
        //   from	to	target	type
        //   8	53	70	finally
      }
      
      /* Error */
      public final CarUiInfo zzlJ()
        throws RemoteException
      {
        // Byte code:
        //   0: invokestatic 27	android/os/Parcel:obtain	()Landroid/os/Parcel;
        //   3: astore_1
        //   4: invokestatic 27	android/os/Parcel:obtain	()Landroid/os/Parcel;
        //   7: astore_2
        //   8: aload_1
        //   9: ldc 29
        //   11: invokevirtual 33	android/os/Parcel:writeInterfaceToken	(Ljava/lang/String;)V
        //   14: aload_0
        //   15: getfield 15	com/google/android/gms/car/zzx$zza$zza:zzop	Landroid/os/IBinder;
        //   18: iconst_2
        //   19: aload_1
        //   20: aload_2
        //   21: iconst_0
        //   22: invokeinterface 49 5 0
        //   27: pop
        //   28: aload_2
        //   29: invokevirtual 52	android/os/Parcel:readException	()V
        //   32: aload_2
        //   33: invokevirtual 127	android/os/Parcel:readInt	()I
        //   36: ifeq +28 -> 64
        //   39: getstatic 148	com/google/android/gms/car/CarUiInfo:CREATOR	Landroid/os/Parcelable$Creator;
        //   42: aload_2
        //   43: invokeinterface 143 2 0
        //   48: checkcast 147	com/google/android/gms/car/CarUiInfo
        //   51: astore 5
        //   53: aload_2
        //   54: invokevirtual 65	android/os/Parcel:recycle	()V
        //   57: aload_1
        //   58: invokevirtual 65	android/os/Parcel:recycle	()V
        //   61: aload 5
        //   63: areturn
        //   64: aconst_null
        //   65: astore 5
        //   67: goto -14 -> 53
        //   70: astore_3
        //   71: aload_2
        //   72: invokevirtual 65	android/os/Parcel:recycle	()V
        //   75: aload_1
        //   76: invokevirtual 65	android/os/Parcel:recycle	()V
        //   79: aload_3
        //   80: athrow
        // Local variable table:
        //   start	length	slot	name	signature
        //   0	81	0	this	zza
        //   3	73	1	localParcel1	Parcel
        //   7	65	2	localParcel2	Parcel
        //   70	10	3	localObject	Object
        //   51	15	5	localCarUiInfo	CarUiInfo
        // Exception table:
        //   from	to	target	type
        //   8	53	70	finally
      }
      
      public final List<CarInfo> zzlT()
        throws RemoteException
      {
        Parcel localParcel1 = Parcel.obtain();
        Parcel localParcel2 = Parcel.obtain();
        try
        {
          localParcel1.writeInterfaceToken("com.google.android.gms.car.ICar");
          this.zzop.transact(37, localParcel1, localParcel2, 0);
          localParcel2.readException();
          ArrayList localArrayList = localParcel2.createTypedArrayList(CarInfo.CREATOR);
          return localArrayList;
        }
        finally
        {
          localParcel2.recycle();
          localParcel1.recycle();
        }
      }
      
      public final List<CarInfo> zzlU()
        throws RemoteException
      {
        Parcel localParcel1 = Parcel.obtain();
        Parcel localParcel2 = Parcel.obtain();
        try
        {
          localParcel1.writeInterfaceToken("com.google.android.gms.car.ICar");
          this.zzop.transact(38, localParcel1, localParcel2, 0);
          localParcel2.readException();
          ArrayList localArrayList = localParcel2.createTypedArrayList(CarInfo.CREATOR);
          return localArrayList;
        }
        finally
        {
          localParcel2.recycle();
          localParcel1.recycle();
        }
      }
      
      public final void zzlV()
        throws RemoteException
      {
        Parcel localParcel1 = Parcel.obtain();
        Parcel localParcel2 = Parcel.obtain();
        try
        {
          localParcel1.writeInterfaceToken("com.google.android.gms.car.ICar");
          this.zzop.transact(22, localParcel1, localParcel2, 0);
          localParcel2.readException();
          return;
        }
        finally
        {
          localParcel2.recycle();
          localParcel1.recycle();
        }
      }
      
      public final zzaz zzmg()
        throws RemoteException
      {
        Parcel localParcel1 = Parcel.obtain();
        Parcel localParcel2 = Parcel.obtain();
        try
        {
          localParcel1.writeInterfaceToken("com.google.android.gms.car.ICar");
          this.zzop.transact(7, localParcel1, localParcel2, 0);
          localParcel2.readException();
          zzaz localzzaz = zzaz.zza.zzbG(localParcel2.readStrongBinder());
          return localzzaz;
        }
        finally
        {
          localParcel2.recycle();
          localParcel1.recycle();
        }
      }
      
      public final zzz zzmh()
        throws RemoteException
      {
        Parcel localParcel1 = Parcel.obtain();
        Parcel localParcel2 = Parcel.obtain();
        try
        {
          localParcel1.writeInterfaceToken("com.google.android.gms.car.ICar");
          this.zzop.transact(8, localParcel1, localParcel2, 0);
          localParcel2.readException();
          zzz localzzz = zzz.zza.zzbf(localParcel2.readStrongBinder());
          return localzzz;
        }
        finally
        {
          localParcel2.recycle();
          localParcel1.recycle();
        }
      }
      
      public final zzar zzmi()
        throws RemoteException
      {
        Parcel localParcel1 = Parcel.obtain();
        Parcel localParcel2 = Parcel.obtain();
        try
        {
          localParcel1.writeInterfaceToken("com.google.android.gms.car.ICar");
          this.zzop.transact(9, localParcel1, localParcel2, 0);
          localParcel2.readException();
          zzar localzzar = zzar.zza.zzbx(localParcel2.readStrongBinder());
          return localzzar;
        }
        finally
        {
          localParcel2.recycle();
          localParcel1.recycle();
        }
      }
      
      public final zzah zzmj()
        throws RemoteException
      {
        Parcel localParcel1 = Parcel.obtain();
        Parcel localParcel2 = Parcel.obtain();
        try
        {
          localParcel1.writeInterfaceToken("com.google.android.gms.car.ICar");
          this.zzop.transact(12, localParcel1, localParcel2, 0);
          localParcel2.readException();
          zzah localzzah = zzah.zza.zzbn(localParcel2.readStrongBinder());
          return localzzah;
        }
        finally
        {
          localParcel2.recycle();
          localParcel1.recycle();
        }
      }
      
      public final zzan zzmk()
        throws RemoteException
      {
        Parcel localParcel1 = Parcel.obtain();
        Parcel localParcel2 = Parcel.obtain();
        try
        {
          localParcel1.writeInterfaceToken("com.google.android.gms.car.ICar");
          this.zzop.transact(14, localParcel1, localParcel2, 0);
          localParcel2.readException();
          zzan localzzan = zzan.zza.zzbt(localParcel2.readStrongBinder());
          return localzzan;
        }
        finally
        {
          localParcel2.recycle();
          localParcel1.recycle();
        }
      }
      
      public final zzal zzml()
        throws RemoteException
      {
        Parcel localParcel1 = Parcel.obtain();
        Parcel localParcel2 = Parcel.obtain();
        try
        {
          localParcel1.writeInterfaceToken("com.google.android.gms.car.ICar");
          this.zzop.transact(15, localParcel1, localParcel2, 0);
          localParcel2.readException();
          zzal localzzal = zzal.zza.zzbr(localParcel2.readStrongBinder());
          return localzzal;
        }
        finally
        {
          localParcel2.recycle();
          localParcel1.recycle();
        }
      }
      
      public final zzat zzmm()
        throws RemoteException
      {
        Parcel localParcel1 = Parcel.obtain();
        Parcel localParcel2 = Parcel.obtain();
        try
        {
          localParcel1.writeInterfaceToken("com.google.android.gms.car.ICar");
          this.zzop.transact(16, localParcel1, localParcel2, 0);
          localParcel2.readException();
          zzat localzzat = zzat.zza.zzbz(localParcel2.readStrongBinder());
          return localzzat;
        }
        finally
        {
          localParcel2.recycle();
          localParcel1.recycle();
        }
      }
      
      public final zzap zzmn()
        throws RemoteException
      {
        Parcel localParcel1 = Parcel.obtain();
        Parcel localParcel2 = Parcel.obtain();
        try
        {
          localParcel1.writeInterfaceToken("com.google.android.gms.car.ICar");
          this.zzop.transact(17, localParcel1, localParcel2, 0);
          localParcel2.readException();
          zzap localzzap = zzap.zza.zzbv(localParcel2.readStrongBinder());
          return localzzap;
        }
        finally
        {
          localParcel2.recycle();
          localParcel1.recycle();
        }
      }
      
      public final zzaf zzmo()
        throws RemoteException
      {
        Parcel localParcel1 = Parcel.obtain();
        Parcel localParcel2 = Parcel.obtain();
        try
        {
          localParcel1.writeInterfaceToken("com.google.android.gms.car.ICar");
          this.zzop.transact(18, localParcel1, localParcel2, 0);
          localParcel2.readException();
          zzaf localzzaf = zzaf.zza.zzbl(localParcel2.readStrongBinder());
          return localzzaf;
        }
        finally
        {
          localParcel2.recycle();
          localParcel1.recycle();
        }
      }
      
      public final void zzmp()
        throws RemoteException
      {
        Parcel localParcel1 = Parcel.obtain();
        Parcel localParcel2 = Parcel.obtain();
        try
        {
          localParcel1.writeInterfaceToken("com.google.android.gms.car.ICar");
          this.zzop.transact(27, localParcel1, localParcel2, 0);
          localParcel2.readException();
          return;
        }
        finally
        {
          localParcel2.recycle();
          localParcel1.recycle();
        }
      }
      
      public final void zzmq()
        throws RemoteException
      {
        Parcel localParcel1 = Parcel.obtain();
        Parcel localParcel2 = Parcel.obtain();
        try
        {
          localParcel1.writeInterfaceToken("com.google.android.gms.car.ICar");
          this.zzop.transact(31, localParcel1, localParcel2, 0);
          localParcel2.readException();
          return;
        }
        finally
        {
          localParcel2.recycle();
          localParcel1.recycle();
        }
      }
      
      public final zzb zzmr()
        throws RemoteException
      {
        Parcel localParcel1 = Parcel.obtain();
        Parcel localParcel2 = Parcel.obtain();
        try
        {
          localParcel1.writeInterfaceToken("com.google.android.gms.car.ICar");
          this.zzop.transact(32, localParcel1, localParcel2, 0);
          localParcel2.readException();
          zzb localzzb = zzb.zza.zzbK(localParcel2.readStrongBinder());
          return localzzb;
        }
        finally
        {
          localParcel2.recycle();
          localParcel1.recycle();
        }
      }
      
      public final zzax zzms()
        throws RemoteException
      {
        Parcel localParcel1 = Parcel.obtain();
        Parcel localParcel2 = Parcel.obtain();
        try
        {
          localParcel1.writeInterfaceToken("com.google.android.gms.car.ICar");
          this.zzop.transact(35, localParcel1, localParcel2, 0);
          localParcel2.readException();
          zzax localzzax = zzax.zza.zzbC(localParcel2.readStrongBinder());
          return localzzax;
        }
        finally
        {
          localParcel2.recycle();
          localParcel1.recycle();
        }
      }
      
      public final ICarRetailMode zzmt()
        throws RemoteException
      {
        Parcel localParcel1 = Parcel.obtain();
        Parcel localParcel2 = Parcel.obtain();
        try
        {
          localParcel1.writeInterfaceToken("com.google.android.gms.car.ICar");
          this.zzop.transact(36, localParcel1, localParcel2, 0);
          localParcel2.readException();
          ICarRetailMode localICarRetailMode = ICarRetailMode.zza.zzbE(localParcel2.readStrongBinder());
          return localICarRetailMode;
        }
        finally
        {
          localParcel2.recycle();
          localParcel1.recycle();
        }
      }
      
      public final boolean zzn(Intent paramIntent)
        throws RemoteException
      {
        boolean bool = true;
        Parcel localParcel1 = Parcel.obtain();
        Parcel localParcel2 = Parcel.obtain();
        for (;;)
        {
          try
          {
            localParcel1.writeInterfaceToken("com.google.android.gms.car.ICar");
            if (paramIntent != null)
            {
              localParcel1.writeInt(1);
              paramIntent.writeToParcel(localParcel1, 0);
              this.zzop.transact(10, localParcel1, localParcel2, 0);
              localParcel2.readException();
              int i = localParcel2.readInt();
              if (i != 0) {
                return bool;
              }
            }
            else
            {
              localParcel1.writeInt(0);
              continue;
            }
            bool = false;
          }
          finally
          {
            localParcel2.recycle();
            localParcel1.recycle();
          }
        }
      }
    }
  }
}


/* Location:           F:\apktool\apktool\Google_Play_Store6.0.5\classes-dex2jar.jar
 * Qualified Name:     com.google.android.gms.car.zzx
 * JD-Core Version:    0.7.0.1
 */