package com.google.android.gms.car;

import android.content.Intent;
import android.os.Binder;
import android.os.IBinder;
import android.os.IInterface;
import android.os.Parcel;
import android.os.Parcelable.Creator;
import android.os.RemoteException;

public abstract interface zzy
  extends IInterface
{
  public abstract void onActivityStarted(Intent paramIntent)
    throws RemoteException;
  
  public abstract void onNewActivityRequest(Intent paramIntent)
    throws RemoteException;
  
  public static abstract class zza
    extends Binder
    implements zzy
  {
    public static zzy zzbe(IBinder paramIBinder)
    {
      if (paramIBinder == null) {
        return null;
      }
      IInterface localIInterface = paramIBinder.queryLocalInterface("com.google.android.gms.car.ICarActivityStartListener");
      if ((localIInterface != null) && ((localIInterface instanceof zzy))) {
        return (zzy)localIInterface;
      }
      return new zza(paramIBinder);
    }
    
    public IBinder asBinder()
    {
      return this;
    }
    
    public boolean onTransact(int paramInt1, Parcel paramParcel1, Parcel paramParcel2, int paramInt2)
      throws RemoteException
    {
      switch (paramInt1)
      {
      default: 
        return super.onTransact(paramInt1, paramParcel1, paramParcel2, paramInt2);
      case 1598968902: 
        paramParcel2.writeString("com.google.android.gms.car.ICarActivityStartListener");
        return true;
      case 1: 
        paramParcel1.enforceInterface("com.google.android.gms.car.ICarActivityStartListener");
        int j = paramParcel1.readInt();
        Intent localIntent2 = null;
        if (j != 0) {
          localIntent2 = (Intent)Intent.CREATOR.createFromParcel(paramParcel1);
        }
        onActivityStarted(localIntent2);
        return true;
      }
      paramParcel1.enforceInterface("com.google.android.gms.car.ICarActivityStartListener");
      int i = paramParcel1.readInt();
      Intent localIntent1 = null;
      if (i != 0) {
        localIntent1 = (Intent)Intent.CREATOR.createFromParcel(paramParcel1);
      }
      onNewActivityRequest(localIntent1);
      return true;
    }
    
    private static final class zza
      implements zzy
    {
      private IBinder zzop;
      
      zza(IBinder paramIBinder)
      {
        this.zzop = paramIBinder;
      }
      
      public final IBinder asBinder()
      {
        return this.zzop;
      }
      
      /* Error */
      public final void onActivityStarted(Intent paramIntent)
        throws RemoteException
      {
        // Byte code:
        //   0: invokestatic 27	android/os/Parcel:obtain	()Landroid/os/Parcel;
        //   3: astore_2
        //   4: aload_2
        //   5: ldc 29
        //   7: invokevirtual 33	android/os/Parcel:writeInterfaceToken	(Ljava/lang/String;)V
        //   10: aload_1
        //   11: ifnull +33 -> 44
        //   14: aload_2
        //   15: iconst_1
        //   16: invokevirtual 37	android/os/Parcel:writeInt	(I)V
        //   19: aload_1
        //   20: aload_2
        //   21: iconst_0
        //   22: invokevirtual 43	android/content/Intent:writeToParcel	(Landroid/os/Parcel;I)V
        //   25: aload_0
        //   26: getfield 15	com/google/android/gms/car/zzy$zza$zza:zzop	Landroid/os/IBinder;
        //   29: iconst_1
        //   30: aload_2
        //   31: aconst_null
        //   32: iconst_1
        //   33: invokeinterface 49 5 0
        //   38: pop
        //   39: aload_2
        //   40: invokevirtual 52	android/os/Parcel:recycle	()V
        //   43: return
        //   44: aload_2
        //   45: iconst_0
        //   46: invokevirtual 37	android/os/Parcel:writeInt	(I)V
        //   49: goto -24 -> 25
        //   52: astore_3
        //   53: aload_2
        //   54: invokevirtual 52	android/os/Parcel:recycle	()V
        //   57: aload_3
        //   58: athrow
        // Local variable table:
        //   start	length	slot	name	signature
        //   0	59	0	this	zza
        //   0	59	1	paramIntent	Intent
        //   3	51	2	localParcel	Parcel
        //   52	6	3	localObject	Object
        // Exception table:
        //   from	to	target	type
        //   4	10	52	finally
        //   14	25	52	finally
        //   25	39	52	finally
        //   44	49	52	finally
      }
      
      /* Error */
      public final void onNewActivityRequest(Intent paramIntent)
        throws RemoteException
      {
        // Byte code:
        //   0: invokestatic 27	android/os/Parcel:obtain	()Landroid/os/Parcel;
        //   3: astore_2
        //   4: aload_2
        //   5: ldc 29
        //   7: invokevirtual 33	android/os/Parcel:writeInterfaceToken	(Ljava/lang/String;)V
        //   10: aload_1
        //   11: ifnull +33 -> 44
        //   14: aload_2
        //   15: iconst_1
        //   16: invokevirtual 37	android/os/Parcel:writeInt	(I)V
        //   19: aload_1
        //   20: aload_2
        //   21: iconst_0
        //   22: invokevirtual 43	android/content/Intent:writeToParcel	(Landroid/os/Parcel;I)V
        //   25: aload_0
        //   26: getfield 15	com/google/android/gms/car/zzy$zza$zza:zzop	Landroid/os/IBinder;
        //   29: iconst_2
        //   30: aload_2
        //   31: aconst_null
        //   32: iconst_1
        //   33: invokeinterface 49 5 0
        //   38: pop
        //   39: aload_2
        //   40: invokevirtual 52	android/os/Parcel:recycle	()V
        //   43: return
        //   44: aload_2
        //   45: iconst_0
        //   46: invokevirtual 37	android/os/Parcel:writeInt	(I)V
        //   49: goto -24 -> 25
        //   52: astore_3
        //   53: aload_2
        //   54: invokevirtual 52	android/os/Parcel:recycle	()V
        //   57: aload_3
        //   58: athrow
        // Local variable table:
        //   start	length	slot	name	signature
        //   0	59	0	this	zza
        //   0	59	1	paramIntent	Intent
        //   3	51	2	localParcel	Parcel
        //   52	6	3	localObject	Object
        // Exception table:
        //   from	to	target	type
        //   4	10	52	finally
        //   14	25	52	finally
        //   25	39	52	finally
        //   44	49	52	finally
      }
    }
  }
}


/* Location:           F:\apktool\apktool\Google_Play_Store6.0.5\classes-dex2jar.jar
 * Qualified Name:     com.google.android.gms.car.zzy
 * JD-Core Version:    0.7.0.1
 */