package com.google.android.gms.ads.internal.purchase;

import android.app.Activity;
import android.content.ComponentName;
import android.content.Context;
import android.content.Intent;
import android.content.ServiceConnection;
import android.content.res.Configuration;
import android.content.res.Resources;
import android.os.Bundle;
import android.os.RemoteException;
import android.text.TextUtils;
import com.google.android.gms.ads.internal.zzp;
import com.google.android.gms.internal.zzgc;
import com.google.android.gms.internal.zzge.zza;
import com.google.android.gms.internal.zzhb;
import com.google.android.gms.internal.zzir;

@zzhb
public final class zze
  extends zzge.zza
  implements ServiceConnection
{
  private final Activity mActivity;
  private zzb zzEY;
  zzh zzEZ;
  private zzk zzFb;
  private Context zzFg;
  private zzgc zzFh;
  private zzf zzFi;
  private zzj zzFj;
  private String zzFk = null;
  
  public zze(Activity paramActivity)
  {
    this.mActivity = paramActivity;
    this.zzEZ = zzh.zzz(this.mActivity.getApplicationContext());
  }
  
  public final void onActivityResult(int paramInt1, int paramInt2, Intent paramIntent)
  {
    if (paramInt1 == 1001) {}
    label391:
    label402:
    label418:
    label422:
    for (;;)
    {
      String str2;
      String str3;
      label239:
      int j;
      try
      {
        zzp.zzbS();
        int i;
        zzk localzzk;
        String str1;
        if (paramIntent == null)
        {
          i = 5;
          if (paramInt2 != -1) {
            continue;
          }
          zzp.zzbS();
          if (i != 0) {
            continue;
          }
          localzzk = this.zzFb;
          str1 = this.zzFk;
          if (str1 == null) {
            break label391;
          }
          if (paramIntent == null)
          {
            break label391;
            this.zzFh.recordPlayBillingResolution(i);
            this.mActivity.finish();
            this.zzFh.getProductId();
          }
        }
        else
        {
          Object localObject2 = paramIntent.getExtras().get("RESPONSE_CODE");
          if (localObject2 == null)
          {
            com.google.android.gms.ads.internal.util.client.zzb.w("Intent with no response code, assuming OK (known issue)");
            i = 0;
            continue;
          }
          if ((localObject2 instanceof Integer))
          {
            i = ((Integer)localObject2).intValue();
            continue;
          }
          if ((localObject2 instanceof Long))
          {
            i = (int)((Long)localObject2).longValue();
            continue;
          }
          com.google.android.gms.ads.internal.util.client.zzb.w("Unexpected type for intent response code. " + localObject2.getClass().getName());
          i = 5;
          continue;
        }
        zzp.zzbS();
        if (paramIntent == null)
        {
          str2 = null;
          zzp.zzbS();
          if (paramIntent == null)
          {
            str3 = null;
            break label402;
          }
        }
        else
        {
          str2 = paramIntent.getStringExtra("INAPP_PURCHASE_DATA");
          continue;
        }
        str3 = paramIntent.getStringExtra("INAPP_DATA_SIGNATURE");
        break label402;
        zzp.zzbS();
        if (!str1.equals(zzi.zzap(str2)))
        {
          com.google.android.gms.ads.internal.util.client.zzb.w("Developer payload not match.");
          j = 0;
        }
        else
        {
          if (localzzk.zzvc == null) {
            break label418;
          }
          String str4 = localzzk.zzvc;
          boolean bool;
          if ((TextUtils.isEmpty(str2)) || (TextUtils.isEmpty(str4)) || (TextUtils.isEmpty(str3)))
          {
            com.google.android.gms.ads.internal.util.client.zzb.e("Purchase verification failed: missing data.");
            bool = false;
            if (bool) {
              break label418;
            }
            com.google.android.gms.ads.internal.util.client.zzb.w("Fail to verify signature.");
            j = 0;
          }
          else
          {
            bool = zzl.zza(zzl.zzar(str4), str2, str3);
            continue;
            this.zzEZ.zza(this.zzFi);
            continue;
            j = 0;
          }
        }
      }
      catch (RemoteException localRemoteException)
      {
        com.google.android.gms.ads.internal.util.client.zzb.w("Fail to process purchase result.");
        this.mActivity.finish();
        return;
      }
      finally
      {
        this.zzFk = null;
      }
      for (;;)
      {
        if (j == 0) {
          break label422;
        }
        break;
        if ((str2 != null) && (str3 != null)) {
          break label239;
        }
        j = 0;
        continue;
        j = 1;
      }
    }
  }
  
  public final void onCreate()
  {
    GInAppPurchaseManagerInfoParcel localGInAppPurchaseManagerInfoParcel = GInAppPurchaseManagerInfoParcel.zzc(this.mActivity.getIntent());
    this.zzFj = localGInAppPurchaseManagerInfoParcel.zzEU;
    this.zzFb = localGInAppPurchaseManagerInfoParcel.zzrR;
    this.zzFh = localGInAppPurchaseManagerInfoParcel.zzES;
    this.zzEY = new zzb(this.mActivity.getApplicationContext());
    this.zzFg = localGInAppPurchaseManagerInfoParcel.zzET;
    if (this.mActivity.getResources().getConfiguration().orientation == 2) {
      this.mActivity.setRequestedOrientation(zzp.zzbK().zzhl());
    }
    for (;;)
    {
      Intent localIntent = new Intent("com.android.vending.billing.InAppBillingService.BIND");
      localIntent.setPackage("com.android.vending");
      this.mActivity.bindService(localIntent, this, 1);
      return;
      this.mActivity.setRequestedOrientation(zzp.zzbK().zzhm());
    }
  }
  
  public final void onDestroy()
  {
    this.mActivity.unbindService(this);
    this.zzEY.zzEV = null;
  }
  
  /* Error */
  public final void onServiceConnected(ComponentName paramComponentName, android.os.IBinder paramIBinder)
  {
    // Byte code:
    //   0: aload_0
    //   1: getfield 218	com/google/android/gms/ads/internal/purchase/zze:zzEY	Lcom/google/android/gms/ads/internal/purchase/zzb;
    //   4: astore_3
    //   5: aload_3
    //   6: aload_3
    //   7: getfield 287	com/google/android/gms/ads/internal/purchase/zzb:mContext	Landroid/content/Context;
    //   10: invokevirtual 293	android/content/Context:getClassLoader	()Ljava/lang/ClassLoader;
    //   13: ldc_w 295
    //   16: invokevirtual 301	java/lang/ClassLoader:loadClass	(Ljava/lang/String;)Ljava/lang/Class;
    //   19: ldc_w 303
    //   22: iconst_1
    //   23: anewarray 123	java/lang/Class
    //   26: dup
    //   27: iconst_0
    //   28: ldc_w 305
    //   31: aastore
    //   32: invokevirtual 309	java/lang/Class:getDeclaredMethod	(Ljava/lang/String;[Ljava/lang/Class;)Ljava/lang/reflect/Method;
    //   35: aconst_null
    //   36: iconst_1
    //   37: anewarray 117	java/lang/Object
    //   40: dup
    //   41: iconst_0
    //   42: aload_2
    //   43: aastore
    //   44: invokevirtual 315	java/lang/reflect/Method:invoke	(Ljava/lang/Object;[Ljava/lang/Object;)Ljava/lang/Object;
    //   47: putfield 276	com/google/android/gms/ads/internal/purchase/zzb:zzEV	Ljava/lang/Object;
    //   50: invokestatic 319	com/google/android/gms/ads/internal/zzp:zzbI	()Lcom/google/android/gms/internal/zziq;
    //   53: pop
    //   54: aload_0
    //   55: invokestatic 324	com/google/android/gms/internal/zziq:zzhi	()Ljava/lang/String;
    //   58: putfield 32	com/google/android/gms/ads/internal/purchase/zze:zzFk	Ljava/lang/String;
    //   61: aload_0
    //   62: getfield 218	com/google/android/gms/ads/internal/purchase/zze:zzEY	Lcom/google/android/gms/ads/internal/purchase/zzb;
    //   65: aload_0
    //   66: getfield 34	com/google/android/gms/ads/internal/purchase/zze:mActivity	Landroid/app/Activity;
    //   69: invokevirtual 327	android/app/Activity:getPackageName	()Ljava/lang/String;
    //   72: aload_0
    //   73: getfield 62	com/google/android/gms/ads/internal/purchase/zze:zzFh	Lcom/google/android/gms/internal/zzgc;
    //   76: invokeinterface 75 1 0
    //   81: aload_0
    //   82: getfield 32	com/google/android/gms/ads/internal/purchase/zze:zzFk	Ljava/lang/String;
    //   85: invokevirtual 331	com/google/android/gms/ads/internal/purchase/zzb:zzb	(Ljava/lang/String;Ljava/lang/String;Ljava/lang/String;)Landroid/os/Bundle;
    //   88: astore 7
    //   90: aload 7
    //   92: ldc_w 333
    //   95: invokevirtual 337	android/os/Bundle:getParcelable	(Ljava/lang/String;)Landroid/os/Parcelable;
    //   98: checkcast 339	android/app/PendingIntent
    //   101: astore 8
    //   103: aload 8
    //   105: ifnonnull +152 -> 257
    //   108: invokestatic 58	com/google/android/gms/ads/internal/zzp:zzbS	()Lcom/google/android/gms/ads/internal/purchase/zzi;
    //   111: pop
    //   112: aload 7
    //   114: ldc 83
    //   116: invokevirtual 89	android/os/Bundle:get	(Ljava/lang/String;)Ljava/lang/Object;
    //   119: astore 10
    //   121: aload 10
    //   123: ifnonnull +59 -> 182
    //   126: ldc_w 341
    //   129: invokestatic 97	com/google/android/gms/ads/internal/util/client/zzb:w	(Ljava/lang/String;)V
    //   132: iconst_0
    //   133: istore 11
    //   135: aload_0
    //   136: getfield 62	com/google/android/gms/ads/internal/purchase/zze:zzFh	Lcom/google/android/gms/internal/zzgc;
    //   139: iload 11
    //   141: invokeinterface 68 2 0
    //   146: aload_0
    //   147: getfield 62	com/google/android/gms/ads/internal/purchase/zze:zzFh	Lcom/google/android/gms/internal/zzgc;
    //   150: invokeinterface 75 1 0
    //   155: pop
    //   156: aload_0
    //   157: getfield 34	com/google/android/gms/ads/internal/purchase/zze:mActivity	Landroid/app/Activity;
    //   160: invokevirtual 71	android/app/Activity:finish	()V
    //   163: return
    //   164: astore 4
    //   166: aload_3
    //   167: getfield 345	com/google/android/gms/ads/internal/purchase/zzb:zzEW	Z
    //   170: ifeq -120 -> 50
    //   173: ldc_w 347
    //   176: invokestatic 97	com/google/android/gms/ads/internal/util/client/zzb:w	(Ljava/lang/String;)V
    //   179: goto -129 -> 50
    //   182: aload 10
    //   184: instanceof 99
    //   187: ifeq +16 -> 203
    //   190: aload 10
    //   192: checkcast 99	java/lang/Integer
    //   195: invokevirtual 103	java/lang/Integer:intValue	()I
    //   198: istore 11
    //   200: goto -65 -> 135
    //   203: aload 10
    //   205: instanceof 105
    //   208: ifeq +17 -> 225
    //   211: aload 10
    //   213: checkcast 105	java/lang/Long
    //   216: invokevirtual 109	java/lang/Long:longValue	()J
    //   219: l2i
    //   220: istore 11
    //   222: goto -87 -> 135
    //   225: new 111	java/lang/StringBuilder
    //   228: dup
    //   229: ldc 113
    //   231: invokespecial 115	java/lang/StringBuilder:<init>	(Ljava/lang/String;)V
    //   234: aload 10
    //   236: invokevirtual 121	java/lang/Object:getClass	()Ljava/lang/Class;
    //   239: invokevirtual 126	java/lang/Class:getName	()Ljava/lang/String;
    //   242: invokevirtual 130	java/lang/StringBuilder:append	(Ljava/lang/String;)Ljava/lang/StringBuilder;
    //   245: invokevirtual 133	java/lang/StringBuilder:toString	()Ljava/lang/String;
    //   248: invokestatic 97	com/google/android/gms/ads/internal/util/client/zzb:w	(Ljava/lang/String;)V
    //   251: iconst_5
    //   252: istore 11
    //   254: goto -119 -> 135
    //   257: aload_0
    //   258: new 349	com/google/android/gms/ads/internal/purchase/zzf
    //   261: dup
    //   262: aload_0
    //   263: getfield 62	com/google/android/gms/ads/internal/purchase/zze:zzFh	Lcom/google/android/gms/internal/zzgc;
    //   266: invokeinterface 75 1 0
    //   271: aload_0
    //   272: getfield 32	com/google/android/gms/ads/internal/purchase/zze:zzFk	Ljava/lang/String;
    //   275: invokespecial 352	com/google/android/gms/ads/internal/purchase/zzf:<init>	(Ljava/lang/String;Ljava/lang/String;)V
    //   278: putfield 184	com/google/android/gms/ads/internal/purchase/zze:zzFi	Lcom/google/android/gms/ads/internal/purchase/zzf;
    //   281: aload_0
    //   282: getfield 48	com/google/android/gms/ads/internal/purchase/zze:zzEZ	Lcom/google/android/gms/ads/internal/purchase/zzh;
    //   285: astore 13
    //   287: aload_0
    //   288: getfield 184	com/google/android/gms/ads/internal/purchase/zze:zzFi	Lcom/google/android/gms/ads/internal/purchase/zzf;
    //   291: astore 14
    //   293: aload 14
    //   295: ifnull +26 -> 321
    //   298: getstatic 355	com/google/android/gms/ads/internal/purchase/zzh:zzqp	Ljava/lang/Object;
    //   301: astore 15
    //   303: aload 15
    //   305: monitorenter
    //   306: aload 13
    //   308: invokevirtual 359	com/google/android/gms/ads/internal/purchase/zzh:getWritableDatabase	()Landroid/database/sqlite/SQLiteDatabase;
    //   311: astore 17
    //   313: aload 17
    //   315: ifnonnull +68 -> 383
    //   318: aload 15
    //   320: monitorexit
    //   321: aload_0
    //   322: getfield 34	com/google/android/gms/ads/internal/purchase/zze:mActivity	Landroid/app/Activity;
    //   325: aload 8
    //   327: invokevirtual 363	android/app/PendingIntent:getIntentSender	()Landroid/content/IntentSender;
    //   330: sipush 1001
    //   333: new 77	android/content/Intent
    //   336: dup
    //   337: invokespecial 364	android/content/Intent:<init>	()V
    //   340: iconst_0
    //   341: invokestatic 368	java/lang/Integer:valueOf	(I)Ljava/lang/Integer;
    //   344: invokevirtual 103	java/lang/Integer:intValue	()I
    //   347: iconst_0
    //   348: invokestatic 368	java/lang/Integer:valueOf	(I)Ljava/lang/Integer;
    //   351: invokevirtual 103	java/lang/Integer:intValue	()I
    //   354: iconst_0
    //   355: invokestatic 368	java/lang/Integer:valueOf	(I)Ljava/lang/Integer;
    //   358: invokevirtual 103	java/lang/Integer:intValue	()I
    //   361: invokevirtual 372	android/app/Activity:startIntentSenderForResult	(Landroid/content/IntentSender;ILandroid/content/Intent;III)V
    //   364: return
    //   365: astore 5
    //   367: ldc_w 374
    //   370: aload 5
    //   372: invokestatic 377	com/google/android/gms/ads/internal/util/client/zzb:w	(Ljava/lang/String;Ljava/lang/Throwable;)V
    //   375: aload_0
    //   376: getfield 34	com/google/android/gms/ads/internal/purchase/zze:mActivity	Landroid/app/Activity;
    //   379: invokevirtual 71	android/app/Activity:finish	()V
    //   382: return
    //   383: new 379	android/content/ContentValues
    //   386: dup
    //   387: invokespecial 380	android/content/ContentValues:<init>	()V
    //   390: astore 18
    //   392: aload 18
    //   394: ldc_w 382
    //   397: aload 14
    //   399: getfield 385	com/google/android/gms/ads/internal/purchase/zzf:zzFn	Ljava/lang/String;
    //   402: invokevirtual 388	android/content/ContentValues:put	(Ljava/lang/String;Ljava/lang/String;)V
    //   405: aload 18
    //   407: ldc_w 390
    //   410: aload 14
    //   412: getfield 393	com/google/android/gms/ads/internal/purchase/zzf:zzFm	Ljava/lang/String;
    //   415: invokevirtual 388	android/content/ContentValues:put	(Ljava/lang/String;Ljava/lang/String;)V
    //   418: aload 18
    //   420: ldc_w 395
    //   423: invokestatic 400	android/os/SystemClock:elapsedRealtime	()J
    //   426: invokestatic 403	java/lang/Long:valueOf	(J)Ljava/lang/Long;
    //   429: invokevirtual 406	android/content/ContentValues:put	(Ljava/lang/String;Ljava/lang/Long;)V
    //   432: aload 14
    //   434: aload 17
    //   436: ldc_w 408
    //   439: aconst_null
    //   440: aload 18
    //   442: invokevirtual 414	android/database/sqlite/SQLiteDatabase:insert	(Ljava/lang/String;Ljava/lang/String;Landroid/content/ContentValues;)J
    //   445: putfield 418	com/google/android/gms/ads/internal/purchase/zzf:zzFl	J
    //   448: aload 13
    //   450: invokevirtual 421	com/google/android/gms/ads/internal/purchase/zzh:getRecordCount	()I
    //   453: i2l
    //   454: ldc2_w 422
    //   457: lcmp
    //   458: ifle +26 -> 484
    //   461: getstatic 355	com/google/android/gms/ads/internal/purchase/zzh:zzqp	Ljava/lang/Object;
    //   464: astore 19
    //   466: aload 19
    //   468: monitorenter
    //   469: aload 13
    //   471: invokevirtual 359	com/google/android/gms/ads/internal/purchase/zzh:getWritableDatabase	()Landroid/database/sqlite/SQLiteDatabase;
    //   474: astore 21
    //   476: aload 21
    //   478: ifnonnull +25 -> 503
    //   481: aload 19
    //   483: monitorexit
    //   484: aload 15
    //   486: monitorexit
    //   487: goto -166 -> 321
    //   490: astore 16
    //   492: aload 15
    //   494: monitorexit
    //   495: aload 16
    //   497: athrow
    //   498: astore 5
    //   500: goto -133 -> 367
    //   503: aload 21
    //   505: ldc_w 408
    //   508: aconst_null
    //   509: aconst_null
    //   510: aconst_null
    //   511: aconst_null
    //   512: aconst_null
    //   513: ldc_w 425
    //   516: ldc_w 427
    //   519: invokevirtual 431	android/database/sqlite/SQLiteDatabase:query	(Ljava/lang/String;[Ljava/lang/String;Ljava/lang/String;[Ljava/lang/String;Ljava/lang/String;Ljava/lang/String;Ljava/lang/String;Ljava/lang/String;)Landroid/database/Cursor;
    //   522: astore 25
    //   524: aload 25
    //   526: astore 23
    //   528: aload 23
    //   530: ifnull +28 -> 558
    //   533: aload 23
    //   535: invokeinterface 437 1 0
    //   540: ifeq +18 -> 558
    //   543: aload 23
    //   545: ifnonnull +39 -> 584
    //   548: aconst_null
    //   549: astore 26
    //   551: aload 13
    //   553: aload 26
    //   555: invokevirtual 187	com/google/android/gms/ads/internal/purchase/zzh:zza	(Lcom/google/android/gms/ads/internal/purchase/zzf;)V
    //   558: aload 23
    //   560: ifnull +10 -> 570
    //   563: aload 23
    //   565: invokeinterface 440 1 0
    //   570: aload 19
    //   572: monitorexit
    //   573: goto -89 -> 484
    //   576: astore 20
    //   578: aload 19
    //   580: monitorexit
    //   581: aload 20
    //   583: athrow
    //   584: new 349	com/google/android/gms/ads/internal/purchase/zzf
    //   587: dup
    //   588: aload 23
    //   590: iconst_0
    //   591: invokeinterface 444 2 0
    //   596: aload 23
    //   598: iconst_1
    //   599: invokeinterface 448 2 0
    //   604: aload 23
    //   606: iconst_2
    //   607: invokeinterface 448 2 0
    //   612: invokespecial 451	com/google/android/gms/ads/internal/purchase/zzf:<init>	(JLjava/lang/String;Ljava/lang/String;)V
    //   615: astore 26
    //   617: goto -66 -> 551
    //   620: astore 22
    //   622: new 111	java/lang/StringBuilder
    //   625: dup
    //   626: ldc_w 453
    //   629: invokespecial 115	java/lang/StringBuilder:<init>	(Ljava/lang/String;)V
    //   632: aload 22
    //   634: invokevirtual 456	android/database/sqlite/SQLiteException:getMessage	()Ljava/lang/String;
    //   637: invokevirtual 130	java/lang/StringBuilder:append	(Ljava/lang/String;)Ljava/lang/StringBuilder;
    //   640: invokevirtual 133	java/lang/StringBuilder:toString	()Ljava/lang/String;
    //   643: invokestatic 97	com/google/android/gms/ads/internal/util/client/zzb:w	(Ljava/lang/String;)V
    //   646: aload 23
    //   648: ifnull -78 -> 570
    //   651: aload 23
    //   653: invokeinterface 440 1 0
    //   658: goto -88 -> 570
    //   661: aload 23
    //   663: ifnull +10 -> 673
    //   666: aload 23
    //   668: invokeinterface 440 1 0
    //   673: aload 24
    //   675: athrow
    //   676: astore 24
    //   678: goto -17 -> 661
    //   681: astore 22
    //   683: aconst_null
    //   684: astore 23
    //   686: goto -64 -> 622
    //   689: astore 24
    //   691: aconst_null
    //   692: astore 23
    //   694: goto -33 -> 661
    // Local variable table:
    //   start	length	slot	name	signature
    //   0	697	0	this	zze
    //   0	697	1	paramComponentName	ComponentName
    //   0	697	2	paramIBinder	android.os.IBinder
    //   4	163	3	localzzb	zzb
    //   164	1	4	localException	java.lang.Exception
    //   365	6	5	localRemoteException	RemoteException
    //   498	1	5	localSendIntentException	android.content.IntentSender.SendIntentException
    //   88	25	7	localBundle	Bundle
    //   101	225	8	localPendingIntent	android.app.PendingIntent
    //   119	116	10	localObject1	Object
    //   133	120	11	i	int
    //   285	267	13	localzzh	zzh
    //   291	142	14	localzzf1	zzf
    //   301	192	15	localObject2	Object
    //   490	6	16	localObject3	Object
    //   311	124	17	localSQLiteDatabase1	android.database.sqlite.SQLiteDatabase
    //   390	51	18	localContentValues	android.content.ContentValues
    //   464	115	19	localObject4	Object
    //   576	6	20	localObject5	Object
    //   474	30	21	localSQLiteDatabase2	android.database.sqlite.SQLiteDatabase
    //   620	13	22	localSQLiteException1	android.database.sqlite.SQLiteException
    //   681	1	22	localSQLiteException2	android.database.sqlite.SQLiteException
    //   526	167	23	localCursor1	android.database.Cursor
    //   673	1	24	localObject6	Object
    //   676	1	24	localObject7	Object
    //   689	1	24	localObject8	Object
    //   522	3	25	localCursor2	android.database.Cursor
    //   549	67	26	localzzf2	zzf
    // Exception table:
    //   from	to	target	type
    //   5	50	164	java/lang/Exception
    //   50	103	365	android/os/RemoteException
    //   108	121	365	android/os/RemoteException
    //   126	132	365	android/os/RemoteException
    //   135	163	365	android/os/RemoteException
    //   182	200	365	android/os/RemoteException
    //   203	222	365	android/os/RemoteException
    //   225	251	365	android/os/RemoteException
    //   257	293	365	android/os/RemoteException
    //   298	306	365	android/os/RemoteException
    //   321	364	365	android/os/RemoteException
    //   495	498	365	android/os/RemoteException
    //   306	313	490	finally
    //   318	321	490	finally
    //   383	469	490	finally
    //   484	487	490	finally
    //   492	495	490	finally
    //   581	584	490	finally
    //   50	103	498	android/content/IntentSender$SendIntentException
    //   108	121	498	android/content/IntentSender$SendIntentException
    //   126	132	498	android/content/IntentSender$SendIntentException
    //   135	163	498	android/content/IntentSender$SendIntentException
    //   182	200	498	android/content/IntentSender$SendIntentException
    //   203	222	498	android/content/IntentSender$SendIntentException
    //   225	251	498	android/content/IntentSender$SendIntentException
    //   257	293	498	android/content/IntentSender$SendIntentException
    //   298	306	498	android/content/IntentSender$SendIntentException
    //   321	364	498	android/content/IntentSender$SendIntentException
    //   495	498	498	android/content/IntentSender$SendIntentException
    //   469	476	576	finally
    //   481	484	576	finally
    //   563	570	576	finally
    //   570	573	576	finally
    //   578	581	576	finally
    //   651	658	576	finally
    //   666	673	576	finally
    //   673	676	576	finally
    //   533	543	620	android/database/sqlite/SQLiteException
    //   551	558	620	android/database/sqlite/SQLiteException
    //   584	617	620	android/database/sqlite/SQLiteException
    //   533	543	676	finally
    //   551	558	676	finally
    //   584	617	676	finally
    //   622	646	676	finally
    //   503	524	681	android/database/sqlite/SQLiteException
    //   503	524	689	finally
  }
  
  public final void onServiceDisconnected(ComponentName paramComponentName)
  {
    com.google.android.gms.ads.internal.util.client.zzb.i("In-app billing service disconnected.");
    this.zzEY.zzEV = null;
  }
}


/* Location:           F:\apktool\apktool\Google_Play_Store6.0.5\classes-dex2jar.jar
 * Qualified Name:     com.google.android.gms.ads.internal.purchase.zze
 * JD-Core Version:    0.7.0.1
 */